Workbook
Name cuatro1: #REF!
Name cuatro1: #REF!
Name cuatro10: #REF!
Name cuatro10: #REF!
Name cuatro2: #REF!
Name cuatro2: #REF!
Name cuatro3: #REF!
Name cuatro3: #REF!
Name cuatro4: #REF!
Name cuatro4: #REF!
Name cuatro5: #REF!
Name cuatro5: #REF!
Name cuatro6: #REF!
Name cuatro6: #REF!
Name cuatro7: #REF!
Name cuatro7: #REF!
Name cuatro8: #REF!
Name cuatro8: #REF!
Name cuatro9: #REF!
Name cuatro9: #REF!
Name DICIEMBRE: [1]PROMEDIO!#REF!
Name DICIEMBRE: #REF!
Name DICIEMBRE: [1]PROMEDIO!#REF!
Name FrequencyList: '[2]Report Form'!$D$4:$D$20
Name FrequencyList: '[3]Report Form'!$D$4:$D$20
Name FrequencyList2: '[4]Report Form'!$D$4:$D$20
Name FrequencyList2: '[5]Report Form'!$D$4:$D$20
Name junio: [1]PROMEDIO!#REF!
Name L: 'COMPOS CART'!$M$12
Name p: #REF!
Name PeriodList: '[2]Report Form'!$B$4:$B$34
Name PeriodList: '[3]Report Form'!$B$4:$B$34
Name PeriodList2: '[4]Report Form'!$B$4:$B$34
Name PeriodList2: '[5]Report Form'!$B$4:$B$34
Name Range_AllCurrencyTypes: [6]Control!$B$36:$B$38
Name Range_AllScaleTypes: [7]Control!$H$36:$H$39
Name Range_Country: [6]Control!$B$13
Name Range_DownloadDateTime: [6]Control!$B$14
Name Reporting_Country_Code: '[2]Report Form'!$M$2
Name Reporting_Country_Code: '[3]Report Form'!$M$2
Name Reporting_country_code_2: '[4]Report Form'!$M$2
Name Reporting_country_code_2: '[5]Report Form'!$M$2
Name Reporting_Country_Name: '[2]Report Form'!$M$3
Name Reporting_Country_Name: '[3]Report Form'!$M$3
Name Reporting_CountryCode: [6]Control!$B$28
Name Reporting_Currency_Code: '[2]Report Form'!$M$5
Name Reporting_Currency_Code: '[3]Report Form'!$M$5
Name Reporting_Currency_Code_2: '[4]Report Form'!$M$5
Name Reporting_Currency_Code_2: '[5]Report Form'!$M$5
Name Reporting_Currency_Name: '[2]Report Form'!$M$6
Name Reporting_Currency_Name: '[3]Report Form'!$M$6
Name reporting_currency_name_2: '[4]Report Form'!$M$6
Name reporting_currency_name_2: '[5]Report Form'!$M$6
Name Reporting_Scale_Name: '[2]Report Form'!$M$7
Name Reporting_Scale_Name: '[3]Report Form'!$M$7
Name Reporting_scale_name_2: '[4]Report Form'!$M$7
Name Reporting_scale_name_2: '[5]Report Form'!$M$7
Name t: #REF!
Name t: #REF!
Name wrqwer: #REF!

Sheet Homologación
C1: CATÁLOGO ÚNICO DE CUENTAS PARA USO DE LAS ENTIDADES DE LOS SECTORES FINANCIEROS PÚBLICO Y PRIVADO CODIFICACIÓN DE CUENTAS
A2: CUENTA | B2: largo | C2: CÓDIGO 2015 | D2: PLAN DE CUENTAS 2015 | E2: BP | F2: TH | G2: CFN | H2: BEV | I2: BEDE | J2: BFN | K2: BANEC | L2: CC | M2: ALM | N2: SGC | Q2: CÓDIGO 2021 | R2: PLAN DE CUENTAS 2021 | S2: HOMOLOGACION 2021 2015
A3: CUENTA | C3: CÓDIGO 2015 | D3: PLAN DE CUENTAS 2015 | E3: BP | F3: TH | G3: CFN | H3: BEV | I3: BEDE | J3: BNF | K3: BANEC | L3: CC | M3: ALM | N3: SGC | Q3: CÓDIGO 2021 | R3: PLAN DE CUENTAS 2021 | S3: HOMOLOGACION 2021 2015
B4: =LEN(C4) -> 1 | C4: 1 | D4: ACTIVO | E4: BP | F4: TH | G4: CFN | H4: BEV | I4: BEDE | J4: BFN | K4: BANEC | L4: CC | M4: ALM | N4: SGC | O4: GF | Q4: 1 | R4: ACTIVO | S4: =+C4 -> 1
A5: 11 | B5: =LEN(C5) -> 2 | C5: 11 | D5: FONDOS DISPONIBLES | E5: X | F5: X | G5: X | H5: X | I5: X | J5: X | K5: X | L5: X | M5: X | N5: X | O5: X | Q5: 11 | R5: FONDOS DISPONIBLES | S5: =+C5 -> 11
A6: 1101 | B6: =LEN(C6) -> 4 | C6: 1101 | D6: Caja | E6: X | F6: X | G6: X | H6: X | I6: X | J6: X | K6: X | L6: X | M6: X | N6: X | O6: X | Q6: 1101 | R6: Caja | S6: =+C6 -> 1101
A7: 1101 | B7: =LEN(C7) -> 6 | C7: 110105 | D7: Efectivo | E7: X | F7: X | G7: X | H7: X | I7: X | J7: X | K7: X | L7: X | M7: X | N7: X | O7: X | Q7: 110105 | R7: Efectivo | S7: =+C7 -> 110105
A8: 1101 | B8: =LEN(C8) -> 6 | C8: 110110 | D8: Caja chica | E8: X | F8: X | G8: X | H8: X | I8: X | J8: X | K8: X | L8: X | M8: X | N8: X | O8: X | Q8: 110110 | R8: Caja chica | S8: =+C8 -> 110110
A9: 1102 | B9: =LEN(C9) -> 4 | C9: 1102 | D9: Depósitos para encaje | E9: X | F9: X | G9: X | H9: X | I9: X | J9: X | K9: X | O9: X | Q9: 1102 | R9: Depósitos para encaje | S9: =+C9 -> 1102
A10: 1102 | B10: =LEN(C10) -> 6 | C10: 110205 | D10: Banco Central del Ecuador | E10: X | F10: X | G10: X | H10: X | I10: X | J10: X | K10: X | O10: X | Q10: 110205 | R10: Banco Central del Ecuador | S10: =+C10 -> 110205
A11: 1102 | B11: =LEN(C11) -> 6 | C11: 110210 | D11: Banco Nacional de Fomento | E11: X | F11: X | H11: X | I11: X | O11: X | Q11: 110210 | R11: Banco Nacional de Fomento | S11: =+C11 -> 110210
A12: 1102 | B12: =LEN(C12) -> 6 | C12: 110215 | D12: Bancos locales | E12: X | F12: X | H12: X | I12: X | O12: X | Q12: 110215 | R12: Bancos locales | S12: =+C12 -> 110215
A13: 1103 | B13: =LEN(C13) -> 4 | C13: 1103 | D13: Bancos y otras instituciones financieras | E13: X | F13: X | G13: X | H13: X | I13: X | J13: X | K13: X | L13: X | M13: X | N13: X | O13: X | Q13: 1103 | R13: Bancos y otras instituciones financieras | S13: =+C13 -> 1103
A14: 1103 | B14: =LEN(C14) -> 6 | C14: 110305 | D14: Banco Central del Ecuador | E14: X | G14: X | I14: X | J14: X | K14: X | N14: X | O14: X | Q14: 110305 | R14: Banco Central del Ecuador | S14: =+C14 -> 110305
A15: 1103 | B15: =LEN(C15) -> 6 | C15: 110310 | D15: Bancos e instituciones financieras locales | E15: X | F15: X | G15: X | H15: X | I15: X | J15: X | K15: X | L15: X | M15: X | N15: X | O15: X | Q15: 110310 | R15: Bancos e instituciones financieras locales | S15: =+C15 -> 110310
A16: 1103 | B16: =LEN(C16) -> 6 | C16: 110315 | D16: Bancos e instituciones financieras del exterior | E16: X | F16: X | G16: X | J16: X | K16: X | L16: X | M16: X | N16: X | O16: X | Q16: 110315 | R16: Bancos e instituciones financieras del exterior | S16: =+C16 -> 110315
A17: 1104 | B17: =LEN(C17) -> 4 | C17: 1104 | D17: Efectos de cobro inmediato | E17: X | F17: X | G17: X | H17: X | I17: X | J17: X | K17: X | L17: X | M17: X | N17: X | O17: X | Q17: 1104 | R17: Efectos de cobro inmediato | S17: =+C17 -> 1104
A18: 1105 | B18: =LEN(C18) -> 4 | C18: 1105 | D18: Remesas en tránsito | E18: X | F18: X | G18: X | H18: X | I18: X | J18: X | K18: X | L18: X | M18: X | N18: X | O18: X | Q18: 1105 | R18: Remesas en tránsito | S18: =+C18 -> 1105
A19: 1105 | B19: =LEN(C19) -> 6 | C19: 110505 | D19: Del país | E19: X | F19: X | G19: X | H19: X | I19: X | J19: X | K19: X | L19: X | M19: X | N19: X | O19: X | Q19: 110505 | R19: Del país | S19: =+C19 -> 110505
A20: 1105 | B20: =LEN(C20) -> 6 | C20: 110510 | D20: Del exterior | E20: X | F20: X | G20: X | H20: X | I20: X | J20: X | K20: X | L20: X | M20: X | N20: X | O20: X | Q20: 110510 | R20: Del exterior | S20: =+C20 -> 110510
A21: 12 | B21: =LEN(C21) -> 2 | C21: 12 | D21: OPERACIONES INTERBANCARIAS | E21: X | F21: X | G21: X | H21: X | I21: X | J21: X | K21: X | L21: X | M21: X | N21: X | O21: X | Q21: 12 | R21: OPERACIONES INTERBANCARIAS | S21: =+C21 -> 12
A22: 1201 | B22: =LEN(C22) -> 4 | C22: 1201 | D22: Fondos interbancarios vendidos | E22: X | G22: X | H22: X | I22: X | J22: X | K22: X | O22: X | Q22: 1201 | R22: Fondos interbancarios vendidos | S22: =+C22 -> 1201
A23: 1201 | B23: =LEN(C23) -> 6 | C23: 120105 | D23: Bancos | E23: X | G23: X | H23: X | I23: X | J23: X | K23: X | O23: X | Q23: 120105 | R23: Bancos | S23: =+C23 -> 120105
A24: 1201 | B24: =LEN(C24) -> 6 | C24: 120110 | D24: Otras instituciones del sistema financiero | E24: X | G24: X | H24: X | I24: X | J24: X | K24: X | O24: X | Q24: 120110 | R24: Otras instituciones del sistema financiero | S24: =+C24 -> 120110
A25: 1202 | B25: =LEN(C25) -> 4 | C25: 1202 | D25: Operaciones de reporto con instituciones financieras | E25: X | F25: X | G25: X | H25: X | I25: X | J25: X | K25: X | L25: X | M25: X | N25: X | O25: X | Q25: 1202 | R25: Operaciones de reporto con instituciones financieras | S25: =+C25 -> 1202
A26: 1202 | B26: =LEN(C26) -> 6 | C26: 120205 | D26: Instituciones financieras públicas | E26: X | F26: X | G26: X | H26: X | I26: X | J26: X | K26: X | L26: X | M26: X | N26: X | O26: X | Q26: 120205 | R26: Instituciones financieras públicas | S26: =+C26 -> 120205
A27: 1202 | B27: =LEN(C27) -> 6 | C27: 120210 | D27: Bancos | E27: X | F27: X | G27: X | H27: X | I27: X | J27: X | K27: X | L27: X | M27: X | N27: X | O27: X | Q27: 120210 | R27: Bancos | S27: =+C27 -> 120210
A28: 1202 | B28: =LEN(C28) -> 6 | C28: 120215 | D28: Otras instituciones del sistema financiero | E28: X | F28: X | G28: X | H28: X | I28: X | J28: X | K28: X | L28: X | M28: X | N28: X | O28: X | Q28: 120215 | R28: Otras instituciones del sistema financiero | S28: =+C28 -> 120215
A29: 1299 | B29: =LEN(C29) -> 4 | C29: 1299 | D29: (Provisión para operaciones interbancarias y de reporto) | E29: X | F29: X | G29: X | H29: X | I29: X | J29: X | K29: X | L29: X | M29: X | N29: X | O29: X | Q29: 1299 | R29: (Provisión para operaciones interbancarias y de reporto) | S29: =+C29 -> 1299
A30: 1299 | B30: =LEN(C30) -> 6 | C30: 129905 | D30: (Provisión fondos interbancarios vendidos) | E30: X | G30: X | H30: X | I30: X | J30: X | K30: X | O30: X | Q30: 129905 | R30: (Provisión fondos interbancarios vendidos) | S30: =+C30 -> 129905
A31: 1299 | B31: =LEN(C31) -> 6 | C31: 129910 | D31: (Provisión para operaciones de reporto con instituciones financieras) | E31: X | F31: X | G31: X | H31: X | I31: X | J31: X | K31: X | L31: X | M31: X | N31: X | O31: X | Q31: 129910 | R31: (Provisión para operaciones de reporto con instituciones financieras) | S31: =+C31 -> 129910
A32: 13 | B32: =LEN(C32) -> 2 | C32: 13 | D32: INVERSIONES | E32: X | F32: X | G32: X | H32: X | I32: X | J32: X | K32: X | L32: X | M32: X | N32: X | O32: X | Q32: 13 | R32: INVERSIONES | S32: =+C32 -> 13
A33: 1301 | B33: =LEN(C33) -> 4 | C33: 1301 | D33: A valor razonable con cambios en el estado de resultados de entidades del sector privado | E33: X | F33: X | G33: X | H33: X | I33: X | J33: X | K33: X | L33: X | M33: X | N33: X | O33: X | Q33: 1301 | R33: A valor razonable con cambios en el estado de resultados de entidades del sector privado | S33: =+C33 -> 1301
A34: 1301 | B34: =LEN(C34) -> 6 | C34: 130105 | D34: De 1 a 30 días | E34: X | F34: X | G34: X | H34: X | I34: X | J34: X | K34: X | L34: X | M34: X | N34: X | O34: X | Q34: 130105 | R34: De 1 a 30 días | S34: =+C34 -> 130105
A35: 1301 | B35: =LEN(C35) -> 6 | C35: 130110 | D35: De 31 a 90 días | E35: X | F35: X | G35: X | H35: X | I35: X | J35: X | K35: X | L35: X | M35: X | N35: X | O35: X | Q35: 130110 | R35: De 31 a 90 días | S35: =+C35 -> 130110
A36: 1301 | B36: =LEN(C36) -> 6 | C36: 130115 | D36: De 91 a 180 días | E36: X | F36: X | G36: X | H36: X | I36: X | J36: X | K36: X | L36: X | M36: X | N36: X | O36: X | Q36: 130115 | R36: De 91 a 180 días | S36: =+C36 -> 130115
A37: 1301 | B37: =LEN(C37) -> 6 | C37: 130120 | D37: De 181 a 360 días | E37: X | F37: X | G37: X | H37: X | I37: X | J37: X | K37: X | L37: X | M37: X | N37: X | O37: X | Q37: 130120 | R37: De 181 a 360 días | S37: =+C37 -> 130120
A38: 1301 | B38: =LEN(C38) -> 6 | C38: 130125 | D38: De más de 360 días | E38: X | F38: X | G38: X | H38: X | I38: X | J38: X | K38: X | L38: X | M38: X | N38: X | O38: X | Q38: 130125 | R38: De más de 360 días | S38: =+C38 -> 130125
A39: 1302 | B39: =LEN(C39) -> 4 | C39: 1302 | D39: A valor razonable con cambios en el estado de resultados del Estado o de entidades del sector público | E39: X | F39: X | G39: X | H39: X | I39: X | J39: X | K39: X | L39: X | M39: X | N39: X | O39: X | Q39: 1302 | R39: A valor razonable con cambios en el estado de resultados del Estado o de entidades del sector público | S39: =+C39 -> 1302
A40: 1302 | B40: =LEN(C40) -> 6 | C40: 130205 | D40: De 1 a 30 días | E40: X | F40: X | G40: X | H40: X | I40: X | J40: X | K40: X | L40: X | M40: X | N40: X | O40: X | Q40: 130205 | R40: De 1 a 30 días | S40: =+C40 -> 130205
A41: 1302 | B41: =LEN(C41) -> 6 | C41: 130210 | D41: De 31 a 90 días | E41: X | F41: X | G41: X | H41: X | I41: X | J41: X | K41: X | L41: X | M41: X | N41: X | O41: X | Q41: 130210 | R41: De 31 a 90 días | S41: =+C41 -> 130210
A42: 1302 | B42: =LEN(C42) -> 6 | C42: 130215 | D42: De 91 a 180 días | E42: X | F42: X | G42: X | H42: X | I42: X | J42: X | K42: X | L42: X | M42: X | N42: X | O42: X | Q42: 130215 | R42: De 91 a 180 días | S42: =+C42 -> 130215
... A56: 1304 | B56: =LEN(C56) -> 6 | C56: 130425 | D56: De más de 360 días | E56: X | F56: X | G56: X | H56: X | I56: X | J56: X | K56: X | L56: X | M56: X | N56: X | O56: X | Q56: 130425 | R56: De más de 360 días | S56: =+C56 -> 130425
A57: 1304 | B57: =LEN(C57) -> 6 | C57: 130430 | D57: Certificados de abono tributario | G57: X | H57: X | I57: X | J57: X | K57: X | Q57: 130430 | R57: Certificados de abono tributario | S57: =+C57 -> 130430
A58: 1305 | B58: =LEN(C58) -> 4 | C58: 1305 | D58: Mantenidas hasta el vencimiento de entidades del sector privado | E58: X | F58: X | G58: X | H58: X | I58: X | J58: X | K58: X | L58: X | M58: X | N58: X | O58: X | Q58: 1305 | R58: Mantenidas hasta el vencimiento de entidades del sector privado | S58: =+C58 -> 1305
A59: 1305 | B59: =LEN(C59) -> 6 | C59: 130505 | D59: De 1 a 30 días | E59: X | F59: X | G59: X | H59: X | I59: X | J59: X | K59: X | L59: X | M59: X | N59: X | O59: X | Q59: 130505 | R59: De 1 a 30 días | S59: =+C59 -> 130505
A60: 1305 | B60: =LEN(C60) -> 6 | C60: 130510 | D60: De 31 a 90 días | E60: X | F60: X | G60: X | H60: X | I60: X | J60: X | K60: X | L60: X | M60: X | N60: X | O60: X | Q60: 130510 | R60: De 31 a 90 días | S60: =+C60 -> 130510
A61: 1305 | B61: =LEN(C61) -> 6 | C61: 130515 | D61: De 91 a 180 días | E61: X | F61: X | G61: X | H61: X | I61: X | J61: X | K61: X | L61: X | M61: X | N61: X | O61: X | Q61: 130515 | R61: De 91 a 180 días | S61: =+C61 -> 130515
A62: 1305 | B62: =LEN(C62) -> 6 | C62: 130520 | D62: De 181 días a 1 año | E62: X | F62: X | G62: X | H62: X | I62: X | J62: X | K62: X | L62: X | M62: X | N62: X | O62: X | Q62: 130520 | R62: De 181 días a 1 año | S62: =+C62 -> 130520
A63: 1305 | B63: =LEN(C63) -> 6 | C63: 130525 | D63: De 1 a 3 años | E63: X | F63: X | G63: X | H63: X | I63: X | J63: X | K63: X | L63: X | M63: X | N63: X | O63: X | Q63: 130525 | R63: De 1 a 3 años | S63: =+C63 -> 130525
A64: 1305 | B64: =LEN(C64) -> 6 | C64: 130530 | D64: De 3 a 5 años | E64: X | F64: X | G64: X | H64: X | I64: X | J64: X | K64: X | L64: X | M64: X | N64: X | O64: X | Q64: 130530 | R64: De 3 a 5 años | S64: =+C64 -> 130530
A65: 1305 | B65: =LEN(C65) -> 6 | C65: 130535 | D65: De 5 a 10 años | E65: X | F65: X | G65: X | H65: X | I65: X | J65: X | K65: X | L65: X | M65: X | N65: X | O65: X | Q65: 130535 | R65: De 5 a 10 años | S65: =+C65 -> 130535
A66: 1305 | B66: =LEN(C66) -> 6 | C66: 130540 | D66: De más de 10 años | E66: X | F66: X | G66: X | H66: X | I66: X | J66: X | K66: X | L66: X | M66: X | N66: X | O66: X | Q66: 130540 | R66: De más de 10 años | S66: =+C66 -> 130540
A67: 1306 | B67: =LEN(C67) -> 4 | C67: 1306 | D67: Mantenidas hasta su vencimiento del Estado o de entidades del sector público | E67: X | F67: X | G67: X | H67: X | I67: X | J67: X | K67: X | L67: X | M67: X | N67: X | O67: X | Q67: 1306 | R67: Mantenidas hasta su vencimiento del Estado o de entidades del sector público | S67: =+C67 -> 1306
A68: 1306 | B68: =LEN(C68) -> 6 | C68: 130605 | D68: De 1 a 30 días | E68: X | F68: X | G68: X | H68: X | I68: X | J68: X | K68: X | L68: X | M68: X | N68: X | O68: X | Q68: 130605 | R68: De 1 a 30 días | S68: =+C68 -> 130605
A69: 1306 | B69: =LEN(C69) -> 6 | C69: 130610 | D69: De 31 a 90 días | E69: X | F69: X | G69: X | H69: X | I69: X | J69: X | K69: X | L69: X | M69: X | N69: X | O69: X | Q69: 130610 | R69: De 31 a 90 días | S69: =+C69 -> 130610
... A78: 1307 | B78: =LEN(C78) -> 6 | C78: 130710 | D78: Depósitos sujetos a restricción | E78: X | F78: X | G78: X | H78: X | I78: X | J78: X | K78: X | L78: X | M78: X | N78: X | O78: X | Q78: 130710 | R78: Depósitos sujetos a restricción | S78: =+C78 -> 130710
A79: 1307 | B79: =LEN(C79) -> 6 | C79: 130715 | D79: Títulos valores para encaje | E79: X | F79: X | G79: X | H79: X | I79: X | J79: X | K79: X | O79: X | Q79: 130715 | R79: Títulos valores para encaje | S79: =+C79 -> 130715
A80: 1307 | B80: =LEN(C80) -> 6 | C80: 130720 | D80: Entregados en garantía | E80: X | F80: X | G80: X | H80: X | I80: X | J80: X | K80: X | L80: X | M80: X | N80: X | O80: X | Q80: 130720 | R80: Entregados en garantía | S80: =+C80 -> 130720
A81: 1307 | B81: =LEN(C81) -> 6 | C81: 130790 | D81: Otros | E81: X | F81: X | G81: X | H81: X | I81: X | J81: X | K81: X | L81: X | M81: X | N81: X | O81: X | Q81: 130790 | R81: Otros | S81: =+C81 -> 130790
A82: 1399 | B82: =LEN(C82) -> 4 | C82: 1399 | D82: (Provisión para inversiones) | E82: X | F82: X | G82: X | H82: X | I82: X | J82: X | K82: X | L82: X | M82: X | N82: X | O82: X | Q82: 1399 | R82: (Provisión para inversiones) | S82: =+C82 -> 1399
A83: 1399 | B83: =LEN(C83) -> 6 | C83: 139905 | D83: (Provisión para valuación de inversiones) | E83: X | F83: X | G83: X | H83: X | I83: X | J83: X | K83: X | L83: X | M83: X | N83: X | O83: X | Q83: 139905 | R83: (Provisión para valuación de inversiones) | S83: =+C83 -> 139905
A84: 1399 | B84: =LEN(C84) -> 6 | C84: 139910 | D84: (Provisión general para inversiones) | E84: X | F84: X | G84: X | H84: X | I84: X | J84: X | K84: X | L84: X | M84: X | N84: X | O84: X | Q84: 139910 | R84: (Provisión general para inversiones) | S84: =+C84 -> 139910
A85: 14 | B85: =LEN(C85) -> 2 | C85: 14 | D85: CARTERA DE CRÉDITOS | E85: X | F85: X | G85: X | H85: X | I85: X | J85: X | K85: X | L85: X | N85: X | O85: X | Q85: 14 | R85: CARTERA DE CRÉDITOS | S85: =+Q85 -> 14
A86: 1401 | B86: =LEN(C86) -> 4 | C86: 1401 | D86: Cartera de créditos comercial prioritario por vencer | E86: X | G86: X | H86: X | I86: X | J86: X | K86: X | O86: X | Q86: 1401 | R86: CARTERA DE CRÉDITOS PRODUCTIVO POR VENCER | S86: =VLOOKUP(Q86,[8]CUC!I88:K1592,3,0) -> 1401+1405+1406
A87: 1401 | B87: =LEN(C87) -> 6 | C87: 140105 | D87: De 1 a 30 días | E87: X | G87: X | H87: X | I87: X | J87: X | K87: X | O87: X | Q87: 140105 | R87: DE 1 A 30 DÍAS | S87: 140105+140505+140605
A88: 1401 | B88: =LEN(C88) -> 6 | C88: 140110 | D88: De 31 a 90 días | E88: X | G88: X | H88: X | I88: X | J88: X | K88: X | O88: X | Q88: 140110 | R88: DE 31 A 90 DÍAS | S88: 140110+141010+140610
A89: 1401 | B89: =LEN(C89) -> 6 | C89: 140115 | D89: De 91 a 180 días | E89: X | G89: X | H89: X | I89: X | J89: X | K89: X | O89: X | Q89: 140115 | R89: DE 91 A 180 DÍAS | S89: 140115+140515+140615
A90: 1401 | B90: =LEN(C90) -> 6 | C90: 140120 | D90: De 181 a 360 días | E90: X | G90: X | H90: X | I90: X | J90: X | K90: X | O90: X | Q90: 140120 | R90: DE 181 A 360 DÍAS | S90: 140120+1405120+140620
A91: 1401 | B91: =LEN(C91) -> 6 | C91: 140125 | D91: De más de 360 días | E91: X | G91: X | H91: X | I91: X | J91: X | K91: X | O91: X | Q91: 140125 | R91: DE MÁS DE 360 DÍAS | S91: 140125+1405125+140625
A92: 1402 | B92: =LEN(C92) -> 4 | C92: 1402 | D92: Cartera de créditos de consumo prioritario por vencer | E92: X | J92: X | K92: X | O92: X | Q92: 1402 | R92: CARTERA DE CRÉDITOS DE CONSUMO POR VENCER | S92: =VLOOKUP(Q92,[8]CUC!I94:K1598,3,0) -> 1402+1407
A93: 1402 | B93: =LEN(C93) -> 6 | C93: 140205 | D93: De 1 a 30 días | E93: X | J93: X | K93: X | O93: X | Q93: 140205 | R93: DE 1 A 30 DÍAS | S93: 140205+140705
A94: 1402 | B94: =LEN(C94) -> 6 | C94: 140210 | D94: De 31 a 90 días | E94: X | J94: X | K94: X | O94: X | Q94: 140210 | R94: DE 31 A 90 DÍAS | S94: 140210+140710
A95: 1402 | B95: =LEN(C95) -> 6 | C95: 140215 | D95: De 91 a 180 días | E95: X | J95: X | K95: X | O95: X | Q95: 140215 | R95: DE 91 A 180 DÍAS | S95: 140215+140715
A96: 1402 | B96: =LEN(C96) -> 6 | C96: 140220 | D96: De 181 a 360 días | E96: X | J96: X | K96: X | O96: X | Q96: 140220 | R96: DE 181 A 360 DÍAS | S96: 140220+140720
A97: 1402 | B97: =LEN(C97) -> 6 | C97: 140225 | D97: De más de 360 días | E97: X | J97: X | K97: X | O97: X | Q97: 140225 | R97: DE MÁS DE 360 DÍAS | S97: 140225+140725
A98: 1403 | B98: =LEN(C98) -> 4 | C98: 1403 | D98: Cartera de crédito inmobiliario por vencer | E98: X | F98: X | G98: X | H98: X | I98: X | J98: X | K98: X | O98: X | Q98: 1403 | R98: CARTERA DE CRÉDITOS INMOBILIARIO POR VENCER | S98: =VLOOKUP(Q98,[8]CUC!I100:K1604,3,0) -> 1403
A99: 1403 | B99: =LEN(C99) -> 6 | C99: 140305 | D99: De 1 a 30 días | E99: X | F99: X | G99: X | H99: X | I99: X | J99: X | K99: X | O99: X | Q99: 140305 | R99: DE 1 A 30 DÍAS | S99: 140305
A100: 1403 | B100: =LEN(C100) -> 6 | C100: 140310 | D100: De 31 a 90 días | E100: X | F100: X | G100: X | H100: X | I100: X | J100: X | K100: X | O100: X | Q100: 140310 | R100: DE 31 A 90 DÍAS | S100: 140310
A101: 1403 | B101: =LEN(C101) -> 6 | C101: 140315 | D101: De 91 a 180 días | E101: X | F101: X | G101: X | H101: X | I101: X | J101: X | K101: X | O101: X | Q101: 140315 | R101: DE 91 A 180 DÍAS | S101: 140315
A102: 1403 | B102: =LEN(C102) -> 6 | C102: 140320 | D102: De 181 a 360 días | E102: X | F102: X | G102: X | H102: X | I102: X | J102: X | K102: X | O102: X | Q102: 140320 | R102: DE 181 A 360 DÍAS | S102: 140320
A103: 1403 | B103: =LEN(C103) -> 6 | C103: 140325 | D103: De más de 360 días | E103: X | F103: X | G103: X | H103: X | I103: X | J103: X | K103: X | O103: X | Q103: 140325 | R103: DE MÁS DE 360 DÍAS | S103: 140325
A104: 1404 | B104: =LEN(C104) -> 4 | C104: 1404 | D104: Cartera de créditos para la microempresa por vencer | E104: X | G104: X | J104: X | K104: X | O104: X | Q104: 1404 | R104: CARTERA DE CRÉDITOS PARA MICROCRÉDITO POR VENCER | S104: =VLOOKUP(Q104,[8]CUC!I106:K1610,3,0) -> 1404
A105: 1404 | B105: =LEN(C105) -> 6 | C105: 140405 | D105: De 1 a 30 días | E105: X | G105: X | J105: X | K105: X | O105: X | Q105: 140405 | R105: DE 1 A 30 DÍAS | S105: 140405
A106: 1404 | B106: =LEN(C106) -> 6 | C106: 140410 | D106: De 31 a 90 días | E106: X | G106: X | J106: X | K106: X | O106: X | Q106: 140410 | R106: DE 31 A 90 DÍAS | S106: 140410
A107: 1404 | B107: =LEN(C107) -> 6 | C107: 140415 | D107: De 91 a 180 días | E107: X | G107: X | J107: X | K107: X | O107: X | Q107: 140415 | R107: DE 91 A 180 DÍAS | S107: 140415
A108: 1404 | B108: =LEN(C108) -> 6 | C108: 140420 | D108: De 181 a 360 días | E108: X | G108: X | J108: X | K108: X | O108: X | Q108: 140420 | R108: DE 181 A 360 DÍAS | S108: 140420
A109: 1404 | B109: =LEN(C109) -> 6 | C109: 140425 | D109: De más de 360 días | E109: X | G109: X | J109: X | K109: X | O109: X | Q109: 140425 | R109: DE MÁS DE 360 DÍAS | S109: 140425
A110: 1405 | B110: =LEN(C110) -> 4 | C110: 1405 | D110: Cartera de crédito productivo por vencer | E110: X | G110: X | J110: X | K110: X | O110: X | Q110: DESHABILITAR | R110: DESHABILITAR | S110: DESHABILITAR
A111: 1405 | B111: =LEN(C111) -> 6 | C111: 140505 | D111: De 1 a 30 días | E111: X | G111: X | J111: X | K111: X | O111: X | Q111: DESHABILITAR | R111: DESHABILITAR | S111: DESHABILITAR
A112: 1405 | B112: =LEN(C112) -> 6 | C112: 140510 | D112: De 31 a 90 días | E112: X | G112: X | J112: X | K112: X | O112: X | Q112: DESHABILITAR | R112: DESHABILITAR | S112: DESHABILITAR
A113: 1405 | B113: =LEN(C113) -> 6 | C113: 140515 | D113: De 91 a 180 días | E113: X | G113: X | J113: X | K113: X | O113: X | Q113: DESHABILITAR | R113: DESHABILITAR | S113: DESHABILITAR
A114: 1405 | B114: =LEN(C114) -> 6 | C114: 140520 | D114: De 181 a 360 días | E114: X | G114: X | J114: X | K114: X | O114: X | Q114: DESHABILITAR | R114: DESHABILITAR | S114: DESHABILITAR
A115: 1405 | B115: =LEN(C115) -> 6 | C115: 140525 | D115: De más de 360 días | E115: X | G115: X | J115: X | K115: X | O115: X | Q115: DESHABILITAR | R115: DESHABILITAR | S115: DESHABILITAR
A116: 1406 | B116: =LEN(C116) -> 4 | C116: 1406 | D116: Cartera de crédito comercial ordinario por vencer | E116: X | G116: X | J116: X | K116: X | O116: X | Q116: DESHABILITAR | R116: DESHABILITAR | S116: DESHABILITAR
A117: 1406 | B117: =LEN(C117) -> 6 | C117: 140605 | D117: De 1 a 30 días | E117: X | G117: X | J117: X | K117: X | O117: X | Q117: DESHABILITAR | R117: DESHABILITAR | S117: DESHABILITAR
A118: 1406 | B118: =LEN(C118) -> 6 | C118: 140610 | D118: De 31 a 90 días | E118: X | G118: X | J118: X | K118: X | O118: X | Q118: DESHABILITAR | R118: DESHABILITAR | S118: DESHABILITAR
A119: 1406 | B119: =LEN(C119) -> 6 | C119: 140615 | D119: De 91 a 180 días | E119: X | G119: X | J119: X | K119: X | O119: X | Q119: DESHABILITAR | R119: DESHABILITAR | S119: DESHABILITAR
A120: 1406 | B120: =LEN(C120) -> 6 | C120: 140620 | D120: De 181 a 360 días | E120: X | G120: X | J120: X | K120: X | O120: X | Q120: DESHABILITAR | R120: DESHABILITAR | S120: DESHABILITAR
A121: 1406 | B121: =LEN(C121) -> 6 | C121: 140625 | D121: De más de 360 días | E121: X | G121: X | J121: X | K121: X | O121: X | Q121: DESHABILITAR | R121: DESHABILITAR | S121: DESHABILITAR
...

Sheet BALANCE
D1: 0 | E1: 0 | F1: 0 | G1: 0 | H1: 0 | I1: 0 | J1: 0 | K1: 0 | L1: 0 | M1: 0 | N1: 0 | O1: 0 | P1: 0 | Q1: 0 | R1: 0 | S1: 0 | T1: 0 | U1: 0 | V1: 0 | W1: 0 | X1: 0 | Y1: 0 | Z1: 0 | AA1: 0 | AB1: 0 | AC1: 0 | AD1: 0 | AE1: 0 | AF1: 0 | AG1: 4.6566129e-10 | AH1: 0 | AI1: 5.8207661e-11 | AJ1: 2.2351742e-08
B2: ESTADO DE SITUACIÓN | D2: 0 | E2: 1.8189894e-11 | F2: 0 | G2: 3.2741809e-11 | H2: -2.3283064e-10 | I2: 0 | J2: 0 | K2: 0 | L2: 0 | M2: 0 | N2: 0 | O2: 0 | P2: -4.5474735e-12 | Q2: -5.4569682e-12 | R2: 0 | S2: 4.206413e-12 | T2: -1.5276669e-13 | U2: 1.2789769e-13 | V2: 0 | W2: 0 | X2: 0 | Y2: 0 | Z2: 1.9895197e-13 | AA2: -1.080025e-12 | AB2: 0 | AC2: 0 | AD2: 1.0004442e-11 | AE2: 0 | AF2: 0 | AG2: 3.6379788e-11 | AH2: 0 | AI2: 0 | AJ2: 0
B3: SISTEMA DE BANCOS PRIVADOS
B4: 44439
B5: (en miles de dólares)
B8: CÓDIGO | C8: CUENTA | D8: BP GUAYAQUIL | E8: BP PACIFICO | F8: BP PICHINCHA | G8: BP PRODUBANCO | H8: BANCOS PRIVADOS GRANDES | I8: BP AUSTRO | J8: BP BOLIVARIANO | K8: BP CITIBANK | L8: BP DINERS | M8: BP GENERAL RUMIÑAHUI | N8: BP INTERNACIONAL | O8: BP LOJA | P8: BP MACHALA | Q8: BP SOLIDARIO | R8: BANCOS PRIVADOS MEDIANOS | S8: BP PROCREDIT | T8: BP AMAZONAS | U8: BP COMERCIAL DE MANABI | V8: BP LITORAL | W8: BP COOPNACIONAL | X8: BP CAPITAL | Y8: BP FINCA S.A. | Z8: BP DELBANK | AA8: BP D-MIRO S.A. | AB8: BP BANCO DESARROLLO DE LOS PUEBLOS S.A., CODESARROLLO | AC8: BP VISIONFUND ECUADOR S.A. | AD8: BANCOS PRIVADOS PEQUEÑOS | AE8: TOTAL BANCOS PRIVADOS | AF8: BANCOS PRIVADOS COMERCIALES | AG8: BANCOS PRIVADOS CONSUMO | AH8: BANCOS PRIVADOS VIVIENDA | AI8: BANCOS PRIVADOS DE MICROCRÉDITO | AJ8: BANCA MULTIPLE
B9: ACTIVO | C9: ACTIVO | D9: #N/A | E9: #N/A | F9: #N/A | G9: #N/A | I9: #N/A | J9: #N/A | K9: #N/A | L9: #N/A | M9: #N/A | N9: #N/A | O9: #N/A | P9: #N/A | Q9: #N/A | S9: #N/A | T9: #N/A | U9: #N/A | V9: #N/A | W9: #N/A | X9: #N/A | Y9: #N/A | Z9: #N/A | AA9: #N/A | AB9: #N/A | AC9: #N/A
B10: 11 | C10: FONDOS DISPONIBLES | D10: 851347.57 | E10: 1203729.2 | F10: 1740514.5 | G10: 895515.05 | H10: 4691106.3 | I10: 430335.96 | J10: 871739.42 | K10: 297817.12 | L10: 72585.907 | M10: 163183.69 | N10: 736322.44 | O10: 150658.3 | P10: 163296.08 | Q10: 72369.493 | R10: 2958308.4 | S10: 67381.47 | T10: 29676.345 | U10: 10340.623 | V10: 1984.3271 | W10: 59570.614 | X10: 3134.4886 | Y10: 9134.2929 | Z10: 6793.6288 | AA10: 7038.1645 | AB10: 23371.86 | AC10: 4390.1098 | AD10: 222815.92 | AE10: 7872230.6 | AF10: 1034139.6 | AG10: 237753.93 | AH10: 0 | AI10: 20562.567 | AJ10: 6579774.5
B11: 1101 | C11: Caja | D11: 202092.29 | E11: 242545.55 | F11: 286144.05 | G11: 111773.52 | H11: 842555.41 | I11: 63654.693 | J11: 170070.44 | K11: 653.2 | L11: 3.8 | M11: 15984.809 | N11: 86571.521 | O11: 20668.291 | P11: 25276.415 | Q11: 18975.428 | R11: 401858.59 | S11: 5429.2029 | T11: 4596.1246 | U11: 2910.2387 | V11: 508.30004 | W11: 8038.5995 | X11: 424.26849 | Y11: 743.1339 | Z11: 1907.2755 | AA11: 1523.319 | AB11: 4598.4674 | AC11: 814.35751 | AD11: 31493.288 | AE11: 1275907.3 | AF11: 87224.721 | AG11: 16496.909 | AH11: 0 | AI11: 3080.8104 | AJ11: 1169104.9
B12: 110105 | C12: Efectivo | D12: 202092.29 | E12: 242545.55 | F12: 286110.05 | G12: 111773.52 | H12: 842521.41 | I12: 63652.593 | J12: 170070.23 | K12: 653.2 | L12: 0 | M12: 15984.059 | N12: 86561.221 | O12: 20665.571 | P12: 25276.315 | Q12: 18957.428 | R12: 401820.62 | S12: 5429.2029 | T12: 4595.7246 | U12: 2910.1387 | V12: 507.27255 | W12: 8018.5995 | X12: 423.56849 | Y12: 739.3839 | Z12: 1906.8755 | AA12: 1523.319 | AB12: 4593.6674 | AC12: 802.85751 | AD12: 31450.61 | AE12: 1275792.6 | AF12: 87214.421 | AG12: 16491.331 | AH12: 0 | AI12: 3065.5604 | AJ12: 1169021.3
B13: 110110 | C13: Caja chica | D13: 0 | E13: 0 | F13: 34 | G13: 0 | H13: 34 | I13: 2.1 | J13: 0.20547 | K13: 0 | L13: 3.8 | M13: 0.75 | N13: 10.3 | O13: 2.72 | P13: 0.1 | Q13: 18 | R13: 37.97547 | S13: 0 | T13: 0.4 | U13: 0.1 | V13: 1.02749 | W13: 20 | X13: 0.7 | Y13: 3.75 | Z13: 0.4 | AA13: 0 | AB13: 4.8 | AC13: 11.5 | AD13: 42.67749 | AE13: 114.65296 | AF13: 10.3 | AG13: 5.57749 | AH13: 0 | AI13: 15.25 | AJ13: 83.52547
B14: 1102 | C14: Depósitos para encaje | D14: 508927.33 | E14: 819280.33 | F14: 1054553.1 | G14: 385722.35 | H14: 2768483.1 | I14: 233168.16 | J14: 261221.21 | K14: 117329.07 | L14: 27355.617 | M14: 22889.849 | N14: 336604.29 | O14: 90549.539 | P14: 66904.258 | Q14: 19048.414 | R14: 1175070.4 | S14: 30382.774 | T14: 10810.449 | U14: 5253.0565 | V14: 1213.8774 | W14: 3920.0003 | X14: 836.40884 | Y14: 5192.1089 | Z14: 1569.1817 | AA14: 1997.9862 | AB14: 8100.2283 | AC14: 394.27054 | AD14: 69670.342 | AE14: 4013223.8 | AF14: 453933.36 | AG14: 51459.343 | AH14: 0 | AI14: 7584.3656 | AJ14: 3500246.8
B15: 110205 | C15: Banco Central del Ecuador | D15: 508927.14 | E15: 819280.33 | F15: 1054553.1 | G15: 385722.35 | H15: 2768482.9 | I15: 233164.08 | J15: 261221.21 | K15: 117329.07 | L15: 27355.617 | M15: 22889.849 | N15: 336604.29 | O15: 90519.542 | P15: 66904.258 | Q15: 19048.414 | R15: 1175036.3 | S15: 30382.774 | T15: 10810.449 | U15: 5253.0565 | V15: 1213.8774 | W15: 3920.0003 | X15: 836.40884 | Y15: 5192.1089 | Z15: 1569.1817 | AA15: 1997.9862 | AB15: 8100.2283 | AC15: 394.27054 | AD15: 69670.342 | AE15: 4013189.6 | AF15: 453933.36 | AG15: 51459.343 | AH15: 0 | AI15: 7584.3656 | AJ15: 3500212.5
B16: 110210 | C16: Banco Nacional de Fomento | D16: 0 | E16: 0 | F16: 0 | G16: 0 | H16: 0 | I16: 4.08304 | J16: 0 | K16: 0 | L16: 0 | M16: 0 | N16: 0 | O16: 29.99731 | P16: 0 | Q16: 0 | R16: 34.08035 | S16: 0 | T16: 0 | U16: 0 | V16: 0 | W16: 0 | X16: 0 | Y16: 0 | Z16: 0 | AA16: 0 | AB16: 0 | AC16: 0 | AD16: 0 | AE16: 34.08035 | AF16: 0 | AG16: 0 | AH16: 0 | AI16: 0 | AJ16: 34.08035
B17: 110215 | C17: Bancos locales | D17: 0.19135 | E17: 0 | F17: 0 | G17: 0 | H17: 0.19135 | I17: 0 | J17: 0 | K17: 0 | L17: 0 | M17: 0 | N17: 0 | O17: 0 | P17: 0 | Q17: 0 | R17: 0 | S17: 0 | T17: 0 | U17: 0 | V17: 0 | W17: 0 | X17: 0 | Y17: 0 | Z17: 0 | AA17: 0 | AB17: 0 | AC17: 0 | AD17: 0 | AE17: 0.19135 | AF17: 0 | AG17: 0 | AH17: 0 | AI17: 0 | AJ17: 0.19135
B18: 1103 | C18: Bancos y otras instituciones financieras | D18: 103605.12 | E18: 94441.238 | F18: 282503.16 | G18: 329668.7 | H18: 810218.22 | I18: 128102.01 | J18: 388864.83 | K18: 176761.3 | L18: 45226.49 | M18: 88124.944 | N18: 290434.5 | O18: 36646.547 | P18: 65857.718 | Q18: 34144.486 | R18: 1254162.8 | S18: 30397.39 | T18: 13945.767 | U18: 1899.0149 | V18: 206.19702 | W18: 47523.491 | X18: 1792.0048 | Y18: 3194.3974 | Z18: 3303.7433 | AA18: 3507.9051 | AB18: 10209.184 | AC18: 3181.4818 | AD18: 119160.58 | AE18: 2183541.6 | AF18: 467195.8 | AG18: 133557.63 | AH18: 0 | AI18: 9883.7843 | AJ18: 1572904.4
B19: 110305 | C19: Banco Central del Ecuador | D19: 0 | E19: 0 | F19: 0 | G19: 0 | H19: 0 | I19: 0 | J19: 0 | K19: 0 | L19: 0 | M19: 0 | N19: 0 | O19: 0 | P19: 0 | Q19: 0 | R19: 0 | S19: 0 | T19: 0 | U19: 0 | V19: 0 | W19: 0 | X19: 0 | Y19: 0.123 | Z19: 0 | AA19: 0 | AB19: 0 | AC19: 0 | AD19: 0.123 | AE19: 0.123 | AF19: 0 | AG19: 0 | AH19: 0 | AI19: 0.123 | AJ19: 0
B20: 110310 | C20: Bancos e instituciones financieras locales | D20: 84319.642 | E20: 3915.5001 | F20: 5986.2384 | G20: 252519.75 | H20: 346741.13 | I20: 116245.48 | J20: 142015.11 | K20: 39919.589 | L20: 37931.276 | M20: 57229.965 | N20: 124818.68 | O20: 19655.831 | P20: 54606.788 | Q20: 12016.406 | R20: 604439.13 | S20: 22238.099 | T20: 12471.694 | U20: 1695.8697 | V20: 206.19702 | W20: 47523.491 | X20: 1778.0417 | Y20: 2250.5918 | Z20: 2903.4106 | AA20: 3507.9051 | AB20: 9160.0934 | AC20: 3181.4818 | AD20: 106916.88 | AE20: 1058097.1 | AF20: 164738.27 | AG20: 95367.439 | AH20: 0 | AI20: 8939.9786 | AJ20: 789051.45
B21: 110315 | C21: Bancos e instituciones financieras del exterior | D21: 19285.474 | E21: 90525.737 | F21: 141946.25 | G21: 77148.949 | H21: 328906.41 | I21: 11856.526 | J21: 246849.72 | K21: 133735.14 | L21: 7295.2135 | M21: 30894.978 | N21: 165615.83 | O21: 16990.716 | P21: 11250.93 | Q21: 22128.081 | R21: 646617.14 | S21: 8159.2906 | T21: 1474.0735 | U21: 203.14513 | V21: 0 | W21: 0 | X21: 13.96315 | Y21: 0 | Z21: 400.33273 | AA21: 0 | AB21: 1049.0905 | AC21: 0 | AD21: 11299.896 | AE21: 986823.44 | AF21: 299350.97 | AG21: 38190.192 | AH21: 0 | AI21: 0 | AJ21: 649282.28
B22: 110320 | C22: EXCEDENTE DE FONDO DE LIQUIDEZ | D22: 0 | E22: 0 | F22: 134570.68 | G22: 0 | H22: 134570.68 | I22: 0 | J22: 0 | K22: 3106.565 | L22: 0 | M22: 0 | N22: 0 | O22: 0 | P22: 0 | Q22: 0 | R22: 3106.565 | S22: 0 | T22: 0 | U22: 0 | V22: 0 | W22: 0 | X22: 0 | Y22: 943.68267 | Z22: 0 | AA22: 0 | AB22: 0 | AC22: 0 | AD22: 943.68267 | AE22: 138620.93
B23: 1104 | C23: Efectos de cobro inmediato | D23: 36722.834 | E23: 16350.502 | F23: 50577.92 | G23: 30210.061 | H23: 133861.32 | I23: 5411.0924 | J23: 33749.507 | K23: 3073.552 | L23: 0 | M23: 806.63097 | N23: 22711.618 | O23: 0 | P23: 2879.1237 | Q23: 196.16484 | R23: 68827.689 | S23: 1172.1026 | T23: 324.00372 | U23: 278.19511 | V23: 41.47253 | W23: 88.52325 | X23: 81.80643 | Y23: 4.6527 | Z23: 13.42829 | AA23: 0 | AB23: 78.53879 | AC23: 0 | AD23: 2082.7234 | AE23: 204771.73 | AF23: 25785.17 | AG23: 848.1035 | AH23: 0 | AI23: 4.6527 | AJ23: 178133.8
B24: 1105 | C24: Remesas en tránsito | D24: 0 | E24: 31111.537 | F24: 66736.268 | G24: 38140.424 | H24: 135988.23 | I24: 0 | J24: 17833.428 | K24: 0 | L24: 0 | M24: 35377.461 | N24: 0.51 | O24: 2793.9245 | P24: 2378.5658 | Q24: 5 | R24: 58388.89 | S24: 0 | T24: 0 | U24: 0.11793 | V24: 14.48016 | W24: 0 | X24: 0 | Y24: 0 | Z24: 0 | AA24: 8.95427 | AB24: 385.44135 | AC24: 0 | AD24: 408.99371 | AE24: 194786.11 | AF24: 0.51 | AG24: 35391.941 | AH24: 0 | AI24: 8.95427 | AJ24: 159384.71
B25: 110505 | C25: Del país | D25: 0 | E25: 31111.537 | F25: 66736.268 | G25: 37905.942 | H25: 135753.75 | I25: 0 | J25: 17819.862 | K25: 0 | L25: 0 | M25: 35377.461 | N25: 0 | O25: 2786.9806 | P25: 2378.5658 | Q25: 0 | R25: 58362.87 | S25: 0 | T25: 0 | U25: 0 | V25: 14.48016 | W25: 0 | X25: 0 | Y25: 0 | Z25: 0 | AA25: 8.95427 | AB25: 385.44135 | AC25: 0 | AD25: 408.87578 | AE25: 194525.49 | AF25: 0 | AG25: 35391.941 | AH25: 0 | AI25: 8.95427 | AJ25: 159124.6
B26: 110510 | C26: Del exterior | D26: 0 | E26: 0 | F26: 0 | G26: 234.48169 | H26: 234.48169 | I26: 0 | J26: 13.5656 | K26: 0 | L26: 0 | M26: 0 | N26: 0.51 | O26: 6.94389 | P26: 0 | Q26: 5 | R26: 26.01949 | S26: 0 | T26: 0 | U26: 0.11793 | V26: 0 | W26: 0 | X26: 0 | Y26: 0 | Z26: 0 | AA26: 0 | AB26: 0 | AC26: 0 | AD26: 0.11793 | AE26: 260.61911 | AF26: 0.51 | AG26: 0 | AH26: 0 | AI26: 0 | AJ26: 260.10911
B27: 12 | C27: OPERACIONES INTERBANCARIAS | D27: 0 | E27: 0 | F27: 0 | G27: 0 | H27: 0 | I27: 0 | J27: 0 | K27: 0 | L27: 0 | M27: 0 | N27: 0 | O27: 0 | P27: 0 | Q27: 0 | R27: 0 | S27: 0 | T27: 0 | U27: 0 | V27: 0 | W27: 0 | X27: 0 | Y27: 0 | Z27: 0 | AA27: 0 | AB27: 0 | AC27: 0 | AD27: 0 | AE27: 0 | AF27: 0 | AG27: 0 | AH27: 0 | AI27: 0 | AJ27: 0
B28: 1201 | C28: Fondos interbancarios vendidos | D28: 0 | E28: 0 | F28: 0 | G28: 0 | H28: 0 | I28: 0 | J28: 0 | K28: 0 | L28: 0 | M28: 0 | N28: 0 | O28: 0 | P28: 0 | Q28: 0 | R28: 0 | S28: 0 | T28: 0 | U28: 0 | V28: 0 | W28: 0 | X28: 0 | Y28: 0 | Z28: 0 | AA28: 0 | AB28: 0 | AC28: 0 | AD28: 0 | AE28: 0 | AF28: 0 | AG28: 0 | AH28: 0 | AI28: 0 | AJ28: 0
B29: 120105 | C29: Bancos | D29: 0 | E29: 0 | F29: 0 | G29: 0 | H29: 0 | I29: 0 | J29: 0 | K29: 0 | L29: 0 | M29: 0 | N29: 0 | O29: 0 | P29: 0 | Q29: 0 | R29: 0 | S29: 0 | T29: 0 | U29: 0 | V29: 0 | W29: 0 | X29: 0 | Y29: 0 | Z29: 0 | AA29: 0 | AB29: 0 | AC29: 0 | AD29: 0 | AE29: 0 | AF29: 0 | AG29: 0 | AH29: 0 | AI29: 0 | AJ29: 0
B30: 120110 | C30: Otras instituciones del sistema financiero | D30: 0 | E30: 0 | F30: 0 | G30: 0 | H30: 0 | I30: 0 | J30: 0 | K30: 0 | L30: 0 | M30: 0 | N30: 0 | O30: 0 | P30: 0 | Q30: 0 | R30: 0 | S30: 0 | T30: 0 | U30: 0 | V30: 0 | W30: 0 | X30: 0 | Y30: 0 | Z30: 0 | AA30: 0 | AB30: 0 | AC30: 0 | AD30: 0 | AE30: 0 | AF30: 0 | AG30: 0 | AH30: 0 | AI30: 0 | AJ30: 0
B31: 1202 | C31: Operaciones de reporto con instituciones financieras | D31: 0 | E31: 0 | F31: 0 | G31: 0 | H31: 0 | I31: 0 | J31: 0 | K31: 0 | L31: 0 | M31: 0 | N31: 0 | O31: 0 | P31: 0 | Q31: 0 | R31: 0 | S31: 0 | T31: 0 | U31: 0 | V31: 0 | W31: 0 | X31: 0 | Y31: 0 | Z31: 0 | AA31: 0 | AB31: 0 | AC31: 0 | AD31: 0 | AE31: 0 | AF31: 0 | AG31: 0 | AH31: 0 | AI31: 0 | AJ31: 0
B32: 120205 | C32: Instituciones financieras públicas | D32: 0 | E32: 0 | F32: 0 | G32: 0 | H32: 0 | I32: 0 | J32: 0 | K32: 0 | L32: 0 | M32: 0 | N32: 0 | O32: 0 | P32: 0 | Q32: 0 | R32: 0 | S32: 0 | T32: 0 | U32: 0 | V32: 0 | W32: 0 | X32: 0 | Y32: 0 | Z32: 0 | AA32: 0 | AB32: 0 | AC32: 0 | AD32: 0 | AE32: 0 | AF32: 0 | AG32: 0 | AH32: 0 | AI32: 0 | AJ32: 0
B33: 120210 | C33: Bancos | D33: 0 | E33: 0 | F33: 0 | G33: 0 | H33: 0 | I33: 0 | J33: 0 | K33: 0 | L33: 0 | M33: 0 | N33: 0 | O33: 0 | P33: 0 | Q33: 0 | R33: 0 | S33: 0 | T33: 0 | U33: 0 | V33: 0 | W33: 0 | X33: 0 | Y33: 0 | Z33: 0 | AA33: 0 | AB33: 0 | AC33: 0 | AD33: 0 | AE33: 0 | AF33: 0 | AG33: 0 | AH33: 0 | AI33: 0 | AJ33: 0
B34: 120215 | C34: Otras instituciones del sistema financiero | D34: 0 | E34: 0 | F34: 0 | G34: 0 | H34: 0 | I34: 0 | J34: 0 | K34: 0 | L34: 0 | M34: 0 | N34: 0 | O34: 0 | P34: 0 | Q34: 0 | R34: 0 | S34: 0 | T34: 0 | U34: 0 | V34: 0 | W34: 0 | X34: 0 | Y34: 0 | Z34: 0 | AA34: 0 | AB34: 0 | AC34: 0 | AD34: 0 | AE34: 0 | AF34: 0 | AG34: 0 | AH34: 0 | AI34: 0 | AJ34: 0
... B90: 139910 | C90: (Provisión general para inversiones) | D90: -6057.6105 | E90: -2635 | F90: 0 | G90: 0 | H90: -8692.6105 | I90: 0 | J90: -1156.1564 | K90: 0 | L90: 0 | M90: -6704.2211 | N90: -2.3 | O90: 0 | P90: 0 | Q90: 0 | R90: -7862.6775 | S90: 0 | T90: 0 | U90: -78.69071 | V90: 0 | W90: -110.06781 | X90: 0 | Y90: 0 | Z90: 0 | AA90: 0 | AB90: 0 | AC90: 0 | AD90: -188.75852 | AE90: -16744.047 | AF90: -2.3 | AG90: -6704.2211 | AH90: 0 | AI90: 0 | AJ90: -10037.525
A91: 2 | B91: 14 | C91: CARTERA DE CRÉDITOS | D91: 3680242.8 | E91: 4109265.9 | F91: 6866034.2 | G91: 3511766.6 | H91: 18167310 | I91: 1174443.8 | J91: 2370883.9 | K91: 184852.06 | L91: 1785415.2 | M91: 610152.75 | N91: 2428345.8 | O91: 354916.54 | P91: 528634.4 | Q91: 532636.33 | R91: 9970280.8 | S91: 433689.51 | T91: 125240.75 | U91: 30152.521 | V91: 26897.07 | W91: 86662.114 | X91: 14591.048 | Y91: 66210.444 | Z91: 15485.992 | AA91: 74316.385 | AB91: 153865.92 | AC91: 77705.929 | AD91: 1104817.7 | AE91: 29242408 | AF91: 2613197.9 | AG91: 2422465 | AH91: 0 | AI91: 218232.76 | AJ91: 23988512
A92: 4 | B92: 1401 | C92: CARTERA DE CRÉDITOS PRODUCTIVO POR VENCER | D92: 1962543.7 | E92: 875507.94 | F92: 2724189.3 | G92: 2264074.9 | H92: 7826315.9 | I92: 546136.56 | J92: 1763520.1 | K92: 200456.66 | L92: 89846.324 | M92: 47644.449 | N92: 2019830.3 | O92: 89331.174 | P92: 341579.8 | Q92: 33.75639 | R92: 5098379.1 | S92: 322474.05 | T92: 61827.193 | U92: 12831.412 | V92: 3996.6694 | W92: 78805.76 | X92: 1036.2916 | Y92: 0 | Z92: 6272.3455 | AA92: 0 | AB92: 13666.176 | AC92: 0 | AD92: 500909.9 | AE92: 13425605 | AF92: 2220287 | AG92: 141487.44 | AH92: 0 | AI92: 0 | AJ92: 11063830
A93: 6 | B93: 140105 | C93: DE 1 A 30 DÍAS | D93: 191837.3 | E93: 57109.117 | F93: 323351.8 | G93: 211224.62 | H93: 783522.83 | I93: 40655.791 | J93: 135235.47 | K93: 39562.386 | L93: 41635.41 | M93: 6105.5604 | N93: 146885.16 | O93: 4234.0088 | P93: 12582.924 | Q93: 0 | R93: 426896.71 | S93: 11630.607 | T93: 5403.9779 | U93: 344.22073 | V93: 211.74078 | W93: 1245.6691 | X93: 285.10442 | Y93: 0 | Z93: 510.20573 | AA93: 0 | AB93: 689.20597 | AC93: 0 | AD93: 20320.732 | AE93: 1230740.3 | AF93: 186447.54 | AG93: 47952.711 | AH93: 0 | AI93: 0 | AJ93: 996340.02
A94: 6 | B94: 140110 | C94: DE 31 A 90 DÍAS | D94: 302152.44 | E94: 71146.733 | F94: 374440.57 | G94: 201051.49 | H94: 948791.24 | I94: 52689.109 | J94: 225206.37 | K94: 69975.35 | L94: 16184.823 | M94: 8306.2152 | N94: 232545.5 | O94: 5252.0365 | P94: 17164.665 | Q94: 33.75639 | R94: 627357.83 | S94: 24604.351 | T94: 8997.9737 | U94: 1033.9001 | V94: 399.98943 | W94: 10492.294 | X94: 400.83031 | Y94: 0 | Z94: 849.53712 | AA94: 0 | AB94: 1368.3347 | AC94: 0 | AD94: 48147.21 | AE94: 1624296.3 | AF94: 302520.85 | AG94: 24891.027 | AH94: 0 | AI94: 0 | AJ94: 1296884.4
A95: 6 | B95: 140115 | C95: DE 91 A 180 DÍAS | D95: 266516.49 | E95: 105895.73 | F95: 443678.65 | G95: 259101.27 | H95: 1075192.1 | I95: 71966.871 | J95: 249255.94 | K95: 48877.396 | L95: 16220.749 | M95: 10345.019 | N95: 336710.48 | O95: 8531.1704 | P95: 24101.855 | Q95: 0 | R95: 766009.48 | S95: 28078.277 | T95: 10817.213 | U95: 769.63818 | V95: 494.3601 | W95: 11772.552 | X95: 233.40025 | Y95: 0 | Z95: 920.99092 | AA95: 0 | AB95: 2042.7355 | AC95: 0 | AD95: 55129.167 | AE95: 1896330.8 | AF95: 385587.88 | AG95: 27060.128 | AH95: 0 | AI95: 0 | AJ95: 1483682.8
A96: 6 | B96: 140120 | C96: DE 181 A 360 DÍAS | D96: 240314.91 | E96: 126402.01 | F96: 455196.08 | G96: 299852.55 | H96: 1121765.5 | I96: 102130.82 | J96: 305529.2 | K96: 12900.81 | L96: 8789.0018 | M96: 8092.7226 | N96: 320130.29 | O96: 14764.63 | P96: 49392.015 | Q96: 0 | R96: 821729.5 | S96: 57390.787 | T96: 10024.537 | U96: 1690.927 | V96: 972.77359 | W96: 23921.861 | X96: 4.2461 | Y96: 0 | Z96: 1562.5037 | AA96: 0 | AB96: 3833.5572 | AC96: 0 | AD96: 99401.192 | AE96: 2042896.2 | AF96: 333031.1 | AG96: 17854.498 | AH96: 0 | AI96: 0 | AJ96: 1692010.6
A97: 6 | B97: 140125 | C97: DE MÁS DE 360 DÍAS | D97: 961722.57 | E97: 514954.35 | F97: 1127522.2 | G97: 1292845 | H97: 3897044.1 | I97: 278693.97 | J97: 848293.08 | K97: 29140.72 | L97: 7016.3408 | M97: 14794.932 | N97: 983558.87 | O97: 56549.328 | P97: 238338.34 | Q97: 0 | R97: 2456385.6 | S97: 200770.03 | T97: 26583.492 | U97: 8992.7259 | V97: 1917.8055 | W97: 31373.384 | X97: 112.71048 | Y97: 0 | Z97: 2429.108 | AA97: 0 | AB97: 5732.343 | AC97: 0 | AD97: 277911.6 | AE97: 6631341.3 | AF97: 1012699.6 | AG97: 23729.078 | AH97: 0 | AI97: 0 | AJ97: 5594912.6
A98: 4 | B98: 1402 | C98: CARTERA DE CRÉDITOS DE CONSUMO POR VENCER | D98: 1358414.4 | E98: 1760846.3 | F98: 2375413.4 | G98: 981969.93 | H98: 6476644.1 | I98: 474604.86 | J98: 594222.89 | K98: 0 | L98: 1671682.5 | M98: 464703.53 | N98: 305278.61 | O98: 145131.79 | P98: 160939.91 | Q98: 248562.94 | R98: 4065127.1 | S98: 4050.5684 | T98: 55130.573 | U98: 8238.6812 | V98: 17268.504 | W98: 804.66754 | X98: 12893.287 | Y98: 3625.2436 | Z98: 3815.8856 | AA98: 0 | AB98: 41087.48 | AC98: 30.08534 | AD98: 146944.98 | AE98: 10688716 | AF98: 305278.61 | AG98: 2153654.6 | AH98: 0 | AI98: 3655.3289 | AJ98: 8226127.6
A99: 6 | B99: 140205 | C99: DE 1 A 30 DÍAS | D99: 308477.63 | E99: 159632.05 | F99: 484794.08 | G99: 346831.68 | H99: 1299735.4 | I99: 96586.601 | J99: 309165.81 | K99: 0 | L99: 706509.91 | M99: 52676.473 | N99: 95451.041 | O99: 9921.0736 | P99: 24694.46 | Q99: 20612.498 | R99: 1315617.9 | S99: 147.33406 | T99: 8468.5879 | U99: 1004.5365 | V99: 601.26947 | W99: 35.21862 | X99: 793.57249 | Y99: 173.58085 | Z99: 192.03883 | AA99: 0 | AB99: 1114.0942 | AC99: 0.1579 | AD99: 12530.391 | AE99: 2627883.7 | AF99: 95451.041 | AG99: 759787.65 | AH99: 0 | AI99: 173.73875 | AJ99: 1772471.3
A100: 6 | B100: 140210 | C100: DE 31 A 90 DÍAS | D100: 97228.765 | E100: 159742.63 | F100: 172136.58 | G100: 68803.382 | H100: 497911.35 | I100: 29128.407 | J100: 35097.596 | K100: 0 | L100: 189870.29 | M100: 20728.063 | N100: 24139.752 | O100: 7501.8238 | P100: 11630.437 | Q100: 33520.28 | R100: 351616.65 | S100: 407.66367 | T100: 3781.4699 | U100: 632.17859 | V100: 927.47575 | W100: 63.74453 | X100: 935.07161 | Y100: 300.46278 | Z100: 318.914 | AA100: 0 | AB100: 2119.5057 | AC100: 0.16053 | AD100: 9486.647 | AE100: 859014.65 | AF100: 24139.752 | AG100: 211525.83 | AH100: 0 | AI100: 300.62331 | AJ100: 623048.45
A101: 6 | B101: 140215 | C101: DE 91 A 180 DÍAS | D101: 125224.61 | E101: 183932.17 | F101: 205244.02 | G101: 84037.368 | H101: 598438.17 | I101: 37867.405 | J101: 42587.817 | K101: 0 | L101: 177182.34 | M101: 28546.751 | N101: 29881.864 | O101: 11116.419 | P101: 14119.167 | Q101: 41913.346 | R101: 383215.11 | S101: 618.72643 | T101: 4727.7988 | U101: 744.23343 | V101: 1455.6197 | W101: 89.42315 | X101: 1315.0315 | Y101: 504.39243 | Z101: 461.22386 | AA101: 0 | AB101: 3248.1665 | AC101: 0.81901 | AD101: 13165.435 | AE101: 994818.72 | AF101: 29881.864 | AG101: 207184.71 | AH101: 0 | AI101: 505.21144 | AJ101: 757246.93
A102: 6 | B102: 140220 | C102: DE 181 A 360 DÍAS | D102: 212516.73 | E102: 259786.72 | F102: 324816.52 | G102: 129233.27 | H102: 926353.25 | I102: 65342.927 | J102: 59547.978 | K102: 0 | L102: 197600.83 | M102: 52798.186 | N102: 45950.946 | O102: 19793.742 | P102: 23543.498 | Q102: 64726.315 | R102: 529304.42 | S102: 750.17479 | T102: 8553.6036 | U102: 1325.1121 | V102: 3015.0664 | W102: 174.13983 | X102: 1990.0303 | Y102: 988.20243 | Z102: 885.79743 | AA102: 0 | AB102: 6720.3114 | AC102: 19.3659 | AD102: 24421.804 | AE102: 1480079.5 | AF102: 45950.946 | AG102: 253414.08 | AH102: 0 | AI102: 1007.5683 | AJ102: 1179706.9
... A537: 6 | B537: 149989 | C537: (PROVISIÓN GENERICA VOLUNTARIA) | D537: -66046.776 | E537: -52320.994 | F537: -192774.2 | G537: -46346.859 | H537: -357488.83 | I537: -6936.8568 | J537: -38024 | K537: -8691.196 | L537: -106741.55 | M537: -9795.5832 | N537: -11891.992 | O537: -5105.7874 | P537: -3188.7578 | Q537: -11603.721 | R537: -201979.44 | S537: -321.88337 | T537: -20.20584 | U537: -349.31309 | V537: -3.20128 | W537: -847.30747 | X537: 0 | Y537: -7.17443 | Z537: -2.21835 | AA537: -143.89157 | AB537: -283.46216 | AC537: -603.6323 | AD537: -2582.2899 | AE537: -562050.56 | AF537: -20583.188 | AG537: -116540.33 | AH537: 0 | AI537: -754.6983 | AJ537: -424172.35
B538: 15 | C538: DEUDORES POR ACEPTACIONES | D538: 0 | E538: 4879.3975 | F538: 221.7718 | G538: 30.24157 | H538: 5131.4109 | I538: 64.1558 | J538: 0 | K538: 262.886 | L538: 0 | M538: 0 | N538: 0 | O538: 0 | P538: 0 | Q538: 0 | R538: 327.0418 | S538: 0 | T538: 0 | U538: 0 | V538: 0 | W538: 0 | X538: 0 | Y538: 0 | Z538: 0 | AA538: 0 | AB538: 0 | AC538: 0 | AD538: 0 | AE538: 5458.4527 | AF538: 262.886 | AG538: 0 | AH538: 0 | AI538: 0 | AJ538: 5195.5667
B539: 1501 | C539: Dentro del plazo | D539: 0 | E539: 4879.3975 | F539: 221.7718 | G539: 30.24157 | H539: 5131.4109 | I539: 64.1558 | J539: 0 | K539: 262.886 | L539: 0 | M539: 0 | N539: 0 | O539: 0 | P539: 0 | Q539: 0 | R539: 327.0418 | S539: 0 | T539: 0 | U539: 0 | V539: 0 | W539: 0 | X539: 0 | Y539: 0 | Z539: 0 | AA539: 0 | AB539: 0 | AC539: 0 | AD539: 0 | AE539: 5458.4527 | AF539: 262.886 | AG539: 0 | AH539: 0 | AI539: 0 | AJ539: 5195.5667
B540: 1502 | C540: Después del plazo | D540: 0 | E540: 0 | F540: 0 | G540: 0 | H540: 0 | I540: 0 | J540: 0 | K540: 0 | L540: 0 | M540: 0 | N540: 0 | O540: 0 | P540: 0 | Q540: 0 | R540: 0 | S540: 0 | T540: 0 | U540: 0 | V540: 0 | W540: 0 | X540: 0 | Y540: 0 | Z540: 0 | AA540: 0 | AB540: 0 | AC540: 0 | AD540: 0 | AE540: 0 | AF540: 0 | AG540: 0 | AH540: 0 | AI540: 0 | AJ540: 0
B541: 16 | C541: CUENTAS POR COBRAR | D541: 62575.842 | E541: 144140.39 | F541: 267993.89 | G541: 70848.291 | H541: 545558.42 | I541: 56591.787 | J541: 38051.296 | K541: 2769.963 | L541: 36806.046 | M541: 8545.1306 | N541: 52860.23 | O541: 11256.446 | P541: 12773.967 | Q541: 9307.2569 | R541: 228962.12 | S541: 4740.878 | T541: 6138.2228 | U541: 3345.4794 | V541: 373.65136 | W541: 642.17083 | X541: 355.57897 | Y541: 4059.1604 | Z541: 3558.6259 | AA541: 4415.2526 | AB541: 3992.2928 | AC541: 1381.4073 | AD541: 33002.72 | AE541: 807523.26 | AF541: 55630.193 | AG541: 45724.828 | AH541: 0 | AI541: 9855.8203 | AJ541: 696312.42
B542: 1601 | C542: INTERESES por cobrar de operaciones interbancarias | D542: 0 | E542: 0 | F542: 0.07539 | G542: 0 | H542: 0.07539 | I542: 0 | J542: 0 | K542: 0 | L542: 0 | M542: 0 | N542: 0 | O542: 0 | P542: 0 | Q542: 0 | R542: 0 | S542: 0 | T542: 0 | U542: 0 | V542: 0 | W542: 0 | X542: 0 | Y542: 0 | Z542: 0 | AA542: 0 | AB542: 0 | AC542: 0 | AD542: 0 | AE542: 0.07539 | AF542: 0 | AG542: 0 | AH542: 0 | AI542: 0 | AJ542: 0.07539
B543: 160105 | C543: Interbancarios vendidos | D543: 0 | E543: 0 | F543: 0.07539 | G543: 0 | H543: 0.07539 | I543: 0 | J543: 0 | K543: 0 | L543: 0 | M543: 0 | N543: 0 | O543: 0 | P543: 0 | Q543: 0 | R543: 0 | S543: 0 | T543: 0 | U543: 0 | V543: 0 | W543: 0 | X543: 0 | Y543: 0 | Z543: 0 | AA543: 0 | AB543: 0 | AC543: 0 | AD543: 0 | AE543: 0.07539 | AF543: 0 | AG543: 0 | AH543: 0 | AI543: 0 | AJ543: 0.07539
B544: 160110 | C544: Operaciones de reporto con instituciones financieras | D544: 0 | E544: 0 | F544: 0 | G544: 0 | H544: 0 | I544: 0 | J544: 0 | K544: 0 | L544: 0 | M544: 0 | N544: 0 | O544: 0 | P544: 0 | Q544: 0 | R544: 0 | S544: 0 | T544: 0 | U544: 0 | V544: 0 | W544: 0 | X544: 0 | Y544: 0 | Z544: 0 | AA544: 0 | AB544: 0 | AC544: 0 | AD544: 0 | AE544: 0 | AF544: 0 | AG544: 0 | AH544: 0 | AI544: 0 | AJ544: 0
B545: 1602 | C545: INTERESES por cobrar inversiones | D545: 3242.0965 | E545: 2504.6303 | F545: 6527.1177 | G545: 845.16728 | H545: 13119.012 | I545: 1802.8088 | J545: 1517.7886 | K545: 714.571 | L545: 483.63615 | M545: 681.56836 | N545: 5958.3453 | O545: 1467.6278 | P545: 516.77804 | Q545: 452.32599 | R545: 13595.45 | S545: 112.27451 | T545: 194.39953 | U545: 58.3707 | V545: 13.71684 | W545: 87.6091 | X545: 2.44391 | Y545: 11.68891 | Z545: 18.7001 | AA545: 152.11814 | AB545: 92.57915 | AC545: 8.19973 | AD545: 752.10062 | AE545: 27466.562 | AF545: 6672.9163 | AG545: 1178.9214 | AH545: 0 | AI545: 172.00678 | AJ545: 19442.718
B546: 160205 | C546: A valor razonable con cambios en el estado de resultados | D546: 0 | E546: 0 | F546: 0 | G546: 0 | H546: 0 | I546: 196.50137 | J546: 0 | K546: 73 | L546: 0 | M546: 0 | N546: 13.6009 | O546: 0.55555 | P546: 0 | Q546: 0 | R546: 283.65782 | S546: 0 | T546: 0 | U546: 0 | V546: 0 | W546: 0 | X546: 0 | Y546: 0 | Z546: 0 | AA546: 0 | AB546: 0 | AC546: 0 | AD546: 0 | AE546: 283.65782 | AF546: 86.6009 | AG546: 0 | AH546: 0 | AI546: 0 | AJ546: 197.05692
B547: 160210 | C547: Disponibles para la venta | D547: 3240.2031 | E547: 2503.6017 | F547: 5961.6316 | G547: 803.46765 | H547: 12508.904 | I547: 1387.3037 | J547: 1505.1906 | K547: 641.571 | L547: 483.63615 | M547: 681.34554 | N547: 5944.7307 | O547: 1461.3423 | P547: 308.64179 | Q547: 452.32599 | R547: 12866.088 | S547: 112.27451 | T547: 186.76977 | U547: 0 | V547: 13.71684 | W547: 87.6091 | X547: 2.26382 | Y547: 11.68891 | Z547: 18.7001 | AA547: 152.11814 | AB547: 37.71931 | AC547: 3.14417 | AD547: 626.00467 | AE547: 26000.997 | AF547: 6586.3017 | AG547: 1178.6985 | AH547: 0 | AI547: 166.95122 | AJ547: 18069.045
B548: 160215 | C548: Mantenidas hasta el vencimiento | D548: 1.89339 | E548: 0 | F548: 0 | G548: 24.83816 | H548: 26.73155 | I548: 0 | J548: 2.57632 | K548: 0 | L548: 0 | M548: 0 | N548: 0 | O548: 0 | P548: 204.46201 | Q548: 0 | R548: 207.03833 | S548: 0 | T548: 5.4398 | U548: 58.3707 | V548: 0 | W548: 0 | X548: 0 | Y548: 0 | Z548: 0 | AA548: 0 | AB548: 54.85984 | AC548: 5.05556 | AD548: 123.7259 | AE548: 357.49578 | AF548: 0 | AG548: 0 | AH548: 0 | AI548: 5.05556 | AJ548: 352.44022
B549: 160220 | C549: De disponibilidad restringida | D549: 0 | E549: 1.02858 | F549: 565.4861 | G549: 16.86147 | H549: 583.37615 | I549: 219.00376 | J549: 10.02173 | K549: 0 | L549: 0 | M549: 0.22282 | N549: 0.01367 | O549: 5.72985 | P549: 3.67424 | Q549: 0 | R549: 238.66607 | S549: 0 | T549: 2.18996 | U549: 0 | V549: 0 | W549: 0 | X549: 0.18009 | Y549: 0 | Z549: 0 | AA549: 0 | AB549: 0 | AC549: 0 | AD549: 2.37005 | AE549: 824.41227 | AF549: 0.01367 | AG549: 0.22282 | AH549: 0 | AI549: 0 | AJ549: 824.17578
... B750: 4 | C750: GASTOS | D750: 361553.83 | E750: 477021.33 | F750: 882943.83 | G750: 330620.96 | H750: 2052139.9 | I750: 136884.88 | J750: 185512.59 | K750: 23401.499 | L750: 277725.13 | M750: 68026.677 | N750: 184167 | O750: 36828.923 | P750: 48807.033 | Q750: 91457.742 | R750: 1052811.5 | S750: 32948.932 | T750: 14446.778 | U750: 3589.4558 | V750: 2769.5332 | W750: 7349.2586 | X750: 3312.1349 | Y750: 17028.809 | Z750: 4283.9411 | AA750: 13550.737 | AB750: 22859.316 | AC750: 11402.493 | AD750: 133541.39 | AE750: 3238492.8 | AF750: 207568.5 | AG750: 348521.34 | AH750: 0 | AI750: 41982.039 | AJ750: 2640420.9
B752: +1+4 | C752: TOTAL ACTIVO Y GASTOS | D752: 6388862.8 | E752: 7298757.8 | F752: 13528625 | G752: 5867035.7 | H752: 33083281 | I752: 2366415.2 | J752: 4237426.5 | K752: 655712.2 | L752: 2499053.8 | M752: 1024230 | N752: 4280816.3 | O752: 642515.54 | P752: 959697.65 | Q752: 863217.1 | R752: 17529084 | S752: 583740.26 | T752: 270376.48 | U752: 63161.1 | V752: 40269.509 | W752: 199917.16 | X752: 34828.179 | Y752: 108193.62 | Z752: 36284.662 | AA752: 128092.59 | AB752: 236961.65 | AC752: 98327.905 | AD752: 1800153.1 | AE752: 52412519 | AF752: 4936528.5 | AG752: 3563553.3 | AH752: 0 | AI752: 334614.11 | AJ752: 43577823
C754: PASIVO
B755: 21 | C755: OBLIGACIONES CON EL PÚBLICO | D755: 4721386.6 | E755: 5300777.7 | F755: 10169669 | G755: 4471422.8 | H755: 24663257 | I755: 1971925.2 | J755: 3285806.6 | K755: 503234.89 | L755: 1131205.3 | M755: 793641.46 | N755: 3443537.3 | O755: 520848.42 | P755: 784627.77 | Q755: 378108.12 | R755: 12812935 | S755: 295132.14 | T755: 208616.87 | U755: 45679.439 | V755: 24668.123 | W755: 157369.72 | X755: 23734.246 | Y755: 67718.414 | Z755: 18109.232 | AA755: 39426.216 | AB755: 156391.03 | AC755: 13928.757 | AD755: 1050774.2 | AE755: 38526966 | AF755: 3946772.2 | AG755: 1949514.9 | AH755: 0 | AI755: 121073.39 | AJ755: 32509605
B756: 2101 | C756: Depósitos a la vista | D756: 2800216.2 | E756: 2737906.9 | F756: 7229246.3 | G756: 2800488.5 | H756: 15567858 | I756: 962397.48 | J756: 2106113.1 | K756: 502615.09 | L756: 11267.245 | M756: 339829.33 | N756: 2062830.8 | O756: 293624.39 | P756: 427928.2 | Q756: 74655.045 | R756: 6781260.6 | S756: 174155.49 | T756: 64101.215 | U756: 34331.48 | V756: 8631.8647 | W756: 114075.22 | X756: 2887.002 | Y756: 6730.7101 | Z756: 10123.197 | AA756: 5925.9983 | AB756: 62588.313 | AC756: 4400.2502 | AD756: 487950.74 | AE756: 22837069 | AF756: 2565445.9 | AG756: 359728.44 | AH756: 0 | AI756: 17056.959 | AJ756: 19894838
B757: 210105 | C757: Depósitos monetarios que generan INTERESES | D757: 641105.87 | E757: 569516.7 | F757: 520409.92 | G757: 7691.4857 | H757: 1738724 | I757: 60197.391 | J757: 418511.88 | K757: 32985.351 | L757: 0 | M757: 47358.709 | N757: 1024753.4 | O757: 0 | P757: 104.94928 | Q757: 8970.6 | R757: 1592882.3 | S757: 54887.659 | T757: 14091.834 | U757: 4959.4053 | V757: 0 | W757: 0 | X757: 1033.0742 | Y757: 0 | Z757: 0 | AA757: 0 | AB757: 4566.8288 | AC757: 0 | AD757: 79538.801 | AE757: 3411145 | AF757: 1057738.7 | AG757: 47358.709 | AH757: 0 | AI757: 0 | AJ757: 2306047.6
B758: 210110 | C758: Depósitos monetarios que no generan INTERESES | D758: 833556.61 | E758: 930340.52 | F758: 2627205 | G758: 1478628 | H758: 5869730.1 | I758: 182272.45 | J758: 755459.33 | K758: 462429.99 | L758: 0 | M758: 37240.326 | N758: 148868.92 | O758: 74280.236 | P758: 140908.8 | Q758: 37.39988 | R758: 1801497.4 | S758: 0 | T758: 14555.268 | U758: 7302.714 | V758: 3345.1034 | W758: 173.77805 | X758: 36.57367 | Y758: 0 | Z758: 3009.9217 | AA758: 0 | AB758: 0 | AC758: 0 | AD758: 28423.359 | AE758: 7699650.9 | AF758: 611298.91 | AG758: 40585.429 | AH758: 0 | AI758: 0 | AJ758: 7047766.6
B759: 210115 | C759: Depósitos monetarios de instituciones financieras | D759: 130179.39 | E759: 11296.971 | F759: 188083.34 | G759: 77351.913 | H759: 406911.62 | I759: 75074.06 | J759: 211719.93 | K759: 1210.099 | L759: 0 | M759: 4538.619 | N759: 186057.5 | O759: 2017.4073 | P759: 25650.298 | Q759: 15.29311 | R759: 506283.21 | S759: 231.56437 | T759: 608.71536 | U759: 50.93432 | V759: 0 | W759: 0 | X759: 0 | Y759: 0 | Z759: 0 | AA759: 0 | AB759: 969.63725 | AC759: 0 | AD759: 1860.8513 | AE759: 915055.68 | AF759: 187267.6 | AG759: 4538.619 | AH759: 0 | AI759: 0 | AJ759: 723249.46
B760: 210120 | C760: EJECUCIÓN PRESUPUESTARIA | D760: 1676.1749 | E760: 5e-05 | F760: 0 | G760: 0 | H760: 1676.175 | I760: 0 | J760: 4396.9582 | K760: 0 | L760: 0 | M760: 0 | N760: 0 | O760: 231.68756 | P760: 351.15298 | Q760: 0 | R760: 4979.7987 | S760: 0 | T760: 0 | U760: 0 | V760: 0 | W760: 0 | X760: 0 | Y760: 0 | Z760: 0 | AA760: 0 | AB760: 0 | AC760: 0 | AD760: 0 | AE760: 6655.9737 | AF760: 0 | AG760: 0 | AH760: 0 | AI760: 0 | AJ760: 6655.9737
B761: 210125 | C761: Depósitos de otras instituciones para encaje | D761: 0 | E761: 0 | F761: 0 | G761: 0 | H761: 0 | I761: 0 | J761: 0 | K761: 0 | L761: 0 | M761: 0 | N761: 0 | O761: 0 | P761: 0 | Q761: 0 | R761: 0 | S761: 0 | T761: 0 | U761: 0 | V761: 0 | W761: 0 | X761: 0 | Y761: 0 | Z761: 0 | AA761: 0 | AB761: 0 | AC761: 0 | AD761: 0 | AE761: 0 | AF761: 0 | AG761: 0 | AH761: 0 | AI761: 0 | AJ761: 0
B762: 210130 | C762: Cheques certificados | D762: 6708.7225 | E762: 9932.9741 | F762: 26518.716 | G762: 9290.7994 | H762: 52451.212 | I762: 1759.924 | J762: 5807.7812 | K762: 2692.411 | L762: 0 | M762: 316.79743 | N762: 4132.8931 | O762: 360.14636 | P762: 1428.3948 | Q762: 18.16093 | R762: 16516.509 | S762: 210.08187 | T762: 67.734 | U762: 332.3411 | V762: 191.56456 | W762: 3 | X762: 60.74878 | Y762: 0 | Z762: 17.37702 | AA762: 0 | AB762: 20.4772 | AC762: 0 | AD762: 903.32453 | AE762: 69871.045 | AF762: 6825.3041 | AG762: 508.36199 | AH762: 0 | AI762: 0 | AJ762: 62537.379
B763: 210131 | C763: Cheques de emergencia | D763: 5880.661 | E763: 0 | F763: 7245.5688 | G763: 7358.2198 | H763: 20484.45 | I763: 1267.3647 | J763: 6079.6832 | K763: 0.452 | L763: 0 | M763: 1540.2598 | N763: 6988.2913 | O763: 9.33289 | P763: 417.76805 | Q763: 275.75143 | R763: 16578.903 | S763: 136.60539 | T763: 0 | U763: 0 | V763: 382.68639 | W763: 115.74753 | X763: 0 | Y763: 0 | Z763: 21.5671 | AA763: 0 | AB763: 0 | AC763: 0 | AD763: 656.60641 | AE763: 37719.959 | AF763: 6988.7433 | AG763: 1922.9462 | AH763: 0 | AI763: 0 | AJ763: 28808.27
B764: 210135 | C764: Depósitos de ahorro | D764: 1135563.4 | E764: 1156813.8 | F764: 3767437.6 | G764: 1166252.1 | H764: 7226066.9 | I764: 633838.75 | J764: 651423.46 | K764: 0 | L764: 0 | M764: 246096.87 | N764: 670210.23 | O764: 215035.46 | P764: 255765.39 | Q764: 62245.018 | R764: 2734615.2 | S764: 117464.67 | T764: 33945.524 | U764: 21302.194 | V764: 4560.5433 | W764: 113694.36 | X764: 1671.0719 | Y764: 6180.6586 | Z764: 6524.8399 | AA764: 5925.9983 | AB764: 56685.221 | AC764: 4393.1702 | AD764: 372348.25 | AE764: 10333030 | AF764: 670210.23 | AG764: 250657.41 | AH764: 0 | AI764: 16499.827 | AJ764: 9395662.8
B765: 210140 | C765: Otros depósitos | D765: 86.16903 | E765: 35356.384 | F765: 19108.388 | G765: 20130.36 | H765: 74681.301 | I765: 29.8601 | J765: 18643.125 | K765: 0 | L765: 3985.2358 | M765: 1645.8432 | N765: 908.48232 | O765: 864.51259 | P765: 345.17521 | Q765: 2556.4765 | R765: 28978.711 | S765: 52.56228 | T765: 327.10755 | U765: 2.71882 | V765: 139.81264 | W765: 0 | X765: 85.53348 | Y765: 545.39884 | Z765: 535.92525 | AA765: 0 | AB765: 267.50972 | AC765: 7.08 | AD765: 1963.6486 | AE765: 105623.66 | AF765: 908.48232 | AG765: 5770.8916 | AH765: 0 | AI765: 552.47884 | AJ765: 98391.807
B766: 210145 | C766: Fondos de tarjetahabientes | D766: 7337.4645 | E766: 9938.9064 | F766: 4974.1546 | G766: 5409.8289 | H766: 27660.354 | I766: 1567.8628 | J766: 1257.2061 | K766: 0 | L766: 7282.0092 | M766: 331.06758 | N766: 1370.2173 | O766: 72.64873 | P766: 146.5628 | Q766: 486.11229 | R766: 12513.687 | S766: 0 | T766: 145.2072 | U766: 0 | V766: 0 | W766: 0 | X766: 0 | Y766: 0 | Z766: 0 | AA766: 0 | AB766: 0 | AC766: 0 | AD766: 145.2072 | AE766: 40319.248 | AF766: 1370.2173 | AG766: 7613.0768 | AH766: 0 | AI766: 0 | AJ766: 31335.954
... B952: 2 | C952: TOTAL PASIVOS | D952: 5458923.5 | E952: 6019469.3 | F952: 11331689 | G952: 5064030.1 | H952: 27874112 | I952: 2023581.7 | J952: 3676872.8 | K952: 548487.04 | L952: 1756884.5 | M952: 868380.12 | N952: 3690621.2 | O952: 543381.47 | P952: 844687.76 | Q952: 618617.82 | R952: 14571514 | S952: 493818.54 | T952: 231908.27 | U952: 46838.004 | V952: 26008.175 | W952: 161346.21 | X952: 25654.444 | Y952: 82709.879 | Z952: 20503.697 | AA952: 94214.256 | AB952: 188871.75 | AC952: 68626.976 | AD952: 1440500.2 | AE952: 43886127 | AF952: 4239108.2 | AG952: 2651272.8 | AH952: 0 | AI952: 245551.11 | AJ952: 36750195
C954: PATRIMONIO
B955: 31 | C955: CAPITAL SOCIAL | D955: 449900 | E955: 582479.74 | F955: 919241.6 | G955: 394760 | H955: 2346381.3 | I955: 146000 | J955: 300000 | K955: 68559.042 | L955: 220000 | M955: 70334.805 | N955: 310159.21 | O955: 46700 | P955: 56300 | Q955: 95457.728 | R955: 1313510.8 | S955: 51748 | T955: 21083.923 | U955: 11000 | V955: 11090.785 | W955: 21738.121 | X955: 14000 | Y955: 17513.178 | Z955: 11271.945 | AA955: 20968.6 | AB955: 18122.5 | AC955: 16701.1 | AD955: 215238.15 | AE955: 3875130.3 | AF955: 378718.25 | AG955: 301425.59 | AH955: 0 | AI955: 55182.878 | AJ955: 3139803.6
B956: 3101 | C956: Capital pagado | D956: 449900 | E956: 582479.74 | F956: 919241.6 | G956: 394760 | H956: 2346381.3 | I956: 146000 | J956: 300000 | K956: 68559.042 | L956: 220000 | M956: 70334.805 | N956: 310159.21 | O956: 46700 | P956: 56300 | Q956: 100997.65 | R956: 1319050.7 | S956: 51748 | T956: 21083.923 | U956: 11000 | V956: 11090.785 | W956: 21738.121 | X956: 14000 | Y956: 17513.178 | Z956: 11271.945 | AA956: 20968.6 | AB956: 18122.5 | AC956: 16701.1 | AD956: 215238.15 | AE956: 3880670.2 | AF956: 378718.25 | AG956: 301425.59 | AH956: 0 | AI956: 55182.878 | AJ956: 3145343.5
B957: 3102 | C957: (Acciones en tesorería) | D957: 0 | E957: 0 | F957: 0 | G957: 0 | H957: 0 | I957: 0 | J957: 0 | K957: 0 | L957: 0 | M957: 0 | N957: 0 | O957: 0 | P957: 0 | Q957: -5539.922 | R957: -5539.922 | S957: 0 | T957: 0 | U957: 0 | V957: 0 | W957: 0 | X957: 0 | Y957: 0 | Z957: 0 | AA957: 0 | AB957: 0 | AC957: 0 | AD957: 0 | AE957: -5539.922 | AF957: 0 | AG957: 0 | AH957: 0 | AI957: 0 | AJ957: -5539.922
B958: 3103 | C958: Aportes de socios | D958: 0 | E958: 0 | F958: 0 | G958: 0 | H958: 0 | I958: 0 | J958: 0 | K958: 0 | L958: 0 | M958: 0 | N958: 0 | O958: 0 | P958: 0 | Q958: 0 | R958: 0 | S958: 0 | T958: 0 | U958: 0 | V958: 0 | W958: 0 | X958: 0 | Y958: 0 | Z958: 0 | AA958: 0 | AB958: 0 | AC958: 0 | AD958: 0 | AE958: 0 | AF958: 0 | AG958: 0 | AH958: 0 | AI958: 0 | AJ958: 0
B959: 32 | C959: PRIMA O DESCUENTO EN COLOCACIÓN DE ACCIONES Y CERTIFICADOS | D959: 0 | E959: 0 | F959: 0 | G959: 1104.7742 | H959: 1104.7742 | I959: 0 | J959: 0 | K959: 0 | L959: 0 | M959: 0 | N959: 0 | O959: 0 | P959: 0 | Q959: 1107.9844 | R959: 1107.9844 | S959: 0 | T959: 0 | U959: 0 | V959: 0 | W959: 0 | X959: 0 | Y959: 0 | Z959: 0 | AA959: 0 | AB959: 0 | AC959: 0 | AD959: 0 | AE959: 2212.7586 | AF959: 0 | AG959: 0 | AH959: 0 | AI959: 0 | AJ959: 2212.7586
B960: 3201 | C960: Prima EN COLOCACIÓN de acciones y certificados de aportación | D960: 0 | E960: 0 | F960: 0 | G960: 1104.7742 | H960: 1104.7742 | I960: 0 | J960: 0 | K960: 0 | L960: 0 | M960: 0 | N960: 0 | O960: 0 | P960: 0 | Q960: 1107.9844 | R960: 1107.9844 | S960: 0 | T960: 0 | U960: 0 | V960: 0 | W960: 0 | X960: 0 | Y960: 0 | Z960: 0 | AA960: 0 | AB960: 0 | AC960: 0 | AD960: 0 | AE960: 2212.7586 | AF960: 0 | AG960: 0 | AH960: 0 | AI960: 0 | AJ960: 2212.7586
B961: 3202 | C961: (Descuento en colocación de acciones) | D961: 0 | E961: 0 | F961: 0 | G961: 0 | H961: 0 | I961: 0 | J961: 0 | K961: 0 | L961: 0 | M961: 0 | N961: 0 | O961: 0 | P961: 0 | Q961: 0 | R961: 0 | S961: 0 | T961: 0 | U961: 0 | V961: 0 | W961: 0 | X961: 0 | Y961: 0 | Z961: 0 | AA961: 0 | AB961: 0 | AC961: 0 | AD961: 0 | AE961: 0 | AF961: 0 | AG961: 0 | AH961: 0 | AI961: 0 | AJ961: 0
B962: 33 | C962: RESERVAS | D962: 72784.289 | E962: 148771.15 | F962: 213197.37 | G962: 58100.996 | H962: 492853.8 | I962: 33863.243 | J962: 47910.101 | K962: 11670.269 | L962: 198200.46 | M962: 10224.347 | N962: 50875.2 | O962: 9425.7692 | P962: 4597.8224 | Q962: 19628.615 | R962: 386395.83 | S962: 5842.2717 | T962: 1648.5866 | U962: 1475.4078 | V962: 449.26413 | W962: 7585.9768 | X962: 0 | Y962: 0.02658 | Z962: 102.71679 | AA962: 1082.1644 | AB962: 2933.706 | AC962: 849.16793 | AD962: 21969.289 | AE962: 901218.92 | AF962: 62545.469 | AG962: 208874.07 | AH962: 0 | AI962: 1931.3589 | AJ962: 627868.02
B963: 3301 | C963: Legales | D963: 71552.933 | E963: 148770.32 | F963: 134879.44 | G963: 58100.996 | H963: 413303.69 | I963: 16983.512 | J963: 44919.032 | K963: 11670.269 | L963: 63398.476 | M963: 10224.347 | N963: 50875.2 | O963: 7876.5939 | P963: 4595.0251 | Q963: 17323.912 | R963: 227866.37 | S963: 5626.1192 | T963: 1464.4356 | U963: 962.70059 | V963: 403.79621 | W963: 6550.009 | X963: 0 | Y963: 0.02658 | Z963: 102.71679 | AA963: 1082.1107 | AB963: 2886.7856 | AC963: 848.57539 | AD963: 19927.276 | AE963: 661097.33 | AF963: 62545.469 | AG963: 74026.619 | AH963: 0 | AI963: 1930.7126 | AJ963: 522594.53
B964: 3302 | C964: Generales | D964: 0 | E964: 0 | F964: 0 | G964: 0 | H964: 0 | I964: 0 | J964: 0 | K964: 0 | L964: 0 | M964: 0 | N964: 0 | O964: 0 | P964: 0 | Q964: 0 | R964: 0 | S964: 0 | T964: 0 | U964: 0 | V964: 0 | W964: 0 | X964: 0 | Y964: 0 | Z964: 0 | AA964: 0 | AB964: 0 | AC964: 0 | AD964: 0 | AE964: 0 | AF964: 0 | AG964: 0 | AH964: 0 | AI964: 0 | AJ964: 0
B965: 3303 | C965: Especiales | D965: 4.54842 | E965: 0.83412 | F965: 47431.699 | G965: 0 | H965: 47437.081 | I965: 12881.364 | J965: 32.16035 | K965: 0 | L965: 131839.69 | M965: 0 | N965: 0 | O965: 6.40264 | P965: 0 | Q965: 0.00068 | R965: 144759.62 | S965: 216.15253 | T965: 184.151 | U965: 221.95578 | V965: 45.46792 | W965: 64.34845 | X965: 0 | Y965: 0 | Z965: 0 | AA965: 0.05371 | AB965: 19.26319 | AC965: 0.59254 | AD965: 751.98512 | AE965: 192948.68 | AF965: 0 | AG965: 131885.16 | AH965: 0 | AI965: 0.64625 | AJ965: 61062.88
B966: 330305 | C966: A disposición de la Junta General de Accionistas | D966: 0 | E966: 0 | F966: 0 | G966: 0 | H966: 0 | I966: 0 | J966: 0 | K966: 0 | L966: 59001.599 | M966: 0 | N966: 0 | O966: 5.9899 | P966: 0 | Q966: 0 | R966: 59007.589 | S966: 0 | T966: 0 | U966: 0 | V966: 0 | W966: 0 | X966: 0 | Y966: 0 | Z966: 0 | AA966: 0 | AB966: 0 | AC966: 0 | AD966: 0 | AE966: 59007.589 | AF966: 0 | AG966: 59001.599 | AH966: 0 | AI966: 0 | AJ966: 5.9899
... B999: 3 | C999: TOTAL PATRIMONIO | D999: 527415.01 | E999: 790452.78 | F999: 1251227.8 | G999: 448355.63 | H999: 3017451.2 | I999: 199316.45 | J999: 351009.45 | K999: 80646.063 | L999: 440643.39 | M999: 81172.327 | N999: 379732.11 | O999: 59416.635 | P999: 63976.736 | Q999: 150918.15 | R999: 1806831.3 | S999: 57632.713 | T999: 23991.783 | U999: 12689.092 | V999: 11250.26 | W999: 30511.565 | X999: 7194.829 | Y999: 14571.762 | Z999: 11403.717 | AA999: 19906.124 | AB999: 23928.884 | AC999: 17568.579 | AD999: 230649.31 | AE999: 5054931.8 | AF999: 460378.17 | AG999: 533065.98 | AH999: 0 | AI999: 52046.465 | AJ999: 4009441.2
B1001: +2+3 | C1001: TOTAL PASIVO Y PATRIMONIO | D1001: 5986338.5 | E1001: 6809922.1 | F1001: 12582917 | G1001: 5512385.7 | H1001: 30891563 | I1001: 2222898.1 | J1001: 4027882.3 | K1001: 629133.11 | L1001: 2197527.9 | M1001: 949552.45 | N1001: 4070353.3 | O1001: 602798.1 | P1001: 908664.49 | Q1001: 769535.97 | R1001: 16378346 | S1001: 551451.26 | T1001: 255900.05 | U1001: 59527.096 | V1001: 37258.435 | W1001: 191857.78 | X1001: 32849.273 | Y1001: 97281.641 | Z1001: 31907.414 | AA1001: 114120.38 | AB1001: 212800.63 | AC1001: 86195.555 | AD1001: 1671149.5 | AE1001: 48941059 | AF1001: 4699486.4 | AG1001: 3184338.8 | AH1001: 0 | AI1001: 297597.58 | AJ1001: 40759636
B1003: 5 | C1003: INGRESOS | D1003: 402524.28 | E1003: 488835.76 | F1003: 945707.78 | G1003: 354650 | H1003: 2191717.8 | I1003: 143517.05 | J1003: 209544.25 | K1003: 26579.097 | L1003: 301525.91 | M1003: 74677.503 | N1003: 210463 | O1003: 39717.433 | P1003: 51033.153 | Q1003: 93681.138 | R1003: 1150738.5 | S1003: 32289.009 | T1003: 14476.433 | U1003: 3634.0048 | V1003: 3011.0741 | W1003: 8059.38 | X1003: 1978.9057 | Y1003: 10911.976 | Z1003: 4377.2483 | AA1003: 13972.208 | AB1003: 24161.022 | AC1003: 12132.35 | AD1003: 129003.61 | AE1003: 3471460 | AF1003: 237042.1 | AG1003: 379214.49 | AH1003: 0 | AI1003: 37016.533 | AJ1003: 2818186.9
B1005: +2+3+5 | C1005: TOTAL PASIVO, PATRIMONIO E INGRESOS | D1005: 6388862.8 | E1005: 7298757.8 | F1005: 13528625 | G1005: 5867035.7 | H1005: 33083281 | I1005: 2366415.2 | J1005: 4237426.5 | K1005: 655712.2 | L1005: 2499053.8 | M1005: 1024230 | N1005: 4280816.3 | O1005: 642515.54 | P1005: 959697.65 | Q1005: 863217.1 | R1005: 17529084 | S1005: 583740.26 | T1005: 270376.48 | U1005: 63161.1 | V1005: 40269.509 | W1005: 199917.16 | X1005: 34828.179 | Y1005: 108193.62 | Z1005: 36284.662 | AA1005: 128092.59 | AB1005: 236961.65 | AC1005: 98327.905 | AD1005: 1800153.1 | AE1005: 52412519 | AF1005: 4936528.5 | AG1005: 3563553.3 | AH1005: 0 | AI1005: 334614.11 | AJ1005: 43577823
B1007: 0 | C1007: CUADRE | D1007: 0 | E1007: 0 | F1007: 0 | G1007: 0 | H1007: 0 | I1007: 0 | J1007: 0 | K1007: 0 | L1007: 0 | M1007: 0 | N1007: 0 | O1007: 0 | P1007: 0 | Q1007: 0 | R1007: 0 | S1007: 0 | T1007: 0 | U1007: 0 | V1007: 0 | W1007: 0 | X1007: 0 | Y1007: 0 | Z1007: 0 | AA1007: 0 | AB1007: 0 | AC1007: 0 | AD1007: 0 | AE1007: 0
B1009: 6 | C1009: CUENTAS CONTINGENTES | D1009: 1700584.9 | E1009: 1961032.2 | F1009: 4080019.3 | G1009: 1387822.1 | H1009: 9129458.5 | I1009: 352453.7 | J1009: 969404.24 | K1009: 145305.58 | L1009: 3008993.9 | M1009: 135526.81 | N1009: 837790.4 | O1009: 43121.598 | P1009: 60789.966 | Q1009: 372690.22 | R1009: 5926076.4 | S1009: 6155.1417 | T1009: 22502.708 | U1009: 2221.9089 | V1009: 0 | W1009: 0 | X1009: 55.18557 | Y1009: 0 | Z1009: 0 | AA1009: 0 | AB1009: 1946.0487 | AC1009: 0 | AD1009: 32880.993 | AE1009: 15088416 | AF1009: 983095.98 | AG1009: 3144520.7 | AH1009: 0 | AI1009: 0 | AJ1009: 10960799
B1010: 61 | C1010: DEUDORAS | D1010: 0 | E1010: 0 | F1010: 395247.02 | G1010: 2518.5276 | H1010: 397765.55 | I1010: 0 | J1010: 0 | K1010: 2904.476 | L1010: 0 | M1010: 0 | N1010: 19329.686 | O1010: 0 | P1010: 0 | Q1010: 0 | R1010: 22234.162 | S1010: 0 | T1010: 0 | U1010: 0 | V1010: 0 | W1010: 0 | X1010: 0 | Y1010: 0 | Z1010: 0 | AA1010: 0 | AB1010: 0 | AC1010: 0 | AD1010: 0 | AE1010: 419999.71 | AF1010: 22234.162 | AG1010: 0 | AH1010: 0 | AI1010: 0 | AJ1010: 397765.55
B1011: 6101 | C1011: Compras a futuro de moneda extranjera | D1011: 0 | E1011: 0 | F1011: 384909.46 | G1011: 2284.7094 | H1011: 387194.17 | I1011: 0 | J1011: 0 | K1011: 2904.476 | L1011: 0 | M1011: 0 | N1011: 19329.686 | O1011: 0 | P1011: 0 | Q1011: 0 | R1011: 22234.162 | S1011: 0 | T1011: 0 | U1011: 0 | V1011: 0 | W1011: 0 | X1011: 0 | Y1011: 0 | Z1011: 0 | AA1011: 0 | AB1011: 0 | AC1011: 0 | AD1011: 0 | AE1011: 409428.33 | AF1011: 22234.162 | AG1011: 0 | AH1011: 0 | AI1011: 0 | AJ1011: 387194.17
B1012: 610105 | C1012: A término no negociables | D1012: 0 | E1012: 0 | F1012: 267149.46 | G1012: 2284.7094 | H1012: 269434.17 | I1012: 0 | J1012: 0 | K1012: 2904.476 | L1012: 0 | M1012: 0 | N1012: 19329.686 | O1012: 0 | P1012: 0 | Q1012: 0 | R1012: 22234.162 | S1012: 0 | T1012: 0 | U1012: 0 | V1012: 0 | W1012: 0 | X1012: 0 | Y1012: 0 | Z1012: 0 | AA1012: 0 | AB1012: 0 | AC1012: 0 | AD1012: 0 | AE1012: 291668.33 | AF1012: 22234.162 | AG1012: 0 | AH1012: 0 | AI1012: 0 | AJ1012: 269434.17
B1013: 610110 | C1013: A término negociables | D1013: 0 | E1013: 0 | F1013: 0 | G1013: 0 | H1013: 0 | I1013: 0 | J1013: 0 | K1013: 0 | L1013: 0 | M1013: 0 | N1013: 0 | O1013: 0 | P1013: 0 | Q1013: 0 | R1013: 0 | S1013: 0 | T1013: 0 | U1013: 0 | V1013: 0 | W1013: 0 | X1013: 0 | Y1013: 0 | Z1013: 0 | AA1013: 0 | AB1013: 0 | AC1013: 0 | AD1013: 0 | AE1013: 0 | AF1013: 0 | AG1013: 0 | AH1013: 0 | AI1013: 0 | AJ1013: 0
B1014: 610115 | C1014: Con pacto de retroventa | D1014: 0 | E1014: 0 | F1014: 0 | G1014: 0 | H1014: 0 | I1014: 0 | J1014: 0 | K1014: 0 | L1014: 0 | M1014: 0 | N1014: 0 | O1014: 0 | P1014: 0 | Q1014: 0 | R1014: 0 | S1014: 0 | T1014: 0 | U1014: 0 | V1014: 0 | W1014: 0 | X1014: 0 | Y1014: 0 | Z1014: 0 | AA1014: 0 | AB1014: 0 | AC1014: 0 | AD1014: 0 | AE1014: 0 | AF1014: 0 | AG1014: 0 | AH1014: 0 | AI1014: 0 | AJ1014: 0
B1015: 610120 | C1015: Opción de compra – venta | D1015: 0 | E1015: 0 | F1015: 117760 | G1015: 0 | H1015: 117760 | I1015: 0 | J1015: 0 | K1015: 0 | L1015: 0 | M1015: 0 | N1015: 0 | O1015: 0 | P1015: 0 | Q1015: 0 | R1015: 0 | S1015: 0 | T1015: 0 | U1015: 0 | V1015: 0 | W1015: 0 | X1015: 0 | Y1015: 0 | Z1015: 0 | AA1015: 0 | AB1015: 0 | AC1015: 0 | AD1015: 0 | AE1015: 117760 | AF1015: 0 | AG1015: 0 | AH1015: 0 | AI1015: 0 | AJ1015: 117760
B1016: 6102 | C1016: Ventas a futuro en moneda local | D1016: 0 | E1016: 0 | F1016: 0 | G1016: 233.8182 | H1016: 233.8182 | I1016: 0 | J1016: 0 | K1016: 0 | L1016: 0 | M1016: 0 | N1016: 0 | O1016: 0 | P1016: 0 | Q1016: 0 | R1016: 0 | S1016: 0 | T1016: 0 | U1016: 0 | V1016: 0 | W1016: 0 | X1016: 0 | Y1016: 0 | Z1016: 0 | AA1016: 0 | AB1016: 0 | AC1016: 0 | AD1016: 0 | AE1016: 233.8182 | AF1016: 0 | AG1016: 0 | AH1016: 0 | AI1016: 0 | AJ1016: 233.8182
...

Sheet PYG
B2: ESTADO DE PÉRDIDAS Y GANANCIAS
B3: SISTEMA DE BANCOS PRIVADOS
B4: 44439
B5: (en miles de dólares)
B6: CÓDIGO | D6: BP GUAYAQUIL | E6: BP PACIFICO | F6: BP PICHINCHA | G6: BP PRODUBANCO | I6: BP AUSTRO | J6: BP BOLIVARIANO | K6: BP CITIBANK | L6: BP DINERS | M6: BP GENERAL RUMIÑAHUI | N6: BP INTERNACIONAL | O6: BP LOJA | P6: BP MACHALA | Q6: BP SOLIDARIO | S6: BP PROCREDIT | T6: BP AMAZONAS | U6: BP COMERCIAL DE MANABI | V6: BP LITORAL | W6: BP COOPNACIONAL | X6: BP CAPITAL | Y6: BP FINCA S.A. | Z6: BP DELBANK | AA6: BP D MIRO S.A. | AB6: BP BANCO DESARROLLO DE LOS PUEBLOS S.A., CODESARROLLO | AC6: BP VISIONFUND ECUADOR S.A. | AF6: BANCA ESPECIALIZADA
A7: 1 | B7: CODIGO | C7: CUENTA | D7: BP GUAYAQUIL | E7: BP PACIFICO | F7: BP PICHINCHA | G7: BP PRODUBANCO | H7: BANCOS PRIVADOS GRANDES | I7: BP AUSTRO | J7: BP BOLIVARIANO | K7: BP CITIBANK | L7: BP DINERS | M7: BP GENERAL RUMIÑAHUI | N7: BP INTERNACIONAL | O7: BP LOJA | P7: BP MACHALA | Q7: BP SOLIDARIO | R7: BANCOS PRIVADOS MEDIANOS | S7: BP PROCREDIT | T7: BP AMAZONAS | U7: BP COMERCIAL DE MANABI | V7: BP LITORAL | W7: BP COOPNACIONAL | X7: BP CAPITAL | Y7: BP FINCA S.A. | Z7: BP DELBANK | AA7: BP D MIRO S.A. | AB7: BP BANCODESARROLLO | AC7: BP VISIONFUND ECUADOR S.A. | AD7: BANCOS PRIVADOS PEQUEÑOS | AE7: TOTAL BANCOS PRIVADOS | AF7: BANCOS PRIVADOS COMERCIALES | AG7: BANCOS PRIVADOS CONSUMO | AH7: BANCOS PRIVADOS VIVIENDA | AI7: BANCOS PRIVADOS DE MICROCRÉDITO | AJ7: BANCA MULTIPLE
A8: 2
A9: 3 | B9: 5 | C9: TOTAL INGRESOS | D9: 402524.28 | E9: 488835.76 | F9: 945707.78 | G9: 354650 | H9: 2191717.8 | I9: 143517.05 | J9: 209544.25 | K9: 26579.097 | L9: 301525.91 | M9: 74677.503 | N9: 210463 | O9: 39717.433 | P9: 51033.153 | Q9: 93681.138 | R9: 1150738.5 | S9: 32289.009 | T9: 14476.433 | U9: 3634.0048 | V9: 3011.0741 | W9: 8059.38 | X9: 1978.9057 | Y9: 10911.976 | Z9: 4377.2483 | AA9: 13972.208 | AB9: 24161.022 | AC9: 12132.35 | AD9: 129003.61 | AE9: 3471460 | AF9: 237042.1 | AG9: 379214.49 | AH9: 0 | AI9: 37016.533 | AJ9: 2818186.9
A11: 5 | B11: 51 | C11: INTERESES Y DESCUENTOS GANADOS | D11: 274029.58 | E11: 315132.99 | F11: 635423.38 | G11: 250135.3 | H11: 1474721.3 | I11: 104396.19 | J11: 159887.25 | K11: 12510.992 | L11: 149579.17 | M11: 61454.807 | N11: 166376.53 | O11: 34583.589 | P11: 44499.92 | Q11: 69622.94 | R11: 802911.39 | S11: 27043.628 | T11: 10724.565 | U11: 2991.0627 | V11: 2659.8091 | W11: 7422.6906 | X11: 1579.3235 | Y11: 8047.8449 | Z11: 1430.3599 | AA11: 11709.227 | AB11: 17379.926 | AC11: 10847.921 | AD11: 101836.36 | AE11: 2379469 | AF11: 178887.52 | AG11: 213693.79 | AH11: 0 | AI11: 30604.993 | AJ11: 1956282.7
A12: 6 | B12: 5101 | C12: Depósitos | D12: 656.52043 | E12: 33.78399 | F12: 75.86967 | G12: 1156.5777 | H12: 1922.7518 | I12: 2530.3063 | J12: 1680.6005 | K12: 157.705 | L12: 42.53233 | M12: 748.1086 | N12: 1501.7388 | O12: 121.85043 | P12: 450.05632 | Q12: 94.63167 | R12: 7327.53 | S12: 160.26238 | T12: 102.37617 | U12: 0.11885 | V12: 0.15416 | W12: 853.31618 | X12: 1.95332 | Y12: 1.3989 | Z12: 27.66156 | AA12: 22.8316 | AB12: 80.81663 | AC12: 56.70009 | AD12: 1307.5898 | AE12: 10557.872 | AF12: 1659.4438 | AG12: 790.79509 | AH12: 0 | AI12: 80.93059 | AJ12: 8026.7021
A13: 7 | B13: 5102 | C13: Operaciones interbancarias | D13: 0 | E13: 0 | F13: 4.36112 | G13: 0 | H13: 4.36112 | I13: 0 | J13: 0 | K13: 0 | L13: 0 | M13: 0 | N13: 0 | O13: 0 | P13: 0 | Q13: 0 | R13: 0 | S13: 0 | T13: 0 | U13: 0 | V13: 0 | W13: 0 | X13: 0 | Y13: 0 | Z13: 0 | AA13: 0 | AB13: 0 | AC13: 0 | AD13: 0 | AE13: 4.36112 | AF13: 0 | AG13: 0 | AH13: 0 | AI13: 0 | AJ13: 4.36112
A14: 8 | B14: 5103 | C14: Intereses y descuentos de inversiones en títulos valores | D14: 7884.1334 | E14: 12848.721 | F14: 24320.881 | G14: 5789.4521 | H14: 50843.188 | I14: 11631.815 | J14: 5711.4247 | K14: 2692.959 | L14: 1341.7153 | M14: 1774.6651 | N14: 11923.694 | O14: 1088.5994 | P14: 3264.4822 | Q14: 1694.6364 | R14: 41123.991 | S14: 312.31936 | T14: 1461.0145 | U14: 165.77557 | V14: 108.02627 | W14: 1155.0738 | X14: 41.7456 | Y14: 83.23393 | Z14: 110.88598 | AA14: 737.56347 | AB14: 244.77339 | AC14: 37.25495 | AD14: 4457.6669 | AE14: 96424.846 | AF14: 14616.653 | AG14: 3224.4066 | AH14: 0 | AI14: 858.05235 | AJ14: 77725.734
A15: 9 | B15: 5104 | C15: Intereses y descuentos de cartera de créditos | D15: 265488.93 | E15: 302227.03 | F15: 608339.09 | G15: 243189.27 | H15: 1419244.3 | I15: 90230.835 | J15: 152231.19 | K15: 9646.3 | L15: 148178.16 | M15: 58932.033 | N15: 152951.09 | O15: 33373.139 | P15: 40785.382 | Q15: 67833.672 | R15: 754161.8 | S15: 26571.047 | T15: 9157.3797 | U15: 2818.8348 | V15: 2551.6287 | W15: 5414.3006 | X15: 1535.6246 | Y15: 7963.2121 | Z15: 1291.8124 | AA15: 10948.832 | AB15: 17054.335 | AC15: 10753.966 | AD15: 96060.973 | AE15: 2269467.1 | AF15: 162597.39 | AG15: 209661.82 | AH15: 0 | AI15: 29666.01 | AJ15: 1867541.9
A16: 10 | B16: 510405 | C16: Cartera de créditos productivo | D16: 96146.015 | E16: 39984.04 | F16: 136365.78 | G16: 120820.33 | H16: 393316.17 | I16: 28213.583 | J16: 92090.672 | K16: 6716.544 | L16: 908.94075 | M16: 2977.3405 | N16: 107148.45 | O16: 5818.3552 | P16: 22050.346 | Q16: 0 | R16: 265924.24 | S16: 17863.546 | T16: 2856.2016 | U16: 866.68925 | V16: 256.61856 | W16: 4091.8769 | X16: 47.62969 | Y16: 0 | Z16: 445.93083 | AA16: 0 | AB16: 684.91055 | AC16: 0 | AD16: 27113.403 | AE16: 686353.81 | AF16: 113865 | AG16: 4142.8998 | AH16: 0 | AI16: 0 | AJ16: 568345.91
A17: 11 | B17: 510410 | C17: Cartera de créditos de consumo | D17: 123987.67 | E17: 151113.17 | F17: 215427.59 | G17: 90397.05 | H17: 580925.48 | I17: 45652.44 | J17: 53781.411 | K17: 0 | L17: 136708.19 | M17: 46881.489 | N17: 30664.697 | O17: 12570.27 | P17: 15222.633 | Q17: 28525.329 | R17: 370006.46 | S17: 261.70458 | T17: 5178.3825 | U17: 852.83649 | V17: 1622.044 | W17: 76.47376 | X17: 931.91606 | Y17: 366.20007 | Z17: 413.38187 | AA17: 0 | AB17: 3287.906 | AC17: 0.1837 | AD17: 12991.029 | AE17: 963922.97 | AF17: 30664.697 | AG17: 185211.72 | AH17: 0 | AI17: 366.38377 | AJ17: 747680.16
A18: 12 | B18: 510415 | C18: Cartera de crédito inmobiliario | D18: 12429.285 | E18: 27666.055 | F18: 48893.262 | G18: 16962.871 | H18: 105951.47 | I18: 3365.5852 | J18: 4551.8368 | K18: 0 | L18: 0 | M18: 5492.4187 | N18: 7373.2427 | O18: 2410.2579 | P18: 1262.9728 | Q18: 1.9709 | R18: 24458.285 | S18: 951.68994 | T18: 79.90662 | U18: 1.75604 | V18: 3.44354 | W18: 9.35666 | X18: 0.13643 | Y18: 0 | Z18: 115.9596 | AA18: 0 | AB18: 312.25549 | AC18: 0 | AD18: 1474.5043 | AE18: 131884.26 | AF18: 7373.2427 | AG18: 5495.8622 | AH18: 0 | AI18: 0 | AJ18: 119015.16
A19: 13 | B19: 510420 | C19: Cartera de créditos para microcrédito | D19: 20715.002 | E19: 657.90663 | F19: 127219.85 | G19: 1771.6229 | H19: 150364.38 | I19: 598.29381 | J19: 0 | K19: 0 | L19: 0 | M19: 0 | N19: 336.35799 | O19: 6669.742 | P19: 661.44602 | Q19: 37203.209 | R19: 45469.048 | S19: 5558.085 | T19: 8.11049 | U19: 806.34358 | V19: 129.75091 | W19: 1229.4782 | X19: 73.8361 | Y19: 6068.0054 | Z19: 8.07208 | AA19: 10534.861 | AB19: 5681.792 | AC19: 10179.43 | AD19: 40277.765 | AE19: 236111.19 | AF19: 336.35799 | AG19: 129.75091 | AH19: 0 | AI19: 26782.296 | AJ19: 208862.79
A20: 14 | B20: 510421 | C20: Cartera de crédito productivo | D20: 0 | E20: 0 | F20: 0 | G20: 0 | H20: 0 | I20: 0 | J20: 0 | K20: 0 | L20: 0 | M20: 0 | N20: 0 | O20: 0 | P20: 0 | Q20: 0 | R20: 0 | S20: 0 | T20: 0 | U20: 0 | V20: 0 | W20: 0 | X20: 0 | Y20: 0 | Z20: 0 | AA20: 0 | AB20: 0 | AC20: 0 | AD20: 0 | AE20: 0 | AF20: 0 | AG20: 0 | AH20: 0 | AI20: 0 | AJ20: 0
A21: 15 | B21: 510425 | C21: Cartera de crédito comercial ordinario | D21: 0 | E21: 0 | F21: 0 | G21: 0 | H21: 0 | I21: 0 | J21: 0 | K21: 0 | L21: 0 | M21: 0 | N21: 0 | O21: 0 | P21: 0 | Q21: 0 | R21: 0 | S21: 0 | T21: 0 | U21: 0 | V21: 0 | W21: 0 | X21: 0 | Y21: 0 | Z21: 0 | AA21: 0 | AB21: 0 | AC21: 0 | AD21: 0 | AE21: 0 | AF21: 0 | AG21: 0 | AH21: 0 | AI21: 0 | AJ21: 0
... A36: 30 | B36: 4105 | C36: Otros intereses | D36: 0 | E36: 0 | F36: 6.44316 | G36: 0 | H36: 6.44316 | I36: 0 | J36: 0 | K36: 0 | L36: 0 | M36: 0 | N36: 0 | O36: 0 | P36: 0 | Q36: 0 | R36: 0 | S36: 0 | T36: 0.70914 | U36: 0 | V36: 0 | W36: 0 | X36: 0 | Y36: 0 | Z36: 0 | AA36: 0 | AB36: 0 | AC36: 0 | AD36: 0.70914 | AE36: 7.1523 | AF36: 0 | AG36: 0 | AH36: 0 | AI36: 0 | AJ36: 7.1523
A37: 31 | B37: MARGEN NETO INTERESES | C37: MARGEN NETO INTERESES | D37: 176291.82 | E37: 183262.08 | F37: 497336.54 | G37: 175104.34 | H37: 1031994.8 | I37: 58870.143 | J37: 100006.18 | K37: 12451.179 | L37: 100871.86 | M37: 40773.667 | N37: 102913.22 | O37: 23414.072 | P37: 28134.432 | Q37: 47767.972 | R37: 515202.73 | S37: 15388.603 | T37: 3970.9707 | U37: 2493.2203 | V37: 2083.6296 | W37: 5854.8562 | X37: 664.72616 | Y37: 3898.9985 | Z37: 1078.7761 | AA37: 6781.7533 | AB37: 11054.481 | AC37: 8164.9144 | AD37: 61434.93 | AE37: 1608632.4 | AF37: 115364.39 | AG37: 143729.16 | AH37: 0 | AI37: 18845.666 | AJ37: 1330693.2
A39: 33 | B39: 52 | C39: COMISIONES GANADAS | D39: 25154.623 | E39: 29368.712 | F39: 30165.535 | G39: 14722.19 | H39: 99411.059 | I39: 7384.3537 | J39: 16773.085 | K39: 1556.33 | L39: 39371.025 | M39: 2914.9053 | N39: 14334.415 | O39: 787.43964 | P39: 727.71544 | Q39: 2582.064 | R39: 86431.333 | S39: 33.43968 | T39: 173.16509 | U39: 14.228 | V39: 0.006 | W39: 0 | X39: 0 | Y39: 0 | Z39: 48.92544 | AA39: 0 | AB39: 47.03894 | AC39: 0 | AD39: 316.80315 | AE39: 186159.2 | AF39: 15890.745 | AG39: 42285.936 | AH39: 0 | AI39: 0 | AJ39: 127982.51
A40: 34 | B40: 5201 | C40: Cartera de créditos | D40: 16.98241 | E40: 0 | F40: 0 | G40: 0 | H40: 16.98241 | I40: 0 | J40: 0 | K40: 0 | L40: 0 | M40: 0 | N40: 0 | O40: 0 | P40: 0.05617 | Q40: 0 | R40: 0.05617 | S40: 0 | T40: 0 | U40: 0 | V40: 0 | W40: 0 | X40: 0 | Y40: 0 | Z40: 0 | AA40: 0 | AB40: 0 | AC40: 0 | AD40: 0 | AE40: 17.03858 | AF40: 0 | AG40: 0 | AH40: 0 | AI40: 0 | AJ40: 17.03858
A41: 35 | B41: 520105 | C41: Cartera de créditos comercial | D41: 2.82237 | E41: 0 | F41: 0 | G41: 0 | H41: 2.82237 | I41: 0 | J41: 0 | K41: 0 | L41: 0 | M41: 0 | N41: 0 | O41: 0 | P41: 0.05617 | Q41: 0 | R41: 0.05617 | S41: 0 | T41: 0 | U41: 0 | V41: 0 | W41: 0 | X41: 0 | Y41: 0 | Z41: 0 | AA41: 0 | AB41: 0 | AC41: 0 | AD41: 0 | AE41: 2.87854 | AF41: 0 | AG41: 0 | AH41: 0 | AI41: 0 | AJ41: 2.87854
A42: 36 | B42: 520110 | C42: Cartera de créditos de consumo | D42: 10.30673 | E42: 0 | F42: 0 | G42: 0 | H42: 10.30673 | I42: 0 | J42: 0 | K42: 0 | L42: 0 | M42: 0 | N42: 0 | O42: 0 | P42: 0 | Q42: 0 | R42: 0 | S42: 0 | T42: 0 | U42: 0 | V42: 0 | W42: 0 | X42: 0 | Y42: 0 | Z42: 0 | AA42: 0 | AB42: 0 | AC42: 0 | AD42: 0 | AE42: 10.30673 | AF42: 0 | AG42: 0 | AH42: 0 | AI42: 0 | AJ42: 10.30673
A43: 37 | B43: 520115 | C43: Cartera de créditos de vivienda | D43: 0 | E43: 0 | F43: 0 | G43: 0 | H43: 0 | I43: 0 | J43: 0 | K43: 0 | L43: 0 | M43: 0 | N43: 0 | O43: 0 | P43: 0 | Q43: 0 | R43: 0 | S43: 0 | T43: 0 | U43: 0 | V43: 0 | W43: 0 | X43: 0 | Y43: 0 | Z43: 0 | AA43: 0 | AB43: 0 | AC43: 0 | AD43: 0 | AE43: 0 | AF43: 0 | AG43: 0 | AH43: 0 | AI43: 0 | AJ43: 0
A44: 38 | B44: 520120 | C44: Cartera de créditos para la microempresa | D44: 3.85331 | E44: 0 | F44: 0 | G44: 0 | H44: 3.85331 | I44: 0 | J44: 0 | K44: 0 | L44: 0 | M44: 0 | N44: 0 | O44: 0 | P44: 0 | Q44: 0 | R44: 0 | S44: 0 | T44: 0 | U44: 0 | V44: 0 | W44: 0 | X44: 0 | Y44: 0 | Z44: 0 | AA44: 0 | AB44: 0 | AC44: 0 | AD44: 0 | AE44: 3.85331 | AF44: 0 | AG44: 0 | AH44: 0 | AI44: 0 | AJ44: 3.85331
A45: 39 | B45: 520125 | C45: Cartera de créditos reestructurada | D45: 0 | E45: 0 | F45: 0 | G45: 0 | H45: 0 | I45: 0 | J45: 0 | K45: 0 | L45: 0 | M45: 0 | N45: 0 | O45: 0 | P45: 0 | Q45: 0 | R45: 0 | S45: 0 | T45: 0 | U45: 0 | V45: 0 | W45: 0 | X45: 0 | Y45: 0 | Z45: 0 | AA45: 0 | AB45: 0 | AC45: 0 | AD45: 0 | AE45: 0 | AF45: 0 | AG45: 0 | AH45: 0 | AI45: 0 | AJ45: 0
A46: 40 | B46: 5202 | C46: Deudores por aceptación | D46: 0 | E46: 0 | F46: 0 | G46: 0 | H46: 0 | I46: 0 | J46: 0 | K46: 2.375 | L46: 0 | M46: 0 | N46: 0 | O46: 0 | P46: 0 | Q46: 0 | R46: 2.375 | S46: 0 | T46: 0 | U46: 0 | V46: 0 | W46: 0 | X46: 0 | Y46: 0 | Z46: 0 | AA46: 0 | AB46: 0 | AC46: 0 | AD46: 0 | AE46: 2.375 | AF46: 2.375 | AG46: 0 | AH46: 0 | AI46: 0 | AJ46: 0
A47: 41 | B47: 5203 | C47: Avales | D47: 0 | E47: 26.36767 | F47: 1465.5589 | G47: 297.66633 | H47: 1789.5929 | I47: 695.38135 | J47: 758.0313 | K47: 0 | L47: 0 | M47: 25.47061 | N47: 613.9625 | O47: 69.64107 | P47: 5.2 | Q47: 0 | R47: 2167.6868 | S47: 0 | T47: 0 | U47: 0 | V47: 0 | W47: 0 | X47: 0 | Y47: 0 | Z47: 0 | AA47: 0 | AB47: 0 | AC47: 0 | AD47: 0 | AE47: 3957.2797 | AF47: 613.9625 | AG47: 25.47061 | AH47: 0 | AI47: 0 | AJ47: 3317.8466
A48: 42 | B48: 5204 | C48: Fianzas | D48: 2937.2466 | E48: 2682.3415 | F48: 4042.2793 | G48: 2293.1607 | H48: 11955.028 | I48: 298.79033 | J48: 1399.2196 | K48: 1469.924 | L48: 0 | M48: 131.29442 | N48: 2438.0694 | O48: 0 | P48: 122.81186 | Q48: 3.74808 | R48: 5863.8577 | S48: 24.27702 | T48: 20.39027 | U48: 14.228 | V48: 0 | W48: 0 | X48: 0 | Y48: 0 | Z48: 0 | AA48: 0 | AB48: 22.63069 | AC48: 0 | AD48: 81.52598 | AE48: 17900.412 | AF48: 3907.9934 | AG48: 131.29442 | AH48: 0 | AI48: 0 | AJ48: 13861.124
A49: 43 | B49: 5205 | C49: Cartas de Crédito | D49: 1600.7695 | E49: 791.73966 | F49: 883.05087 | G49: 1186.4868 | H49: 4462.0469 | I49: 70.6267 | J49: 1431.3487 | K49: 8.452 | L49: 0 | M49: 6.29637 | N49: 2263.7725 | O49: 0 | P49: 10 | Q49: 0 | R49: 3790.4963 | S49: 8.23067 | T49: 0 | U49: 0 | V49: 0 | W49: 0 | X49: 0 | Y49: 0 | Z49: 0 | AA49: 0 | AB49: 0 | AC49: 0 | AD49: 8.23067 | AE49: 8260.7739 | AF49: 2272.2245 | AG49: 6.29637 | AH49: 0 | AI49: 0 | AJ49: 5982.253
A50: 44 | B50: 5290 | C50: Otras | D50: 20599.624 | E50: 25868.264 | F50: 23774.646 | G50: 10944.876 | H50: 81187.409 | I50: 6319.5553 | J50: 13184.485 | K50: 75.579 | L50: 39371.025 | M50: 2751.8439 | N50: 9018.6108 | O50: 717.79857 | P50: 589.64741 | Q50: 2578.3159 | R50: 74606.861 | S50: 0.93199 | T50: 152.77482 | U50: 0 | V50: 0.006 | W50: 0 | X50: 0 | Y50: 0 | Z50: 48.92544 | AA50: 0 | AB50: 24.40825 | AC50: 0 | AD50: 227.0465 | AE50: 156021.32 | AF50: 9094.1898 | AG50: 42122.875 | AH50: 0 | AI50: 0 | AJ50: 104804.25
... A61: 55 | B61: 540510 | C61: Tarifa periódica | D61: 0 | E61: 0 | F61: 0 | G61: 0 | H61: 0 | I61: 0 | J61: 0 | K61: 0 | L61: 0 | M61: 0 | N61: 0 | O61: 0 | P61: 0 | Q61: 0 | R61: 0 | S61: 0 | T61: 0 | U61: 0 | V61: 0 | W61: 0 | X61: 0 | Y61: 0 | Z61: 0 | AA61: 0 | AB61: 0 | AC61: 0 | AD61: 0 | AE61: 0 | AF61: 0 | AG61: 0 | AH61: 0 | AI61: 0 | AJ61: 0
B62: 5406 | C62: Servicios Financieros con cargo máximo | D62: 57218.499 | E62: 50659.914 | F62: 68249.611 | G62: 36060.803 | H62: 212188.83 | I62: 12336.661 | J62: 14483.654 | K62: 898.466 | L62: 56578.344 | M62: 3663.929 | N62: 11842.502 | O62: 2164.819 | P62: 3426.5793 | Q62: 2648.8748 | R62: 108043.83 | S62: 551.29426 | T62: 419.36686 | U62: 326.81234 | V62: 102.27602 | W62: 496.18411 | X62: 31.12234 | Y62: 6.53985 | Z62: 86.25228 | AA62: 35.3859 | AB62: 278.8755 | AC62: 382.4514 | AD62: 2716.5609 | AE62: 322949.22 | AF62: 12740.968 | AG62: 60344.549 | AH62: 0 | AI62: 424.37715 | AJ62: 249439.32
B63: 5407 | C63: Servicios Financieros con cargo diferenciado | D63: 21571.917 | E63: 21919.16 | F63: 46713.259 | G63: 13236.264 | H63: 103440.6 | I63: 2591.641 | J63: 10094.498 | K63: 290.988 | L63: 8409.5557 | M63: 2150.251 | N63: 7311.7423 | O63: 276.21595 | P63: 786.91965 | Q63: 8638.961 | R63: 40550.773 | S63: 13.53682 | T63: 1212.1293 | U63: 43.78299 | V63: 37.09739 | W63: 0 | X63: 0 | Y63: 0 | Z63: 2043.3073 | AA63: 9.5803 | AB63: 161.2373 | AC63: 0 | AD63: 3520.6714 | AE63: 147512.04 | AF63: 7602.7303 | AG63: 10596.904 | AH63: 0 | AI63: 9.5803 | AJ63: 129302.83
A64: 56 | B64: 5490 | C64: Otros servicios | D64: 0 | E64: 0 | F64: 0 | G64: 0 | H64: 0 | I64: 0 | J64: 0 | K64: 0 | L64: 0 | M64: 0 | N64: 0.00275 | O64: 0 | P64: 0 | Q64: 0 | R64: 0.00275 | S64: 0 | T64: 0 | U64: 0 | V64: 0 | W64: 3.39933 | X64: 0 | Y64: 0 | Z64: 0 | AA64: 0.08205 | AB64: 0 | AC64: 0 | AD64: 3.48138 | AE64: 3.48413 | AF64: 0.00275 | AG64: 0 | AH64: 0 | AI64: 0.08205 | AJ64: 3.39933
A65: 57 | B65: 549005 | C65: Tarifados con costo máximo | D65: 0 | E65: 0 | F65: 0 | G65: 0 | H65: 0 | I65: 0 | J65: 0 | K65: 0 | L65: 0 | M65: 0 | N65: 0 | O65: 0 | P65: 0 | Q65: 0 | R65: 0 | S65: 0 | T65: 0 | U65: 0 | V65: 0 | W65: 0 | X65: 0 | Y65: 0 | Z65: 0 | AA65: 0 | AB65: 0 | AC65: 0 | AD65: 0 | AE65: 0 | AF65: 0 | AG65: 0 | AH65: 0 | AI65: 0 | AJ65: 0
A66: 58 | B66: 549010 | C66: Tarifados diferenciados | D66: 0 | E66: 0 | F66: 0 | G66: 0 | H66: 0 | I66: 0 | J66: 0 | K66: 0 | L66: 0 | M66: 0 | N66: 0 | O66: 0 | P66: 0 | Q66: 0 | R66: 0 | S66: 0 | T66: 0 | U66: 0 | V66: 0 | W66: 0 | X66: 0 | Y66: 0 | Z66: 0 | AA66: 0 | AB66: 0 | AC66: 0 | AD66: 0 | AE66: 0 | AF66: 0 | AG66: 0 | AH66: 0 | AI66: 0 | AJ66: 0
A67: 59 | B67: 549090 | C67: Otros | D67: 0 | E67: 0 | F67: 0 | G67: 0 | H67: 0 | I67: 0 | J67: 0 | K67: 0 | L67: 0 | M67: 0 | N67: 0 | O67: 0 | P67: 0 | Q67: 0 | R67: 0 | S67: 0 | T67: 0 | U67: 0 | V67: 0 | W67: 0 | X67: 0 | Y67: 0 | Z67: 0 | AA67: 0 | AB67: 0 | AC67: 0 | AD67: 0 | AE67: 0 | AF67: 0 | AG67: 0 | AH67: 0 | AI67: 0 | AJ67: 0
A68: 60 | B68: 42 | C68: COMISIONES CAUSADAS | D68: 17978.328 | E68: 28269.415 | F68: 5051.6572 | G68: 1872.0431 | H68: 53171.443 | I68: 8863.4994 | J68: 2212.7901 | K68: 1148.673 | L68: 627.03472 | M68: 413.48741 | N68: 1301.5471 | O68: 459.65419 | P68: 707.04796 | Q68: 592.04037 | R68: 16325.774 | S68: 800.28049 | T68: 219.93922 | U68: 164.88566 | V68: 7.92696 | W68: 5.376 | X68: 9.13617 | Y68: 46.0331 | Z68: 241.37806 | AA68: 75.3 | AB68: 175.1989 | AC68: 95.13033 | AD68: 1840.5849 | AE68: 71337.802 | AF68: 2450.2201 | AG68: 1048.4491 | AH68: 0 | AI68: 216.46343 | AJ68: 67622.669
A69: 61 | B69: 4201 | C69: Obligaciones financieras | D69: 1111.7639 | E69: 1800.5099 | F69: 19.05282 | G69: 898.47823 | H69: 3829.8048 | I69: 0 | J69: 699.71967 | K69: 0 | L69: 0 | M69: 0 | N69: 418.55633 | O69: 0.89606 | P69: 0 | Q69: 470 | R69: 1589.1721 | S69: 221.13275 | T69: 0 | U69: 0 | V69: 0 | W69: 0 | X69: 0 | Y69: 46.0331 | Z69: 0 | AA69: 70.5 | AB69: 29.86667 | AC69: 95.13033 | AD69: 462.66285 | AE69: 5881.6397 | AF69: 418.55633 | AG69: 0 | AH69: 0 | AI69: 211.66343 | AJ69: 5251.4199
A70: 62 | B70: 4202 | C70: Operaciones contingentes | D70: 0 | E70: 0 | F70: 364.71271 | G70: 197.38515 | H70: 562.09786 | I70: 0 | J70: 0 | K70: 0 | L70: 0 | M70: 0 | N70: 0 | O70: 0 | P70: 0 | Q70: 0 | R70: 0 | S70: 0 | T70: 0 | U70: 0 | V70: 0 | W70: 0 | X70: 0 | Y70: 0 | Z70: 0 | AA70: 0 | AB70: 0 | AC70: 0 | AD70: 0 | AE70: 562.09786 | AF70: 0 | AG70: 0 | AH70: 0 | AI70: 0 | AJ70: 562.09786
A71: 63 | B71: 4203 | C71: Cobranzas | D71: 0 | E71: 0 | F71: 103.73219 | G71: 0 | H71: 103.73219 | I71: 8e-05 | J71: 0 | K71: 0 | L71: 0 | M71: 47.90547 | N71: 0 | O71: 0 | P71: 0 | Q71: 0 | R71: 47.90555 | S71: 0 | T71: 0 | U71: 0 | V71: 0 | W71: 0 | X71: 0 | Y71: 0 | Z71: 0 | AA71: 0 | AB71: 0 | AC71: 0 | AD71: 0 | AE71: 151.63774 | AF71: 0 | AG71: 47.90547 | AH71: 0 | AI71: 0 | AJ71: 103.73227
A72: 64 | B72: 4204 | C72: Por operaciones de permuta financiera | D72: 0 | E72: 0 | F72: 0 | G72: 0 | H72: 0 | I72: 0 | J72: 0 | K72: 0 | L72: 0 | M72: 0 | N72: 0 | O72: 0 | P72: 0 | Q72: 0 | R72: 0 | S72: 0 | T72: 0 | U72: 0 | V72: 0 | W72: 0 | X72: 0 | Y72: 0 | Z72: 0 | AA72: 0 | AB72: 0 | AC72: 0 | AD72: 0 | AE72: 0 | AF72: 0 | AG72: 0 | AH72: 0 | AI72: 0 | AJ72: 0
A73: 65 | B73: 4205 | C73: Servicios fiduciarios | D73: 7.40965 | E73: 20.40917 | F73: 10 | G73: 0 | H73: 37.81882 | I73: 0 | J73: 5.8 | K73: 0 | L73: 0 | M73: 0 | N73: 16.8 | O73: 4.8 | P73: 5.376 | Q73: 0 | R73: 32.776 | S73: 0 | T73: 0 | U73: 55.47128 | V73: 0 | W73: 5.376 | X73: 0 | Y73: 0 | Z73: 4.8 | AA73: 4.8 | AB73: 5.376 | AC73: 0 | AD73: 75.82328 | AE73: 146.4181 | AF73: 16.8 | AG73: 0 | AH73: 0 | AI73: 4.8 | AJ73: 124.8181
A74: 66 | B74: 4290 | C74: Varias | D74: 16859.154 | E74: 26448.496 | F74: 4554.1594 | G74: 776.17973 | H74: 48637.989 | I74: 8863.4993 | J74: 1507.2704 | K74: 1148.673 | L74: 627.03472 | M74: 365.58194 | N74: 866.19079 | O74: 453.95813 | P74: 701.67196 | Q74: 122.04037 | R74: 14655.921 | S74: 579.14774 | T74: 219.93922 | U74: 109.41438 | V74: 7.92696 | W74: 0 | X74: 9.13617 | Y74: 0 | Z74: 236.57806 | AA74: 0 | AB74: 139.95623 | AC74: 0 | AD74: 1302.0988 | AE74: 64596.008 | AF74: 2014.8638 | AG74: 1000.5436 | AH74: 0 | AI74: 0 | AJ74: 61580.601
A75: 67 | B75: 53 | C75: UTILIDADES FINANCIERAS | D75: 6839.1125 | E75: 5679.5794 | F75: 10475.452 | G75: 5589.4308 | H75: 28583.575 | I75: 6216.6616 | J75: 3008.4681 | K75: 1071.11 | L75: 7546.6127 | M75: 2475.6711 | N75: 3290.2898 | O75: 26.02342 | P75: 72.32727 | Q75: 3124.4595 | R75: 26831.624 | S75: 178.05153 | T75: 1062.3279 | U75: 0.704 | V75: 0.61809 | W75: 2.8174 | X75: 0.01528 | Y75: 44.2509 | Z75: 99.06185 | AA75: 72.50261 | AB75: 483.12608 | AC75: 0.14195 | AD75: 1943.6176 | AE75: 57358.816 | AF75: 4361.3998 | AG75: 10022.902 | AH75: 0 | AI75: 116.89546 | AJ75: 42857.619
... A89: 81 | B89: 4390 | C89: Otras | D89: 0 | E89: 0 | F89: 0 | G89: 0 | H89: 0 | I89: 0 | J89: 0 | K89: 0 | L89: 0 | M89: 0 | N89: 0 | O89: 0 | P89: 0 | Q89: 0 | R89: 0 | S89: 0 | T89: 0 | U89: 0 | V89: 0 | W89: 0 | X89: 0 | Y89: 0 | Z89: 0 | AA89: 0 | AB89: 0 | AC89: 0 | AD89: 0 | AE89: 0 | AF89: 0 | AG89: 0 | AH89: 0 | AI89: 0 | AJ89: 0
A90: 82 | B90: MARGEN BRUTO FINANCIERO | C90: MARGEN BRUTO FINANCIERO | D90: 271092.28 | E90: 261939.92 | F90: 635671.57 | G90: 242251.85 | H90: 1410955.6 | I90: 73755.912 | J90: 141533.76 | K90: 14136.201 | L90: 212063.07 | M90: 51296.808 | N90: 136971.11 | O90: 26170.097 | P90: 32285.265 | Q90: 46611.155 | R90: 734823.37 | S90: 15253.343 | T90: 6074.7033 | U90: 2805.1476 | V90: 2215.7001 | W90: 6351.8811 | X90: 646.92036 | Y90: 3885.3593 | Z90: 3076.5529 | AA90: 6850.993 | AB90: 8741.9418 | AC90: 8452.3775 | AD90: 64354.919 | AE90: 2210133.9 | AF90: 151107.31 | AG90: 265575.58 | AH90: 0 | AI90: 19188.73 | AJ90: 1774262.3
A92: 84 | B92: 44 | C92: PROVISIONES | D92: 77024.279 | E92: 107715.13 | F92: 215395.6 | G92: 91843.935 | H92: 491978.95 | I92: 13849.167 | J92: 21639.467 | K92: 493.886 | L92: 88410.812 | M92: 12967.851 | N92: 21089.002 | O92: 7587.5226 | P92: 5549.0056 | Q92: 231.2524 | R92: 171817.97 | S92: 4799.1376 | T92: 1690.282 | U92: 138.11516 | V92: 61.07379 | W92: 88.0112 | X92: 183.55659 | Y92: 5262.9563 | Z92: 537.53953 | AA92: 836.36911 | AB92: 4101.901 | AC92: 2669.1549 | AD92: 20368.097 | AE92: 684165.01 | AF92: 21582.888 | AG92: 101439.74 | AH92: 0 | AI92: 8768.4803 | AJ92: 552373.9
A93: 85 | B93: 4401 | C93: Inversiones | D93: 0 | E93: 0 | F93: 43080.158 | G93: 0 | H93: 43080.158 | I93: 258.58854 | J93: 0 | K93: 0 | L93: 0 | M93: 1658.8685 | N93: 0.00146 | O93: 0 | P93: 0 | Q93: 0 | R93: 1917.4585 | S93: 0 | T93: 0 | U93: 1.39448 | V93: 0 | W93: 0 | X93: 0 | Y93: 0 | Z93: 0 | AA93: 0 | AB93: 0 | AC93: 0 | AD93: 1.39448 | AE93: 44999.011 | AF93: 0.00146 | AG93: 1658.8685 | AH93: 0 | AI93: 0 | AJ93: 43340.141
A94: 86 | B94: 4402 | C94: Cartera de créditos | D94: 70866.401 | E94: 94065.43 | F94: 139000.31 | G94: 80021.366 | H94: 383953.51 | I94: 11003.87 | J94: 21054.156 | K94: 478.327 | L94: 83778.741 | M94: 10107.424 | N94: 16706.332 | O94: 7300.0331 | P94: 5190.2627 | Q94: 110.08378 | R94: 155729.23 | S94: 4451.2774 | T94: 1237.2649 | U94: 122.01177 | V94: 35.3136 | W94: 84.11862 | X94: 138.66508 | Y94: 5187.9419 | Z94: 522.08656 | AA94: 797.2979 | AB94: 2994.5533 | AC94: 2597.9784 | AD94: 18168.509 | AE94: 557851.24 | AF94: 17184.659 | AG94: 93921.478 | AH94: 0 | AI94: 8583.2182 | AJ94: 438161.89
A95: 87 | B95: 440205 | C95: Crédito productivo | D95: 0 | E95: 0 | F95: 0 | G95: 0 | H95: 0 | I95: 0 | J95: 0 | K95: 0 | L95: 0 | M95: 0 | N95: 0 | O95: 0 | P95: 0 | Q95: 0 | R95: 0 | S95: 0 | T95: 0 | U95: 0 | V95: 0 | W95: 0 | X95: 0 | Y95: 0 | Z95: 0 | AA95: 0 | AB95: 0 | AC95: 0 | AD95: 0 | AE95: 0 | AF95: 0 | AG95: 0 | AH95: 0 | AI95: 0 | AJ95: 0
A96: 88 | B96: 440210 | C96: Crédito Productivo | D96: 2674.2189 | E96: 20693.798 | F96: 58913.668 | G96: 31608.995 | H96: 113890.68 | I96: 0 | J96: 9234.741 | K96: 478.327 | L96: 5199.4884 | M96: 0 | N96: 6838.9941 | O96: 1892.8796 | P96: 951.04653 | Q96: 0.28445 | R96: 24595.761 | S96: 3043.747 | T96: 524.38265 | U96: 28.54958 | V96: 0.50176 | W96: 13.75009 | X96: 11.5708 | Y96: 0 | Z96: 262.40589 | AA96: 0 | AB96: 78.72261 | AC96: 0 | AD96: 3963.6304 | AE96: 142450.07 | AF96: 7317.3211 | AG96: 5199.9902 | AH96: 0 | AI96: 0 | AJ96: 129932.76
A97: 89 | B97: 440215 | C97: Crédito comercial ordinario | D97: 0 | E97: 0 | F97: 0 | G97: 0 | H97: 0 | I97: 0 | J97: 0 | K97: 0 | L97: 0 | M97: 0 | N97: 0 | O97: 0 | P97: 0 | Q97: 0 | R97: 0 | S97: 0 | T97: 0 | U97: 0 | V97: 0 | W97: 0 | X97: 0 | Y97: 0 | Z97: 0 | AA97: 0 | AB97: 0 | AC97: 0 | AD97: 0 | AE97: 0 | AF97: 0 | AG97: 0 | AH97: 0 | AI97: 0 | AJ97: 0
A98: 90 | B98: 440220 | C98: Crédito de Consumo | D98: 54287.081 | E98: 61939.517 | F98: 41049.893 | G98: 46824.127 | H98: 204100.62 | I98: 10737.573 | J98: 11508.331 | K98: 0 | L98: 78579.252 | M98: 10107.424 | N98: 9838.9447 | O98: 4775.9033 | P98: 3877.4662 | Q98: 100.55597 | R98: 129525.45 | S98: 43.7024 | T98: 699.49678 | U98: 25.4572 | V98: 34.68378 | W98: 0.98033 | X98: 127.09428 | Y98: 27.1356 | Z98: 211.72621 | AA98: 0 | AB98: 780.81183 | AC98: 0.31366 | AD98: 1951.4021 | AE98: 335577.47 | AF98: 9838.9447 | AG98: 88721.36 | AH98: 0 | AI98: 27.44926 | AJ98: 236989.72
A99: 91 | B99: 440225 | C99: Crédito de consumo ordinario | D99: 0 | E99: 0 | F99: 0 | G99: 0 | H99: 0 | I99: 0 | J99: 0 | K99: 0 | L99: 0 | M99: 0 | N99: 0 | O99: 0 | P99: 0 | Q99: 0 | R99: 0 | S99: 0 | T99: 0 | U99: 0 | V99: 0 | W99: 0 | X99: 0 | Y99: 0 | Z99: 0 | AA99: 0 | AB99: 0 | AC99: 0 | AD99: 0 | AE99: 0 | AF99: 0 | AG99: 0 | AH99: 0 | AI99: 0 | AJ99: 0
A100: 92 | B100: 440230 | C100: Crédito inmobiliario | D100: 1073.3713 | E100: 3995.2853 | F100: 6569.0597 | G100: 644.44283 | H100: 12282.159 | I100: 0 | J100: 289.449 | K100: 0 | L100: 0 | M100: 0 | N100: 0 | O100: 148.08851 | P100: 149.36776 | Q100: 8.3323 | R100: 595.23757 | S100: 299.18566 | T100: 4.66752 | U100: 0.00909 | V100: 0.02113 | W100: 0 | X100: 0 | Y100: 0 | Z100: 44.65711 | AA100: 0 | AB100: 123.61335 | AC100: 0 | AD100: 472.15386 | AE100: 13349.551 | AF100: 0 | AG100: 0.02113 | AH100: 0 | AI100: 0 | AJ100: 13349.529
A101: 93 | B101: 440235 | C101: Crédito de vivienda de interés social y público | D101: 0 | E101: 1458.7651 | F101: 41.40938 | G101: 0 | H101: 1500.1745 | I101: 0 | J101: 0 | K101: 0 | L101: 0 | M101: 0 | N101: 0.79801 | O101: 0 | P101: 0 | Q101: 0 | R101: 0.79801 | S101: 0 | T101: 0 | U101: 0 | V101: 0 | W101: 0 | X101: 0 | Y101: 0 | Z101: 0 | AA101: 0 | AB101: 0 | AC101: 0 | AD101: 0 | AE101: 1500.9725 | AF101: 0.79801 | AG101: 0 | AH101: 0 | AI101: 0 | AJ101: 1500.1745
A102: 94 | B102: 440240 | C102: Microcrédito | D102: 12783.643 | E102: 1256.1379 | F102: 32309.572 | G102: 926.14172 | H102: 47275.494 | I102: 266.29711 | J102: 0 | K102: 0 | L102: 0 | M102: 0 | N102: 27.59525 | O102: 482.88417 | P102: 200.5756 | Q102: 0.91106 | R102: 978.26319 | S102: 1062.7304 | T102: 8.71798 | U102: 67.9959 | V102: 0.10693 | W102: 69.3882 | X102: 0 | Y102: 5160.8063 | Z102: 3.29735 | AA102: 797.2979 | AB102: 2011.4055 | AC102: 2597.6647 | AD102: 11779.411 | AE102: 60033.168 | AF102: 27.59525 | AG102: 0.10693 | AH102: 0 | AI102: 8555.7689 | AJ102: 51449.697
A103: 95 | B103: 440245 | C103: Crédito educativo | D103: 48.08716 | E103: 4721.9277 | F103: 116.70644 | G103: 17.65961 | H103: 4904.3809 | I103: 0 | J103: 21.635 | K103: 0 | L103: 0 | M103: 0 | N103: 0 | O103: 0.2775 | P103: 11.80657 | Q103: 0 | R103: 33.71907 | S103: 1.91197 | T103: 0 | U103: 0 | V103: 0 | W103: 0 | X103: 0 | Y103: 0 | Z103: 0 | AA103: 0 | AB103: 0 | AC103: 0 | AD103: 1.91197 | AE103: 4940.0119 | AF103: 0 | AG103: 0 | AH103: 0 | AI103: 0 | AJ103: 4940.0119
... A109: 101 | B109: 4407 | C109: Operaciones interbancarias y de reporto | D109: 0 | E109: 0 | F109: 0 | G109: 0 | H109: 0 | I109: 0 | J109: 0 | K109: 0 | L109: 0 | M109: 0 | N109: 0 | O109: 0 | P109: 0 | Q109: 0 | R109: 0 | S109: 0 | T109: 0 | U109: 0 | V109: 0 | W109: 0 | X109: 0 | Y109: 0 | Z109: 0 | AA109: 0 | AB109: 0 | AC109: 0 | AD109: 0 | AE109: 0 | AF109: 0 | AG109: 0 | AH109: 0 | AI109: 0 | AJ109: 0
A110: 102 | B110: MARGEN NETO FINANCIERO | C110: MARGEN NETO FINANCIERO | D110: 194068 | E110: 154224.79 | F110: 420275.97 | G110: 150407.91 | H110: 918976.67 | I110: 59906.745 | J110: 119894.29 | K110: 13642.315 | L110: 123652.26 | M110: 38328.956 | N110: 115882.1 | O110: 18582.574 | P110: 26736.259 | Q110: 46379.903 | R110: 563005.4 | S110: 10454.205 | T110: 4384.4213 | U110: 2667.0324 | V110: 2154.6263 | W110: 6263.8699 | X110: 463.36377 | Y110: -1377.597 | Z110: 2539.0134 | AA110: 6014.6238 | AB110: 4640.0408 | AC110: 5783.2226 | AD110: 43986.822 | AE110: 1525968.9 | AF110: 129524.42 | AG110: 164135.84 | AH110: 0 | AI110: 10420.249 | AJ110: 1221888.4
A112: 104 | B112: 45 | C112: GASTOS DE OPERACIÓN | D112: 144935.09 | E112: 187598.57 | F112: 416933.27 | G112: 146077.07 | H112: 895544 | I112: 54816.625 | J112: 88838.538 | K112: 18164.156 | L112: 116450.79 | M112: 29480.191 | N112: 74934.326 | O112: 15757.526 | P112: 23864.346 | Q112: 42574.125 | R112: 464880.62 | S112: 14898.794 | T112: 5111.5694 | U112: 2512.4568 | V112: 2116.4235 | W112: 5281.886 | X112: 2164.3004 | Y112: 5587.4507 | Z112: 3115.0477 | AA112: 6795.0098 | AB112: 7514.9252 | AC112: 5370.7813 | AD112: 60468.645 | AE112: 1420893.3 | AF112: 93098.482 | AG112: 148047.4 | AH112: 0 | AI112: 17753.242 | AJ112: 1161994.1
A113: 105 | B113: 4501 | C113: Gastos de personal | D113: 53572.935 | E113: 65842.037 | F113: 97517.636 | G113: 40633.936 | H113: 257566.54 | I113: 16631.242 | J113: 27603.151 | K113: 5444.711 | L113: 23776.551 | M113: 10505.561 | N113: 24921.676 | O113: 6463.755 | P113: 9666.8567 | Q113: 23399.935 | R113: 148413.44 | S113: 4884.0926 | T113: 1828.1912 | U113: 877.57174 | V113: 1000.3124 | W113: 1785.207 | X113: 865.15368 | Y113: 3024.6188 | Z113: 1245.6998 | AA113: 3312.093 | AB113: 4162.4905 | AC113: 3240.8768 | AD113: 26226.308 | AE113: 432206.29 | AF113: 30366.387 | AG113: 35282.425 | AH113: 0 | AI113: 9577.5886 | AJ113: 356979.89
A114: 106 | B114: 4502 | C114: Honorarios | D114: 2121.6866 | E114: 5851.4335 | F114: 47302.518 | G114: 3265.6438 | H114: 58541.282 | I114: 4755.7209 | J114: 1000.4087 | K114: 166.667 | L114: 1294.0869 | M114: 1133.3185 | N114: 262.51663 | O114: 233.67507 | P114: 359.50271 | Q114: 1005.765 | R114: 10211.662 | S114: 380.25451 | T114: 251.80112 | U114: 148.29143 | V114: 168.25276 | W114: 320.66726 | X114: 193.31122 | Y114: 289.15267 | Z114: 136.43134 | AA114: 450.10982 | AB114: 226.31895 | AC114: 372.25003 | AD114: 2936.8411 | AE114: 71689.785 | AF114: 429.18363 | AG114: 2595.6582 | AH114: 0 | AI114: 1111.5125 | AJ114: 67553.43
A115: 107 | B115: 4503 | C115: Servicios varios | D115: 39587.055 | E115: 42949.16 | F115: 110634.05 | G115: 53094.42 | H115: 246264.68 | I115: 15152.786 | J115: 18809.112 | K115: 7051.045 | L115: 62906.93 | M115: 6879.472 | N115: 9754.2123 | O115: 3271.0139 | P115: 5647.7312 | Q115: 9060.065 | R115: 138532.37 | S115: 4366.2462 | T115: 1063.6531 | U115: 432.16071 | V115: 363.50397 | W115: 721.84391 | X115: 376.71487 | Y115: 993.17973 | Z115: 1304.3794 | AA115: 1025.6647 | AB115: 1288.1348 | AC115: 1030.4606 | AD115: 12965.942 | AE115: 397762.99 | AF115: 16805.257 | AG115: 70149.906 | AH115: 0 | AI115: 3049.305 | AJ115: 307758.52
A116: 108 | B116: 4504 | C116: Impuestos, contribuciones y multas | D116: 25540.819 | E116: 34859.729 | F116: 65666.113 | G116: 27240.952 | H116: 153307.61 | I116: 11685.392 | J116: 23550.574 | K116: 5018.702 | L116: 20237.981 | M116: 4631.4813 | N116: 18893.758 | O116: 3741.204 | P116: 4415.6913 | Q116: 5073.971 | R116: 97248.755 | S116: 2780.9693 | T116: 993.94932 | U116: 396.16356 | V116: 259.37021 | W116: 848.47941 | X116: 192.44434 | Y116: 523.83112 | Z116: 288.38869 | AA116: 504.52677 | AB116: 940.03732 | AC116: 237.19254 | AD116: 7965.3526 | AE116: 258521.72 | AF116: 23912.46 | AG116: 25128.833 | AH116: 0 | AI116: 1265.5504 | AJ116: 208214.88
A117: 109 | B117: 4505 | C117: Depreciaciones | D117: 7354.223 | E117: 9042.5173 | F117: 15372.887 | G117: 4573.1237 | H117: 36342.751 | I117: 1839.3479 | J117: 2970.7083 | K117: 160.845 | L117: 1860.4316 | M117: 760.94058 | N117: 3232.3684 | O117: 652.12066 | P117: 1518.3602 | Q117: 1101.5173 | R117: 14096.64 | S117: 488.3044 | T117: 284.39798 | U117: 222.7417 | V117: 53.26103 | W117: 276.05158 | X117: 173.38825 | Y117: 194.74277 | Z117: 17.32442 | AA117: 172.92689 | AB117: 301.02593 | AC117: 132.3871 | AD117: 2316.552 | AE117: 52755.943 | AF117: 3393.2134 | AG117: 2674.6332 | AH117: 0 | AI117: 500.05676 | AJ117: 46188.039
A118: 110 | B118: 4506 | C118: Amortizaciones | D118: 7870.3123 | E118: 8628.5987 | F118: 10251.935 | G118: 6492.3526 | H118: 33243.198 | I118: 1450.6321 | J118: 2346.7562 | K118: 34.616 | L118: 356.49962 | M118: 1882.7132 | N118: 2360.5927 | O118: 125.07796 | P118: 808.19229 | Q118: 590.98629 | R118: 9956.0664 | S118: 234.15133 | T118: 160.47915 | U118: 131.46594 | V118: 165.96427 | W118: 58.03101 | X118: 79.28277 | Y118: 94.85287 | Z118: 74.8243 | AA118: 451.51156 | AB118: 176.85707 | AC118: 93.99779 | AD118: 1721.4181 | AE118: 44920.683 | AF118: 2395.2087 | AG118: 2405.1771 | AH118: 0 | AI118: 640.36222 | AJ118: 39479.935
A119: 111 | B119: 4507 | C119: Otros gastos | D119: 8888.0568 | E119: 20425.093 | F119: 70188.132 | G119: 10776.643 | H119: 110277.92 | I119: 3301.5038 | J119: 12557.828 | K119: 287.57 | L119: 6018.3056 | M119: 3686.7039 | N119: 15509.202 | O119: 1270.6795 | P119: 1448.0118 | Q119: 2341.8856 | R119: 46421.69 | S119: 1764.776 | T119: 529.0976 | U119: 304.06169 | V119: 105.7589 | W119: 1271.6058 | X119: 284.00524 | Y119: 467.07266 | Z119: 47.99976 | AA119: 878.17699 | AB119: 420.06061 | AC119: 263.61651 | AD119: 6336.2317 | AE119: 163035.85 | AF119: 15796.772 | AG119: 9810.7684 | AH119: 0 | AI119: 1608.8662 | AJ119: 135819.44
A120: 112 | B120: MARGEN DE INTERMEDIACIÓN | C120: MARGEN DE INTERMEDIACIÓN | D120: 49132.913 | E120: -33373.782 | F120: 3342.7026 | G120: 4330.8423 | H120: 23432.676 | I120: 5090.12 | J120: 31055.75 | K120: -4521.841 | L120: 7201.4701 | M120: 8848.7658 | N120: 40947.777 | O120: 2825.0482 | P120: 2871.9129 | Q120: 3805.7775 | R120: 98124.781 | S120: -4444.5894 | T120: -727.14813 | U120: 154.57562 | V120: 38.20279 | W120: 981.98388 | X120: -1700.9366 | Y120: -6965.0477 | Z120: -576.03431 | AA120: -780.38592 | AB120: -2874.8844 | AC120: 412.44126 | AD120: -16481.823 | AE120: 105075.63 | AF120: 36425.936 | AG120: 16088.439 | AH120: 0 | AI120: -7332.9924 | AJ120: 59894.252
A122: 114 | B122: 55 | C122: OTROS INGRESOS OPERACIONALES | D122: 466.11774 | E122: 8365.5048 | F122: 57719.399 | G122: 7543.4603 | H122: 74094.482 | I122: 1864.5113 | J122: 3616.7489 | K122: 369.604 | L122: 17234.78 | M122: 48.97346 | N122: 757.4206 | O122: 304.11499 | P122: 23.91845 | Q122: 3118.3662 | R122: 27338.438 | S122: 285.7429 | T122: 9.27524 | U122: 0 | V122: 140.69153 | W122: 0 | X122: 63.26893 | Y122: 1992.2962 | Z122: 0 | AA122: 1468.2632 | AB122: 145.27851 | AC122: 0 | AD122: 4104.8165 | AE122: 105537.74 | AF122: 1127.0246 | AG122: 17424.445 | AH122: 0 | AI122: 3460.5594 | AJ122: 83525.708
A123: 115 | B123: 5501 | C123: Utilidades en acciones y participaciones | D123: 466.11774 | E123: 540.52086 | F123: 41325.886 | G123: 3169.9869 | H123: 45502.512 | I123: 498.38453 | J123: 619.88625 | K123: 118.523 | L123: 12544.596 | M123: 0 | N123: 740.20676 | O123: 188.49682 | P123: 0 | Q123: 0 | R123: 14710.093 | S123: 0 | T123: 9.27524 | U123: 0 | V123: 0 | W123: 0 | X123: 0 | Y123: 0 | Z123: 0 | AA123: 0 | AB123: 0 | AC123: 0 | AD123: 9.27524 | AE123: 60221.88 | AF123: 858.72976 | AG123: 12544.596 | AH123: 0 | AI123: 0 | AJ123: 46818.555
A124: 116 | B124: 5502 | C124: Utilidad en venta de bienes realizables y recuperados | D124: 0 | E124: 0 | F124: 0 | G124: 0 | H124: 0 | I124: 0 | J124: 0 | K124: 0 | L124: 0 | M124: 0 | N124: 0 | O124: 0 | P124: 0 | Q124: 0 | R124: 0 | S124: 0 | T124: 0 | U124: 0 | V124: 0 | W124: 0 | X124: 0 | Y124: 0 | Z124: 0 | AA124: 0 | AB124: 4.01686 | AC124: 0 | AD124: 4.01686 | AE124: 4.01686 | AF124: 0 | AG124: 0 | AH124: 0 | AI124: 0 | AJ124: 4.01686
A125: 117 | B125: 5503 | C125: Dividendos por certificados de aportación | D125: 0 | E125: 0 | F125: 0 | G125: 0 | H125: 0 | I125: 0 | J125: 0 | K125: 0 | L125: 0 | M125: 0 | N125: 0 | O125: 0 | P125: 0 | Q125: 0 | R125: 0 | S125: 0 | T125: 0 | U125: 0 | V125: 0 | W125: 0 | X125: 0 | Y125: 0 | Z125: 0 | AA125: 0 | AB125: 0 | AC125: 0 | AD125: 0 | AE125: 0 | AF125: 0 | AG125: 0 | AH125: 0 | AI125: 0 | AJ125: 0
A126: 118 | B126: 5504 | C126: Convenios | D126: 0 | E126: 0 | F126: 0 | G126: 0 | H126: 0 | I126: 0 | J126: 0 | K126: 0 | L126: 0 | M126: 0 | N126: 0 | O126: 0 | P126: 0 | Q126: 0 | R126: 0 | S126: 0 | T126: 0 | U126: 0 | V126: 0 | W126: 0 | X126: 0 | Y126: 0 | Z126: 0 | AA126: 0 | AB126: 0 | AC126: 0 | AD126: 0 | AE126: 0 | AF126: 0 | AG126: 0 | AH126: 0 | AI126: 0 | AJ126: 0
A127: 119 | B127: 5505 | C127: Ingresos por subsidios realizados | D127: 0 | E127: 0 | F127: 0 | G127: 0 | H127: 0 | I127: 0 | J127: 0 | K127: 0 | L127: 0 | M127: 0 | N127: 0 | O127: 0 | P127: 0 | Q127: 0 | R127: 0 | S127: 0 | T127: 0 | U127: 0 | V127: 0 | W127: 0 | X127: 0 | Y127: 0 | Z127: 0 | AA127: 0 | AB127: 0 | AC127: 0 | AD127: 0 | AE127: 0 | AF127: 0 | AG127: 0 | AH127: 0 | AI127: 0 | AJ127: 0
A128: 120 | B128: 5506 | C128: Ingresos por subsidios recuperados | D128: 0 | E128: 0 | F128: 0 | G128: 0 | H128: 0 | I128: 0 | J128: 0 | K128: 0 | L128: 0 | M128: 0 | N128: 0 | O128: 0 | P128: 0 | Q128: 0 | R128: 0 | S128: 0 | T128: 0 | U128: 0 | V128: 0 | W128: 0 | X128: 0 | Y128: 0 | Z128: 0 | AA128: 0 | AB128: 0 | AC128: 0 | AD128: 0 | AE128: 0 | AF128: 0 | AG128: 0 | AH128: 0 | AI128: 0 | AJ128: 0
A129: 121 | B129: 5507 | C129: Ingresos por demora en transferencias | D129: 0 | E129: 0 | F129: 0 | G129: 0 | H129: 0 | I129: 0 | J129: 0 | K129: 0 | L129: 0 | M129: 0 | N129: 0 | O129: 0 | P129: 0 | Q129: 0 | R129: 0 | S129: 0 | T129: 0 | U129: 0 | V129: 0 | W129: 0 | X129: 0 | Y129: 0 | Z129: 0 | AA129: 0 | AB129: 0 | AC129: 0 | AD129: 0 | AE129: 0 | AF129: 0 | AG129: 0 | AH129: 0 | AI129: 0 | AJ129: 0
A130: 122 | B130: 5590 | C130: Otros | D130: 0 | E130: 7824.984 | F130: 16393.513 | G130: 4373.4734 | H130: 28591.971 | I130: 1366.1268 | J130: 2996.8627 | K130: 251.081 | L130: 4690.1837 | M130: 48.97346 | N130: 17.21384 | O130: 115.61817 | P130: 23.91845 | Q130: 3118.3662 | R130: 12628.344 | S130: 285.7429 | T130: 0 | U130: 0 | V130: 140.69153 | W130: 0 | X130: 63.26893 | Y130: 1992.2962 | Z130: 0 | AA130: 1468.2632 | AB130: 141.26165 | AC130: 0 | AD130: 4091.5244 | AE130: 45311.839 | AF130: 268.29484 | AG130: 4879.8487 | AH130: 0 | AI130: 3460.5594 | AJ130: 36703.136
A131: 123 | B131: 46 | C131: OTRAS PÉRDIDAS OPERACIONALES | D131: 149.29214 | E131: 1461.3604 | F131: 54098.94 | G131: 2113.4898 | H131: 57823.082 | I131: 0.03539 | J131: 139.33939 | K131: 7.015 | L131: 8837.2766 | M131: 472.13003 | N131: 257.8508 | O131: 127.32451 | P131: 0 | Q131: 6454.6097 | R131: 16295.581 | S131: 0 | T131: 27.31152 | U131: 5e-05 | V131: 6.62129 | W131: 0.4 | X131: 0.73714 | Y131: 0 | Z131: 0 | AA131: 291.4505 | AB131: 0.1312 | AC131: 0 | AD131: 326.6517 | AE131: 74445.315 | AF131: 264.8658 | AG131: 9316.0279 | AH131: 0 | AI131: 291.4505 | AJ131: 64572.971
A132: 124 | B132: 4601 | C132: Pérdida en acciones y participaciones | D132: 0 | E132: 70.16684 | F132: 44221.459 | G132: 2112.5868 | H132: 46404.213 | I132: 0 | J132: 83.49594 | K132: 0 | L132: 8837.2766 | M132: 0 | N132: 257.8508 | O132: 114.87531 | P132: 0 | Q132: 0 | R132: 9293.4987 | S132: 0 | T132: 4.55646 | U132: 0 | V132: 0 | W132: 0 | X132: 0 | Y132: 0 | Z132: 0 | AA132: 0 | AB132: 0 | AC132: 0 | AD132: 4.55646 | AE132: 55702.268 | AF132: 257.8508 | AG132: 8837.2766 | AH132: 0 | AI132: 0 | AJ132: 46607.14
A133: 125 | B133: 4602 | C133: Pérdida en venta de bienes realizables y recuperados | D133: 143.95998 | E133: 17.80676 | F133: 12.987 | G133: 0.90301 | H133: 175.65675 | I133: 0 | J133: 0 | K133: 0 | L133: 0 | M133: 0.2297 | N133: 0 | O133: 0 | P133: 0 | Q133: 0 | R133: 0.2297 | S133: 0 | T133: 0 | U133: 0 | V133: 6.60911 | W133: 0 | X133: 0.73714 | Y133: 0 | Z133: 0 | AA133: 0 | AB133: 0 | AC133: 0 | AD133: 7.34625 | AE133: 183.2327 | AF133: 0 | AG133: 6.83881 | AH133: 0 | AI133: 0 | AJ133: 176.39389
A134: 126 | B134: 4690 | C134: Otras | D134: 5.33216 | E134: 1373.3868 | F134: 9864.4938 | G134: 0 | H134: 11243.213 | I134: 0.03539 | J134: 55.84345 | K134: 7.015 | L134: 0 | M134: 471.90033 | N134: 0 | O134: 12.4492 | P134: 0 | Q134: 6454.6097 | R134: 7001.8531 | S134: 0 | T134: 22.75506 | U134: 5e-05 | V134: 0.01218 | W134: 0.4 | X134: 0 | Y134: 0 | Z134: 0 | AA134: 291.4505 | AB134: 0.1312 | AC134: 0 | AD134: 314.74899 | AE134: 18559.815 | AF134: 7.015 | AG134: 471.91251 | AH134: 0 | AI134: 291.4505 | AJ134: 17789.437
A135: 127 | B135: MARGEN OPERACIONAL | C135: MARGEN OPERACIONAL | D135: 49449.739 | E135: -26469.638 | F135: 6963.1623 | G135: 9760.8127 | H135: 39704.076 | I135: 6954.596 | J135: 34533.16 | K135: -4159.252 | L135: 15598.973 | M135: 8425.6092 | N135: 41447.346 | O135: 3001.8387 | P135: 2895.8314 | Q135: 469.53402 | R135: 109167.64 | S135: -4158.8465 | T135: -745.18441 | U135: 154.57557 | V135: 172.27303 | W135: 981.58388 | X135: -1638.4048 | Y135: -4972.7515 | Z135: -576.03431 | AA135: 396.4268 | AB135: -2729.7371 | AC135: 412.44126 | AD135: -12703.658 | AE135: 136168.06 | AF135: 37288.094 | AG135: 24196.856 | AH135: 0 | AI135: -4163.8835 | AJ135: 78846.989
A137: 129 | B137: 56 | C137: OTROS INGRESOS | D137: 13084.806 | E137: 57709.892 | F137: 96961.15 | G137: 27276.418 | H137: 195032.27 | I137: 8727.0311 | J137: 1646.5386 | K137: 9881.607 | L137: 22806.425 | M137: 1968.9664 | N137: 6550.1016 | O137: 1575.2307 | P137: 1495.7731 | Q137: 3945.4722 | R137: 58597.146 | S137: 4183.3149 | T137: 875.60046 | U137: 166.12916 | V137: 70.57603 | W137: 134.28858 | X137: 305.1757 | Y137: 821.04377 | Z137: 669.34151 | AA137: 650.17842 | AB137: 5665.5397 | AC137: 901.83468 | AD137: 14443.023 | AE137: 268072.44 | AF137: 16431.709 | AG137: 24845.967 | AH137: 0 | AI137: 2373.0569 | AJ137: 224421.7
A138: 130 | B138: 5601 | C138: Utilidad en venta de bienes | D138: 92.14237 | E138: 213.68479 | F138: 13230.719 | G138: 5.22141 | H138: 13541.768 | I138: 108.68142 | J138: 0 | K138: 0 | L138: 0.43563 | M138: 1.28175 | N138: 5.96131 | O138: 5.39548 | P138: 0.42979 | Q138: 16.08014 | R138: 138.26552 | S138: 8.12927 | T138: 2.40937 | U138: 0 | V138: 25.324 | W138: 0 | X138: 0 | Y138: 0 | Z138: 0 | AA138: 0.07143 | AB138: 3.57143 | AC138: 48.07148 | AD138: 87.57698 | AE138: 13767.61 | AF138: 5.96131 | AG138: 27.04138 | AH138: 0 | AI138: 48.14291 | AJ138: 13686.465
A139: 131 | B139: 5602 | C139: Utilidad en venta de acciones y participaciones | D139: 0 | E139: 0 | F139: 0 | G139: 0 | H139: 0 | I139: 0 | J139: 0 | K139: 0 | L139: 0 | M139: 0 | N139: 0 | O139: 0 | P139: 0 | Q139: 0 | R139: 0 | S139: 0 | T139: 0 | U139: 0 | V139: 0 | W139: 0 | X139: 0 | Y139: 0 | Z139: 0 | AA139: 0 | AB139: 0 | AC139: 0 | AD139: 0 | AE139: 0 | AF139: 0 | AG139: 0 | AH139: 0 | AI139: 0 | AJ139: 0
A140: 132 | B140: 5603 | C140: Arrendamientos | D140: 2 | E140: 100.03591 | F140: 1038.3994 | G140: 737.40495 | H140: 1877.8403 | I140: 47.96192 | J140: 0 | K140: 0 | L140: 61.49008 | M140: 0 | N140: 146.79136 | O140: 16.01787 | P140: 0 | Q140: 0 | R140: 272.26123 | S140: 0 | T140: 165.29628 | U140: 0 | V140: 0 | W140: 3.4196 | X140: 15 | Y140: 0 | Z140: 0 | AA140: 0 | AB140: 0 | AC140: 0 | AD140: 183.71588 | AE140: 2333.8174 | AF140: 146.79136 | AG140: 61.49008 | AH140: 0 | AI140: 0 | AJ140: 2125.5359
A141: 133 | B141: 5604 | C141: Recuperaciones de activos financieros | D141: 12780.587 | E141: 43442.587 | F141: 71192.955 | G141: 22812.568 | H141: 150228.7 | I141: 8530.6879 | J141: 1378.0988 | K141: 7434.561 | L141: 21382.327 | M141: 1691.351 | N141: 3466.4804 | O141: 1278.7104 | P141: 1017.3517 | Q141: 3545.2813 | R141: 49724.85 | S141: 4133.071 | T141: 355.837 | U141: 166.12916 | V141: 44.20241 | W141: 120.34521 | X141: 272.29845 | Y141: 821.04377 | Z141: 669.34151 | AA141: 347.80091 | AB141: 5492.8575 | AC141: 367.61428 | AD141: 12790.541 | AE141: 212744.09 | AF141: 10901.041 | AG141: 23117.881 | AH141: 0 | AI141: 1536.459 | AJ141: 177188.71
A142: 134 | B142: 5690 | C142: Otros | D142: 210.077 | E142: 13953.584 | F142: 11499.076 | G142: 3721.2246 | H142: 29383.962 | I142: 39.69982 | J142: 268.4398 | K142: 2447.046 | L142: 1362.1718 | M142: 276.33363 | N142: 2930.8685 | O142: 275.107 | P142: 477.9916 | Q142: 384.11078 | R142: 8461.769 | S142: 42.11457 | T142: 352.05781 | U142: 0 | V142: 1.04962 | W142: 10.52377 | X142: 17.87725 | Y142: 0 | Z142: 0 | AA142: 302.30608 | AB142: 169.11084 | AC142: 486.14892 | AD142: 1381.1889 | AE142: 39226.92 | AF142: 5377.9145 | AG142: 1639.555 | AH142: 0 | AI142: 788.455 | AJ142: 31420.995
A143: 135 | B143: 47 | C143: OTROS GASTOS Y PÉRDIDAS | D143: 3494.0235 | E143: 13875.824 | F143: 11975.724 | G143: 513.19661 | H143: 29858.768 | I143: 4017.6627 | J143: 293.0387 | K143: 291.808 | L143: 2267.7359 | M143: 271.74943 | N143: 6658.9425 | O143: 25.86687 | P143: 623.85395 | Q143: 691.61059 | R143: 15142.269 | S143: 71.6609 | T143: 82.0063 | U143: 250.6676 | V143: 1.30813 | W143: 1.95659 | X143: 0 | Y143: 1965.1252 | Z143: 0 | AA143: 239.39684 | AB143: 808.83247 | AC143: 121.58748 | AD143: 3542.5415 | AE143: 48543.578 | AF143: 6950.7505 | AG143: 2540.7934 | AH143: 0 | AI143: 2326.1096 | AJ143: 36725.924
A144: 136 | B144: 4701 | C144: Pérdida en venta de bienes | D144: 106.62043 | E144: 0 | F144: 284.77728 | G144: 0.02155 | H144: 391.41926 | I144: 18.86532 | J144: 0 | K144: 0 | L144: 20.52682 | M144: 0 | N144: 81.4255 | O144: 0 | P144: 0 | Q144: 1.39007 | R144: 122.20771 | S144: 7.79668 | T144: 0 | U144: 0 | V144: 0 | W144: 0 | X144: 0 | Y144: 4.97276 | Z144: 0 | AA144: 0 | AB144: 4.76323 | AC144: 0 | AD144: 17.53267 | AE144: 531.15964 | AF144: 81.4255 | AG144: 20.52682 | AH144: 0 | AI144: 4.97276 | AJ144: 424.23456
A145: 137 | B145: 4702 | C145: Pérdida en venta de acciones y participaciones | D145: 0 | E145: 0 | F145: 0 | G145: 0 | H145: 0 | I145: 0 | J145: 0 | K145: 0 | L145: 0 | M145: 0 | N145: 0 | O145: 0 | P145: 0 | Q145: 0 | R145: 0 | S145: 0 | T145: 0 | U145: 0 | V145: 0 | W145: 0 | X145: 0 | Y145: 0 | Z145: 0 | AA145: 0 | AB145: 0 | AC145: 0 | AD145: 0 | AE145: 0 | AF145: 0 | AG145: 0 | AH145: 0 | AI145: 0 | AJ145: 0
A146: 138 | B146: 4703 | C146: Intereses y comisiones devengados en ejercicios anteriores | D146: 1560.4133 | E146: 1669.2939 | F146: 11690.943 | G146: 478.07243 | H146: 15398.723 | I146: 1657.8128 | J146: 222.98242 | K146: 151.47 | L146: 2061.8137 | M146: 264.46546 | N146: 451.86385 | O146: 0.70215 | P146: 40.31512 | Q146: 690.1368 | R146: 5541.5622 | S146: 63.70859 | T146: 82.0063 | U146: 250.6676 | V146: 0.90288 | W146: 1.95604 | X146: 0 | Y146: 85.24007 | Z146: 0 | AA146: 7.00106 | AB146: 761.20795 | AC146: 109.53138 | AD146: 1362.2219 | AE146: 22302.507 | AF146: 603.33385 | AG146: 2327.182 | AH146: 0 | AI146: 201.77251 | AJ146: 19170.219
A147: 139 | B147: 4790 | C147: Otros | D147: 1826.9897 | E147: 12206.53 | F147: 0.003 | G147: 35.10263 | H147: 14068.625 | I147: 2340.9846 | J147: 70.05628 | K147: 140.338 | L147: 185.39538 | M147: 7.28397 | N147: 6125.6532 | O147: 25.16472 | P147: 583.53883 | Q147: 0.08372 | R147: 9478.4986 | S147: 0.15563 | T147: 0 | U147: 0 | V147: 0.40525 | W147: 0.00055 | X147: 0 | Y147: 1874.9124 | Z147: 0 | AA147: 232.39578 | AB147: 42.86129 | AC147: 12.0561 | AD147: 2162.787 | AE147: 25709.911 | AF147: 6265.9911 | AG147: 193.0846 | AH147: 0 | AI147: 2119.3643 | AJ147: 17131.471
A148: 140 | B148: GANANCIA O (PÉRDIDA) ANTES DE IMPUESTOS | C148: GANANCIA O (PÉRDIDA) ANTES DE IMPUESTOS | D148: 59040.522 | E148: 17364.431 | F148: 91948.588 | G148: 36524.035 | H148: 204877.58 | I148: 11663.964 | J148: 35886.66 | K148: 5430.547 | L148: 36137.662 | M148: 10122.826 | N148: 41338.505 | O148: 4551.2026 | P148: 3767.7505 | Q148: 3723.3957 | R148: 152622.51 | S148: -47.1925 | T148: 48.40975 | U148: 70.03713 | V148: 241.54093 | W148: 1113.9159 | X148: -1333.2291 | Y148: -6116.833 | Z148: 93.3072 | AA148: 807.20838 | AB148: 2126.9702 | AC148: 1192.6885 | AD148: -1803.1767 | AE148: 355696.91 | AF148: 46769.052 | AG148: 46502.029 | AH148: 0 | AI148: -4116.9361 | AJ148: 266542.77
A150: 142 | B150: 48 | C150: IMPUESTOS Y PARTICIPACIÓN A EMPLEADOS | D150: 18070.067 | E150: 5550 | F150: 29184.634 | G150: 12495 | H150: 65299.701 | I150: 5031.7864 | J150: 11855 | K150: 2252.949 | L150: 12336.882 | M150: 3472 | N150: 15042.505 | O150: 1662.6928 | P150: 1541.6305 | Q150: 1500 | R150: 54695.445 | S150: 612.73062 | T150: 18.75479 | U150: 25.4881 | V150: 0 | W150: 403.7945 | X150: 0 | Y150: 0 | Z150: 0 | AA150: 385.73721 | AB150: 825.26444 | AC150: 462.83244 | AD150: 2734.6021 | AE150: 122729.75 | AF150: 17295.454 | AG150: 15808.882 | AH150: 0 | AI150: 848.56965 | AJ150: 88776.843
...

Sheet BALANCE %
B2: ESTADO DE SITUACIÓN CONSOLIDADO
B3: SISTEMA DE BANCOS PRIVADOS
B4: 44439
B5: (en porcentajes)
AF6: BANCA ESPECIALIZADA
A7: 1 | B7: CODIGO | C7: CUENTA | D7: BP GUAYAQUIL | E7: BP PACIFICO | F7: BP PICHINCHA | G7: BP PRODUBANCO | H7: BANCOS PRIVADOS GRANDES | I7: BP AUSTRO | J7: BP BOLIVARIANO | K7: BP CITIBANK | L7: BP DINERS | M7: BP GENERAL RUMIÑAHUI | N7: BP INTERNACIONAL | O7: BP LOJA | P7: BP MACHALA | Q7: BP SOLIDARIO | R7: BANCOS PRIVADOS MEDIANOS | S7: BP PROCREDIT | T7: BP AMAZONAS | U7: BP COMERCIAL DE MANABI | V7: BP LITORAL | W7: BP COOPNACIONAL | X7: BP CAPITAL | Y7: BP FINCA S.A. | Z7: BP DELBANK | AA7: BP D MIRO S.A. | AB7: BP BANCODESARROLLO | AC7: BP VISIONFUND ECUADOR S.A. | AD7: BANCOS PRIVADOS PEQUEÑOS | AE7: TOTAL BANCOS PRIVADOS | AF7: BANCOS PRIVADOS COMERCIALES | AG7: BANCOS PRIVADOS CONSUMO | AH7: BANCOS PRIVADOS VIVIENDA | AI7: BANCOS PRIVADOS DE MICROCRÉDITO | AJ7: BANCA MULTIPLE
A8: 2 | C8: ACTIVO
A9: 3 | B9: 11 | C9: FONDOS DISPONIBLES | D9: 0.14124837 | E9: 0.17645495 | F9: 0.13763707 | G9: 0.16174999 | H9: 0.15117414 | I9: 0.19301642 | J9: 0.21514263 | K9: 0.47099807 | L9: 0.032676797 | M9: 0.17065795 | N9: 0.17973773 | O9: 0.24873969 | P9: 0.17927079 | Q9: 0.093772097 | R9: 0.17954961 | S9: 0.12233575 | T9: 0.11595506 | U9: 0.17358297 | V9: 0.052915424 | W9: 0.30934863 | X9: 0.099456918 | Y9: 0.10019538 | Z9: 0.21229612 | AA9: 0.061446226 | AB9: 0.1091621 | AC9: 0.050504332 | AD9: 0.13369396 | AE9: 0.1600892 | AF9: 0.21868224 | AG9: 0.073950721 | AH9: #DIV/0! | AI9: 0.070267648 | AJ9: 0.1607277
A10: 3 | B10: 12 | C10: OPERACIONES INTERBANCARIAS | D10: 0 | E10: 0 | F10: 0 | G10: 0 | H10: 0 | I10: 0 | J10: 0 | K10: 0 | L10: 0 | M10: 0 | N10: 0 | O10: 0 | P10: 0 | Q10: 0 | R10: 0 | S10: 0 | T10: 0 | U10: 0 | V10: 0 | W10: 0 | X10: 0 | Y10: 0 | Z10: 0 | AA10: 0 | AB10: 0 | AC10: 0 | AD10: 0 | AE10: 0 | AF10: 0 | AG10: 0 | AH10: #DIV/0! | AI10: 0 | AJ10: 0
A11: 3 | B11: 13 | C11: INVERSIONES | D11: 0.18743984 | E11: 0.13950554 | F11: 0.21372311 | G11: 0.13787769 | H11: 0.17877042 | I11: 0.18870505 | J11: 0.15631716 | K11: 0.21033271 | L11: 0.097945219 | M11: 0.14892316 | N11: 0.17575636 | O11: 0.10916456 | P11: 0.18320417 | Q11: 0.15704952 | R11: 0.15909468 | S11: 0.052902191 | T11: 0.2585979 | U11: 0.14892794 | V11: 0.14179635 | W11: 0.20621135 | X11: 0.13490603 | Y11: 0.092750894 | Z11: 0.15581305 | AA11: 0.19681184 | AB11: 0.10955305 | AC11: 0.021810753 | AD11: 0.12888905 | AE11: 0.17048727 | AF11: 0.18037957 | AG11: 0.11361837 | AH11: #DIV/0! | AI11: 0.11240982 | AJ11: 0.17422592
A12: 3 | B12: 0 | C12: INVERSIONES DEL SECTOR PRIVADO | D12: 0.031844765 | E12: 0.038016623 | F12: 0.040015705 | G12: 0.056495587 | H12: 0.040929415 | I12: 0.088182809 | J12: 0.051857193 | K12: 0.012512488 | L12: 0.0073696415 | M12: 0.056282704 | N12: 0.058616775 | O12: 0.05154884 | P12: 0.037285006 | Q12: 0.10270568 | R12: 0.052767301 | S12: 0.012365853 | T12: 0.11434113 | U12: 0.081864708 | V12: 0.063585162 | W12: 0.13357709 | X12: 0.03539391 | Y12: 0.046005495 | Z12: 0.10378516 | AA12: 0.16248768 | AB12: 0.04600524 | AC12: 0.0077364139 | AD12: 0.064095871 | AE12: 0.045680983 | AF12: 0.052452156 | AG12: 0.022572884 | AH12: #DIV/0! | AI12: 0.080231166 | AJ12: 0.046466626
A13: 3 | B13: 0 | C13: INVERSIONES DEL SECTOR PUBLICO | D13: 0.15660011 | E13: 0.086754455 | F13: 0.17014417 | G13: 0.078127282 | H13: 0.13276428 | I13: 0.087151991 | J13: 0.092573717 | K13: 0.19782022 | L13: 0.070539646 | M13: 0.099222967 | N13: 0.087610973 | O13: 0.05745887 | P13: 0.14444331 | Q13: 0.054343845 | R13: 0.091846475 | S13: 0.039719332 | T13: 0.13815924 | U13: 0.067544853 | V13: 0.07821119 | W13: 0.073205833 | X13: 0.084812863 | Y13: 0.0467454 | Z13: 0.050543551 | AA13: 0.034324163 | AB13: 0.063547808 | AC13: 0.014074339 | AD13: 0.063363603 | AE13: 0.11670221 | AF13: 0.10234709 | AG13: 0.079160017 | AH13: #DIV/0! | AI13: 0.032178654 | AJ13: 0.12191305
A14: 3 | B14: 1307 | C14: De disponibilidad restringida | D14: 0 | E14: 0.015248991 | F14: 0.013040703 | G14: 0.0032801122 | H14: 0.0092517778 | I14: 0.013488306 | J14: 0.012171588 | K14: 0 | L14: 0.020035931 | M14: 0.00042877912 | N14: 0.029529173 | O14: 0.00016510188 | P14: 0.0014758522 | Q14: 0 | R14: 0.014974395 | S14: 0.00081700632 | T14: 0.0060975337 | U14: 0.00083932549 | V14: 0 | W14: 0 | X14: 0.01469926 | Y14: 0 | Z14: 0.0015624648 | AA14: 0 | AB14: 0 | AC14: 0 | AD14: 0.0015443324 | AE14: 0.010907979 | AF14: 0.025580818 | AG14: 0.013970744 | AH14: #DIV/0! | AI14: 0 | AJ14: 0.0090504567
A15: 3 | B15: 1399 | C15: (Provisión para inversiones) | D15: -0.0010050274 | E15: -0.00051453149 | F15: -0.0094774587 | G15: -2.5292043e-05 | H15: -0.0041750497 | I15: -0.0001180603 | J15: -0.00028533587 | K15: 0 | L15: 0 | M15: -0.0070112928 | N15: -5.6143444e-07 | O15: -8.2550941e-06 | P15: 0 | Q15: 0 | R15: -0.00049349125 | S15: 0 | T15: 0 | U15: -0.0013209424 | V15: 0 | W15: -0.00057157923 | X15: 0 | Y15: 0 | Z15: -7.812324e-05 | AA15: 0 | AB15: 0 | AC15: 0 | AD15: -0.00011475889 | AE15: -0.0028038931 | AF15: -4.8636487e-07 | AG15: -0.0020852736 | AH15: #DIV/0! | AI15: 0 | AJ15: -0.0032042139
A16: 3 | B16: 14 | C16: CARTERA DE CRÉDITOS | D16: 0.61059468 | E16: 0.60237828 | F16: 0.54295488 | G16: 0.63430337 | H16: 0.58545412 | I16: 0.52676736 | J16: 0.58512691 | K16: 0.29234371 | L16: 0.80376003 | M16: 0.63809942 | N16: 0.5927639 | O16: 0.58597389 | P16: 0.58034894 | Q16: 0.69015856 | R16: 0.60512962 | S16: 0.78739349 | T16: 0.48935607 | U16: 0.50615559 | V16: 0.71725565 | W16: 0.45003407 | X16: 0.46297208 | Y16: 0.72627196 | Z16: 0.48392635 | AA16: 0.64881425 | AB16: 0.71865598 | AC16: 0.89393801 | AD16: 0.66291247 | AE16: 0.59467183 | AF16: 0.55259463 | AG16: 0.75348086 | AH16: #DIV/0! | AI16: 0.74575817 | AJ16: 0.58598033
A17: 3 | B17: 1401+1409+1417+1425+1433+1441+1449+1457+1465+149105+149205+149305+149405+149505+149605 | C17: CARTERA DE CRÉDITOS PRODUCTIVO | D17: 0.3290403 | E17: 0.2279986 | F17: 0.23494085 | G17: 0.41568574 | H17: 0.28393959 | I17: 0.29076119 | J17: 0.4365694 | K17: 0.3228733 | L17: 0.051828857 | M17: 0.0700818 | N17: 0.51408877 | O17: 0.20584509 | P17: 0.3850483 | Q17: 4.376933e-05 | R17: 0.32683301 | S17: 0.62335457 | T17: 0.24804809 | U17: 0.26488302 | V17: 0.14510652 | W17: 0.4121994 | X17: 0.035206906 | Y17: 0 | Z17: 0.31045801 | AA17: 0 | AB17: 0.089642195 | AC17: 0 | AD17: 0.322604 | AE17: 0.2996219 | AF17: 0.48852129 | AG17: 0.058345568 | AH17: #DIV/0! | AI17: 0 | AJ17: 0.29889133
A18: 3 | B18: 1402+1410+1418+1426+1434+1442+1450+1458+1466+149120+149220+149320+149420+149520+149620 | C18: CARTERA DE CREDITOS CONSUMO | D18: 0.23884982 | E18: 0.27145592 | F18: 0.21515626 | G18: 0.19878705 | H18: 0.2292145 | I18: 0.24570082 | J18: 0.15361448 | K18: 0 | L18: 0.85408688 | M18: 0.52780158 | N18: 0.08039953 | O18: 0.27130734 | P18: 0.18199357 | Q18: 0.34194441 | R18: 0.27284656 | S18: 0.007924312 | T18: 0.24917321 | U18: 0.15663732 | V18: 0.58284368 | W18: 0.0044690231 | X18: 0.45443025 | Y18: 0.053851607 | Z18: 0.14085338 | AA18: 0 | AB18: 0.26790763 | AC18: 0.00034610524 | AD18: 0.1087909 | AE18: 0.23975247 | AF18: 0.069649284 | AG18: 0.75388051 | AH18: #DIV/0! | AI18: 0.01687941 | AJ18: 0.2206182
A19: 3 | B19: 1403+1411+1419+1427+1435+1443+1451+1459+1467+149130+149230+149330+149430+149530+149630 | C19: CARTERA DE CRÉDITOS INMOBILIARIO | D19: 0.034424215 | E19: 0.077392246 | F19: 0.059676212 | G19: 0.046247912 | H19: 0.05627021 | I19: 0.022392176 | J19: 0.01754508 | K19: 0 | L19: 0 | M19: 0.098026849 | N19: 0.02742123 | O19: 0.060419981 | P19: 0.021382827 | Q19: 8.2702619e-05 | R19: 0.023258947 | S19: 0.042705437 | T19: 0.006456835 | U19: 0.00042732663 | V19: 0.0031527066 | W19: 0.0008441178 | X19: 3.1729871e-08 | Y19: 0 | Z19: 0.056485133 | AA19: 0 | AB19: 0.056137759 | AC19: 0 | AD19: 0.02358516 | AE19: 0.044101675 | AF19: 0.023754729 | AG19: 0.029191567 | AH19: #DIV/0! | AI19: 0 | AJ19: 0.047938312
A20: 3 | B20: 1404+1412+1420+1428+1436+1444+1452+1460+1468+149140+149240+149340+149440+149540+149640 | C20: CARTERA DE CRÉDITOS MICROCRÉDITO | D20: 0.035735503 | E20: 0.0015565858 | F20: 0.1036837 | G20: 0.003494452 | H20: 0.05015946 | I20: 0.0028610674 | J20: 0 | K20: 0 | L20: 0 | M20: 1.7778647e-08 | N20: 0.00073796463 | O20: 0.10903239 | P20: 0.006378142 | Q20: 0.44544087 | R20: 0.025796153 | S20: 0.13094544 | T20: 0.00073498596 | U20: 0.12442689 | V20: 0.041300945 | W20: 0.046613755 | X20: 0.025498013 | Y20: 0.73910313 | Z20: 0.0038424909 | AA20: 0.70978885 | AB20: 0.3644258 | AC20: 0.96380961 | AD20: 0.24100417 | AE20: 0.048464409 | AF20: 0.00063929115 | AG20: 0.0004817375 | AH20: #DIV/0! | AI20: 0.79437729 | AJ20: 0.052425356
A21: 3 | B21: 1408+1416+1424+1432+1440+1448+1456+1464+1472+149135+149235+149335+149435+149535+149635 | C21: CARTERA DE CRÉDITOS VIVIENDA DE INTERÉS SOCIAL Y PÚBLICO | D21: 0 | E21: 0.0078426533 | F21: 0.00066042799 | G21: 0 | H21: 0.0019932259 | I21: 0 | J21: 0 | K21: 0 | L21: 0 | M21: 0.0032527156 | N21: 0.00010084352 | O21: 0 | P21: 0 | Q21: 0 | R21: 0.00021384556 | S21: 0 | T21: 0 | U21: 0 | V21: 0 | W21: 0 | X21: 0 | Y21: 0 | Z21: 0 | AA21: 0 | AB21: 0 | AC21: 0 | AD21: 0 | AE21: 0.0013294713 | AF21: 8.7359703e-05 | AG21: 0.00096741103 | AH21: #DIV/0! | AI21: 0 | AJ21: 0.001510894
A22: 3 | B22: 1473+1475+1477+1479+1481+1483+1485+1487+1489+149150+149250+149350+149450+149550+149650 | C22: CARTERA DE CRÉDITOS EDUCATIVO | D22: 0.0004387019 | E22: 0.050186855 | F22: 0.0013141448 | G22: 7.1658334e-05 | H22: 0.011666367 | I22: 0 | J22: 0.00089865453 | K22: 0 | L22: 0 | M22: 0 | N22: 0 | O22: 0.00039353252 | P22: 0.0031664027 | Q22: 0 | R22: 0.00041052214 | S22: 0.00037856396 | T22: 0 | U22: 0 | V22: 0 | W22: 0 | X22: 0 | Y22: 0 | Z22: 0 | AA22: 0 | AB22: 0 | AC22: 0 | AD22: 0.00012510997 | AE22: 0.0075038205 | AF22: 0 | AG22: 0 | AH22: #DIV/0! | AI22: 0 | AJ22: 0.0090135926
A23: 3 | B23: 1474+1476+1478+1480+1482+1484+1486+1488+1490+149145+149245+149345+149445+149545+149645 | C23: CARTERA DE CRÉDITO INVERSIÓN PÚBLICA | D23: 0 | E23: 0 | F23: 0 | G23: 0 | H23: 0 | I23: 0 | J23: 0 | K23: 0 | L23: 0 | M23: 0 | N23: 0 | O23: 0 | P23: 0 | Q23: 0 | R23: 0 | S23: 0 | T23: 0 | U23: 0 | V23: 0 | W23: 0 | X23: 0 | Y23: 0 | Z23: 0 | AA23: 0 | AB23: 0 | AC23: 0 | AD23: 0 | AE23: 0 | AF23: 0 | AG23: 0 | AH23: #DIV/0! | AI23: 0 | AJ23: 0
A24: 3 | B24: 1499 | C24: (PROVISIONES PARA CRÉDITOS INCOBRABLES) | D24: -0.027893862 | E24: -0.034054581 | F24: -0.072476717 | G24: -0.029983439 | H24: -0.047789235 | I24: -0.034947904 | J24: -0.023500705 | K24: -0.030529595 | L24: -0.10215571 | M24: -0.061063545 | N24: -0.02998444 | O24: -0.061024437 | P24: -0.017620298 | Q24: -0.097353198 | R24: -0.044229411 | S24: -0.01791483 | T24: -0.015057054 | U24: -0.040218958 | V24: -0.055148192 | W24: -0.014092233 | X24: -0.052163114 | Y24: -0.066682774 | Z24: -0.027712655 | AA24: -0.060974597 | AB24: -0.059457408 | AC24: -0.070217708 | AD24: -0.033196872 | AE24: -0.046101913 | AF24: -0.030057333 | AG24: -0.089385935 | AH24: #DIV/0! | AI24: -0.065498524 | AJ24: -0.044417355
A25: 3 | B25: 149905 | C25: (CARTERA DE CRÉDITOS PRODUCTIVO) | D25: -0.0052423099 | E25: -0.0033429664 | F25: -0.016412518 | G25: -0.0061022684 | H25: -0.0095302334 | I25: -0.0065069961 | J25: -0.0069924303 | K25: -0.010207088 | L25: -0.0016777405 | M25: -0.0045649812 | N25: -0.014726667 | O25: -0.012513895 | P25: -0.0040403739 | Q25: -4.6329208e-07 | R25: -0.0078280065 | S25: -0.0099649452 | T25: -0.0033901923 | U25: -0.0036226049 | V25: -0.0018405412 | W25: -0.0040956429 | X25: -0.00083713585 | Y25: 0 | Z25: -0.0028631617 | AA25: 0 | AB25: -0.0016895542 | AC25: 0 | AD25: -0.0047458651 | AE25: -0.0087977321 | AF25: -0.014122353 | AG25: -0.0025383522 | AH25: #DIV/0! | AI25: 0 | AJ25: -0.0087371197
A26: 3 | B26: 149910 | C26: (CARTERA DE CRÉDITOS DE CONSUMO) | D26: -0.0041677475 | E26: -0.0084810176 | F26: -0.0065630949 | G26: -0.0044942833 | H26: -0.0061503568 | I26: -0.011942077 | J26: -0.0045424302 | K26: 0 | L26: -0.022079417 | M26: -0.014037933 | N26: -0.0036766887 | O26: -0.0058065947 | P26: -0.0045663726 | Q26: -0.022688116 | R26: -0.0089673091 | S26: -0.00021121233 | T26: -0.0064859722 | U26: -0.011777456 | V26: -0.025444746 | W26: -2.9761087e-05 | X26: -0.021767927 | Y26: -0.0027646418 | Z26: -0.0077140246 | AA26: 0 | AB26: -0.0046136345 | AC26: -3.608381e-06 | AD26: -0.0033666105 | AE26: -0.0069998591 | AF26: -0.0031850775 | AG26: -0.019727 | AH26: #DIV/0! | AI26: -0.00086235148 | AJ26: -0.0064848733
A27: 3 | B27: 149915 | C27: (CARTERA DE CRÉDITOS INMOBILIARIO) | D27: -0.00079646985 | E27: -0.0019949537 | F27: -0.0015240511 | G27: -0.00093843896 | H27: -0.001381769 | I27: -0.00044965365 | J27: -0.00051033532 | K27: 0 | L27: 0 | M27: -0.0016991711 | N27: -0.00076034115 | O27: -0.0012294888 | P27: -0.00044485771 | Q27: -4.3613167e-05 | R27: -0.00054584649 | S27: -0.00072246422 | T27: -7.0214358e-05 | U27: -4.2733418e-06 | V27: -8.0535518e-05 | W27: -6.1590744e-06 | X27: -3.1729871e-08 | Y27: 0 | Z27: -0.0021167326 | AA27: 0 | AB27: -0.0012412272 | AC27: 0 | AD27: -0.00045232207 | AE27: -0.0010701835 | AF27: -0.0006586757 | AG27: -0.00050630074 | AH27: #DIV/0! | AI27: 0 | AJ27: -0.0011696543
A28: 3 | B28: 149920 | C28: (CARTERA DE CRÉDITOS PARA MICROCRÉDITO) | D28: -0.00075598882 | E28: -0.00015974924 | F28: -0.0016449528 | G28: -0.00010666894 | H28: -0.00087133301 | I28: -0.00026955209 | J28: 0 | K28: 0 | L28: 0 | M28: -1.5687041e-08 | N28: -2.7243858e-05 | O28: -0.0021582748 | P28: -0.00027630083 | Q28: -0.033346673 | R28: -0.0016998458 | S28: -0.0026662951 | T28: -3.7635725e-05 | U28: -0.014497168 | V28: -0.00090677658 | W28: -0.00082563695 | X28: -0.0047700914 | Y28: -0.01543413 | Z28: -0.00049551571 | AA28: -0.04369013 | AB28: -0.012920497 | AC28: -0.054229003 | AD28: -0.0099558856 | AE28: -0.0014568296 | AF28: -2.3601073e-05 | AG28: -1.0581264e-05 | AH28: #DIV/0! | AI28: -0.038017966 | AJ28: -0.0014746239
A29: 3 | B29: 149940 | C29: (CARTERA DE CRÉDITOS DE VIVIENDA DE INTERÉS SOCIAL Y PÚBLICO) | D29: 0 | E29: -0.00053991039 | F29: -6.6042738e-06 | G29: 0 | H29: -0.00012138264 | I29: 0 | J29: 0 | K29: 0 | L29: 0 | M29: -7.1865535e-05 | N29: -1.330375e-06 | O29: 0 | P29: 0 | Q29: 0 | R29: -4.501512e-06 | S29: 0 | T29: 0 | U29: 0 | V29: 0 | W29: 0 | X29: 0 | Y29: 0 | Z29: 0 | AA29: 0 | AB29: 0 | AC29: 0 | AD29: 0 | AE29: -7.8106481e-05 | AF29: -1.1524902e-06 | AG29: -2.137399e-05 | AH29: #DIV/0! | AI29: 0 | AJ29: -9.2009795e-05
A30: 3 | B30: 149945 | C30: (CARTERA DE CRÉDITO REFINANCIADA) | D30: -0.00095536176 | E30: -0.0029538056 | F30: -0.0029614624 | G30: -0.00063012756 | H30: -0.0021541812 | I30: -0.0030173201 | J30: -1.6682487e-05 | K30: 0 | L30: -0.0050881835 | M30: -0.0015581109 | N30: -0.0016329103 | O30: -0.0043586108 | P30: -0.00013838289 | Q30: -0.0014744552 | R30: -0.0018317608 | S30: -0.0024309467 | T30: -0.00095317978 | U30: -0.0016302862 | V30: -0.01303941 | W30: 0 | X30: -0.0017546866 | Y30: -0.029695432 | Z30: -0.004076235 | AA30: -0.0033983308 | AB30: -0.019129314 | AC30: -0.0060459323 | AD30: -0.006043601 | AE30: -0.0021779715 | AF30: -0.0014145733 | AG30: -0.0041310247 | AH30: #DIV/0! | AI30: -0.012377231 | AJ30: -0.002039866
A31: 3 | B31: 149950 | C31: (CARTERA DE CRÉDITO REESTRUCTURADA) | D31: -0.002419538 | E31: -0.0058462564 | F31: -0.010567252 | G31: -0.0086081979 | H31: -0.0075973221 | I31: -0.0094837087 | J31: -0.0014550591 | K31: -0.0023403573 | L31: -0.020441626 | M31: -0.019596731 | N31: -0.0029580661 | O31: -0.019756937 | P31: -0.0027414257 | Q31: -0.0031166605 | R31: -0.0073835251 | S31: -0.0013307792 | T31: -0.0038932215 | U31: -7.253837e-05 | V31: -0.010809068 | W31: 0 | X31: -0.0033575379 | Y31: -0.018709873 | Z31: -0.0079425982 | AA31: -0.0014664062 | AB31: -0.0031703835 | AC31: -0.0010384373 | AD31: -0.003085133 | AE31: -0.0073727596 | AF31: -0.0028754721 | AG31: -0.020077987 | AH31: #DIV/0! | AI31: -0.0067112039 | AJ31: -0.006899192
A32: 3 | B32: 149955 | C32: (CARTERA DE CRÉDITO EDUCATIVO) | D32: -1.6424326e-05 | E32: -0.001475591 | F32: -1.4497074e-05 | G32: -3.34933e-06 | H32: -0.00033408234 | I32: 0 | J32: -2.1972332e-05 | K32: 0 | L32: 0 | M32: 0 | N32: 0 | O32: -3.6208329e-06 | P32: -4.2326323e-05 | Q32: 0 | R32: -7.8766443e-06 | S32: -3.785626e-06 | T32: 0 | U32: 0 | V32: 0 | W32: 0 | X32: 0 | Y32: 0 | Z32: 0 | AA32: 0 | AB32: 0 | AC32: 0 | AD32: -1.2510952e-06 | AE32: -0.00021350335 | AF32: 0 | AG32: 0 | AH32: #DIV/0! | AI32: 0 | AJ32: -0.00025646032
A33: 3 | B33: 149960 | C33: (CARTERA DE CRÉDITO DE INVERSIÓN PÚBLICA) | D33: 0 | E33: 0 | F33: 0 | G33: 0 | H33: 0 | I33: 0 | J33: 0 | K33: 0 | L33: 0 | M33: 0 | N33: 0 | O33: 0 | P33: 0 | Q33: 0 | R33: 0 | S33: 0 | T33: 0 | U33: 0 | V33: 0 | W33: 0 | X33: 0 | Y33: 0 | Z33: 0 | AA33: 0 | AB33: 0 | AC33: 0 | AD33: 0 | AE33: 0 | AF33: 0 | AG33: 0 | AH33: #DIV/0! | AI33: 0 | AJ33: 0
A34: 3 | B34: 149980 | C34: PROVISIÓN GÉNERICA POR TECNOLOGÍA CREDITICIA | D34: 0 | E34: 0 | F34: 0 | G34: 0 | H34: 0 | I34: 0 | J34: 0 | K34: 0 | L34: 0 | M34: 0 | N34: 0 | O34: -0.0067672647 | P34: 0 | Q34: 0 | R34: -0.00024877238 | S34: 0 | T34: 0 | U34: -0.0027508838 | V34: -0.0022457388 | W34: 0 | X34: -0.0068210078 | Y34: 0 | Z34: 0 | AA34: -0.0086816328 | AB34: -0.0092252487 | AC34: 0 | AD34: -0.002059639 | AE34: -0.00015315932 | AF34: 0 | AG34: -2.6194188e-05 | AH34: #DIV/0! | AI34: -0.003398159 | AJ34: -0.00015762688
A35: 3 | B35: 149985 | C35: PROVISIÓN ANTICÍCLICA | D35: -0.0002049145 | E35: -0.0012522476 | F35: -0.013570786 | G35: -0.00072882846 | H35: -0.0059754331 | I35: 0 | J35: -0.00057758828 | K35: 0 | L35: 0 | M35: -0.0010540404 | N35: 0 | O35: 0 | P35: -0.00099354277 | Q35: 0 | R35: -0.00025814234 | S35: 0 | T35: -0.00014768766 | U35: 0 | V35: -0.00069600818 | W35: 0 | X35: -0.00093226866 | Y35: 0 | Z35: -0.001787221 | AA35: 0 | AB35: 0 | AC35: 0 | AD35: -9.0286014e-05 | AE35: -0.0038603348 | AF35: 0 | AG35: -0.00032160712 | AH35: #DIV/0! | AI35: 0 | AJ35: -0.0046117785
... A43: 3 | B43: 0 | C43: TOTAL ACTIVOS | D43: 1 | E43: 1 | F43: 1 | G43: 1 | H43: 1 | I43: 1 | J43: 1 | K43: 1 | L43: 1 | M43: 1 | N43: 1 | O43: 1 | P43: 1 | Q43: 1 | R43: 1 | S43: 1 | T43: 1 | U43: 1 | V43: 1 | W43: 1 | X43: 1 | Y43: 1 | Z43: 1 | AA43: 1 | AB43: 1 | AC43: 1 | AD43: 1 | AE43: 1 | AF43: 1 | AG43: 1 | AH43: #DIV/0! | AI43: 1 | AJ43: 1
A45: 3
A47: 3
A49: 3 | C49: PASIVO
A50: 3 | B50: 21 | C50: OBLIGACIONES CON EL PÚBLICO | D50: 0.86489335 | E50: 0.88060549 | F50: 0.89745395 | G50: 0.88297714 | H50: 0.88480868 | I50: 0.97447275 | J50: 0.89364162 | K50: 0.91749641 | L50: 0.64387004 | M50: 0.91393325 | N50: 0.93305086 | O50: 0.95853181 | P50: 0.92889682 | Q50: 0.6112144 | R50: 0.87931389 | S50: 0.597653 | T50: 0.89956633 | U50: 0.97526443 | V50: 0.94847574 | W50: 0.97535433 | X50: 0.92515147 | Y50: 0.81874638 | Z50: 0.8832179 | AA50: 0.41847399 | AB50: 0.82802766 | AC50: 0.20296329 | AD50: 0.72945091 | AE50: 0.87788485 | AF50: 0.93103831 | AG50: 0.73531282 | AH50: #DIV/0! | AI50: 0.49306796 | AJ50: 0.88461042
A51: 3 | B51: 2101 | C51: Depósitos a la vista | D51: 0.51296124 | E51: 0.45484191 | F51: 0.63796721 | G51: 0.55301577 | H51: 0.55850596 | I51: 0.47559112 | J51: 0.57280008 | K51: 0.91636639 | L51: 0.0064131962 | M51: 0.39133706 | N51: 0.55893864 | O51: 0.54036511 | P51: 0.5066111 | Q51: 0.1206804 | R51: 0.46537789 | S51: 0.35267103 | T51: 0.27640763 | U51: 0.73298343 | V51: 0.33189044 | W51: 0.70702138 | X51: 0.11253419 | Y51: 0.081377342 | Z51: 0.49372547 | AA51: 0.062899168 | AB51: 0.33137996 | AC51: 0.064118376 | AD51: 0.33873702 | AE51: 0.52037103 | AF51: 0.60518528 | AG51: 0.13568141 | AH51: #DIV/0! | AI51: 0.069463985 | AJ51: 0.54135327
A52: 3 | B52: 2102 | C52: Operaciones de reporto | D52: 0 | E52: 0 | F52: 0 | G52: 0 | H52: 0 | I52: 0 | J52: 0 | K52: 0 | L52: 0 | M52: 0 | N52: 0 | O52: 0 | P52: 0 | Q52: 0 | R52: 0 | S52: 0 | T52: 0 | U52: 0 | V52: 0 | W52: 0 | X52: 0 | Y52: 0 | Z52: 0 | AA52: 0 | AB52: 0 | AC52: 0 | AD52: 0 | AE52: 0 | AF52: 0 | AG52: 0 | AH52: #DIV/0! | AI52: 0 | AJ52: 0
A53: 3 | B53: 2103 | C53: Depósitos a plazo | D53: 0.31679011 | E53: 0.36822189 | F53: 0.22711511 | G53: 0.30326134 | H53: 0.2889834 | I53: 0.47746457 | J53: 0.28583088 | K53: 0 | L53: 0.63275359 | M53: 0.52258081 | N53: 0.3530165 | O53: 0.41812905 | P53: 0.38754385 | Q53: 0.48602496 | R53: 0.39396709 | S53: 0.23556224 | T53: 0.57945942 | U53: 0.20995607 | V53: 0.6148725 | W53: 0.22760563 | X53: 0.80948581 | Y53: 0.73736904 | Z53: 0.35593821 | AA53: 0.35557482 | AB53: 0.48135948 | AC53: 0.13869726 | AD53: 0.37226085 | AE53: 0.32657461 | AF53: 0.30734063 | AG53: 0.59649293 | AH53: #DIV/0! | AI53: 0.42356271 | AJ53: 0.30867245
A54: 3 | B54: 2104 | C54: Depósitos de garantía | D54: 0 | E54: 0 | F54: 2.7838706e-05 | G54: 0 | H54: 1.1317296e-05 | I54: 0.00012206455 | J54: 0.00012384742 | K54: 0 | L54: 0 | M54: 0 | N54: 2.2864823e-05 | O54: 0 | P54: 0 | Q54: 0 | R54: 5.3993303e-05 | S54: 0 | T54: 0.00010872967 | U54: 6.4050552e-06 | V54: 3.844945e-05 | W54: 0 | X54: 0 | Y54: 0 | Z54: 0 | AA54: 0 | AB54: 0 | AC54: 0 | AD54: 1.8407016e-05 | AE54: 2.5719724e-05 | AF54: 1.9906404e-05 | AG54: 3.7717733e-07 | AH54: #DIV/0! | AI54: 0 | AJ54: 2.8390426e-05
A55: 3 | B55: 2105 | C55: Depósitos restringidos | D55: 0.035141995 | E55: 0.057541688 | F55: 0.032343787 | G55: 0.026700027 | H55: 0.037308 | I55: 0.021294992 | J55: 0.034886818 | K55: 0.0011300176 | L55: 0.0047032585 | M55: 1.53723e-05 | N55: 0.021072853 | O55: 3.7645745e-05 | P55: 0.034741865 | Q55: 0.0045090418 | R55: 0.019914921 | S55: 0.009419741 | T55: 0.043590549 | U55: 0.032318525 | V55: 0.0016743482 | W55: 0.040727325 | X55: 0.0031314699 | Y55: 0 | Z55: 0.033554226 | AA55: 0 | AB55: 0.015288212 | AC55: 0.00014764821 | AD55: 0.018434637 | AE55: 0.030913483 | AF55: 0.018492502 | AG55: 0.003138107 | AH55: #DIV/0! | AI55: 4.1264932e-05 | AJ55: 0.034556312
A56: 3 | B56: 22 | C56: OPERACIONES INTERBANCARIAS | D56: 0 | E56: 0 | F56: 0 | G56: 0 | H56: 0 | I56: 0 | J56: 0 | K56: 0 | L56: 0 | M56: 0 | N56: 0 | O56: 0 | P56: 0 | Q56: 0 | R56: 0 | S56: 0 | T56: 0 | U56: 0 | V56: 0 | W56: 0 | X56: 0 | Y56: 0 | Z56: 0 | AA56: 0 | AB56: 0 | AC56: 0 | AD56: 0 | AE56: 0 | AF56: 0 | AG56: 0 | AH56: #DIV/0! | AI56: 0 | AJ56: 0
A57: 3 | B57: 23 | C57: OBLIGACIONES INMEDIATAS | D57: 0.0076513742 | E57: 0.0054576613 | F57: 0.0058260438 | G57: 0.0059465632 | H57: 0.0061258627 | I57: 0.0010144313 | J57: 0.0085460432 | K57: 0.032604834 | L57: 0 | M57: 0.0061971821 | N57: 0.002076708 | O57: 0.0031518975 | P57: 0.0018044186 | Q57: 0.0014602664 | R57: 0.0047040327 | S57: 2.2320162e-05 | T57: 0.0034484091 | U57: 0.00019452943 | V57: 0.002330683 | W57: 0.0023526358 | X57: 0.0011573847 | Y57: 0 | Z57: 0.050176936 | AA57: 0.00023998162 | AB57: 0.0023514454 | AC57: 0 | AD57: 0.0019335574 | AE57: 0.0055161659 | AF57: 0.0060266617 | AG57: 0.0020526468 | AH57: #DIV/0! | AI57: 9.2077327e-05 | AJ57: 0.0057433913
A58: 3 | B58: 24 | C58: ACEPTACIONES EN CIRCULACIÓN | D58: 0 | E58: 0.00081060262 | F58: 1.9570939e-05 | G58: 5.9718385e-06 | H58: 0.00018409235 | I58: 3.1704082e-05 | J58: 0 | K58: 0.000479293 | L58: 0 | M58: 0 | N58: 0 | O58: 0 | P58: 0 | Q58: 0 | R58: 2.2443913e-05 | S58: 0 | T58: 0 | U58: 0 | V58: 0 | W58: 0 | X58: 0 | Y58: 0 | Z58: 0 | AA58: 0 | AB58: 0 | AC58: 0 | AD58: 0 | AE58: 0.00012437764 | AF58: 6.2014458e-05 | AG58: 0 | AH58: #DIV/0! | AI58: 0 | AJ58: 0.00014137522
A59: 3 | B59: 25 | C59: CUENTAS POR PAGAR | D59: 0.029850795 | E59: 0.032765553 | F59: 0.029198524 | G59: 0.029152589 | H59: 0.030088228 | I59: 0.021989151 | J59: 0.026999004 | K59: 0.048267696 | L59: 0.28719447 | M59: 0.027684651 | N59: 0.031321002 | O59: 0.019858726 | P59: 0.01832305 | Q59: 0.053278927 | R59: 0.059957572 | S59: 0.021891393 | T59: 0.031912749 | U59: 0.016424364 | V59: 0.043061004 | W59: 0.022095799 | X59: 0.052890554 | Y59: 0.031811177 | Z59: 0.058372928 | AA59: 0.039980951 | AB59: 0.037677012 | AC59: 0.041992384 | AD59: 0.029583507 | AE59: 0.039989182 | AF59: 0.03351369 | AG59: 0.19980149 | AH59: #DIV/0! | AI59: 0.037791254 | AJ59: 0.029221457
A60: 3 | B60: 26 | C60: OBLIGACIONES FINANCIERAS | D60: 0.084494681 | E60: 0.073970609 | F60: 0.028893134 | G60: 0.054214759 | H60: 0.054117131 | I60: 0.00045984564 | J60: 0.060630071 | K60: 0 | L60: 0.017659101 | M60: 0.035713449 | N60: 0.033214824 | O60: 0.0050450244 | P60: 0.028649995 | Q60: 0.33114372 | R60: 0.043940104 | S60: 0.35972378 | T60: 0.058714164 | U60: 0 | V60: 0 | W60: 0 | X60: 0 | Y60: 0.13401122 | Z60: 0 | AA60: 0.53803007 | AB60: 0.12971172 | AC60: 0.75334789 | AD60: 0.22855088 | AE60: 0.056463594 | AF60: 0.028917245 | AG60: 0.02339927 | AH60: #DIV/0! | AI60: 0.46212026 | AJ60: 0.059315961
A61: 3 | B61: 2601 | C61: Sobregiros | D61: 0 | E61: 0 | F61: 0.0012433879 | G61: 4.129045e-05 | H61: 0.0005129771 | I61: 0 | J61: 0 | K61: 0 | L61: 0 | M61: 0 | N61: 0 | O61: 0 | P61: 0 | Q61: 0 | R61: 0 | S61: 0 | T61: 0 | U61: 0 | V61: 0 | W61: 0 | X61: 0 | Y61: 0 | Z61: 0 | AA61: 0 | AB61: 0 | AC61: 0 | AD61: 0 | AE61: 0.00032581552 | AF61: 0 | AG61: 0 | AH61: #DIV/0! | AI61: 0 | AJ61: 0.00038908042
... A74: 3 | B74: 29 | C74: OTROS PASIVOS | D74: 0.00029090231 | E74: 0.0063900859 | F74: 0.0056260492 | G74: 0.0043026394 | H74: 0.0045057678 | I74: 0.0020321152 | J74: 0.0020212076 | K74: 0.0011517683 | L74: 0.051276392 | M74: 0.0051625562 | N74: 0.00033660363 | O74: 0.013412544 | P74: 0.0045676788 | Q74: 0.0029026836 | R74: 0.0082990469 | S74: 0.00045915254 | T74: 0.0063583517 | U74: 0.008116679 | V74: 0.0061325349 | W74: 0.00019723655 | X74: 0.020800593 | Y74: 0.0015272003 | Z74: 0.0082322379 | AA74: 0.0032750009 | AB74: 0.0018870215 | AC74: 0.001696436 | AD74: 0.0026955168 | AE74: 0.0057058316 | AF74: 0.00044207564 | AG74: 0.035729728 | AH74: #DIV/0! | AI74: 0.0022451032 | AJ74: 0.0041701086
A75: 3 | C75: TOTAL PASIVOS | D75: 1 | E75: 1 | F75: 1 | G75: 1 | H75: 1 | I75: 1 | J75: 1 | K75: 1 | L75: 1 | M75: 1 | N75: 1 | O75: 1 | P75: 1 | Q75: 1 | R75: 1 | S75: 1 | T75: 1 | U75: 1 | V75: 1 | W75: 1 | X75: 1 | Y75: 1 | Z75: 1 | AA75: 1 | AB75: 1 | AC75: 1 | AD75: 1 | AE75: 1 | AF75: 1 | AG75: 1 | AH75: #DIV/0! | AI75: 1 | AJ75: 1
A77: 3 | C77: PATRIMONIO
A78: 3 | B78: 31 | C78: CAPITAL SOCIAL | D78: 0.85302843 | E78: 0.73689378 | F78: 0.73467166 | G78: 0.88046179 | H78: 0.77760374 | I78: 0.73250352 | J78: 0.85467785 | K78: 0.85012262 | L78: 0.49926994 | M78: 0.86648748 | N78: 0.81678426 | O78: 0.78597518 | P78: 0.88000738 | Q78: 0.63251325 | R78: 0.72696924 | S78: 0.89789284 | T78: 0.87879768 | U78: 0.86688629 | V78: 0.98582474 | W78: 0.71245512 | X78: 1.9458419 | Y78: 1.2018572 | Z78: 0.98844478 | AA78: 1.0533744 | AB78: 0.75734832 | AC78: 0.95062326 | AD78: 0.9331836 | AE78: 0.76660386 | AF78: 0.82262426 | AG78: 0.56545644 | AH78: #DIV/0! | AI78: 1.0602618 | AJ78: 0.78310253
A79: 3 | B79: 32 | C79: PRIMA O DESCUENTO EN COLOCACIÓN DE ACCIONES Y CERTIFICADOS | D79: 0 | E79: 0 | F79: 0 | G79: 0.0024640578 | H79: 0.00036612827 | I79: 0 | J79: 0 | K79: 0 | L79: 0 | M79: 0 | N79: 0 | O79: 0 | P79: 0 | Q79: 0.0073416247 | R79: 0.00061321962 | S79: 0 | T79: 0 | U79: 0 | V79: 0 | W79: 0 | X79: 0 | Y79: 0 | Z79: 0 | AA79: 0 | AB79: 0 | AC79: 0 | AD79: 0 | AE79: 0.00043774252 | AF79: 0 | AG79: 0 | AH79: #DIV/0! | AI79: 0 | AJ79: 0.00055188703
A80: 3 | B80: 33 | C80: RESERVAS | D80: 0.13800193 | E80: 0.18821004 | F80: 0.17039053 | G80: 0.12958685 | H80: 0.16333447 | I80: 0.16989688 | J80: 0.13649234 | K80: 0.14470972 | L80: 0.44979788 | M80: 0.12595853 | N80: 0.13397656 | O80: 0.15863856 | P80: 0.071867098 | Q80: 0.13006133 | R80: 0.21385274 | S80: 0.10137076 | T80: 0.068714637 | U80: 0.11627371 | V80: 0.039933665 | W80: 0.24862628 | X80: 0 | Y80: 1.8240759e-06 | Z80: 0.0090073078 | AA80: 0.054363392 | AB80: 0.12260104 | AC80: 0.048334468 | AD80: 0.095249749 | AE80: 0.17828508 | AF80: 0.13585672 | AG80: 0.39183531 | AH80: #DIV/0! | AI80: 0.037108359 | AJ80: 0.15659739
A81: 3 | B81: 34 | C81: OTROS APORTES PATRIMONIALES | D81: 0 | E81: 0 | F81: 0 | G81: 0 | H81: 0 | I81: 0 | J81: 0 | K81: 0 | L81: 0 | M81: 0 | N81: 0 | O81: 0 | P81: 0 | Q81: 0.00010329122 | R81: 8.6275459e-06 | S81: 0.00090566776 | T81: 0 | U81: 0 | V81: 0 | W81: 0.00010388553 | X81: 0 | Y81: 0 | Z81: 0 | AA81: 0 | AB81: 0.064150966 | AC81: 0.0010422687 | AD81: 0.0069748226 | AE81: 0.000321335 | AF81: 0 | AG81: 0 | AH81: #DIV/0! | AI81: 0.0003518237 | AJ81: 0.0004005584
A82: 3 | B82: 35 | C82: SUPERÁVIT POR VALUACIONES | D82: 0.0089696412 | E82: 0.059702577 | F82: 0.07955665 | G82: -0.012528687 | H82: 0.048335156 | I82: 0.097530635 | J82: 0.0085866966 | K82: 0.005167667 | L82: 0.050932177 | M82: 0.0037797023 | N82: 0.048132208 | O82: 0.036146847 | P82: 0.044268559 | Q82: 0.0043586535 | R82: 0.038484492 | S82: 0.019742053 | T82: 0.052487682 | U82: 0.015790888 | V82: 0.0077266345 | W82: 0.038814716 | X82: 0.0063586293 | Y82: 0.0022094774 | Z82: 0.0025479087 | AA82: 0.028206894 | AB82: 0.055899674 | AC82: 0 | AD82: 0.025470552 | AE82: 0.043770862 | AF82: 0.040605958 | AG82: 0.042840215 | AH82: #DIV/0! | AI82: 0.011406844 | AJ82: 0.044678116
A83: 3 | B83: 36 | C83: RESULTADOS | D83: 1.8960401e-10 | E83: 0.015193605 | F83: 0.01538116 | G83: 1.5979993e-05 | H83: 0.010360508 | I83: 6.8968919e-05 | J83: 0.00024311169 | K83: 0 | L83: 0 | M83: 0.0037742912 | N83: 0.0011069791 | O83: 0.01923942 | P83: 0.0038569671 | Q83: 0.22562184 | R83: 0.020071676 | S83: -0.019911318 | T83: 0 | U83: 0.0010491089 | V83: -0.033485039 | W83: 0 | X83: -0.95220057 | Y83: -0.20406853 | Z83: 0 | AA83: -0.13594464 | AB83: 0 | AC83: 0 | AD83: -0.060878724 | AE83: 0.010581117 | AF83: 0.00091306566 | AG83: -0.00013196755 | AH83: #DIV/0! | AI83: -0.10912881 | AJ83: 0.014669522
A84: 3 | B84: 3601 | C84: Utilidades o excedentes acumulados | D84: 1.8960401e-10 | E84: 0.015193605 | F84: 0.01538116 | G84: 1.5979993e-05 | H84: 0.010360508 | I84: 6.8968919e-05 | J84: 0.00024311169 | K84: 0 | L84: 0 | M84: 0.0037742912 | N84: 0.0011069791 | O84: 0.01923942 | P84: 0.0038569671 | Q84: 0.22562184 | R84: 0.020071676 | S84: 0.0069111684 | T84: 0 | U84: 0.0010491089 | V84: 0 | W84: 0 | X84: 0 | Y84: 1.6420114e-05 | Z84: 0 | AA84: 0 | AB84: 0 | AC84: 0 | AD84: 0.0017856585 | AE84: 0.013440403 | AF84: 0.00091306566 | AG84: 0.00057472811 | AH84: #DIV/0! | AI84: 4.5972383e-06 | AJ84: 0.016763772
A85: 3 | B85: 3602 | C85: (Pérdidas acumuladas) | D85: 0 | E85: 0 | F85: 0 | G85: 0 | H85: 0 | I85: 0 | J85: 0 | K85: 0 | L85: 0 | M85: 0 | N85: 0 | O85: 0 | P85: 0 | Q85: 0 | R85: 0 | S85: -0.026822486 | T85: 0 | U85: 0 | V85: -0.033485039 | W85: 0 | X85: -0.95220057 | Y85: -0.20408495 | Z85: 0 | AA85: -0.13594464 | AB85: 0 | AC85: 0 | AD85: -0.062664383 | AE85: -0.0028592861 | AF85: 0 | AG85: -0.00070669566 | AH85: #DIV/0! | AI85: -0.10913341 | AJ85: -0.0020942502
A86: 3 | B86: 3603 | C86: Utilidad o excedente del ejercicio | D86: 0 | E86: 0 | F86: 0 | G86: 0 | H86: 0 | I86: 0 | J86: 0 | K86: 0 | L86: 0 | M86: 0 | N86: 0 | O86: 0 | P86: 0 | Q86: 0 | R86: 0 | S86: 0 | T86: 0 | U86: 0 | V86: 0 | W86: 0 | X86: 0 | Y86: 0 | Z86: 0 | AA86: 0 | AB86: 0 | AC86: 0 | AD86: 0 | AE86: 0 | AF86: 0 | AG86: 0 | AH86: #DIV/0! | AI86: 0 | AJ86: 0
A87: 3 | B87: 3604 | C87: (Pérdida del ejercicio) | D87: 0 | E87: 0 | F87: 0 | G87: 0 | H87: 0 | I87: 0 | J87: 0 | K87: 0 | L87: 0 | M87: 0 | N87: 0 | O87: 0 | P87: 0 | Q87: 0 | R87: 0 | S87: 0 | T87: 0 | U87: 0 | V87: 0 | W87: 0 | X87: 0 | Y87: 0 | Z87: 0 | AA87: 0 | AB87: 0 | AC87: 0 | AD87: 0 | AE87: 0 | AF87: 0 | AG87: 0 | AH87: #DIV/0! | AI87: 0 | AJ87: 0
A88: 3 | B88: 37 | C88: (DESVALORIZACIÓN DEL PATRIMONIO) | D88: 0 | E88: 0 | F88: 0 | G88: 0 | H88: 0 | I88: 0 | J88: 0 | K88: 0 | L88: 0 | M88: 0 | N88: 0 | O88: 0 | P88: 0 | Q88: 0 | R88: 0 | S88: 0 | T88: 0 | U88: 0 | V88: 0 | W88: 0 | X88: 0 | Y88: 0 | Z88: 0 | AA88: 0 | AB88: 0 | AC88: 0 | AD88: 0 | AE88: 0 | AF88: 0 | AG88: 0 | AH88: #DIV/0! | AI88: 0 | AJ88: 0
A89: 3 | B89: 0 | C89: TOTAL PATRIMONIO | D89: 1 | E89: 1 | F89: 1 | G89: 1 | H89: 1 | I89: 1 | J89: 1 | K89: 1 | L89: 1 | M89: 1 | N89: 1 | O89: 1 | P89: 1 | Q89: 1 | R89: 1 | S89: 1 | T89: 1 | U89: 1 | V89: 1 | W89: 1 | X89: 1 | Y89: 1 | Z89: 1 | AA89: 1 | AB89: 1 | AC89: 1 | AD89: 1 | AE89: 1 | AF89: 1 | AG89: 1 | AH89: #DIV/0! | AI89: 1 | AJ89: 1
A91: 3
A93: 3
A94: 3
A95: 3
A96: 3
A97: 3
A98: 3
A99: 3
A100: 3
A101: 3
A102: 3 | B102: Fuente: Estados de situación remitidos por las entidades / Sistema de Administración de Balances (S.A.B.)
A103: 3 | B103: Elaboración: Dirección de Estudios y Gestión de la Información / Subdirección de Estadísticas y Estudios/OM
A104: 3 | B104: Nota: Agrupación de entidades en base a su participación en el Activo Total.
A105: 3 | B105: Grandes (Mayor al 10%)
A106: 3 | B106: Medianas (Entre el 1%% y 10%)
A107: 3 | B107: Pequeñas (Menor al 1%)
A108: 3 | B108: Fecha de consolidación: 06-08-2020
A109: 3 | B109: Código Orgánico Monetario y Financiero Art 162 : Composición del sector financiero privado, Bancos Múltiple y Especializada
A110: 3
A111: 3
B112: PRUEBA CARTERA | D112: 8.3266727e-17 | E112: -1.110223e-16 | F112: 0 | G112: 0 | H112: 8.3266727e-17 | I112: 0 | J112: 0 | K112: 3.1225023e-17 | L112: 0 | M112: 0 | N112: 0 | O112: 0 | P112: 1.6306401e-16 | Q112: 0 | R112: 7.6327833e-17 | S112: -3.1918912e-16 | T112: 0 | U112: 1.0408341e-16 | V112: -8.3266727e-17 | W112: -2.2551405e-17 | X112: 1.110223e-16 | Y112: 0 | Z112: 0 | AA112: 0 | AB112: -1.6653345e-16 | AC112: 0 | AD112: 0 | AE112: 7.6327833e-17 | AF112: -2.220446e-16 | AG112: -1.3877788e-16 | AH112: #DIV/0! | AI112: 1.6653345e-16 | AJ112: 0
B113: PRUEBA INVERSIONES | D113: 1.973248e-17 | E113: 7.3725748e-18 | F113: 5.8980598e-17 | G113: -1.2366681e-18 | H113: 0 | I113: 1.23328e-18 | J113: 2.005774e-17 | K113: 0 | L113: 0 | M113: 0 | N113: -2.8373486e-18 | O113: -2.6529072e-18 | P113: -2.1684043e-18 | Q113: -6.9388939e-18 | R113: 1.4528309e-17 | S113: 7.2641546e-18 | T113: -1.5612511e-17 | U113: -1.0408341e-17 | V113: 1.3877788e-17 | W113: -3.2851326e-17 | X113: 6.9388939e-18 | Y113: 0 | Z113: -1.6805134e-17 | AA113: 2.7755576e-17 | AB113: 1.3877788e-17 | AD113: 2.8460307e-18 | AE113: 3.7296555e-17 | AF113: -1.4055771e-17 | AG113: 0 | AH113: #DIV/0! | AI113: 6.9388939e-18 | AJ113: 1.8214596e-17
B114: PRUEBA DEPOSITOS | D114: 0 | E114: 8.3266727e-17 | F114: -9.0205621e-17 | G114: 7.2858386e-17 | H114: 0 | I114: 0 | J114: -1.3877788e-16 | K114: -1.6479873e-17 | L114: -4.4235449e-17 | M114: 3.0662593e-17 | N114: 7.2858386e-17 | O114: -5.5707663e-17 | P114: 0 | Q114: -8.6736174e-18 | R114: -1.9081958e-16 | S114: 0 | T114: 0 | U114: 0 | V114: 1.0755286e-16 | W114: 0 | X114: 0 | Y114: -1.110223e-16 | Z114: 9.0205621e-17 | AA114: 5.5511151e-17 | AB114: -6.9388939e-17 | AD114: -1.4224733e-16 | AE114: -3.469447e-17 | AF114: 0 | AG114: -1.1058862e-16 | AH114: #DIV/0! | AI114: -3.7777669e-17 | AJ114: -7.6327833e-17
B115: PRUEBA A-C-P-I+G | D115: 0 | E115: 0 | F115: 0 | G115: 0 | H115: 0 | I115: 0 | J115: 0 | K115: 0 | L115: 0 | M115: 0 | N115: 0 | O115: 0 | P115: 0 | Q115: 0 | R115: 0 | S115: 0 | T115: 0 | U115: 0 | V115: 0 | W115: 0 | X115: 0 | Y115: 0 | Z115: 0 | AA115: 0 | AB115: 0 | AD115: 0 | AE115: 0 | AF115: 0 | AG115: 0 | AH115: 0 | AI115: 0 | AJ115: 0
B116: PRUEBA A-C-P SOLO DIC | D116: -1 | E116: -1 | F116: -1 | G116: -1 | H116: -1 | I116: -1 | J116: -1 | K116: -1 | L116: -1 | M116: -1 | N116: -1 | O116: -1 | P116: -1 | Q116: -1 | R116: -1 | S116: -1 | T116: -1 | U116: -1 | V116: -1 | W116: -1 | X116: -1 | Y116: -1 | Z116: -1 | AA116: -1 | AB116: -1 | AD116: -1 | AE116: -1 | AF116: -1 | AG116: -1 | AH116: #DIV/0! | AI116: -1 | AJ116: -1

Sheet EPyG %
B2: ESTADO DE PÉRDIDAS Y GANANCIAS
B3: SISTEMA DE BANCOS PRIVADOS
B4: 44439
B5: (en porcentajes)
AF6: BANCA ESPECIALIZADA
B7: CODIGO | C7: CUENTA | D7: BP GUAYAQUIL | E7: BP PACIFICO | F7: BP PICHINCHA | G7: BP PRODUBANCO | H7: BANCOS PRIVADOS GRANDES | I7: BP AUSTRO | J7: BP BOLIVARIANO | K7: BP CITIBANK | L7: BP DINERS | M7: BP GENERAL RUMIÑAHUI | N7: BP INTERNACIONAL | O7: BP LOJA | P7: BP MACHALA | Q7: BP SOLIDARIO | R7: BANCOS PRIVADOS MEDIANOS | S7: BP PROCREDIT | T7: BP AMAZONAS | U7: BP COMERCIAL DE MANABI | V7: BP LITORAL | W7: BP COOPNACIONAL | X7: BP CAPITAL | Y7: BP FINCA S.A. | Z7: BP DELBANK | AA7: BP D MIRO S.A. | AB7: BP BANCODESARROLLO | AC7: BP VISIONFUND ECUADOR S.A. | AD7: BANCOS PRIVADOS PEQUEÑOS | AE7: TOTAL BANCOS PRIVADOS | AF7: BANCOS PRIVADOS COMERCIALES | AG7: BANCOS PRIVADOS CONSUMO | AH7: BANCOS PRIVADOS VIVIENDA | AI7: BANCOS PRIVADOS DE MICROCRÉDITO | AJ7: BANCA MULTIPLE
C9: TOTAL INGRESOS | D9: 1 | E9: 1 | F9: 1 | G9: 1 | H9: 1 | I9: 1 | J9: 1 | K9: 1 | L9: 1 | M9: 1 | N9: 1 | O9: 1 | P9: 1 | Q9: 1 | R9: 1 | S9: 1 | T9: 1 | U9: 1 | V9: 1 | W9: 1 | X9: 1 | Y9: 1 | Z9: 1 | AA9: 1 | AB9: 1 | AC9: 1 | AD9: 1 | AE9: 1 | AF9: 1 | AG9: 1 | AH9: #DIV/0! | AI9: 1 | AJ9: 1
B11: 51 | C11: INTERESES Y DESCUENTOS GANADOS | D11: 0.68077777 | E11: 0.64466027 | F11: 0.67190245 | G11: 0.70530184 | H11: 0.67286091 | I11: 0.72741317 | J11: 0.76302379 | K11: 0.47070794 | L11: 0.49607401 | M11: 0.82293602 | N11: 0.79052625 | O11: 0.8707408 | P11: 0.87198061 | Q11: 0.74319059 | R11: 0.69773572 | S11: 0.83754905 | T11: 0.74082925 | U11: 0.82307616 | V11: 0.88334228 | W11: 0.9210002 | X11: 0.79807919 | Y11: 0.73752409 | Z11: 0.32677148 | AA11: 0.83803696 | AB11: 0.71933736 | AC11: 0.89413196 | AD11: 0.78940704 | AE11: 0.68543754 | AF11: 0.75466561 | AG11: 0.56351693 | AH11: #DIV/0! | AI11: 0.82679253 | AJ11: 0.69416359
B12: 5101 | C12: Depósitos | D12: 0.0016310083 | E12: 6.9111127e-05 | F12: 8.0225278e-05 | G12: 0.0032611805 | H12: 0.00087728071 | I12: 0.017630701 | J12: 0.0080202655 | K12: 0.005933422 | L12: 0.00014105697 | M12: 0.010017858 | N12: 0.0071354053 | O12: 0.0030679332 | P12: 0.0088189008 | Q12: 0.0010101465 | R12: 0.0063676758 | S12: 0.0049633726 | T12: 0.0070719196 | U12: 3.2704965e-05 | V12: 5.1197676e-05 | W12: 0.10587864 | X12: 0.00098707076 | Y12: 0.0001281986 | Z12: 0.0063193948 | AA12: 0.0016340724 | AB12: 0.0033449178 | AC12: 0.0046734633 | AD12: 0.010136072 | AE12: 0.0030413347 | AF12: 0.0070006291 | AG12: 0.0020853504 | AH12: #DIV/0! | AI12: 0.0021863363 | AJ12: 0.0028481795
B13: 5102 | C13: Operaciones interbancarias | D13: 0 | E13: 0 | F13: 4.6114879e-06 | G13: 0 | H13: 1.9898182e-06 | I13: 0 | J13: 0 | K13: 0 | L13: 0 | M13: 0 | N13: 0 | O13: 0 | P13: 0 | Q13: 0 | R13: 0 | S13: 0 | T13: 0 | U13: 0 | V13: 0 | W13: 0 | X13: 0 | Y13: 0 | Z13: 0 | AA13: 0 | AB13: 0 | AC13: 0 | AD13: 0 | AE13: 1.2562783e-06 | AF13: 0 | AG13: 0 | AH13: #DIV/0! | AI13: 0 | AJ13: 1.5474914e-06
B14: 5103 | C14: Intereses y descuentos de inversiones en títulos valores | D14: 0.019586727 | E14: 0.026284331 | F14: 0.025717121 | G14: 0.01632441 | H14: 0.023197871 | I14: 0.081048314 | J14: 0.027256413 | K14: 0.10131868 | L14: 0.0044497512 | M14: 0.023764387 | N14: 0.056654584 | O14: 0.027408604 | P14: 0.063967872 | Q14: 0.018089409 | R14: 0.035737041 | S14: 0.0096726215 | T14: 0.10092365 | U14: 0.045617873 | V14: 0.035876323 | W14: 0.14332043 | X14: 0.021095295 | Y14: 0.0076277599 | Z14: 0.025332349 | AA14: 0.052787896 | AB14: 0.010130921 | AC14: 0.0030707119 | AD14: 0.03455459 | AE14: 0.027776453 | AF14: 0.061662687 | AG14: 0.0085028572 | AH14: #DIV/0! | AI14: 0.023180246 | AJ14: 0.02758005
B15: 5104 | C15: Intereses y descuentos de cartera de créditos | D15: 0.65956003 | E15: 0.61825883 | F15: 0.64326328 | G15: 0.68571625 | H15: 0.64754883 | I15: 0.62871159 | J15: 0.72648707 | K15: 0.36292806 | L15: 0.49142762 | M15: 0.78915377 | N15: 0.72673626 | O15: 0.84026426 | P15: 0.79919384 | Q15: 0.72409103 | R15: 0.65537199 | S15: 0.82291306 | T15: 0.63257155 | U15: 0.77568273 | V15: 0.84741475 | W15: 0.67180113 | X15: 0.77599683 | Y15: 0.72976813 | Z15: 0.29511974 | AA15: 0.78361499 | AB15: 0.70586152 | AC15: 0.88638779 | AD15: 0.74463787 | AE15: 0.65375004 | AF15: 0.68594311 | AG15: 0.55288452 | AH15: #DIV/0! | AI15: 0.80142595 | AJ15: 0.66267496
B16: 5190 | C16: Otros intereses y descuentos | D16: 0 | E16: 4.7996837e-05 | F16: 0.0028372127 | G16: 0 | H16: 0.0012349385 | I16: 2.2562545e-05 | J16: 0.0012600435 | K16: 0.00052778317 | L16: 5.5590911e-05 | M16: 0 | N16: 0 | O16: 0 | P16: 0 | Q16: 8.5396059e-10 | R16: 0.00025901901 | S16: 0 | T16: 0.00026212051 | U16: 0.0017428485 | V16: 0 | W16: 0 | X16: 0 | Y16: 0 | Z16: 0 | AA16: 0 | AB16: 0 | AC16: 0 | AD16: 7.8510129e-05 | AE16: 0.00086846109 | AF16: 5.9179362e-05 | AG16: 4.4202161e-05 | AH16: #DIV/0! | AI16: 0 | AJ16: 0.0010588502
B17: 41 | C17: INTERESES CAUSADOS | D17: 0.24281209 | E17: 0.26976528 | F17: 0.14601427 | G17: 0.21156339 | H17: 0.20199976 | I17: 0.31721701 | J17: 0.28576812 | K17: 0.0022503774 | L17: 0.16153605 | M17: 0.27693936 | N17: 0.30154141 | O17: 0.28122454 | P17: 0.32068346 | Q17: 0.23329102 | R17: 0.25002088 | S17: 0.36095952 | T17: 0.46652337 | U17: 0.13699554 | V17: 0.19135348 | W17: 0.19453536 | X17: 0.46217327 | Y17: 0.38021038 | Z17: 0.080320737 | AA17: 0.35266248 | AB17: 0.26180369 | AC17: 0.22114489 | AD17: 0.31318061 | AE17: 0.22204967 | AF17: 0.26798246 | AG17: 0.18449882 | AH17: #DIV/0! | AI17: 0.31767769 | AJ17: 0.22198297
B18: 4101 | C18: Obligaciones con el público | D18: 0.19135492 | E18: 0.21229828 | F18: 0.11949437 | G18: 0.17086245 | H18: 0.16170289 | I18: 0.31488347 | J18: 0.2442458 | K18: 0.0021688472 | L18: 0.16074951 | M18: 0.24246891 | N18: 0.28256188 | O18: 0.27596907 | P18: 0.30229958 | Q18: 0.13833427 | R18: 0.22752556 | S18: 0.17719039 | T18: 0.44562381 | U18: 0.13699554 | V18: 0.19135348 | W18: 0.19453536 | X18: 0.4582763 | Y18: 0.32933086 | Z18: 0.080320737 | AA18: 0.14323831 | AB18: 0.22965609 | AC18: 0.040982436 | AD18: 0.21482822 | AE18: 0.18549635 | AF18: 0.25112193 | AG18: 0.17708526 | AH18: #DIV/0! | AI18: 0.16458103 | AJ18: 0.181383
B19: 4102 | C19: Servicios fiduciarios | D19: 0 | E19: 0 | F19: 0 | G19: 0 | H19: 0 | I19: 0 | J19: 0 | K19: 8.1530234e-05 | L19: 7.2778157e-06 | M19: 0 | N19: 0 | O19: 0 | P19: 0 | Q19: 0 | R19: 3.7901312e-06 | S19: 0 | T19: 0 | U19: 0 | V19: 0 | W19: 0 | X19: 0 | Y19: 0 | Z19: 0 | AA19: 0 | AB19: 0 | AC19: 0 | AD19: 0 | AE19: 1.2563734e-06 | AF19: 9.1418361e-06 | AG19: 5.7868306e-06 | AH19: #DIV/0! | AI19: 0 | AJ19: 0
B20: 4103 | C20: Obligaciones financieras | D20: 0.043760383 | E20: 0.057467001 | F20: 0.02230458 | G20: 0.040700944 | H20: 0.037064418 | I20: 0.0023335423 | J20: 0.036868512 | K20: 0 | L20: 0.00077926162 | M20: 0.026919284 | N20: 0.018979529 | O20: 0.0052554714 | P20: 0.011872302 | Q20: 0.094956751 | R20: 0.020865279 | S20: 0.18376913 | T20: 0.020850571 | U20: 0 | V20: 0 | W20: 0 | X20: 0.0038969668 | Y20: 0.050879515 | Z20: 0 | AA20: 0.20942417 | AB20: 0.032147598 | AC20: 0.18016245 | AD20: 0.098346887 | AE20: 0.033971969 | AF20: 0.016851389 | AG20: 0.0059207455 | AH20: #DIV/0! | AI20: 0.15309667 | AJ20: 0.037621885
B21: 4104 | C21: Valores en circulación y obligaciones convertibles en acciones | D21: 0.0076967856 | E21: 0 | F21: 0.0042085118 | G21: 0 | H21: 0.0032295058 | I21: 0 | J21: 0.0046538036 | K21: 0 | L21: 0 | M21: 0.0075511658 | N21: 0 | O21: 0 | P21: 0.0065115743 | Q21: 0 | R21: 0.0016262479 | S21: 0 | T21: 0 | U21: 0 | V21: 0 | W21: 0 | X21: 0 | Y21: 0 | Z21: 0 | AA21: 0 | AB21: 0 | AC21: 0 | AD21: 0 | AE21: 0.0025780368 | AF21: 0 | AG21: 0.0014870271 | AH21: #DIV/0! | AI21: 0 | AJ21: 0.0029755477
B22: 4105 | C22: Otros intereses | D22: 0 | E22: 0 | F22: 6.8130559e-06 | G22: 0 | H22: 2.9397762e-06 | I22: 0 | J22: 0 | K22: 0 | L22: 0 | M22: 0 | N22: 0 | O22: 0 | P22: 0 | Q22: 0 | R22: 0 | S22: 0 | T22: 4.8985824e-05 | U22: 0 | V22: 0 | W22: 0 | X22: 0 | Y22: 0 | Z22: 0 | AA22: 0 | AB22: 0 | AC22: 0 | AD22: 5.4970555e-06 | AE22: 2.0603147e-06 | AF22: 0 | AG22: 0 | AH22: #DIV/0! | AI22: 0 | AJ22: 2.5379084e-06
C23: MARGEN NETO INTERESES | D23: 0.43796568 | E23: 0.37489499 | F23: 0.52588818 | G23: 0.49373845 | H23: 0.47086115 | I23: 0.41019615 | J23: 0.47725567 | K23: 0.46845756 | L23: 0.33453796 | M23: 0.54599666 | N23: 0.48898484 | O23: 0.58951625 | P23: 0.55129715 | Q23: 0.50989957 | R23: 0.44771485 | S23: 0.47658953 | T23: 0.27430588 | U23: 0.68608062 | V23: 0.69198879 | W23: 0.72646484 | X23: 0.33590592 | Y23: 0.35731372 | Z23: 0.24645075 | AA23: 0.48537448 | AB23: 0.45753367 | AC23: 0.67298708 | AD23: 0.47622644 | AE23: 0.46338787 | AF23: 0.48668315 | AG23: 0.37901812 | AH23: #DIV/0! | AI23: 0.50911484 | AJ23: 0.47218062
B25: 52 | C25: COMISIONES GANADAS | D25: 0.062492186 | E25: 0.060078896 | F25: 0.03189731 | G25: 0.041511885 | H25: 0.0453576 | I25: 0.051452796 | J25: 0.080045549 | K25: 0.05855466 | L25: 0.13057261 | M25: 0.039033245 | N25: 0.068108956 | O25: 0.019826046 | P25: 0.01425966 | Q25: 0.027562261 | R25: 0.075109445 | S25: 0.0010356366 | T25: 0.011961862 | U25: 0.0039152397 | V25: 1.9926444e-06 | W25: 0 | X25: 0 | Y25: 0 | Z25: 0.011177214 | AA25: 0 | AB25: 0.0019468937 | AC25: 0 | AD25: 0.0024557697 | AE25: 0.053625621 | AF25: 0.067037651 | AG25: 0.11150928 | AH25: #DIV/0! | AI25: 0 | AJ25: 0.045413069
B26: 5201 | C26: Cartera de créditos | D26: 4.2189778e-05 | E26: 0 | F26: 0 | G26: 0 | H26: 7.7484473e-06 | I26: 0 | J26: 0 | K26: 0 | L26: 0 | M26: 0 | N26: 0 | O26: 0 | P26: 1.100657e-06 | Q26: 0 | R26: 4.8812131e-08 | S26: 0 | T26: 0 | U26: 0 | V26: 0 | W26: 0 | X26: 0 | Y26: 0 | Z26: 0 | AA26: 0 | AB26: 0 | AC26: 0 | AD26: 0 | AE26: 4.9081885e-06 | AF26: 0 | AG26: 0 | AH26: #DIV/0! | AI26: 0 | AJ26: 6.0459369e-06
B27: 5202 | C27: Deudores por aceptación | D27: 0 | E27: 0 | F27: 0 | G27: 0 | H27: 0 | I27: 0 | J27: 0 | K27: 8.9355933e-05 | L27: 0 | M27: 0 | N27: 0 | O27: 0 | P27: 0 | Q27: 0 | R27: 2.0638919e-06 | S27: 0 | T27: 0 | U27: 0 | V27: 0 | W27: 0 | X27: 0 | Y27: 0 | Z27: 0 | AA27: 0 | AB27: 0 | AC27: 0 | AD27: 0 | AE27: 6.8415019e-07 | AF27: 1.0019317e-05 | AG27: 0 | AH27: #DIV/0! | AI27: 0 | AJ27: 0
B28: 5203 | C28: Avales | D28: 0 | E28: 5.3939733e-05 | F28: 0.0015496953 | G28: 0.00083932421 | H28: 0.00081652523 | I28: 0.0048452872 | J28: 0.0036175237 | K28: 0 | L28: 0 | M28: 0.00034107474 | N28: 0.0029171992 | O28: 0.0017534132 | P28: 0.00010189455 | Q28: 0 | R28: 0.0018837353 | S28: 0 | T28: 0 | U28: 0 | V28: 0 | W28: 0 | X28: 0 | Y28: 0 | Z28: 0 | AA28: 0 | AB28: 0 | AC28: 0 | AD28: 0 | AE28: 0.0011399468 | AF28: 0.002590099 | AG28: 6.7166764e-05 | AH28: #DIV/0! | AI28: 0 | AJ28: 0.0011772983
B29: 5204 | C29: Fianzas | D29: 0.0072970668 | E29: 0.0054872039 | F29: 0.0042743428 | G29: 0.0064659826 | H29: 0.0054546383 | I29: 0.0020819152 | J29: 0.0066774419 | K29: 0.05530376 | L29: 0 | M29: 0.0017581522 | N29: 0.011584314 | O29: 0 | P29: 0.0024065113 | Q29: 4.0008908e-05 | R29: 0.0050957342 | S29: 0.00075186638 | T29: 0.0014085148 | U29: 0.0039152397 | V29: 0 | W29: 0 | X29: 0 | Y29: 0 | Z29: 0 | AA29: 0 | AB29: 0.00093666114 | AC29: 0 | AD29: 0.00063196666 | AE29: 0.0051564506 | AF29: 0.016486495 | AG29: 0.00034622733 | AH29: #DIV/0! | AI29: 0 | AJ29: 0.0049184545
B30: 5205 | C30: Cartas de Crédito | D30: 0.0039768272 | E30: 0.0016196435 | F30: 0.00093374601 | G30: 0.0033455147 | H30: 0.0020358674 | I30: 0.00049211364 | J30: 0.0068307706 | K30: 0.00031799425 | L30: 0 | M30: 8.4314147e-05 | N30: 0.010756154 | O30: 0 | P30: 0.00019595105 | Q30: 0 | R30: 0.0032939683 | S30: 0.00025490625 | T30: 0 | U30: 0 | V30: 0 | W30: 0 | X30: 0 | Y30: 0 | Z30: 0 | AA30: 0 | AB30: 0 | AC30: 0 | AD30: 6.3801858e-05 | AE30: 0.0023796253 | AF30: 0.0095857427 | AG30: 1.6603717e-05 | AH30: #DIV/0! | AI30: 0 | AJ30: 0.0021227311
B31: 5290 | C31: Otras | D31: 0.051176103 | E31: 0.052918109 | F31: 0.025139526 | G31: 0.030861063 | H31: 0.03704282 | I31: 0.04403348 | J31: 0.062919813 | K31: 0.0028435503 | L31: 0.13057261 | M31: 0.036849704 | N31: 0.042851289 | O31: 0.018072633 | P31: 0.011554203 | Q31: 0.027522252 | R31: 0.064833894 | S31: 2.8864002e-05 | T31: 0.010553347 | U31: 0 | V31: 1.9926444e-06 | W31: 0 | X31: 0 | Y31: 0 | Z31: 0.011177214 | AA31: 0 | AB31: 0.0010102325 | AC31: 0 | AD31: 0.0017600011 | AE31: 0.044944006 | AF31: 0.038365294 | AG31: 0.11107929 | AH31: #DIV/0! | AI31: 0 | AJ31: 0.037188539
B32: 54 | C32: INGRESOS POR SERVICIOS | D32: 0.20607462 | E32: 0.14847333 | F32: 0.12156278 | G32: 0.1392449 | H32: 0.14594725 | I32: 0.10401761 | J32: 0.11745568 | K32: 0.044751483 | L32: 0.21553007 | M32: 0.077857182 | N32: 0.091010043 | O32: 0.06146004 | P32: 0.082563955 | Q32: 0.12049209 | R32: 0.12915933 | S32: 0.017492983 | T32: 0.11270037 | U32: 0.1270997 | V32: 0.04628694 | W32: 0.061987825 | X32: 0.015727045 | Y32: 0.00059932777 | Z32: 0.48650646 | AA32: 0.0051557391 | AB32: 0.018215819 | AC32: 0.031523276 | AD32: 0.049293126 | AE32: 0.13679051 | AF32: 0.085823156 | AG32: 0.18707474 | AH32: #DIV/0! | AI32: 0.012454659 | AJ32: 0.13594436
B33: 5401 | C33: Servicios fiduciarios | D33: 0 | E33: 0 | F33: 0 | G33: 0 | H33: 0 | I33: 0 | J33: 0 | K33: 0 | L33: 0 | M33: 0 | N33: 0 | O33: 0 | P33: 0 | Q33: 0 | R33: 0 | S33: 0 | T33: 0 | U33: 0 | V33: 0 | W33: 0 | X33: 0 | Y33: 0 | Z33: 0 | AA33: 0 | AB33: 0 | AC33: 0 | AD33: 0 | AE33: 0 | AF33: 0 | AG33: 0 | AH33: #DIV/0! | AI33: 0 | AJ33: 0
B34: 5402 | C34: Servicios especiales | D34: 0 | E34: 0 | F34: 0 | G34: 0 | H34: 0 | I34: 0 | J34: 0 | K34: 0 | L34: 0 | M34: 0 | N34: 0 | O34: 0 | P34: 0 | Q34: 0 | R34: 0 | S34: 0 | T34: 0 | U34: 0 | V34: 0 | W34: 0 | X34: 0 | Y34: 0 | Z34: 0 | AA34: 0 | AB34: 0 | AC34: 0 | AD34: 0 | AE34: 0 | AF34: 0 | AG34: 0 | AH34: #DIV/0! | AI34: 0 | AJ34: 0
B35: 5404 | C35: Manejo y cobranzas | D35: 0.010333851 | E35: 0 | F35: 0 | G35: 0.00024287481 | H35: 0.0019371843 | I35: 0 | J35: 0.000162303 | K35: 0 | L35: 0 | M35: 0 | N35: 0 | O35: 0 | P35: 0 | Q35: 0 | R35: 2.9554637e-05 | S35: 0 | T35: 2.1690426e-07 | U35: 0.025119835 | V35: 0 | W35: 0 | X35: 0 | Y35: 0 | Z35: 0 | AA35: 0.0019316066 | AB35: 0 | AC35: 0 | AD35: 0.00091685458 | AE35: 0.0012669161 | AF35: 0 | AG35: 0 | AH35: #DIV/0! | AI35: 0.0007291015 | AJ35: 0.0015510184
B36: 5405 | C36: Garantías crediticias | D36: 0 | E36: 0 | F36: 0 | G36: 0 | H36: 0 | I36: 0 | J36: 0 | K36: 0 | L36: 0 | M36: 0 | N36: 0 | O36: 0 | P36: 0 | Q36: 0 | R36: 0 | S36: 0 | T36: 0 | U36: 0 | V36: 0 | W36: 0 | X36: 0 | Y36: 0 | Z36: 0 | AA36: 0 | AB36: 0 | AC36: 0 | AD36: 0 | AE36: 0 | AF36: 0 | AG36: 0 | AH36: #DIV/0! | AI36: 0 | AJ36: 0
... B59: 4390 | C59: Otras | D59: 0 | E59: 0 | F59: 0 | G59: 0 | H59: 0 | I59: 0 | J59: 0 | K59: 0 | L59: 0 | M59: 0 | N59: 0 | O59: 0 | P59: 0 | Q59: 0 | R59: 0 | S59: 0 | T59: 0 | U59: 0 | V59: 0 | W59: 0 | X59: 0 | Y59: 0 | Z59: 0 | AA59: 0 | AB59: 0 | AC59: 0 | AD59: 0 | AE59: 0 | AF59: 0 | AG59: 0 | AH59: #DIV/0! | AI59: 0 | AJ59: 0
C60: MARGEN BRUTO FINANCIERO | D60: 0.67348056 | E60: 0.53584444 | F60: 0.67216489 | G60: 0.68307303 | H60: 0.643767 | I60: 0.5139174 | J60: 0.67543612 | K60: 0.53185407 | L60: 0.70329965 | M60: 0.68691112 | N60: 0.65080848 | O60: 0.65890706 | P60: 0.63263315 | Q60: 0.49755112 | R60: 0.63856675 | S60: 0.47240046 | T60: 0.41962708 | U60: 0.7719163 | V60: 0.7358504 | W60: 0.7881352 | X60: 0.32690812 | Y60: 0.35606378 | Z60: 0.7028509 | AA60: 0.49033001 | AB60: 0.36182004 | AC60: 0.69668101 | AD60: 0.49886138 | AE60: 0.63665833 | AF60: 0.63747034 | AG60: 0.70033077 | AH60: #DIV/0! | AI60: 0.51838268 | AJ60: 0.62957582
B62: 44 | C62: PROVISIONES | D62: 0.19135312 | E62: 0.22035036 | F62: 0.22776126 | G62: 0.25897063 | H62: 0.22447185 | I62: 0.096498405 | J62: 0.1032692 | K62: 0.018581745 | L62: 0.29321132 | M62: 0.17365138 | N62: 0.1002029 | O62: 0.19103759 | P62: 0.10873335 | Q62: 0.0024685055 | R62: 0.14931104 | S62: 0.14863069 | T62: 0.11676094 | U62: 0.038006323 | V62: 0.020283057 | W62: 0.010920344 | X62: 0.092756611 | Y62: 0.48231013 | Z62: 0.12280307 | AA62: 0.05985948 | AB62: 0.16977349 | AC62: 0.22000313 | AD62: 0.15788781 | AE62: 0.19708279 | AF62: 0.091050867 | AG62: 0.26749963 | AH62: #DIV/0! | AI62: 0.23688011 | AJ62: 0.19600329
B63: 4401 | C63: Inversiones | D63: 0 | E63: 0 | F63: 0.04555335 | G63: 0 | H63: 0.019655887 | I63: 0.0018017966 | J63: 0 | K63: 0 | L63: 0 | M63: 0.022213765 | N63: 6.9370863e-09 | O63: 0 | P63: 0 | Q63: 0 | R63: 0.0016662851 | S63: 0 | T63: 0 | U63: 0.00038373092 | V63: 0 | W63: 0 | X63: 0 | Y63: 0 | Z63: 0 | AA63: 0 | AB63: 0 | AC63: 0 | AD63: 1.080962e-05 | AE63: 0.012962561 | AF63: 6.1592435e-09 | AG63: 0.0043744861 | AH63: #DIV/0! | AI63: 0 | AJ63: 0.015378732
B64: 4402 | C64: Cartera de créditos | D64: 0.17605497 | E64: 0.19242748 | F64: 0.14698019 | G64: 0.22563475 | H64: 0.17518382 | I64: 0.076672911 | J64: 0.10047594 | K64: 0.01799636 | L64: 0.27784923 | M64: 0.13534764 | N64: 0.07937895 | O64: 0.18379922 | P64: 0.10170374 | Q64: 0.0011750901 | R64: 0.13532981 | S64: 0.13785736 | T64: 0.085467527 | U64: 0.033575016 | V64: 0.011727908 | W64: 0.010437356 | X64: 0.070071594 | Y64: 0.47543562 | Z64: 0.11927278 | AA64: 0.057063128 | AB64: 0.1239415 | AC64: 0.21413646 | AD64: 0.14083722 | AE64: 0.16069644 | AF64: 0.072496233 | AG64: 0.24767376 | AH64: #DIV/0! | AI64: 0.23187526 | AJ64: 0.15547652
B65: 440205 | C65: Crédito productivo | D65: 0 | E65: 0 | F65: 0 | G65: 0 | H65: 0 | I65: 0 | J65: 0 | K65: 0 | L65: 0 | M65: 0 | N65: 0 | O65: 0 | P65: 0 | Q65: 0 | R65: 0 | S65: 0 | T65: 0 | U65: 0 | V65: 0 | W65: 0 | X65: 0 | Y65: 0 | Z65: 0 | AA65: 0 | AB65: 0 | AC65: 0 | AD65: 0 | AE65: 0 | AF65: 0 | AG65: 0 | AH65: #DIV/0! | AI65: 0 | AJ65: 0
B66: 440210 | C66: Crédito Productivo | D66: 0.0066436212 | E66: 0.042332824 | F66: 0.062295848 | G66: 0.089127293 | H66: 0.051964116 | I66: 0 | J66: 0.044070601 | K66: 0.01799636 | L66: 0.017243919 | M66: 0 | N66: 0.032494995 | O66: 0.04765866 | P66: 0.018635857 | Q66: 3.0363636e-06 | R66: 0.021373892 | S66: 0.094265731 | T66: 0.036223194 | U66: 0.0078562306 | V66: 0.00016663821 | W66: 0.0017060977 | X66: 0.0058470698 | Y66: 0 | Z66: 0.059947682 | AA66: 0 | AB66: 0.0032582484 | AC66: 0 | AD66: 0.030724957 | AE66: 0.041034629 | AF66: 0.030869289 | AG66: 0.01371253 | AH66: #DIV/0! | AI66: 0 | AJ66: 0.04610509
B67: 440215 | C67: Crédito comercial ordinario | D67: 0 | E67: 0 | F67: 0 | G67: 0 | H67: 0 | I67: 0 | J67: 0 | K67: 0 | L67: 0 | M67: 0 | N67: 0 | O67: 0 | P67: 0 | Q67: 0 | R67: 0 | S67: 0 | T67: 0 | U67: 0 | V67: 0 | W67: 0 | X67: 0 | Y67: 0 | Z67: 0 | AA67: 0 | AB67: 0 | AC67: 0 | AD67: 0 | AE67: 0 | AF67: 0 | AG67: 0 | AH67: #DIV/0! | AI67: 0 | AJ67: 0
B68: 440220 | C68: Crédito de Consumo | D68: 0.1348666 | E68: 0.12670824 | F68: 0.04340653 | G68: 0.13202912 | H68: 0.093123583 | I68: 0.074817402 | J68: 0.054920767 | K68: 0 | L68: 0.26060531 | M68: 0.13534764 | N68: 0.046749047 | O68: 0.12024703 | P68: 0.075979357 | Q68: 0.0010733854 | R68: 0.11255854 | S68: 0.0013534761 | T68: 0.048319692 | U68: 0.0070052741 | V68: 0.01151874 | W68: 0.00012163839 | X68: 0.064224524 | Y68: 0.0024867724 | Z68: 0.048369705 | AA68: 0 | AB68: 0.032317004 | AC68: 2.5853195e-05 | AD68: 0.015126725 | AE68: 0.096667533 | AF68: 0.041507162 | AG68: 0.23396089 | AH68: #DIV/0! | AI68: 0.00074154054 | AJ68: 0.084092975
B69: 440225 | C69: Crédito de consumo ordinario | D69: 0 | E69: 0 | F69: 0 | G69: 0 | H69: 0 | I69: 0 | J69: 0 | K69: 0 | L69: 0 | M69: 0 | N69: 0 | O69: 0 | P69: 0 | Q69: 0 | R69: 0 | S69: 0 | T69: 0 | U69: 0 | V69: 0 | W69: 0 | X69: 0 | Y69: 0 | Z69: 0 | AA69: 0 | AB69: 0 | AC69: 0 | AD69: 0 | AE69: 0 | AF69: 0 | AG69: 0 | AH69: #DIV/0! | AI69: 0 | AJ69: 0
B70: 440230 | C70: Crédito inmobiliario | D70: 0.0026666002 | E70: 0.0081730626 | F70: 0.0069461834 | G70: 0.0018171234 | H70: 0.0056038962 | I70: 0 | J70: 0.0013813264 | K70: 0 | L70: 0 | M70: 0 | N70: 0 | O70: 0.0037285519 | P70: 0.0029268769 | Q70: 8.8943198e-05 | R70: 0.00051726569 | S70: 0.009265867 | T70: 0.00032242197 | U70: 2.5013726e-06 | V70: 7.0174293e-06 | W70: 0 | X70: 0 | Y70: 0 | Z70: 0.010202097 | AA70: 0 | AB70: 0.0051162303 | AC70: 0 | AD70: 0.003660005 | AE70: 0.0038455148 | AF70: 0 | AG70: 5.5720445e-08 | AH70: #DIV/0! | AI70: 0 | AJ70: 0.0047369213
B71: 440235 | C71: Crédito de vivienda de interés social y público | D71: 0 | E71: 0.0029841621 | F71: 4.3786655e-05 | G71: 0 | H71: 0.0006844743 | I71: 0 | J71: 0 | K71: 0 | L71: 0 | M71: 0 | N71: 3.7916879e-06 | O71: 0 | P71: 0 | Q71: 0 | R71: 6.9347638e-07 | S71: 0 | T71: 0 | U71: 0 | V71: 0 | W71: 0 | X71: 0 | Y71: 0 | Z71: 0 | AA71: 0 | AB71: 0 | AC71: 0 | AD71: 0 | AE71: 0.00043237501 | AF71: 3.3665328e-06 | AG71: 0 | AH71: #DIV/0! | AI71: 0 | AJ71: 0.00053231904
B72: 440240 | C72: Microcrédito | D72: 0.031758687 | E72: 0.0025696522 | F72: 0.034164435 | G72: 0.0026114246 | H72: 0.021570064 | I72: 0.0018555085 | J72: 0 | K72: 0 | L72: 0 | M72: 0 | N72: 0.00013111687 | O72: 0.012157991 | P72: 0.0039302999 | Q72: 9.7251167e-06 | R72: 0.00085011769 | S72: 0.032913071 | T72: 0.00060221879 | U72: 0.01871101 | V72: 3.5512244e-05 | W72: 0.0086096201 | X72: 0 | Y72: 0.47294885 | Z72: 0.00075329289 | AA72: 0.057063128 | AB72: 0.083250018 | AC72: 0.21411061 | AD72: 0.09131071 | AE72: 0.017293349 | AF72: 0.00011641498 | AG72: 2.8197762e-07 | AH72: #DIV/0! | AI72: 0.23113372 | AJ72: 0.018256312
B73: 440245 | C73: Crédito educativo | D73: 0.000119464 | E73: 0.0096595382 | F73: 0.00012340645 | G73: 4.9794473e-05 | H73: 0.0022376881 | I73: 0 | J73: 0.00010324788 | K73: 0 | L73: 0 | M73: 0 | N73: 0 | O73: 6.9868564e-06 | P73: 0.00023135098 | Q73: 0 | R73: 2.9302112e-05 | S73: 5.9214268e-05 | T73: 0 | U73: 0 | V73: 0 | W73: 0 | X73: 0 | Y73: 0 | Z73: 0 | AA73: 0 | AB73: 0 | AC73: 0 | AD73: 1.4821058e-05 | AE73: 0.0014230358 | AF73: 0 | AG73: 0 | AH73: #DIV/0! | AI73: 0 | AJ73: 0.0017529043
... B79: 4407 | C79: Operaciones interbancarias y de reporto | D79: 0 | E79: 0 | F79: 0 | G79: 0 | H79: 0 | I79: 0 | J79: 0 | K79: 0 | L79: 0 | M79: 0 | N79: 0 | O79: 0 | P79: 0 | Q79: 0 | R79: 0 | S79: 0 | T79: 0 | U79: 0 | V79: 0 | W79: 0 | X79: 0 | Y79: 0 | Z79: 0 | AA79: 0 | AB79: 0 | AC79: 0 | AD79: 0 | AE79: 0 | AF79: 0 | AG79: 0 | AH79: #DIV/0! | AI79: 0 | AJ79: 0
C80: MARGEN NETO FINANCIERO | D80: 0.48212744 | E80: 0.31549408 | F80: 0.44440363 | G80: 0.42410239 | H80: 0.41929516 | I80: 0.417419 | J80: 0.57216692 | K80: 0.51327233 | L80: 0.41008833 | M80: 0.51325974 | N80: 0.55060558 | O80: 0.46786947 | P80: 0.52389981 | Q80: 0.49508262 | R80: 0.48925571 | S80: 0.32376977 | T80: 0.30286613 | U80: 0.73390998 | V80: 0.71556734 | W80: 0.77721485 | X80: 0.23415151 | Y80: -0.12624635 | Z80: 0.58004783 | AA80: 0.43047053 | AB80: 0.19204655 | AC80: 0.47667787 | AD80: 0.34097358 | AE80: 0.43957554 | AF80: 0.54641947 | AG80: 0.43283114 | AH80: #DIV/0! | AI80: 0.28150257 | AJ80: 0.43357252
B82: 45 | C82: GASTOS DE OPERACIÓN | D82: 0.36006545 | E82: 0.38376605 | F82: 0.44086902 | G82: 0.4118908 | H82: 0.40860369 | I82: 0.38195199 | J82: 0.42396075 | K82: 0.68340004 | L82: 0.38620491 | M82: 0.39476669 | N82: 0.35604513 | O82: 0.3967408 | P82: 0.46762437 | Q82: 0.45445782 | R82: 0.40398457 | S82: 0.46142 | T82: 0.35309592 | U82: 0.69137409 | V82: 0.70287991 | W82: 0.65537125 | X82: 1.0936854 | Y82: 0.51204758 | Z82: 0.71164519 | AA82: 0.48632326 | AB82: 0.31103508 | AC82: 0.44268271 | AD82: 0.46873607 | AE82: 0.40930711 | AF82: 0.39275084 | AG82: 0.39040544 | AH82: #DIV/0! | AI82: 0.47960304 | AJ82: 0.41231976
B83: 4501 | C83: Gastos de personal | D83: 0.13309243 | E83: 0.13469153 | F83: 0.10311603 | G83: 0.11457475 | H83: 0.11751811 | I83: 0.11588339 | J83: 0.13172946 | K83: 0.20484936 | L83: 0.07885409 | M83: 0.14067906 | N83: 0.11841358 | O83: 0.16274352 | P83: 0.18942307 | Q83: 0.24978278 | R83: 0.12897234 | S83: 0.15126177 | T83: 0.12628741 | U83: 0.24148888 | V83: 0.33221114 | W83: 0.22150674 | X83: 0.43718792 | Y83: 0.27718343 | Z83: 0.28458514 | AA83: 0.23704864 | AB83: 0.17228123 | AC83: 0.26712689 | AD83: 0.20329902 | AE83: 0.12450274 | AF83: 0.12810546 | AG83: 0.093040814 | AH83: #DIV/0! | AI83: 0.25873813 | AJ83: 0.12667006
B84: 4502 | C84: Honorarios | D84: 0.005270953 | E84: 0.011970142 | F84: 0.050018112 | G84: 0.009208075 | H84: 0.026710228 | I84: 0.033136974 | J84: 0.0047742123 | K84: 0.0062706043 | L84: 0.0042917934 | M84: 0.015176171 | N84: 0.0012473291 | O84: 0.0058834384 | P84: 0.0070444933 | Q84: 0.010736046 | R84: 0.0088740067 | S84: 0.011776593 | T84: 0.017393865 | U84: 0.040806613 | V84: 0.055877986 | W84: 0.03978808 | X84: 0.097685916 | Y84: 0.026498654 | Z84: 0.031168289 | AA84: 0.032214652 | AB84: 0.0093671101 | AC84: 0.030682435 | AD84: 0.022765573 | AE84: 0.020651191 | AF84: 0.0018105798 | AG84: 0.0068448287 | AH84: #DIV/0! | AI84: 0.030027461 | AJ84: 0.023970529
B85: 4503 | C85: Servicios varios | D85: 0.098346997 | E85: 0.087860104 | F85: 0.11698545 | G85: 0.14970935 | H85: 0.11236149 | I85: 0.10558178 | J85: 0.089762004 | K85: 0.26528535 | L85: 0.2086286 | M85: 0.092122415 | N85: 0.046346447 | O85: 0.082357133 | P85: 0.11066789 | Q85: 0.096711732 | R85: 0.12038562 | S85: 0.13522392 | T85: 0.073474806 | U85: 0.11892134 | V85: 0.12072236 | W85: 0.089565687 | X85: 0.19036524 | Y85: 0.091017408 | Z85: 0.29799072 | AA85: 0.073407491 | AB85: 0.053314584 | AC85: 0.084934954 | AD85: 0.10050837 | AE85: 0.1145809 | AF85: 0.070895666 | AG85: 0.18498741 | AH85: #DIV/0! | AI85: 0.082376839 | AJ85: 0.10920444
B86: 4504 | C86: Impuestos, contribuciones y multas | D86: 0.063451623 | E86: 0.071311742 | F86: 0.069435944 | G86: 0.076810806 | H86: 0.069948609 | I86: 0.081421625 | J86: 0.1123895 | K86: 0.18882139 | L86: 0.067118548 | M86: 0.062019766 | N86: 0.089772349 | O86: 0.094195516 | P86: 0.086525934 | Q86: 0.054162141 | R86: 0.084509861 | S86: 0.086127429 | T86: 0.068659822 | U86: 0.10901569 | V86: 0.086138765 | W86: 0.1052785 | X86: 0.097247855 | Y86: 0.048005159 | Z86: 0.065883558 | AA86: 0.036109308 | AB86: 0.038907184 | AC86: 0.019550421 | AD86: 0.061745192 | AE86: 0.074470604 | AF86: 0.10087854 | AG86: 0.066265487 | AH86: #DIV/0! | AI86: 0.034188789 | AJ86: 0.073882567
B87: 4505 | C87: Depreciaciones | D87: 0.018270259 | E87: 0.018498069 | F87: 0.01625543 | G87: 0.012894752 | H87: 0.016581857 | I87: 0.012816232 | J87: 0.014176998 | K87: 0.00605156 | L87: 0.0061700555 | M87: 0.01018969 | N87: 0.015358369 | O87: 0.016419003 | P87: 0.029752428 | Q87: 0.011758154 | R87: 0.012250081 | S87: 0.015122929 | T87: 0.019645584 | U87: 0.061293727 | V87: 0.017688382 | W87: 0.03425221 | X87: 0.087618246 | Y87: 0.017846701 | Z87: 0.0039578335 | AA87: 0.01237649 | AB87: 0.012459156 | AC87: 0.01091191 | AD87: 0.017957265 | AE87: 0.015197048 | AF87: 0.014314813 | AG87: 0.0070530882 | AH87: #DIV/0! | AI87: 0.013509011 | AJ87: 0.016389275
B88: 4506 | C88: Amortizaciones | D88: 0.019552391 | E88: 0.017651325 | F88: 0.010840489 | G88: 0.018306366 | H88: 0.015167645 | I88: 0.010107734 | J88: 0.011199335 | K88: 0.0013023768 | L88: 0.0011823184 | M88: 0.02521125 | N88: 0.011216189 | O88: 0.0031491955 | P88: 0.015836613 | Q88: 0.0063084875 | R88: 0.0086518927 | S88: 0.0072517349 | T88: 0.011085545 | U88: 0.0361766 | V88: 0.055117962 | W88: 0.007200431 | X88: 0.040063944 | Y88: 0.0086925479 | Z88: 0.017093913 | AA88: 0.032314975 | AB88: 0.0073199334 | AC88: 0.0077476988 | AD88: 0.013343953 | AE88: 0.012939997 | AF88: 0.010104571 | AG88: 0.0063425242 | AH88: #DIV/0! | AI88: 0.017299357 | AJ88: 0.014008984
B89: 4507 | C89: Otros gastos | D89: 0.022080797 | E89: 0.04178314 | F89: 0.074217568 | G89: 0.030386699 | H89: 0.050315749 | I89: 0.023004261 | J89: 0.059929242 | K89: 0.010819404 | L89: 0.019959497 | M89: 0.049368333 | N89: 0.073690872 | O89: 0.031992991 | P89: 0.028373943 | Q89: 0.024998475 | R89: 0.04034078 | S89: 0.054655625 | T89: 0.036548893 | U89: 0.08367124 | V89: 0.035123313 | W89: 0.1577796 | X89: 0.1435163 | Y89: 0.042803675 | Z89: 0.010965739 | AA89: 0.062851697 | AB89: 0.01738588 | AC89: 0.021728397 | AD89: 0.049116701 | AE89: 0.046964634 | AF89: 0.066641209 | AG89: 0.025871291 | AH89: #DIV/0! | AI89: 0.043463448 | AJ89: 0.048193909
C90: MARGEN DE INTERMEDIACIÓN | D90: 0.12206199 | E90: -0.068271974 | F90: 0.0035346041 | G90: 0.012211595 | H90: 0.010691466 | I90: 0.035467005 | J90: 0.14820617 | K90: -0.17012771 | L90: 0.02388342 | M90: 0.11849306 | N90: 0.19456045 | O90: 0.071128672 | P90: 0.056275436 | Q90: 0.0406248 | R90: 0.085271134 | S90: -0.13765023 | T90: -0.050229786 | U90: 0.042535887 | V90: 0.012687429 | W90: 0.1218436 | X90: -0.85953391 | Y90: -0.63829392 | Z90: -0.13159736 | AA90: -0.055852726 | AB90: -0.11898853 | AC90: 0.033995168 | AD90: -0.12776249 | AE90: 0.030268427 | AF90: 0.15366864 | AG90: 0.042425696 | AH90: #DIV/0! | AI90: -0.19810046 | AJ90: 0.021252761
B92: 55 | C92: OTROS INGRESOS OPERACIONALES | D92: 0.0011579866 | E92: 0.01711312 | F92: 0.061033017 | G92: 0.021270154 | H92: 0.033806579 | I92: 0.012991566 | J92: 0.017260072 | K92: 0.013905815 | L92: 0.057158537 | M92: 0.00065579937 | N92: 0.0035988302 | O92: 0.0076569649 | P92: 0.00046868454 | Q92: 0.033287023 | R92: 0.023757297 | S92: 0.0088495408 | T92: 0.00064071308 | U92: 0 | V92: 0.046724698 | W92: 0 | X92: 0.031971674 | Y92: 0.18257887 | Z92: 0 | AA92: 0.10508455 | AB92: 0.0060129291 | AC92: 0 | AD92: 0.031819393 | AE92: 0.030401542 | AF92: 0.0047545335 | AG92: 0.045948785 | AH92: #DIV/0! | AI92: 0.093486858 | AJ92: 0.029638101
B93: 5501 | C93: Utilidades en acciones y participaciones | D93: 0.0011579866 | E93: 0.001105731 | F93: 0.043698368 | G93: 0.0089383529 | H93: 0.020761118 | I93: 0.0034726502 | J93: 0.0029582594 | K93: 0.0044592561 | L93: 0.041603708 | M93: 0 | N93: 0.0035170399 | O93: 0.0047459467 | P93: 0 | Q93: 0 | R93: 0.012783176 | S93: 0 | T93: 0.00064071308 | U93: 0 | V93: 0 | W93: 0 | X93: 0 | Y93: 0 | Z93: 0 | AA93: 0 | AB93: 0 | AC93: 0 | AD93: 7.1899073e-05 | AE93: 0.01734771 | AF93: 0.0036226888 | AG93: 0.033080477 | AH93: #DIV/0! | AI93: 0 | AJ93: 0.016613006
B94: 5502 | C94: Utilidad en venta de bienes realizables y recuperados | D94: 0 | E94: 0 | F94: 0 | G94: 0 | H94: 0 | I94: 0 | J94: 0 | K94: 0 | L94: 0 | M94: 0 | N94: 0 | O94: 0 | P94: 0 | Q94: 0 | R94: 0 | S94: 0 | T94: 0 | U94: 0 | V94: 0 | W94: 0 | X94: 0 | Y94: 0 | Z94: 0 | AA94: 0 | AB94: 0.00016625373 | AC94: 0 | AD94: 3.1137578e-05 | AE94: 1.1571097e-06 | AF94: 0 | AG94: 0 | AH94: #DIV/0! | AI94: 0 | AJ94: 1.4253349e-06
B95: 5503 | C95: Dividendos por certificados de aportación | D95: 0 | E95: 0.016007389 | F95: 0.01733465 | G95: 0.012331802 | H95: 0.013045462 | I95: 0.0095189162 | J95: 0.014301813 | K95: 0.0094465587 | L95: 0.015554828 | M95: 0.00065579937 | N95: 8.1790338e-05 | O95: 0.0029110182 | P95: 0.00046868454 | Q95: 0.033287023 | R95: 0.010974121 | S95: 0.0088495408 | T95: 0 | U95: 0 | V95: 0.046724698 | W95: 0 | X95: 0.031971674 | Y95: 0.18257887 | Z95: 0 | AA95: 0.10508455 | AB95: 0.0058466754 | AC95: 0 | AD95: 0.031716356 | AE95: 0.013052675 | AF95: 0.0011318447 | AG95: 0.012868308 | AH95: #DIV/0! | AI95: 0.093486858 | AJ95: 0.01302367
B96: 5504 | C96: Convenios | D96: 0 | E96: 0 | F96: 0 | G96: 0 | H96: 0 | I96: 0 | J96: 0 | K96: 0 | L96: 0 | M96: 0 | N96: 0 | O96: 0 | P96: 0 | Q96: 0 | R96: 0 | S96: 0 | T96: 0 | U96: 0 | V96: 0 | W96: 0 | X96: 0 | Y96: 0 | Z96: 0 | AA96: 0 | AB96: 0 | AC96: 0 | AD96: 0 | AE96: 0 | AF96: 0 | AG96: 0 | AH96: #DIV/0! | AI96: 0 | AJ96: 0
B97: 5505 | C97: Ingresos por subsidios realizados | D97: 0 | E97: 0 | F97: 0 | G97: 0 | H97: 0 | I97: 0 | J97: 0 | K97: 0 | L97: 0 | M97: 0 | N97: 0 | O97: 0 | P97: 0 | Q97: 0 | R97: 0 | S97: 0 | T97: 0 | U97: 0 | V97: 0 | W97: 0 | X97: 0 | Y97: 0 | Z97: 0 | AA97: 0 | AB97: 0 | AC97: 0 | AD97: 0 | AE97: 0 | AF97: 0 | AG97: 0 | AH97: #DIV/0! | AI97: 0 | AJ97: 0
B98: 5506 | C98: Ingresos por subsidios recuperados | D98: 0 | E98: 0 | F98: 0 | G98: 0 | H98: 0 | I98: 0 | J98: 0 | K98: 0 | L98: 0 | M98: 0 | N98: 0 | O98: 0 | P98: 0 | Q98: 0 | R98: 0 | S98: 0 | T98: 0 | U98: 0 | V98: 0 | W98: 0 | X98: 0 | Y98: 0 | Z98: 0 | AA98: 0 | AB98: 0 | AC98: 0 | AD98: 0 | AE98: 0 | AF98: 0 | AG98: 0 | AH98: #DIV/0! | AI98: 0 | AJ98: 0
B99: 5507 | C99: Ingresos por demora en transferencias | D99: 0 | E99: 0 | F99: 0 | G99: 0 | H99: 0 | I99: 0 | J99: 0 | K99: 0 | L99: 0 | M99: 0 | N99: 0 | O99: 0 | P99: 0 | Q99: 0 | R99: 0 | S99: 0 | T99: 0 | U99: 0 | V99: 0 | W99: 0 | X99: 0 | Y99: 0 | Z99: 0 | AA99: 0 | AB99: 0 | AC99: 0 | AD99: 0 | AE99: 0 | AF99: 0 | AG99: 0 | AH99: #DIV/0! | AI99: 0 | AJ99: 0
B100: 5590 | C100: Otros | D100: 0 | E100: 0.016007389 | F100: 0.01733465 | G100: 0.012331802 | H100: 0.013045462 | I100: 0.0095189162 | J100: 0.014301813 | K100: 0.0094465587 | L100: 0.015554828 | M100: 0.00065579937 | N100: 8.1790338e-05 | O100: 0.0029110182 | P100: 0.00046868454 | Q100: 0.033287023 | R100: 0.010974121 | S100: 0.0088495408 | T100: 0 | U100: 0 | V100: 0.046724698 | W100: 0 | X100: 0.031971674 | Y100: 0.18257887 | Z100: 0 | AA100: 0.10508455 | AB100: 0.0058466754 | AC100: 0 | AD100: 0.031716356 | AE100: 0.013052675 | AF100: 0.0011318447 | AG100: 0.012868308 | AH100: #DIV/0! | AI100: 0.093486858 | AJ100: 0.01302367
B101: 46 | C101: OTRAS PÉRDIDAS OPERACIONALES | D101: 0.00037088977 | E101: 0.0029894711 | F101: 0.05720471 | G101: 0.0059593678 | H101: 0.02638254 | I101: 2.465909e-07 | J101: 0.00066496403 | K101: 0.00026392921 | L101: 0.029308515 | M101: 0.0063222525 | N101: 0.0012251598 | O101: 0.0032057588 | P101: 0 | Q101: 0.068899779 | R101: 0.014160977 | S101: 0 | T101: 0.0018866194 | U101: 1.3758925e-08 | V101: 0.0021989794 | W101: 4.9631609e-05 | X101: 0.00037249879 | Y101: 0 | Z101: 0 | AA101: 0.020859301 | AB101: 5.430234e-06 | AC101: 0 | AD101: 0.0025321129 | AE101: 0.021444959 | AF101: 0.0011173787 | AG101: 0.024566646 | AH101: #DIV/0! | AI101: 0.0078735223 | AJ101: 0.022912949
B102: 4601 | C102: Pérdida en acciones y participaciones | D102: 0 | E102: 0.00014353868 | F102: 0.046760173 | G102: 0.0059568216 | H102: 0.021172531 | I102: 0 | J102: 0.00039846448 | K102: 0 | L102: 0.029308515 | M102: 0 | N102: 0.0012251598 | O102: 0.0028923146 | P102: 0 | Q102: 0 | R102: 0.0080761166 | S102: 0 | T102: 0.00031475019 | U102: 0 | V102: 0 | W102: 0 | X102: 0 | Y102: 0 | Z102: 0 | AA102: 0 | AB102: 0 | AC102: 0 | AD102: 3.5320407e-05 | AE102: 0.016045776 | AF102: 0.0010877848 | AG102: 0.023304164 | AH102: #DIV/0! | AI102: 0 | AJ102: 0.016537988
B103: 4602 | C103: Pérdida en venta de bienes realizables y recuperados | D103: 0.00035764297 | E103: 3.6426877e-05 | F103: 1.3732572e-05 | G103: 2.5462005e-06 | H103: 8.0145696e-05 | I103: 0 | J103: 0 | K103: 0 | L103: 0 | M103: 3.0758929e-06 | N103: 0 | O103: 0 | P103: 0 | Q103: 0 | R103: 1.9961094e-07 | S103: 0 | T103: 0 | U103: 0 | V103: 0.0021949343 | W103: 0 | X103: 0.00037249879 | Y103: 0 | Z103: 0 | AA103: 0 | AB103: 0 | AC103: 0 | AD103: 5.6946081e-05 | AE103: 5.2782605e-05 | AF103: 0 | AG103: 1.8034147e-05 | AH103: #DIV/0! | AI103: 0 | AJ103: 6.2591268e-05
B104: 4690 | C104: Otras | D104: 1.3246803e-05 | E104: 0.0028095055 | F104: 0.010430805 | G104: 0 | H104: 0.0051298632 | I104: 2.465909e-07 | J104: 0.00026649956 | K104: 0.00026392921 | L104: 0 | M104: 0.0063191766 | N104: 0 | O104: 0.00031344423 | P104: 0 | Q104: 0.068899779 | R104: 0.0060846603 | S104: 0 | T104: 0.0015718693 | U104: 1.3758925e-08 | V104: 4.0450681e-06 | W104: 4.9631609e-05 | X104: 0 | Y104: 0 | Z104: 0 | AA104: 0.020859301 | AB104: 5.430234e-06 | AC104: 0 | AD104: 0.0024398464 | AE104: 0.0053464003 | AF104: 2.95939e-05 | AG104: 0.0012444475 | AH104: #DIV/0! | AI104: 0.0078735223 | AJ104: 0.0063123695
C105: MARGEN OPERACIONAL | D105: 0.12284908 | E105: -0.054148325 | F105: 0.007362911 | G105: 0.027522382 | H105: 0.018115506 | I105: 0.048458325 | J105: 0.16480128 | K105: -0.15648583 | L105: 0.051733442 | M105: 0.11282661 | N105: 0.19693412 | O105: 0.075579878 | P105: 0.05674412 | Q105: 0.0050120444 | R105: 0.094867455 | S105: -0.12880069 | T105: -0.051475692 | U105: 0.042535874 | V105: 0.057213148 | W105: 0.12179397 | X105: -0.82793474 | Y105: -0.45571505 | Z105: -0.13159736 | AA105: 0.028372523 | AB105: -0.11298103 | AC105: 0.033995168 | AD105: -0.098475214 | AE105: 0.039225011 | AF105: 0.15730579 | AG105: 0.063807835 | AH105: #DIV/0! | AI105: -0.11248713 | AJ105: 0.027977914
B107: 56 | C107: OTROS INGRESOS | D107: 0.032506874 | E107: 0.11805579 | F107: 0.1025276 | G107: 0.076910809 | H107: 0.088986029 | I107: 0.060808321 | J107: 0.0078577131 | K107: 0.37178114 | L107: 0.0756367 | M107: 0.026366259 | N107: 0.031122343 | O107: 0.03966094 | P107: 0.02930983 | Q107: 0.042115973 | R107: 0.050921337 | S107: 0.12955848 | T107: 0.060484545 | U107: 0.045715173 | V107: 0.023438822 | W107: 0.016662396 | X107: 0.15421437 | Y107: 0.075242449 | Z107: 0.15291376 | AA107: 0.046533691 | AB107: 0.2344909 | AC107: 0.074333061 | AD107: 0.11195829 | AE107: 0.077221814 | AF107: 0.069319791 | AG107: 0.065519562 | AH107: #DIV/0! | AI107: 0.064108026 | AJ107: 0.079633365
B108: 5601 | C108: Utilidad en venta de bienes | D108: 0.00022891133 | E108: 0.00043713003 | F108: 0.013990283 | G108: 1.4722713e-05 | H108: 0.0061786091 | I108: 0.00075727182 | J108: 0 | K108: 0 | L108: 1.4447515e-06 | M108: 1.7163804e-05 | N108: 2.8324741e-05 | O108: 0.00013584665 | P108: 8.4217802e-06 | Q108: 0.00017164757 | R108: 0.00012015372 | S108: 0.00025176586 | T108: 0.00016643395 | U108: 0 | V108: 0.0084102877 | W108: 0 | X108: 0 | Y108: 0 | Z108: 0 | AA108: 5.1122914e-06 | AB108: 0.00014781784 | AC108: 0.0039622564 | AD108: 0.00067887232 | AE108: 0.0039659424 | AF108: 2.514874e-05 | AG108: 7.1308932e-05 | AH108: #DIV/0! | AI108: 0.0013005786 | AJ108: 0.0048564788
B109: 5602 | C109: Utilidad en venta de acciones y participaciones | D109: 0 | E109: 0 | F109: 0 | G109: 0 | H109: 0 | I109: 0 | J109: 0 | K109: 0 | L109: 0 | M109: 0 | N109: 0 | O109: 0 | P109: 0 | Q109: 0 | R109: 0 | S109: 0 | T109: 0 | U109: 0 | V109: 0 | W109: 0 | X109: 0 | Y109: 0 | Z109: 0 | AA109: 0 | AB109: 0 | AC109: 0 | AD109: 0 | AE109: 0 | AF109: 0 | AG109: 0 | AH109: #DIV/0! | AI109: 0 | AJ109: 0
B110: 5603 | C110: Arrendamientos | D110: 4.9686443e-06 | E110: 0.00020464115 | F110: 0.001098013 | G110: 0.002079247 | H110: 0.00085678925 | I110: 0.00033418969 | J110: 0 | K110: 0 | L110: 0.00020392967 | M110: 0 | N110: 0.00069746872 | O110: 0.0004032957 | P110: 0 | Q110: 0 | R110: 0.00023659695 | S110: 0 | T110: 0.011418302 | U110: 0 | V110: 0 | W110: 0.00042430063 | X110: 0.0075799466 | Y110: 0 | Z110: 0 | AA110: 0 | AB110: 0 | AC110: 0 | AD110: 0.0014241143 | AE110: 0.00067228699 | AF110: 0.00061926283 | AG110: 0.00016215119 | AH110: #DIV/0! | AI110: 0 | AJ110: 0.00075422108
B111: 5604 | C111: Recuperaciones de activos financieros | D111: 0.031751095 | E111: 0.088869496 | F111: 0.075280077 | G111: 0.064324172 | H111: 0.068543813 | I111: 0.059440239 | J111: 0.0065766482 | K111: 0.27971458 | L111: 0.070913731 | M111: 0.022648736 | N111: 0.016470736 | O111: 0.032195192 | P111: 0.019935113 | Q111: 0.037844132 | R111: 0.043211249 | S111: 0.12800241 | T111: 0.024580433 | U111: 0.045715173 | V111: 0.014679947 | W111: 0.014932316 | X111: 0.13760051 | Y111: 0.075242449 | Z111: 0.15291376 | AA111: 0.024892337 | AB111: 0.22734376 | AC111: 0.030300337 | AD111: 0.099148708 | AE111: 0.061283751 | AF111: 0.045987787 | AG111: 0.060962546 | AH111: #DIV/0! | AI111: 0.04150737 | AJ111: 0.0628733
B112: 5690 | C112: Otros | D112: 0.00052189895 | E112: 0.028544525 | F112: 0.012159227 | G112: 0.010492668 | H112: 0.013406818 | I112: 0.00027662092 | J112: 0.001281065 | K112: 0.092066559 | L112: 0.0045175945 | M112: 0.0037003598 | N112: 0.013925814 | O112: 0.0069266058 | P112: 0.0093662956 | Q112: 0.0041001934 | R112: 0.0073533376 | S112: 0.0013043005 | T112: 0.024319375 | U112: 0 | V112: 0.00034858657 | W112: 0.0013057791 | X112: 0.0090339067 | Y112: 0 | Z112: 0 | AA112: 0.021636242 | AB112: 0.0069993249 | AC112: 0.040070468 | AD112: 0.010706591 | AE112: 0.011299834 | AF112: 0.022687593 | AG112: 0.0043235559 | AH112: #DIV/0! | AI112: 0.021300077 | AJ112: 0.011149365
B113: 47 | C113: OTROS GASTOS Y PÉRDIDAS | D113: 0.0086802799 | E113: 0.028385452 | F113: 0.012663239 | G113: 0.0014470509 | H113: 0.013623454 | I113: 0.027994322 | J113: 0.0013984574 | K113: 0.010978853 | L113: 0.0075208656 | M113: 0.0036389732 | N113: 0.031639492 | O113: 0.00065127246 | P113: 0.012224484 | Q113: 0.0073826024 | R113: 0.013158739 | S113: 0.0022193589 | T113: 0.005664814 | U113: 0.068978334 | V113: 0.00043443965 | W113: 0.00024277178 | X113: 0 | Y113: 0.18008886 | Z113: 0 | AA113: 0.017133787 | AB113: 0.03347675 | AC113: 0.010021759 | AD113: 0.027460794 | AE113: 0.01398362 | AF113: 0.029322853 | AG113: 0.0067001486 | AH113: #DIV/0! | AI113: 0.062839746 | AJ113: 0.013031756
B114: 4701 | C114: Pérdida en venta de bienes | D114: 0.0002648795 | E114: 0 | F114: 0.00030112608 | G114: 6.0764134e-08 | H114: 0.00017859017 | I114: 0.00013145002 | J114: 0 | K114: 0 | L114: 6.8076471e-05 | M114: 0 | N114: 0.00038688748 | O114: 0 | P114: 0 | Q114: 1.4838313e-05 | R114: 0.00010619937 | S114: 0.00024146545 | T114: 0 | U114: 0 | V114: 0 | W114: 0 | X114: 0 | Y114: 0.00045571583 | Z114: 0 | AA114: 0 | AB114: 0.00019714522 | AC114: 0 | AD114: 0.00013590837 | AE114: 0.00015300757 | AF114: 0.0003435065 | AG114: 5.4129841e-05 | AH114: #DIV/0! | AI114: 0.00013433889 | AJ114: 0.00015053457
B115: 4702 | C115: Pérdida en venta de acciones y participaciones | D115: 0 | E115: 0 | F115: 0 | G115: 0 | H115: 0 | I115: 0 | J115: 0 | K115: 0 | L115: 0 | M115: 0 | N115: 0 | O115: 0 | P115: 0 | Q115: 0 | R115: 0 | S115: 0 | T115: 0 | U115: 0 | V115: 0 | W115: 0 | X115: 0 | Y115: 0 | Z115: 0 | AA115: 0 | AB115: 0 | AC115: 0 | AD115: 0 | AE115: 0 | AF115: 0 | AG115: 0 | AH115: #DIV/0! | AI115: 0 | AJ115: 0
