Workbook

Sheet BALANCE
B2: ESTADO DE SITUACIÓN
B3: SISTEMA DE BANCOS PRIVADOS
B4: 31/12/2025
B5: (en miles de dólares)
B8: CÓDIGO | C8: CUENTA | D8: BP GUAYAQUIL | E8: BP PACIFICO | F8: BP PICHINCHA | G8: BP PRODUBANCO | H8: BANCOS PRIVADOS GRANDES | I8: BP AUSTRO | J8: BP BOLIVARIANO | K8: BP CITIBANK | L8: BP DINERS | M8: BP GENERAL RUMIÑAHUI | N8: BP INTERNACIONAL | O8: BP LOJA | P8: BP MACHALA | Q8: BP SOLIDARIO | R8: BANCOS PRIVADOS MEDIANOS | S8: BP PROCREDIT | T8: BP AMAZONAS | U8: BP BANCO COMERCIAL DE MANABI | V8: BP LITORAL | W8: BP COOPNACIONAL | X8: BP CAPITAL | Y8: BP DELBANK | Z8: BANCO ATLÁNTIDA S.A. | AA8: BP BANCO DESARROLLO DE LOS PUEBLOS S.A., CODESARROLLO | AB8: BP VISIONFUND ECUADOR S.A. | AC8: BANCOS PRIVADOS PEQUEÑOS | AD8: TOTAL BANCOS PRIVADOS | AE8: BANCOS PRIVADOS COMERCIALES | AF8: BANCOS PRIVADOS CONSUMO | AG8: BANCOS PRIVADOS VIVIENDA | AH8: BANCOS PRIVADOS MICROCRÉDITO | AI8: BANCA MÚLTIPLE
C9: ACTIVO
B10: 11 | C10: FONDOS DISPONIBLES | D10: 1012534 | E10: 1235542.8 | F10: 2498737.9 | G10: 981717.15 | H10: 5728532 | I10: 475145.08 | J10: 623981.53 | K10: 171488.36 | L10: 200616.25 | M10: 195315.74 | N10: 870369.02 | O10: 217427.37 | P10: 226529.59 | Q10: 72438.662 | R10: 3053311.6 | S10: 112879.01 | T10: 38903.616 | U10: 14053.52 | V10: 4211.866 | W10: 62878.608 | X10: 3006.965 | Y10: 7719.4678 | Z10: 11644.528 | AA10: 50258.056 | AB10: 13248.125 | AC10: 318803.76 | AD10: 9100647.3 | AE10: 1041857.4 | AF10: 400143.85 | AG10: 0 | AH10: 24892.653 | AI10: 7633753.4
B11: 1101 | C11: Caja | D11: 210660.51 | E11: 260202.89 | F11: 395013.43 | G11: 103733.6 | H11: 969610.43 | I11: 76237.982 | J11: 154205.18 | K11: 132.99 | L11: 3.1 | M11: 13313.452 | N11: 83146.229 | O11: 21448.534 | P11: 24352.66 | Q11: 17828.551 | R11: 390668.68 | S11: 4176.5703 | T11: 2098.6154 | U11: 2936.4617 | V11: 374.12083 | W11: 7113.5681 | X11: 191.42857 | Y11: 2215.0576 | Z11: 876.53716 | AA11: 4769.7263 | AB11: 1436.0947 | AC11: 26188.181 | AD11: 1386467.3 | AE11: 83279.219 | AF11: 13690.673 | AG11: 0 | AH11: 2312.6319 | AI11: 1287184.8
B12: 110105 | C12: Efectivo | D12: 210660.51 | E12: 260202.89 | F12: 394956.68 | G12: 103733.6 | H12: 969553.68 | I12: 76237.382 | J12: 154205.18 | K12: 132.99 | L12: 0 | M12: 13312.952 | N12: 83138.099 | O12: 21447.004 | P12: 24352.46 | Q12: 17810.351 | R12: 390636.42 | S12: 4176.5703 | T12: 2098.2154 | U12: 2935.4617 | V12: 373.80348 | W12: 7098.5681 | X12: 190.77857 | Y12: 2214.6576 | Z12: 876.53716 | AA12: 4764.3263 | AB12: 1423.4947 | AC12: 26152.413 | AD12: 1386342.5 | AE12: 83271.089 | AF12: 13686.756 | AG12: 0 | AH12: 2300.0319 | AI12: 1287084.6
B13: 110110 | C13: Caja chica | D13: 0 | E13: 0 | F13: 56.75 | G13: 0 | H13: 56.75 | I13: 0.6 | J13: 0 | K13: 0 | L13: 3.1 | M13: 0.5 | N13: 8.13 | O13: 1.53 | P13: 0.2 | Q13: 18.2 | R13: 32.26 | S13: 0 | T13: 0.4 | U13: 1 | V13: 0.31735 | W13: 15 | X13: 0.65 | Y13: 0.4 | Z13: 0 | AA13: 5.4 | AB13: 12.6 | AC13: 35.76735 | AD13: 124.77735 | AE13: 8.13 | AF13: 3.91735 | AG13: 0 | AH13: 12.6 | AI13: 100.13
B14: 1102 | C14: Depósitos para encaje | D14: 298492.71 | E14: 849788.36 | F14: 895328.25 | G14: 363803.85 | H14: 2407413.2 | I14: 192744.4 | J14: 198527.55 | K14: 75780.873 | L14: 119850.19 | M14: 49009.257 | N14: 490640.51 | O14: 114617.96 | P14: 57433.899 | Q14: 20940.562 | R14: 1319545.2 | S14: 65464.185 | T14: 21862.63 | U14: 4683.2675 | V14: 3672.5645 | W14: 8464.6794 | X14: 2715.4893 | Y14: 3706.0755 | Z14: 6551.7481 | AA14: 13224.602 | AB14: 3172.3963 | AC14: 133517.64 | AD14: 3860476 | AE14: 566421.38 | AF14: 172532.01 | AG14: 0 | AH14: 9724.1444 | AI14: 3111798.5
B15: 110205 | C15: Banco Central del Ecuador | D15: 298492.53 | E15: 849788.36 | F15: 895328.25 | G15: 363803.85 | H15: 2407413 | I15: 192744.4 | J15: 198527.55 | K15: 75780.873 | L15: 119850.19 | M15: 49009.257 | N15: 490640.51 | O15: 114615.83 | P15: 57433.899 | Q15: 20940.562 | R15: 1319543.1 | S15: 65464.185 | T15: 21862.63 | U15: 4683.2675 | V15: 3672.5645 | W15: 8464.6794 | X15: 2715.4893 | Y15: 3706.0755 | Z15: 6551.7481 | AA15: 13224.602 | AB15: 3172.3963 | AC15: 133517.64 | AD15: 3860473.7 | AE15: 566421.38 | AF15: 172532.01 | AG15: 0 | AH15: 9724.1444 | AI15: 3111796.2
B16: 110210 | C16: Banco Nacional de Fomento | D16: 0 | E16: 0 | F16: 0 | G16: 0 | H16: 0 | I16: 0 | J16: 0 | K16: 0 | L16: 0 | M16: 0 | N16: 0 | O16: 2.13793 | P16: 0 | Q16: 0 | R16: 2.13793 | S16: 0 | T16: 0 | U16: 0 | V16: 0 | W16: 0 | X16: 0 | Y16: 0 | Z16: 0 | AA16: 0 | AB16: 0 | AC16: 0 | AD16: 2.13793 | AE16: 0 | AF16: 0 | AG16: 0 | AH16: 0 | AI16: 2.13793
B17: 110215 | C17: Bancos locales | D17: 0.18693 | E17: 0 | F17: 0 | G17: 0 | H17: 0.18693 | I17: 0 | J17: 0 | K17: 0 | L17: 0 | M17: 0 | N17: 0 | O17: 0 | P17: 0 | Q17: 0 | R17: 0 | S17: 0 | T17: 0 | U17: 0 | V17: 0 | W17: 0 | X17: 0 | Y17: 0 | Z17: 0 | AA17: 0 | AB17: 0 | AC17: 0 | AD17: 0.18693 | AE17: 0 | AF17: 0 | AG17: 0 | AH17: 0 | AI17: 0.18693
B18: 1103 | C18: Bancos y otras instituciones financieras | D18: 470697.27 | E18: 116940.9 | F18: 1174063.4 | G18: 493553.19 | H18: 2255254.8 | I18: 202939.7 | J18: 254025.63 | K18: 95281.333 | L18: 80762.952 | M18: 132559.93 | N18: 278364.68 | O18: 81351.469 | P18: 142205.58 | Q18: 33291.05 | R18: 1300782.3 | S18: 42159.694 | T18: 14808.612 | U18: 5618.3098 | V18: 157.12811 | W18: 47286.443 | X18: 100.04713 | Y18: 1753.6679 | Z18: 4216.2425 | AA18: 32199.184 | AB18: 8639.3342 | AC18: 156938.66 | AD18: 3712975.8 | AE18: 373646.01 | AF18: 213480.01 | AG18: 0 | AH18: 12855.577 | AI18: 3112994.2
B19: 110305 | C19: Banco Central del Ecuador | D19: 0 | E19: 0 | F19: 0 | G19: 0 | H19: 0 | I19: 0 | J19: 0 | K19: 0 | L19: 0 | M19: 0 | N19: 0 | O19: 0 | P19: 0 | Q19: 0 | R19: 0 | S19: 0 | T19: 0 | U19: 0 | V19: 0 | W19: 0 | X19: 0 | Y19: 0 | Z19: 0 | AA19: 0 | AB19: 0 | AC19: 0 | AD19: 0 | AE19: 0 | AF19: 0 | AG19: 0 | AH19: 0 | AI19: 0
B20: 110310 | C20: Bancos e instituciones financieras locales | D20: 29231.685 | E20: 39208.346 | F20: 1012181.3 | G20: 184073.64 | H20: 1264695 | I20: 190908.65 | J20: 137619.1 | K20: 18031.522 | L20: 59535.479 | M20: 82077.494 | N20: 97061.581 | O20: 52312.821 | P20: 129311.8 | Q20: 11511.54 | R20: 778369.98 | S20: 38551.967 | T20: 13753.664 | U20: 4799.5376 | V20: 157.12811 | W20: 47286.443 | X20: 91.17285 | Y20: 1617.7859 | Z20: 4216.2425 | AA20: 29205.296 | AB20: 8639.3342 | AC20: 148318.57 | AD20: 2191383.5 | AE20: 115093.1 | AF20: 141770.1 | AG20: 0 | AH20: 12855.577 | AI20: 1921664.7
B21: 110315 | C21: Bancos e instituciones financieras del exterior | D21: 441465.59 | E21: 77732.558 | F21: 161882.12 | G21: 309479.55 | H21: 990559.81 | I21: 12031.052 | J21: 116406.54 | K21: 77249.811 | L21: 21227.473 | M21: 50482.432 | N21: 181303.1 | O21: 29038.648 | P21: 12893.778 | Q21: 21779.509 | R21: 522412.34 | S21: 3607.7272 | T21: 1054.9479 | U21: 818.77228 | V21: 0 | W21: 0 | X21: 8.87428 | Y21: 135.88199 | Z21: 0 | AA21: 2993.8879 | AB21: 0 | AC21: 8620.0916 | AD21: 1521592.2 | AE21: 258552.91 | AF21: 71709.905 | AG21: 0 | AH21: 0 | AI21: 1191329.4
... B750: +1+4 | C750: TOTAL ACTIVO Y GASTOS | D750: 10723674 | E750: 10819535 | F750: 23941863 | G750: 9935022.6 | H750: 55420094 | I750: 3688634 | J750: 6652903.9 | K750: 849954.32 | L750: 3868918.7 | M750: 1541110 | N750: 6496440.4 | O750: 1103601.8 | P750: 1357910.1 | Q750: 917687.32 | R750: 26477160 | S750: 786439.26 | T750: 463058.42 | U750: 151904.26 | V750: 48121.282 | W750: 248872.9 | X750: 87055.749 | Y750: 44275.044 | Z750: 142695.9 | AA750: 376224.59 | AB750: 194708.43 | AC750: 2543355.8 | AD750: 84440611 | AE750: 7346394.7 | AF750: 5458149.9 | AG750: 0 | AH750: 337404.34 | AI750: 71298662
C752: PASIVOS
B753: 21 | C753: OBLIGACIONES CON EL PÚBLICO | D753: 7713105.9 | E753: 7847569.2 | F753: 17657367 | G753: 7218086.1 | H753: 40436128 | I753: 2851376.1 | J753: 4723713.8 | K753: 646608.33 | L753: 1836693.5 | M753: 1139618.6 | N753: 4950342.4 | O753: 827237.62 | P753: 1028061.9 | Q753: 342953.33 | R753: 18346606 | S753: 625854.49 | T753: 346735.32 | U753: 116051.07 | V753: 29376.024 | W753: 196738.7 | X753: 59356.148 | Y753: 22297.447 | Z753: 98133.093 | AA753: 258898.53 | AB753: 62058.228 | AC753: 1815499.1 | AD753: 60598233 | AE753: 5596950.7 | AF753: 3005688.1 | AG753: 0 | AH753: 160191.32 | AI753: 51835402
B754: 2101 | C754: Depósitos a la vista | D754: 4192096.6 | E754: 3510597 | F754: 11818453 | G754: 4086242 | H754: 23607388 | I754: 1427745.9 | J754: 2514328 | K754: 646524.08 | L754: 186163.69 | M754: 438605.41 | N754: 2690834 | O754: 452040.49 | P754: 532327.51 | Q754: 89338.118 | R754: 8977907.2 | S754: 360460.32 | T754: 123051.89 | U754: 47615.149 | V754: 16599.158 | W754: 108469.64 | X754: 4202.416 | Y754: 9151.0389 | Z754: 25688.659 | AA754: 130387.66 | AB754: 14515.083 | AC754: 840141.01 | AD754: 33425437 | AE754: 3337358.1 | AF754: 641368.26 | AG754: 0 | AH754: 40203.741 | AI754: 29406506
B755: 210105 | C755: Depósitos monetarios que generan INTERESES | D755: 779877.64 | E755: 674840.5 | F755: 209976.64 | G755: 29489.693 | H755: 1694184.5 | I755: 58038.07 | J755: 597703.94 | K755: 137029.82 | L755: 0 | M755: 42544.4 | N755: 1192171.5 | O755: 0 | P755: 20923.914 | Q755: 11057.151 | R755: 2059468.8 | S755: 76439.69 | T755: 2887.9631 | U755: 3933.7155 | V755: 0 | W755: 0 | X755: 1671.1403 | Y755: 0 | Z755: 0 | AA755: 4065.2725 | AB755: 0 | AC755: 88997.781 | AD755: 3842651 | AE755: 1329201.3 | AF755: 42544.4 | AG755: 0 | AH755: 0 | AI755: 2470905.3
B756: 210110 | C756: Depósitos monetarios que no generan INTERESES | D756: 917808.53 | E756: 1022321.8 | F756: 3488745.9 | G756: 1669177.9 | H756: 7098054.1 | I756: 182989.23 | J756: 826382.84 | K756: 505116.32 | L756: 0 | M756: 55135.568 | N756: 326982.8 | O756: 88453.131 | P756: 166463.69 | Q756: 80.44795 | R756: 2151604 | S756: 0 | T756: 24020.545 | U756: 8854.1995 | V756: 7964.2761 | W756: 110.53401 | X756: 36.5142 | Y756: 2575.8454 | Z756: 0 | AA756: 0 | AB756: 0 | AC756: 43561.914 | AD756: 9293220 | AE756: 832099.12 | AF756: 63099.844 | AG756: 0 | AH756: 0 | AI756: 8398021.1
B757: 210115 | C757: Depósitos monetarios de instituciones financieras | D757: 385452.55 | E757: 10769.629 | F757: 448630.2 | G757: 192182.9 | H757: 1037035.3 | I757: 148739.07 | J757: 278682.82 | K757: 1984.809 | L757: 0 | M757: 4144.3556 | N757: 175769.86 | O757: 3250.006 | P757: 30656.838 | Q757: 5.38474 | R757: 643233.14 | S757: 1185.6536 | T757: 1710.7163 | U757: 1080.0412 | V757: 0 | W757: 0 | X757: 0 | Y757: 0 | Z757: 0 | AA757: 5205.0201 | AB757: 0 | AC757: 9181.4312 | AD757: 1689449.9 | AE757: 177754.67 | AF757: 4144.3556 | AG757: 0 | AH757: 0 | AI757: 1507550.8
B758: 210120 | C758: EJECUCIÓN PRESUPUESTARIA | D758: 2589.9418 | E758: 0.10005 | F758: 0 | G758: 0 | H758: 2590.0419 | I758: 0 | J758: 5558.0049 | K758: 0 | L758: 0 | M758: 0 | N758: 0 | O758: 72.57798 | P758: 413.65876 | Q758: 0 | R758: 6044.2416 | S758: 0 | T758: 0 | U758: 0 | V758: 0 | W758: 0 | X758: 0 | Y758: 0 | Z758: 0 | AA758: 0 | AB758: 0 | AC758: 0 | AD758: 8634.2835 | AE758: 0 | AF758: 0 | AG758: 0 | AH758: 0 | AI758: 8634.2835
B759: 210125 | C759: Depósitos de otras instituciones para encaje | D759: 0 | E759: 0 | F759: 0 | G759: 0 | H759: 0 | I759: 0 | J759: 0 | K759: 0 | L759: 0 | M759: 0 | N759: 0 | O759: 0 | P759: 0 | Q759: 0 | R759: 0 | S759: 0 | T759: 0 | U759: 0 | V759: 0 | W759: 0 | X759: 0 | Y759: 0 | Z759: 0 | AA759: 0 | AB759: 0 | AC759: 0 | AD759: 0 | AE759: 0 | AF759: 0 | AG759: 0 | AH759: 0 | AI759: 0
B760: 210130 | C760: Cheques certificados | D760: 6698.8545 | E760: 9251.4455 | F760: 16149.092 | G760: 8447.9776 | H760: 40547.37 | I760: 1406.637 | J760: 6680.8914 | K760: 2119.077 | L760: 0 | M760: 388.83846 | N760: 2812.4074 | O760: 237.27344 | P760: 986.12628 | Q760: 14.29581 | R760: 14645.547 | S760: 91.63723 | T760: 207.09813 | U760: 45.37173 | V760: 55.87421 | W760: 0.0117 | X760: 153.40232 | Y760: 4.44268 | Z760: 0 | AA760: 16.02143 | AB760: 0 | AC760: 573.85943 | AD760: 55766.776 | AE760: 4931.4844 | AF760: 444.71267 | AG760: 0 | AH760: 0 | AI760: 50390.579
B761: 210131 | C761: Cheques de emergencia | D761: 5754.6602 | E761: 5917.4362 | F761: 8318.496 | G761: 3206.199 | H761: 23196.791 | I761: 950.673 | J761: 3517.2016 | K761: 0 | L761: 0 | M761: 936.36896 | N761: 1793.8017 | O761: 17.62256 | P761: 1540.7718 | Q761: 464.81932 | R761: 9221.2589 | S761: 21.18986 | T761: 0 | U761: 347.2 | V761: 181.87996 | W761: 100.54859 | X761: 0 | Y761: 13.61283 | Z761: 0 | AA761: 0 | AB761: 0 | AC761: 664.43124 | AD761: 33082.482 | AE761: 1793.8017 | AF761: 1118.2489 | AG761: 0 | AH761: 0 | AI761: 30170.431
B762: 210135 | C762: Depósitos de ahorro | D762: 2036522.8 | E762: 1713328.2 | F762: 7569637.5 | G762: 2134820.4 | H762: 13454309 | I762: 1025411.3 | J762: 737232.2 | K762: 0 | L762: 170412.51 | M762: 331007 | N762: 968951.9 | O762: 355478.92 | P762: 308785.15 | Q762: 75255.614 | R762: 3972534.6 | S762: 281643.34 | T762: 78080.065 | U762: 33238.729 | V762: 8393.2852 | W762: 108244.63 | X762: 2280.2489 | Y762: 6138.6033 | Z762: 25685.883 | AA762: 120851.63 | AB762: 14451.107 | AC762: 679007.52 | AD762: 18105851 | AE762: 968951.9 | AF762: 509812.8 | AG762: 0 | AH762: 40136.99 | AI762: 16586949
B763: 210140 | C763: Otros depósitos | D763: 26.57289 | E763: 54380.593 | F763: 14670.681 | G763: 18693.416 | H763: 87771.262 | I763: 131.44344 | J763: 37884.076 | K763: 0 | L763: 5956.4863 | M763: 2543.5986 | N763: 1874.8429 | O763: 3448.9729 | P763: 74.95104 | Q763: 1586.9101 | R763: 53501.281 | S763: 0 | T763: 15873.39 | U763: 2.71882 | V763: 0.8 | W763: 0 | X763: 61.11033 | Y763: 411.35886 | Z763: 2.77546 | AA763: 184.77091 | AB763: 63.67604 | AC763: 16600.601 | AD763: 157873.14 | AE763: 1874.8429 | AF763: 8500.8849 | AG763: 0 | AH763: 66.4515 | AI763: 147430.96
B764: 210145 | C764: Fondos de tarjetahabientes | D764: 19885.7 | E764: 12398.889 | F764: 6188.5114 | G764: 8478.9931 | H764: 46952.093 | I764: 6865.8452 | J764: 2421.2948 | K764: 0 | L764: 9794.6888 | M764: 593.48318 | N764: 2444.4368 | O764: 85.51726 | P764: 339.19874 | Q764: 634.53042 | R764: 23178.995 | S764: 0 | T764: 240.44148 | U764: 0 | V764: 0 | W764: 0 | X764: 0 | Y764: 0 | Z764: 0 | AA764: 0 | AB764: 0 | AC764: 240.44148 | AD764: 70371.53 | AE764: 2444.4368 | AF764: 10388.172 | AG764: 0 | AH764: 0 | AI764: 57538.921
... B950: 2 | C950: TOTAL PASIVOS | D950: 8813834.7 | E950: 8764021.4 | F950: 19331677 | G950: 8362070.7 | H950: 45271603 | I950: 3078390.2 | J950: 5576518.5 | K950: 690837.14 | L950: 2714086.5 | M950: 1255990.6 | N950: 5475944.3 | O950: 914818.88 | P950: 1156629.5 | Q950: 616580.41 | R950: 21479796 | S950: 665281.14 | T950: 376292.74 | U950: 120451.51 | V950: 31147.688 | W950: 201300.46 | X950: 65567.478 | Y950: 27001.861 | Z950: 112055.39 | AA950: 299198.1 | AB950: 138960.77 | AC950: 2037257.1 | AD950: 68788657 | AE950: 6166781.4 | AF950: 4001224.8 | AG950: 0 | AH950: 251016.16 | AI950: 58369634
C952: PATRIMONIO
B953: 31 | C953: CAPITAL SOCIAL | D953: 646103 | E953: 645966.04 | F953: 1457000 | G953: 547720 | H953: 3296789 | I953: 199570 | J953: 445000 | K953: 76065.364 | L953: 400000 | M953: 101836.15 | N953: 413420.07 | O953: 61527 | P953: 71946 | Q953: 111107.14 | R953: 1880471.7 | S953: 52979 | T953: 35465.01 | U953: 15763.1 | V953: 11210.657 | W953: 24866.788 | X953: 16050 | Y953: 11671.864 | Z953: 14920 | AA953: 28587.8 | AB953: 20456.1 | AC953: 231970.32 | AD953: 5409231.1 | AE953: 489485.43 | AF953: 513046.8 | AG953: 0 | AH953: 35376.1 | AI953: 4371322.7
B954: 3101 | C954: Capital pagado | D954: 646103 | E954: 645966.04 | F954: 1463000 | G954: 547720 | H954: 3302789 | I954: 199570 | J954: 445000 | K954: 76065.364 | L954: 400000 | M954: 101836.15 | N954: 413420.07 | O954: 61527 | P954: 71946 | Q954: 111107.14 | R954: 1880471.7 | S954: 52979 | T954: 35465.01 | U954: 15763.1 | V954: 11210.657 | W954: 24866.788 | X954: 16050 | Y954: 11671.864 | Z954: 14920 | AA954: 28587.8 | AB954: 20456.1 | AC954: 231970.32 | AD954: 5415231.1 | AE954: 489485.43 | AF954: 513046.8 | AG954: 0 | AH954: 35376.1 | AI954: 4377322.7
B955: 3102 | C955: (Acciones en tesorería) | D955: 0 | E955: 0 | F955: -6000 | G955: 0 | H955: -6000 | I955: 0 | J955: 0 | K955: 0 | L955: 0 | M955: 0 | N955: 0 | O955: 0 | P955: 0 | Q955: 0 | R955: 0 | S955: 0 | T955: 0 | U955: 0 | V955: 0 | W955: 0 | X955: 0 | Y955: 0 | Z955: 0 | AA955: 0 | AB955: 0 | AC955: 0 | AD955: -6000 | AE955: 0 | AF955: 0 | AG955: 0 | AH955: 0 | AI955: -6000
B956: 3103 | C956: Aportes de socios | D956: 0 | E956: 0 | F956: 0 | G956: 0 | H956: 0 | I956: 0 | J956: 0 | K956: 0 | L956: 0 | M956: 0 | N956: 0 | O956: 0 | P956: 0 | Q956: 0 | R956: 0 | S956: 0 | T956: 0 | U956: 0 | V956: 0 | W956: 0 | X956: 0 | Y956: 0 | Z956: 0 | AA956: 0 | AB956: 0 | AC956: 0 | AD956: 0 | AE956: 0 | AF956: 0 | AG956: 0 | AH956: 0 | AI956: 0
B957: 32 | C957: PRIMA O DESCUENTO EN COLOCACIÓN DE ACCIONES Y CERTIFICADOS | D957: 0 | E957: 0 | F957: 0 | G957: 1104.7742 | H957: 1104.7742 | I957: 0 | J957: 0 | K957: 0 | L957: 0 | M957: 0 | N957: 0 | O957: 0 | P957: 0 | Q957: 0 | R957: 0 | S957: 0 | T957: 0 | U957: 0 | V957: 0 | W957: 0 | X957: 0 | Y957: 0 | Z957: 0 | AA957: 0 | AB957: 0 | AC957: 0 | AD957: 1104.7742 | AE957: 0 | AF957: 0 | AG957: 0 | AH957: 0 | AI957: 1104.7742
B958: 3201 | C958: Prima EN COLOCACIÓN de acciones y certificados de aportación | D958: 0 | E958: 0 | F958: 0 | G958: 1104.7742 | H958: 1104.7742 | I958: 0 | J958: 0 | K958: 0 | L958: 0 | M958: 0 | N958: 0 | O958: 0 | P958: 0 | Q958: 0 | R958: 0 | S958: 0 | T958: 0 | U958: 0 | V958: 0 | W958: 0 | X958: 0 | Y958: 0 | Z958: 0 | AA958: 0 | AB958: 0 | AC958: 0 | AD958: 1104.7742 | AE958: 0 | AF958: 0 | AG958: 0 | AH958: 0 | AI958: 1104.7742
B959: 3202 | C959: (Descuento en colocación de acciones) | D959: 0 | E959: 0 | F959: 0 | G959: 0 | H959: 0 | I959: 0 | J959: 0 | K959: 0 | L959: 0 | M959: 0 | N959: 0 | O959: 0 | P959: 0 | Q959: 0 | R959: 0 | S959: 0 | T959: 0 | U959: 0 | V959: 0 | W959: 0 | X959: 0 | Y959: 0 | Z959: 0 | AA959: 0 | AB959: 0 | AC959: 0 | AD959: 0 | AE959: 0 | AF959: 0 | AG959: 0 | AH959: 0 | AI959: 0
B960: 33 | C960: RESERVAS | D960: 115381.91 | E960: 188231.56 | F960: 250811.48 | G960: 81804.755 | H960: 636229.71 | I960: 32148.79 | J960: 70802.591 | K960: 15264.911 | L960: 129064.91 | M960: 15096.543 | N960: 72148.686 | O960: 12416.478 | P960: 6573.5098 | Q960: 24191.601 | R960: 377708.02 | S960: 1605.2066 | T960: 1631.8686 | U960: 1290.7258 | V960: 444.27202 | W960: 7933.0288 | X960: 0 | Y960: 113.81248 | Z960: 0 | AA960: 3530.119 | AB960: 1796.5487 | AC960: 18345.582 | AD960: 1032283.3 | AE960: 87413.597 | AF960: 144605.73 | AG960: 0 | AH960: 1796.5487 | AI960: 798467.45
B961: 3301 | C961: Legales | D961: 114150.39 | E961: 188230.73 | F961: 193682.17 | G961: 81804.755 | H961: 577868.05 | I961: 22169.067 | J961: 67719.206 | K961: 15264.911 | L961: 81069.748 | M961: 15096.543 | N961: 72148.686 | O961: 10873.705 | P961: 6570.7124 | Q961: 20784.145 | R961: 311696.72 | S961: 1605.2066 | T961: 1631.8686 | U961: 993.26859 | V961: 444.26308 | W961: 6897.5809 | X961: 0 | Y961: 113.81248 | Z961: 0 | AA961: 3463.6427 | AB961: 1795.8139 | AC961: 16945.457 | AD961: 906510.23 | AE961: 87413.597 | AF961: 96610.554 | AG961: 0 | AH961: 1795.8139 | AI961: 720690.26
B962: 3302 | C962: Generales | D962: 0 | E962: 0 | F962: 0 | G962: 0 | H962: 0 | I962: 0 | J962: 0 | K962: 0 | L962: 0 | M962: 0 | N962: 0 | O962: 0 | P962: 0 | Q962: 0 | R962: 0 | S962: 0 | T962: 0 | U962: 0 | V962: 0 | W962: 0 | X962: 0 | Y962: 0 | Z962: 0 | AA962: 0 | AB962: 0 | AC962: 0 | AD962: 0 | AE962: 0 | AF962: 0 | AG962: 0 | AH962: 0 | AI962: 0
B963: 3303 | C963: Especiales | D963: 4.71162 | E963: 0.83412 | F963: 26243.089 | G963: 0 | H963: 26248.634 | I963: 5981.3562 | J963: 124.47585 | K963: 0 | L963: 45032.865 | M963: 0 | N963: 0 | O963: 0 | P963: 0 | Q963: 1102.7541 | R963: 52241.452 | S963: 0 | T963: 0 | U963: 6.70575 | V963: 0.00894 | W963: 63.82848 | X963: 0 | Y963: 0 | Z963: 0 | AA963: 38.819 | AB963: 0.7348 | AC963: 110.09697 | AD963: 78600.183 | AE963: 0 | AF963: 45032.874 | AG963: 0 | AH963: 0.7348 | AI963: 33566.574
B964: 330305 | C964: A disposición de la Junta General de Accionistas | D964: 0 | E964: 0 | F964: 0 | G964: 0 | H964: 0 | I964: 0 | J964: 0 | K964: 0 | L964: 45032.865 | M964: 0 | N964: 0 | O964: 0 | P964: 0 | Q964: 1102.7524 | R964: 46135.618 | S964: 0 | T964: 0 | U964: 0 | V964: 0 | W964: 0 | X964: 0 | Y964: 0 | Z964: 0 | AA964: 0 | AB964: 0 | AC964: 0 | AD964: 46135.618 | AE964: 0 | AF964: 45032.865 | AG964: 0 | AH964: 0 | AI964: 1102.7524
... B1399: 749090 | C1399: Otras | D1399: 660584.3 | E1399: 6126.9827 | F1399: 9421.8401 | G1399: 225.49591 | H1399: 676358.62 | I1399: 0 | J1399: 0 | K1399: 0 | L1399: 25250.288 | M1399: 0 | N1399: 8854.7566 | O1399: 0 | P1399: 0 | Q1399: 1.33431 | R1399: 34106.379 | S1399: 0 | T1399: 0 | U1399: 0 | V1399: 785.61287 | W1399: 0 | X1399: 683.22834 | Y1399: 0 | Z1399: 0 | AA1399: 336705.24 | AB1399: 0 | AC1399: 338174.08 | AD1399: 1048639.1 | AE1399: 8854.7566 | AF1399: 26035.901 | AG1399: 0 | AH1399: 0 | AI1399: 1013748.4

Sheet PYG
B3: ESTADO DE PÉRDIDAS Y GANANCIAS
B4: SISTEMA DE BANCOS PRIVADOS
B5: 31/12/2025
B6: (en miles de dólares)
B8: CÓDIGO | C8: CUENTA | D8: BP GUAYAQUIL | E8: BP PACIFICO | F8: BP PICHINCHA | G8: BP PRODUBANCO | H8: BANCOS PRIVADOS GRANDES | I8: BP AUSTRO | J8: BP BOLIVARIANO | K8: BP CITIBANK | L8: BP DINERS | M8: BP GENERAL RUMIÑAHUI | N8: BP INTERNACIONAL | O8: BP LOJA | P8: BP MACHALA | Q8: BP SOLIDARIO | R8: BANCOS PRIVADOS MEDIANOS | S8: BP PROCREDIT | T8: BP AMAZONAS | U8: BP BANCO COMERCIAL DE MANABI | V8: BP LITORAL | W8: BP COOPNACIONAL | X8: BP CAPITAL | Y8: BP DELBANK | Z8: BANCO ATLÁNTIDA S.A. | AA8: BP BANCO DESARROLLO DE LOS PUEBLOS S.A., CODESARROLLO | AB8: BP VISIONFUND ECUADOR S.A. | AC8: BANCOS PRIVADOS PEQUEÑOS | AD8: TOTAL BANCOS PRIVADOS | AE8: BANCOS PRIVADOS COMERCIALES | AF8: BANCOS PRIVADOS CONSUMO | AG8: BANCOS PRIVADOS VIVIENDA | AH8: BANCOS PRIVADOS MICROCRÉDITO | AI8: BANCA MÚLTIPLE
B9: 5 | C9: INGRESOS | D9: 1141648.7 | E9: 1148450 | F9: 2639590.7 | G9: 933402.64 | H9: 5863092 | I9: 347384.93 | J9: 538528.74 | K9: 66719.813 | L9: 601913.03 | M9: 165798.87 | N9: 515723.58 | O9: 109582.39 | P9: 115769.42 | Q9: 155204.06 | R9: 2616624.8 | S9: 66573.908 | T9: 46694.442 | U9: 13222.642 | V9: 5377.9936 | W9: 13352.44 | X9: 10853.671 | Y9: 5478.9117 | Z9: 18689.402 | AA9: 40152.618 | AB9: 33350.923 | AC9: 253746.95 | AD9: 8733463.8 | AE9: 582443.4 | AF9: 773089.89 | AG9: 0 | AH9: 52040.326 | AI9: 7325890.2
B11: 51 | C11: INTERESES Y DESCUENTOS GANADOS | D11: 811373.86 | E11: 740517.5 | F11: 1854667.2 | G11: 660468.14 | H11: 4067026.7 | I11: 258538.69 | J11: 409127.21 | K11: 41936.962 | L11: 287242.27 | M11: 131281.35 | N11: 411192.59 | O11: 95915.067 | P11: 101606.91 | Q11: 115824.69 | R11: 1852665.7 | S11: 62106.599 | T11: 34072.388 | U11: 10370.381 | V11: 4587.0167 | W11: 11760.401 | X11: 6183.4066 | Y11: 3269.5239 | Z11: 10901.823 | AA11: 32512.74 | AB11: 28908.403 | AC11: 204672.68 | AD11: 6124365.1 | AE11: 453129.55 | AF11: 423110.64 | AG11: 0 | AH11: 39810.226 | AI11: 5208314.7
B12: 5101 | C12: Depósitos | D12: 2190.6773 | E12: 1578.4875 | F12: 30453.859 | G12: 11106.899 | H12: 45329.923 | I12: 5561.3059 | J12: 5318.4078 | K12: 2319.673 | L12: 523.8508 | M12: 4217.0865 | N12: 6948.3826 | O12: 2122.9008 | P12: 3394.3579 | Q12: 183.68303 | R12: 30589.648 | S12: 635.53972 | T12: 765.60765 | U12: 168.50418 | V12: 0.19109 | W12: 2264.9207 | X12: 7.63455 | Y12: 43.19513 | Z12: 240.37982 | AA12: 145.46343 | AB12: 117.98436 | AC12: 4389.4207 | AD12: 80308.992 | AE12: 9268.0556 | AF12: 4741.1284 | AG12: 0 | AH12: 358.36418 | AI12: 65941.444
B13: 5102 | C13: Operaciones interbancarias | D13: 0 | E13: 0 | F13: 14.41666 | G13: 2.01639 | H13: 16.43305 | I13: 0 | J13: 6.55554 | K13: 4.306 | L13: 0 | M13: 0 | N13: 17.79166 | O13: 0 | P13: 0 | Q13: 0 | R13: 28.6532 | S13: 0 | T13: 0 | U13: 0 | V13: 0 | W13: 0 | X13: 0 | Y13: 0 | Z13: 0 | AA13: 0 | AB13: 0 | AC13: 0 | AD13: 45.08625 | AE13: 22.09766 | AF13: 0 | AG13: 0 | AH13: 0 | AI13: 22.98859
B14: 5103 | C14: INTERESES y descuentos de inversiones en títulos valores | D14: 90618.347 | E14: 57079.332 | F14: 131822.24 | G14: 28989.466 | H14: 308509.39 | I14: 21458.496 | J14: 20945.142 | K14: 12777.769 | L14: 11316.139 | M14: 5716.9666 | N14: 26669.997 | O14: 4472.989 | P14: 7166.4339 | Q14: 3028.9459 | R14: 113552.88 | S14: 4187.5924 | T14: 2874.6928 | U14: 2027.1818 | V14: 159.82145 | W14: 6543.4205 | X14: 305.45248 | Y14: 182.61067 | Z14: 3570.5354 | AA14: 1860.355 | AB14: 74.03136 | AC14: 21785.694 | AD14: 443847.96 | AE14: 39447.766 | AF14: 17192.927 | AG14: 0 | AH14: 3644.5667 | AI14: 383562.7
B15: 5104 | C15: INTERESES Y DESCUENTOS DE CARTERA DE CRÉDITOS | D15: 718564.84 | E15: 681826.86 | F15: 1690900 | G15: 619320.97 | H15: 3710612.7 | I15: 230801.1 | J15: 382340.74 | K15: 25047.873 | L15: 274196.86 | M15: 121347.29 | N15: 377250.22 | O15: 89319.177 | P15: 91046.114 | Q15: 112612.06 | R15: 1703961.4 | S15: 57283.467 | T15: 28857.598 | U15: 8134.4175 | V15: 4427.0042 | W15: 2952.06 | X15: 5714.0586 | Y15: 3043.7181 | Z15: 7090.9083 | AA15: 30506.922 | AB15: 28716.387 | AC15: 176726.54 | AD15: 5591300.6 | AE15: 402298.1 | AF15: 399971.15 | AG15: 0 | AH15: 35807.295 | AI15: 4753224.1
B16: 510405 | C16: CARTERA DE CRÉDITOS PRODUCTIVO | D16: 239113.93 | E16: 132906.35 | F16: 492276.72 | G16: 273629.9 | H16: 1137926.9 | I16: 55928.247 | J16: 230169.17 | K16: 24926.136 | L16: 2709.3381 | M16: 6934.8973 | N16: 268583.92 | O16: 18482.447 | P16: 54221.475 | Q16: 0.02377 | R16: 661955.65 | S16: 28844.605 | T16: 10994.809 | U16: 2520.5389 | V16: 667.6398 | W16: 2430.9499 | X16: -3.46367 | Y16: 2019.5917 | Z16: 366.80253 | AA16: 3380.6066 | AB16: 0 | AC16: 51222.08 | AD16: 1851104.6 | AE16: 293510.05 | AF16: 10311.875 | AG16: 0 | AH16: 366.80253 | AI16: 1546915.9
B17: 510410 | C17: CARTERA DE CRÉDITOS DE CONSUMO | D17: 329300.8 | E17: 458001.96 | F17: 614487.06 | G17: 267965.78 | H17: 1669755.6 | I17: 149732.8 | J17: 132724.59 | K17: 0 | L17: 239143.59 | M17: 96806.779 | N17: 81515.988 | O17: 35909.159 | P17: 23815.408 | Q17: 40643.401 | R17: 800291.71 | S17: 1652.4724 | T17: 13385.744 | U17: 3113.97 | V17: 2957.9953 | W17: 53.70063 | X17: 3136.1332 | Y17: 541.81368 | Z17: 428.21297 | AA17: 12665.701 | AB17: 257.28973 | AC17: 38193.033 | AD17: 2508240.4 | AE17: 81515.988 | AF17: 338908.36 | AG17: 0 | AH17: 685.5027 | AI17: 2087130.5
B18: 510415 | C18: CARTERA DE CRÉDITOS INMOBILIARIO | D18: 22966.016 | E18: 41130.534 | F18: 85605.117 | G18: 30141.8 | H18: 179843.47 | I18: 5735.5732 | J18: 13400.603 | K18: 0 | L18: 32.87026 | M18: 10743.47 | N18: 15128.372 | O18: 5631.0311 | P18: 4234.4872 | Q18: 0 | R18: 54906.407 | S18: 2454.9851 | T18: 345.36954 | U18: 0 | V18: 0 | W18: 20.28524 | X18: 0 | Y18: 102.72215 | Z18: 4.5243 | AA18: 2289.6282 | AB18: 0 | AC18: 5217.5145 | AD18: 239967.39 | AE18: 15128.372 | AF18: 10776.34 | AG18: 0 | AH18: 4.5243 | AI18: 214058.15
B19: 510420 | C19: CARTERA DE CRÉDITOS PARA MICROCRÉDITO | D19: 83057.39 | E19: 610.06873 | F19: 382893.25 | G19: 5554.2029 | H19: 472114.92 | I19: 1731.0952 | J19: 84.83012 | K19: 0 | L19: 6.90606 | M19: 71.06555 | N19: 829.16849 | O19: 22612.717 | P19: 1202.9199 | Q19: 67024.754 | R19: 93563.457 | S19: 19389.147 | T19: 542.29569 | U19: 1349.8963 | V19: 187.65793 | W19: 445.70641 | X19: 1912.2488 | Y19: 52.3321 | Z19: 5565.734 | AA19: 10464.906 | AB19: 27756.928 | AC19: 67666.852 | AD19: 633345.22 | AE19: 829.16849 | AF19: 265.62954 | AG19: 0 | AH19: 33322.662 | AI19: 598927.76
B20: 510427 | C20: CARTERA DE CRÉDITO DE VIVIENDA DE INTERÉS SOCIAL Y PÚBLICO | D20: 0 | E20: 101.59694 | F20: 4376.6598 | G20: 0 | H20: 4478.2567 | I20: 0 | J20: 0 | K20: 0 | L20: 0 | M20: 492.92766 | N20: 14.36358 | O20: 0 | P20: 0 | Q20: 0 | R20: 507.29124 | S20: 0 | T20: 0 | U20: 0 | V20: 0 | W20: 0 | X20: 0 | Y20: 0 | Z20: 0 | AA20: 0 | AB20: 0 | AC20: 0 | AD20: 4985.548 | AE20: 14.36358 | AF20: 492.92766 | AG20: 0 | AH20: 0 | AI20: 4478.2567
B21: 510428 | C21: CARTERA DE CRÉDITO EDUCATIVO | D21: 149.0496 | E21: 11706.238 | F21: 3133.6639 | G21: 87.65435 | H21: 15076.606 | I21: 0 | J21: 214.70103 | K21: 0 | L21: 0 | M21: 0 | N21: 0 | O21: 18.20949 | P21: 110.23831 | Q21: 0 | R21: 343.14883 | S21: 3.3075 | T21: 0 | U21: 0 | V21: 0 | W21: 0 | X21: 0 | Y21: 0 | Z21: 0 | AA21: 0 | AB21: 0 | AC21: 3.3075 | AD21: 15423.062 | AE21: 0 | AF21: 0 | AG21: 0 | AH21: 0 | AI21: 15423.062
... B33: 4105 | C33: Otros INTERESES | D33: 0 | E33: 0 | F33: 7.91529 | G33: 0 | H33: 7.91529 | I33: 0 | J33: 0 | K33: 0 | L33: 0 | M33: 0 | N33: 0 | O33: 0 | P33: 0 | Q33: 0 | R33: 0 | S33: 0 | T33: 0.74169 | U33: 0 | V33: 0 | W33: 0 | X33: 2.05594 | Y33: 0 | Z33: 0 | AA33: 0 | AB33: 0 | AC33: 2.79763 | AD33: 10.71292 | AE33: 0 | AF33: 0 | AG33: 0 | AH33: 0 | AI33: 10.71292
C34: MARGEN NETO INTERESES | D34: 480964.56 | E34: 406459.26 | F34: 1236929 | G34: 369780.99 | H34: 2494133.8 | I34: 133690.45 | J34: 208722.37 | K34: 41376.667 | L34: 161866.29 | M34: 73153.521 | N34: 207508.02 | O34: 60519.322 | P34: 58725.505 | Q34: 76556.605 | R34: 1022118.7 | S34: 20953.342 | T34: 12782.802 | U34: 5568.3814 | V34: 3608.8799 | W34: 7610.8679 | X34: 2102.3488 | Y34: 1917.1388 | Z34: 4248.4807 | AA34: 19223.63 | AB34: 20500.198 | AC34: 98516.07 | AD34: 3614768.6 | AE34: 248884.69 | AF34: 238628.69 | AG34: 0 | AH34: 24748.679 | AI34: 3102506.6
B36: 52 | C36: COMISIONES GANADAS | D36: 98259.677 | E36: 56721.755 | F36: 68220.751 | G36: 34244.031 | H36: 257446.21 | I36: 17237.633 | J36: 41792.309 | K36: 3458.709 | L36: 72691.162 | M36: 6421.5154 | N36: 32923.346 | O36: 1138.0241 | P36: 1643.4657 | Q36: 3513.7799 | R36: 180819.94 | S36: 179.71074 | T36: 424.50522 | U36: 240.99461 | V36: 0 | W36: 0 | X36: 0 | Y36: 34.97712 | Z36: 0 | AA36: 222.17452 | AB36: 0 | AC36: 1102.3622 | AD36: 439368.52 | AE36: 36382.055 | AF36: 79112.677 | AG36: 0 | AH36: 0 | AI36: 323873.79
B37: 5201 | C37: Cartera de créditos | D37: 96.75831 | E37: 0 | F37: 0 | G37: 0 | H37: 96.75831 | I37: 0 | J37: 0 | K37: 0 | L37: 0 | M37: 0.0014 | N37: 0 | O37: 0 | P37: 0 | Q37: 0 | R37: 0.0014 | S37: 0 | T37: 0 | U37: 0 | V37: 0 | W37: 0 | X37: 0 | Y37: 0 | Z37: 0 | AA37: 0 | AB37: 0 | AC37: 0 | AD37: 96.75971 | AE37: 0 | AF37: 0.0014 | AG37: 0 | AH37: 0 | AI37: 96.75831
B38: 520105 | C38: Cartera de créditos productivo | D38: 3.45132 | E38: 0 | F38: 0 | G38: 0 | H38: 3.45132 | I38: 0 | J38: 0 | K38: 0 | L38: 0 | M38: 0.0014 | N38: 0 | O38: 0 | P38: 0 | Q38: 0 | R38: 0.0014 | S38: 0 | T38: 0 | U38: 0 | V38: 0 | W38: 0 | X38: 0 | Y38: 0 | Z38: 0 | AA38: 0 | AB38: 0 | AC38: 0 | AD38: 3.45272 | AE38: 0 | AF38: 0.0014 | AG38: 0 | AH38: 0 | AI38: 3.45132
B39: 520110 | C39: Cartera de créditos de consumo | D39: 76.4841 | E39: 0 | F39: 0 | G39: 0 | H39: 76.4841 | I39: 0 | J39: 0 | K39: 0 | L39: 0 | M39: 0 | N39: 0 | O39: 0 | P39: 0 | Q39: 0 | R39: 0 | S39: 0 | T39: 0 | U39: 0 | V39: 0 | W39: 0 | X39: 0 | Y39: 0 | Z39: 0 | AA39: 0 | AB39: 0 | AC39: 0 | AD39: 76.4841 | AE39: 0 | AF39: 0 | AG39: 0 | AH39: 0 | AI39: 76.4841
B40: 520115 | C40: Cartera de créditos de vivienda | D40: 0 | E40: 0 | F40: 0 | G40: 0 | H40: 0 | I40: 0 | J40: 0 | K40: 0 | L40: 0 | M40: 0 | N40: 0 | O40: 0 | P40: 0 | Q40: 0 | R40: 0 | S40: 0 | T40: 0 | U40: 0 | V40: 0 | W40: 0 | X40: 0 | Y40: 0 | Z40: 0 | AA40: 0 | AB40: 0 | AC40: 0 | AD40: 0 | AE40: 0 | AF40: 0 | AG40: 0 | AH40: 0 | AI40: 0
B41: 520120 | C41: Cartera de créditos PARA MICROCRÉDITO | D41: 16.82289 | E41: 0 | F41: 0 | G41: 0 | H41: 16.82289 | I41: 0 | J41: 0 | K41: 0 | L41: 0 | M41: 0 | N41: 0 | O41: 0 | P41: 0 | Q41: 0 | R41: 0 | S41: 0 | T41: 0 | U41: 0 | V41: 0 | W41: 0 | X41: 0 | Y41: 0 | Z41: 0 | AA41: 0 | AB41: 0 | AC41: 0 | AD41: 16.82289 | AE41: 0 | AF41: 0 | AG41: 0 | AH41: 0 | AI41: 16.82289
B42: 520125 | C42: Cartera de créditos reestructurada | D42: 0 | E42: 0 | F42: 0 | G42: 0 | H42: 0 | I42: 0 | J42: 0 | K42: 0 | L42: 0 | M42: 0 | N42: 0 | O42: 0 | P42: 0 | Q42: 0 | R42: 0 | S42: 0 | T42: 0 | U42: 0 | V42: 0 | W42: 0 | X42: 0 | Y42: 0 | Z42: 0 | AA42: 0 | AB42: 0 | AC42: 0 | AD42: 0 | AE42: 0 | AF42: 0 | AG42: 0 | AH42: 0 | AI42: 0
B43: 5202 | C43: Deudores por aceptación | D43: 0 | E43: 0 | F43: 0 | G43: 0 | H43: 0 | I43: 0 | J43: 383.42979 | K43: 0.484 | L43: 0 | M43: 0 | N43: 0 | O43: 0 | P43: 0 | Q43: 0 | R43: 383.91379 | S43: 0 | T43: 0 | U43: 0 | V43: 0 | W43: 0 | X43: 0 | Y43: 0 | Z43: 0 | AA43: 0 | AB43: 0 | AC43: 0 | AD43: 383.91379 | AE43: 0.484 | AF43: 0 | AG43: 0 | AH43: 0 | AI43: 383.42979
B44: 5203 | C44: Avales | D44: 0 | E44: 146.4117 | F44: 343.23203 | G44: 204.72042 | H44: 694.36415 | I44: 70.88362 | J44: 1591.5643 | K44: 0 | L44: 0 | M44: 23.47357 | N44: 724.16323 | O44: 117.32244 | P44: 25.41428 | Q44: 0 | R44: 2552.8214 | S44: 0 | T44: 0 | U44: 229.47083 | V44: 0 | W44: 0 | X44: 0 | Y44: 0 | Z44: 0 | AA44: 0 | AB44: 0 | AC44: 229.47083 | AD44: 3476.6564 | AE44: 724.16323 | AF44: 23.47357 | AG44: 0 | AH44: 0 | AI44: 2729.0196
B45: 5204 | C45: Fianzas | D45: 5286.2295 | E45: 4091.9315 | F45: 5131.2726 | G45: 4067.5778 | H45: 18577.011 | I45: 420.18007 | J45: 4388.9039 | K45: 3189.786 | L45: 12.6375 | M45: 247.8802 | N45: 5691.5616 | O45: 0 | P45: 454.5584 | Q45: 2.62167 | R45: 14408.129 | S45: 97.06601 | T45: 83.38729 | U45: 11.52378 | V45: 0 | W45: 0 | X45: 0 | Y45: 0 | Z45: 0 | AA45: 20.43507 | AB45: 0 | AC45: 212.41215 | AD45: 33197.553 | AE45: 8881.3476 | AF45: 260.5177 | AG45: 0 | AH45: 0 | AI45: 24055.688
B46: 5205 | C46: Cartas de Crédito | D46: 2450.2708 | E46: 938.7358 | F46: 7780.4615 | G46: 1718.8833 | H46: 12888.351 | I46: 239.26742 | J46: 2750.5189 | K46: 1.8 | L46: 0 | M46: 0 | N46: 4260.2109 | O46: 0 | P46: 39.94324 | Q46: 0 | R46: 7291.7405 | S46: 81.47512 | T46: 0 | U46: 0 | V46: 0 | W46: 0 | X46: 0 | Y46: 0 | Z46: 0 | AA46: 0 | AB46: 0 | AC46: 81.47512 | AD46: 20261.567 | AE46: 4262.0109 | AF46: 0 | AG46: 0 | AH46: 0 | AI46: 15999.556
B47: 5290 | C47: Otras | D47: 90426.418 | E47: 51544.676 | F47: 54965.785 | G47: 28252.85 | H47: 225189.73 | I47: 16507.302 | J47: 32677.892 | K47: 266.639 | L47: 72678.525 | M47: 6150.1602 | N47: 22247.41 | O47: 1020.7017 | P47: 1123.5497 | Q47: 3511.1583 | R47: 156183.34 | S47: 1.16961 | T47: 341.11793 | U47: 0 | V47: 0 | W47: 0 | X47: 0 | Y47: 34.97712 | Z47: 0 | AA47: 201.73945 | AB47: 0 | AC47: 579.00411 | AD47: 381952.07 | AE47: 22514.049 | AF47: 78828.685 | AG47: 0 | AH47: 0 | AI47: 280609.34
... B83: 4390 | C83: Otras | D83: 0 | E83: 0 | F83: 0 | G83: 0 | H83: 0 | I83: 0 | J83: 0 | K83: 0 | L83: 0 | M83: 0 | N83: 0 | O83: 0 | P83: 0 | Q83: 0 | R83: 0 | S83: 0 | T83: 0 | U83: 0 | V83: 0 | W83: 0 | X83: 0 | Y83: 0 | Z83: 0 | AA83: 0 | AB83: 0 | AC83: 0 | AD83: 0 | AE83: 0 | AF83: 0 | AG83: 0 | AH83: 0 | AI83: 0
C84: MARGEN BRUTO FINANCIERO | D84: 733941.98 | E84: 593557.38 | F84: 1707271.2 | G84: 558169.88 | H84: 3592940.5 | I84: 174471.72 | J84: 321554.28 | K84: 46976.086 | L84: 405783.01 | M84: 97679.329 | N84: 287523.2 | O84: 67732.352 | P84: 67992.807 | Q84: 105360.58 | R84: 1575073.4 | S84: 21723.158 | T84: 17875.071 | U84: 7718.9149 | V84: 3917.0539 | W84: 8712.4412 | X84: 2495.4519 | Y84: 3494.1582 | Z84: 6279.5542 | AA84: 18840.208 | AB84: 20886.197 | AC84: 111942.21 | AD84: 5279956 | AE84: 334499.29 | AF84: 507379.39 | AG84: 0 | AH84: 27165.751 | AI84: 4410911.6
B86: 44 | C86: PROVISIONES | D86: 233770.16 | E86: 192768.46 | F86: 650051.95 | G86: 223608.84 | H86: 1300199.4 | I86: 40273.219 | J86: 65599.784 | K86: 2957.022 | L86: 148967.27 | M86: 29611.548 | N86: 67539.279 | O86: 24029.032 | P86: 19376.457 | Q86: 30391.288 | R86: 428744.9 | S86: 5471.1537 | T86: 3913.9019 | U86: 611.84817 | V86: 215.02603 | W86: 69.62345 | X86: 1013.0203 | Y86: 280.51467 | Z86: 1796.3132 | AA86: 8169.7871 | AB86: 3152.2985 | AC86: 24693.487 | AD86: 1753637.8 | AE86: 70496.301 | AF86: 178793.85 | AG86: 0 | AH86: 4948.6118 | AI86: 1499399
B87: 4401 | C87: Inversiones | D87: 0 | E87: 0.00176 | F87: 3776.1786 | G87: 10.9437 | H87: 3787.1241 | I87: 472.70278 | J87: 0 | K87: 0 | L87: 0 | M87: 0 | N87: 0 | O87: 0 | P87: 0 | Q87: 0 | R87: 472.70278 | S87: 0 | T87: 0 | U87: 149.71337 | V87: 0 | W87: 0 | X87: 0 | Y87: 0 | Z87: 0 | AA87: 5.47909 | AB87: 0 | AC87: 155.19246 | AD87: 4415.0193 | AE87: 0 | AF87: 0 | AG87: 0 | AH87: 0 | AI87: 4415.0193
B88: 4402 | C88: CARTERA DE CRÉDITOS | D88: 218148.61 | E88: 174876.2 | F88: 587780.59 | G88: 191245.7 | H88: 1172051.1 | I88: 23450.642 | J88: 58933.854 | K88: 2885.76 | L88: 142643.78 | M88: 28321.92 | N88: 59678.173 | O88: 23297.389 | P88: 16951.267 | Q88: 30169.275 | R88: 386332.06 | S88: 3474.061 | T88: 2900.0141 | U88: 280.91016 | V88: 173.8514 | W88: 41.21628 | X88: 885.01102 | Y88: 255.23713 | Z88: 1751.5159 | AA88: 7390.8119 | AB88: 2930.9055 | AC88: 20083.534 | AD88: 1578466.7 | AE88: 62563.933 | AF88: 171139.55 | AG88: 0 | AH88: 4682.4214 | AI88: 1340080.8
B89: 440210 | C89: CRÉDITO PRODUCTIVO | D89: 11980.924 | E89: 16984.548 | F89: 136595.14 | G89: 16489.912 | H89: 182050.53 | I89: 1849.7122 | J89: 12847.42 | K89: 2885.76 | L89: 3157.0066 | M89: 0 | N89: 13803.086 | O89: 3687.7309 | P89: 8604.1394 | Q89: 0 | R89: 46834.855 | S89: 1808.3095 | T89: 1117.2153 | U89: 68.68374 | V89: 25.17192 | W89: 0.13748 | X89: 3.72261 | Y89: 186.53299 | Z89: 175.69909 | AA89: 304.49738 | AB89: 0 | AC89: 3689.97 | AD89: 232575.35 | AE89: 16688.846 | AF89: 3182.1785 | AG89: 0 | AH89: 175.69909 | AI89: 212528.63
B90: 440220 | C90: CRÉDITO DE CONSUMO | D90: 166014.9 | E90: 150148.23 | F90: 285689.35 | G90: 170496.18 | H90: 772348.65 | I90: 20768.346 | J90: 45215.522 | K90: 0 | L90: 138948.16 | M90: 28321.92 | N90: 44561.278 | O90: 17499.512 | P90: 7149.6718 | Q90: 9598.7622 | R90: 312063.17 | S90: 216.47319 | T90: 1737.447 | U90: 79.34045 | V90: 121.39663 | W90: 7.71614 | X90: 562.86815 | Y90: 67.59737 | Z90: 121.2138 | AA90: 2613.709 | AB90: 52.38639 | AC90: 5580.1481 | AD90: 1089992 | AE90: 44561.278 | AF90: 167391.47 | AG90: 0 | AH90: 173.60019 | AI90: 877865.61
B91: 440230 | C91: CRÉDITO INMOBILIARIO | D91: 1553.0406 | E91: 6967.4677 | F91: 15369.58 | G91: 2498.8263 | H91: 26388.914 | I91: 706.45247 | J91: 800.93 | K91: 0 | L91: 0 | M91: 0 | N91: 1278.4129 | O91: 404.62843 | P91: 241.94144 | Q91: 0 | R91: 3432.3652 | S91: 10.63782 | T91: 6.96654 | U91: 0 | V91: 0 | W91: 0 | X91: 0 | Y91: 0.49499 | Z91: 1.2452 | AA91: 246.22323 | AB91: 0 | AC91: 265.56778 | AD91: 30086.847 | AE91: 1278.4129 | AF91: 0 | AG91: 0 | AH91: 1.2452 | AI91: 28807.189
B92: 440235 | C92: CRÉDITO DE VIVIENDA DE INTERÉS SOCIAL Y PÚBLICO | D92: 0 | E92: 348.18229 | F92: 135.84722 | G92: 0 | H92: 484.02951 | I92: 0 | J92: 0 | K92: 0 | L92: 0 | M92: 0 | N92: 0.24413 | O92: 0 | P92: 0 | Q92: 0 | R92: 0.24413 | S92: 0 | T92: 0 | U92: 0 | V92: 0 | W92: 0 | X92: 0 | Y92: 0 | Z92: 0 | AA92: 0 | AB92: 0 | AC92: 0 | AD92: 484.27364 | AE92: 0.24413 | AF92: 0 | AG92: 0 | AH92: 0 | AI92: 484.02951
B93: 440240 | C93: MICROCRÉDITO | D93: 38599.656 | E93: 167.29932 | F93: 149589.54 | G93: 1743.1704 | H93: 190099.67 | I93: 126.13122 | J93: 43.044 | K93: 0 | L93: 538.61154 | M93: 0 | N93: 35.15213 | O93: 1704.5743 | P93: 949.0606 | Q93: 20570.513 | R93: 23967.087 | S93: 1438.0987 | T93: 38.3853 | U93: 132.88597 | V93: 27.28285 | W93: 33.36266 | X93: 318.42026 | Y93: 0.61178 | Z93: 1453.3579 | AA93: 4226.3823 | AB93: 2878.5191 | AC93: 10547.307 | AD93: 224614.06 | AE93: 35.15213 | AF93: 565.89439 | AG93: 0 | AH93: 4331.8769 | AI93: 219681.14
B94: 440245 | C94: CRÉDITO EDUCATIVO | D94: 0.08873 | E94: 260.4775 | F94: 401.1306 | G94: 17.61952 | H94: 679.31635 | I94: 0 | J94: 26.938 | K94: 0 | L94: 0 | M94: 0 | N94: 0 | O94: 0.94378 | P94: 6.45369 | Q94: 0 | R94: 34.33547 | S94: 0.54183 | T94: 0 | U94: 0 | V94: 0 | W94: 0 | X94: 0 | Y94: 0 | Z94: 0 | AA94: 0 | AB94: 0 | AC94: 0.54183 | AD94: 714.19365 | AE94: 0 | AF94: 0 | AG94: 0 | AH94: 0 | AI94: 714.19365
B95: 440250 | C95: CRÉDITO DE INVERSIÓN PÚBLICA | D95: 0 | E95: 0 | F95: 0 | G95: 0 | H95: 0 | I95: 0 | J95: 0 | K95: 0 | L95: 0 | M95: 0 | N95: 0 | O95: 0 | P95: 0 | Q95: 0 | R95: 0 | S95: 0 | T95: 0 | U95: 0 | V95: 0 | W95: 0 | X95: 0 | Y95: 0 | Z95: 0 | AA95: 0 | AB95: 0 | AC95: 0 | AD95: 0 | AE95: 0 | AF95: 0 | AG95: 0 | AH95: 0 | AI95: 0
B96: 4403 | C96: Cuentas por cobrar | D96: 11026.636 | E96: 16468.367 | F96: 41686.636 | G96: 28560.797 | H96: 97742.437 | I96: 9948.0181 | J96: 3510 | K96: 32.075 | L96: 6323.4978 | M96: 1017.1708 | N96: 3587.5234 | O96: 576.69105 | P96: 1403.9904 | Q96: 0 | R96: 26398.967 | S96: 718.29986 | T96: 414.99129 | U96: 133.80163 | V96: 18.68617 | W96: 26.69002 | X96: 128.00931 | Y96: 0 | Z96: 40.44316 | AA96: 366.84805 | AB96: 207.20702 | AC96: 2054.9765 | AD96: 126196.38 | AE96: 3619.5984 | AF96: 7359.3548 | AG96: 0 | AH96: 247.65018 | AI96: 114969.78
B97: 4404 | C97: Bienes realizables, adjudicados por pago y de arrendamiento mercantil | D97: 2555.8018 | E97: 769.36436 | F97: 7302.317 | G97: 1489.2141 | H97: 12116.697 | I97: 1578.0796 | J97: 0 | K97: 0 | L97: 0 | M97: 271.84412 | N97: 1556.0393 | O97: 40.02654 | P97: 945.37599 | Q97: 12.11038 | R97: 4403.4759 | S97: 1266.0116 | T97: 227.49226 | U97: 29.67727 | V97: 0 | W97: 0 | X97: 0 | Y97: 0 | Z97: 0 | AA97: 399.06381 | AB97: 0 | AC97: 1922.245 | AD97: 18442.418 | AE97: 1556.0393 | AF97: 271.84412 | AG97: 0 | AH97: 0 | AI97: 16614.535
... B100: 4407 | C100: Operaciones interbancarias y de reporto | D100: 0 | E100: 0 | F100: 0 | G100: 0 | H100: 0 | I100: 0 | J100: 0 | K100: 0 | L100: 0 | M100: 0 | N100: 0 | O100: 0 | P100: 0 | Q100: 0 | R100: 0 | S100: 0 | T100: 0 | U100: 0 | V100: 0 | W100: 0 | X100: 0 | Y100: 0 | Z100: 0 | AA100: 0 | AB100: 0 | AC100: 0 | AD100: 0 | AE100: 0 | AF100: 0 | AG100: 0 | AH100: 0 | AI100: 0
C101: MARGEN NETO FINANCIERO | D101: 500171.82 | E101: 400788.92 | F101: 1057219.3 | G101: 334561.03 | H101: 2292741.1 | I101: 134198.5 | J101: 255954.5 | K101: 44019.064 | L101: 256815.73 | M101: 68067.78 | N101: 219983.92 | O101: 43703.319 | P101: 48616.35 | Q101: 74969.29 | R101: 1146328.5 | S101: 16252.004 | T101: 13961.169 | U101: 7107.0667 | V101: 3702.0279 | W101: 8642.8178 | X101: 1482.4316 | Y101: 3213.6435 | Z101: 4483.2409 | AA101: 10670.421 | AB101: 17733.898 | AC101: 87248.72 | AD101: 3526318.2 | AE101: 264002.99 | AF101: 328585.54 | AG101: 0 | AH101: 22217.139 | AI101: 2911512.6
B103: 45 | C103: GASTOS DE OPERACIÓN | D103: 303904.27 | E103: 274808.63 | F103: 890395.33 | G103: 288182.8 | H103: 1757291 | I103: 105283 | J103: 160612.95 | K103: 28317.834 | L103: 242164.6 | M103: 53707.188 | N103: 130242.07 | O103: 31691.681 | P103: 41403.129 | Q103: 64216.876 | R103: 857639.33 | S103: 27277.013 | T103: 14707.25 | U103: 7170.1559 | V103: 3727.0175 | W103: 8056.76 | X103: 4535.3025 | Y103: 3548.5379 | Z103: 9608.444 | AA103: 12379.589 | AB103: 13615.948 | AC103: 104626.02 | AD103: 2719556.4 | AE103: 158559.9 | AF103: 299598.81 | AG103: 0 | AH103: 23224.392 | AI103: 2238173.3
B104: 4501 | C104: Gastos de personal | D104: 119000.33 | E104: 103026.21 | F104: 254451.39 | G104: 85910.878 | H104: 562388.81 | I104: 30835.913 | J104: 55400.796 | K104: 11747.845 | L104: 35432.535 | M104: 20005.145 | N104: 51379.575 | O104: 15291.931 | P104: 19387.377 | Q104: 36103.971 | R104: 275585.09 | S104: 11052.249 | T104: 5281.371 | U104: 3573.01 | V104: 2086.0869 | W104: 3010.5706 | X104: 2097.9806 | Y104: 1858.0316 | Z104: 4770.9027 | AA104: 6798.2831 | AB104: 8480.1594 | AC104: 49008.645 | AD104: 886982.54 | AE104: 63127.42 | AF104: 57523.767 | AG104: 0 | AH104: 13251.062 | AI104: 753080.29
B105: 4502 | C105: Honorarios | D105: 13757.984 | E105: 5175.1427 | F105: 109698.8 | G105: 5197.765 | H105: 133829.69 | I105: 12061.617 | J105: 1786.0328 | K105: 0 | L105: 2342.25 | M105: 2733.902 | N105: 541.9802 | O105: 770.20722 | P105: 1458.0556 | Q105: 2115.4216 | R105: 23809.466 | S105: 411.96425 | T105: 1794.8357 | U105: 292.1215 | V105: 212.7293 | W105: 672.69243 | X105: 271.84061 | Y105: 123.23309 | Z105: 491.87292 | AA105: 368.96066 | AB105: 777.36364 | AC105: 5417.6141 | AD105: 163056.78 | AE105: 541.9802 | AF105: 5288.8813 | AG105: 0 | AH105: 1269.2366 | AI105: 155956.68
B106: 4503 | C106: Servicios varios | D106: 101557.34 | E106: 63705.229 | F106: 251379.44 | G106: 122229.93 | H106: 538871.94 | I106: 26586.52 | J106: 47708.118 | K106: 9395.968 | L106: 158400.77 | M106: 13383.865 | N106: 19747.952 | O106: 7355.8271 | P106: 11168.671 | Q106: 14862.939 | R106: 308610.63 | S106: 7031.457 | T106: 3141.2417 | U106: 826.5558 | V106: 616.72087 | W106: 1216.8341 | X106: 1006.6437 | Y106: 1158.6082 | Z106: 1948.8078 | AA106: 3040.688 | AB106: 2949.4604 | AC106: 22937.018 | AD106: 870419.59 | AE106: 29143.92 | AF106: 172401.36 | AG106: 0 | AH106: 4898.2682 | AI106: 663976.04
B107: 4504 | C107: Impuestos, contribuciones y multas | D107: 23890.145 | E107: 46926.6 | F107: 84882.314 | G107: 27895.193 | H107: 183594.25 | I107: 14463.503 | J107: 17337.121 | K107: 5640.077 | L107: 23994.006 | M107: 3723.2337 | N107: 15275.022 | O107: 3640.2509 | P107: 3584.3214 | Q107: 5713.8497 | R107: 93371.384 | S107: 3964.4293 | T107: 1056.9155 | U107: 756.84165 | V107: 267.26056 | W107: 447.94121 | X107: 397.62073 | Y107: 194.81701 | Z107: 264.07129 | AA107: 959.43867 | AB107: 449.90844 | AC107: 8759.2444 | AD107: 285724.88 | AE107: 20915.099 | AF107: 27984.5 | AG107: 0 | AH107: 713.97973 | AI107: 236111.3
B108: 4505 | C108: Depreciaciones | D108: 10800.588 | E108: 10989.432 | F108: 24733.539 | G108: 8554.5111 | H108: 55078.07 | I108: 5708.1403 | J108: 5080.9099 | K108: 581.664 | L108: 1554.9649 | M108: 1229.6119 | N108: 3844.5544 | O108: 961.75265 | P108: 1109.8808 | Q108: 1688.6956 | R108: 21760.174 | S108: 581.32465 | T108: 348.85362 | U108: 414.06651 | V108: 46.5541 | W108: 222.8804 | X108: 171.00648 | Y108: 23.21105 | Z108: 216.56338 | AA108: 368.73138 | AB108: 180.35867 | AC108: 2573.5502 | AD108: 79411.794 | AE108: 4426.2184 | AF108: 2831.1309 | AG108: 0 | AH108: 396.92205 | AI108: 71757.523
B109: 4506 | C109: Amortizaciones | D109: 18565.138 | E109: 21599.739 | F109: 41336.191 | G109: 13323.299 | H109: 94824.367 | I109: 10369.605 | J109: 3237.9445 | K109: 239.022 | L109: 4355.8045 | M109: 3706.7057 | N109: 5743.6375 | O109: 572.53217 | P109: 2044.8244 | Q109: 544.40358 | R109: 30814.479 | S109: 144.75336 | T109: 299.09916 | U109: 349.77361 | V109: 320.94316 | W109: 540.79274 | X109: 361.9574 | Y109: 108.58584 | Z109: 507.50713 | AA109: 180.12767 | AB109: 220.10688 | AC109: 3033.6469 | AD109: 128672.49 | AE109: 5982.6595 | AF109: 8383.4533 | AG109: 0 | AH109: 727.61401 | AI109: 113578.77
B110: 4507 | C110: Otros gastos | D110: 16332.746 | E110: 23386.272 | F110: 123913.66 | G110: 25071.224 | H110: 188703.9 | I110: 5257.6997 | J110: 30062.033 | K110: 713.258 | L110: 16084.266 | M110: 8924.7248 | N110: 33709.345 | O110: 3099.1808 | P110: 2649.9998 | Q110: 3187.5958 | R110: 103688.1 | S110: 4090.8349 | T110: 2784.9337 | U110: 957.78684 | V110: 176.72267 | W110: 1945.0485 | X110: 228.25299 | Y110: 82.05105 | Z110: 1408.7188 | AA110: 663.35942 | AB110: 558.59054 | AC110: 12896.299 | AD110: 305288.3 | AE110: 34422.603 | AF110: 25185.713 | AG110: 0 | AH110: 1967.3093 | AI110: 243712.67
C111: MARGEN DE INTERMEDIACIÓN | D111: 196267.55 | E111: 125980.3 | F111: 166823.96 | G111: 46378.236 | H111: 535450.04 | I111: 28915.504 | J111: 95341.542 | K111: 15701.23 | L111: 14651.135 | M111: 14360.592 | N111: 89741.858 | O111: 12011.638 | P111: 7213.221 | Q111: 10752.414 | R111: 288689.13 | S111: -11025.009 | T111: -746.08121 | U111: -63.08917 | V111: -24.98966 | W111: 586.05778 | X111: -3052.8709 | Y111: -334.89445 | Z111: -5125.2031 | AA111: -1709.1681 | AB111: 4117.95 | AC111: -17377.298 | AD111: 806761.88 | AE111: 105443.09 | AF111: 28986.737 | AG111: 0 | AH111: -1007.253 | AI111: 673339.3
B113: 55 | C113: OTROS INGRESOS OPERACIONALES | D113: 3697.6887 | E113: 45370.15 | F113: 191823.59 | G113: 28339.907 | H113: 269231.33 | I113: 9354.1543 | J113: 3263.3362 | K113: 743.721 | L113: 25477.947 | M113: 31.07931 | N113: 2617.0033 | O113: 1951.8795 | P113: 42.47337 | Q113: 5114.5012 | R113: 48596.095 | S113: 1126.7149 | T113: 18.37152 | U113: 12.79 | V113: 219.00694 | W113: 0 | X113: 1915.2806 | Y113: 0 | Z113: 255.58501 | AA113: 378.4727 | AB113: 0 | AC113: 3926.2216 | AD113: 321753.65 | AE113: 3360.7243 | AF113: 25728.034 | AG113: 0 | AH113: 255.58501 | AI113: 292409.31
B114: 5501 | C114: Utilidades en acciones y participaciones | D114: 3697.6887 | E114: 1790.6198 | F114: 111963.38 | G114: 4744.7752 | H114: 122196.46 | I114: 1155.3619 | J114: 265.74627 | K114: 268.36 | L114: 14878.828 | M114: 0 | N114: 2410.1049 | O114: 181.45449 | P114: 0 | Q114: 0 | R114: 19159.856 | S114: 0 | T114: 18.37152 | U114: 0 | V114: 0 | W114: 0 | X114: 0 | Y114: 0 | Z114: 0 | AA114: 0 | AB114: 0 | AC114: 18.37152 | AD114: 141374.69 | AE114: 2678.4649 | AF114: 14878.828 | AG114: 0 | AH114: 0 | AI114: 123817.39
B115: 5502 | C115: Utilidad en venta de bienes realizables y recuperados | D115: 0 | E115: 0 | F115: 0 | G115: 0 | H115: 0 | I115: 0 | J115: 0 | K115: 0 | L115: 0 | M115: 0 | N115: 0 | O115: 0 | P115: 0 | Q115: 1.5 | R115: 1.5 | S115: 0 | T115: 0 | U115: 0 | V115: 0 | W115: 0 | X115: 0 | Y115: 0 | Z115: 0 | AA115: 1.29441 | AB115: 0 | AC115: 1.29441 | AD115: 2.79441 | AE115: 0 | AF115: 0 | AG115: 0 | AH115: 0 | AI115: 2.79441
B116: 5505 | C116: Ingresos por subsidios realizados | D116: 0 | E116: 0 | F116: 0 | G116: 0 | H116: 0 | I116: 0 | J116: 0 | K116: 0 | L116: 0 | M116: 0 | N116: 0 | O116: 0 | P116: 0 | Q116: 0 | R116: 0 | S116: 0 | T116: 0 | U116: 0 | V116: 0 | W116: 0 | X116: 0 | Y116: 0 | Z116: 0 | AA116: 0 | AB116: 0 | AC116: 0 | AD116: 0 | AE116: 0 | AF116: 0 | AG116: 0 | AH116: 0 | AI116: 0
B117: 5506 | C117: Ingresos por subsidios recuperados | D117: 0 | E117: 0 | F117: 0 | G117: 0 | H117: 0 | I117: 0 | J117: 0 | K117: 0 | L117: 0 | M117: 0 | N117: 0 | O117: 0 | P117: 0 | Q117: 0 | R117: 0 | S117: 0 | T117: 0 | U117: 0 | V117: 0 | W117: 0 | X117: 0 | Y117: 0 | Z117: 0 | AA117: 0 | AB117: 0 | AC117: 0 | AD117: 0 | AE117: 0 | AF117: 0 | AG117: 0 | AH117: 0 | AI117: 0
B118: 5507 | C118: Ingresos por demora en transferencias | D118: 0 | E118: 0 | F118: 0 | G118: 0 | H118: 0 | I118: 0 | J118: 0 | K118: 0 | L118: 0 | M118: 0 | N118: 0 | O118: 0 | P118: 0 | Q118: 0 | R118: 0 | S118: 0 | T118: 0 | U118: 0 | V118: 0 | W118: 0 | X118: 0 | Y118: 0 | Z118: 0 | AA118: 0 | AB118: 0 | AC118: 0 | AD118: 0 | AE118: 0 | AF118: 0 | AG118: 0 | AH118: 0 | AI118: 0
B119: 5590 | C119: Otros | D119: 0 | E119: 43579.53 | F119: 79860.213 | G119: 23595.131 | H119: 147034.87 | I119: 8198.7924 | J119: 2997.5899 | K119: 475.361 | L119: 10599.119 | M119: 31.07931 | N119: 206.89835 | O119: 1770.425 | P119: 42.47337 | Q119: 5113.0012 | R119: 29434.74 | S119: 1126.7149 | T119: 0 | U119: 12.79 | V119: 219.00694 | W119: 0 | X119: 1915.2806 | Y119: 0 | Z119: 255.58501 | AA119: 377.17829 | AB119: 0 | AC119: 3906.5557 | AD119: 180376.17 | AE119: 682.25935 | AF119: 10849.205 | AG119: 0 | AH119: 255.58501 | AI119: 168589.12
B120: 46 | C120: OTRAS PÉRDIDAS OPERACIONALES | D120: 2540.1581 | E120: 3772.2362 | F120: 133706.55 | G120: 1796.5672 | H120: 141815.51 | I120: 808.66766 | J120: 155.80222 | K120: 5.593 | L120: 7362.2954 | M120: 228.06521 | N120: 228.79261 | O120: 387.36572 | P120: 0 | Q120: 15422.147 | R120: 24598.729 | S120: 0 | T120: 209.49864 | U120: 35.26082 | V120: 26.42345 | W120: 0 | X120: 0 | Y120: 0 | Z120: 119.07245 | AA120: 30.92817 | AB120: 0 | AC120: 421.18353 | AD120: 166835.43 | AE120: 234.38561 | AF120: 7616.7841 | AG120: 0 | AH120: 119.07245 | AI120: 158865.18
B121: 4601 | C121: Pérdida en acciones y participaciones | D121: 1999.3686 | E121: 1337.6736 | F121: 110589.22 | G121: 1596.4936 | H121: 115522.75 | I121: 550.45665 | J121: 28.95264 | K121: 0 | L121: 7362.2954 | M121: 0 | N121: 228.79261 | O121: 7.93987 | P121: 0 | Q121: 0 | R121: 8178.4372 | S121: 0 | T121: 10.15038 | U121: 0 | V121: 0 | W121: 0 | X121: 0 | Y121: 0 | Z121: 0 | AA121: 0 | AB121: 0 | AC121: 10.15038 | AD121: 123711.34 | AE121: 228.79261 | AF121: 7362.2954 | AG121: 0 | AH121: 0 | AI121: 116120.25
B122: 4602 | C122: Pérdida en venta de bienes realizables y recuperados | D122: 429.35456 | E122: 554.86453 | F122: 0 | G122: 200.07363 | H122: 1184.2927 | I122: 0 | J122: 0 | K122: 0 | L122: 0 | M122: 61.735 | N122: 0 | O122: 0 | P122: 0 | Q122: 5.39837 | R122: 67.13337 | S122: 0 | T122: 23.98219 | U122: 0 | V122: 26.42345 | W122: 0 | X122: 0 | Y122: 0 | Z122: 0 | AA122: 0 | AB122: 0 | AC122: 50.40564 | AD122: 1301.8317 | AE122: 0 | AF122: 88.15845 | AG122: 0 | AH122: 0 | AI122: 1213.6733
B123: 4690 | C123: Otras | D123: 111.43488 | E123: 1879.6981 | F123: 23117.337 | G123: 0 | H123: 25108.47 | I123: 258.21101 | J123: 126.84958 | K123: 5.593 | L123: 0 | M123: 166.33021 | N123: 0 | O123: 379.42585 | P123: 0 | Q123: 15416.748 | R123: 16353.158 | S123: 0 | T123: 175.36607 | U123: 35.26082 | V123: 0 | W123: 0 | X123: 0 | Y123: 0 | Z123: 119.07245 | AA123: 30.92817 | AB123: 0 | AC123: 360.62751 | AD123: 41822.255 | AE123: 5.593 | AF123: 166.33021 | AG123: 0 | AH123: 119.07245 | AI123: 41531.26
C124: MARGEN OPERACIONAL | D124: 197425.08 | E124: 167578.21 | F124: 224941 | G124: 72921.576 | H124: 662865.86 | I124: 37460.99 | J124: 98449.076 | K124: 16439.358 | L124: 32766.787 | M124: 14163.606 | N124: 92130.068 | O124: 13576.152 | P124: 7255.6944 | Q124: 444.76861 | R124: 312686.5 | S124: -9898.2942 | T124: -937.20833 | U124: -85.55999 | V124: 167.59383 | W124: 586.05778 | X124: -1137.5903 | Y124: -334.89445 | Z124: -4988.6905 | AA124: -1361.6236 | AB124: 4117.95 | AC124: -13872.26 | AD124: 961680.1 | AE124: 108569.43 | AF124: 47097.987 | AG124: 0 | AH124: -870.74048 | AI124: 806883.43
B126: 56 | C126: OTROS INGRESOS | D126: 28323.734 | E126: 120851.01 | F126: 107630.83 | G126: 50091.188 | H126: 306896.76 | I126: 13557.139 | J126: 7228.8806 | K126: 14403.56 | L126: 43495.868 | M126: 8035.9037 | N126: 12503.971 | O126: 3386.3126 | P126: 3951.7936 | Q126: 3992.5544 | R126: 110555.98 | S126: 981.79495 | T126: 3539.5065 | U126: 344.72601 | V126: 260.16012 | W126: 310.95963 | X126: 1503.8589 | Y126: 373.88494 | Z126: 5082.3928 | AA126: 5605.4922 | AB126: 3124.9156 | AC126: 21127.692 | AD126: 438580.43 | AE126: 26907.531 | AF126: 51791.932 | AG126: 0 | AH126: 8207.3083 | AI126: 351673.66
B127: 5601 | C127: Utilidad en venta de bienes | D127: 637.2142 | E127: 241.01787 | F127: 1231.2791 | G127: 236.76782 | H127: 2346.279 | I127: 2038.2308 | J127: 19.41509 | K127: 0 | L127: 2.92068 | M127: 3.97924 | N127: 2673.8009 | O127: 12.83688 | P127: 0 | Q127: 4.84369 | R127: 4756.0273 | S127: 81.25684 | T127: 4.15008 | U127: 1.34289 | V127: 0 | W127: 0 | X127: 5.37252 | Y127: 0 | Z127: 38.83761 | AA127: 0.23378 | AB127: 0 | AC127: 131.19372 | AD127: 7233.5 | AE127: 2673.8009 | AF127: 6.89992 | AG127: 0 | AH127: 38.83761 | AI127: 4513.9616
B128: 5602 | C128: Utilidad en venta de acciones y participaciones | D128: 0 | E128: 0 | F128: 0 | G128: 0 | H128: 0 | I128: 0 | J128: 0 | K128: 0 | L128: 0 | M128: 0 | N128: 0 | O128: 0 | P128: 0 | Q128: 0 | R128: 0 | S128: 0 | T128: 0 | U128: 0 | V128: 0 | W128: 0 | X128: 0 | Y128: 0 | Z128: 0 | AA128: 0 | AB128: 0 | AC128: 0 | AD128: 0 | AE128: 0 | AF128: 0 | AG128: 0 | AH128: 0 | AI128: 0
B129: 5603 | C129: Arrendamientos | D129: 46.6128 | E129: 0 | F129: 1937.9024 | G129: 2450.6406 | H129: 4435.1559 | I129: 81.72688 | J129: 28 | K129: 0 | L129: 89.43474 | M129: 0 | N129: 138.09024 | O129: 0 | P129: 0 | Q129: 89.36694 | R129: 426.6188 | S129: 0 | T129: 211.58526 | U129: 0 | V129: 1.6 | W129: 5.1294 | X129: 54.55456 | Y129: 0 | Z129: 0 | AA129: 0 | AB129: 0 | AC129: 272.86922 | AD129: 5134.6439 | AE129: 138.09024 | AF129: 91.03474 | AG129: 0 | AH129: 0 | AI129: 4905.5189
B130: 5604 | C130: Recuperaciones de activos financieros | D130: 26497.409 | E130: 98813.27 | F130: 95898.132 | G130: 40219.507 | H130: 261428.32 | I130: 9647.1772 | J130: 4875.456 | K130: 4998.101 | L130: 41665.902 | M130: 6561.8959 | N130: 7525.2366 | O130: 2358.0701 | P130: 3178.056 | Q130: 2133.6792 | R130: 82943.574 | S130: 695.19989 | T130: 711.65439 | U130: 343.38312 | V130: 255.96427 | W130: 195.61993 | X130: 1141.96 | Y130: 213.97043 | Z130: 3538.1562 | AA130: 5081.0246 | AB130: 1509.4171 | AC130: 13686.35 | AD130: 358058.24 | AE130: 12523.338 | AF130: 48483.762 | AG130: 0 | AH130: 5047.5733 | AI130: 292003.57
B131: 5690 | C131: Otros | D131: 1142.4977 | E131: 21796.722 | F131: 8563.5126 | G131: 7184.272 | H131: 38687.005 | I131: 1790.0045 | J131: 2306.0095 | K131: 9405.459 | L131: 1737.6106 | M131: 1470.0285 | N131: 2166.8437 | O131: 1015.4057 | P131: 773.73756 | Q131: 1764.6646 | R131: 22429.764 | S131: 205.33822 | T131: 2612.1168 | U131: 0 | V131: 2.59585 | W131: 110.2103 | X131: 301.97181 | Y131: 159.91451 | Z131: 1505.399 | AA131: 524.23381 | AB131: 1615.4985 | AC131: 7037.2787 | AD131: 68154.047 | AE131: 11572.303 | AF131: 3210.235 | AG131: 0 | AH131: 3120.8974 | AI131: 50250.612
B132: 47 | C132: OTROS GASTOS Y PÉRDIDAS | D132: 7334.8396 | E132: 12356.858 | F132: 18077.024 | G132: 910.10393 | H132: 38678.826 | I132: 10324.858 | J132: 1390.9813 | K132: 286.683 | L132: 10579.449 | M132: 1419.0689 | N132: 7779.6391 | O132: 585.90263 | P132: 858.65258 | Q132: 803.08014 | R132: 34028.315 | S132: 646.41749 | T132: 569.38066 | U132: 107.06368 | V132: 78.20778 | W132: 1.39855 | X132: 327.56602 | Y132: 6.89883 | Z132: 0.66709 | AA132: 889.75206 | AB132: 107.65185 | AC132: 2735.004 | AD132: 75442.145 | AE132: 8066.3221 | AF132: 12076.726 | AG132: 0 | AH132: 108.31894 | AI132: 55190.778
B133: 4701 | C133: Pérdida en venta de bienes | D133: 8.6879 | E133: 0 | F133: 0.21715 | G133: 25.77872 | H133: 34.68377 | I133: 1101.2462 | J133: 0 | K133: 0 | L133: 0.53692 | M133: 0 | N133: 28.37405 | O133: 1.19994 | P133: 15.44991 | Q133: 2.89238 | R133: 1149.6994 | S133: 285.63378 | T133: 0 | U133: 0 | V133: 0 | W133: 0 | X133: 0 | Y133: 0 | Z133: 0 | AA133: 15.18116 | AB133: 0 | AC133: 300.81494 | AD133: 1485.1981 | AE133: 28.37405 | AF133: 0.53692 | AG133: 0 | AH133: 0 | AI133: 1456.2872
B134: 4702 | C134: Pérdida en venta de acciones y participaciones | D134: 0 | E134: 0 | F134: 0 | G134: 83.6258 | H134: 83.6258 | I134: 0 | J134: 0 | K134: 0 | L134: 0 | M134: 0 | N134: 0 | O134: 0 | P134: 0 | Q134: 0 | R134: 0 | S134: 0 | T134: 0 | U134: 0 | V134: 0 | W134: 0 | X134: 0 | Y134: 0 | Z134: 0 | AA134: 0 | AB134: 0 | AC134: 0 | AD134: 83.6258 | AE134: 0 | AF134: 0 | AG134: 0 | AH134: 0 | AI134: 83.6258
B135: 4703 | C135: INTERESES y comisiones devengados en ejercicios anteriores | D135: 2113.1439 | E135: 3715.6226 | F135: 18076.807 | G135: 800.69941 | H135: 24706.273 | I135: 5409.7269 | J135: 1295.7082 | K135: 38.109 | L135: 3833.5233 | M135: 979.29849 | N135: 1214.0604 | O135: 570.10766 | P135: 472.34556 | Q135: 610.72159 | R135: 14423.601 | S135: 360.78371 | T135: 569.38066 | U135: 26.42808 | V135: 78.18354 | W135: 1.39855 | X135: 0 | Y135: 0 | Z135: 0.66709 | AA135: 655.21083 | AB135: 52.75702 | AC135: 1744.8095 | AD135: 40874.684 | AE135: 1252.1694 | AF135: 4891.0054 | AG135: 0 | AH135: 53.42411 | AI135: 34678.085
B136: 4790 | C136: Otros | D136: 5213.0078 | E136: 8641.2357 | F136: 0 | G136: 0 | H136: 13854.244 | I136: 3813.8844 | J136: 95.27311 | K136: 248.574 | L136: 6745.3891 | M136: 439.77045 | N136: 6537.2046 | O136: 14.59503 | P136: 370.85711 | Q136: 189.46617 | R136: 18455.014 | S136: 0 | T136: 0 | U136: 80.6356 | V136: 0.02424 | W136: 0 | X136: 327.56602 | Y136: 6.89883 | Z136: 0 | AA136: 219.36007 | AB136: 54.89483 | AC136: 689.37959 | AD136: 32998.637 | AE136: 6785.7786 | AF136: 7185.1838 | AG136: 0 | AH136: 54.89483 | AI136: 18972.78
C137: GANANCIA O (PÉRDIDA) ANTES DE IMPUESTOS | D137: 218413.97 | E137: 276072.36 | F137: 314494.8 | G137: 122102.66 | H137: 931083.79 | I137: 40693.272 | J137: 104286.97 | K137: 30556.235 | L137: 65683.205 | M137: 20780.441 | N137: 96854.4 | O137: 16376.562 | P137: 10348.835 | Q137: 3634.2429 | R137: 389214.17 | S137: -9562.9168 | T137: 2032.9175 | U137: 152.10234 | V137: 349.54617 | W137: 895.61886 | X137: 38.70251 | Y137: 32.09166 | Z137: 93.03519 | AA137: 3354.1165 | AB137: 7135.2137 | AC137: 4520.4277 | AD137: 1324818.4 | AE137: 127410.64 | AF137: 86813.193 | AG137: 0 | AH137: 7228.2489 | AI137: 1103366.3
B139: 48 | C139: IMPUESTOS Y PARTICIPACIÓN A EMPLEADOS | D139: 65754.541 | E139: 69940.889 | F139: 73996.913 | G139: 36829.557 | H139: 246521.9 | I139: 17186.753 | J139: 33617.97 | K139: 8939.801 | L139: 22634.894 | M139: 5553.5446 | N139: 28711.739 | O139: 5809.9358 | P139: 2995.7353 | Q139: 797.56896 | R139: 126247.94 | S139: 0 | T139: 677.39381 | U139: 129.30322 | V139: 166.29935 | W139: 430.92047 | X139: 129.53011 | Y139: 22.13061 | Z139: 77.5309 | AA139: 1346.616 | AB139: 2626.0679 | AC139: 5605.7924 | AD139: 378375.63 | AE139: 37651.54 | AF139: 28354.738 | AG139: 0 | AH139: 2703.5988 | AI139: 309665.76
B140: 4810 | C140: Participación a empleados | D140: 32389.082 | E140: 0 | F140: 46968.096 | G140: 18312.019 | H140: 97669.197 | I140: 6103.9908 | J140: 15643.046 | K140: 4583.435 | L140: 8749.256 | M140: 3117.0662 | N140: 14528.16 | O140: 2456.4843 | P140: 1552.3253 | Q140: 545.13644 | R140: 57278.9 | S140: 0 | T140: 304.93762 | U140: 22.81535 | V140: 52.43193 | W140: 134.34283 | X140: 5.80538 | Y140: 4.81375 | Z140: 13.95531 | AA140: 503.11748 | AB140: 1070.2821 | AC140: 2112.5017 | AD140: 157060.6 | AE140: 19111.595 | AF140: 11918.754 | AG140: 0 | AH140: 1084.2374 | AI140: 124946.01
B141: 4815 | C141: Impuesto a la renta | D141: 33365.459 | E141: 69940.889 | F141: 27028.817 | G141: 18517.538 | H141: 148852.7 | I141: 11082.763 | J141: 17974.924 | K141: 7603.422 | L141: 13885.638 | M141: 2436.4785 | N141: 14183.579 | O141: 3353.4515 | P141: 1443.41 | Q141: 252.43252 | R141: 72216.097 | S141: 0 | T141: 372.45619 | U141: 106.48787 | V141: 113.86742 | W141: 296.57764 | X141: 123.72473 | Y141: 17.31686 | Z141: 63.57559 | AA141: 843.49856 | AB141: 1555.7858 | AC141: 3493.2907 | AD141: 224562.09 | AE141: 21787.001 | AF141: 16435.984 | AG141: 0 | AH141: 1619.3614 | AI141: 184719.75
B142: 4890 | C142: Otros | D142: 0 | E142: 0 | F142: 0 | G142: 0 | H142: 0 | I142: 0 | J142: 0 | K142: -3247.056 | L142: 0 | M142: 0 | N142: 0 | O142: 0 | P142: 0 | Q142: 0 | R142: -3247.056 | S142: 0 | T142: 0 | U142: 0 | V142: 0 | W142: 0 | X142: 0 | Y142: 0 | Z142: 0 | AA142: 0 | AB142: 0 | AC142: 0 | AD142: -3247.056 | AE142: -3247.056 | AF142: 0 | AG142: 0 | AH142: 0 | AI142: 0
C143: GANANCIA O (PÉRDIDA) DEL EJERCICIO | D143: 152659.43 | E143: 206131.47 | F143: 240497.89 | G143: 85273.102 | H143: 684561.89 | I143: 23506.519 | J143: 70669.005 | K143: 21616.434 | L143: 43048.312 | M143: 15226.897 | N143: 68142.661 | O143: 10566.626 | P143: 7353.1001 | Q143: 2836.6739 | R143: 262966.23 | S143: -9562.9168 | T143: 1355.5237 | U143: 22.79912 | V143: 183.24682 | W143: 464.69839 | X143: -90.8276 | Y143: 9.96105 | Z143: 15.50429 | AA143: 2007.5005 | AB143: 4509.1458 | AC143: -1085.3647 | AD143: 946442.75 | AE143: 89759.095 | AF143: 58458.455 | AG143: 0 | AH143: 4524.6501 | AI143: 793700.55

Sheet BALANCE %
B3: ESTADO DE SITUACIÓN CONSOLIDADO
B4: SISTEMA DE BANCOS PRIVADOS
B5: 31/12/2025
B6: (en porcentajes)
B8: CÓDIGO | C8: CUENTA | D8: BP GUAYAQUIL | E8: BP PACIFICO | F8: BP PICHINCHA | G8: BP PRODUBANCO | H8: BANCOS PRIVADOS GRANDES | I8: BP AUSTRO | J8: BP BOLIVARIANO | K8: BP CITIBANK | L8: BP DINERS | M8: BP GENERAL RUMIÑAHUI | N8: BP INTERNACIONAL | O8: BP LOJA | P8: BP MACHALA | Q8: BP SOLIDARIO | R8: BANCOS PRIVADOS MEDIANOS | S8: BP PROCREDIT | T8: BP AMAZONAS | U8: BP BANCO COMERCIAL DE MANABI | V8: BP LITORAL | W8: BP COOPNACIONAL | X8: BP CAPITAL | Y8: BP DELBANK | Z8: BANCO ATLÁNTIDA S.A. | AA8: BP BANCO DESARROLLO DE LOS PUEBLOS S.A., CODESARROLLO | AB8: BP VISIONFUND ECUADOR S.A. | AC8: BANCOS PRIVADOS PEQUEÑOS | AD8: TOTAL BANCOS PRIVADOS | AE8: BANCOS PRIVADOS COMERCIALES | AF8: BANCOS PRIVADOS CONSUMO | AG8: BANCOS PRIVADOS VIVIENDA | AH8: BANCOS PRIVADOS MICROCRÉDITO | AI8: BANCA MÚLTIPLE
C9: ACTIVO
B10: 11 | C10: FONDOS DISPONIBLES | D10: 0.10401303 | E10: 0.12509018 | F10: 0.11598963 | G10: 0.10803661 | H10: 0.11401978 | I10: 0.14121236 | J10: 0.10088554 | K10: 0.21306848 | L10: 0.060608149 | M10: 0.14046056 | N10: 0.14388977 | O10: 0.21643479 | P10: 0.1812971 | Q10: 0.094651477 | R10: 0.12657 | S10: 0.15891682 | T10: 0.093133348 | U10: 0.10131992 | V10: 0.098118005 | W10: 0.26645154 | X10: 0.039507497 | Y10: 0.19892412 | Z10: 0.093890821 | AA10: 0.14865752 | AB10: 0.079872142 | AC10: 0.13930543 | AD10: 0.11872435 | AE10: 0.15201363 | AF10: 0.084355917 | AG10: 0 | AH10: 0.085869702 | AI10: 0.11786582
B11: 12 | C11: OPERACIONES INTERBANCARIAS | D11: 0 | E11: 0 | F11: 0 | G11: 0 | H11: 0 | I11: 0 | J11: 0 | K11: 0 | L11: 0 | M11: 0 | N11: 0 | O11: 0 | P11: 0 | Q11: 0 | R11: 0 | S11: 0 | T11: 0 | U11: 0 | V11: 0 | W11: 0 | X11: 0 | Y11: 0 | Z11: 0 | AA11: 0 | AB11: 0 | AC11: 0 | AD11: 0 | AE11: 0 | AF11: 0 | AG11: 0 | AH11: 0 | AI11: 0
B12: 13 | C12: INVERSIONES | D12: 0.15520984 | E12: 0.1942001 | F12: 0.21062203 | G12: 0.1696505 | H12: 0.18924676 | I12: 0.20031243 | J12: 0.18010838 | K12: 0.31829912 | L12: 0.081626781 | M12: 0.16850648 | N12: 0.12970145 | O12: 0.13500869 | P12: 0.12142123 | Q12: 0.090338397 | R12: 0.15295019 | S12: 0.097167095 | T12: 0.21949281 | U12: 0.29849813 | V12: 0.091344894 | W12: 0.56032853 | X12: 0.075767405 | Y12: 0.049556261 | Z12: 0.28115768 | AA12: 0.18230881 | AB12: 0.028108311 | AC12: 0.19537246 | AD12: 0.17800682 | AE12: 0.15184902 | AF12: 0.10718306 | AG12: 0 | AH12: 0.1363695 | AI12: 0.18614841
C13: INVERSIONES DEL SECTOR PRIVADO | D13: 0.008003797 | E13: 0.04724842 | F13: 0.036377404 | G13: 0.09228086 | H13: 0.04312791 | I13: 0.073176102 | J13: 0.024075802 | K13: 0.077032897 | L13: 0.0026326877 | M13: 0.060208088 | N13: 0.060204261 | O13: 0.065215605 | P13: 0.016214818 | Q13: 0.041989443 | R13: 0.042765062 | S13: 0.003802035 | T13: 0.11732124 | U13: 0.21094263 | V13: 0.015142149 | W13: 0.48198154 | X13: 0.000181606 | Y13: 0 | Z13: 0.10550277 | AA13: 0.12468179 | AB13: 0 | AC13: 0.1095064 | AD13: 0.044995475 | AE13: 0.062180496 | AF13: 0.019623824 | AG13: 0 | AH13: 0.045136864 | AI13: 0.045034519
C14: INVERSIONES DEL SECTOR PUBLICO | D14: 0.13698846 | E14: 0.13662178 | F14: 0.15350368 | G14: 0.066286098 | H14: 0.13121032 | I14: 0.11404083 | J14: 0.14827537 | K14: 0.24126622 | L14: 0.06673125 | M14: 0.10256925 | N14: 0.062910048 | O14: 0.069698516 | P14: 0.097339157 | Q14: 0.048348955 | R14: 0.1022937 | S14: 0.09091282 | T14: 0.10153882 | U14: 0.08530484 | V14: 0.076202744 | W14: 0.078427496 | X14: 0.070134831 | Y14: 0.048332226 | Z14: 0.16466816 | AA14: 0.057627023 | AB14: 0.028108311 | AC14: 0.084063895 | AD14: 0.12070245 | AE14: 0.083854927 | AF14: 0.077322688 | AG14: 0 | AH14: 0.086532212 | AI14: 0.12793182
B15: 1307 | C15: De disponibilidad restringida | D15: 0.010226659 | E15: 0.010619272 | F15: 0.02311989 | G15: 0.011088597 | H15: 0.015988147 | I15: 0.013235983 | J15: 0.0079441317 | K15: 0 | L15: 0.012262843 | M15: 0.0072942273 | N15: 0.0065871399 | O15: 9.9543491e-05 | P15: 0.0078672588 | Q15: 0 | R15: 0.0080493704 | S15: 0.0024522397 | T15: 0.00074421969 | U15: 0.0052657911 | V15: 0 | W15: 0 | X15: 0.005450968 | Y15: 0.0012884574 | Z15: 0.01098675 | AA15: 0 | AB15: 0 | AC15: 0.0020146501 | AD15: 0.013072566 | AE15: 0.0058135931 | AF15: 0.010695346 | AG15: 0 | AH15: 0.0047004208 | AI15: 0.014052306
B16: 1399 | C16: (Provisión para inversiones) | D16: -9.078624e-06 | E16: -0.0002893778 | F16: -0.0023789445 | G16: -5.056041e-06 | H16: -0.0010796165 | I16: -0.00014048651 | J16: -0.00018692775 | K16: 0 | L16: 0 | M16: -0.001565088 | N16: 0 | O16: -4.977175e-06 | P16: 0 | Q16: 0 | R16: -0.00015794446 | S16: 0 | T16: -0.00011146518 | U16: -0.0030151326 | V16: 0 | W16: -8.0504386e-05 | X16: 0 | Y16: -6.4422872e-05 | Z16: 0 | AA16: 0 | AB16: 0 | AC16: -0.00021248251 | AD16: -0.00076367028 | AE16: 0 | AF16: -0.00045879748 | AG16: 0 | AH16: 0 | AI16: -0.00087023041
B17: 14 | C17: CARTERA DE CRÉDITOS | D17: 0.67654236 | E17: 0.61794319 | F17: 0.56940454 | G17: 0.67017338 | H17: 0.6179312 | I17: 0.52754745 | J17: 0.66540337 | K17: 0.4297836 | L17: 0.76953226 | M17: 0.63901952 | N17: 0.67716246 | O17: 0.603164 | P17: 0.63660907 | Q17: 0.7451697 | R17: 0.65247685 | S17: 0.69764482 | T17: 0.56288265 | U17: 0.42978584 | V17: 0.73065234 | W17: 0.14347556 | X17: 0.68707083 | Y17: 0.68880279 | Z17: 0.52677581 | AA17: 0.61087875 | AB17: 0.86574897 | AC17: 0.58989184 | AD17: 0.62796587 | AE17: 0.64811205 | AF17: 0.73092128 | AG17: 0 | AH17: 0.72072733 | AI17: 0.61787828
C18: CARTERA DE CRÉDITOS PRODUCTIVO | D18: 0.34607966 | E18: 0.24997195 | F18: 0.2528779 | G18: 0.41567744 | H18: 0.29980974 | I18: 0.18069562 | J18: 0.48174692 | K18: 0.45102874 | L18: 0.054093944 | M18: 0.067026265 | N18: 0.57072975 | O18: 0.18877277 | P18: 0.46413152 | Q18: 2.5476274e-05 | R18: 0.35006283 | S18: 0.4431912 | T18: 0.28381499 | U18: 0.23270159 | V18: 0.21500343 | W18: 0.14159333 | X18: 0.0078959612 | Y18: 0.54046924 | Z18: 0.06775265 | AA18: 0.09336188 | AB18: 0 | AC18: 0.24898843 | AD18: 0.3141075 | AE18: 0.55667292 | AF18: 0.05934114 | AG18: 0 | AH18: 0.028986368 | AI18: 0.30837412
C19: CARTERA DE CRÉDITOS CONSUMO | D19: 0.28330458 | E19: 0.34457536 | F19: 0.24136852 | G19: 0.2463718 | H19: 0.27068876 | I19: 0.34509145 | J19: 0.17337619 | K19: 0 | L19: 0.77366053 | M19: 0.53941582 | N19: 0.10780367 | O19: 0.2800279 | P19: 0.15552272 | Q19: 0.4020413 | R19: 0.28933777 | S19: 0.017517437 | T19: 0.28015245 | U19: 0.15601505 | V19: 0.54238322 | W19: 0.0020087482 | X19: 0.4657482 | Y19: 0.12551983 | Z19: 0.11026478 | AA19: 0.27561445 | AB19: 0.02136511 | AC19: 0.14226757 | AD19: 0.27272369 | AE19: 0.095143971 | AF19: 0.70289995 | AG19: 0 | AH19: 0.059398729 | AI19: 0.26096408
C20: CARTERA DE CRÉDITOS INMOBILIARIO | D20: 0.024093455 | E20: 0.049955917 | F20: 0.047674386 | G20: 0.035190611 | H20: 0.041296072 | I20: 0.017769259 | J20: 0.026614951 | K20: 0 | L20: 4.9923418e-05 | M20: 0.087983312 | N20: 0.026128043 | O20: 0.058695897 | P20: 0.035316729 | Q20: 5.0959e-08 | R20: 0.025205762 | S20: 0.038683892 | T20: 0.0084384325 | U20: 0 | V20: 0.00084925839 | W20: 0.00091381528 | X20: 0 | Y20: 0.036884301 | Z20: 0.0010040126 | AA20: 0.094094246 | AB20: 0 | AC20: 0.02823718 | AD20: 0.035842444 | AE20: 0.023059752 | AF20: 0.025834376 | AG20: 0 | AH20: 0.00042954305 | AI20: 0.038086631
C21: CARTERA DE CRÉDITOS MICROCRÉDITO | D21: 0.046679776 | E21: 0.0016287272 | F21: 0.099281057 | G21: 0.0067179592 | H21: 0.053149908 | I21: 0.0043532459 | J21: 0.00013465733 | K21: 0 | L21: 0.003223202 | M21: 0.00023469954 | N21: 0.00097072104 | O21: 0.14605601 | P21: 0.0079364115 | Q21: 0.42031427 | R21: 0.021168766 | S21: 0.22611271 | T21: 0.01322272 | U21: 0.049492742 | V21: 0.029420115 | W21: 0.0093887901 | X21: 0.23145323 | Y21: 0.0054366511 | Z21: 0.36894456 | AA21: 0.20368498 | AB21: 0.90651858 | AC21: 0.20068944 | AD21: 0.047490037 | AE21: 0.00085672648 | AF21: 0.0025842073 | AG21: 0 | AH21: 0.67653026 | AI21: 0.052898255
C22: CARTERA DE CRÉDITOS VIVIENDA DE INTERÉS SOCIAL Y PÚBLICO | D22: 0 | E22: 0.00034893266 | F22: 0.00034611953 | G22: 0 | H22: 0.00021700871 | I22: 0 | J22: 0 | K22: 0 | L22: 0 | M22: 0.0098153564 | N22: 4.7544679e-05 | O22: 0 | P22: 0 | Q22: 0 | R22: 0.0005777029 | S22: 0 | T22: 0 | U22: 0 | V22: 0 | W22: 0 | X22: 0 | Y22: 0 | Z22: 0 | AA22: 0 | AB22: 0 | AC22: 0 | AD22: 0.00032404319 | AE22: 4.196137e-05 | AF22: 0.0028773211 | AG22: 0 | AH22: 0 | AI22: 0.00016834107
C23: CARTERA DE CRÃ¿DITOS EDUCATIVO | D23: 0.00016903451 | E23: 0.012246797 | F23: 0.0016378248 | G23: 0.00010158754 | H23: 0.0031610513 | I23: 0 | J23: 0.00038257629 | K23: 0 | L23: 0 | M23: 0 | N23: 0 | O23: 0.00020080706 | P23: 0.00087118847 | Q23: 0 | R23: 0.00015157517 | S23: 2.5788241e-05 | T23: 0 | U23: 0 | V23: 0 | W23: 0 | X23: 0 | Y23: 0 | Z23: 0 | AA23: 0 | AB23: 0 | AC23: 8.004047e-06 | AD23: 0.0021198094 | AE23: 0 | AF23: 0 | AG23: 0 | AH23: 0 | AI23: 0.0025088753
C24: CARTERA DE CRÉDITO INVERSIÓN PÚBLICA | D24: 0 | E24: 0 | F24: 0 | G24: 0 | H24: 0 | I24: 0 | J24: 0 | K24: 0 | L24: 0 | M24: 0 | N24: 0 | O24: 0 | P24: 0 | Q24: 0 | R24: 0 | S24: 0 | T24: 0 | U24: 0 | V24: 0 | W24: 0 | X24: 0 | Y24: 0 | Z24: 0 | AA24: 0 | AB24: 0 | AC24: 0 | AD24: 0 | AE24: 0 | AF24: 0 | AG24: 0 | AH24: 0 | AI24: 0
B25: 1499 | C25: (PROVISIONES PARA CRÉDITOS INCOBRABLES) | D25: -0.023784144 | E25: -0.040784506 | F25: -0.073781273 | G25: -0.033886011 | H25: -0.050391347 | I25: -0.020362116 | J25: -0.016851923 | K25: -0.021245146 | L25: -0.061495333 | M25: -0.065455933 | N25: -0.028517264 | O25: -0.070589388 | P25: -0.027169496 | Q25: -0.077211397 | R25: -0.034027565 | S25: -0.027886202 | T25: -0.022745944 | U25: -0.0084235426 | V25: -0.057003684 | W25: -0.010429127 | X25: -0.01802656 | Y25: -0.019507239 | Z25: -0.021190194 | AA25: -0.055876806 | AB25: -0.06213472 | AC25: -0.030298787 | AD25: -0.044641662 | AE25: -0.027663278 | AF25: -0.062615715 | AG25: 0 | AH25: -0.044617573 | AI25: -0.045122028
B26: 149905 | C26: (CARTERA DE CRÉDITOS PRODUCTIVO) | D26: -0.0042870144 | E26: -0.0034792789 | F26: -0.0090292933 | G26: -0.0060121072 | H26: -0.0064736378 | I26: -0.0028586491 | J26: -0.0048945514 | K26: -0.013096651 | L26: -0.0018907914 | M26: -0.0030526809 | N26: -0.014138784 | O26: -0.012730167 | P26: -0.0046050779 | Q26: -2.79295e-07 | R26: -0.0068398988 | S26: -0.0080385225 | T26: -0.0058440951 | U26: -0.0020630996 | V26: -0.0045709294 | W26: -0.0063763634 | X26: -6.7779598e-05 | Y26: -0.010679783 | Z26: -0.0014650553 | AA26: -0.0010328819 | AB26: 0 | AC26: -0.004845295 | AD26: -0.0065402883 | AE26: -0.014016404 | AF26: -0.0022556472 | AG26: 0 | AH26: -0.00062678923 | AI26: -0.0060894284
B27: 149910 | C27: (CARTERA DE CRÉDITOS DE CONSUMO) | D27: -0.0070656442 | E27: -0.010799912 | F27: -0.0084342896 | G27: -0.006735524 | H27: -0.0083269269 | I27: -0.011034676 | J27: -0.0065192353 | K27: 0 | L27: -0.024545754 | M27: -0.016816444 | N27: -0.0070784665 | O27: -0.013805228 | P27: -0.0055304974 | Q27: -0.022159249 | R27: -0.010887178 | S27: -0.00053510072 | T27: -0.0069986325 | U27: -0.0023544665 | V27: -0.031087034 | W27: -4.5692408e-05 | X27: -0.0096444148 | Y27: -0.0021956266 | Z27: -0.0011135034 | AA27: -0.015476065 | AB27: -0.00034792593 | AC27: -0.0049038452 | AD27: -0.0090304609 | AE27: -0.0062472218 | AF27: -0.022339142 | AG27: 0 | AH27: -0.00067546012 | AI27: -0.0083876523
B28: 149915 | C28: (CARTERA DE CRÉDITOS INMOBILIARIO) | D28: -0.00035796243 | E28: -0.0012483851 | F28: -0.0010792994 | G28: -0.00082303306 | H28: -0.00092642685 | I28: -0.00060947027 | J28: -0.000444712 | K28: 0 | L28: -4.99234e-07 | M28: -0.0011124769 | N28: -0.00056418147 | O28: -0.0016017725 | P28: -0.00067324092 | Q28: -5.0959e-08 | R28: -0.00050626554 | S28: -0.00044917377 | T28: -0.0001155914 | U28: 0 | V28: -2.3296e-08 | W28: -1.3473347e-05 | X28: 0 | Y28: -0.00038525341 | Z28: -1.0040154e-05 | AA28: -0.0010534399 | AB28: 0 | AC28: -0.00032460069 | AD28: -0.00077623094 | AE28: -0.00049792801 | AF28: -0.00032646544 | AG28: 0 | AH28: -4.295442e-06 | AI28: -0.00084207757
B29: 149920 | C29: (CARTERA DE CRÉDITOS PARA MICROCRÉDITO) | D29: -0.0016977219 | E29: -1.3931343e-05 | F29: -0.0050080175 | G29: -0.00011896071 | H29: -0.0025005579 | I29: -0.00036102165 | J29: -4.470183e-06 | K29: 0 | L29: -9.2846434e-05 | M29: -4.936694e-06 | N29: -1.5993916e-05 | O29: -0.006192526 | P29: -0.00067633653 | Q29: -0.038267191 | R29: -0.0015754753 | S29: -0.0043750614 | T29: -0.00016464977 | U29: -0.00060447413 | V29: -0.001837063 | W29: -0.00012938949 | X29: -0.0036878607 | Y29: -6.6279024e-05 | Z29: -0.01149694 | AA29: -0.023670452 | AB29: -0.048415639 | AC29: -0.0092250735 | AD29: -0.0024101901 | AE29: -1.4115704e-05 | AF29: -8.2860459e-05 | AG29: 0 | AH29: -0.032620847 | AI29: -0.0026989815
B30: 149940 | C30: (CARTERA DE CRÉDITOS DE VIVIENDA DE INTERÉS SOCIAL Y PÚBLICO) | D30: 0 | E30: -1.9149073e-05 | F30: -3.478909e-06 | G30: 0 | H30: -5.256303e-06 | I30: 0 | J30: 0 | K30: 0 | L30: 0 | M30: -0.00028613551 | N30: -2.067765e-06 | O30: 0 | P30: 0 | Q30: 0 | R30: -1.7012037e-05 | S30: 0 | T30: 0 | U30: 0 | V30: 0 | W30: 0 | X30: 0 | Y30: 0 | Z30: 0 | AA30: 0 | AB30: 0 | AC30: 0 | AD30: -8.798998e-06 | AE30: -1.824941e-06 | AF30: -8.3879148e-05 | AG30: 0 | AH30: 0 | AI30: -4.077494e-06
B31: 149945 | C31: (CARTERA DE CRÉDITO REFINANCIADA) | D31: -0.0017524699 | E31: -0.0007704982 | F31: -0.00055612089 | G31: -0.0022824714 | H31: -0.0011423028 | I31: -0.0020046971 | J31: -5.5832489e-05 | K31: 0 | L31: -0.0016770472 | M31: -0.0034484364 | N31: -0.00097702065 | O31: -0.004766685 | P31: -0.0044579603 | Q31: -0.0010833637 | R31: -0.0014315774 | S31: -0.0039944319 | T31: -0.0028432593 | U31: -0.00040403372 | V31: -0.013195951 | W31: -3.77142e-07 | X31: -0.00029366276 | Y31: -0.0019928419 | Z31: -0.0029741068 | AA31: -0.010328619 | AB31: -0.0020786412 | AC31: -0.0039120147 | AD31: -0.0013160307 | AE31: -0.0008622863 | AF31: -0.0023005613 | AG31: 0 | AH31: -0.002461745 | AI31: -0.0012868113
B32: 149950 | C32: (CARTERA DE CRÉDITO REESTRUCTURADA) | D32: -0.0024017124 | E32: -0.0071243319 | F32: -0.01032085 | G32: -0.0095649732 | H32: -0.0080213282 | I32: -0.0033162269 | J32: -0.0012262749 | K32: 0 | L32: -0.015838852 | M32: -0.0021762358 | N32: -0.0037747604 | O32: -0.0062571931 | P32: -0.0077143081 | Q32: -0.0021335764 | R32: -0.0047500227 | S32: -0.010491741 | T32: -0.0065421603 | U32: -0.00014588022 | V32: -0.0054977423 | W32: 0 | X32: -0.00023860415 | Y32: -0.0010178595 | Z32: -0.0041305487 | AA32: -0.0042583975 | AB32: -0.00056864696 | AC32: -0.0054818163 | AD32: -0.0069160039 | AE32: -0.0033314794 | AF32: -0.011740144 | AG32: 0 | AH32: -0.0020925223 | AI32: -0.0069635928
B33: 149955 | C33: (CARTERA DE CRÉDITO EDUCATIVO) | D33: -6.739335e-06 | E33: -0.00029445015 | F33: -3.5964875e-05 | G33: -3.065951e-06 | H33: -7.5168761e-05 | I33: 0 | J33: -1.0133378e-05 | K33: 0 | L33: 0 | M33: 0 | N33: 0 | O33: -4.474281e-06 | P33: -1.0662958e-05 | Q33: 0 | R33: -3.336725e-06 | S33: -2.170597e-06 | T33: 0 | U33: 0 | V33: 0 | W33: 0 | X33: 0 | Y33: 0 | Z33: 0 | AA33: 0 | AB33: 0 | AC33: -6.73701e-07 | AD33: -5.0338561e-05 | AE33: 0 | AF33: 0 | AG33: 0 | AH33: 0 | AI33: -5.9577607e-05
B34: 149960 | C34: (CARTERA DE CRÉDITO DE INVERSIÓN PÚBLICA) | D34: 0 | E34: 0 | F34: 0 | G34: 0 | H34: 0 | I34: 0 | J34: 0 | K34: 0 | L34: 0 | M34: 0 | N34: 0 | O34: 0 | P34: 0 | Q34: 0 | R34: 0 | S34: 0 | T34: 0 | U34: 0 | V34: 0 | W34: 0 | X34: 0 | Y34: 0 | Z34: 0 | AA34: 0 | AB34: 0 | AC34: 0 | AD34: 0 | AE34: 0 | AF34: 0 | AG34: 0 | AH34: 0 | AI34: 0
B35: 149980 | C35: PROVISIÓN GÉNERICA POR TECNOLOGÍA CREDITICIA | D35: 0 | E35: 0 | F35: 0 | G35: 0 | H35: 0 | I35: 0 | J35: 0 | K35: 0 | L35: 0 | M35: 0 | N35: 0 | O35: 0 | P35: 0 | Q35: 0 | R35: 0 | S35: 0 | T35: 0 | U35: 0 | V35: 0 | W35: 0 | X35: 0 | Y35: 0 | Z35: 0 | AA35: 0 | AB35: 0 | AC35: 0 | AD35: 0 | AE35: 0 | AF35: 0 | AG35: 0 | AH35: 0 | AI35: 0
B36: 149985 | C36: PROVISIÓN ANTICÍCLICA | D36: -0.00012687447 | E36: -0.00086486946 | F36: -0.0016530756 | G36: -0.0004440568 | H36: -0.00098373747 | I36: 0 | J36: -0.00037838663 | K36: 0 | L36: 0 | M36: -0.00072481073 | N36: 0 | O36: 0 | P36: -0.00024410589 | Q36: 0 | R36: -0.00015143836 | S36: 0 | T36: -9.0485744e-05 | U36: 0 | V36: -0.00060802229 | W36: 0 | X36: -0.00038603255 | Y36: -0.0025368083 | Z36: 0 | AA36: 0 | AB36: 0 | AC36: -8.3775844e-05 | AD36: -0.00069493753 | AE36: 0 | AF36: -0.00021797684 | AG36: 0 | AH36: 0 | AI36: -0.00080652037
... B44: 1 | C44: TOTAL ACTIVO | D44: 1 | E44: 1 | F44: 1 | G44: 1 | H44: 1 | I44: 1 | J44: 1 | K44: 1 | L44: 1 | M44: 1 | N44: 1 | O44: 1 | P44: 1 | Q44: 1 | R44: 1 | S44: 1 | T44: 1 | U44: 1 | V44: 1 | W44: 1 | X44: 1 | Y44: 1 | Z44: 1 | AA44: 1 | AB44: 1 | AC44: 1 | AD44: 1 | AE44: 1 | AF44: 1 | AG44: 0 | AH44: 1 | AI44: 1
C47: PASIVOS
B48: 21 | C48: OBLIGACIONES CON EL PÚBLICO | D48: 0.87511352 | E48: 0.89543017 | F48: 0.91339034 | G48: 0.86319362 | H48: 0.89318966 | I48: 0.92625558 | J48: 0.8470722 | K48: 0.93597795 | L48: 0.67672622 | M48: 0.90734644 | N48: 0.9040162 | O48: 0.90426383 | P48: 0.8888429 | Q48: 0.55621834 | R48: 0.85413314 | S48: 0.94073685 | T48: 0.921451 | U48: 0.96346712 | V48: 0.9431205 | W48: 0.97733854 | X48: 0.90526812 | Y48: 0.82577446 | Z48: 0.8757552 | AA48: 0.86530808 | AB48: 0.44658811 | AC48: 0.8911487 | AD48: 0.88093351 | AE48: 0.90759673 | AF48: 0.75119202 | AG48: 0 | AH48: 0.63817134 | AI48: 0.88805426
B49: 2101 | C49: Depósitos a la vista | D49: 0.47562687 | E49: 0.4005692 | F49: 0.61135167 | G49: 0.48866389 | H49: 0.52146128 | I49: 0.46379628 | J49: 0.45087773 | K49: 0.935856 | L49: 0.068591656 | M49: 0.34921073 | N49: 0.49139178 | O49: 0.49413113 | P49: 0.46024032 | Q49: 0.14489289 | R49: 0.41796985 | S49: 0.54181652 | T49: 0.32701107 | U49: 0.39530552 | V49: 0.53291781 | W49: 0.53884448 | X49: 0.064092995 | Y49: 0.33890401 | Z49: 0.22924964 | AA49: 0.43579039 | AB49: 0.10445454 | AC49: 0.4123883 | AD49: 0.48591495 | AE49: 0.54118314 | AF49: 0.16029298 | AG49: 0 | AH49: 0.16016396 | AI49: 0.50379803
B50: 2102 | C50: Operaciones de reporto | D50: 0 | E50: 0 | F50: 0 | G50: 0 | H50: 0 | I50: 0 | J50: 0 | K50: 0 | L50: 0 | M50: 0 | N50: 0 | O50: 0 | P50: 0 | Q50: 0 | R50: 0 | S50: 0 | T50: 0 | U50: 0 | V50: 0 | W50: 0 | X50: 0 | Y50: 0 | Z50: 0 | AA50: 0 | AB50: 0 | AC50: 0 | AD50: 0 | AE50: 0 | AF50: 0 | AG50: 0 | AH50: 0 | AI50: 0
B51: 2103 | C51: Depósitos a plazo | D51: 0.37393511 | E51: 0.43896749 | F51: 0.27144857 | G51: 0.34916152 | H51: 0.33818533 | I51: 0.43977009 | J51: 0.36068515 | K51: 8.612739e-06 | L51: 0.60393633 | M51: 0.5581254 | N51: 0.38208292 | O51: 0.41012833 | P51: 0.39921478 | Q51: 0.40278774 | R51: 0.41354422 | S51: 0.38113124 | T51: 0.56649162 | U51: 0.48117944 | V51: 0.40872698 | W51: 0.42901527 | X51: 0.83994988 | Y51: 0.45680032 | Z51: 0.64650556 | AA51: 0.42204783 | AB51: 0.34176396 | AC51: 0.46012687 | AD51: 0.36532817 | AE51: 0.33928083 | AF51: 0.58803659 | AG51: 0 | AH51: 0.47780277 | AI51: 0.35232979
B52: 2104 | C52: Depósitos de garantía | D52: 0 | E52: 0 | F52: 1.6930162e-05 | G52: 0 | H52: 7.229442e-06 | I52: 0.00011936405 | J52: 5.0282844e-05 | K52: 0 | L52: 0 | M52: 0 | N52: 1.2363164e-05 | O52: 0 | P52: 0 | Q52: 0 | R52: 3.3312809e-05 | S52: 0 | T52: 1.1095909e-05 | U52: 2.490629e-06 | V52: 3.2105111e-05 | W52: 0 | X52: 0 | Y52: 0 | Z52: 0 | AA52: 0 | AB52: 0 | AC52: 2.687589e-06 | AD52: 1.5239665e-05 | AE52: 1.0978174e-05 | AF52: 2.49923e-07 | AG52: 0 | AH52: 0 | AI52: 1.6782974e-05
B53: 2105 | C53: Depósitos restringidos | D53: 0.025551536 | E53: 0.055893482 | F53: 0.030573173 | G53: 0.02536822 | H53: 0.033535817 | I53: 0.022569851 | J53: 0.035459036 | K53: 0.00011334075 | L53: 0.0041982374 | M53: 1.030979e-05 | N53: 0.030529139 | O53: 4.37245e-06 | P53: 0.029387802 | Q53: 0.0085377063 | R53: 0.022585748 | S53: 0.017789089 | T53: 0.027937207 | U53: 0.086979665 | V53: 0.0014436111 | W53: 0.0094787917 | X53: 0.0012252434 | Y53: 0.030070136 | Z53: 0 | AA53: 0.0074698632 | AB53: 0.00036961396 | AC53: 0.01863084 | AD53: 0.029675144 | AE53: 0.027121792 | AF53: 0.002862197 | AG53: 0 | AH53: 0.00020461567 | AI53: 0.031909665
B54: 22 | C54: OPERACIONES INTERBANCARIAS | D54: 0 | E54: 0 | F54: 0 | G54: 0 | H54: 0 | I54: 0 | J54: 0 | K54: 0 | L54: 0 | M54: 0 | N54: 0 | O54: 0 | P54: 0 | Q54: 0 | R54: 0 | S54: 0 | T54: 0 | U54: 0 | V54: 0 | W54: 0 | X54: 0 | Y54: 0 | Z54: 0 | AA54: 0 | AB54: 0 | AC54: 0 | AD54: 0 | AE54: 0 | AF54: 0 | AG54: 0 | AH54: 0 | AI54: 0
B55: 23 | C55: OBLIGACIONES INMEDIATAS | D55: 0.0006191648 | E55: 0.0027768379 | F55: 0.00085621764 | G55: 0.0010865168 | H55: 0.0012244129 | I55: 0.0014965411 | J55: 0.0022469422 | K55: 7.8310787e-05 | L55: 0 | M55: 0.0011266092 | N55: 0.0020557397 | O55: 0.0011181138 | P55: 0.00025493245 | Q55: 0 | R55: 0.0014516438 | S55: 2.0410604e-05 | T55: 0.0017853228 | U55: 2.7479937e-05 | V55: 0.0017759629 | W55: 0.0024166412 | X55: 0.012235199 | Y55: 0.047608511 | Z55: 5.8696863e-05 | AA55: 0.00058255193 | AB55: 0 | AC55: 0.0017175574 | AD55: 0.0013099726 | AE55: 0.0018342172 | AF55: 0.00036746942 | AG55: 0 | AH55: 2.6202695e-05 | AI55: 0.001324715
B56: 24 | C56: ACEPTACIONES EN CIRCULACIÓN | D56: 0 | E56: 3.7977224e-05 | F56: 5.6246915e-05 | G56: 0 | H56: 3.1370225e-05 | I56: 0 | J56: 0.01055424 | K56: 0 | L56: 0 | M56: 0 | N56: 0 | O56: 0 | P56: 0 | Q56: 0 | R56: 0.0027400593 | S56: 0 | T56: 0 | U56: 0 | V56: 0 | W56: 0 | X56: 0 | Y56: 0 | Z56: 0 | AA56: 0 | AB56: 0 | AC56: 0 | AD56: 0.00087625052 | AE56: 0 | AF56: 0 | AG56: 0 | AH56: 0 | AI56: 0.0010326619
B57: 25 | C57: CUENTAS POR PAGAR | D57: 0.032041686 | E57: 0.036227409 | F57: 0.026367201 | G57: 0.027343883 | H57: 0.02956117 | I57: 0.022720277 | J57: 0.027733977 | K57: 0.06208691 | L57: 0.2382468 | M57: 0.030157448 | N57: 0.035868712 | O57: 0.019890366 | P57: 0.019968645 | Q57: 0.052593561 | R57: 0.056896647 | S57: 0.021744991 | T57: 0.028412156 | U57: 0.017609136 | V57: 0.049408141 | W57: 0.019993849 | X57: 0.075106095 | Y57: 0.12092504 | Z57: 0.016685505 | AA57: 0.034918958 | AB57: 0.043634374 | AC57: 0.029163309 | AD57: 0.038085104 | AE57: 0.03880582 | AF57: 0.17145721 | AG57: 0 | AH57: 0.031604208 | AI57: 0.028894204
B58: 26 | C58: OBLIGACIONES FINANCIERAS | D58: 0.080572863 | E58: 0.058994089 | F58: 0.040670443 | G58: 0.078234539 | H58: 0.058924618 | I58: 0.044700245 | J58: 0.065817187 | K58: 0 | L58: 0.058337616 | M58: 0.041430271 | N58: 0.054414138 | O58: 0.065879187 | P58: 0.070940564 | Q58: 0.37256139 | R58: 0.064479534 | S58: 0.019541613 | T58: 0.027065386 | U58: 0 | V58: 0 | W58: 0 | X58: 0 | Y58: 0 | Z58: 0.10708989 | AA58: 0.093981388 | AB58: 0.5088554 | AC58: 0.065782155 | AD58: 0.060862278 | AE58: 0.048318363 | AF58: 0.052576243 | AG58: 0 | AH58: 0.32950443 | AI58: 0.061600271
B59: 2601 | C59: Sobregiros | D59: 0 | E59: 0 | F59: 1.584676e-06 | G59: 3.811836e-06 | H59: 1.380761e-06 | I59: 0 | J59: 0 | K59: 0 | L59: 0 | M59: 0 | N59: 0 | O59: 0 | P59: 0 | Q59: 0 | R59: 0 | S59: 0 | T59: 0 | U59: 0 | V59: 0 | W59: 0 | X59: 0 | Y59: 0 | Z59: 0 | AA59: 0 | AB59: 0 | AC59: 0 | AD59: 9.08715e-07 | AE59: 0 | AF59: 0 | AG59: 0 | AH59: 0 | AI59: 1.070921e-06
... B73: 2 | C73: TOTAL PASIVOS | D73: 1 | E73: 1 | F73: 1 | G73: 1 | H73: 1 | I73: 1 | J73: 1 | K73: 1 | L73: 1 | M73: 1 | N73: 1 | O73: 1 | P73: 1 | Q73: 1 | R73: 1 | S73: 1 | T73: 1 | U73: 1 | V73: 1 | W73: 1 | X73: 1 | Y73: 1 | Z73: 1 | AA73: 1 | AB73: 1 | AC73: 1 | AD73: 1 | AE73: 1 | AF73: 1 | AG73: 0 | AH73: 1 | AI73: 1
C75: PATRIMONIO
B76: 31 | C76: CAPITAL SOCIAL | D76: 0.70163759 | E76: 0.58028112 | F76: 0.65894999 | G76: 0.75566099 | H76: 0.66334306 | I76: 0.69690682 | J76: 0.73127569 | K76: 0.66715924 | L76: 0.67117752 | M76: 0.75687959 | N76: 0.72160782 | O76: 0.6854067 | P76: 0.77474339 | Q76: 0.74699134 | R76: 0.71130142 | S76: 1.1767544 | T76: 0.85608942 | U76: 0.86359427 | V76: 0.95176185 | W76: 0.71693833 | X76: 1.5222256 | Y76: 0.98878633 | Z76: 1.2468024 | AA76: 0.73525693 | AB76: 0.76028343 | AC76: 0.9232048 | AD76: 0.68776568 | AE76: 0.71257066 | AF76: 0.69116414 | AG76: 0 | AH76: 0.9100547 | AI76: 0.68335681
B77: 32 | C77: PRIMA O DESCUENTO EN COLOCACIÓN DE ACCIONES Y CERTIFICADOS | D77: 0 | E77: 0 | F77: 0 | G77: 0.0015241999 | H77: 0.00022229032 | I77: 0 | J77: 0 | K77: 0 | L77: 0 | M77: 0 | N77: 0 | O77: 0 | P77: 0 | Q77: 0 | R77: 0 | S77: 0 | T77: 0 | U77: 0 | V77: 0 | W77: 0 | X77: 0 | Y77: 0 | Z77: 0 | AA77: 0 | AB77: 0 | AC77: 0 | AD77: 0.00014046835 | AE77: 0 | AF77: 0 | AG77: 0 | AH77: 0 | AI77: 0.0001727063
B78: 33 | C78: RESERVAS | D78: 0.12529935 | E78: 0.16909128 | F78: 0.11343324 | G78: 0.11286179 | H78: 0.12801503 | I78: 0.11226493 | J78: 0.11635104 | K78: 0.13388651 | L78: 0.21656367 | M78: 0.11220245 | N78: 0.12593258 | O78: 0.13831874 | P78: 0.07078619 | Q78: 0.16264407 | R78: 0.14287067 | S78: 0.035654388 | T78: 0.039391655 | U78: 0.070713462 | V78: 0.037717786 | W78: 0.22871842 | X78: 0 | Y78: 0.009641667 | Z78: 0 | AA78: 0.090792031 | AB78: 0.066771585 | AC78: 0.073012484 | AD78: 0.13125138 | AE78: 0.12725274 | AF78: 0.19480931 | AG78: 0 | AH78: 0.046216446 | AI78: 0.12482221
B79: 34 | C79: OTROS APORTES PATRIMONIALES | D79: 0 | E79: 0 | F79: 0 | G79: 0 | H79: 0 | I79: 0 | J79: 0 | K79: 0 | L79: 0 | M79: 0 | N79: 0 | O79: 0 | P79: 0 | Q79: 0.00010480415 | R79: 5.896465e-06 | S79: 0 | T79: 0 | U79: 0 | V79: 0 | W79: 9.1386415e-05 | X79: 0 | Y79: 0 | Z79: 0 | AA79: 0.039480626 | AB79: 0.0053554254 | AC79: 0.0066953775 | AD79: 0.00021588381 | AE79: 0 | AF79: 0 | AG79: 0 | AH79: 0.0037067972 | AI79: 0.00024290427
B80: 35 | C80: SUPERÁVIT POR VALUACIONES | D80: 0.0072820684 | E80: 0.058720351 | F80: 0.073206197 | G80: 0.011971094 | H80: 0.048816391 | I80: 0.10391354 | J80: 0.035460352 | K80: 0.0093593665 | L80: 0.03967697 | M80: 0.01504258 | N80: 0.032334761 | O80: 0.036286489 | P80: 0.073980444 | Q80: 0.053207792 | R80: 0.043363239 | S80: 0 | T80: 0.071797957 | U80: 0.063714533 | V80: 0.014996067 | W80: 0.040854067 | X80: 0.00057655834 | Y80: 0.00072815322 | Z80: -0.11438696 | AA80: 0.055485799 | AB80: 0 | AC80: 0.026005045 | AD80: 0.046254608 | AE80: 0.028521394 | AF80: 0.034820126 | AG80: 0 | AH80: -0.035213181 | AI80: 0.049980833
B81: 36 | C81: RESULTADOS | D81: 0.16578099 | E81: 0.19190726 | F81: 0.15441057 | G81: 0.11798192 | H81: 0.15960322 | I81: 0.086914718 | J81: 0.11691291 | K81: 0.18959488 | L81: 0.072581845 | M81: 0.11587538 | N81: 0.12012484 | O81: 0.13998807 | P81: 0.080489974 | Q81: 0.037051992 | R81: 0.10245878 | S81: -0.21240877 | T81: 0.032720969 | U81: 0.0019777394 | V81: -0.0044757022 | W81: 0.013397793 | X81: -0.52280211 | Y81: 0.0008438541 | Z81: -0.13241544 | AA81: 0.078984614 | AB81: 0.16758956 | AC81: -0.028917707 | AD81: 0.13437198 | AE81: 0.13165521 | AF81: 0.079206422 | AG81: 0 | AH81: 0.075235238 | AI81: 0.14142453
B82: 3601 | C82: Utilidades o excedentes acumulados | D82: 0 | E82: 0.0067362226 | F82: 0.045641818 | G82: 0.0003350292 | H82: 0.021863329 | I82: 0.0048289674 | J82: 0.00078139606 | K82: 0 | L82: 0.00034919769 | M82: 0.0027041003 | N82: 0.0011846087 | O82: 0.022276552 | P82: 0.0013088423 | Q82: 0.017980572 | R82: 0.0029899839 | S82: 0 | T82: 0 | U82: 0.00072867105 | V82: 0 | W82: 0 | X82: 0 | Y82: 0 | Z82: 0 | AA82: 0.027353196 | AB82: 0 | AC82: 0.0042856122 | AD82: 0.014957706 | AE82: 0.00098799192 | AF82: 0.00077050365 | AG82: 0 | AH82: 0 | AI82: 0.018195043
B83: 3602 | C83: (Pérdidas acumuladas) | D83: 0 | E83: 0 | F83: 0 | G83: 0 | H83: 0 | I83: 0 | J83: 0 | K83: 0 | L83: 0 | M83: 0 | N83: 0 | O83: 0 | P83: 0 | Q83: 0 | R83: 0 | S83: 0 | T83: 0 | U83: 0 | V83: -0.020032982 | W83: 0 | X83: -0.51418778 | Y83: 0 | Z83: -0.13371107 | AA83: 0 | AB83: 0 | AC83: -0.028883741 | AD83: -0.00092276854 | AE83: 0 | AF83: -0.00031788687 | AG83: 0 | AH83: -0.041161965 | AI83: -0.00084752483
B84: 3603 | C84: Utilidad o excedente del ejercicio | D84: 0.16578099 | E84: 0.18517104 | F84: 0.10876876 | G84: 0.11764689 | H84: 0.1377399 | I84: 0.08208575 | J84: 0.11613152 | K84: 0.18959488 | L84: 0.072232647 | M84: 0.11317128 | N84: 0.11894023 | O84: 0.11771151 | P84: 0.079181132 | Q84: 0.01907142 | R84: 0.099468792 | S84: 0 | T84: 0.032720969 | U84: 0.0012490683 | V84: 0.01555728 | W84: 0.013397793 | X84: 0 | Y84: 0.0008438541 | Z84: 0.0012956291 | AA84: 0.051631418 | AB84: 0.16758956 | AC84: 0.034100782 | AD84: 0.12156448 | AE84: 0.13066721 | AF84: 0.078753805 | AG84: 0 | AH84: 0.1163972 | AI84: 0.12558616
B85: 3604 | C85: (Pérdida del ejercicio) | D85: 0 | E85: 0 | F85: 0 | G85: 0 | H85: 0 | I85: 0 | J85: 0 | K85: 0 | L85: 0 | M85: 0 | N85: 0 | O85: 0 | P85: 0 | Q85: 0 | R85: 0 | S85: -0.21240877 | T85: 0 | U85: 0 | V85: 0 | W85: 0 | X85: -0.0086143361 | Y85: 0 | Z85: 0 | AA85: 0 | AB85: 0 | AC85: -0.03842036 | AD85: -0.0012274414 | AE85: 0 | AF85: 0 | AG85: 0 | AH85: 0 | AI85: -0.0015091432
B86: 37 | C86: (DESVALORIZACIÓN DEL PATRIMONIO) | D86: 0 | E86: 0 | F86: 0 | G86: 0 | H86: 0 | I86: 0 | J86: 0 | K86: 0 | L86: 0 | M86: 0 | N86: 0 | O86: 0 | P86: 0 | Q86: 0 | R86: 0 | S86: 0 | T86: 0 | U86: 0 | V86: 0 | W86: 0 | X86: 0 | Y86: 0 | Z86: 0 | AA86: 0 | AB86: 0 | AC86: 0 | AD86: 0 | AE86: 0 | AF86: 0 | AG86: 0 | AH86: 0 | AI86: 0
B87: 3 | C87: TOTAL PATRIMONIO | D87: 1 | E87: 1 | F87: 1 | G87: 1 | H87: 1 | I87: 1 | J87: 1 | K87: 1 | L87: 1 | M87: 1 | N87: 1 | O87: 1 | P87: 1 | Q87: 1 | R87: 1 | S87: 1 | T87: 1 | U87: 1 | V87: 1 | W87: 1 | X87: 1 | Y87: 1 | Z87: 1 | AA87: 1 | AB87: 1 | AC87: 1 | AD87: 1 | AE87: 1 | AF87: 1 | AG87: 0 | AH87: 1 | AI87: 1

Sheet EPyG %
B3: ESTADO DE PÉRDIDAS Y GANANCIAS
B4: SISTEMA DE BANCOS PRIVADOS
B5: 31/12/2025
B6: (en porcentajes)
B8: CÓDIGO | C8: CUENTA | D8: BP GUAYAQUIL | E8: BP PACIFICO | F8: BP PICHINCHA | G8: BP PRODUBANCO | H8: BANCOS PRIVADOS GRANDES | I8: BP AUSTRO | J8: BP BOLIVARIANO | K8: BP CITIBANK | L8: BP DINERS | M8: BP GENERAL RUMIÑAHUI | N8: BP INTERNACIONAL | O8: BP LOJA | P8: BP MACHALA | Q8: BP SOLIDARIO | R8: BANCOS PRIVADOS MEDIANOS | S8: BP PROCREDIT | T8: BP AMAZONAS | U8: BP BANCO COMERCIAL DE MANABI | V8: BP LITORAL | W8: BP COOPNACIONAL | X8: BP CAPITAL | Y8: BP DELBANK | Z8: BANCO ATLÁNTIDA S.A. | AA8: BP BANCO DESARROLLO DE LOS PUEBLOS S.A., CODESARROLLO | AB8: BP VISIONFUND ECUADOR S.A. | AC8: BANCOS PRIVADOS PEQUEÑOS | AD8: TOTAL BANCOS PRIVADOS | AE8: BANCOS PRIVADOS COMERCIALES | AF8: BANCOS PRIVADOS CONSUMO | AG8: BANCOS PRIVADOS VIVIENDA | AH8: BANCOS PRIVADOS MICROCRÉDITO | AI8: BANCA MÚLTIPLE
C9: TOTAL INGRESOS | D9: 1 | E9: 1 | F9: 1 | G9: 1 | H9: 1 | I9: 1 | J9: 1 | K9: 1 | L9: 1 | M9: 1 | N9: 1 | O9: 1 | P9: 1 | Q9: 1 | R9: 1 | S9: 1 | T9: 1 | U9: 1 | V9: 1 | W9: 1 | X9: 1 | Y9: 1 | Z9: 1 | AA9: 1 | AB9: 1 | AC9: 1 | AD9: 1 | AE9: 1 | AF9: 1 | AG9: 0 | AH9: 1 | AI9: 1
B11: 51 | C11: INTERESES Y DESCUENTOS GANADOS | D11: 0.71070359 | E11: 0.64479734 | F11: 0.7026344 | G11: 0.7075919 | H11: 0.69366585 | I11: 0.74424268 | J11: 0.75971287 | K11: 0.62855335 | L11: 0.47721557 | M11: 0.79181087 | N11: 0.79731198 | O11: 0.87527814 | P11: 0.87766616 | Q11: 0.7462736 | R11: 0.70803644 | S11: 0.932897 | T11: 0.72968831 | U11: 0.78428963 | V11: 0.85292343 | W11: 0.88076798 | X11: 0.56970648 | Y11: 0.59674695 | Z11: 0.58331579 | AA11: 0.80972902 | AB11: 0.86679468 | AC11: 0.80660155 | AD11: 0.70125271 | AE11: 0.77798041 | AF11: 0.54729811 | AG11: 0 | AH11: 0.76498803 | AI11: 0.71094633
B12: 5101 | C12: Depósitos | D12: 0.0019188715 | E12: 0.0013744504 | F12: 0.011537341 | G12: 0.011899366 | H12: 0.0077314022 | I12: 0.016009059 | J12: 0.0098758106 | K12: 0.034767379 | L12: 0.0008703098 | M12: 0.025434954 | N12: 0.013473075 | O12: 0.019372646 | P12: 0.029319986 | Q12: 0.0011834937 | R12: 0.011690498 | S12: 0.0095463784 | T12: 0.01639612 | U12: 0.012743609 | V12: 3.55318e-05 | W12: 0.16962599 | X12: 0.0007034072 | Y12: 0.0078838887 | Z12: 0.012861825 | AA12: 0.0036227633 | AB12: 0.003537664 | AC12: 0.017298417 | AD12: 0.0091955487 | AE12: 0.015912371 | AF12: 0.0061327001 | AG12: 0 | AH12: 0.0068862786 | AI12: 0.009001151
B13: 5102 | C13: Operaciones interbancarias | D13: 0 | E13: 0 | F13: 5.4617e-06 | G13: 2.1603e-06 | H13: 2.8028e-06 | I13: 0 | J13: 1.21731e-05 | K13: 6.45386e-05 | L13: 0 | M13: 0 | N13: 3.44984e-05 | O13: 0 | P13: 0 | Q13: 0 | R13: 1.09504e-05 | S13: 0 | T13: 0 | U13: 0 | V13: 0 | W13: 0 | X13: 0 | Y13: 0 | Z13: 0 | AA13: 0 | AB13: 0 | AC13: 0 | AD13: 5.1625e-06 | AE13: 3.79396e-05 | AF13: 0 | AG13: 0 | AH13: 0 | AI13: 3.138e-06
B14: 5103 | C14: INTERESES y descuentos de inversiones en títulos valores | D14: 0.07937498 | E14: 0.049701191 | F14: 0.049940411 | G14: 0.031057836 | H14: 0.052618889 | I14: 0.061771521 | J14: 0.038893267 | K14: 0.19151386 | L14: 0.01880029 | M14: 0.034481336 | N14: 0.051713743 | O14: 0.040818503 | P14: 0.061902647 | Q14: 0.019515894 | R14: 0.043396698 | S14: 0.062901405 | T14: 0.061563918 | U14: 0.15331141 | V14: 0.029717672 | W14: 0.49005431 | X14: 0.028142781 | Y14: 0.033329734 | Z14: 0.19104599 | AA14: 0.046332098 | AB14: 0.0022197694 | AC14: 0.085855983 | AD14: 0.050821526 | AE14: 0.067728068 | AF14: 0.022239234 | AG14: 0 | AH14: 0.070033511 | AI14: 0.052357146
B15: 5104 | C15: INTERESES Y DESCUENTOS DE CARTERA DE CRÉDITOS | D15: 0.62940974 | E15: 0.59369312 | F15: 0.64059175 | G15: 0.66350891 | H15: 0.63287642 | I15: 0.66439584 | J15: 0.70997278 | K15: 0.37541881 | L15: 0.45554231 | M15: 0.73189458 | N15: 0.73149694 | O15: 0.81508699 | P15: 0.78644352 | Q15: 0.72557421 | R15: 0.65120587 | S15: 0.86044921 | T15: 0.61800928 | U15: 0.61518854 | V15: 0.82317022 | W15: 0.22108769 | X15: 0.52646323 | Y15: 0.55553333 | Z15: 0.37940798 | AA15: 0.75977416 | AB15: 0.86103724 | AC15: 0.69646764 | AD15: 0.6402157 | AE15: 0.69070763 | AF15: 0.51736694 | AG15: 0 | AH15: 0.68806824 | AI15: 0.64882546
B16: 5190 | C16: Otros INTERESES y descuentos | D16: 0 | E16: 2.85792e-05 | F16: 0.0005594385 | G16: 0.0011236266 | H16: 0.0004363408 | I16: 0.0020662661 | J16: 0.00095884 | K16: 0.026788759 | L16: 0.0020026603 | M16: 0 | N16: 0.0005937237 | O16: 0 | P16: 0 | Q16: 0 | R16: 0.0017324296 | S16: 0 | T16: 0.033718989 | U16: 0.0030460797 | V16: 0 | W16: 0 | X16: 0.014397064 | Y16: 0 | Z16: 0 | AA16: 0 | AB16: 0 | AC16: 0.0069795029 | AD16: 0.0010147694 | AE16: 0.0035944065 | AF16: 0.001559233 | AG16: 0 | AH16: 0 | AI16: 0.000759428
B17: 41 | C17: INTERESES CAUSADOS | D17: 0.28941415 | E17: 0.29087748 | F17: 0.23402804 | G17: 0.3114274 | H17: 0.26827021 | I17: 0.35939453 | J17: 0.37213398 | K17: 0.0083977304 | L17: 0.20829585 | M17: 0.35059242 | N17: 0.39494912 | O17: 0.32300579 | P17: 0.37040351 | Q17: 0.2530094 | R17: 0.31741157 | S17: 0.61815895 | T17: 0.45593405 | U17: 0.3631649 | V17: 0.18187765 | W17: 0.31076968 | X17: 0.37600715 | Y17: 0.24683462 | Z17: 0.35599548 | AA17: 0.33096497 | AB17: 0.2521131 | AC17: 0.41835621 | AD17: 0.28735409 | AE17: 0.35066904 | AF17: 0.23862936 | AG17: 0 | AH17: 0.2894207 | AI17: 0.28744741
B18: 4101 | C18: Obligaciones con el público | D18: 0.22479428 | E18: 0.26078475 | F18: 0.19700499 | G18: 0.2284161 | H18: 0.21990974 | I18: 0.32510733 | J18: 0.29195158 | K18: 0.008231408 | L18: 0.18597295 | M18: 0.30960707 | N18: 0.34893609 | O18: 0.27481947 | P18: 0.3060423 | Q18: 0.12163263 | R18: 0.26689386 | S18: 0.54201098 | T18: 0.42964771 | U18: 0.3631649 | V18: 0.16975089 | W18: 0.31076968 | X18: 0.37581772 | Y18: 0.24683462 | Z18: 0.31813738 | AA18: 0.27464251 | AB18: 0.10077611 | AC18: 0.36168386 | AD18: 0.2381058 | AE18: 0.30990783 | AF18: 0.212375 | AG18: 0 | AH18: 0.17883773 | AI18: 0.23553354
B19: 4102 | C19: Operaciones interbancarias | D19: 0 | E19: 0 | F19: 7.7147e-06 | G19: 0 | H19: 3.4732e-06 | I19: 0 | J19: 6.9634e-06 | K19: 0.0001663224 | L19: 0 | M19: 0 | N19: 1.78552e-05 | O19: 0 | P19: 0 | Q19: 4.2954e-06 | R19: 9.448e-06 | S19: 0 | T19: 0 | U19: 0 | V19: 0 | W19: 0 | X19: 0 | Y19: 0 | Z19: 0 | AA19: 0 | AB19: 0 | AC19: 0 | AD19: 5.1624e-06 | AE19: 3.48623e-05 | AF19: 0 | AG19: 0 | AH19: 0 | AI19: 3.3826e-06
B20: 4103 | C20: Obligaciones financieras | D20: 0.059320517 | E20: 0.030092733 | F20: 0.035338109 | G20: 0.080630779 | H20: 0.04619104 | I20: 0.032591496 | J20: 0.067913601 | K20: 0 | L20: 0.022322897 | M20: 0.029326217 | N20: 0.040519783 | O20: 0.048186324 | P20: 0.047629437 | Q20: 0.12324167 | R20: 0.044719035 | S20: 0.076147968 | T20: 0.014404893 | U20: 0 | V20: 0.01212677 | W20: 0 | X20: 0 | Y20: 0 | Z20: 0.037858104 | AA20: 0.056322464 | AB20: 0.15133699 | AC20: 0.054477825 | AD20: 0.045990783 | AE20: 0.035878177 | AF20: 0.023753918 | AG20: 0 | AH20: 0.11058297 | AI20: 0.048682567
B21: 4104 | C21: Valores en circulación y obligaciones convertibles en acciones | D21: 0.0052993574 | E21: 0 | F21: 0.0016742262 | G21: 0.0023805227 | H21: 0.0021646023 | I21: 0.0016956969 | J21: 0.012261828 | K21: 0 | L21: 0 | M21: 0.011659131 | N21: 0.0054753893 | O21: 0 | P21: 0.016731767 | Q21: 0.0081308093 | R21: 0.0057892235 | S21: 0 | T21: 0.011865564 | U21: 0 | V21: 0 | W21: 0 | X21: 0 | Y21: 0 | Z21: 0 | AA21: 0 | AB21: 0 | AC21: 0.0021834976 | AD21: 0.0032511206 | AE21: 0.0048481748 | AF21: 0.0025004475 | AG21: 0 | AH21: 0 | AI21: 0.0032264593
B22: 4105 | C22: Otros INTERESES | D22: 0 | E22: 0 | F22: 2.9987e-06 | G22: 0 | H22: 1.35e-06 | I22: 0 | J22: 0 | K22: 0 | L22: 0 | M22: 0 | N22: 0 | O22: 0 | P22: 0 | Q22: 0 | R22: 0 | S22: 0 | T22: 1.58839e-05 | U22: 0 | V22: 0 | W22: 0 | X22: 0.0001894235 | Y22: 0 | Z22: 0 | AA22: 0 | AB22: 0 | AC22: 1.10253e-05 | AD22: 1.2267e-06 | AE22: 0 | AF22: 0 | AG22: 0 | AH22: 0 | AI22: 1.4623e-06
C23: MARGEN NETO INTERESES | D23: 0.42128944 | E23: 0.35391986 | F23: 0.46860636 | G23: 0.3961645 | H23: 0.42539564 | I23: 0.38484816 | J23: 0.38757889 | K23: 0.62015562 | L23: 0.26891972 | M23: 0.44121846 | N23: 0.40236287 | O23: 0.55227234 | P23: 0.50726265 | Q23: 0.4932642 | R23: 0.39062487 | S23: 0.31473805 | T23: 0.27375426 | U23: 0.42112473 | V23: 0.67104577 | W23: 0.5699983 | X23: 0.19369934 | Y23: 0.34991234 | Z23: 0.22732031 | AA23: 0.47876405 | AB23: 0.61468158 | AC23: 0.38824534 | AD23: 0.41389862 | AE23: 0.42731137 | AF23: 0.30866874 | AG23: 0 | AH23: 0.47556733 | AI23: 0.42349892
B25: 52 | C25: COMISIONES GANADAS | D25: 0.086068221 | E25: 0.049389835 | F25: 0.025845201 | G25: 0.036687309 | H25: 0.043909632 | I25: 0.049621129 | J25: 0.077604604 | K25: 0.051839309 | L25: 0.12076689 | M25: 0.038730755 | N25: 0.063839132 | O25: 0.010385101 | P25: 0.014196025 | Q25: 0.022639743 | R25: 0.069104268 | S25: 0.002699417 | T25: 0.0090911296 | U25: 0.018225905 | V25: 0 | W25: 0 | X25: 0 | Y25: 0.0063839539 | Z25: 0 | AA25: 0.0055332511 | AB25: 0 | AC25: 0.0043443368 | AD25: 0.050308621 | AE25: 0.062464533 | AF25: 0.10233309 | AG25: 0 | AH25: 0 | AI25: 0.044209479
B26: 5201 | C26: Cartera de créditos | D26: 8.47531e-05 | E26: 0 | F26: 0 | G26: 0 | H26: 1.65029e-05 | I26: 0 | J26: 0 | K26: 0 | L26: 0 | M26: 8.4e-09 | N26: 0 | O26: 0 | P26: 0 | Q26: 0 | R26: 5e-10 | S26: 0 | T26: 0 | U26: 0 | V26: 0 | W26: 0 | X26: 0 | Y26: 0 | Z26: 0 | AA26: 0 | AB26: 0 | AC26: 0 | AD26: 1.10792e-05 | AE26: 0 | AF26: 1.8e-09 | AG26: 0 | AH26: 0 | AI26: 1.32077e-05
B27: 5202 | C27: Deudores por aceptación | D27: 0 | E27: 0 | F27: 0 | G27: 0 | H27: 0 | I27: 0 | J27: 0.000711995 | K27: 7.2542e-06 | L27: 0 | M27: 0 | N27: 0 | O27: 0 | P27: 0 | Q27: 0 | R27: 0.000146721 | S27: 0 | T27: 0 | U27: 0 | V27: 0 | W27: 0 | X27: 0 | Y27: 0 | Z27: 0 | AA27: 0 | AB27: 0 | AC27: 0 | AD27: 4.39589e-05 | AE27: 8.31e-07 | AF27: 0 | AG27: 0 | AH27: 0 | AI27: 5.2339e-05
B28: 5203 | C28: Avales | D28: 0 | E28: 0.0001274864 | F28: 0.0001300323 | G28: 0.000219327 | H28: 0.0001184297 | I28: 0.0002040492 | J28: 0.0029553934 | K28: 0 | L28: 0 | M28: 0.0001415786 | N28: 0.0014041693 | O28: 0.0010706323 | P28: 0.000219525 | Q28: 0 | R28: 0.0009756161 | S28: 0 | T28: 0 | U28: 0.017354386 | V28: 0 | W28: 0 | X28: 0 | Y28: 0 | Z28: 0 | AA28: 0 | AB28: 0 | AC28: 0.0009043294 | AD28: 0.0003980845 | AE28: 0.0012433195 | AF28: 3.03633e-05 | AG28: 0 | AH28: 0 | AI28: 0.0003725171
B29: 5204 | C29: Fianzas | D29: 0.0046303467 | E29: 0.0035630036 | F29: 0.0019439653 | G29: 0.0043577955 | H29: 0.0031684666 | I29: 0.0012095518 | J29: 0.0081498046 | K29: 0.047808677 | L29: 2.09956e-05 | M29: 0.0014950657 | N29: 0.01103607 | O29: 0 | P29: 0.0039264115 | Q29: 1.68918e-05 | R29: 0.0055063795 | S29: 0.0014580188 | T29: 0.0017858076 | U29: 0.0008715187 | V29: 0 | W29: 0 | X29: 0 | Y29: 0 | Z29: 0 | AA29: 0.0005089349 | AB29: 0 | AC29: 0.0008371023 | AD29: 0.0038011897 | AE29: 0.01524843 | AF29: 0.0003369824 | AG29: 0 | AH29: 0 | AI29: 0.0032836539
B30: 5205 | C30: Cartas de Crédito | D30: 0.0021462563 | E30: 0.0008173937 | F30: 0.0029476016 | G30: 0.0018415239 | H30: 0.0021982175 | I30: 0.0006887674 | J30: 0.0051074692 | K30: 2.69785e-05 | L30: 0 | M30: 0 | N30: 0.0082606478 | O30: 0 | P30: 0.0003450241 | Q30: 0 | R30: 0.002786697 | S30: 0.0012238296 | T30: 0 | U30: 0 | V30: 0 | W30: 0 | X30: 0 | Y30: 0 | Z30: 0 | AA30: 0 | AB30: 0 | AC30: 0.0003210881 | AD30: 0.0023199921 | AE30: 0.0073174679 | AF30: 0 | AG30: 0 | AH30: 0 | AI30: 0.0021839743
B31: 5290 | C31: Otras | D31: 0.079206865 | E31: 0.044881951 | F31: 0.020823602 | G31: 0.030268663 | H31: 0.038408015 | I31: 0.047518761 | J31: 0.060679942 | K31: 0.0039963991 | L31: 0.12074589 | M31: 0.037094102 | N31: 0.043138245 | O31: 0.0093144686 | P31: 0.0097050646 | Q31: 0.022622851 | R31: 0.059688854 | S31: 1.75686e-05 | T31: 0.007305322 | U31: 0 | V31: 0 | W31: 0 | X31: 0 | Y31: 0.0063839539 | Z31: 0 | AA31: 0.0050243162 | AB31: 0 | AC31: 0.002281817 | AD31: 0.043734316 | AE31: 0.038654484 | AF31: 0.10196574 | AG31: 0 | AH31: 0 | AI31: 0.038303787
B32: 54 | C32: INGRESOS POR SERVICIOS | D32: 0.15473287 | E32: 0.13029413 | F32: 0.10941081 | G32: 0.12347932 | H32: 0.12456611 | I32: 0.10189687 | J32: 0.095295949 | K32: 0.032123756 | L32: 0.24375796 | M32: 0.059340973 | N32: 0.083781717 | O32: 0.056404291 | P32: 0.066924427 | Q32: 0.12842526 | R32: 0.12324623 | S32: 0.025129919 | T32: 0.058748901 | U32: 0.15494698 | V32: 0.040336511 | W32: 0.060858774 | X32: 0.012500659 | Y32: 0.28907018 | Z32: 0.0071283676 | AA32: 0.019285103 | AB32: 0.019193773 | AC32: 0.042411408 | AD32: 0.12178369 | AE32: 0.077864215 | AF32: 0.20279232 | AG32: 0 | AH32: 0.014860687 | AI32: 0.11748632
B33: 5401 | C33: Servicios fiduciarios | D33: 0 | E33: 0 | F33: 0 | G33: 0 | H33: 0 | I33: 0 | J33: 0 | K33: 0 | L33: 0 | M33: 0 | N33: 0 | O33: 0 | P33: 0 | Q33: 0 | R33: 0 | S33: 0 | T33: 0 | U33: 0 | V33: 0 | W33: 0 | X33: 0 | Y33: 0 | Z33: 0 | AA33: 0 | AB33: 0 | AC33: 0 | AD33: 0 | AE33: 0 | AF33: 0 | AG33: 0 | AH33: 0 | AI33: 0
B34: 5402 | C34: Servicios especiales | D34: 0 | E34: 0 | F34: 0 | G34: 0 | H34: 0 | I34: 0 | J34: 0 | K34: 0 | L34: 0 | M34: 0 | N34: 0 | O34: 0 | P34: 0 | Q34: 0 | R34: 0 | S34: 0 | T34: 0 | U34: 0 | V34: 0 | W34: 0 | X34: 0 | Y34: 0 | Z34: 0 | AA34: 0 | AB34: 0 | AC34: 0 | AD34: 0 | AE34: 0 | AF34: 0 | AG34: 0 | AH34: 0 | AI34: 0
B35: 5404 | C35: Manejo y cobranzas | D35: 0.0009325999 | E35: 0 | F35: 0 | G35: 0.0001703865 | H35: 0.0002087194 | I35: 0 | J35: 0 | K35: 0 | L35: 0 | M35: 0 | N35: 0 | O35: 0 | P35: 0 | Q35: 0 | R35: 0 | S35: 0 | T35: 0 | U35: 0.092232204 | V35: 0 | W35: 0 | X35: 0 | Y35: 0 | Z35: 0.0055570295 | AA35: 0 | AB35: 0 | AC35: 0.0052154752 | AD35: 0.0002916542 | AE35: 0 | AF35: 0 | AG35: 0 | AH35: 0.0019957131 | AI35: 0.000333515
B36: 5405 | C36: Garantías crediticias | D36: 0 | E36: 0 | F36: 0 | G36: 0 | H36: 0 | I36: 0 | J36: 0 | K36: 0 | L36: 0 | M36: 0 | N36: 0 | O36: 0 | P36: 0 | Q36: 0 | R36: 0 | S36: 0 | T36: 0 | U36: 0 | V36: 0 | W36: 0 | X36: 0 | Y36: 0 | Z36: 0 | AA36: 0 | AB36: 0 | AC36: 0 | AD36: 0 | AE36: 0 | AF36: 0 | AG36: 0 | AH36: 0 | AI36: 0
... B59: 4390 | C59: Otras | D59: 0 | E59: 0 | F59: 0 | G59: 0 | H59: 0 | I59: 0 | J59: 0 | K59: 0 | L59: 0 | M59: 0 | N59: 0 | O59: 0 | P59: 0 | Q59: 0 | R59: 0 | S59: 0 | T59: 0 | U59: 0 | V59: 0 | W59: 0 | X59: 0 | Y59: 0 | Z59: 0 | AA59: 0 | AB59: 0 | AC59: 0 | AD59: 0 | AE59: 0 | AF59: 0 | AG59: 0 | AH59: 0 | AI59: 0
C60: MARGEN BRUTO FINANCIERO | D60: 0.64287898 | E60: 0.51683346 | F60: 0.64679394 | G60: 0.59799475 | H60: 0.61280643 | I60: 0.5022432 | J60: 0.59709772 | K60: 0.70408 | L60: 0.67415555 | M60: 0.58914352 | N60: 0.55751417 | O60: 0.61809524 | P60: 0.5873123 | Q60: 0.67885195 | R60: 0.60194849 | S60: 0.32630137 | T60: 0.3828094 | U60: 0.58376497 | V60: 0.72834857 | W60: 0.65249808 | X60: 0.22991778 | Y60: 0.63774675 | Z60: 0.33599545 | AA60: 0.46921493 | AB60: 0.62625542 | AC60: 0.44115686 | AD60: 0.60456609 | AE60: 0.57430351 | AF60: 0.65630064 | AG60: 0 | AH60: 0.52201346 | AI60: 0.60209906
B62: 44 | C62: PROVISIONES | D62: 0.2047654 | E62: 0.16785098 | F62: 0.24626998 | G62: 0.23956311 | H62: 0.22176002 | I62: 0.11593254 | J62: 0.12181297 | K62: 0.044319998 | L62: 0.2474897 | M62: 0.17859922 | N62: 0.13096023 | O62: 0.21927823 | P62: 0.16737111 | Q62: 0.19581504 | R62: 0.16385417 | S62: 0.082181652 | T62: 0.083819439 | U62: 0.046272764 | V62: 0.039982575 | W62: 0.0052142868 | X62: 0.093334351 | Y62: 0.051198976 | Z62: 0.096114 | AA62: 0.20346835 | AB62: 0.094519079 | AC62: 0.097315404 | AD62: 0.20079522 | AE62: 0.12103545 | AF62: 0.23127174 | AG62: 0 | AH62: 0.095091868 | AI62: 0.20467124
B63: 4401 | C63: Inversiones | D63: 0 | E63: 1.5e-09 | F63: 0.0014305925 | G63: 1.17245e-05 | H63: 0.0006459261 | I63: 0.0013607464 | J63: 0 | K63: 0 | L63: 0 | M63: 0 | N63: 0 | O63: 0 | P63: 0 | Q63: 0 | R63: 0.0001806536 | S63: 0 | T63: 0 | U63: 0.011322501 | V63: 0 | W63: 0 | X63: 0 | Y63: 0 | Z63: 0 | AA63: 0.0001364566 | AB63: 0 | AC63: 0.0006116033 | AD63: 0.000505529 | AE63: 0 | AF63: 0 | AG63: 0 | AH63: 0 | AI63: 0.0006026598
B64: 4402 | C64: CARTERA DE CRÉDITOS | D64: 0.19108207 | E64: 0.1522715 | F64: 0.22267869 | G64: 0.2048909 | H64: 0.19990324 | I64: 0.067506215 | J64: 0.10943493 | K64: 0.04325192 | L64: 0.23698403 | M64: 0.17082095 | N64: 0.11571736 | O64: 0.21260159 | P64: 0.14642266 | Q64: 0.19438458 | R64: 0.14764518 | S64: 0.052183522 | T64: 0.062106195 | U64: 0.021244632 | V64: 0.032326442 | W64: 0.0030867977 | X64: 0.081540249 | Y64: 0.04658537 | Z64: 0.093717066 | AA64: 0.18406799 | AB64: 0.087880789 | AC64: 0.079147885 | AD64: 0.18073776 | AE64: 0.10741633 | AF64: 0.22137082 | AG64: 0 | AH64: 0.089976789 | AI64: 0.18292395
B65: 440210 | C65: CRÉDITO PRODUCTIVO | D65: 0.010494405 | E65: 0.014789105 | F65: 0.051748608 | G65: 0.017666451 | H65: 0.031050259 | I65: 0.0053246759 | J65: 0.023856517 | K65: 0.04325192 | L65: 0.0052449548 | M65: 0 | N65: 0.026764504 | O65: 0.033652588 | P65: 0.074321346 | Q65: 0 | R65: 0.017898957 | S65: 0.027162435 | T65: 0.023926088 | U65: 0.0051944038 | V65: 0.0046805411 | W65: 1.02962e-05 | X65: 0.0003429817 | Y65: 0.034045628 | Z65: 0.009401001 | AA65: 0.0075835 | AB65: 0 | AC65: 0.014541928 | AD65: 0.026630367 | AE65: 0.028653164 | AF65: 0.0041161818 | AG65: 0 | AH65: 0.0033762104 | AI65: 0.029010622
B66: 440220 | C66: CRÉDITO DE CONSUMO | D66: 0.14541679 | E66: 0.13073989 | F66: 0.10823244 | G66: 0.18266091 | H66: 0.1317306 | I66: 0.059784821 | J66: 0.083961206 | K66: 0 | L66: 0.23084424 | M66: 0.17082095 | N66: 0.086405353 | O66: 0.15969274 | P66: 0.061757859 | Q66: 0.061846077 | R66: 0.11926172 | S66: 0.0032516221 | T66: 0.03720886 | U66: 0.0060003479 | V66: 0.022572848 | W66: 0.0005778824 | X66: 0.051859703 | Y66: 0.012337737 | Z66: 0.006485697 | AA66: 0.065094361 | AB66: 0.0015707628 | AC66: 0.021990996 | AD66: 0.12480638 | AE66: 0.076507483 | AF66: 0.21652265 | AG66: 0 | AH66: 0.0033358782 | AI66: 0.11983057
B67: 440230 | C67: CRÉDITO INMOBILIARIO | D67: 0.0013603489 | E67: 0.0060668447 | F67: 0.0058227132 | G67: 0.0026771151 | H67: 0.0045008528 | I67: 0.0020336301 | J67: 0.0014872558 | K67: 0 | L67: 0 | M67: 0 | N67: 0.0024788722 | O67: 0.0036924586 | P67: 0.0020898561 | Q67: 0 | R67: 0.0013117529 | S67: 0.0001597896 | T67: 0.0001491942 | U67: 0 | V67: 0 | W67: 0 | X67: 0 | Y67: 9.03446e-05 | Z67: 6.6626e-05 | AA67: 0.0061321837 | AB67: 0 | AC67: 0.0010465851 | AD67: 0.0034450074 | AE67: 0.0021949135 | AF67: 0 | AG67: 0 | AH67: 2.39276e-05 | AI67: 0.0039322442
B68: 440235 | C68: CRÉDITO DE VIVIENDA DE INTERÉS SOCIAL Y PÚBLICO | D68: 0 | E68: 0.0003031758 | F68: 5.14653e-05 | G68: 0 | H68: 8.25553e-05 | I68: 0 | J68: 0 | K68: 0 | L68: 0 | M68: 0 | N68: 4.734e-07 | O68: 0 | P68: 0 | Q68: 0 | R68: 9.33e-08 | S68: 0 | T68: 0 | U68: 0 | V68: 0 | W68: 0 | X68: 0 | Y68: 0 | Z68: 0 | AA68: 0 | AB68: 0 | AC68: 0 | AD68: 5.54504e-05 | AE68: 4.191e-07 | AF68: 0 | AG68: 0 | AH68: 0 | AI68: 6.60711e-05
B69: 440240 | C69: MICROCRÉDITO | D69: 0.033810449 | E69: 0.000145674 | F69: 0.056671492 | G69: 0.0018675439 | H69: 0.032423108 | I69: 0.0003630878 | J69: 7.99289e-05 | K69: 0 | L69: 0.0008948328 | M69: 0 | N69: 6.81608e-05 | O69: 0.015555185 | P69: 0.0081978519 | Q69: 0.1325385 | R69: 0.0091595426 | S69: 0.021601536 | T69: 0.0008220529 | U69: 0.010049881 | V69: 0.0050730537 | W69: 0.0024986191 | X69: 0.029337564 | Y69: 0.0001116609 | Z69: 0.077763742 | AA69: 0.10525795 | AB69: 0.086310026 | AC69: 0.04156624 | AD69: 0.025718783 | AE69: 6.03529e-05 | AF69: 0.0007319904 | AG69: 0 | AH69: 0.083240773 | AI69: 0.029986955
B70: 440245 | C70: CRÉDITO EDUCATIVO | D70: 7.77e-08 | E70: 0.0002268079 | F70: 0.000151967 | G70: 1.88767e-05 | H70: 0.0001158632 | I70: 0 | J70: 5.00215e-05 | K70: 0 | L70: 0 | M70: 0 | N70: 0 | O70: 8.6125e-06 | P70: 5.57461e-05 | Q70: 0 | R70: 1.3122e-05 | S70: 8.1388e-06 | T70: 0 | U70: 0 | V70: 0 | W70: 0 | X70: 0 | Y70: 0 | Z70: 0 | AA70: 0 | AB70: 0 | AC70: 2.1353e-06 | AD70: 8.17767e-05 | AE70: 0 | AF70: 0 | AG70: 0 | AH70: 0 | AI70: 9.7489e-05
B71: 440250 | C71: CRÉDITO DE INVERSIÓN PÚBLICA | D71: 0 | E71: 0 | F71: 0 | G71: 0 | H71: 0 | I71: 0 | J71: 0 | K71: 0 | L71: 0 | M71: 0 | N71: 0 | O71: 0 | P71: 0 | Q71: 0 | R71: 0 | S71: 0 | T71: 0 | U71: 0 | V71: 0 | W71: 0 | X71: 0 | Y71: 0 | Z71: 0 | AA71: 0 | AB71: 0 | AC71: 0 | AD71: 0 | AE71: 0 | AF71: 0 | AG71: 0 | AH71: 0 | AI71: 0
B72: 4403 | C72: Cuentas por cobrar | D72: 0.0096585192 | E72: 0.014339647 | F72: 0.015792841 | G72: 0.030598582 | H72: 0.0166708 | I72: 0.028636873 | J72: 0.006517758 | K72: 0.0004807418 | L72: 0.010505667 | M72: 0.0061349682 | N72: 0.0069562912 | O72: 0.0052626254 | P72: 0.012127471 | Q72: 0 | R72: 0.010088938 | S72: 0.01078951 | T72: 0.0088873809 | U72: 0.01011913 | V72: 0.0034745616 | W72: 0.0019988872 | X72: 0.011794103 | Y72: 0 | Z72: 0.0021639622 | AA72: 0.009136342 | AB72: 0.006212932 | AC72: 0.0080985269 | AD72: 0.014449751 | AE72: 0.0062145068 | AF72: 0.0095194037 | AG72: 0 | AH72: 0.004758813 | AI72: 0.015693625
B73: 4404 | C73: Bienes realizables, adjudicados por pago y de arrendamiento mercantil | D73: 0.0022386936 | E73: 0.0006699154 | F73: 0.0027664581 | G73: 0.001595468 | H73: 0.0020666053 | I73: 0.0045427405 | J73: 0 | K73: 0 | L73: 0 | M73: 0.0016396018 | N73: 0.0030171963 | O73: 0.0003652644 | P73: 0.0081660248 | Q73: 7.80288e-05 | R73: 0.0016828839 | S73: 0.019016634 | T73: 0.0048719345 | U73: 0.0022444282 | V73: 0 | W73: 0 | X73: 0 | Y73: 0 | Z73: 0 | AA73: 0.0099386747 | AB73: 0 | AC73: 0.0075754407 | AD73: 0.0021116957 | AE73: 0.0026715717 | AF73: 0.0003516333 | AG73: 0 | AH73: 0 | AI73: 0.0022679202
... B76: 4407 | C76: Operaciones interbancarias y de reporto | D76: 0 | E76: 0 | F76: 0 | G76: 0 | H76: 0 | I76: 0 | J76: 0 | K76: 0 | L76: 0 | M76: 0 | N76: 0 | O76: 0 | P76: 0 | Q76: 0 | R76: 0 | S76: 0 | T76: 0 | U76: 0 | V76: 0 | W76: 0 | X76: 0 | Y76: 0 | Z76: 0 | AA76: 0 | AB76: 0 | AC76: 0 | AD76: 0 | AE76: 0 | AF76: 0 | AG76: 0 | AH76: 0 | AI76: 0
C77: MARGEN NETO FINANCIERO | D77: 0.43811358 | E77: 0.34898248 | F77: 0.40052396 | G77: 0.35843164 | H77: 0.39104641 | I77: 0.38631066 | J77: 0.47528475 | K77: 0.65976 | L77: 0.42666585 | M77: 0.4105443 | N77: 0.42655394 | O77: 0.39881701 | P77: 0.41994119 | Q77: 0.48303692 | R77: 0.43809431 | S77: 0.24411972 | T77: 0.29898996 | U77: 0.5374922 | V77: 0.68836599 | W77: 0.64728379 | X77: 0.13658343 | Y77: 0.58654778 | Z77: 0.23988145 | AA77: 0.26574658 | AB77: 0.53173634 | AC77: 0.34384145 | AD77: 0.40377087 | AE77: 0.45326806 | AF77: 0.42502889 | AG77: 0 | AH77: 0.4269216 | AI77: 0.39742782
B79: 45 | C79: GASTOS DE OPERACIÓN | D79: 0.2661977 | E79: 0.23928654 | F79: 0.33732326 | G79: 0.30874436 | H79: 0.29972087 | I79: 0.30307301 | J79: 0.29824398 | K79: 0.42442916 | L79: 0.4023249 | M79: 0.32392976 | N79: 0.25254239 | O79: 0.28920415 | P79: 0.35763441 | Q79: 0.41375771 | R79: 0.32776549 | S79: 0.40972528 | T79: 0.31496791 | U79: 0.5422635 | V79: 0.69301264 | W79: 0.60339236 | X79: 0.41785886 | Y79: 0.64767204 | Z79: 0.51411189 | AA79: 0.30831337 | AB79: 0.408263 | AC79: 0.41232424 | AD79: 0.31139493 | AE79: 0.27223229 | AF79: 0.38753424 | AG79: 0 | AH79: 0.44627684 | AI79: 0.30551554
B80: 4501 | C80: Gastos de personal | D80: 0.1042355 | E80: 0.089708922 | F80: 0.096398049 | G80: 0.092040535 | H80: 0.095920174 | I80: 0.088765834 | J80: 0.10287435 | K80: 0.17607731 | L80: 0.058866536 | M80: 0.12065912 | N80: 0.09962619 | O80: 0.13954734 | P80: 0.16746543 | Q80: 0.23262259 | R80: 0.10532083 | S80: 0.16601473 | T80: 0.11310492 | U80: 0.27021908 | V80: 0.38789315 | W80: 0.22546971 | X80: 0.19329687 | Y80: 0.33912422 | Z80: 0.25527315 | AA80: 0.16931108 | AB80: 0.2542706 | AC80: 0.19313984 | AD80: 0.10156137 | AE80: 0.10838379 | AF80: 0.074407605 | AG80: 0 | AH80: 0.25463065 | AI80: 0.1027971
B81: 4502 | C81: Honorarios | D81: 0.012050978 | E81: 0.0045061977 | F81: 0.041559021 | G81: 0.0055686205 | H81: 0.022825788 | I81: 0.034721186 | J81: 0.0033165041 | K81: 0 | L81: 0.003891343 | M81: 0.016489268 | N81: 0.0010509122 | O81: 0.0070285677 | P81: 0.012594479 | Q81: 0.013629938 | R81: 0.0090993046 | S81: 0.0061880737 | T81: 0.038437889 | U81: 0.022092522 | V81: 0.039555514 | W81: 0.05037974 | X81: 0.02504596 | Y81: 0.022492257 | Z81: 0.02631828 | AA81: 0.0091889565 | AB81: 0.023308609 | AC81: 0.02135046 | AD81: 0.018670344 | AE81: 0.0009305285 | AF81: 0.0068412242 | AG81: 0 | AH81: 0.024389481 | AI81: 0.021288427
B82: 4503 | C82: Servicios varios | D82: 0.088956734 | E82: 0.055470617 | F82: 0.095234251 | G82: 0.13095091 | H82: 0.091909173 | I82: 0.076533313 | J82: 0.088589735 | K82: 0.14082725 | L82: 0.26316223 | M82: 0.080723501 | N82: 0.038291738 | O82: 0.067125998 | P82: 0.096473405 | Q82: 0.095763854 | R82: 0.11794225 | S82: 0.10561881 | T82: 0.067272284 | U82: 0.062510641 | V82: 0.1146749 | W82: 0.091131967 | X82: 0.092746841 | Y82: 0.21146686 | Z82: 0.10427341 | AA82: 0.075728263 | AB82: 0.088437143 | AC82: 0.090393274 | AD82: 0.099664876 | AE82: 0.050037344 | AF82: 0.22300299 | AG82: 0 | AH82: 0.094124472 | AI82: 0.090634179
B83: 4504 | C83: Impuestos, contribuciones y multas | D83: 0.020926003 | E83: 0.040860813 | F83: 0.032157378 | G83: 0.029885488 | H83: 0.031313555 | I83: 0.041635378 | J83: 0.032193493 | K83: 0.084533765 | L83: 0.039862912 | M83: 0.022456327 | N83: 0.029618622 | O83: 0.033219307 | P83: 0.030960864 | Q83: 0.036815079 | R83: 0.035683902 | S83: 0.059549296 | T83: 0.022634719 | U83: 0.05723831 | V83: 0.049695217 | W83: 0.033547518 | X83: 0.036634677 | Y83: 0.035557611 | Z83: 0.014129467 | AA83: 0.023894797 | AB83: 0.013490134 | AC83: 0.034519605 | AD83: 0.032716101 | AE83: 0.035909238 | AF83: 0.036198249 | AG83: 0 | AH83: 0.01371974 | AI83: 0.032229708
B84: 4505 | C84: Depreciaciones | D84: 0.0094605175 | E84: 0.0095689253 | F84: 0.0093702175 | G84: 0.0091648671 | H84: 0.0093940313 | I84: 0.016431744 | J84: 0.009434798 | K84: 0.00871801 | L84: 0.0025833714 | M84: 0.0074162861 | N84: 0.0074546803 | O84: 0.0087765259 | P84: 0.0095869938 | Q84: 0.010880486 | R84: 0.0083161232 | S84: 0.0087320193 | T84: 0.0074709882 | U84: 0.031314961 | V84: 0.0086564068 | W84: 0.016692111 | X84: 0.015755635 | Y84: 0.0042364344 | Z84: 0.011587496 | AA84: 0.0091832463 | AB84: 0.0054079063 | AC84: 0.010142192 | AD84: 0.0090928177 | AE84: 0.0075993967 | AF84: 0.0036620979 | AG84: 0 | AH84: 0.0076272015 | AI84: 0.0097950585
B85: 4506 | C85: Amortizaciones | D85: 0.01626169 | E85: 0.018807732 | F85: 0.015660076 | G85: 0.014273904 | H85: 0.016173099 | I85: 0.029850474 | J85: 0.0060125752 | K85: 0.0035824741 | L85: 0.0072366011 | M85: 0.02235664 | N85: 0.011137046 | O85: 0.0052246733 | P85: 0.017662906 | Q85: 0.0035076633 | R85: 0.011776422 | S85: 0.0021743257 | T85: 0.0064054553 | U85: 0.026452627 | V85: 0.059677119 | W85: 0.040501418 | X85: 0.033348846 | Y85: 0.01981887 | Z85: 0.027154808 | AA85: 0.0044860753 | AB85: 0.0065997237 | AC85: 0.011955403 | AD85: 0.014733272 | AE85: 0.010271658 | AF85: 0.010844086 | AG85: 0 | AH85: 0.013981734 | AI85: 0.01550375
B86: 4507 | C86: Otros gastos | D86: 0.014306279 | E86: 0.020363335 | F86: 0.04694427 | G86: 0.026860031 | H86: 0.032185048 | I86: 0.015135083 | J86: 0.055822523 | K86: 0.010690348 | L86: 0.02672191 | M86: 0.053828623 | N86: 0.065363202 | O86: 0.028281742 | P86: 0.022890325 | Q86: 0.020538095 | R86: 0.03962666 | S86: 0.061448021 | T86: 0.059641653 | U86: 0.072435363 | V86: 0.032860335 | W86: 0.14566989 | X86: 0.021030027 | Y86: 0.014975793 | Z86: 0.075375273 | AA86: 0.016520951 | AB86: 0.016748878 | AC86: 0.050823465 | AD86: 0.034956153 | AE86: 0.05910034 | AF86: 0.032577988 | AG86: 0 | AH86: 0.037803555 | AI86: 0.033267312
C87: MARGEN DE INTERMEDIACIÓN | D87: 0.17191588 | E87: 0.10969594 | F87: 0.063200693 | G87: 0.049687278 | H87: 0.091325539 | I87: 0.083237645 | J87: 0.17704077 | K87: 0.23533085 | L87: 0.024340949 | M87: 0.086614537 | N87: 0.17401155 | O87: 0.10961285 | P87: 0.062306788 | Q87: 0.069279207 | R87: 0.11032882 | S87: -0.16560556 | T87: -0.015977945 | U87: -0.0047712985 | V87: -0.0046466511 | W87: 0.043891438 | X87: -0.28127543 | Y87: -0.061124265 | Z87: -0.27423044 | AA87: -0.042566792 | AB87: 0.12347334 | AC87: -0.068482785 | AD87: 0.092375934 | AE87: 0.18103577 | AF87: 0.037494653 | AG87: 0 | AH87: -0.019355241 | AI87: 0.091912284
B89: 55 | C89: OTROS INGRESOS OPERACIONALES | D89: 0.0032389022 | E89: 0.039505551 | F89: 0.072671718 | G89: 0.030361931 | H89: 0.045919684 | I89: 0.026927346 | J89: 0.0060597252 | K89: 0.011146929 | L89: 0.042328287 | M89: 0.0001874519 | N89: 0.0050744301 | O89: 0.017811982 | P89: 0.000366879 | Q89: 0.032953399 | R89: 0.018572053 | S89: 0.016924271 | T89: 0.0003934413 | U89: 0.0009672802 | V89: 0.040722797 | W89: 0 | X89: 0.17646385 | Y89: 0 | Z89: 0.013675398 | AA89: 0.0094258536 | AB89: 0 | AC89: 0.015472981 | AD89: 0.036841471 | AE89: 0.0057700444 | AF89: 0.033279485 | AG89: 0 | AH89: 0.0049112877 | AI89: 0.039914509
B90: 5501 | C90: Utilidades en acciones y participaciones | D90: 0.0032389022 | E90: 0.0015591622 | F90: 0.042416946 | G90: 0.0050833103 | H90: 0.020841641 | I90: 0.0033258837 | J90: 0.0004934672 | K90: 0.0040221935 | L90: 0.024719233 | M90: 0 | N90: 0.0046732493 | O90: 0.0016558728 | P90: 0 | Q90: 0 | R90: 0.0073223549 | S90: 0 | T90: 0.0003934413 | U90: 0 | V90: 0 | W90: 0 | X90: 0 | Y90: 0 | Z90: 0 | AA90: 0 | AB90: 0 | AC90: 7.24009e-05 | AD90: 0.016187699 | AE90: 0.0045986699 | AF90: 0.019245922 | AG90: 0 | AH90: 0 | AI90: 0.016901344
B91: 5502 | C91: Utilidad en venta de bienes realizables y recuperados | D91: 0 | E91: 0 | F91: 0 | G91: 0 | H91: 0 | I91: 0 | J91: 0 | K91: 0 | L91: 0 | M91: 0 | N91: 0 | O91: 0 | P91: 0 | Q91: 9.6647e-06 | R91: 5.733e-07 | S91: 0 | T91: 0 | U91: 0 | V91: 0 | W91: 0 | X91: 0 | Y91: 0 | Z91: 0 | AA91: 3.22373e-05 | AB91: 0 | AC91: 5.1012e-06 | AD91: 3.2e-07 | AE91: 0 | AF91: 0 | AG91: 0 | AH91: 0 | AI91: 3.814e-07
B92: 5505 | C92: Ingresos por subsidios realizados | D92: 0 | E92: 0 | F92: 0 | G92: 0 | H92: 0 | I92: 0 | J92: 0 | K92: 0 | L92: 0 | M92: 0 | N92: 0 | O92: 0 | P92: 0 | Q92: 0 | R92: 0 | S92: 0 | T92: 0 | U92: 0 | V92: 0 | W92: 0 | X92: 0 | Y92: 0 | Z92: 0 | AA92: 0 | AB92: 0 | AC92: 0 | AD92: 0 | AE92: 0 | AF92: 0 | AG92: 0 | AH92: 0 | AI92: 0
B93: 5506 | C93: Ingresos por subsidios recuperados | D93: 0 | E93: 0 | F93: 0 | G93: 0 | H93: 0 | I93: 0 | J93: 0 | K93: 0 | L93: 0 | M93: 0 | N93: 0 | O93: 0 | P93: 0 | Q93: 0 | R93: 0 | S93: 0 | T93: 0 | U93: 0 | V93: 0 | W93: 0 | X93: 0 | Y93: 0 | Z93: 0 | AA93: 0 | AB93: 0 | AC93: 0 | AD93: 0 | AE93: 0 | AF93: 0 | AG93: 0 | AH93: 0 | AI93: 0
B94: 5507 | C94: Ingresos por demora en transferencias | D94: 0 | E94: 0 | F94: 0 | G94: 0 | H94: 0 | I94: 0 | J94: 0 | K94: 0 | L94: 0 | M94: 0 | N94: 0 | O94: 0 | P94: 0 | Q94: 0 | R94: 0 | S94: 0 | T94: 0 | U94: 0 | V94: 0 | W94: 0 | X94: 0 | Y94: 0 | Z94: 0 | AA94: 0 | AB94: 0 | AC94: 0 | AD94: 0 | AE94: 0 | AF94: 0 | AG94: 0 | AH94: 0 | AI94: 0
B95: 5590 | C95: Otros | D95: 0 | E95: 0.037946389 | F95: 0.030254772 | G95: 0.025278621 | H95: 0.025078043 | I95: 0.023601462 | J95: 0.005566258 | K95: 0.0071247352 | L95: 0.017609054 | M95: 0.0001874519 | N95: 0.0004011807 | O95: 0.016156109 | P95: 0.000366879 | Q95: 0.032943734 | R95: 0.011249125 | S95: 0.016924271 | T95: 0 | U95: 0.0009672802 | V95: 0.040722797 | W95: 0 | X95: 0.17646385 | Y95: 0 | Z95: 0.013675398 | AA95: 0.0093936164 | AB95: 0 | AC95: 0.015395478 | AD95: 0.020653451 | AE95: 0.0011713745 | AF95: 0.014033563 | AG95: 0 | AH95: 0.0049112877 | AI95: 0.023012783
B96: 46 | C96: OTRAS PÉRDIDAS OPERACIONALES | D96: 0.0022249909 | E96: 0.0032846326 | F96: 0.050654275 | G96: 0.0019247505 | H96: 0.024187837 | I96: 0.002327872 | J96: 0.0002893109 | K96: 8.38282e-05 | L96: 0.012231494 | M96: 0.0013755535 | N96: 0.0004436342 | O96: 0.0035349268 | P96: 0 | Q96: 0.099366904 | R96: 0.0094009383 | S96: 0 | T96: 0.0044865863 | U96: 0.0026667001 | V96: 0.0049132543 | W96: 0 | X96: 0 | Y96: 0 | Z96: 0.0063711213 | AA96: 0.0007702653 | AB96: 0 | AC96: 0.0016598565 | AD96: 0.019103008 | AE96: 0.0004024178 | AF96: 0.0098523912 | AG96: 0 | AH96: 0.0022880804 | AI96: 0.021685444
B97: 4601 | C97: Pérdida en acciones y participaciones | D97: 0.0017512993 | E97: 0.0011647644 | F97: 0.04189635 | G97: 0.0017104018 | H97: 0.019703384 | I97: 0.0015845726 | J97: 5.37625e-05 | K97: 0 | L97: 0.012231494 | M97: 0 | N97: 0.0004436342 | O97: 7.24557e-05 | P97: 0 | Q97: 0 | R97: 0.0031255674 | S97: 0 | T97: 0.0002173788 | U97: 0 | V97: 0 | W97: 0 | X97: 0 | Y97: 0 | Z97: 0 | AA97: 0 | AB97: 0 | AC97: 4.0002e-05 | AD97: 0.014165209 | AE97: 0.0003928152 | AF97: 0.0095232074 | AG97: 0 | AH97: 0 | AI97: 0.015850668
B98: 4602 | C98: Pérdida en venta de bienes realizables y recuperados | D98: 0.0003760829 | E98: 0.0004831421 | F98: 0 | G98: 0.0002143487 | H98: 0.0002019912 | I98: 0 | J98: 0 | K98: 0 | L98: 0 | M98: 0.0003723487 | N98: 0 | O98: 0 | P98: 0 | Q98: 3.47824e-05 | R98: 2.56565e-05 | S98: 0 | T98: 0.0005135984 | U98: 0 | V98: 0.0049132543 | W98: 0 | X98: 0 | Y98: 0 | Z98: 0 | AA98: 0 | AB98: 0 | AC98: 0.0001986453 | AD98: 0.0001490625 | AE98: 0 | AF98: 0.0001140339 | AG98: 0 | AH98: 0 | AI98: 0.0001656691
B99: 4690 | C99: Otras | D99: 9.76087e-05 | E99: 0.0016367261 | F99: 0.0087579249 | G99: 0 | H99: 0.0042824622 | I99: 0.0007432994 | J99: 0.0002355484 | K99: 8.38282e-05 | L99: 0 | M99: 0.0010032047 | N99: 0 | O99: 0.0034624711 | P99: 0 | Q99: 0.099332121 | R99: 0.0062497144 | S99: 0 | T99: 0.0037556091 | U99: 0.0026667001 | V99: 0 | W99: 0 | X99: 0 | Y99: 0 | Z99: 0.0063711213 | AA99: 0.0007702653 | AB99: 0 | AC99: 0.0014212092 | AD99: 0.0047887363 | AE99: 9.6026e-06 | AF99: 0.0002151499 | AG99: 0 | AH99: 0.0022880804 | AI99: 0.0056691076
C100: MARGEN OPERACIONAL | D100: 0.17292979 | E100: 0.14591686 | F100: 0.085218136 | G100: 0.078124459 | H100: 0.11305739 | I100: 0.10783712 | J100: 0.18281118 | K100: 0.24639395 | L100: 0.054437742 | M100: 0.085426436 | N100: 0.17864234 | O100: 0.12388991 | P100: 0.062673667 | Q100: 0.0028657022 | R100: 0.11949994 | S100: -0.14868129 | T100: -0.02007109 | U100: -0.0064707184 | V100: 0.031162891 | W100: 0.043891438 | X100: -0.10481158 | Y100: -0.061124265 | Z100: -0.26692617 | AA100: -0.033911204 | AB100: 0.12347334 | AC100: -0.054669661 | AD100: 0.1101144 | AE100: 0.18640339 | AF100: 0.060921747 | AG100: 0 | AH100: -0.016732034 | AI100: 0.11014135
B102: 56 | C102: OTROS INGRESOS | D102: 0.024809499 | E102: 0.10522967 | F102: 0.040775575 | G102: 0.053665145 | H102: 0.052343841 | I102: 0.039026274 | J102: 0.013423389 | K102: 0.2158813 | L102: 0.072262712 | M102: 0.048467783 | N102: 0.024245491 | O102: 0.030901979 | P102: 0.034135037 | Q102: 0.025724549 | R102: 0.04225137 | S102: 0.014747444 | T102: 0.075801452 | U102: 0.026070888 | V102: 0.048374941 | W102: 0.0232886 | X102: 0.13855763 | Y102: 0.068240731 | Z102: 0.27193982 | AA102: 0.13960465 | AB102: 0.093698022 | AC102: 0.083262839 | AD102: 0.050218383 | AE102: 0.046197676 | AF102: 0.066993415 | AG102: 0 | AH102: 0.15771055 | AI102: 0.048004222
B103: 5601 | C103: Utilidad en venta de bienes | D103: 0.0005581526 | E103: 0.0002098636 | F103: 0.0004664659 | G103: 0.000253661 | H103: 0.0004001778 | I103: 0.0058673553 | J103: 3.60521e-05 | K103: 0 | L103: 4.8523e-06 | M103: 2.40004e-05 | N103: 0.005184562 | O103: 0.0001171436 | P103: 0 | Q103: 3.12085e-05 | R103: 0.0018176191 | S103: 0.0012205508 | T103: 8.88774e-05 | U103: 0.0001015599 | V103: 0 | W103: 0 | X103: 0.0004949957 | Y103: 0 | Z103: 0.0020780552 | AA103: 5.8223e-06 | AB103: 0 | AC103: 0.0005170258 | AD103: 0.000828251 | AE103: 0.0045906622 | AF103: 8.9251e-06 | AG103: 0 | AH103: 0.0007462984 | AI103: 0.0006161656
B104: 5602 | C104: Utilidad en venta de acciones y participaciones | D104: 0 | E104: 0 | F104: 0 | G104: 0 | H104: 0 | I104: 0 | J104: 0 | K104: 0 | L104: 0 | M104: 0 | N104: 0 | O104: 0 | P104: 0 | Q104: 0 | R104: 0 | S104: 0 | T104: 0 | U104: 0 | V104: 0 | W104: 0 | X104: 0 | Y104: 0 | Z104: 0 | AA104: 0 | AB104: 0 | AC104: 0 | AD104: 0 | AE104: 0 | AF104: 0 | AG104: 0 | AH104: 0 | AI104: 0
B105: 5603 | C105: Arrendamientos | D105: 4.08294e-05 | E105: 0 | F105: 0.0007341678 | G105: 0.0026254915 | H105: 0.0007564534 | I105: 0.0002352632 | J105: 5.19935e-05 | K105: 0 | L105: 0.0001485842 | M105: 0 | N105: 0.0002677602 | O105: 0 | P105: 0 | Q105: 0.0005758029 | R105: 0.0001630416 | S105: 0 | T105: 0.004531273 | U105: 0 | V105: 0.0002975087 | W105: 0.0003841545 | X105: 0.0050263695 | Y105: 0 | Z105: 0 | AA105: 0 | AB105: 0 | AC105: 0.0010753596 | AD105: 0.0005879275 | AE105: 0.0002370878 | AF105: 0.0001177544 | AG105: 0 | AH105: 0 | AI105: 0.000669614
B106: 5604 | C106: Recuperaciones de activos financieros | D106: 0.023209774 | E106: 0.086040551 | F106: 0.036330683 | G106: 0.043089129 | H106: 0.044588814 | I106: 0.027770857 | J106: 0.0090532885 | K106: 0.074911796 | L106: 0.069222462 | M106: 0.039577447 | N106: 0.014591609 | O106: 0.021518696 | P106: 0.027451601 | Q106: 0.013747574 | R106: 0.031698688 | S106: 0.010442528 | T106: 0.015240666 | U106: 0.025969328 | V106: 0.047594752 | W106: 0.014650501 | X106: 0.10521417 | Y106: 0.039053455 | Z106: 0.1893135 | AA106: 0.1265428 | AB106: 0.04525863 | AC106: 0.053937002 | AD106: 0.040998423 | AE106: 0.021501381 | AF106: 0.062714262 | AG106: 0 | AH106: 0.096993499 | AI106: 0.039859124
B107: 5690 | C107: Otros | D107: 0.0010007436 | E107: 0.018979253 | F107: 0.0032442578 | G107: 0.0076968628 | H107: 0.0065983963 | I107: 0.0051527983 | J107: 0.0042820547 | K107: 0.1409695 | L107: 0.0028868134 | M107: 0.0088663364 | N107: 0.0042015602 | O107: 0.0092661394 | P107: 0.0066834362 | Q107: 0.011369964 | R107: 0.0085720212 | S107: 0.0030843648 | T107: 0.055940636 | U107: 0 | V107: 0.00048268 | W107: 0.0082539449 | X107: 0.02782209 | Y107: 0.029187276 | Z107: 0.080548268 | AA107: 0.013056031 | AB107: 0.048439392 | AC107: 0.027733451 | AD107: 0.0078037819 | AE107: 0.019868545 | AF107: 0.0041524731 | AG107: 0 | AH107: 0.059970751 | AI107: 0.0068593182
B108: 47 | C108: OTROS GASTOS Y PÉRDIDAS | D108: 0.0064247779 | E108: 0.010759596 | F108: 0.0068484195 | G108: 0.000975039 | H108: 0.0065970014 | I108: 0.029721662 | J108: 0.0025829286 | K108: 0.0042968196 | L108: 0.017576375 | M108: 0.0085589784 | N108: 0.015084901 | O108: 0.0053466862 | P108: 0.0074169202 | Q108: 0.0051743501 | R108: 0.013004659 | S108: 0.0097097723 | T108: 0.012193757 | U108: 0.0080969963 | V108: 0.014542186 | W108: 0.0001047412 | X108: 0.030180206 | Y108: 0.0012591606 | Z108: 3.56935e-05 | AA108: 0.022159254 | AB108: 0.0032278522 | AC108: 0.01077847 | AD108: 0.0086382845 | AE108: 0.013849109 | AF108: 0.015621374 | AG108: 0 | AH108: 0.0020814424 | AI108: 0.0075336616
B109: 4701 | C109: Pérdida en venta de bienes | D109: 7.61e-06 | E109: 0 | F109: 8.23e-08 | G109: 2.7618e-05 | H109: 5.9156e-06 | I109: 0.0031701036 | J109: 0 | K109: 0 | L109: 8.92e-07 | M109: 0 | N109: 5.50179e-05 | O109: 1.09501e-05 | P109: 0.0001334541 | Q109: 1.8636e-05 | R109: 0.0004393826 | S109: 0.0042904764 | T109: 0 | U109: 0 | V109: 0 | W109: 0 | X109: 0 | Y109: 0 | Z109: 0 | AA109: 0.0003780864 | AB109: 0 | AC109: 0.0011854918 | AD109: 0.0001700583 | AE109: 4.87155e-05 | AF109: 6.945e-07 | AG109: 0 | AH109: 0 | AI109: 0.0001987864
B110: 4702 | C110: Pérdida en venta de acciones y participaciones | D110: 0 | E110: 0 | F110: 0 | G110: 8.95924e-05 | H110: 1.42631e-05 | I110: 0 | J110: 0 | K110: 0 | L110: 0 | M110: 0 | N110: 0 | O110: 0 | P110: 0 | Q110: 0 | R110: 0 | S110: 0 | T110: 0 | U110: 0 | V110: 0 | W110: 0 | X110: 0 | Y110: 0 | Z110: 0 | AA110: 0 | AB110: 0 | AC110: 0 | AD110: 9.5753e-06 | AE110: 0 | AF110: 0 | AG110: 0 | AH110: 0 | AI110: 1.14151e-05
B111: 4703 | C111: INTERESES y comisiones devengados en ejercicios anteriores | D111: 0.001850958 | E111: 0.0032353369 | F111: 0.0068483373 | G111: 0.0008578285 | H111: 0.0042138641 | I111: 0.015572716 | J111: 0.0024060149 | K111: 0.0005711797 | L111: 0.006368899 | M111: 0.0059065451 | N111: 0.0023540914 | O111: 0.0052025483 | P111: 0.0040800545 | Q111: 0.0039349589 | R111: 0.0055122924 | S111: 0.0054192959 | T111: 0.012193757 | U111: 0.001998699 | V111: 0.014537678 | W111: 0.0001047412 | X111: 0 | Y111: 0 | Z111: 3.56935e-05 | AA111: 0.01631801 | AB111: 0.0015818758 | AC111: 0.0068761791 | AD111: 0.0046802374 | AE111: 0.002149856 | AF111: 0.0063265674 | AG111: 0 | AH111: 0.0010265906 | AI111: 0.0047336342
B112: 4790 | C112: Otros | D112: 0.0045662099 | E112: 0.0075242595 | F112: 0 | G112: 0 | H112: 0.0023629586 | I112: 0.010978842 | J112: 0.0001769137 | K112: 0.0037256399 | L112: 0.011206584 | M112: 0.0026524334 | N112: 0.012675792 | O112: 0.0001331877 | P112: 0.0032034115 | Q112: 0.0012207553 | R112: 0.0070529844 | S112: 0 | T112: 0 | U112: 0.0060982974 | V112: 4.5073e-06 | W112: 0 | X112: 0.030180206 | Y112: 0.0012591606 | Z112: 0 | AA112: 0.0054631573 | AB112: 0.0016459763 | AC112: 0.0027167995 | AD112: 0.0037784135 | AE112: 0.011650538 | AF112: 0.0092941117 | AG112: 0 | AH112: 0.0010548518 | AI112: 0.0025898259
C113: GANANCIA O PERDIDA ANTES DE IMPUESTOS (MARGEN BENFICIO NETO) | D113: 0.19131451 | E113: 0.24038693 | F113: 0.11914529 | G113: 0.13081456 | H113: 0.15880423 | I113: 0.11714173 | J113: 0.19365164 | K113: 0.45797843 | L113: 0.10912408 | M113: 0.12533524 | N113: 0.18780293 | O113: 0.1494452 | P113: 0.089391784 | Q113: 0.023415901 | R113: 0.14874665 | S113: -0.14364361 | T113: 0.043536606 | U113: 0.011503173 | V113: 0.064995647 | W113: 0.067075298 | X113: 0.0035658452 | Y113: 0.0058573055 | Z113: 0.004977965 | AA113: 0.083534193 | AB113: 0.21394351 | AC113: 0.017814707 | AD113: 0.1516945 | AE113: 0.21875196 | AF113: 0.11229379 | AG113: 0 | AH113: 0.13889707 | AI113: 0.15061191
C115: IMPUESTOS Y PARTICIPACIÓN A EMPLEADOS | D115: 0.057596123 | E115: 0.060900248 | F115: 0.02803348 | G115: 0.03945731 | H115: 0.042046398 | I115: 0.049474666 | J115: 0.062425582 | K115: 0.1339902 | L115: 0.037604924 | M115: 0.033495673 | N115: 0.055672729 | O115: 0.053018883 | P115: 0.02587674 | Q115: 0.0051388409 | R115: 0.048248392 | S115: 0 | T115: 0.014506948 | U115: 0.009778925 | V115: 0.030922192 | W115: 0.032272789 | X115: 0.011934221 | Y115: 0.0040392346 | Z115: 0.0041483884 | AA115: 0.033537441 | AB115: 0.078740485 | AC115: 0.022092058 | AD115: 0.043324807 | AE115: 0.064644119 | AF115: 0.036677155 | AG115: 0 | AH115: 0.051951996 | AI115: 0.042270052
C117: GANANCIA O (PÉRDIDA) DEL EJERCICIO | D117: 0.13371839 | E117: 0.17948668 | F117: 0.091111811 | G117: 0.091357254 | H117: 0.11675783 | I117: 0.067667065 | J117: 0.13122606 | K117: 0.32398823 | L117: 0.071519155 | M117: 0.091839568 | N117: 0.1321302 | O117: 0.096426317 | P117: 0.063515044 | Q117: 0.01827706 | R117: 0.10049825 | S117: -0.14364361 | T117: 0.029029658 | U117: 0.0017242485 | V117: 0.034073455 | W117: 0.034802508 | X117: -0.0083683761 | Y117: 0.0018180709 | Z117: 0.0008295766 | AA117: 0.049996752 | AB117: 0.13520303 | AC117: -0.0042773507 | AD117: 0.10836969 | AE117: 0.15410784 | AF117: 0.075616633 | AG117: 0 | AH117: 0.086945077 | AI117: 0.10834186

Sheet CONSCOND
B3: ESTADO DE SITUACIÓN
B4: SISTEMA DE BANCOS PRIVADOS
B5: CONSCOND
B6: 31/12/2025
B7: (en miles de dólares)
B9: CÓDIGO | C9: CUENTA | D9: BP GUAYAQUIL | E9: BP PACIFICO | F9: BP PICHINCHA | G9: BP PRODUBANCO | H9: BANCOS GRANDES | I9: BP AUSTRO | J9: BP BOLIVARIANO | K9: BP CITIBANK | L9: BP DINERS | M9: BP GENERAL RUMIÑAHUI | N9: BP INTERNACIONAL | O9: BP LOJA | P9: BP MACHALA | Q9: BP SOLIDARIO | R9: BANCOS MEDIANOS | S9: BP PROCREDIT | T9: BP AMAZONAS | U9: BP BANCO COMERCIAL DE MANABI | V9: BP LITORAL | W9: BP COOPNACIONAL | X9: BP CAPITAL | Y9: BP DELBANK | Z9: BANCO ATLÁNTIDA S.A. | AA9: BP BANCO DESARROLLO DE LOS PUEBLOS S.A., CODESARROLLO | AB9: BP VISIONFUND ECUADOR S.A. | AC9: BANCOS PEQUEÑOS | AD9: BANCOS PRIVADOS | AE9: BANCOS PRIVADOS COMERCIALES | AF9: BANCOS PRIVADOS CONSUMO | AG9: BANCOS PRIVADOS VIVIENDA | AH9: BANCOS PRIVADOS MICROCRÉDITO | AI9: BANCA MÚLTIPLE
C10: ACTIVO
B11: 11 | C11: FONDOS DISPONIBLES | D11: 1012534 | E11: 1235542.8 | F11: 2498737.9 | G11: 981717.15 | H11: 5728532 | I11: 475145.08 | J11: 623981.53 | K11: 171488.36 | L11: 200616.25 | M11: 195315.74 | N11: 870369.02 | O11: 217427.37 | P11: 226529.59 | Q11: 72438.662 | R11: 3053311.6 | S11: 112879.01 | T11: 38903.616 | U11: 14053.52 | V11: 4211.866 | W11: 62878.608 | X11: 3006.965 | Y11: 7719.4678 | Z11: 11644.528 | AA11: 50258.056 | AB11: 13248.125 | AC11: 318803.76 | AD11: 9100647.3 | AE11: 1041857.4 | AF11: 400143.85 | AG11: 0 | AH11: 24892.653 | AI11: 7633753.4
B12: 12 | C12: OPERACIONES INTERBANCARIAS | D12: 0 | E12: 0 | F12: 0 | G12: 0 | H12: 0 | I12: 0 | J12: 0 | K12: 0 | L12: 0 | M12: 0 | N12: 0 | O12: 0 | P12: 0 | Q12: 0 | R12: 0 | S12: 0 | T12: 0 | U12: 0 | V12: 0 | W12: 0 | X12: 0 | Y12: 0 | Z12: 0 | AA12: 0 | AB12: 0 | AC12: 0 | AD12: 0 | AE12: 0 | AF12: 0 | AG12: 0 | AH12: 0 | AI12: 0
B13: 13 | C13: INVERSIONES | D13: 1510918.9 | E13: 1918156.4 | F13: 4537382 | G13: 1541595.9 | H13: 9508053.2 | I13: 674002.39 | J13: 1113978.3 | K13: 256183.35 | L13: 270189.05 | M13: 234314.66 | N13: 784545.84 | O13: 135627.84 | P13: 151715.07 | Q13: 69137.776 | R13: 3689694.2 | S13: 69018.024 | T13: 91686.427 | U13: 41403.008 | V13: 3921.1198 | W13: 132229.22 | X13: 5766.752 | Y13: 1923.0849 | Z13: 34869.739 | AA13: 61634.866 | AB13: 4662.2315 | AC13: 447114.47 | AD13: 13644862 | AE13: 1040729.2 | AF13: 508424.83 | AG13: 0 | AH13: 39531.971 | AI13: 12056176
C14: INVERSIONES DEL SECTOR PRIVADO | D14: 77914.44 | E14: 466682.87 | F14: 783670.05 | G14: 838546.31 | H14: 2166813.7 | I14: 246219.7 | J14: 148909.9 | K14: 62000 | L14: 8714.3384 | M14: 83721.634 | N14: 364167.12 | O14: 65514.686 | P14: 20260.313 | Q14: 32135.357 | R14: 1031643 | S14: 2700.5947 | T14: 49007.368 | U14: 29258.674 | V14: 650 | W14: 113740.49 | X14: 13.82226 | Y14: 0 | Z14: 13084.665 | AA14: 42152.352 | AB14: 0 | AC14: 250607.96 | AD14: 3449064.7 | AE14: 426167.12 | AF14: 93085.972 | AG14: 0 | AH14: 13084.665 | AI14: 2916726.9
C15: INVERSIONES DEL SECTOR PUBLICO | D15: 1333539.5 | E15: 1349442.9 | F15: 3306894.5 | G15: 602334.69 | H15: 6592211.6 | I15: 383719.54 | J15: 917089.71 | K15: 194183.35 | L15: 220884.04 | M15: 142626.44 | N15: 380534.04 | O15: 70018.156 | P15: 121624.67 | Q15: 37002.419 | R15: 2467682.4 | S15: 64575.598 | T15: 42414.745 | U15: 11832.158 | V15: 3271.1198 | W15: 18507.725 | X15: 5338.0497 | Y15: 1875.5849 | Z15: 20422.475 | AA15: 19482.514 | AB15: 4662.2315 | AC15: 192382.2 | AD15: 9252276.2 | AE15: 574717.38 | AF15: 366781.6 | AG15: 0 | AH15: 25084.707 | AI15: 8285692.5
B16: 1307 | C16: De disponibilidad restringida | D16: 99553.305 | E16: 104888.85 | F16: 498066.48 | G16: 100760.9 | H16: 803269.53 | I16: 44535.849 | J16: 49134.805 | K16: 0 | L16: 40590.672 | M16: 10142.9 | N16: 39844.683 | O16: 100 | P16: 9830.0908 | Q16: 0 | R16: 194179 | S16: 1741.8319 | T16: 310.87508 | U16: 730.38847 | V16: 0 | W16: 0 | X16: 414.87999 | Y16: 50 | Z16: 1362.5987 | AA16: 0 | AB16: 0 | AC16: 4610.5741 | AD16: 1002059.1 | AE16: 39844.683 | AF16: 50733.572 | AG16: 0 | AH16: 1362.5987 | AI16: 910118.25
B17: 1399 | C17: (Provisión para inversiones) | D17: -88.37754 | E17: -2858.2472 | F17: -51249.055 | G17: -45.9437 | H17: -54241.623 | I17: -472.70278 | J17: -1156.1564 | K17: 0 | L17: 0 | M17: -2176.3143 | N17: 0 | O17: -5 | P17: 0 | Q17: 0 | R17: -3810.1735 | S17: 0 | T17: -46.56118 | U17: -418.2122 | V17: 0 | W17: -18.99784 | X17: 0 | Y17: -2.5 | Z17: 0 | AA17: 0 | AB17: 0 | AC17: -486.27122 | AD17: -58538.068 | AE17: 0 | AF17: -2176.3143 | AG17: 0 | AH17: 0 | AI17: -56361.754
B18: 14 | C18: CARTERA DE CRÉDITOS | D18: 6585926.5 | E18: 6103558.6 | F18: 12266551 | G18: 6089793.8 | H18: 31045830 | I18: 1775068.3 | J18: 4115549.2 | K18: 345911.73 | L18: 2547193.3 | M18: 888580.91 | N18: 4096060.6 | O18: 605930.12 | P18: 795439.06 | Q18: 570293.23 | R18: 15740026 | S18: 495538.82 | T18: 235127.06 | U18: 59613.193 | V18: 31364.373 | W18: 33858.102 | X18: 52293.82 | Y18: 26729.745 | Z18: 65331.792 | AA18: 206525.56 | AB18: 143598.89 | AC18: 1349981.4 | AD18: 48135838 | AE18: 4441972.3 | AF18: 3467138.6 | AG18: 0 | AH18: 208930.68 | AI18: 40017796
C19: CARTERA DE CRÉDITOS PRODUCTIVO | D19: 3368976.4 | E19: 2469027.1 | F19: 5447690.6 | G19: 3777216.4 | H19: 15062910 | I19: 607996.59 | J19: 2979626 | K19: 363010.91 | L19: 179053.88 | M19: 93202.568 | N19: 3452264.1 | O19: 189638.49 | P19: 579929.44 | Q19: 19.4975 | R19: 8444741.4 | S19: 314799.79 | T19: 118555.05 | U19: 32276.737 | V19: 9229.3522 | W19: 33413.925 | X19: 600.97148 | Y19: 20973.5 | Z19: 8402.8194 | AA19: 31563.735 | AB19: 0 | AC19: 569815.89 | AD19: 24077468 | AE19: 3815275 | AF19: 281485.8 | AG19: 0 | AH19: 8402.8194 | AI19: 19972304
C20: CARTERA DE CREDITOS CONSUMO | D20: 2757880.7 | E20: 3403445.4 | F20: 5199746.6 | G20: 2238754.2 | H20: 13599827 | I20: 1161148.4 | J20: 1072339.4 | K20: 0 | L20: 2560858.1 | M20: 750078.19 | N20: 652089.22 | O20: 281312.12 | P20: 194324.66 | Q20: 307690.22 | R20: 6979840.3 | S20: 12442.678 | T20: 117025.14 | U20: 21639.976 | V20: 23282.632 | W20: 474.03476 | X20: 35448.678 | Y20: 4870.9343 | Z20: 13675.259 | AA20: 93179.586 | AB20: 3543.7593 | AC20: 325582.68 | AD20: 20905250 | AE20: 652089.22 | AF20: 3334218.9 | AG20: 0 | AH20: 17219.018 | AI20: 16901723
C21: CARTERA DE CRÉDITOS INMOBILIARIO | D21: 234542.19 | E21: 493425.4 | F21: 1027038.3 | G21: 319773.32 | H21: 2074779.3 | I21: 59789.214 | J21: 164614.65 | K21: 0 | L21: 165.24921 | M21: 122344.14 | N21: 158044.86 | O21: 58965.077 | P21: 44128.033 | Q21: 0.039 | R21: 608051.26 | S21: 27477.263 | T21: 3524.8978 | U21: 0 | V21: 36.45572 | W21: 215.64684 | X21: 0 | Y21: 1431.3356 | Z21: 124.51966 | AA21: 31811.333 | AB21: 0 | AC21: 64621.452 | AD21: 2747452 | AE21: 158044.86 | AF21: 122545.84 | AG21: 0 | AH21: 124.51966 | AI21: 2466736.7
C22: CARTERA DE CRÉDITOS MICROCRÉDITO | D22: 454412.9 | E22: 16087.291 | F22: 2138789 | G22: 61045.377 | H22: 2670334.5 | I22: 14647.609 | J22: 832.86151 | K22: 0 | L22: 10668.973 | M22: 326.35863 | N22: 5871.7552 | O22: 146725.83 | P22: 9916.4967 | Q22: 321674.89 | R22: 510664.77 | S22: 160608.4 | T22: 5523.3881 | U22: 6864.8618 | V22: 1262.9036 | W22: 2215.6151 | X22: 17616.195 | Y22: 210.97519 | Z22: 45757.244 | AA22: 68861.711 | AB22: 150361.21 | AC22: 459282.51 | AD22: 3640281.8 | AE22: 5871.7552 | AF22: 12258.235 | AG22: 0 | AH22: 196118.45 | AI22: 3426033.4
C23: CARTERA DE CRÉDITOS VIVIENDA DE INTERÉS SOCIAL Y PÚBLICO | D23: 0 | E23: 3446.4834 | F23: 7456.3734 | G23: 0 | H23: 10902.857 | I23: 0 | J23: 0 | K23: 0 | L23: 0 | M23: 13648.626 | N23: 287.59108 | O23: 0 | P23: 0 | Q23: 0 | R23: 13936.217 | S23: 0 | T23: 0 | U23: 0 | V23: 0 | W23: 0 | X23: 0 | Y23: 0 | Z23: 0 | AA23: 0 | AB23: 0 | AC23: 0 | AD23: 24839.074 | AE23: 287.59108 | AF23: 13648.626 | AG23: 0 | AH23: 0 | AI23: 10902.857
C24: CARTERA DE CRÉDITOS EDUCATIVO | D24: 1645.4977 | E24: 120964.26 | F24: 35283.284 | G24: 923.1151 | H24: 158816.16 | I24: 0 | J24: 2366.2512 | K24: 0 | L24: 0 | M24: 0 | N24: 0 | O24: 201.72797 | P24: 1088.5446 | Q24: 0 | R24: 3656.5238 | S24: 18.31745 | T24: 0 | U24: 0 | V24: 0 | W24: 0 | X24: 0 | Y24: 0 | Z24: 0 | AA24: 0 | AB24: 0 | AC24: 18.31745 | AD24: 162491 | AE24: 0 | AF24: 0 | AG24: 0 | AH24: 0 | AI24: 162491
C25: CARTERA DE CRÉDITO INVERSIÓN PÚBLICA | D25: 0 | E25: 0 | F25: 0 | G25: 0 | H25: 0 | I25: 0 | J25: 0 | K25: 0 | L25: 0 | M25: 0 | N25: 0 | O25: 0 | P25: 0 | Q25: 0 | R25: 0 | S25: 0 | T25: 0 | U25: 0 | V25: 0 | W25: 0 | X25: 0 | Y25: 0 | Z25: 0 | AA25: 0 | AB25: 0 | AC25: 0 | AD25: 0 | AE25: 0 | AF25: 0 | AG25: 0 | AH25: 0 | AI25: 0
B26: 1499 | C26: (PROVISIONES PARA CRÉDITOS INCOBRABLES) | D26: -231531.14 | E26: -402837.4 | F26: -1589453 | G26: -307918.56 | H26: -2531740.1 | I26: -68513.545 | J26: -104229.89 | K26: -17099.176 | L26: -203552.87 | M26: -91018.961 | N26: -172496.92 | O26: -70913.112 | P26: -33948.116 | Q26: -59091.421 | R26: -820864.02 | S26: -19807.637 | T26: -9501.4245 | U26: -1168.3825 | V26: -2446.9707 | W26: -2461.1191 | X26: -1372.024 | Y26: -756.99973 | Z26: -2628.0504 | AA26: -18890.801 | AB26: -10306.078 | AC26: -69339.488 | AD26: -3421943.6 | AE26: -189596.1 | AF26: -297018.81 | AG26: 0 | AH26: -12934.129 | AI26: -2922394.6
B27: 149905 | C27: (CARTERA DE CRÉDITOS PRODUCTIVO) | D27: -41732.733 | E27: -34365.591 | F27: -194515.99 | G27: -54631.375 | H27: -325245.69 | I27: -9618.6555 | J27: -30273.017 | K27: -10540.852 | L27: -6258.6215 | M27: -4244.8688 | N27: -85523.52 | O27: -12788.548 | P27: -5754.0162 | Q27: -0.21375 | R27: -165002.31 | S27: -5709.7821 | T27: -2441.1925 | U27: -286.16102 | V27: -196.21416 | W27: -1504.7271 | X27: -5.15879 | Y27: -414.44065 | Z27: -181.69909 | AA27: -349.19616 | AB27: 0 | AC27: -11088.572 | AD27: -501336.57 | AE27: -96064.372 | AF27: -10699.704 | AG27: 0 | AH27: -181.69909 | AI27: -394390.8
B28: 149910 | C28: (CARTERA DE CRÉDITOS DE CONSUMO) | D28: -68781.819 | E28: -106673.07 | F28: -181697.96 | G28: -61204.987 | H28: -418357.83 | I28: -37128.988 | J28: -40321.758 | K28: 0 | L28: -81247.772 | M28: -23383.904 | N28: -42816.649 | O28: -13868.539 | P28: -6910.322 | Q28: -16958.915 | R28: -262636.85 | S28: -380.08334 | T28: -2923.4653 | U28: -326.5749 | V28: -1334.4586 | W28: -10.78273 | X28: -734.04847 | Y28: -85.20369 | Z28: -138.09892 | AA28: -5232.1398 | AB28: -57.70931 | AC28: -11222.565 | AD28: -692217.24 | AE28: -42816.649 | AF28: -105966.13 | AG28: 0 | AH28: -195.80823 | AI28: -543238.65
B29: 149915 | C29: (CARTERA DE CRÉDITOS INMOBILIARIO) | D29: -3484.6514 | E29: -12330.569 | F29: -23251.1 | G29: -7478.8135 | H29: -46545.134 | I29: -2050.7185 | J29: -2750.5634 | K29: 0 | L29: -1.65249 | M29: -1546.9414 | N29: -3412.6544 | O29: -1609.1182 | P29: -841.21033 | Q29: -0.039 | R29: -12212.898 | S29: -319.04922 | T29: -48.28478 | U29: 0 | V29: -0.001 | W29: -3.17951 | X29: 0 | Y29: -14.95018 | Z29: -1.2452 | AA29: -356.14642 | AB29: 0 | AC29: -742.85631 | AD29: -59500.888 | AE29: -3412.6544 | AF29: -1548.5948 | AG29: 0 | AH29: -1.2452 | AI29: -54538.393
B30: 149920 | C30: (CARTERA DE CRÉDITOS PARA MICROCRÉDITO) | D30: -16526.787 | E30: -137.60289 | F30: -107886.57 | G30: -1080.9833 | H30: -125631.94 | I30: -1214.7496 | J30: -27.64828 | K30: 0 | L30: -307.32671 | M30: -6.86466 | N30: -96.74495 | O30: -6220.9251 | P30: -845.07827 | Q30: -29286.644 | R30: -38005.982 | S30: -3107.6168 | T30: -68.77742 | U30: -83.84323 | V30: -78.85875 | W30: -30.534 | X30: -280.68769 | Y30: -2.57203 | Z30: -1425.8735 | AA30: -8002.4941 | AB30: -8030.5402 | AC30: -21111.798 | AD30: -184749.72 | AE30: -96.74495 | AF30: -393.05012 | AG30: 0 | AH30: -9456.4138 | AI30: -174803.51
B31: 149940 | C31: (CARTERA DE CRÉDITOS DE VIVIENDA DE INTERÉS SOCIAL Y PÚBLICO) | D31: 0 | E31: -189.13954 | F31: -74.94533 | G31: 0 | H31: -264.08487 | I31: 0 | J31: 0 | K31: 0 | L31: 0 | M31: -397.88229 | N31: -12.50762 | O31: 0 | P31: 0 | Q31: 0 | R31: -410.38991 | S31: 0 | T31: 0 | U31: 0 | V31: 0 | W31: 0 | X31: 0 | Y31: 0 | Z31: 0 | AA31: 0 | AB31: 0 | AC31: 0 | AD31: -674.47478 | AE31: -12.50762 | AF31: -397.88229 | AG31: 0 | AH31: 0 | AI31: -264.08487
B32: 149945 | C32: (CARTERA DE CRÉDITO REFINANCIADA) | D32: -17059.742 | E32: -7610.3775 | F32: -11980.384 | G32: -20740.573 | H32: -57391.077 | I32: -6745.3158 | J32: -345.32641 | K32: 0 | L32: -5551.1168 | M32: -4795.1819 | N32: -5909.8606 | O32: -4788.5451 | P32: -5570.1936 | Q32: -829.11982 | R32: -34534.66 | S32: -2837.2547 | T32: -1187.6849 | U32: -56.04126 | V32: -566.45645 | W32: -0.089 | X32: -22.35104 | Y32: -77.33441 | Z32: -368.85469 | AA32: -3491.8941 | AB32: -344.77727 | AC32: -8952.7378 | AD32: -100878.48 | AE32: -5909.8606 | AF32: -10912.755 | AG32: 0 | AH32: -713.63196 | AI32: -83342.228
B33: 149950 | C33: (CARTERA DE CRÉDITO REESTRUCTURADA) | D33: -23379.913 | E33: -70368.568 | F33: -222339.71 | G33: -86915.889 | H33: -403004.08 | I33: -11158.293 | J33: -7584.5643 | K33: 0 | L33: -52427.454 | M33: -3026.1385 | N33: -22832.995 | O33: -6285.8887 | P33: -9638.9799 | Q33: -1632.8685 | R33: -114587.18 | S33: -7452.3094 | T33: -2732.788 | U33: -20.23423 | V33: -235.99903 | W33: 0 | X33: -18.16046 | Y33: -39.49915 | Z33: -512.27893 | AA33: -1439.6768 | AB33: -94.31957 | AC33: -12545.266 | AD33: -530136.53 | AE33: -22832.995 | AF33: -55689.592 | AG33: 0 | AH33: -606.5985 | AI33: -451007.34
B34: 149955 | C34: (CARTERA DE CRÉDITO EDUCATIVO) | D34: -65.6053 | E34: -2908.3479 | F34: -774.78303 | G34: -27.85997 | H34: -3776.5961 | I34: 0 | J34: -62.67539 | K34: 0 | L34: 0 | M34: 0 | N34: 0 | O34: -4.4948 | P34: -13.3233 | Q34: 0 | R34: -80.49349 | S34: -1.54178 | T34: 0 | U34: 0 | V34: 0 | W34: 0 | X34: 0 | Y34: 0 | Z34: 0 | AA34: 0 | AB34: 0 | AC34: -1.54178 | AD34: -3858.6314 | AE34: 0 | AF34: 0 | AG34: 0 | AH34: 0 | AI34: -3858.6314
B35: 149960 | C35: (CARTERA DE CRÉDITO DE INVERSIÓN PÚBLICA) | D35: 0 | E35: 0 | F35: 0 | G35: 0 | H35: 0 | I35: 0 | J35: 0 | K35: 0 | L35: 0 | M35: 0 | N35: 0 | O35: 0 | P35: 0 | Q35: 0 | R35: 0 | S35: 0 | T35: 0 | U35: 0 | V35: 0 | W35: 0 | X35: 0 | Y35: 0 | Z35: 0 | AA35: 0 | AB35: 0 | AC35: 0 | AD35: 0 | AE35: 0 | AF35: 0 | AG35: 0 | AH35: 0 | AI35: 0
B36: 149980 | C36: PROVISIÓN GÉNERICA POR TECNOLOGÍA CREDITICIA | D36: 0 | E36: 0 | F36: 0 | G36: 0 | H36: 0 | I36: 0 | J36: 0 | K36: 0 | L36: 0 | M36: 0 | N36: 0 | O36: 0 | P36: 0 | Q36: 0 | R36: 0 | S36: 0 | T36: 0 | U36: 0 | V36: 0 | W36: 0 | X36: 0 | Y36: 0 | Z36: 0 | AA36: 0 | AB36: 0 | AC36: 0 | AD36: 0 | AE36: 0 | AF36: 0 | AG36: 0 | AH36: 0 | AI36: 0
B37: 149985 | C37: PROVISIÓN ANTICÍCLICA | D37: -1235.083 | E37: -8542.5028 | F37: -35611.827 | G37: -4035.0966 | H37: -49424.51 | I37: 0 | J37: -2340.338 | K37: 0 | L37: 0 | M37: -1007.8769 | N37: 0 | O37: 0 | P37: -305.00878 | Q37: 0 | R37: -3653.2236 | S37: 0 | T37: -37.79766 | U37: 0 | V37: -26.10029 | W37: 0 | X37: -29.38142 | Y37: -98.44362 | Z37: 0 | AA37: 0 | AB37: 0 | AC37: -191.72299 | AD37: -53269.456 | AE37: 0 | AF37: -1033.9771 | AG37: 0 | AH37: 0 | AI37: -52235.479
... B49: +1+4 | C49: TOTAL ACTIVO Y GASTOS | D49: 10723674 | E49: 10819535 | F49: 23941863 | G49: 9935022.6 | H49: 55420094 | I49: 3688634 | J49: 6652903.9 | K49: 849954.32 | L49: 3868918.7 | M49: 1541110 | N49: 6496440.4 | O49: 1103601.8 | P49: 1357910.1 | Q49: 917687.32 | R49: 26477160 | S49: 786439.26 | T49: 463058.42 | U49: 151904.26 | V49: 48121.282 | W49: 248872.9 | X49: 87055.749 | Y49: 44275.044 | Z49: 142695.9 | AA49: 376224.59 | AB49: 194708.43 | AC49: 2543355.8 | AD49: 84440611 | AE49: 7346394.7 | AF49: 5458149.9 | AG49: 0 | AH49: 337404.34 | AI49: 71298662
C51: PASIVOS
B52: 21 | C52: OBLIGACIONES CON EL PÚBLICO | D52: 7713105.9 | E52: 7847569.2 | F52: 17657367 | G52: 7218086.1 | H52: 40436128 | I52: 2851376.1 | J52: 4723713.8 | K52: 646608.33 | L52: 1836693.5 | M52: 1139618.6 | N52: 4950342.4 | O52: 827237.62 | P52: 1028061.9 | Q52: 342953.33 | R52: 18346606 | S52: 625854.49 | T52: 346735.32 | U52: 116051.07 | V52: 29376.024 | W52: 196738.7 | X52: 59356.148 | Y52: 22297.447 | Z52: 98133.093 | AA52: 258898.53 | AB52: 62058.228 | AC52: 1815499.1 | AD52: 60598233 | AE52: 5596950.7 | AF52: 3005688.1 | AG52: 0 | AH52: 160191.32 | AI52: 51835402
B53: 2101 | C53: Depósitos a la vista | D53: 4192096.6 | E53: 3510597 | F53: 11818453 | G53: 4086242 | H53: 23607388 | I53: 1427745.9 | J53: 2514328 | K53: 646524.08 | L53: 186163.69 | M53: 438605.41 | N53: 2690834 | O53: 452040.49 | P53: 532327.51 | Q53: 89338.118 | R53: 8977907.2 | S53: 360460.32 | T53: 123051.89 | U53: 47615.149 | V53: 16599.158 | W53: 108469.64 | X53: 4202.416 | Y53: 9151.0389 | Z53: 25688.659 | AA53: 130387.66 | AB53: 14515.083 | AC53: 840141.01 | AD53: 33425437 | AE53: 3337358.1 | AF53: 641368.26 | AG53: 0 | AH53: 40203.741 | AI53: 29406506
B54: 2102 | C54: Operaciones de reporto | D54: 0 | E54: 0 | F54: 0 | G54: 0 | H54: 0 | I54: 0 | J54: 0 | K54: 0 | L54: 0 | M54: 0 | N54: 0 | O54: 0 | P54: 0 | Q54: 0 | R54: 0 | S54: 0 | T54: 0 | U54: 0 | V54: 0 | W54: 0 | X54: 0 | Y54: 0 | Z54: 0 | AA54: 0 | AB54: 0 | AC54: 0 | AD54: 0 | AE54: 0 | AF54: 0 | AG54: 0 | AH54: 0 | AI54: 0
B55: 2103 | C55: Depósitos a plazo | D55: 3295802.3 | E55: 3847120.5 | F55: 5247556 | G55: 2919713.3 | H55: 15310192 | I55: 1353784 | J55: 2011367.4 | K55: 5.95 | L55: 1639135.4 | M55: 701000.27 | N55: 2092264.8 | O55: 375193.14 | P55: 461743.58 | Q55: 248351.03 | R55: 8882845.5 | S55: 253559.43 | T55: 213166.69 | U55: 57958.791 | V55: 12730.9 | W55: 86360.971 | X55: 55073.395 | Y55: 12334.459 | Z55: 72444.434 | AA55: 126275.91 | AB55: 47491.783 | AC55: 937396.75 | AD55: 25130434 | AE55: 2092270.7 | AF55: 2352866.6 | AG55: 0 | AH55: 119936.22 | AI55: 20565361
B56: 2104 | C56: Depósitos de garantía | D56: 0 | E56: 0 | F56: 327.28841 | G56: 0 | H56: 327.28841 | I56: 367.44913 | J56: 280.40321 | K56: 0 | L56: 0 | M56: 0 | N56: 67.7 | O56: 0 | P56: 0 | Q56: 0 | R56: 715.55234 | S56: 0 | T56: 4.17531 | U56: 0.3 | V56: 1 | W56: 0 | X56: 0 | Y56: 0 | Z56: 0 | AA56: 0 | AB56: 0 | AC56: 5.47531 | AD56: 1048.3161 | AE56: 67.7 | AF56: 1 | AG56: 0 | AH56: 0 | AI56: 979.61606
B57: 2105 | C57: Depósitos restringidos | D57: 225207.02 | E57: 489851.67 | F57: 591030.69 | G57: 212130.85 | H57: 1518220.2 | I57: 69478.808 | J57: 197737.97 | K57: 78.3 | L57: 11394.379 | M57: 12.949 | N57: 167175.86 | O57: 4 | P57: 33990.797 | Q57: 5264.1824 | R57: 485137.25 | S57: 11834.745 | T57: 10512.568 | U57: 10476.832 | V57: 44.96515 | W57: 1908.0851 | X57: 80.33612 | Y57: 811.94962 | Z57: 0 | AA57: 2234.9689 | AB57: 51.36184 | AC57: 37955.812 | AD57: 2041313.3 | AE57: 167254.16 | AF57: 11452.293 | AG57: 0 | AH57: 51.36184 | AI57: 1862555.5
B58: 22 | C58: OPERACIONES INTERBANCARIAS | D58: 0 | E58: 0 | F58: 0 | G58: 0 | H58: 0 | I58: 0 | J58: 0 | K58: 0 | L58: 0 | M58: 0 | N58: 0 | O58: 0 | P58: 0 | Q58: 0 | R58: 0 | S58: 0 | T58: 0 | U58: 0 | V58: 0 | W58: 0 | X58: 0 | Y58: 0 | Z58: 0 | AA58: 0 | AB58: 0 | AC58: 0 | AD58: 0 | AE58: 0 | AF58: 0 | AG58: 0 | AH58: 0 | AI58: 0
B59: 23 | C59: OBLIGACIONES INMEDIATAS | D59: 5457.2162 | E59: 24336.266 | F59: 16552.123 | G59: 9085.53 | H59: 55431.135 | I59: 4606.9374 | J59: 12530.115 | K59: 54.1 | L59: 0 | M59: 1415.0106 | N59: 11257.116 | O59: 1022.8716 | P59: 294.86238 | Q59: 0 | R59: 31181.013 | S59: 13.57879 | T59: 671.804 | U59: 3.31 | V59: 55.31714 | W59: 486.47099 | X59: 802.23113 | Y59: 1285.5184 | Z59: 6.5773 | AA59: 174.29843 | AB59: 0 | AC59: 3499.1062 | AD59: 90111.254 | AE59: 11311.216 | AF59: 1470.3277 | AG59: 0 | AH59: 6.5773 | AI59: 77323.133
B60: 24 | C60: ACEPTACIONES EN CIRCULACIÓN | D60: 0 | E60: 332.8332 | F60: 1087.3472 | G60: 0 | H60: 1420.1804 | I60: 0 | J60: 58855.916 | K60: 0 | L60: 0 | M60: 0 | N60: 0 | O60: 0 | P60: 0 | Q60: 0 | R60: 58855.916 | S60: 0 | T60: 0 | U60: 0 | V60: 0 | W60: 0 | X60: 0 | Y60: 0 | Z60: 0 | AA60: 0 | AB60: 0 | AC60: 0 | AD60: 60276.096 | AE60: 0 | AF60: 0 | AG60: 0 | AH60: 0 | AI60: 60276.096
B61: 25 | C61: CUENTAS POR PAGAR | D61: 282410.12 | E61: 317497.78 | F61: 509722.2 | G61: 228651.48 | H61: 1338281.6 | I61: 69941.88 | J61: 154659.04 | K61: 42891.943 | L61: 646622.41 | M61: 37877.472 | N61: 196415.07 | O61: 18196.082 | P61: 23096.324 | Q61: 32428.159 | R61: 1222128.4 | S61: 14466.532 | T61: 10691.288 | U61: 2121.0471 | V61: 1538.9494 | W61: 4024.7711 | X61: 4924.5173 | Y61: 3265.2012 | Z61: 1869.7008 | AA61: 10447.686 | AB61: 6063.4662 | AC61: 59413.16 | AD61: 2619823.1 | AE61: 239307.01 | AF61: 686038.84 | AG61: 0 | AH61: 7933.167 | AI61: 1686544.1
B62: 26 | C62: OBLIGACIONES FINANCIERAS | D62: 710155.9 | E62: 517025.45 | F62: 786227.86 | G62: 654202.75 | H62: 2667612 | I62: 137604.8 | J62: 367030.76 | K62: 0 | L62: 158333.33 | M62: 52036.033 | N62: 297968.79 | O62: 60267.524 | P62: 82051.947 | Q62: 229714.06 | R62: 1385007.2 | S62: 13000.667 | T62: 10184.508 | U62: 0 | V62: 0 | W62: 0 | X62: 0 | Y62: 0 | Z62: 12000 | AA62: 28119.053 | AB62: 70710.939 | AC62: 134015.17 | AD62: 4186634.4 | AE62: 297968.79 | AF62: 210369.37 | AG62: 0 | AH62: 82710.939 | AI62: 3595585.3
B63: 2601 | C63: Sobregiros | D63: 0 | E63: 0 | F63: 30.63444 | G63: 31.87484 | H63: 62.50928 | I63: 0 | J63: 0 | K63: 0 | L63: 0 | M63: 0 | N63: 0 | O63: 0 | P63: 0 | Q63: 0 | R63: 0 | S63: 0 | T63: 0 | U63: 0 | V63: 0 | W63: 0 | X63: 0 | Y63: 0 | Z63: 0 | AA63: 0 | AB63: 0 | AC63: 0 | AD63: 62.50928 | AE63: 0 | AF63: 0 | AG63: 0 | AH63: 0 | AI63: 62.50928
... B77: 2 | C77: TOTAL PASIVOS | D77: 8813834.7 | E77: 8764021.4 | F77: 19331677 | G77: 8362070.7 | H77: 45271603 | I77: 3078390.2 | J77: 5576518.5 | K77: 690837.14 | L77: 2714086.5 | M77: 1255990.6 | N77: 5475944.3 | O77: 914818.88 | P77: 1156629.5 | Q77: 616580.41 | R77: 21479796 | S77: 665281.14 | T77: 376292.74 | U77: 120451.51 | V77: 31147.688 | W77: 201300.46 | X77: 65567.478 | Y77: 27001.861 | Z77: 112055.39 | AA77: 299198.1 | AB77: 138960.77 | AC77: 2037257.1 | AD77: 68788657 | AE77: 6166781.4 | AF77: 4001224.8 | AG77: 0 | AH77: 251016.16 | AI77: 58369634
C79: PATRIMONIO
B80: 31 | C80: CAPITAL SOCIAL | D80: 646103 | E80: 645966.04 | F80: 1457000 | G80: 547720 | H80: 3296789 | I80: 199570 | J80: 445000 | K80: 76065.364 | L80: 400000 | M80: 101836.15 | N80: 413420.07 | O80: 61527 | P80: 71946 | Q80: 111107.14 | R80: 1880471.7 | S80: 52979 | T80: 35465.01 | U80: 15763.1 | V80: 11210.657 | W80: 24866.788 | X80: 16050 | Y80: 11671.864 | Z80: 14920 | AA80: 28587.8 | AB80: 20456.1 | AC80: 231970.32 | AD80: 5409231.1 | AE80: 489485.43 | AF80: 513046.8 | AG80: 0 | AH80: 35376.1 | AI80: 4371322.7
B81: 32 | C81: PRIMA O DESCUENTO EN COLOCACIÓN DE ACCIONES Y CERTIFICADOS | D81: 0 | E81: 0 | F81: 0 | G81: 1104.7742 | H81: 1104.7742 | I81: 0 | J81: 0 | K81: 0 | L81: 0 | M81: 0 | N81: 0 | O81: 0 | P81: 0 | Q81: 0 | R81: 0 | S81: 0 | T81: 0 | U81: 0 | V81: 0 | W81: 0 | X81: 0 | Y81: 0 | Z81: 0 | AA81: 0 | AB81: 0 | AC81: 0 | AD81: 1104.7742 | AE81: 0 | AF81: 0 | AG81: 0 | AH81: 0 | AI81: 1104.7742
B82: 33 | C82: RESERVAS | D82: 115381.91 | E82: 188231.56 | F82: 250811.48 | G82: 81804.755 | H82: 636229.71 | I82: 32148.79 | J82: 70802.591 | K82: 15264.911 | L82: 129064.91 | M82: 15096.543 | N82: 72148.686 | O82: 12416.478 | P82: 6573.5098 | Q82: 24191.601 | R82: 377708.02 | S82: 1605.2066 | T82: 1631.8686 | U82: 1290.7258 | V82: 444.27202 | W82: 7933.0288 | X82: 0 | Y82: 113.81248 | Z82: 0 | AA82: 3530.119 | AB82: 1796.5487 | AC82: 18345.582 | AD82: 1032283.3 | AE82: 87413.597 | AF82: 144605.73 | AG82: 0 | AH82: 1796.5487 | AI82: 798467.45
B83: 34 | C83: OTROS APORTES PATRIMONIALES | D83: 0 | E83: 0 | F83: 0 | G83: 0 | H83: 0 | I83: 0 | J83: 0 | K83: 0 | L83: 0 | M83: 0 | N83: 0 | O83: 0 | P83: 0 | Q83: 15.58852 | R83: 15.58852 | S83: 0 | T83: 0 | U83: 0 | V83: 0 | W83: 3.16971 | X83: 0 | Y83: 0 | Z83: 0 | AA83: 1535.061 | AB83: 144.09247 | AC83: 1682.3232 | AD83: 1697.9117 | AE83: 0 | AF83: 0 | AG83: 0 | AH83: 144.09247 | AI83: 1553.8193
B84: 35 | C84: SUPERÁVIT POR VALUACIONES | D84: 6705.6929 | E84: 65367.202 | F84: 161865.74 | G84: 8676.9169 | H84: 242615.55 | I84: 29757.241 | J84: 21578.533 | K84: 1067.097 | L84: 23646.185 | M84: 2023.9393 | N84: 18525.075 | O84: 3257.3344 | P84: 6870.1418 | Q84: 7914.1017 | R84: 114639.65 | S84: 0 | T84: 2974.3567 | U84: 1162.975 | V84: 176.63638 | W84: 1417.0109 | X84: 6.0791 | Y84: 8.59529 | Z84: -1368.8243 | AA84: 2157.3641 | AB84: 0 | AC84: 6534.1932 | AD84: 363789.4 | AE84: 19592.172 | AF84: 25846.761 | AG84: 0 | AH84: -1368.8243 | AI84: 319719.29
B85: 36 | C85: RESULTADOS | D85: 152659.43 | E85: 213630.2 | F85: 341416.21 | G85: 85515.938 | H85: 793221.78 | I85: 24889.368 | J85: 71144.505 | K85: 21616.434 | L85: 43256.422 | M85: 15590.726 | N85: 68821.342 | O85: 12566.328 | P85: 7474.6448 | Q85: 5511.0957 | R85: 270870.86 | S85: -9562.9168 | T85: 1355.5237 | U85: 36.09948 | V85: -52.71861 | W85: 464.69839 | X85: -5512.3066 | Y85: 9.96105 | Z85: -1584.5641 | AA85: 3071.0303 | AB85: 4509.1458 | AC85: -7266.0473 | AD85: 1056826.6 | AE85: 90437.776 | AF85: 58794.429 | AG85: 0 | AH85: 2924.5817 | AI85: 904669.81
B86: 3601 | C86: Utilidades o excedentes acumulados | D86: 0 | E86: 7498.7294 | F86: 100918.32 | G86: 242.83666 | H86: 108659.89 | I86: 1382.8492 | J86: 475.49953 | K86: 0 | L86: 208.11048 | M86: 363.82954 | N86: 678.68028 | O86: 1999.7024 | P86: 121.54472 | Q86: 2674.4217 | R86: 7904.6378 | S86: 0 | T86: 0 | U86: 13.30036 | V86: 0 | W86: 0 | X86: 0 | Y86: 0 | Z86: 0 | AA86: 1063.5298 | AB86: 0 | AC86: 1076.8302 | AD86: 117641.36 | AE86: 678.68028 | AF86: 571.94002 | AG86: 0 | AH86: 0 | AI86: 116390.74
B87: 3602 | C87: (Pérdidas acumuladas) | D87: 0 | E87: 0 | F87: 0 | G87: 0 | H87: 0 | I87: 0 | J87: 0 | K87: 0 | L87: 0 | M87: 0 | N87: 0 | O87: 0 | P87: 0 | Q87: 0 | R87: 0 | S87: 0 | T87: 0 | U87: 0 | V87: -235.96543 | W87: 0 | X87: -5421.4789 | Y87: 0 | Z87: -1600.0684 | AA87: 0 | AB87: 0 | AC87: -7257.5128 | AD87: -7257.5128 | AE87: 0 | AF87: -235.96543 | AG87: 0 | AH87: -1600.0684 | AI87: -5421.4789
B88: 3603 | C88: Utilidad o excedente del ejercicio | D88: 152659.43 | E88: 206131.47 | F88: 240497.89 | G88: 85273.102 | H88: 684561.89 | I88: 23506.519 | J88: 70669.005 | K88: 21616.434 | L88: 43048.312 | M88: 15226.897 | N88: 68142.661 | O88: 10566.626 | P88: 7353.1001 | Q88: 2836.6739 | R88: 262966.23 | S88: 0 | T88: 1355.5237 | U88: 22.79912 | V88: 183.24682 | W88: 464.69839 | X88: 0 | Y88: 9.96105 | Z88: 15.50429 | AA88: 2007.5005 | AB88: 4509.1458 | AC88: 8568.3797 | AD88: 956096.5 | AE88: 89759.095 | AF88: 58458.455 | AG88: 0 | AH88: 4524.6501 | AI88: 803354.3
B89: 3604 | C89: (Pérdida del ejercicio) | D89: 0 | E89: 0 | F89: 0 | G89: 0 | H89: 0 | I89: 0 | J89: 0 | K89: 0 | L89: 0 | M89: 0 | N89: 0 | O89: 0 | P89: 0 | Q89: 0 | R89: 0 | S89: -9562.9168 | T89: 0 | U89: 0 | V89: 0 | W89: 0 | X89: -90.8276 | Y89: 0 | Z89: 0 | AA89: 0 | AB89: 0 | AC89: -9653.7444 | AD89: -9653.7444 | AE89: 0 | AF89: 0 | AG89: 0 | AH89: 0 | AI89: -9653.7444
B90: 37 | C90: (DESVALORIZACIÓN DEL PATRIMONIO) | D90: 0 | E90: 0 | F90: 0 | G90: 0 | H90: 0 | I90: 0 | J90: 0 | K90: 0 | L90: 0 | M90: 0 | N90: 0 | O90: 0 | P90: 0 | Q90: 0 | R90: 0 | S90: 0 | T90: 0 | U90: 0 | V90: 0 | W90: 0 | X90: 0 | Y90: 0 | Z90: 0 | AA90: 0 | AB90: 0 | AC90: 0 | AD90: 0 | AE90: 0 | AF90: 0 | AG90: 0 | AH90: 0 | AI90: 0
B91: 3 | C91: TOTAL PATRIMONIO | D91: 920850.04 | E91: 1113195 | F91: 2211093.4 | G91: 724822.38 | H91: 4969960.9 | I91: 286365.4 | J91: 608525.63 | K91: 114013.81 | L91: 595967.52 | M91: 134547.35 | N91: 572915.17 | O91: 89767.141 | P91: 92864.296 | Q91: 148739.53 | R91: 2643705.8 | S91: 45021.29 | T91: 41426.759 | U91: 18252.9 | V91: 11778.847 | W91: 34684.696 | X91: 10543.773 | Y91: 11804.233 | Z91: 11966.612 | AA91: 38881.374 | AB91: 26905.887 | AC91: 251266.37 | AD91: 7864933.1 | AE91: 686928.98 | AF91: 742293.72 | AG91: 0 | AH91: 38872.499 | AI91: 6396837.9
... B100: 7 | C100: CUENTAS DE ORDEN | D100: 26886091 | E100: 20374641 | F100: 51364506 | G100: 13679927 | H100: 1.1230516e+08 | I100: 8957802.7 | J100: 8314979.3 | K100: 2365960.3 | L100: 7609883.4 | M100: 3138755.4 | N100: 24724681 | O100: 2002688.3 | P100: 2597954.3 | Q100: 1891109.5 | R100: 61603814 | S100: 2451947.8 | T100: 1118810.7 | U100: 268735.83 | V100: 125210.97 | W100: 145022.59 | X100: 359737.81 | Y100: 168191.18 | Z100: 192595.17 | AA100: 1155810 | AB100: 406529.02 | AC100: 6392591 | AD100: 1.8030157e+08 | AE100: 27090641 | AF100: 10873850 | AG100: 0 | AH100: 599124.19 | AI100: 1.4173795e+08

Sheet RK
B3: RANKING EN BASE A LA PARTICIPACIÓN DE LAS PRINCIPALES CUENTAS DEL BALANCE
B4: SISTEMA DE BANCOS PRIVADOS
B5: 31/12/2025
B6: (en miles de dólares y porcentajes)
C8: ACTIVOS | J8: PASIVOS
B9: ENTIDADES | C9: November 2025 (USD) | D9: November 2025 (%) | E9: December 2025 (USD) | F9: December 2025 (%) | I9: ENTIDADES | J9: November 2025 (USD) | K9: November 2025 (%) | L9: December 2025 (USD) | M9: December 2025 (%)
B10: BP PICHINCHA | C10: 21495772 | D10: 0.28401324 | E10: 21542770 | F10: 0.28104059 | I10: BP PICHINCHA | J10: 19331002 | K10: 0.28447858 | L10: 19331677 | M10: 0.28103001
B11: BP PACIFICO | C11: 9688491.1 | D11: 0.12800935 | E11: 9877216.4 | F11: 0.12885524 | I11: BP GUAYAQUIL | J11: 8702673.5 | K11: 0.12807014 | L11: 8813834.7 | M11: 0.12812919
B12: BP GUAYAQUIL | C12: 9601851 | D12: 0.12686461 | E12: 9734684.7 | F12: 0.12699581 | I12: BP PACIFICO | J12: 8601640.7 | K12: 0.12658332 | L12: 8764021.4 | M12: 0.12740504
B13: BP PRODUBANCO | C13: 8767205.3 | D13: 0.11583684 | E13: 9086893.1 | F13: 0.11854491 | I13: BP PRODUBANCO | J13: 8053121.3 | K13: 0.11851121 | L13: 8362070.7 | M13: 0.12156177
B14: BP BOLIVARIANO | C14: 6156726.8 | D14: 0.081345853 | E14: 6185044.1 | F14: 0.080688252 | I14: BP BOLIVARIANO | J14: 5557458.1 | K14: 0.081784574 | L14: 5576518.5 | M14: 0.081067414
B15: BP INTERNACIONAL | C15: 5846623.6 | D15: 0.077248611 | E15: 6048859.5 | F15: 0.078911627 | I15: BP INTERNACIONAL | J15: 5280323.5 | K15: 0.077706211 | L15: 5475944.3 | M15: 0.079605338
B16: BP AUSTRO | C16: 3327242.3 | D16: 0.043961243 | E16: 3364755.6 | F16: 0.043895604 | I16: BP AUSTRO | J16: 3043639.9 | K16: 0.044790764 | L16: 3078390.2 | M16: 0.044751422
B17: BP DINERS | C17: 3358091.2 | D17: 0.044368835 | E17: 3310054 | F17: 0.043181983 | I17: BP DINERS | J17: 2764555.5 | K17: 0.040683706 | L17: 2714086.5 | M17: 0.039455436
B18: BP GENERAL RUMIÑAHUI | C18: 1414528.4 | D18: 0.01868948 | E18: 1390538 | F18: 0.018140546 | I18: BP GENERAL RUMIÑAHUI | J18: 1281149.8 | K18: 0.018853636 | L18: 1255990.6 | M18: 0.018258688
B19: BP MACHALA | C19: 1227737.7 | D19: 0.016221505 | E19: 1249493.8 | F19: 0.016300525 | I19: BP MACHALA | J19: 1135996.4 | K19: 0.016717532 | L19: 1156629.5 | M19: 0.016814247
B20: BP LOJA | C20: 1005780 | D20: 0.013288884 | E20: 1004586 | F20: 0.013105531 | I20: BP LOJA | J20: 916013.54 | K20: 0.013480224 | L20: 914818.88 | M20: 0.013298979
B21: BP CITIBANK | C21: 752492.23 | D21: 0.0099423159 | E21: 804850.94 | F21: 0.010499847 | I21: BP CITIBANK | J21: 638658.62 | K21: 0.0093986175 | L21: 690837.14 | M21: 0.010042893
... B37: BANCOS PRIVADOS PEQUEÑOS | C37: 2280142.3 | D37: 0.030126418 | E37: 2288523.5 | F37: 0.029855399 | I37: BANCOS PRIVADOS PEQUEÑOS | J37: 2030240.6 | K37: 0.029877393 | L37: 2037257.1 | M37: 0.029616179
C39: PATRIMONIO | J39: INVERSIONES
B40: ENTIDADES | C40: November 2025 (USD) | D40: November 2025 (%) | E40: December 2025 (USD) | F40: December 2025 (%) | I40: ENTIDADES | J40: November 2025 (USD) | K40: November 2025 (%) | L40: December 2025 (USD) | M40: December 2025 (%)
B41: BP PICHINCHA | C41: 1968297.7 | D41: 0.28467666 | E41: 2211093.4 | F41: 0.28113315 | I41: BP PICHINCHA | J41: 4987945 | K41: 0.3587179 | L41: 4537382 | M41: 0.33253411
B42: BP PACIFICO | C42: 906798.77 | D42: 0.13115112 | E42: 1113195 | F42: 0.14153903 | I42: BP PACIFICO | J42: 1877101.5 | K42: 0.13499546 | L42: 1918156.4 | M42: 0.14057719
B43: BP GUAYAQUIL | C43: 768159.17 | D43: 0.11109955 | E43: 920850.04 | F43: 0.11708301 | I43: BP PRODUBANCO | J43: 1259017.8 | K43: 0.090544749 | L43: 1541595.9 | M43: 0.11297996
B44: BP PRODUBANCO | C44: 637745.56 | D44: 0.092237711 | E44: 724822.38 | F44: 0.092158748 | I44: BP GUAYAQUIL | J44: 1662051.5 | K44: 0.11952971 | L44: 1510918.9 | M44: 0.11073171
B45: BP BOLIVARIANO | C45: 537236.01 | D45: 0.077700925 | E45: 608525.63 | F45: 0.077372003 | I45: BP BOLIVARIANO | J45: 1124555 | K45: 0.080874587 | L45: 1113978.3 | M45: 0.08164086
B46: BP DINERS | C46: 552469.57 | D46: 0.079904169 | E46: 595967.52 | F46: 0.075775282 | I46: BP INTERNACIONAL | J46: 787628.25 | K46: 0.056643839 | L46: 784545.84 | M46: 0.057497529
B47: BP INTERNACIONAL | C47: 504741.41 | D47: 0.073001202 | E47: 572915.17 | F47: 0.072844253 | I47: BP AUSTRO | J47: 643266.31 | K47: 0.046261765 | L47: 674002.39 | M47: 0.049396058
B48: BP AUSTRO | C48: 262743.58 | D48: 0.038000839 | E48: 286365.4 | F48: 0.036410405 | I48: BP DINERS | J48: 290634.29 | K48: 0.020901538 | L48: 270189.05 | M48: 0.019801523
B49: BP SOLIDARIO | C49: 145855.78 | D49: 0.021095252 | E49: 148739.53 | F49: 0.018911734 | I49: BP CITIBANK | J49: 240323.86 | K49: 0.017283364 | L49: 256183.35 | M49: 0.018775078
B50: BP GENERAL RUMIÑAHUI | C50: 119378.42 | D50: 0.017265807 | E50: 134547.35 | F50: 0.017107247 | I50: BP GENERAL RUMIÑAHUI | J50: 231384.47 | K50: 0.016640471 | L50: 234314.66 | M50: 0.017172373
B51: BP CITIBANK | C51: 93060.11 | D51: 0.013459367 | E51: 114013.81 | F51: 0.014496475 | I51: BP MACHALA | J51: 159750.3 | K51: 0.011488758 | L51: 151715.07 | M51: 0.011118843
B52: BP MACHALA | C52: 85512.475 | D52: 0.012367746 | E52: 92864.296 | F52: 0.011807385 | I52: BP LOJA | J52: 130748.12 | K52: 0.0094030088 | L52: 135627.84 | M52: 0.0099398471
... B68: BANCOS PRIVADOS PEQUEÑOS | C68: 252953.7 | D68: 0.036584921 | E68: 251266.37 | F68: 0.031947681 | I68: BANCOS PRIVADOS PEQUEÑOS | J68: 437773.57 | K68: 0.03148 | L68: 447114.47 | M68: 0.003277
C70: CARTERA | J70: DEPOSITOS A LA VISTA
B71: ENTIDADES | C71: November 2025 (USD) | D71: November 2025 (%) | E71: December 2025 (USD) | F71: December 2025 (%) | I71: ENTIDADES | J71: November 2025 (USD) | K71: November 2025 (%) | L71: December 2025 (USD) | M71: December 2025 (%)
B72: BP PICHINCHA | C72: 12314427 | D72: 0.25752527 | E72: 12266551 | F72: 0.25483199 | I72: BP PICHINCHA | J72: 11575385 | K72: 0.35754514 | L72: 11818453 | M72: 0.35357662
B73: BP GUAYAQUIL | C73: 6436678.2 | D73: 0.13460694 | E73: 6585926.5 | F73: 0.13681961 | I73: BP GUAYAQUIL | J73: 4122118 | K73: 0.12732564 | L73: 4192096.6 | M73: 0.12541636
B74: BP PACIFICO | C74: 6056029.6 | D74: 0.12664663 | E74: 6103558.6 | F74: 0.12679864 | I74: BP PRODUBANCO | J74: 3790353 | K74: 0.11707795 | L74: 4086242 | M74: 0.12224947
B75: BP PRODUBANCO | C75: 5999587.9 | D75: 0.12546629 | E75: 6089793.8 | F75: 0.12651268 | I75: BP PACIFICO | J75: 3374199.6 | K75: 0.10422363 | L75: 3510597 | M75: 0.10502771
B76: BP BOLIVARIANO | C76: 4065930.9 | D76: 0.085028719 | E76: 4115549.2 | F76: 0.085498652 | I76: BP INTERNACIONAL | J76: 2544877.7 | K76: 0.078607206 | L76: 2690834 | M76: 0.080502584
B77: BP INTERNACIONAL | C77: 4118570.7 | D77: 0.08612955 | E77: 4096060.6 | F77: 0.085093784 | I77: BP BOLIVARIANO | J77: 2500297.6 | K77: 0.077230195 | L77: 2514328 | M77: 0.075221994
B78: BP DINERS | C78: 2549738.9 | D78: 0.053321377 | E78: 2547193.3 | F78: 0.052916776 | I78: BP AUSTRO | J78: 1384908.3 | K78: 0.042777604 | L78: 1427745.9 | M78: 0.042714354
B79: BP AUSTRO | C79: 1766000.3 | D79: 0.036931455 | E79: 1775068.3 | F79: 0.036876231 | I79: BP CITIBANK | J79: 591703.35 | K79: 0.018276771 | L79: 646524.08 | M79: 0.019342278
B80: BP GENERAL RUMIÑAHUI | C80: 877483.14 | D80: 0.018350353 | E80: 888580.91 | F80: 0.018459862 | I80: BP MACHALA | J80: 517870.34 | K80: 0.015996187 | L80: 532327.51 | M80: 0.015925821
B81: BP MACHALA | C81: 788501.28 | D81: 0.016489521 | E81: 795439.06 | F81: 0.016524882 | I81: BP LOJA | J81: 425104.98 | K81: 0.013130813 | L81: 452040.49 | M81: 0.013523847
B82: BP LOJA | C82: 609875.99 | D82: 0.012754023 | E82: 605930.12 | F82: 0.012587921 | I82: BP GENERAL RUMIÑAHUI | J82: 455634.32 | K82: 0.014073816 | L82: 438605.41 | M82: 0.013121905
B83: BP SOLIDARIO | C83: 564039.64 | D83: 0.011795471 | E83: 570293.23 | F83: 0.011847581 | I83: BP PROCREDIT | J83: 345747.14 | K83: 0.010679577 | L83: 360460.32 | M83: 0.010784012
... B99: BANCOS PRIVADOS PEQUEÑOS | C99: 1338357.5 | D99: 0.027988381 | E99: 1349981.4 | F99: 0.028045245 | I99: BANCOS PRIVADOS PEQUEÑOS | J99: 827038.57 | K99: 0.0255459 | L99: 840141.01 | M99: 0.02513478
C101: DEPOSITOS A PLAZO | J101: CAPITAL Y RESERVAS
B102: ENTIDADES | C102: November 2025 (USD) | D102: November 2025 (%) | E102: December 2025 (USD) | F102: December 2025 (%) | I102: ENTIDADES | J102: November 2025 (USD) | K102: November 2025 (%) | L102: December 2025 (USD) | M102: December 2025 (%)
B103: BP PICHINCHA | C103: 5339690 | D103: 0.21438863 | E103: 5247556 | F103: 0.20881278 | I103: BP PICHINCHA | J103: 1707811.5 | K103: 0.26512577 | L103: 1707811.5 | M103: 0.26512577
B104: BP PACIFICO | C104: 3757607.2 | D104: 0.15086798 | E104: 3847120.5 | F104: 0.15308611 | I104: BP PACIFICO | J104: 834197.61 | K104: 0.12950334 | L104: 834197.61 | M104: 0.12950334
B105: BP GUAYAQUIL | C105: 3276796.4 | D105: 0.13156342 | E105: 3295802.3 | F105: 0.13114784 | I105: BP GUAYAQUIL | J105: 761484.91 | K105: 0.1182152 | L105: 761484.91 | M105: 0.1182152
B106: BP PRODUBANCO | C106: 2814528.7 | D106: 0.11300337 | E106: 2919713.3 | F106: 0.11618236 | I106: BP PRODUBANCO | J106: 629524.75 | K106: 0.09772931 | L106: 629524.75 | M106: 0.09772931
B107: BP INTERNACIONAL | C107: 2019629.6 | D107: 0.08108816 | E107: 2092264.8 | F107: 0.083256212 | I107: BP DINERS | J107: 529064.91 | K107: 0.082133622 | L107: 529064.91 | M107: 0.082133622
B108: BP BOLIVARIANO | C108: 1994332.8 | D108: 0.080072493 | E108: 2011367.4 | F108: 0.080037114 | I108: BP BOLIVARIANO | J108: 515802.59 | K108: 0.08007474 | L108: 515802.59 | M108: 0.08007474
B109: BP DINERS | C109: 1616010.8 | D109: 0.064882859 | E109: 1639135.4 | F109: 0.065225113 | I109: BP INTERNACIONAL | J109: 485568.76 | K109: 0.075381149 | L109: 485568.76 | M109: 0.075381149
B110: BP AUSTRO | C110: 1347401 | D110: 0.05409817 | E110: 1353784 | F110: 0.053870297 | I110: BP AUSTRO | J110: 231718.79 | K110: 0.035972719 | L110: 231718.79 | M110: 0.035972719
B111: BP GENERAL RUMIÑAHUI | C111: 702430.91 | D111: 0.028202611 | E111: 701000.27 | F111: 0.027894475 | I111: BP SOLIDARIO | J111: 135298.74 | K111: 0.021004182 | L111: 135298.74 | M111: 0.021004182
B112: BP MACHALA | C112: 451739.82 | D112: 0.01813736 | E112: 461743.58 | F112: 0.01837388 | I112: BP GENERAL RUMIÑAHUI | J112: 116932.69 | K112: 0.018152981 | L112: 116932.69 | M112: 0.018152981
B113: BP LOJA | C113: 384367.26 | D113: 0.015432351 | E113: 375193.14 | F113: 0.014929831 | I113: BP CITIBANK | J113: 91330.275 | K113: 0.014178386 | L113: 91330.275 | M113: 0.014178386
B114: BP PROCREDIT | C114: 267340.1 | D114: 0.010733709 | E114: 253559.43 | F114: 0.010089735 | I114: BP MACHALA | J114: 78519.51 | K114: 0.012189604 | L114: 78519.51 | M114: 0.012189604
... B130: BANCOS PRIVADOS PEQUEÑOS | C130: 950852.96 | D130: 0.03817676 | E130: 937396.75 | F130: 0.037301256 | I130: BANCOS PRIVADOS PEQUEÑOS | J130: 250315.9 | K130: 0.038859791 | L130: 250315.9 | M130: 0.038859791
C132: RESULTADOS
B133: ENTIDADES | C133: November 2025 (USD) | D133: November 2025 (%) | E133: December 2025 (USD) | F133: December 2025 (%)
B134: BP PICHINCHA | C134: 196471.97 | D134: 0.23981718 | E134: 240497.89 | F134: 0.25410716
B135: BP PACIFICO | C135: 180051.67 | D135: 0.21977427 | E135: 206131.47 | F135: 0.21779603
B136: BP GUAYAQUIL | C136: 131018.32 | D136: 0.15992329 | E136: 152659.43 | F136: 0.16129811
B137: BP PRODUBANCO | C137: 76338.504 | D137: 0.093180135 | E137: 85273.102 | F137: 0.090098531
B138: BP BOLIVARIANO | C138: 62032.655 | D138: 0.075718162 | E138: 70669.005 | F138: 0.074668018
B139: BP INTERNACIONAL | C139: 61558.713 | D139: 0.07513966 | E139: 68142.661 | F139: 0.071998714
B140: BP DINERS | C140: 41066.156 | D140: 0.05012608 | E140: 43048.312 | F140: 0.045484327
B141: BP AUSTRO | C141: 20858.802 | D141: 0.025460625 | E141: 23506.519 | F141: 0.024836704
B142: BP CITIBANK | C142: 20773.501 | D142: 0.025356505 | E142: 21616.434 | F142: 0.022839663
B143: BP GENERAL RUMIÑAHUI | C143: 14000.212 | D143: 0.017088907 | E143: 15226.897 | F143: 0.016088555
B144: BP LOJA | C144: 10566.626 | D144: 0.012897812 | E144: 10566.626 | F144: 0.01116457
B145: BP MACHALA | C145: 6228.7823 | D145: 0.0076029625 | E145: 7353.1001 | F145: 0.0077691968
... B161: BANCOS PRIVADOS PEQUEÑOS | C161: -3051.9297 | D161: -0.0037252397 | E161: -1085.3647 | F161: -0.0011467833
B163: Fuente: Estados de situación remitidos por las entidades / Sistema de Administración de Balances (S.A.B.)
B164: Elaboración: Dirección de Estudios y Gestión de la Información / Subdirección de Estadísticas y Estudios/OM
B165: Nota: Agrupación de entidades en base a su participación en el Activo Total.
B166: Grandes (Mayor al 10%)
B167: Medianas (Entre el 1%% y 10%)
B168: Pequeñas (Menor al 1%)
B169: Fecha de consolidación: 06-08-2020
B170: Código Orgánico Monetario y Financiero Art 162 : Composición del sector financiero privado, Bancos Múltiple y Especializada

Sheet Gráficos RK

Sheet COMPOS CART
B3: COMPOSICIÓN DE LA CARTERA DE CRÉDITOS POR VENCIMIENTOS Y LÍNEAS DE NEGOCIO
B4: SISTEMA DE BANCOS PRIVADOS
B5: 31/12/2025
B6: En miles de dólares
B8: CÓDIGO | C8: CUENTA | D8: BP GUAYAQUIL | E8: BP PACIFICO | F8: BP PICHINCHA | G8: BP PRODUBANCO | H8: BANCOS PRIVADOS GRANDES | I8: BP AUSTRO | J8: BP BOLIVARIANO | K8: BP CITIBANK | L8: BP DINERS | M8: BP GENERAL RUMIÑAHUI | N8: BP INTERNACIONAL | O8: BP LOJA | P8: BP MACHALA | Q8: BP SOLIDARIO | R8: BANCOS PRIVADOS MEDIANOS | S8: BP PROCREDIT | T8: BP AMAZONAS | U8: BP BANCO COMERCIAL DE MANABI | V8: BP LITORAL | W8: BP COOPNACIONAL | X8: BP CAPITAL | Y8: BP DELBANK | Z8: BANCO ATLÁNTIDA S.A. | AA8: BP BANCO DESARROLLO DE LOS PUEBLOS S.A., CODESARROLLO | AB8: BP VISIONFUND ECUADOR S.A. | AC8: BANCOS PRIVADOS PEQUEÑOS | AD8: TOTAL BANCOS PRIVADOS | AE8: BANCOS PRIVADOS COMERCIALES | AF8: BANCOS PRIVADOS CONSUMO | AG8: BANCOS PRIVADOS VIVIENDA | AH8: BANCOS PRIVADOS MICROCRÉDITO | AI8: BANCA MÚLTIPLE
C9: CARTERA BRUTA | D9: 6817457.7 | E9: 6506396 | F9: 13856004 | G9: 6397712.4 | H9: 33577570 | I9: 1843581.8 | J9: 4219779.1 | K9: 363010.91 | L9: 2750746.2 | M9: 979599.88 | N9: 4268557.5 | O9: 676843.24 | P9: 829387.18 | Q9: 629384.65 | R9: 16560890 | S9: 515346.45 | T9: 244628.48 | U9: 60781.575 | V9: 33811.344 | W9: 36319.221 | X9: 53665.844 | Y9: 27486.745 | Z9: 67959.842 | AA9: 225416.37 | AB9: 153904.97 | AC9: 1419320.8 | AD9: 51557782 | AE9: 4631568.4 | AF9: 3764157.4 | AG9: 0 | AH9: 221864.81 | AI9: 42940191
B11: 1401 | C11: CARTERA DE CRÉDITOS PRODUCTIVO POR VENCER | D11: 3328747.5 | E11: 2288393.5 | F11: 5162208.1 | G11: 3722911.7 | H11: 14502261 | I11: 521493.44 | J11: 2971224.4 | K11: 363010.91 | L11: 165644.94 | M11: 82819.98 | N11: 3368444.6 | O11: 173760.44 | P11: 533703.95 | Q11: 19.4755 | R11: 8180122.1 | S11: 274931.25 | T11: 115573.05 | U11: 31203.066 | V11: 7794.3525 | W11: 33413.925 | X11: 591.56896 | Y11: 19875.097 | Z11: 8402.8194 | AA11: 30675.99 | AB11: 0 | AC11: 522461.12 | AD11: 23204844 | AE11: 3731455.5 | AF11: 256259.27 | AG11: 0 | AH11: 8402.8194 | AI11: 19208726
B12: 1402 | C12: CARTERA DE CRÉDITOS DE CONSUMO POR VENCER | D12: 2599614.7 | E12: 3205765.4 | F12: 4749519.9 | G12: 1914267.4 | H12: 12469167 | I12: 1088403.7 | J12: 1015497.6 | K12: 0 | L12: 2244327.3 | M12: 700809.13 | N12: 592741.88 | O12: 261419.22 | P12: 173033.06 | Q12: 292782.72 | R12: 6369014.6 | S12: 11471.14 | T12: 103108.69 | U12: 21007.212 | V12: 19518.068 | W12: 466.93699 | X12: 34253.008 | Y12: 4265.695 | Z12: 13675.259 | AA12: 85604.629 | AB12: 3517.7135 | AC12: 296888.35 | AD12: 19135070 | AE12: 592741.88 | AF12: 2964654.5 | AG12: 0 | AH12: 17192.972 | AI12: 15560481
B13: 1403 | C13: CARTERA DE CRÉDITOS INMOBILIARIO POR VENCER | D13: 210389.74 | E13: 459139.16 | F13: 924828.11 | G13: 301499.61 | H13: 1895856.6 | I13: 54708.117 | J13: 159582.63 | K13: 0 | L13: 165.24921 | M13: 113685.43 | N13: 150959.75 | O13: 56589.767 | P13: 42675.706 | Q13: 0 | R13: 578366.64 | S13: 25965.18 | T13: 3524.8978 | U13: 0 | V13: 0 | W13: 215.64284 | X13: 0 | Y13: 1411.228 | Z13: 124.51966 | AA13: 30301.574 | AB13: 0 | AC13: 61543.043 | AD13: 2535766.3 | AE13: 150959.75 | AF13: 113850.68 | AG13: 0 | AH13: 124.51966 | AI13: 2270831.3
B14: 1404 | C14: CARTERA DE CRÉDITOS PARA MICROCRÉDITO POR VENCER | D14: 411901.08 | E14: 15579.373 | F14: 1861288.9 | G14: 59107.287 | H14: 2347876.6 | I14: 12969.174 | J14: 799.05341 | K14: 0 | L14: 9687.2987 | M14: 326.34263 | N14: 5664.9731 | O14: 133617.8 | P14: 7435.9954 | Q14: 300202.79 | R14: 470703.42 | S14: 145066.94 | T14: 5505.5175 | U14: 6600.3103 | V14: 1046.0175 | W14: 2205.8276 | X14: 17063.428 | Y14: 210.91819 | Z14: 39780.837 | AA14: 53487.177 | AB14: 141542.98 | AC14: 412509.95 | AD14: 3231090 | AE14: 5664.9731 | AF14: 11059.659 | AG14: 0 | AH14: 181323.82 | AI14: 3033041.5
B15: 1408 | C15: CARTERA DE CRÉDITO DE VIVIENDA DE INTERÉS SOCIAL Y PÚBLICO POR VENCER | D15: 0 | E15: 2092.5078 | F15: 7456.3654 | G15: 0 | H15: 9548.8732 | I15: 0 | J15: 0 | K15: 0 | L15: 0 | M15: 13183.368 | N15: 287.59108 | O15: 0 | P15: 0 | Q15: 0 | R15: 13470.959 | S15: 0 | T15: 0 | U15: 0 | V15: 0 | W15: 0 | X15: 0 | Y15: 0 | Z15: 0 | AA15: 0 | AB15: 0 | AC15: 0 | AD15: 23019.833 | AE15: 287.59108 | AF15: 13183.368 | AG15: 0 | AH15: 0 | AI15: 9548.8732
B16: 1409 | C16: CARTERA DE CRÉDITOS PRODUCTIVO REFINANCIADA POR VENCER | D16: 12810.851 | E16: 91556.035 | F16: 51240.763 | G16: 8016.6064 | H16: 163624.25 | I16: 79710.091 | J16: 0 | K16: 0 | L16: 2196.481 | M16: 5686.5109 | N16: 31283.746 | O16: 6176.2705 | P16: 30156.918 | Q16: 0 | R16: 155210.02 | S16: 14787.173 | T16: 1181.9501 | U16: 493.76685 | V16: 1151.4271 | W16: 0 | X16: 0 | Y16: 793.70176 | Z16: 0 | AA16: 847.72192 | AB16: 0 | AC16: 19255.74 | AD16: 338090.01 | AE16: 31283.746 | AF16: 9034.4189 | AG16: 0 | AH16: 0 | AI16: 297771.85
B17: 1410 | C17: CARTERA DE CRÉDITOS CONSUMO REFINANCIADA POR VENCER | D17: 51125.667 | E17: 47.93083 | F17: 38278.236 | G17: 95378.02 | H17: 184829.85 | I17: 15370.686 | J17: 807.13237 | K17: 0 | L17: 28164.215 | M17: 22177.045 | N17: 730.05483 | O17: 4572.0346 | P17: 5422.3285 | Q17: 1084.8902 | R17: 78328.388 | S17: 186.27237 | T17: 5691.1111 | U17: 41.73303 | V17: 1493.4302 | W17: 0 | X17: 224.67231 | Y17: 314.12107 | Z17: 0 | AA17: 1306.7573 | AB17: 0 | AC17: 9258.0973 | AD17: 272416.34 | AE17: 730.05483 | AF17: 51834.691 | AG17: 0 | AH17: 0 | AI17: 219851.59
B18: 1411 | C18: CARTERA DE CRÉDITOS INMOBILIARIO REFINANCIADA POR VENCER | D18: 13958.54 | E18: 4395.446 | F18: 5327.2114 | G18: 2064.2817 | H18: 25745.479 | I18: 2462.3644 | J18: 1837.8572 | K18: 0 | L18: 0 | M18: 3466.6775 | N18: 895.90369 | O18: 890.23644 | P18: 630.06604 | Q18: 0 | R18: 10183.105 | S18: 1173.7108 | T18: 0 | U18: 0 | V18: 36.45472 | W18: 0 | X18: 0 | Y18: 0 | Z18: 0 | AA18: 665.95296 | AB18: 0 | AC18: 1876.1185 | AD18: 37804.703 | AE18: 895.90369 | AF18: 3503.1322 | AG18: 0 | AH18: 0 | AI18: 33405.667
B19: 1412 | C19: CARTERA DE CRÉDITOS PARA MICROCRÉDITO REFINANCIADA POR VENCER | D19: 4296.8111 | E19: 0 | F19: 4735.5945 | G19: 330.3202 | H19: 9362.7258 | I19: 193.23999 | J19: 0 | K19: 0 | L19: 135.7114 | M19: 0 | N19: 58.369 | O19: 5227.5714 | P19: 409.21887 | Q19: 1498.478 | R19: 7522.5887 | S19: 8348.1157 | T19: 0 | U19: 52.06143 | V19: 0 | W19: 0 | X19: 74.95015 | Y19: 0 | Z19: 2026.8267 | AA19: 2962.0752 | AB19: 930.60266 | AC19: 14394.632 | AD19: 31279.946 | AE19: 58.369 | AF19: 135.7114 | AG19: 0 | AH19: 2957.4294 | AI19: 28128.437
B20: 1416 | C20: CARTERA DE CRÉDITOS DE VIVIENDA DE INTERÉS SOCIAL Y PÚBLICO REFINANCIADA POR VENCER | D20: 0 | E20: 55.42109 | F20: 0 | G20: 0 | H20: 55.42109 | I20: 0 | J20: 0 | K20: 0 | L20: 0 | M20: 16.96254 | N20: 0 | O20: 0 | P20: 0 | Q20: 0 | R20: 16.96254 | S20: 0 | T20: 0 | U20: 0 | V20: 0 | W20: 0 | X20: 0 | Y20: 0 | Z20: 0 | AA20: 0 | AB20: 0 | AC20: 0 | AD20: 72.38363 | AE20: 0 | AF20: 16.96254 | AG20: 0 | AH20: 0 | AI20: 55.42109
B21: 1417 | C21: CARTERA DE CRÉDITOS PRODUCTIVO REESTRUCTURADA POR VENCER | D21: 4642.1061 | E21: 58652.727 | F21: 123691.26 | G21: 7085.0292 | H21: 194071.13 | I21: 803.09435 | J21: 9.54185 | K21: 0 | L21: 3436.9925 | M21: 3123.0786 | N21: 38639.804 | O21: 5751.1714 | P21: 9811.146 | Q21: 0 | R21: 61574.829 | S21: 9731.6572 | T21: 702.63809 | U21: 13.58596 | V21: 17.3681 | W21: 0 | X21: 0 | Y21: 0 | Z21: 0 | AA21: 0 | AB21: 0 | AC21: 10465.249 | AD21: 266111.2 | AE21: 38639.804 | AF21: 6577.4392 | AG21: 0 | AH21: 0 | AI21: 220893.96
B22: 1418 | C22: CARTERA DE CRÉDITOS DE CONSUMO REESTRUCTURADA POR VENCER | D22: 11805.286 | E22: 68490.315 | F22: 127855.33 | G22: 94323.795 | H22: 302474.73 | I22: 6557.793 | J22: 8320.2175 | K22: 0 | L22: 128444 | M22: 3678.6698 | N22: 4685.6771 | O22: 1984.0557 | P22: 4006.4133 | Q22: 531.44527 | R22: 158208.27 | S22: 82.18053 | T22: 3721.6682 | U22: 4.86231 | V22: 180.56349 | W22: 0 | X22: 43.01878 | Y22: 13.28686 | Z22: 0 | AA22: 211.73537 | AB22: 0 | AC22: 4257.3155 | AD22: 464940.31 | AE22: 4685.6771 | AF22: 132303.23 | AG22: 0 | AH22: 0 | AI22: 327951.4
... B45: 149450 | C45: EDUCATIVO POR VENCER | D45: 0 | E45: 0 | F45: 173.18004 | G45: 0 | H45: 173.18004 | I45: 0 | J45: 0 | K45: 0 | L45: 0 | M45: 0 | N45: 0 | O45: 0 | P45: 0 | Q45: 0 | R45: 0 | S45: 0 | T45: 0 | U45: 0 | V45: 0 | W45: 0 | X45: 0 | Y45: 0 | Z45: 0 | AA45: 0 | AB45: 0 | AC45: 0 | AD45: 173.18004 | AE45: 0 | AF45: 0 | AG45: 0 | AH45: 0 | AI45: 173.18004
C46: TOTAL CARTERA POR VENCER | D46: 6656651.8 | E46: 6338677.5 | F46: 13321029 | G46: 6226506.5 | H46: 32542865 | I46: 1784453.9 | J46: 4161092.3 | K46: 363010.91 | L46: 2592528.6 | M46: 952444.04 | N46: 4197507.4 | O46: 653155.76 | P46: 808842.7 | Q46: 598002.67 | R46: 16111038 | S46: 496971.5 | T46: 239068.57 | U46: 59693.089 | V46: 31309.299 | W46: 36302.332 | X46: 52399.205 | Y46: 26891.742 | Z46: 65792.026 | AA46: 207385.6 | AB46: 146061.82 | AC46: 1361875.2 | AD46: 50015778 | AE46: 4560518.3 | AF46: 3576282 | AG46: 0 | AH46: 211853.84 | AI46: 41667124
B48: 1425 | C48: CARTERA DE CRÉDITOS PRODUCTIVO QUE NO DEVENGA INTERESES | D48: 4704.5225 | E48: 3178.3425 | F48: 18806.152 | G48: 3374.4917 | H48: 30063.509 | I48: 1750.0373 | J48: 1821.645 | K48: 0 | L48: 804.93436 | M48: 322.75542 | N48: 2545.0881 | O48: 1228.6262 | P48: 781.70209 | Q48: 0 | R48: 9254.7885 | S48: 2379.1998 | T48: 0.72718 | U48: 97.82469 | V48: 75.4849 | W48: 0 | X48: 9.04759 | Y48: 143.45646 | Z48: 0 | AA48: 0 | AB48: 0 | AC48: 2705.7406 | AD48: 42024.038 | AE48: 2545.0881 | AF48: 1203.1747 | AG48: 0 | AH48: 0 | AI48: 38275.775
B49: 1426 | C49: CARTERA DE CRÉDITOS DE CONSUMO QUE NO DEVENGA INTERESES | D49: 57492.168 | E49: 69642.344 | F49: 122751.74 | G49: 61955.257 | H49: 311841.51 | I49: 27393.266 | J49: 33335.226 | K49: 0 | L49: 45382.2 | M49: 15152.551 | N49: 36403.199 | O49: 5001.974 | P49: 4966.5793 | Q49: 10823.181 | R49: 178458.18 | S49: 224.84866 | T49: 1055.3689 | U49: 267.12586 | V49: 899.55123 | W49: 5.31241 | X49: 754.92162 | Y49: 136.72147 | Z49: 0 | AA49: 2959.4715 | AB49: 18.84132 | AC49: 6322.1629 | AD49: 496621.85 | AE49: 36403.199 | AF49: 61434.302 | AG49: 0 | AH49: 18.84132 | AI49: 398765.51
B50: 1427 | C50: CARTERA DE CRÉDITOS INMOBILIARIO QUE NO DEVENGA INTERESES | D50: 2186.1743 | E50: 4682.2753 | F50: 11547.103 | G50: 1481.6611 | H50: 19897.214 | I50: 1642.2741 | J50: 1094.6859 | K50: 0 | L50: 0 | M50: 868.76672 | N50: 1632.0073 | O50: 240.53042 | P50: 537.70136 | Q50: 0 | R50: 6015.9658 | S50: 35.06864 | T50: 0 | U50: 0 | V50: 0 | W50: 0 | X50: 0 | Y50: 0 | Z50: 0 | AA50: 63.3495 | AB50: 0 | AC50: 98.41814 | AD50: 26011.597 | AE50: 1632.0073 | AF50: 868.76672 | AG50: 0 | AH50: 0 | AI50: 23510.823
B51: 1428 | C51: CARTERA DE CRÉDITOS PARA MICROCRÉDITO QUE NO DEVENGA INTERESES | D51: 18758.284 | E51: 232.40548 | F51: 64563.59 | G51: 924.81394 | H51: 84479.093 | I51: 706.57191 | J51: 24.59639 | K51: 0 | L51: 153.97423 | M51: 0 | N51: 44.56295 | O51: 2462.318 | P51: 773.41641 | Q51: 14371.566 | R51: 18537.006 | S51: 1462.4473 | T51: 0 | U51: 52.38825 | V51: 80.96872 | W51: 3.63983 | X51: 325.63782 | Y51: 0 | Z51: 263.13265 | AA51: 4396.0871 | AB51: 3300.994 | AC51: 9885.2956 | AD51: 112901.39 | AE51: 44.56295 | AF51: 234.94295 | AG51: 0 | AH51: 3564.1266 | AI51: 109057.76
B52: 1432 | C52: CARTERA DE CRÉDITO DE VIVIENDA DE INTERÉS SOCIAL Y PÚBLICO QUE NO DEVENGA INTERESES | D52: 0 | E52: 0 | F52: 0 | G52: 0 | H52: 0 | I52: 0 | J52: 0 | K52: 0 | L52: 0 | M52: 168.07405 | N52: 0 | O52: 0 | P52: 0 | Q52: 0 | R52: 168.07405 | S52: 0 | T52: 0 | U52: 0 | V52: 0 | W52: 0 | X52: 0 | Y52: 0 | Z52: 0 | AA52: 0 | AB52: 0 | AC52: 0 | AD52: 168.07405 | AE52: 0 | AF52: 168.07405 | AG52: 0 | AH52: 0 | AI52: 0
B53: 1433 | C53: CARTERA DE CRÉDITOS PRODUCTIVO REFINANCIADA QUE NO DEVENGA INTERESES | D53: 1509.2863 | E53: 224.65996 | F53: 3796.444 | G53: 1610.232 | H53: 7140.6223 | I53: 415.28326 | J53: 0 | K53: 0 | L53: 400.87204 | M53: 148.90227 | N53: 699.38375 | O53: 200.06688 | P53: 1437.7778 | Q53: 0 | R53: 3302.286 | S53: 911.60053 | T53: 0 | U53: 0 | V53: 43.93826 | W53: 0 | X53: 0 | Y53: 34.6721 | Z53: 0 | AA53: 0 | AB53: 0 | AC53: 990.21089 | AD53: 11433.119 | AE53: 699.38375 | AF53: 593.71257 | AG53: 0 | AH53: 0 | AI53: 10140.023
B54: 1434 | C54: CARTERA DE CRÉDITOS DE CONSUMO REFINANCIADA QUE NO DEVENGA INTERESES | D54: 12298.767 | E54: 1.63503 | F54: 2403.8548 | G54: 13340.021 | H54: 28044.278 | I54: 3464.8258 | J54: 209.02483 | K54: 0 | L54: 7194.1205 | M54: 3123.3217 | N54: 308.05727 | O54: 585.93436 | P54: 2457.1887 | Q54: 426.0806 | R54: 17768.554 | S54: 173.53256 | T54: 439.88339 | U54: 24.37043 | V54: 77.80223 | W54: 0 | X54: 25.95058 | Y54: 79.22709 | Z54: 0 | AA54: 463.52861 | AB54: 0 | AC54: 1284.2949 | AD54: 47097.126 | AE54: 308.05727 | AF54: 10395.244 | AG54: 0 | AH54: 0 | AI54: 36393.825
B55: 1435 | C55: CARTERA DE CRÉDITOS INMOBILIARIO REFINANCIADA QUE NO DEVENGA INTERESES | D55: 3032.6408 | E55: 194.73857 | F55: 176.9889 | G55: 66.6454 | H55: 3471.0136 | I55: 510.69718 | J55: 375.05639 | K55: 0 | L55: 0 | M55: 279.17251 | N55: 121.53833 | O55: 0 | P55: 235.32512 | Q55: 0 | R55: 1521.7895 | S55: 0 | T55: 0 | U55: 0 | V55: 0 | W55: 0 | X55: 0 | Y55: 10.85488 | Z55: 0 | AA55: 12.03338 | AB55: 0 | AC55: 22.88826 | AD55: 5015.6914 | AE55: 121.53833 | AF55: 279.17251 | AG55: 0 | AH55: 0 | AI55: 4614.9806
B56: 1436 | C56: CARTERA DE CRÉDITOS PARA MICROCRÉDITO REFINANCIADA QUE NO DEVENGA INTERESES | D56: 2940.0234 | E56: 0 | F56: 385.98049 | G56: 35.07937 | H56: 3361.0833 | I56: 25.41741 | J56: 0 | K56: 0 | L56: 24.35683 | M56: 0 | N56: 22.96089 | O56: 1011.9746 | P56: 309.17612 | Q56: 705.4466 | R56: 2099.3324 | S56: 894.1374 | T56: 0 | U56: 0 | V56: 0 | W56: 0 | X56: 11.33646 | Y56: 0 | Z56: 226.69917 | AA56: 1837.1753 | AB56: 333.24614 | AC56: 3302.5944 | AD56: 8763.0102 | AE56: 22.96089 | AF56: 24.35683 | AG56: 0 | AH56: 559.94531 | AI56: 8155.7471
B57: 1440 | C57: CARTERA DE CRÉDITOS DE VIVIENDA DE INTERÉS SOCIAL Y PÚBLICO REFINANCIADA QUE NO DEVENGA INTERESES | D57: 0 | E57: 0 | F57: 0 | G57: 0 | H57: 0 | I57: 0 | J57: 0 | K57: 0 | L57: 0 | M57: 38.55327 | N57: 0 | O57: 0 | P57: 0 | Q57: 0 | R57: 38.55327 | S57: 0 | T57: 0 | U57: 0 | V57: 0 | W57: 0 | X57: 0 | Y57: 0 | Z57: 0 | AA57: 0 | AB57: 0 | AC57: 0 | AD57: 38.55327 | AE57: 0 | AF57: 38.55327 | AG57: 0 | AH57: 0 | AI57: 0
B58: 1441 | C58: CARTERA DE CRÉDITOS PRODUCTIVO REESTRUCTURADA QUE NO DEVENGA INTERESES | D58: 1947.9592 | E58: 1803.5549 | F58: 25698.741 | G58: 5988.5184 | H58: 35438.774 | I58: 650.05719 | J58: 8.11128 | K58: 0 | L58: 1085.2319 | M58: 119.63077 | N58: 2681.7542 | O58: 522.98199 | P58: 3005.6427 | Q58: 0 | R58: 8073.41 | S58: 4249.15 | T58: 0 | U58: 0 | V58: 0 | W58: 0 | X58: 0 | Y58: 44.11429 | Z58: 0 | AA58: 0 | AB58: 0 | AC58: 4293.2643 | AD58: 47805.448 | AE58: 2681.7542 | AF58: 1204.8627 | AG58: 0 | AH58: 0 | AI58: 43918.831
B59: 1442 | C59: CARTERA DE CRÉDITOS DE CONSUMO REESTRUCTURADA QUE NO DEVENGA INTERESES | D59: 7622.2281 | E59: 34292.11 | F59: 46977.246 | G59: 34063.212 | H59: 122954.8 | I59: 4722.2997 | J59: 3752.8326 | K59: 0 | L59: 33689.991 | M59: 383.99733 | N59: 2746.0032 | O59: 476.9531 | P59: 2638.4866 | Q59: 208.03638 | R59: 48618.6 | S59: 0 | T59: 782.146 | U59: 2.91222 | V59: 11.37292 | W59: 0 | X59: 16.24443 | Y59: 0 | Z59: 0 | AA59: 185.41714 | AB59: 0 | AC59: 998.09271 | AD59: 172571.49 | AE59: 2746.0032 | AF59: 34085.361 | AG59: 0 | AH59: 0 | AI59: 135740.12
... B82: 149550 | C82: EDUCATIVO QUE NO DEVENGA INTERESES | D82: 0 | E82: 0 | F82: 77.98502 | G82: 0 | H82: 77.98502 | I82: 0 | J82: 0 | K82: 0 | L82: 0 | M82: 0 | N82: 0 | O82: 0 | P82: 0 | Q82: 0 | R82: 0 | S82: 0 | T82: 0 | U82: 0 | V82: 0 | W82: 0 | X82: 0 | Y82: 0 | Z82: 0 | AA82: 0 | AB82: 0 | AC82: 0 | AD82: 77.98502 | AE82: 0 | AF82: 0 | AG82: 0 | AH82: 0 | AI82: 77.98502
C83: TOTAL CARTERA QUE NO DEVENGA INTERES | D83: 117749.32 | E83: 116772.45 | F83: 349056.61 | G83: 130681.43 | H83: 714259.81 | I83: 42277.096 | J83: 40640.822 | K83: 0 | L83: 90886.625 | M83: 20981.931 | N83: 48661.227 | O83: 12155.751 | P83: 17368.129 | Q83: 27392.24 | R83: 300363.82 | S83: 11942.125 | T83: 2279.9259 | U83: 473.69235 | V83: 1217.7456 | W83: 8.95224 | X83: 1174.6215 | Y83: 449.04629 | Z83: 1183.2662 | AA83: 10468.904 | AB83: 3703.9754 | AC83: 32902.255 | AD83: 1047525.9 | AE83: 48661.227 | AF83: 113086.3 | AG83: 0 | AH83: 4887.2416 | AI83: 880891.12
B85: 1449 | C85: CARTERA DE CRÉDITOS PRODUCTIVO VENCIDA | D85: 10559.025 | E85: 3952.0241 | F85: 25515.716 | G85: 14363.841 | H85: 54390.606 | I85: 2395.6338 | J85: 6539.7492 | K85: 0.001 | L85: 2944.3096 | M85: 315.86993 | N85: 3681.7633 | O85: 837.98767 | P85: 735.28953 | Q85: 0.019 | R85: 17450.623 | S85: 2028.3147 | T85: 797.18215 | U85: 318.44016 | V85: 74.51204 | W85: 0 | X85: 0.35493 | Y85: 66.18847 | Z85: 0 | AA85: 0.018 | AB85: 0 | AC85: 3285.0105 | AD85: 75126.239 | AE85: 3681.7643 | AF85: 3334.6916 | AG85: 0 | AH85: 0 | AI85: 68109.783
B86: 1450 | C86: CARTERA DE CRÉDITOS DE CONSUMO VENCIDA | D86: 16690.274 | E86: 22235.529 | F86: 48234.921 | G86: 6001.2973 | H86: 93162.022 | I86: 8648.5581 | J86: 9901.6112 | K86: 0 | L86: 39000.344 | M86: 3977.7786 | N86: 13527.722 | O86: 5065.7082 | P86: 1478.3219 | Q86: 1783.0751 | R86: 83383.119 | S86: 111.14052 | T86: 1178.4446 | U86: 266.21627 | V86: 602.38115 | W86: 1.78236 | X86: 72.61096 | Y86: 54.79958 | Z86: 0 | AA86: 1940.7436 | AB86: 7.20455 | AC86: 4235.3235 | AD86: 180780.46 | AE86: 13527.722 | AF86: 43580.504 | AG86: 0 | AH86: 7.20455 | AI86: 123665.03
B87: 1451 | C87: CARTERA DE CRÉDITOS INMOBILIARIO VENCIDA | D87: 340.48742 | E87: 8162.339 | F87: 10401.25 | G87: 4484.0836 | H87: 23388.16 | I87: 254.0356 | J87: 895.17263 | K87: 0 | L87: 0 | M87: 131.71811 | N87: 229.48883 | O87: 343.1143 | P87: 37.12011 | Q87: 0.039 | R87: 1890.6886 | S87: 14.21191 | T87: 0 | U87: 0 | V87: 0.001 | W87: 0.004 | X87: 0 | Y87: 0.004 | Z87: 0 | AA87: 6.46292 | AB87: 0 | AC87: 20.68383 | AD87: 25299.532 | AE87: 229.48883 | AF87: 131.71911 | AG87: 0 | AH87: 0 | AI87: 24938.324
B88: 1452 | C88: CARTERA DE CRÉDITOS PARA MICROCRÉDITO VENCIDA | D88: 8918.0121 | E88: 124.62757 | F88: 32016.043 | G88: 172.92543 | H88: 41231.608 | I88: 564.15799 | J88: 8.36115 | K88: 0 | L88: 116.39911 | M88: 0.015 | N88: 31.00925 | O88: 1884.856 | P88: 254.96326 | Q88: 2080.7142 | R88: 4940.4759 | S88: 594.7757 | T88: 17.87065 | U88: 12.18453 | V88: 25.36286 | W88: 6.06167 | X88: 12.743 | Y88: 0.055 | Z88: 871.24584 | AA88: 3934.2089 | AB88: 4029.3774 | AC88: 9503.8855 | AD88: 55675.969 | AE88: 31.00925 | AF88: 141.77697 | AG88: 0 | AH88: 4900.6232 | AI88: 50602.56
B89: 1456 | C89: CARTERA DE CRÉDITOS DE VIVIENDA DE INTERÉS SOCIAL Y PÚBLICO VENCIDA | D89: 0 | E89: 161.09528 | F89: 0.008 | G89: 0 | H89: 161.10328 | I89: 0 | J89: 0 | K89: 0 | L89: 0 | M89: 241.0652 | N89: 0 | O89: 0 | P89: 0 | Q89: 0 | R89: 241.0652 | S89: 0 | T89: 0 | U89: 0 | V89: 0 | W89: 0 | X89: 0 | Y89: 0 | Z89: 0 | AA89: 0 | AB89: 0 | AC89: 0 | AD89: 402.16848 | AE89: 0 | AF89: 241.0652 | AG89: 0 | AH89: 0 | AI89: 161.10328
B90: 1457 | C90: CARTERA DE CRÉDITOS PRODUCTIVO REFINANCIADA VENCIDA | D90: 1999.9926 | E90: 592.28267 | F90: 2926.1122 | G90: 4485.3467 | H90: 10003.734 | I90: 83.67365 | J90: 0 | K90: 0 | L90: 22.88234 | M90: 390.53476 | N90: 1380.5617 | O90: 212.32716 | P90: 123.36957 | Q90: 0 | R90: 2213.3492 | S90: 1017.7882 | T90: 241.74311 | U90: 0 | V90: 34.65305 | W90: 0 | X90: 0 | Y90: 7.15607 | Z90: 0 | AA90: 40 | AB90: 0 | AC90: 1341.3404 | AD90: 13558.424 | AE90: 1380.5617 | AF90: 448.07015 | AG90: 0 | AH90: 0 | AI90: 11729.792
B91: 1458 | C91: CARTERA DE CRÉDITOS DE CONSUMO REFINANCIADA VENCIDA | D91: 626.09942 | E91: 1.83227 | F91: 442.64576 | G91: 571.65909 | H91: 1642.2365 | I91: 1483.2458 | J91: 6.7467 | K91: 0 | L91: 891.20484 | M91: 202.09477 | N91: 104.37552 | O91: 807.82951 | P91: 146.50578 | Q91: 30.33609 | R91: 3672.339 | S91: 1.04849 | T91: 393.73082 | U91: 3.83782 | V91: 189.46938 | W91: 0 | X91: 0.16386 | Y91: 6.25584 | Z91: 0 | AA91: 254.11305 | AB91: 0 | AC91: 848.61926 | AD91: 6163.1948 | AE91: 104.37552 | AF91: 1282.769 | AG91: 0 | AH91: 0 | AI91: 4776.0503
B92: 1459 | C92: CARTERA DE CRÉDITOS INMOBILIARIO REFINANCIADA VENCIDA | D92: 388.91714 | E92: 949.24911 | F92: 3.10171 | G92: 191.66312 | H92: 1532.9311 | I92: 31.78885 | J92: 138.85939 | K92: 0 | L92: 0 | M92: 265.30444 | N92: 13.49293 | O92: 69.48522 | P92: 12.11462 | Q92: 0 | R92: 531.04545 | S92: 0.001 | T92: 0 | U92: 0 | V92: 0 | W92: 0 | X92: 0 | Y92: 1.5548 | Z92: 0 | AA92: 5.36456 | AB92: 0 | AC92: 6.92036 | AD92: 2070.8969 | AE92: 13.49293 | AF92: 265.30444 | AG92: 0 | AH92: 0 | AI92: 1792.0995
B93: 1460 | C93: CARTERA DE CRÉDITOS PARA MICROCRÉDITO REFINANCIADA VENCIDA | D93: 509.87835 | E93: 0 | F93: 89.00791 | G93: 1.36242 | H93: 600.24868 | I93: 6.57961 | J93: 0 | K93: 0 | L93: 1.88812 | M93: 0 | N93: 0.94211 | O93: 909.56977 | P93: 28.30113 | Q93: 46.8751 | R93: 994.15584 | S93: 173.78826 | T93: 0 | U93: 8.96775 | V93: 0.001 | W93: 0 | X93: 0.85099 | Y93: 0.001 | Z93: 29.4462 | AA93: 794.2246 | AB93: 82.68196 | AC93: 1089.9618 | AD93: 2684.3663 | AE93: 0.94211 | AF93: 1.88912 | AG93: 0 | AH93: 112.12816 | AI93: 2569.4069
B94: 1464 | C94: CARTERA DE CRÉDITO DE VIVIENDA DE INTERÉS SOCIAL Y PÚBLICO REFINANCIADA VENCIDA | D94: 0 | E94: 0 | F94: 0 | G94: 0 | H94: 0 | I94: 0 | J94: 0 | K94: 0 | L94: 0 | M94: 0.60249 | N94: 0 | O94: 0 | P94: 0 | Q94: 0 | R94: 0.60249 | S94: 0 | T94: 0 | U94: 0 | V94: 0 | W94: 0 | X94: 0 | Y94: 0 | Z94: 0 | AA94: 0 | AB94: 0 | AC94: 0 | AD94: 0.60249 | AE94: 0 | AF94: 0.60249 | AG94: 0 | AH94: 0 | AI94: 0
B95: 1465 | C95: CARTERA DE CRÉDITOS PRODUCTIVO REESTRUCTURADA VENCIDA | D95: 2055.0936 | E95: 6263.7495 | F95: 19478.018 | G95: 5817.8445 | H95: 33614.706 | I95: 117.63729 | J95: 22.52174 | K95: 0 | L95: 2195.5154 | M95: 186.22386 | N95: 2907.3879 | O95: 457.10635 | P95: 82.48088 | Q95: 0.003 | R95: 5968.8764 | S95: 2105.5195 | T95: 57.76778 | U95: 0 | V95: 0 | W95: 0 | X95: 0 | Y95: 9.11333 | Z95: 0 | AA95: 0.001 | AB95: 0 | AC95: 2172.4016 | AD95: 41755.984 | AE95: 2907.3879 | AF95: 2381.7392 | AG95: 0 | AH95: 0 | AI95: 36466.857
B96: 1466 | C96: CARTERA DE CRÉDITOS DE CONSUMO REESTRUCTURADA VENCIDA | D96: 378.94535 | E96: 2765.5543 | F96: 32439.834 | G96: 1400.6682 | H96: 36985.002 | I96: 3098.4988 | J96: 484.99996 | K96: 0 | L96: 22034.894 | M96: 81.90407 | N96: 457.45002 | O96: 522.00997 | P96: 170.86891 | Q96: 20.45576 | R96: 26871.082 | S96: 0 | T96: 585.87478 | U96: 0.45909 | V96: 59.12319 | W96: 0 | X96: 1.07519 | Y96: 0.81946 | Z96: 0 | AA96: 96.7738 | AB96: 0 | AC96: 744.12551 | AD96: 64600.209 | AE96: 457.45002 | AF96: 22175.921 | AG96: 0 | AH96: 0 | AI96: 41966.838
... B119: 149650 | C119: EDUCATIVO VENCIDA | D119: 0 | E119: 0 | F119: 8.01048 | G119: 0 | H119: 8.01048 | I119: 0 | J119: 0 | K119: 0 | L119: 0 | M119: 0 | N119: 0 | O119: 0 | P119: 0 | Q119: 0 | R119: 0 | S119: 0 | T119: 0 | U119: 0 | V119: 0 | W119: 0 | X119: 0 | Y119: 0 | Z119: 0 | AA119: 0 | AB119: 0 | AC119: 0 | AD119: 8.01048 | AE119: 0 | AF119: 0 | AG119: 0 | AH119: 0 | AI119: 8.01048
