Workbook

Sheet BALANCE
B2: ESTADO DE SITUACIÓN
B3: SISTEMA DE BANCOS PRIVADOS
B4: 31/05/2022
B5: (en miles de dólares)
B8: CÓDIGO | C8: CUENTA | D8: BP GUAYAQUIL | E8: BP PACIFICO | F8: BP PICHINCHA | G8: BP PRODUBANCO | H8: BANCOS PRIVADOS GRANDES | I8: BP AUSTRO | J8: BP BOLIVARIANO | K8: BP CITIBANK | L8: BP DINERS | M8: BP GENERAL RUMIÑAHUI | N8: BP INTERNACIONAL | O8: BP LOJA | P8: BP MACHALA | Q8: BP SOLIDARIO | R8: BANCOS PRIVADOS MEDIANOS | S8: BP PROCREDIT | T8: BP AMAZONAS | U8: BP COMERCIAL DE MANABI | V8: BP LITORAL | W8: BP COOPNACIONAL | X8: BP CAPITAL | Y8: BP FINCA S.A. | Z8: BP DELBANK | AA8: BP D-MIRO S.A. | AB8: BP BANCO DESARROLLO DE LOS PUEBLOS S.A., CODESARROLLO | AC8: BP VISIONFUND ECUADOR S.A. | AD8: BANCOS PRIVADOS PEQUEÑOS | AE8: TOTAL BANCOS PRIVADOS | AF8: BANCOS PRIVADOS COMERCIALES | AG8: BANCOS PRIVADOS CONSUMO | AH8: BANCOS PRIVADOS VIVIENDA | AI8: BANCOS PRIVADOS MICROCRÉDITO | AJ8: BANCA MÚLTIPLE
C9: ACTIVO
B10: 11 | C10: FONDOS DISPONIBLES | D10: 792200.41 | E10: 1236038.6 | F10: 1488170.3 | G10: 987314.77 | H10: 4503724 | I10: 366159.71 | J10: 768019.82 | K10: 204523.83 | L10: 121830.17 | M10: 168221.88 | N10: 548137.48 | O10: 141836.42 | P10: 163203.33 | Q10: 74083.198 | R10: 2556015.8 | S10: 58397.463 | T10: 30121.58 | U10: 7352.3701 | V10: 2360.7643 | W10: 64574.45 | X10: 2383.9728 | Y10: 11518.839 | Z10: 7097.2385 | AA10: 6089.1321 | AB10: 23600.842 | AC10: 3852.1231 | AD10: 217348.78 | AE10: 7277088.6 | AF10: 752661.31 | AG10: 292412.82 | AH10: 0 | AI10: 21460.095 | AJ10: 6210554.4
B11: 1101 | C11: Caja | D11: 210661.69 | E11: 276141.01 | F11: 292245.18 | G11: 112243.17 | H11: 891291.06 | I11: 71529.333 | J11: 165693.42 | K11: 302.857 | L11: 3.8 | M11: 13935.736 | N11: 90253.213 | O11: 25103.707 | P11: 28236.973 | Q11: 20341.038 | R11: 415400.08 | S11: 3519.8899 | T11: 3407.5709 | U11: 2951.1471 | V11: 666.48793 | W11: 8024.9419 | X11: 245.00216 | Y11: 720.7087 | Z11: 2364.3583 | AA11: 1674.8937 | AB11: 5241.8854 | AC11: 883.69505 | AD11: 29700.581 | AE11: 1336391.7 | AF11: 90556.07 | AG11: 14606.024 | AH11: 0 | AI11: 3279.2975 | AJ11: 1227950.3
B12: 110105 | C12: Efectivo | D12: 210661.69 | E12: 276141.01 | F12: 292214.08 | G12: 112243.17 | H12: 891259.96 | I12: 71527.233 | J12: 165692.82 | K12: 302.857 | L12: 0 | M12: 13934.986 | N12: 90243.243 | O12: 25100.987 | P12: 28236.773 | Q12: 20323.339 | R12: 415362.24 | S12: 3519.8899 | T12: 3407.1709 | U12: 2951.0471 | V12: 665.33793 | W12: 8009.9419 | X12: 244.30216 | Y12: 717.4087 | Z12: 2363.9583 | AA12: 1674.8937 | AB12: 5237.0854 | AC12: 871.49505 | AD12: 29662.531 | AE12: 1336284.7 | AF12: 90546.1 | AG12: 14600.324 | AH12: 0 | AI12: 3263.7975 | AJ12: 1227874.5
B13: 110110 | C13: Caja chica | D13: 0 | E13: 0 | F13: 31.1 | G13: 0 | H13: 31.1 | I13: 2.1 | J13: 0.6008 | K13: 0 | L13: 3.8 | M13: 0.75 | N13: 9.97 | O13: 2.72 | P13: 0.2 | Q13: 17.7 | R13: 37.8408 | S13: 0 | T13: 0.4 | U13: 0.1 | V13: 1.15 | W13: 15 | X13: 0.7 | Y13: 3.3 | Z13: 0.4 | AA13: 0 | AB13: 4.8 | AC13: 12.2 | AD13: 38.05 | AE13: 106.9908 | AF13: 9.97 | AG13: 5.7 | AH13: 0 | AI13: 15.5 | AJ13: 75.8208
B14: 1102 | C14: Depósitos para encaje | D14: 463515.35 | E14: 850193.68 | F14: 884528.46 | G14: 422073.52 | H14: 2620311 | I14: 135017.58 | J14: 233606.11 | K14: 134019.93 | L14: 45469.204 | M14: 29555.078 | N14: 195533.19 | O14: 77029.028 | P14: 61081.296 | Q14: 21370.708 | R14: 932682.12 | S14: 29411.383 | T14: 4859.5429 | U14: 3575.087 | V14: 1211.7347 | W14: 6119.6277 | X14: 1689.646 | Y14: 9036.5716 | Z14: 1001.0707 | AA14: 2082.1987 | AB14: 8165.4723 | AC14: 860.15499 | AD14: 68012.489 | AE14: 3621005.6 | AF14: 329553.11 | AG14: 76236.016 | AH14: 0 | AI14: 11978.925 | AJ14: 3203237.6
B15: 110205 | C15: Banco Central del Ecuador | D15: 463515.16 | E15: 850193.68 | F15: 884528.46 | G15: 422073.52 | H15: 2620310.8 | I15: 134978.42 | J15: 233606.11 | K15: 134019.93 | L15: 45469.204 | M15: 29555.078 | N15: 195533.19 | O15: 76977.351 | P15: 61081.296 | Q15: 21370.708 | R15: 932591.28 | S15: 29411.383 | T15: 4859.5429 | U15: 3575.087 | V15: 1211.7347 | W15: 6119.6277 | X15: 1689.646 | Y15: 9036.5716 | Z15: 1001.0707 | AA15: 2082.1987 | AB15: 8165.4723 | AC15: 860.15499 | AD15: 68012.489 | AE15: 3620914.6 | AF15: 329553.11 | AG15: 76236.016 | AH15: 0 | AI15: 11978.925 | AJ15: 3203146.5
B16: 110210 | C16: Banco Nacional de Fomento | D16: 0 | E16: 0 | F16: 0 | G16: 0 | H16: 0 | I16: 39.15989 | J16: 0 | K16: 0 | L16: 0 | M16: 0 | N16: 0 | O16: 51.67676 | P16: 0 | Q16: 0 | R16: 90.83665 | S16: 0 | T16: 0 | U16: 0 | V16: 0 | W16: 0 | X16: 0 | Y16: 0 | Z16: 0 | AA16: 0 | AB16: 0 | AC16: 0 | AD16: 0 | AE16: 90.83665 | AF16: 0 | AG16: 0 | AH16: 0 | AI16: 0 | AJ16: 90.83665
B17: 110215 | C17: Bancos locales | D17: 0.18952 | E17: 0 | F17: 0 | G17: 0 | H17: 0.18952 | I17: 0 | J17: 0 | K17: 0 | L17: 0 | M17: 0 | N17: 0 | O17: 0 | P17: 0 | Q17: 0 | R17: 0 | S17: 0 | T17: 0 | U17: 0 | V17: 0 | W17: 0 | X17: 0 | Y17: 0 | Z17: 0 | AA17: 0 | AB17: 0 | AC17: 0 | AD17: 0 | AE17: 0.18952 | AF17: 0 | AG17: 0 | AH17: 0 | AI17: 0 | AJ17: 0.18952
B18: 1103 | C18: Bancos y otras instituciones financieras | D18: 75499.074 | E18: 46085.319 | F18: 176029.6 | G18: 386545.32 | H18: 684159.31 | I18: 153632.49 | J18: 317806.54 | K18: 68087.035 | L18: 76357.169 | M18: 88238.284 | N18: 237649.25 | O18: 37053.445 | P18: 67291.111 | Q18: 32031.893 | R18: 1078147.2 | S18: 24336.873 | T18: 21578.436 | U18: 552.36562 | V18: 261.69236 | W18: 50344.235 | X18: 438.28388 | Y18: 1740.3002 | Z18: 3695.934 | AA18: 2217.2749 | AB18: 9918.0731 | AC18: 2108.2731 | AD18: 117191.74 | AE18: 1879498.3 | AF18: 305736.29 | AG18: 164857.15 | AH18: 0 | AI18: 6065.8482 | AJ18: 1402839
B19: 110305 | C19: Banco Central del Ecuador | D19: 0 | E19: 0 | F19: 0 | G19: 0 | H19: 0 | I19: 0 | J19: 0 | K19: 0 | L19: 0 | M19: 0 | N19: 0 | O19: 0 | P19: 0 | Q19: 0 | R19: 0 | S19: 0 | T19: 0 | U19: 0 | V19: 0 | W19: 0 | X19: 0 | Y19: 0.123 | Z19: 0 | AA19: 0 | AB19: 0 | AC19: 0 | AD19: 0.123 | AE19: 0.123 | AF19: 0 | AG19: 0 | AH19: 0 | AI19: 0.123 | AJ19: 0
B20: 110310 | C20: Bancos e instituciones financieras locales | D20: 45792.245 | E20: 2819.3998 | F20: 6309.2033 | G20: 284416.96 | H20: 339337.81 | I20: 133429.13 | J20: 165824.45 | K20: 25196.162 | L20: 67808.648 | M20: 67299.589 | N20: 91258.037 | O20: 20475.04 | P20: 51853.547 | Q20: 11006.177 | R20: 634150.77 | S20: 18883.319 | T20: 19999.559 | U20: 137.31506 | V20: 261.69236 | W20: 50344.235 | X20: 424.32019 | Y20: 719.64398 | Z20: 3361.6144 | AA20: 2217.2749 | AB20: 8493.4436 | AC20: 2108.2731 | AD20: 106950.69 | AE20: 1080439.3 | AF20: 116454.2 | AG20: 135369.93 | AH20: 0 | AI20: 5045.192 | AJ20: 823569.95
B21: 110315 | C21: Bancos e instituciones financieras del exterior | D21: 29706.829 | E21: 43265.919 | F21: 169720.39 | G21: 102128.36 | H21: 344821.5 | I21: 20203.357 | J21: 151982.09 | K21: 42890.873 | L21: 8548.5209 | M21: 20938.696 | N21: 146391.21 | O21: 16578.405 | P21: 15437.564 | Q21: 21025.716 | R21: 443996.44 | S21: 5453.5532 | T21: 1578.877 | U21: 415.05056 | V21: 0 | W21: 0 | X21: 13.96369 | Y21: 0 | Z21: 334.31962 | AA21: 0 | AB21: 1424.6294 | AC21: 0 | AD21: 9220.3936 | AE21: 798038.33 | AF21: 189282.09 | AG21: 29487.217 | AH21: 0 | AI21: 0 | AJ21: 579269.03
... B750: +1+4 | C750: TOTAL ACTIVO Y GASTOS | D750: 6720401.7 | E750: 7166919.2 | F750: 14459710 | G750: 6494865.8 | H750: 34841897 | I750: 2528857.7 | J750: 4508834.7 | K750: 649992.59 | L750: 2434861.2 | M750: 1056537.3 | N750: 4409829.8 | O750: 711134.47 | P750: 1003220 | Q750: 890489.84 | R750: 18193758 | S750: 619091.76 | T750: 302659.7 | U750: 63659.166 | V750: 42292.298 | W750: 208925.49 | X750: 42059.295 | Y750: 91765.34 | Z750: 34248.497 | AA750: 117124.11 | AB750: 254743.28 | AC750: 105520.36 | AD750: 1882089.3 | AE750: 54917743 | AF750: 5059822.4 | AG750: 3533690.7 | AH750: 0 | AI750: 314409.81 | AJ750: 46009820
C752: PASIVOS
B753: 21 | C753: OBLIGACIONES CON EL PÚBLICO | D753: 5098291.4 | E753: 5282140.4 | F753: 11260193 | G753: 4851768.7 | H753: 26492394 | I753: 2043022.2 | J753: 3498858.9 | K753: 506984.53 | L753: 1091780.9 | M753: 850333.16 | N753: 3577829.7 | O753: 569346.89 | P753: 830901.15 | Q753: 398910.15 | R753: 13367967 | S753: 345261.97 | T753: 243751.96 | U753: 46134.849 | V753: 27574.166 | W753: 168108.17 | X753: 30666.169 | Y753: 64693.752 | Z753: 18033.29 | AA753: 45329.211 | AB753: 178481.48 | AC753: 19702.17 | AD753: 1187737.2 | AE753: 41048098 | AF753: 4084814.2 | AG753: 1969688.2 | AH753: 0 | AI753: 129725.13 | AJ753: 34863871
B754: 2101 | C754: Depósitos a la vista | D754: 3091403.9 | E754: 2690974.5 | F754: 7653545.9 | G754: 2991157.7 | H754: 16427082 | I754: 1041303.6 | J754: 2251664.5 | K754: 506378.72 | L754: 15940.699 | M754: 383238.38 | N754: 2129772.6 | O754: 314083.2 | P754: 438619.01 | Q754: 81383.456 | R754: 7162384.1 | S754: 204989.79 | T754: 88498.148 | U754: 34342.513 | V754: 9971.3719 | W754: 118078.25 | X754: 3390.7132 | Y754: 6094.0138 | Z754: 9576.378 | AA754: 6153.6148 | AB754: 66437.076 | AC754: 6076.2931 | AD754: 553608.16 | AE754: 24143074 | AF754: 2636151.3 | AG754: 409150.45 | AH754: 0 | AI754: 18323.922 | AJ754: 21079449
B755: 210105 | C755: Depósitos monetarios que generan INTERESES | D755: 691912.26 | E755: 531285.49 | F755: 451679.73 | G755: 6040.5508 | H755: 1680918 | I755: 61202.732 | J755: 395908.36 | K755: 47152.536 | L755: 0 | M755: 47164.446 | N755: 1077389.9 | O755: 0 | P755: 0 | Q755: 9535.8907 | R755: 1638353.8 | S755: 58995.71 | T755: 691.70534 | U755: 4012.6628 | V755: 0 | W755: 0 | X755: 1584.5034 | Y755: 0 | Z755: 0 | AA755: 0 | AB755: 3551.7512 | AC755: 0 | AD755: 68836.333 | AE755: 3388108.2 | AF755: 1124542.4 | AG755: 47164.446 | AH755: 0 | AI755: 0 | AJ755: 2216401.3
B756: 210110 | C756: Depósitos monetarios que no generan INTERESES | D756: 925675.76 | E756: 882951.78 | F756: 2787864.2 | G756: 1564825.8 | H756: 6161317.5 | I756: 182572.73 | J756: 786227.92 | K756: 454130.7 | L756: 0 | M756: 40911.363 | N756: 179151.17 | O756: 73883.775 | P756: 146809.34 | Q756: 32.90972 | R756: 1863719.9 | S756: 0 | T756: 22115.828 | U756: 8662.6735 | V756: 3668.7931 | W756: 246.77431 | X756: 36.78497 | Y756: 0 | Z756: 2813.5583 | AA756: 0 | AB756: 0 | AC756: 0 | AD756: 37544.412 | AE756: 8062581.8 | AF756: 633281.87 | AG756: 44580.156 | AH756: 0 | AI756: 0 | AJ756: 7384719.8
B757: 210115 | C757: Depósitos monetarios de instituciones financieras | D757: 151385.35 | E757: 7614.7 | F757: 141271.27 | G757: 82116.089 | H757: 382387.41 | I757: 86485.354 | J757: 226649.46 | K757: 581.339 | L757: 0 | M757: 5227.5146 | N757: 134015.23 | O757: 3885.7995 | P757: 14563.529 | Q757: 5.75253 | R757: 471413.98 | S757: 5256.6248 | T757: 773.94065 | U757: 54.59913 | V757: 0 | W757: 0 | X757: 0 | Y757: 0 | Z757: 0 | AA757: 0 | AB757: 1898.3533 | AC757: 0 | AD757: 7983.5179 | AE757: 861784.9 | AF757: 134596.57 | AG757: 5227.5146 | AH757: 0 | AI757: 0 | AJ757: 721960.82
B758: 210120 | C758: EJECUCIÓN PRESUPUESTARIA | D758: 2082.0787 | E758: 5e-05 | F758: 0 | G758: 0 | H758: 2082.0787 | I758: 0 | J758: 12419.09 | K758: 0 | L758: 0 | M758: 0 | N758: 0 | O758: 366.52952 | P758: 621.44252 | Q758: 0 | R758: 13407.062 | S758: 0 | T758: 0 | U758: 0 | V758: 0 | W758: 0 | X758: 0 | Y758: 0 | Z758: 0 | AA758: 0 | AB758: 0 | AC758: 0 | AD758: 0 | AE758: 15489.141 | AF758: 0 | AG758: 0 | AH758: 0 | AI758: 0 | AJ758: 15489.141
B759: 210125 | C759: Depósitos de otras instituciones para encaje | D759: 0 | E759: 0 | F759: 0 | G759: 0 | H759: 0 | I759: 0 | J759: 0 | K759: 0 | L759: 0 | M759: 0 | N759: 0 | O759: 0 | P759: 0 | Q759: 0 | R759: 0 | S759: 0 | T759: 0 | U759: 0 | V759: 0 | W759: 0 | X759: 0 | Y759: 0 | Z759: 0 | AA759: 0 | AB759: 0 | AC759: 0 | AD759: 0 | AE759: 0 | AF759: 0 | AG759: 0 | AH759: 0 | AI759: 0 | AJ759: 0
B760: 210130 | C760: Cheques certificados | D760: 6526.5809 | E760: 9775.8722 | F760: 24154.877 | G760: 9711.5572 | H760: 50168.887 | I760: 2281.6839 | J760: 9360.0254 | K760: 2392.176 | L760: 0 | M760: 410.83918 | N760: 3946.1938 | O760: 317.48773 | P760: 1148.5665 | Q760: 6.17596 | R760: 19863.148 | S760: 99.50313 | T760: 112.74102 | U760: 37.33546 | V760: 170.75842 | W760: 34.60033 | X760: 39.8566 | Y760: 0 | Z760: 27.00323 | AA760: 0 | AB760: 6.74928 | AC760: 0 | AD760: 528.54747 | AE760: 70560.583 | AF760: 6338.3698 | AG760: 581.5976 | AH760: 0 | AI760: 0 | AJ760: 63640.616
B761: 210131 | C761: Cheques de emergencia | D761: 4079.5133 | E761: 0 | F761: 10521.58 | G761: 6642.9914 | H761: 21244.084 | I761: 1445.4536 | J761: 25657.924 | K761: 0 | L761: 0 | M761: 1192.5425 | N761: 2734.6426 | O761: 342.8401 | P761: 498.10961 | Q761: 501.15331 | R761: 32372.666 | S761: 39.10098 | T761: 0 | U761: 0 | V761: 416.97039 | W761: 120.03669 | X761: 0 | Y761: 0 | Z761: 42.14342 | AA761: 0 | AB761: 0 | AC761: 0 | AD761: 618.25148 | AE761: 54235.002 | AF761: 2734.6426 | AG761: 1609.5129 | AH761: 0 | AI761: 0 | AJ761: 49890.846
B762: 210135 | C762: Depósitos de ahorro | D762: 1246548.1 | E762: 1159518 | F762: 4140122.1 | G762: 1264794.6 | H762: 7810982.7 | I762: 698871.21 | J762: 739362.51 | K762: 0 | L762: 1487.0937 | M762: 285498.53 | N762: 704138.17 | O762: 232189.95 | P762: 270580.27 | Q762: 68902.635 | R762: 3001030.4 | S762: 139469.29 | T762: 60993.983 | U762: 21309.771 | V762: 5521.0313 | W762: 117604.13 | X762: 1651.1049 | Y762: 5778.6044 | Z762: 6475.3913 | AA762: 6153.6148 | AB762: 60872.492 | AC762: 6049.2068 | AD762: 431878.62 | AE762: 11243892 | AF762: 704138.17 | AG762: 292506.66 | AH762: 0 | AI762: 17981.426 | AJ762: 10229265
B763: 210140 | C763: Otros depósitos | D763: 2146.41 | E763: 73159.936 | F763: 14650.761 | G763: 18265.704 | H763: 108222.81 | I763: 83.49137 | J763: 20640.937 | K763: 0 | L763: 6094.9157 | M763: 1103.2338 | N763: 2425.7368 | O763: 1338.051 | P763: 190.03601 | Q763: 1732.3078 | R763: 33608.71 | S763: 0 | T763: 3422.4918 | U763: 2.71882 | V763: 56.18045 | W763: 0 | X763: 78.46336 | Y763: 294.15057 | Z763: 195.44974 | AA763: 0 | AB763: 66.98949 | AC763: 27.08626 | AD763: 4143.5305 | AE763: 145975.05 | AF763: 2425.7368 | AG763: 7254.3299 | AH763: 0 | AI763: 321.23683 | AJ763: 135973.75
B764: 210145 | C764: Fondos de tarjetahabientes | D764: 14709.39 | E764: 10707.65 | F764: 5309.3798 | G764: 5585.591 | H764: 36312.011 | I764: 1652.6086 | J764: 1313.7472 | K764: 0 | L764: 8358.6895 | M764: 406.99541 | N764: 1440.1814 | O764: 75.04551 | P764: 189.58823 | Q764: 614.43492 | R764: 14051.291 | S764: 0 | T764: 121.75672 | U764: 0 | V764: 0 | W764: 0 | X764: 0 | Y764: 0 | Z764: 0 | AA764: 0 | AB764: 0 | AC764: 0 | AD764: 121.75672 | AE764: 50485.058 | AF764: 1440.1814 | AG764: 8765.685 | AH764: 0 | AI764: 0 | AJ764: 40279.192
... B950: 2 | C950: TOTAL PASIVOS | D950: 5870316.9 | E950: 6047165.1 | F950: 12461234 | G950: 5761221 | H950: 30139937 | I950: 2200363.1 | J950: 3971910.8 | K950: 552845.32 | L950: 1764778.2 | M950: 916562.72 | N950: 3861409.6 | O950: 616619.95 | P950: 896526.4 | Q950: 665467.91 | R950: 15446484 | S950: 538183.58 | T950: 265984.79 | U950: 47337.254 | V950: 29001.672 | W950: 171819.94 | X950: 33376.217 | Y950: 76158.429 | Z950: 20359.347 | AA950: 88455.75 | AB950: 212512.56 | AC950: 78723.338 | AD950: 1561912.9 | AE950: 47148334 | AF950: 4414255 | AG950: 2710342.6 | AH950: 0 | AI950: 243337.52 | AJ950: 39780398
C952: PATRIMONIO
B953: 31 | C953: CAPITAL SOCIAL | D953: 483370 | E953: 582479.74 | F953: 919241.6 | G953: 394760 | H953: 2379851.3 | I953: 152900 | J953: 325000 | K953: 68559.042 | L953: 300000 | M953: 70334.805 | N953: 333706.68 | O953: 46700 | P953: 56300 | Q953: 93522.016 | R953: 1447022.5 | S953: 51931 | T953: 21083.923 | U953: 11010.6 | V953: 11090.785 | W953: 21738.121 | X953: 11000 | Y953: 18663.2 | Z953: 11356.808 | AA953: 20968.6 | AB953: 20846.8 | AC953: 16701.1 | AD953: 216390.94 | AE953: 4043264.8 | AF953: 402265.72 | AG953: 381425.59 | AH953: 0 | AI953: 56332.9 | AJ953: 3203240.6
B954: 3101 | C954: Capital pagado | D954: 483370 | E954: 582479.74 | F954: 919241.6 | G954: 394760 | H954: 2379851.3 | I954: 152900 | J954: 325000 | K954: 68559.042 | L954: 300000 | M954: 70334.805 | N954: 333706.68 | O954: 46700 | P954: 56300 | Q954: 100997.65 | R954: 1454498.2 | S954: 51931 | T954: 21083.923 | U954: 11010.6 | V954: 11090.785 | W954: 21738.121 | X954: 11000 | Y954: 18663.2 | Z954: 11356.808 | AA954: 20968.6 | AB954: 20846.8 | AC954: 16701.1 | AD954: 216390.94 | AE954: 4050740.5 | AF954: 402265.72 | AG954: 381425.59 | AH954: 0 | AI954: 56332.9 | AJ954: 3210716.2
B955: 3102 | C955: (Acciones en tesorería) | D955: 0 | E955: 0 | F955: 0 | G955: 0 | H955: 0 | I955: 0 | J955: 0 | K955: 0 | L955: 0 | M955: 0 | N955: 0 | O955: 0 | P955: 0 | Q955: -7475.634 | R955: -7475.634 | S955: 0 | T955: 0 | U955: 0 | V955: 0 | W955: 0 | X955: 0 | Y955: 0 | Z955: 0 | AA955: 0 | AB955: 0 | AC955: 0 | AD955: 0 | AE955: -7475.634 | AF955: 0 | AG955: 0 | AH955: 0 | AI955: 0 | AJ955: -7475.634
B956: 3103 | C956: Aportes de socios | D956: 0 | E956: 0 | F956: 0 | G956: 0 | H956: 0 | I956: 0 | J956: 0 | K956: 0 | L956: 0 | M956: 0 | N956: 0 | O956: 0 | P956: 0 | Q956: 0 | R956: 0 | S956: 0 | T956: 0 | U956: 0 | V956: 0 | W956: 0 | X956: 0 | Y956: 0 | Z956: 0 | AA956: 0 | AB956: 0 | AC956: 0 | AD956: 0 | AE956: 0 | AF956: 0 | AG956: 0 | AH956: 0 | AI956: 0 | AJ956: 0
B957: 32 | C957: PRIMA O DESCUENTO EN COLOCACIÓN DE ACCIONES Y CERTIFICADOS | D957: 0 | E957: 0 | F957: 0 | G957: 1104.7742 | H957: 1104.7742 | I957: 0 | J957: 0 | K957: 0 | L957: 0 | M957: 0 | N957: 0 | O957: 0 | P957: 0 | Q957: 1204.77 | R957: 1204.77 | S957: 0 | T957: 0 | U957: 0 | V957: 0 | W957: 0 | X957: 0 | Y957: 0 | Z957: 0 | AA957: 0 | AB957: 0 | AC957: 0 | AD957: 0 | AE957: 2309.5442 | AF957: 0 | AG957: 0 | AH957: 0 | AI957: 0 | AJ957: 2309.5442
B958: 3201 | C958: Prima EN COLOCACIÓN de acciones y certificados de aportación | D958: 0 | E958: 0 | F958: 0 | G958: 1104.7742 | H958: 1104.7742 | I958: 0 | J958: 0 | K958: 0 | L958: 0 | M958: 0 | N958: 0 | O958: 0 | P958: 0 | Q958: 1204.77 | R958: 1204.77 | S958: 0 | T958: 0 | U958: 0 | V958: 0 | W958: 0 | X958: 0 | Y958: 0 | Z958: 0 | AA958: 0 | AB958: 0 | AC958: 0 | AD958: 0 | AE958: 2309.5442 | AF958: 0 | AG958: 0 | AH958: 0 | AI958: 0 | AJ958: 2309.5442
B959: 3202 | C959: (Descuento en colocación de acciones) | D959: 0 | E959: 0 | F959: 0 | G959: 0 | H959: 0 | I959: 0 | J959: 0 | K959: 0 | L959: 0 | M959: 0 | N959: 0 | O959: 0 | P959: 0 | Q959: 0 | R959: 0 | S959: 0 | T959: 0 | U959: 0 | V959: 0 | W959: 0 | X959: 0 | Y959: 0 | Z959: 0 | AA959: 0 | AB959: 0 | AC959: 0 | AD959: 0 | AE959: 0 | AF959: 0 | AG959: 0 | AH959: 0 | AI959: 0 | AJ959: 0
B960: 33 | C960: RESERVAS | D960: 80224.95 | E960: 149343.47 | F960: 284176.97 | G960: 91529.105 | H960: 605274.49 | I960: 39542.328 | J960: 52752.481 | K960: 11847.53 | L960: 144068 | M960: 17448.666 | N960: 55080.156 | O960: 9954.8961 | P960: 7305.697 | Q960: 39301.863 | R960: 377301.62 | S960: 5867.0629 | T960: 1924.9699 | U960: 1483.3251 | V960: 459.54687 | W960: 8248.9282 | X960: 0 | Y960: 0.02658 | Z960: 112.1461 | AA960: 1088.5892 | AB960: 3198.3423 | AC960: 958.70372 | AD960: 23341.641 | AE960: 1005917.7 | AF960: 66927.686 | AG960: 161976.21 | AH960: 0 | AI960: 2047.3195 | AJ960: 774966.53
B961: 3301 | C961: Legales | D961: 78991.199 | E961: 149342.63 | F961: 145100.64 | G961: 62680.189 | H961: 436114.67 | I961: 18241.42 | J961: 49003.27 | K961: 11847.53 | L961: 66999.833 | M961: 11214.171 | N961: 55080.156 | O961: 8405.7208 | P961: 4925.2537 | Q961: 18415.064 | R961: 244132.42 | S961: 5650.8614 | T961: 1492.0749 | U961: 973.87988 | V961: 414.07895 | W961: 6616.3041 | X961: 0 | Y961: 0.02658 | Z961: 112.1461 | AA961: 1088.5355 | AB961: 3092.3588 | AC961: 958.11118 | AD961: 20398.377 | AE961: 700645.46 | AF961: 66927.686 | AG961: 78628.082 | AH961: 0 | AI961: 2046.6732 | AJ961: 553043.02
B962: 3302 | C962: Generales | D962: 0 | E962: 0 | F962: 0 | G962: 0 | H962: 0 | I962: 0 | J962: 0 | K962: 0 | L962: 0 | M962: 0 | N962: 0 | O962: 0 | P962: 0 | Q962: 0 | R962: 0 | S962: 0 | T962: 0 | U962: 0 | V962: 0 | W962: 0 | X962: 0 | Y962: 0 | Z962: 0 | AA962: 0 | AB962: 0 | AC962: 0 | AD962: 0 | AE962: 0 | AF962: 0 | AG962: 0 | AH962: 0 | AI962: 0 | AJ962: 0
B963: 3303 | C963: Especiales | D963: 6.9432 | E963: 0.83412 | F963: 108190.1 | G963: 28848.916 | H963: 137046.79 | I963: 17302.54 | J963: 790.30257 | K963: 0 | L963: 74105.868 | M963: 6234.495 | N963: 0 | O963: 6.40264 | P963: 2377.646 | Q963: 18582.097 | R963: 119399.35 | S963: 216.20155 | T963: 432.895 | U963: 218.69378 | V963: 45.46792 | W963: 661.00467 | X963: 0 | Y963: 0 | Z963: 0 | AA963: 0.05371 | AB963: 78.32625 | AC963: 0.59254 | AD963: 1653.2354 | AE963: 258099.38 | AF963: 0 | AG963: 80385.831 | AH963: 0 | AI963: 0.64625 | AJ963: 177712.9
B964: 330305 | C964: A disposición de la Junta General de Accionistas | D964: 0 | E964: 0 | F964: 0 | G964: 0 | H964: 0 | I964: 0 | J964: 0 | K964: 0 | L964: 74018.7 | M964: 0 | N964: 0 | O964: 5.9899 | P964: 0 | Q964: 9820.3623 | R964: 83845.052 | S964: 0 | T964: 0 | U964: 0 | V964: 0 | W964: 0 | X964: 0 | Y964: 0 | Z964: 0 | AA964: 0 | AB964: 0 | AC964: 0 | AD964: 0 | AE964: 83845.052 | AF964: 0 | AG964: 74018.7 | AH964: 0 | AI964: 0 | AJ964: 9826.3522
... B1398: 749090 | C1398: Otras | D1398: 507559.57 | E1398: 50213.706 | F1398: 8969.1492 | G1398: 229.10663 | H1398: 566971.54 | I1398: 0 | J1398: 0 | K1398: 0 | L1398: 1239.294 | M1398: 0 | N1398: 9286.3857 | O1398: 0 | P1398: 0 | Q1398: 755.46489 | R1398: 11281.145 | S1398: 0 | T1398: 0 | U1398: 0 | V1398: 258.02682 | W1398: 0 | X1398: 0 | Y1398: 4.00889 | Z1398: 0 | AA1398: 184.27697 | AB1398: 268546.12 | AC1398: 0 | AD1398: 268992.43 | AE1398: 847245.11 | AF1398: 9286.3857 | AG1398: 1497.3208 | AH1398: 0 | AI1398: 188.28586 | AJ1398: 836273.12

Sheet PYG
B3: ESTADO DE PÉRDIDAS Y GANANCIAS
B4: SISTEMA DE BANCOS PRIVADOS
B5: 31/05/2022
B6: (en miles de dólares)
B8: CÓDIGO | C8: CUENTA | D8: BP GUAYAQUIL | E8: BP PACIFICO | F8: BP PICHINCHA | G8: BP PRODUBANCO | H8: BANCOS PRIVADOS GRANDES | I8: BP AUSTRO | J8: BP BOLIVARIANO | K8: BP CITIBANK | L8: BP DINERS | M8: BP GENERAL RUMIÑAHUI | N8: BP INTERNACIONAL | O8: BP LOJA | P8: BP MACHALA | Q8: BP SOLIDARIO | R8: BANCOS PRIVADOS MEDIANOS | S8: BP PROCREDIT | T8: BP AMAZONAS | U8: BP COMERCIAL DE MANABI | V8: BP LITORAL | W8: BP COOPNACIONAL | X8: BP CAPITAL | Y8: BP FINCA S.A. | Z8: BP DELBANK | AA8: BP D-MIRO S.A. | AB8: BP BANCO DESARROLLO DE LOS PUEBLOS S.A., CODESARROLLO | AC8: BP VISIONFUND ECUADOR S.A. | AD8: BANCOS PRIVADOS PEQUEÑOS | AE8: TOTAL BANCOS PRIVADOS | AF8: BANCOS PRIVADOS COMERCIALES | AG8: BANCOS PRIVADOS CONSUMO | AH8: BANCOS PRIVADOS VIVIENDA | AI8: BANCOS PRIVADOS MICROCRÉDITO | AJ8: BANCA MÚLTIPLE
B9: 5 | C9: INGRESOS | D9: 280589.69 | E9: 313909.88 | F9: 693081.01 | G9: 251156.38 | H9: 1538737 | I9: 103852.22 | J9: 141997.92 | K9: 14640.735 | L9: 204880.25 | M9: 50553.748 | N9: 137340.75 | O9: 30215.888 | P9: 34967.509 | Q9: 64978.528 | R9: 783427.55 | S9: 23028.038 | T9: 10146.072 | U9: 2551.0985 | V9: 1937.5385 | W9: 5316.8333 | X9: 1788.6673 | Y9: 6064.1115 | Z9: 2403.6031 | AA9: 8732.324 | AB9: 15393.983 | AC9: 9118.902 | AD9: 86481.172 | AE9: 2408645.7 | AF9: 151981.48 | AG9: 257371.54 | AH9: 0 | AI9: 23915.337 | AJ9: 1975377.3
B11: 51 | C11: INTERESES Y DESCUENTOS GANADOS | D11: 189422.83 | E11: 188353.53 | F11: 495094.73 | G11: 174265.78 | H11: 1047136.9 | I11: 73879.63 | J11: 106657.78 | K11: 8156.053 | L11: 95562.788 | M11: 41279.22 | N11: 105946.53 | O11: 26168.463 | P11: 29467.281 | Q11: 49986.87 | R11: 537104.61 | S11: 19359.314 | T11: 8165.1041 | U11: 2194.2895 | V11: 1744.4078 | W11: 4440.8967 | X11: 1344.9549 | Y11: 4762.6559 | Z11: 751.80424 | AA11: 6800.046 | AB11: 12162.182 | AC11: 7855.6289 | AD11: 69581.284 | AE11: 1653822.8 | AF11: 114102.58 | AG11: 138586.42 | AH11: 0 | AI11: 19418.331 | AJ11: 1381715.4
B12: 5101 | C12: Depósitos | D12: 157.83461 | E12: 17.99605 | F12: 153.9894 | G12: 773.74569 | H12: 1103.5657 | I12: 1446.8079 | J12: 1032.17 | K12: 124.082 | L12: 18.30715 | M12: 371.18347 | N12: 814.64618 | O12: 69.33644 | P12: 264.42677 | Q12: 33.09515 | R12: 4174.0551 | S12: 92.97459 | T12: 84.3205 | U12: 0.08611 | V12: 0.06393 | W12: 758.7828 | X12: 0.9562 | Y12: 0.40026 | Z12: 29.18173 | AA12: 4.56843 | AB12: 42.69692 | AC12: 19.13907 | AD12: 1033.1705 | AE12: 6310.7914 | AF12: 938.72818 | AG12: 389.55455 | AH12: 0 | AI12: 24.10776 | AJ12: 4958.4009
B13: 5102 | C13: Operaciones interbancarias | D13: 0 | E13: 0 | F13: 3.92777 | G13: 40.62495 | H13: 44.55272 | I13: 0 | J13: 12.50004 | K13: 6.417 | L13: 0.16667 | M13: 0 | N13: 0 | O13: 0 | P13: 0 | Q13: 0 | R13: 19.08371 | S13: 0 | T13: 0 | U13: 0 | V13: 0 | W13: 0 | X13: 0 | Y13: 0 | Z13: 0 | AA13: 0 | AB13: 0 | AC13: 0 | AD13: 0 | AE13: 63.63643 | AF13: 6.417 | AG13: 0.16667 | AH13: 0 | AI13: 0 | AJ13: 57.05276
B14: 5103 | C14: INTERESES y descuentos de inversiones en títulos valores | D14: 6965.9511 | E14: 9026.2905 | F14: 29774.536 | G14: 4416.2216 | H14: 50183 | I14: 7808.7106 | J14: 3872.2623 | K14: 2255.166 | L14: 937.25258 | M14: 1039.6202 | N14: 8203.024 | O14: 851.21106 | P14: 2408.4704 | Q14: 635.07073 | R14: 28010.788 | S14: 183.77729 | T14: 1072.1551 | U14: 124.10633 | V14: 55.4918 | W14: 1012.773 | X14: 38.0101 | Y14: 32.35608 | Z14: 81.53124 | AA14: 326.21716 | AB14: 359.07322 | AC14: 19.65691 | AD14: 3305.1482 | AE14: 81498.936 | AF14: 10458.19 | AG14: 2032.3646 | AH14: 0 | AI14: 378.23015 | AJ14: 68630.151
B15: 5104 | C15: INTERESES Y DESCUENTOS DE CARTERA DE CRÉDITOS | D15: 182299.04 | E15: 179296.71 | F15: 464055.01 | G15: 169035.19 | H15: 994685.95 | I15: 64621.977 | J15: 101559.5 | K15: 5750.991 | L15: 94599.849 | M15: 39868.417 | N15: 96928.858 | O15: 25247.915 | P15: 26794.384 | Q15: 49318.705 | R15: 504690.59 | S15: 19082.563 | T15: 7001.854 | U15: 2066.673 | V15: 1688.8521 | W15: 2669.3409 | X15: 1305.9886 | Y15: 4729.8995 | Z15: 641.09127 | AA15: 6469.2604 | AB15: 11760.412 | AC15: 7816.8329 | AD15: 65232.767 | AE15: 1564609.3 | AF15: 102679.85 | AG15: 136157.12 | AH15: 0 | AI15: 19015.993 | AJ15: 1306756.3
B16: 510405 | C16: CARTERA DE CRÉDITOS PRODUCTIVO | D16: 63615.006 | E16: 27985.813 | F16: 103171.15 | G16: 80216.316 | H16: 274988.28 | I16: 23334.552 | J16: 60782.535 | K16: 5653.649 | L16: 686.38203 | M16: 1903.1151 | N16: 67464.388 | O16: 4404.1178 | P16: 14656.796 | Q16: 0 | R16: 178885.53 | S16: 12897.094 | T16: 2422.5485 | U16: 706.84921 | V16: 270.03638 | W16: 1969.9934 | X16: 43.54542 | Y16: 0 | Z16: 277.6009 | AA16: 0 | AB16: 730.77961 | AC16: 0 | AD16: 19318.447 | AE16: 473192.26 | AF16: 73118.037 | AG16: 2859.5335 | AH16: 0 | AI16: 0 | AJ16: 397214.69
B17: 510410 | C17: CARTERA DE CRÉDITOS DE CONSUMO | D17: 85658.113 | E17: 104470 | F17: 183911.9 | G17: 68087.608 | H17: 442127.62 | I17: 30619.841 | J17: 36326.173 | K17: 0 | L17: 88902.298 | M17: 32332.094 | N17: 20420.194 | O17: 10741.283 | P17: 9976.0428 | Q17: 18020.953 | R17: 247338.88 | S17: 186.73662 | T17: 3969.1415 | U17: 572.65684 | V17: 1063.5489 | W17: 50.15229 | X17: 943.65635 | Y17: 255.76204 | Z17: 175.68583 | AA17: 0 | AB17: 3407.8222 | AC17: 2.81714 | AD17: 10627.98 | AE17: 700094.48 | AF17: 20420.194 | AG17: 122297.94 | AH17: 0 | AI17: 258.57918 | AJ17: 557117.76
B18: 510415 | C18: CARTERA DE CRÉDITOS INMOBILIARIO | D18: 7734.176 | E18: 14396.135 | F18: 26036.144 | G18: 10105.097 | H18: 58271.552 | I18: 2381.0797 | J18: 2936.2098 | K18: 0 | L18: 1.19067 | M18: 3469.1737 | N18: 4648.122 | O18: 1554.7755 | P18: 846.95498 | Q18: 0.76157 | R18: 15838.268 | S18: 1046.8981 | T18: 53.31391 | U18: 0.40337 | V18: 1.22424 | W18: 4.84579 | X18: 0 | Y18: 0 | Z18: 68.95093 | AA18: 0 | AB18: 270.0618 | AC18: 0 | AD18: 1445.6981 | AE18: 75555.518 | AF18: 4648.122 | AG18: 3471.5886 | AH18: 0 | AI18: 0 | AJ18: 67435.807
B19: 510420 | C19: CARTERA DE CRÉDITOS PARA MICROCRÉDITO | D19: 17663.01 | E19: 289.4033 | F19: 105967.67 | G19: 1483.6005 | H19: 125403.68 | I19: 474.22521 | J19: 0 | K19: 0 | L19: 0 | M19: 0 | N19: 143.73113 | O19: 5234.3942 | P19: 314.02009 | Q19: 30264.633 | R19: 36431.004 | S19: 3683.5234 | T19: 2.21905 | U19: 572.24107 | V19: 92.05135 | W19: 642.45023 | X19: 87.46005 | Y19: 3734.013 | Z19: 3.97093 | AA19: 6221.9044 | AB19: 4913.1418 | AC19: 7513.5875 | AD19: 27466.563 | AE19: 189301.25 | AF19: 143.73113 | AG19: 92.05135 | AH19: 0 | AI19: 17469.505 | AJ19: 171595.96
B20: 510427 | C20: CARTERA DE CRÉDITO DE VIVIENDA DE INTERÉS SOCIAL Y PÚBLICO | D20: 0 | E20: 583.12607 | F20: 1450.6134 | G20: 0 | H20: 2033.7395 | I20: 0 | J20: 0 | K20: 0 | L20: 0 | M20: 68.28818 | N20: 8.0266 | O20: 0 | P20: 0 | Q20: 0 | R20: 76.31478 | S20: 0 | T20: 0 | U20: 0 | V20: 0 | W20: 0 | X20: 0 | Y20: 0 | Z20: 0 | AA20: 0 | AB20: 0 | AC20: 0 | AD20: 0 | AE20: 2110.0543 | AF20: 8.0266 | AG20: 68.28818 | AH20: 0 | AI20: 0 | AJ20: 2033.7395
B21: 510428 | C21: CARTERA DE CRÉDITO EDUCATIVO | D21: 82.56158 | E21: 10648.847 | F21: 712.65514 | G21: 42.60958 | H21: 11486.673 | I21: 0 | J21: 106.63579 | K21: 0 | L21: 0 | M21: 0 | N21: 0 | O21: 12.03454 | P21: 103.01293 | Q21: 0 | R21: 221.68326 | S21: 9.77186 | T21: 0 | U21: 0 | V21: 0 | W21: 0 | X21: 0 | Y21: 0 | Z21: 0 | AA21: 0 | AB21: 0 | AC21: 0 | AD21: 9.77186 | AE21: 11718.128 | AF21: 0 | AG21: 0 | AH21: 0 | AI21: 0 | AJ21: 11718.128
... B33: 4105 | C33: Otros INTERESES | D33: 0 | E33: 0 | F33: 4.67618 | G33: 0 | H33: 4.67618 | I33: 0 | J33: 0 | K33: 0 | L33: 0 | M33: 0 | N33: 0 | O33: 0 | P33: 0 | Q33: 0 | R33: 0 | S33: 0 | T33: 0.59317 | U33: 0.03458 | V33: 0 | W33: 0 | X33: 0 | Y33: 0 | Z33: 0 | AA33: 0 | AB33: 0 | AC33: 0 | AD33: 0.62775 | AE33: 5.30393 | AF33: 0 | AG33: 0 | AH33: 0 | AI33: 0 | AJ33: 5.30393
C34: MARGEN NETO INTERESES | D34: 129741.97 | E34: 114579.78 | F34: 397790.34 | G34: 125039.98 | H34: 767152.08 | I34: 42094.41 | J34: 71430.342 | K34: 8130.844 | L34: 69827.586 | M34: 29558.155 | N34: 66545.445 | O34: 17861.672 | P34: 18939.694 | Q34: 36670.234 | R34: 361058.38 | S34: 11615.225 | T34: 3885.1855 | U34: 1850.1956 | V34: 1447.3331 | W34: 3325.7343 | X34: 472.20699 | Y34: 2317.4205 | Z34: 537.14093 | AA34: 3952.6966 | AB34: 7650.0081 | AC34: 6078.5977 | AD34: 43131.744 | AE34: 1171342.2 | AF34: 74676.289 | AG34: 100833.07 | AH34: 0 | AI34: 12348.715 | AJ34: 983484.12
B36: 52 | C36: COMISIONES GANADAS | D36: 21391.943 | E36: 19526.661 | F36: 11137.514 | G36: 11428.572 | H36: 63484.69 | I36: 4720.1361 | J36: 12745.621 | K36: 982.206 | L36: 24600.997 | M36: 1965.1973 | N36: 9779.6769 | O36: 576.79386 | P36: 703.42245 | Q36: 1559.8926 | R36: 57633.943 | S36: 34.82991 | T36: 111.13061 | U36: 7.142 | V36: 0 | W36: 0 | X36: 0 | Y36: 0 | Z36: 23.38586 | AA36: 0 | AB36: 33.56565 | AC36: 0 | AD36: 210.05403 | AE36: 121328.69 | AF36: 10761.883 | AG36: 26566.194 | AH36: 0 | AI36: 0 | AJ36: 84000.61
B37: 5201 | C37: Cartera de créditos | D37: 23.51674 | E37: 0 | F37: 0 | G37: 0 | H37: 23.51674 | I37: 0 | J37: 0 | K37: 0 | L37: 0 | M37: 1.25743 | N37: 0 | O37: 0 | P37: 0 | Q37: 0 | R37: 1.25743 | S37: 0 | T37: 0 | U37: 0 | V37: 0 | W37: 0 | X37: 0 | Y37: 0 | Z37: 0 | AA37: 0 | AB37: 0 | AC37: 0 | AD37: 0 | AE37: 24.77417 | AF37: 0 | AG37: 1.25743 | AH37: 0 | AI37: 0 | AJ37: 23.51674
B38: 520105 | C38: Cartera de créditos productivo | D38: 0.58326 | E38: 0 | F38: 0 | G38: 0 | H38: 0.58326 | I38: 0 | J38: 0 | K38: 0 | L38: 0 | M38: 1.25743 | N38: 0 | O38: 0 | P38: 0 | Q38: 0 | R38: 1.25743 | S38: 0 | T38: 0 | U38: 0 | V38: 0 | W38: 0 | X38: 0 | Y38: 0 | Z38: 0 | AA38: 0 | AB38: 0 | AC38: 0 | AD38: 0 | AE38: 1.84069 | AF38: 0 | AG38: 1.25743 | AH38: 0 | AI38: 0 | AJ38: 0.58326
B39: 520110 | C39: Cartera de créditos de consumo | D39: 17.48745 | E39: 0 | F39: 0 | G39: 0 | H39: 17.48745 | I39: 0 | J39: 0 | K39: 0 | L39: 0 | M39: 0 | N39: 0 | O39: 0 | P39: 0 | Q39: 0 | R39: 0 | S39: 0 | T39: 0 | U39: 0 | V39: 0 | W39: 0 | X39: 0 | Y39: 0 | Z39: 0 | AA39: 0 | AB39: 0 | AC39: 0 | AD39: 0 | AE39: 17.48745 | AF39: 0 | AG39: 0 | AH39: 0 | AI39: 0 | AJ39: 17.48745
B40: 520115 | C40: Cartera de créditos de vivienda | D40: 0 | E40: 0 | F40: 0 | G40: 0 | H40: 0 | I40: 0 | J40: 0 | K40: 0 | L40: 0 | M40: 0 | N40: 0 | O40: 0 | P40: 0 | Q40: 0 | R40: 0 | S40: 0 | T40: 0 | U40: 0 | V40: 0 | W40: 0 | X40: 0 | Y40: 0 | Z40: 0 | AA40: 0 | AB40: 0 | AC40: 0 | AD40: 0 | AE40: 0 | AF40: 0 | AG40: 0 | AH40: 0 | AI40: 0 | AJ40: 0
B41: 520120 | C41: Cartera de créditos PARA MICROCRÉDITO | D41: 5.44603 | E41: 0 | F41: 0 | G41: 0 | H41: 5.44603 | I41: 0 | J41: 0 | K41: 0 | L41: 0 | M41: 0 | N41: 0 | O41: 0 | P41: 0 | Q41: 0 | R41: 0 | S41: 0 | T41: 0 | U41: 0 | V41: 0 | W41: 0 | X41: 0 | Y41: 0 | Z41: 0 | AA41: 0 | AB41: 0 | AC41: 0 | AD41: 0 | AE41: 5.44603 | AF41: 0 | AG41: 0 | AH41: 0 | AI41: 0 | AJ41: 5.44603
B42: 520125 | C42: Cartera de créditos reestructurada | D42: 0 | E42: 0 | F42: 0 | G42: 0 | H42: 0 | I42: 0 | J42: 0 | K42: 0 | L42: 0 | M42: 0 | N42: 0 | O42: 0 | P42: 0 | Q42: 0 | R42: 0 | S42: 0 | T42: 0 | U42: 0 | V42: 0 | W42: 0 | X42: 0 | Y42: 0 | Z42: 0 | AA42: 0 | AB42: 0 | AC42: 0 | AD42: 0 | AE42: 0 | AF42: 0 | AG42: 0 | AH42: 0 | AI42: 0 | AJ42: 0
B43: 5202 | C43: Deudores por aceptación | D43: 0 | E43: 0 | F43: 0 | G43: 0 | H43: 0 | I43: 0 | J43: 13.70995 | K43: 1.268 | L43: 0 | M43: 0 | N43: 0 | O43: 0 | P43: 40.88477 | Q43: 0 | R43: 55.86272 | S43: 0 | T43: 0 | U43: 0 | V43: 0 | W43: 0 | X43: 0 | Y43: 0 | Z43: 0 | AA43: 0 | AB43: 0 | AC43: 0 | AD43: 0 | AE43: 55.86272 | AF43: 1.268 | AG43: 0 | AH43: 0 | AI43: 0 | AJ43: 54.59472
B44: 5203 | C44: Avales | D44: 0 | E44: 6.58925 | F44: 1045.6899 | G44: 180.76152 | H44: 1233.0407 | I44: 54.86167 | J44: 621.95757 | K44: 0 | L44: 0 | M44: 19.88659 | N44: 247.76885 | O44: 35.20413 | P44: 37.68387 | Q44: 0 | R44: 1017.3627 | S44: 0 | T44: 13.85643 | U44: 0 | V44: 0 | W44: 0 | X44: 0 | Y44: 0 | Z44: 0 | AA44: 0 | AB44: 0 | AC44: 0 | AD44: 13.85643 | AE44: 2264.2598 | AF44: 247.76885 | AG44: 19.88659 | AH44: 0 | AI44: 0 | AJ44: 1996.6044
B45: 5204 | C45: Fianzas | D45: 1922.4764 | E45: 1377.0398 | F45: 3534.6389 | G45: 1824.6905 | H45: 8658.8457 | I45: 194.83421 | J45: 1390.762 | K45: 916.181 | L45: 0 | M45: 83.42296 | N45: 1052.1835 | O45: 0 | P45: 160.19944 | Q45: 2.6739 | R45: 3800.257 | S45: 15.77597 | T45: 14.05471 | U45: 7.142 | V45: 0 | W45: 0 | X45: 0 | Y45: 0 | Z45: 0 | AA45: 0 | AB45: 15.4098 | AC45: 0 | AD45: 52.38248 | AE45: 12511.485 | AF45: 1968.3645 | AG45: 83.42296 | AH45: 0 | AI45: 0 | AJ45: 10459.698
B46: 5205 | C46: Cartas de Crédito | D46: 1305.7746 | E46: 334.19445 | F46: 554.79979 | G46: 1153.3802 | H46: 3348.149 | I46: 73.96228 | J46: 1063.7079 | K46: 4.24 | L46: 0 | M46: 9.16902 | N46: 1720.2504 | O46: 0 | P46: 51.29647 | Q46: 0 | R46: 2922.6261 | S46: 17.76155 | T46: 0 | U46: 0 | V46: 0 | W46: 0 | X46: 0 | Y46: 0 | Z46: 0 | AA46: 0 | AB46: 0 | AC46: 0 | AD46: 17.76155 | AE46: 6288.5367 | AF46: 1724.4904 | AG46: 9.16902 | AH46: 0 | AI46: 0 | AJ46: 4554.8773
B47: 5290 | C47: Otras | D47: 18140.175 | E47: 17808.837 | F47: 6002.3857 | G47: 8269.7393 | H47: 50221.137 | I47: 4396.478 | J47: 9655.4838 | K47: 60.517 | L47: 24600.997 | M47: 1851.4613 | N47: 6759.4742 | O47: 541.58973 | P47: 413.3579 | Q47: 1557.2187 | R47: 49836.577 | S47: 1.29239 | T47: 83.21947 | U47: 0 | V47: 0 | W47: 0 | X47: 0 | Y47: 0 | Z47: 23.38586 | AA47: 0 | AB47: 18.15585 | AC47: 0 | AD47: 126.05357 | AE47: 100183.77 | AF47: 6819.9911 | AG47: 26452.458 | AH47: 0 | AI47: 0 | AJ47: 66911.319
... B83: 4390 | C83: Otras | D83: 0 | E83: 0 | F83: 0 | G83: 0 | H83: 0 | I83: 0 | J83: 0 | K83: 0 | L83: 0 | M83: 0 | N83: 0 | O83: 0 | P83: 0 | Q83: 0 | R83: 0 | S83: 0 | T83: 0 | U83: 0 | V83: 0 | W83: 0 | X83: 0 | Y83: 0 | Z83: 0 | AA83: 0 | AB83: 0 | AC83: 0 | AD83: 0 | AE83: 0 | AF83: 0 | AG83: 0 | AH83: 0 | AI83: 0 | AJ83: 0
C84: MARGEN BRUTO FINANCIERO | D84: 195932.67 | E84: 166719.25 | F84: 490455.75 | G84: 174228.87 | H84: 1027336.6 | I84: 51992.468 | J84: 100717.35 | K84: 9769.025 | L84: 148236.41 | M84: 35043.374 | N84: 90404.532 | O84: 19850.19 | P84: 21893.54 | Q84: 44883.56 | R84: 522790.45 | S84: 11567.235 | T84: 4560.3299 | U84: 2034.5267 | V84: 1527.5534 | W84: 3619.715 | X84: 474.54049 | Y84: 2362.8619 | Z84: 1672.6346 | AA84: 4001.0521 | AB84: 8509.2831 | AC84: 6365.9488 | AD84: 46695.681 | AE84: 1596822.7 | AF84: 100173.56 | AG84: 184807.34 | AH84: 0 | AI84: 12729.863 | AJ84: 1299111.9
B86: 44 | C86: PROVISIONES | D86: 39995.063 | E86: 63246.108 | F86: 192322.56 | G86: 37040.822 | H86: 332604.55 | I86: 15662.4 | J86: 12999.859 | K86: 462.469 | L86: 53295.309 | M86: 8917.2994 | N86: 9549.3827 | O86: 5124.3914 | P86: 3558.633 | Q86: 7286.674 | R86: 116856.42 | S86: 4280.5358 | T86: 1262.3231 | U86: 148.92189 | V86: 10.81132 | W86: 155.86145 | X86: 210.28555 | Y86: 102.79245 | Z86: 170.43417 | AA86: 2299.9605 | AB86: 3957.0552 | AC86: 958.12672 | AD86: 13557.108 | AE86: 463018.08 | AF86: 10011.852 | AG86: 62223.419 | AH86: 0 | AI86: 3360.8797 | AJ86: 387421.93
B87: 4401 | C87: Inversiones | D87: 0 | E87: 0.0035 | F87: 1595.4372 | G87: 0 | H87: 1595.4407 | I87: 531.47234 | J87: 0 | K87: 0 | L87: 730.20311 | M87: 0 | N87: 182.28085 | O87: 0 | P87: 91.14237 | Q87: 0 | R87: 1535.0987 | S87: 0 | T87: 0 | U87: 0 | V87: 0 | W87: 0 | X87: 0 | Y87: 0 | Z87: 0 | AA87: 0 | AB87: 166.4 | AC87: 0 | AD87: 166.4 | AE87: 3296.9394 | AF87: 182.28085 | AG87: 730.20311 | AH87: 0 | AI87: 0 | AJ87: 2384.4554
B88: 4402 | C88: CARTERA DE CRÉDITOS | D88: 37752.536 | E88: 56968.808 | F88: 162942.93 | G88: 31439.041 | H88: 289103.31 | I88: 12182.348 | J88: 11799.699 | K88: 0 | L88: 51901.367 | M88: 8558.5643 | N88: 7532.8514 | O88: 5106.009 | P88: 3364.9089 | Q88: 7015.2458 | R88: 107460.99 | S88: 4191.9168 | T88: 828.03948 | U88: 75.79146 | V88: 0 | W88: 150.50021 | X88: 186.81089 | Y88: 59.51512 | Z88: 170.43417 | AA88: 1917.8682 | AB88: 3468.7531 | AC88: 903.85687 | AD88: 11953.486 | AE88: 408517.79 | AF88: 7532.8514 | AG88: 60459.931 | AH88: 0 | AI88: 2881.2402 | AJ88: 337643.77
B89: 440210 | C89: CRÉDITO PRODUCTIVO | D89: 2322.4239 | E89: 24243.75 | F89: 55445.89 | G89: 9740.4557 | H89: 91752.52 | I89: 0 | J89: 2626.894 | K89: 0 | L89: 549.88686 | M89: 0 | N89: 2712.8578 | O89: 1446.5573 | P89: 752.34864 | Q89: 0.40476 | R89: 8088.9494 | S89: 3263.8181 | T89: 240.97934 | U89: 28.52472 | V89: 0 | W89: 31.54073 | X89: 51.70183 | Y89: 0 | Z89: 86.99822 | AA89: 0 | AB89: 72.63903 | AC89: 0 | AD89: 3776.2019 | AE89: 103617.67 | AF89: 2712.8578 | AG89: 549.88686 | AH89: 0 | AI89: 0 | AJ89: 100354.93
B90: 440220 | C90: CRÉDITO DE CONSUMO | D90: 26990.551 | E90: 27661.544 | F90: 42898.448 | G90: 20792.279 | H90: 118342.82 | I90: 11854.196 | J90: 8912.458 | K90: 0 | L90: 51351.48 | M90: 8558.5643 | N90: 4610.1507 | O90: 3180.7056 | P90: 2272.2506 | Q90: 2757.7924 | R90: 93497.598 | S90: 12.14225 | T90: 570.16168 | U90: 22.78619 | V90: 0 | W90: 22.12883 | X90: 135.0804 | Y90: 0 | Z90: 69.65948 | AA90: 0 | AB90: 914.51587 | AC90: 0.03304 | AD90: 1746.5077 | AE90: 213586.93 | AF90: 4610.1507 | AG90: 59910.044 | AH90: 0 | AI90: 0.03304 | AJ90: 149066.7
B91: 440230 | C91: CRÉDITO INMOBILIARIO | D91: 1077.0969 | E91: 1790.1313 | F91: 14640.943 | G91: 540.4826 | H91: 18048.654 | I91: 223.74046 | J91: 257.548 | K91: 0 | L91: 0 | M91: 0 | N91: 190.99832 | O91: 128.91926 | P91: 62.64023 | Q91: 1.99841 | R91: 865.84468 | S91: 63.58117 | T91: 11.52001 | U91: 0.00315 | V91: 0 | W91: 0.05689 | X91: 0 | Y91: 0 | Z91: 11.03353 | AA91: 0 | AB91: 105.95578 | AC91: 0 | AD91: 192.15053 | AE91: 19106.649 | AF91: 190.99832 | AG91: 0 | AH91: 0 | AI91: 0 | AJ91: 18915.651
B92: 440235 | C92: CRÉDITO DE VIVIENDA DE INTERÉS SOCIAL Y PÚBLICO | D92: 0 | E92: 1957.9408 | F92: 0 | G92: 0 | H92: 1957.9408 | I92: 0 | J92: 0 | K92: 0 | L92: 0 | M92: 0 | N92: 0.27365 | O92: 0 | P92: 0 | Q92: 0 | R92: 0.27365 | S92: 0 | T92: 0 | U92: 0 | V92: 0 | W92: 0 | X92: 0 | Y92: 0 | Z92: 0 | AA92: 0 | AB92: 0 | AC92: 0 | AD92: 0 | AE92: 1958.2144 | AF92: 0.27365 | AG92: 0 | AH92: 0 | AI92: 0 | AJ92: 1957.9408
B93: 440240 | C93: MICROCRÉDITO | D93: 7350.2461 | E93: 412.73457 | F93: 49740.151 | G93: 362.61225 | H93: 57865.743 | I93: 104.4116 | J93: 0 | K93: 0 | L93: 0 | M93: 0 | N93: 18.57087 | O93: 349.45669 | P93: 270.49419 | Q93: 4255.0503 | R93: 4997.9836 | S93: 851.45875 | T93: 5.37845 | U93: 24.4774 | V93: 0 | W93: 96.77376 | X93: 0.02866 | Y93: 59.51512 | Z93: 2.74294 | AA93: 1917.8682 | AB93: 2375.6424 | AC93: 903.82383 | AD93: 6237.7096 | AE93: 69101.437 | AF93: 18.57087 | AG93: 0 | AH93: 0 | AI93: 2881.2072 | AJ93: 66201.659
B94: 440245 | C94: CRÉDITO EDUCATIVO | D94: 12.21865 | E94: 902.70752 | F94: 217.49568 | G94: 3.21144 | H94: 1135.6333 | I94: 0 | J94: 2.799 | K94: 0 | L94: 0 | M94: 0 | N94: 0 | O94: 0.37021 | P94: 7.1752 | Q94: 0 | R94: 10.34441 | S94: 0.91662 | T94: 0 | U94: 0 | V94: 0 | W94: 0 | X94: 0 | Y94: 0 | Z94: 0 | AA94: 0 | AB94: 0 | AC94: 0 | AD94: 0.91662 | AE94: 1146.8943 | AF94: 0 | AG94: 0 | AH94: 0 | AI94: 0 | AJ94: 1146.8943
B95: 440250 | C95: CRÉDITO DE INVERSIÓN PÚBLICA | D95: 0 | E95: 0 | F95: 0 | G95: 0 | H95: 0 | I95: 0 | J95: 0 | K95: 0 | L95: 0 | M95: 0 | N95: 0 | O95: 0 | P95: 0 | Q95: 0 | R95: 0 | S95: 0 | T95: 0 | U95: 0 | V95: 0 | W95: 0 | X95: 0 | Y95: 0 | Z95: 0 | AA95: 0 | AB95: 0 | AC95: 0 | AD95: 0 | AE95: 0 | AF95: 0 | AG95: 0 | AH95: 0 | AI95: 0 | AJ95: 0
B96: 4403 | C96: Cuentas por cobrar | D96: 1812.6825 | E96: 4671.6443 | F96: 13314.014 | G96: 5077.1597 | H96: 24875.501 | I96: 2752.926 | J96: 56.5 | K96: 182.768 | L96: 494.96545 | M96: 345.84683 | N96: 978.0486 | O96: 0 | P96: 82.27654 | Q96: 260.9267 | R96: 5154.2581 | S96: 59.30418 | T96: 394.24744 | U96: 2.84985 | V96: 4.74711 | W96: 5.04748 | X96: 22.83533 | Y96: 43.25353 | Z96: 0 | AA96: 382.09232 | AB96: 319.7665 | AC96: 36.75054 | AD96: 1270.8943 | AE96: 31300.653 | AF96: 1160.8166 | AG96: 845.55939 | AH96: 0 | AI96: 462.09639 | AJ96: 28832.181
B97: 4404 | C97: Bienes realizables, adjudicados por pago y de arrendamiento mercantil | D97: 0 | E97: 4.00411 | F97: 0 | G97: 45.19206 | H97: 49.19617 | I97: 0 | J97: 0 | K97: 0 | L97: 0 | M97: 12.8108 | N97: 0 | O97: 18.38235 | P97: 0 | Q97: 0 | R97: 31.19315 | S97: 0 | T97: 0 | U97: 69.35149 | V97: 0 | W97: 0 | X97: 0.63933 | Y97: 0 | Z97: 0 | AA97: 0 | AB97: 0 | AC97: 0 | AD97: 69.99082 | AE97: 150.38014 | AF97: 0 | AG97: 12.8108 | AH97: 0 | AI97: 0 | AJ97: 137.56934
... B100: 4407 | C100: Operaciones interbancarias y de reporto | D100: 0 | E100: 0 | F100: 0 | G100: 0 | H100: 0 | I100: 0 | J100: 0 | K100: 0 | L100: 0 | M100: 0 | N100: 0 | O100: 0 | P100: 0 | Q100: 0 | R100: 0 | S100: 0 | T100: 0 | U100: 0 | V100: 0 | W100: 0 | X100: 0 | Y100: 0 | Z100: 0 | AA100: 0 | AB100: 0 | AC100: 0 | AD100: 0 | AE100: 0 | AF100: 0 | AG100: 0 | AH100: 0 | AI100: 0 | AJ100: 0
C101: MARGEN NETO FINANCIERO | D101: 155937.61 | E101: 103473.14 | F101: 298133.2 | G101: 137188.05 | H101: 694732 | I101: 36330.069 | J101: 87717.493 | K101: 9306.556 | L101: 94941.1 | M101: 26126.075 | N101: 80855.149 | O101: 14725.798 | P101: 18334.907 | Q101: 37596.886 | R101: 405934.03 | S101: 7286.6991 | T101: 3298.0068 | U101: 1885.6048 | V101: 1516.7421 | W101: 3463.8535 | X101: 264.25494 | Y101: 2260.0694 | Z101: 1502.2005 | AA101: 1701.0916 | AB101: 4552.2279 | AC101: 5407.8221 | AD101: 33138.573 | AE101: 1133804.6 | AF101: 90161.705 | AG101: 122583.92 | AH101: 0 | AI101: 9368.9831 | AJ101: 911690
B103: 45 | C103: GASTOS DE OPERACIÓN | D103: 107439.99 | E103: 94941.583 | F103: 276461.4 | G103: 106879.04 | H103: 585722.02 | I103: 37545.951 | J103: 59269.843 | K103: 10494.633 | L103: 82095.761 | M103: 20375.897 | N103: 50258.188 | O103: 11878.263 | P103: 15714.779 | Q103: 30557.652 | R103: 318190.97 | S103: 9769.2369 | T103: 3720.3186 | U103: 1688.2142 | V103: 1453.7492 | W103: 3336.5879 | X103: 1301.8003 | Y103: 2718.9635 | Z103: 1978.3993 | AA103: 4354.2567 | AB103: 5202.2207 | AC103: 4004.6784 | AD103: 39528.426 | AE103: 943441.41 | AF103: 60752.821 | AG103: 103925.41 | AH103: 0 | AI103: 11077.899 | AJ103: 767685.29
B104: 4501 | C104: Gastos de personal | D104: 39774.239 | E104: 25907.484 | F104: 62265.447 | G104: 28327.721 | H104: 156274.89 | I104: 11441.584 | J104: 18254.418 | K104: 3613.816 | L104: 14785.997 | M104: 6866.0656 | N104: 16623.393 | O104: 4698.1948 | P104: 6647.9804 | Q104: 17089.003 | R104: 100020.45 | S104: 3108.7257 | T104: 1302.2788 | U104: 544.67229 | V104: 708.69723 | W104: 1128.0211 | X104: 622.93293 | Y104: 1454.9405 | Z104: 775.07163 | AA104: 2097.0006 | AB104: 2711.5896 | AC104: 2338.2616 | AD104: 16792.192 | AE104: 273087.54 | AF104: 20237.209 | AG104: 22360.76 | AH104: 0 | AI104: 5890.2027 | AJ104: 224599.36
B105: 4502 | C105: Honorarios | D105: 1347.927 | E105: 2280.6739 | F105: 38007.408 | G105: 2587.7829 | H105: 44223.792 | I105: 3397.3073 | J105: 640.30833 | K105: 104.167 | L105: 631.9667 | M105: 723.66948 | N105: 155.10537 | O105: 164.51411 | P105: 212.96664 | Q105: 758.70142 | R105: 6788.7064 | S105: 245.54961 | T105: 238.91379 | U105: 160.35137 | V105: 108.90608 | W105: 199.55062 | X105: 84.21918 | Y105: 65.93659 | Z105: 82.09455 | AA105: 255.32732 | AB105: 134.54729 | AC105: 234.65144 | AD105: 1810.0478 | AE105: 52822.546 | AF105: 259.27237 | AG105: 1464.5423 | AH105: 0 | AI105: 555.91535 | AJ105: 50542.816
B106: 4503 | C106: Servicios varios | D106: 30737.116 | E106: 17946.051 | F106: 75467.525 | G106: 40199.115 | H106: 164349.81 | I106: 9975.7521 | J106: 12782.465 | K106: 3313.331 | L106: 46007.029 | M106: 4790.6871 | N106: 7303.8766 | O106: 2432.026 | P106: 3804.4078 | Q106: 6657.547 | R106: 97067.122 | S106: 2744.1623 | T106: 763.8731 | U106: 258.96689 | V106: 242.31048 | W106: 364.36919 | X106: 182.1456 | Y106: 530.8839 | Z106: 821.14835 | AA106: 675.55728 | AB106: 1114.2584 | AC106: 749.26687 | AD106: 8446.9424 | AE106: 269863.87 | AF106: 10617.208 | AG106: 51040.027 | AH106: 0 | AI106: 1955.708 | AJ106: 206250.93
B107: 4504 | C107: Impuestos, contribuciones y multas | D107: 18349.802 | E107: 25155.595 | F107: 44954.193 | G107: 20166.063 | H107: 108625.65 | I107: 8157.615 | J107: 16049.309 | K107: 3126.443 | L107: 13902.011 | M107: 3833.5099 | N107: 12894.069 | O107: 3119.8847 | P107: 3249.8514 | Q107: 3379.0362 | R107: 67711.73 | S107: 1953.5801 | T107: 742.67954 | U107: 338.326 | V107: 157.78731 | W107: 801.05895 | X107: 135.2958 | Y107: 299.41779 | Z107: 223.06024 | AA107: 334.04592 | AB107: 721.62846 | AC107: 357.0108 | AD107: 6063.8909 | AE107: 182401.27 | AF107: 16020.512 | AG107: 17893.308 | AH107: 0 | AI107: 990.47451 | AJ107: 147496.98
B108: 4505 | C108: Depreciaciones | D108: 4447.1605 | E108: 5724.3125 | F108: 12289.897 | G108: 3037.2474 | H108: 25498.617 | I108: 1608.6994 | J108: 1973.8976 | K108: 81.959 | L108: 935.29754 | M108: 520.27292 | N108: 2025.7446 | O108: 439.71023 | P108: 493.85116 | Q108: 636.537 | R108: 8715.9694 | S108: 282.58062 | T108: 175.436 | U108: 129.57948 | V108: 34.43812 | W108: 151.04173 | X108: 84.97761 | Y108: 110.04425 | Z108: 14.37339 | AA108: 75.57211 | AB108: 206.47754 | AC108: 82.54888 | AD108: 1347.0697 | AE108: 35561.657 | AF108: 2107.7036 | AG108: 1490.0086 | AH108: 0 | AI108: 268.16524 | AJ108: 31695.779
B109: 4506 | C109: Amortizaciones | D109: 6796.862 | E109: 10193.015 | F109: 6653.1724 | G109: 4704.1012 | H109: 28347.151 | I109: 1156.3589 | J109: 1483.9466 | K109: 30.236 | L109: 179.52307 | M109: 1273.9595 | N109: 1402.2593 | O109: 128.46166 | P109: 522.46353 | Q109: 407.10375 | R109: 6584.3123 | S109: 103.92778 | T109: 156.33019 | U109: 69.95929 | V109: 96.93863 | W109: 192.7494 | X109: 61.82487 | Y109: 24.10463 | Z109: 27.23259 | AA109: 313.82799 | AB109: 92.65916 | AC109: 67.50713 | AD109: 1207.0617 | AE109: 36138.525 | AF109: 1432.4953 | AG109: 1550.4212 | AH109: 0 | AI109: 405.43975 | AJ109: 32750.169
B110: 4507 | C110: Otros gastos | D110: 5986.8873 | E110: 7734.4519 | F110: 36823.759 | G110: 7857.0115 | H110: 58402.11 | I110: 1808.6346 | J110: 8085.4986 | K110: 224.681 | L110: 5653.9365 | M110: 2367.7328 | N110: 9853.7393 | O110: 895.47112 | P110: 783.25787 | Q110: 1629.7232 | R110: 31302.675 | S110: 1330.7108 | T110: 340.80716 | U110: 186.35883 | V110: 104.67132 | W110: 499.79696 | X110: 130.40431 | Y110: 233.63589 | Z110: 35.41859 | AA110: 602.92551 | AB110: 221.06029 | AC110: 175.43173 | AD110: 3861.2214 | AE110: 93566.006 | AF110: 10078.42 | AG110: 8126.3407 | AH110: 0 | AI110: 1011.9931 | AJ110: 74349.252
C111: MARGEN DE INTERMEDIACIÓN | D111: 48497.617 | E111: 8531.5583 | F111: 21671.794 | G111: 30309.011 | H111: 109009.98 | I111: -1215.8826 | J111: 28447.649 | K111: -1188.077 | L111: 12845.339 | M111: 5750.1773 | N111: 30596.962 | O111: 2847.5358 | P111: 2620.1279 | Q111: 7039.2345 | R111: 87743.066 | S111: -2482.5378 | T111: -422.31177 | U111: 197.39061 | V111: 62.9929 | W111: 127.26558 | X111: -1037.5454 | Y111: -458.89414 | Z111: -476.19887 | AA111: -2653.1651 | AB111: -649.99279 | AC111: 1403.1437 | AD111: -6389.8531 | AE111: 190363.19 | AF111: 29408.885 | AG111: 18658.509 | AH111: 0 | AI111: -1708.9156 | AJ111: 144004.72
B113: 55 | C113: OTROS INGRESOS OPERACIONALES | D113: 123.11113 | E113: 6742.9115 | F113: 47011.517 | G113: 7547.4901 | H113: 61425.03 | I113: 1525.7405 | J113: 2279.2784 | K113: 246.332 | L113: 13526.194 | M113: 50.12724 | N113: 251.14736 | O113: 176.9902 | P113: 14.49152 | Q113: 2487.5613 | R113: 20557.862 | S113: 265.39649 | T113: 13.85114 | U113: 0 | V113: 77.31373 | W113: 0 | X113: 54.45954 | Y113: 627.87772 | Z113: 0 | AA113: 1260.6404 | AB113: 70.4565 | AC113: 0 | AD113: 2369.9955 | AE113: 84352.888 | AF113: 497.47936 | AG113: 13653.635 | AH113: 0 | AI113: 1888.5181 | AJ113: 68313.255
B114: 5501 | C114: Utilidades en acciones y participaciones | D114: 123.11113 | E114: 339.65054 | F114: 30451.422 | G114: 2078.7198 | H114: 32992.904 | I114: 293.572 | J114: 181.48892 | K114: 111.878 | L114: 11372.161 | M114: 0 | N114: 239.56939 | O114: 82.35297 | P114: 0 | Q114: 0 | R114: 12281.022 | S114: 0 | T114: 13.85114 | U114: 0 | V114: 0 | W114: 0 | X114: 0 | Y114: 0 | Z114: 0 | AA114: 0 | AB114: 0 | AC114: 0 | AD114: 13.85114 | AE114: 45287.777 | AF114: 351.44739 | AG114: 11372.161 | AH114: 0 | AI114: 0 | AJ114: 33564.169
B115: 5502 | C115: Utilidad en venta de bienes realizables y recuperados | D115: 0 | E115: 0 | F115: 0 | G115: 0 | H115: 0 | I115: 0 | J115: 0 | K115: 0 | L115: 0 | M115: 0 | N115: 0 | O115: 0 | P115: 0 | Q115: 0 | R115: 0 | S115: 0 | T115: 0 | U115: 0 | V115: 0 | W115: 0 | X115: 0 | Y115: 0 | Z115: 0 | AA115: 0 | AB115: 0.28012 | AC115: 0 | AD115: 0.28012 | AE115: 0.28012 | AF115: 0 | AG115: 0 | AH115: 0 | AI115: 0 | AJ115: 0.28012
B116: 5505 | C116: Ingresos por subsidios realizados | D116: 0 | E116: 0 | F116: 0 | G116: 0 | H116: 0 | I116: 0 | J116: 0 | K116: 0 | L116: 0 | M116: 0 | N116: 0 | O116: 0 | P116: 0 | Q116: 0 | R116: 0 | S116: 0 | T116: 0 | U116: 0 | V116: 0 | W116: 0 | X116: 0 | Y116: 0 | Z116: 0 | AA116: 0 | AB116: 0 | AC116: 0 | AD116: 0 | AE116: 0 | AF116: 0 | AG116: 0 | AH116: 0 | AI116: 0 | AJ116: 0
B117: 5506 | C117: Ingresos por subsidios recuperados | D117: 0 | E117: 0 | F117: 0 | G117: 0 | H117: 0 | I117: 0 | J117: 0 | K117: 0 | L117: 0 | M117: 0 | N117: 0 | O117: 0 | P117: 0 | Q117: 0 | R117: 0 | S117: 0 | T117: 0 | U117: 0 | V117: 0 | W117: 0 | X117: 0 | Y117: 0 | Z117: 0 | AA117: 0 | AB117: 0 | AC117: 0 | AD117: 0 | AE117: 0 | AF117: 0 | AG117: 0 | AH117: 0 | AI117: 0 | AJ117: 0
B118: 5507 | C118: Ingresos por demora en transferencias | D118: 0 | E118: 0 | F118: 0 | G118: 0 | H118: 0 | I118: 0 | J118: 0 | K118: 0 | L118: 0 | M118: 0 | N118: 0 | O118: 0 | P118: 0 | Q118: 0 | R118: 0 | S118: 0 | T118: 0 | U118: 0 | V118: 0 | W118: 0 | X118: 0 | Y118: 0 | Z118: 0 | AA118: 0 | AB118: 0 | AC118: 0 | AD118: 0 | AE118: 0 | AF118: 0 | AG118: 0 | AH118: 0 | AI118: 0 | AJ118: 0
B119: 5590 | C119: Otros | D119: 0 | E119: 6403.261 | F119: 16560.095 | G119: 5468.7702 | H119: 28432.126 | I119: 1232.1685 | J119: 2097.7894 | K119: 134.454 | L119: 2154.0333 | M119: 50.12724 | N119: 11.57797 | O119: 94.63723 | P119: 14.49152 | Q119: 2487.5613 | R119: 8276.8405 | S119: 265.39649 | T119: 0 | U119: 0 | V119: 77.31373 | W119: 0 | X119: 54.45954 | Y119: 627.87772 | Z119: 0 | AA119: 1260.6404 | AB119: 70.17638 | AC119: 0 | AD119: 2355.8642 | AE119: 39064.83 | AF119: 146.03197 | AG119: 2281.4743 | AH119: 0 | AI119: 1888.5181 | AJ119: 34748.806
B120: 46 | C120: OTRAS PÉRDIDAS OPERACIONALES | D120: 132.47729 | E120: 837.03502 | F120: 27403.726 | G120: 1143.2424 | H120: 29516.481 | I120: 0.0492 | J120: 68.7068 | K120: 81.676 | L120: 7392.3935 | M120: 221.68611 | N120: 186.2851 | O120: 65.28245 | P120: 0 | Q120: 4551.5277 | R120: 12567.607 | S120: 0 | T120: 52.35738 | U120: 0 | V120: 1.51786 | W120: 0 | X120: 8.75742 | Y120: 0 | Z120: 2.52551 | AA120: 191.36869 | AB120: 4.78913 | AC120: 0 | AD120: 261.31599 | AE120: 42345.404 | AF120: 267.9611 | AG120: 7615.5975 | AH120: 0 | AI120: 191.36869 | AJ120: 34270.476
B121: 4601 | C121: Pérdida en acciones y participaciones | D121: 26.99099 | E121: 24.30408 | F121: 21955.261 | G121: 1137.5024 | H121: 23144.059 | I121: 0 | J121: 56.21427 | K121: 78.434 | L121: 7392.3935 | M121: 0 | N121: 186.2851 | O121: 58.03956 | P121: 0 | Q121: 0 | R121: 7771.3664 | S121: 0 | T121: 10.04171 | U121: 0 | V121: 0 | W121: 0 | X121: 0 | Y121: 0 | Z121: 0 | AA121: 0 | AB121: 0 | AC121: 0 | AD121: 10.04171 | AE121: 30925.467 | AF121: 264.7191 | AG121: 7392.3935 | AH121: 0 | AI121: 0 | AJ121: 23268.354
B122: 4602 | C122: Pérdida en venta de bienes realizables y recuperados | D122: 98.8211 | E122: 452.75836 | F122: 20.56212 | G122: 5.74002 | H122: 577.8816 | I122: 0 | J122: 0 | K122: 0 | L122: 0 | M122: 162.88162 | N122: 0 | O122: 0 | P122: 0 | Q122: 0.07383 | R122: 162.95545 | S122: 0 | T122: 0 | U122: 0 | V122: 1.51786 | W122: 0 | X122: 8.75742 | Y122: 0 | Z122: 2.52551 | AA122: 0 | AB122: 0 | AC122: 0 | AD122: 12.80079 | AE122: 753.63784 | AF122: 0 | AG122: 164.39948 | AH122: 0 | AI122: 0 | AJ122: 589.23836
B123: 4690 | C123: Otras | D123: 6.6652 | E123: 359.97258 | F123: 5427.9027 | G123: 0 | H123: 5794.5405 | I123: 0.0492 | J123: 12.49253 | K123: 3.242 | L123: 0 | M123: 58.80449 | N123: 0 | O123: 7.24289 | P123: 0 | Q123: 4551.4538 | R123: 4633.2849 | S123: 0 | T123: 42.31567 | U123: 0 | V123: 0 | W123: 0 | X123: 0 | Y123: 0 | Z123: 0 | AA123: 191.36869 | AB123: 4.78913 | AC123: 0 | AD123: 238.47349 | AE123: 10666.299 | AF123: 3.242 | AG123: 58.80449 | AH123: 0 | AI123: 191.36869 | AJ123: 10412.884
C124: MARGEN OPERACIONAL | D124: 48488.251 | E124: 14437.435 | F124: 41279.585 | G124: 36713.259 | H124: 140918.53 | I124: 309.80869 | J124: 30658.221 | K124: -1023.421 | L124: 18979.139 | M124: 5578.6185 | N124: 30661.824 | O124: 2959.2436 | P124: 2634.6195 | Q124: 4975.2682 | R124: 95733.321 | S124: -2217.1413 | T124: -460.81801 | U124: 197.39061 | V124: 138.78877 | W124: 127.26558 | X124: -991.84324 | Y124: 168.98358 | Z124: -478.72438 | AA124: -1583.8934 | AB124: -584.32542 | AC124: 1403.1437 | AD124: -4281.1736 | AE124: 232370.68 | AF124: 29638.403 | AG124: 24696.546 | AH124: 0 | AI124: -11.7662 | AJ124: 178047.49
B126: 56 | C126: OTROS INGRESOS | D126: 10589.247 | E126: 47389.303 | F126: 50055.399 | G126: 18609.428 | H126: 126643.38 | I126: 11821.431 | J126: 1856.3905 | K126: 3345.121 | L126: 17016.309 | M126: 3322.1095 | N126: 3783.639 | O126: 1413.5902 | P126: 2046.5693 | Q126: 1954.6547 | R126: 46559.814 | S126: 2788.7351 | T126: 757.50251 | U126: 37.69226 | V126: 24.49751 | W126: 567.4222 | X126: 358.27525 | Y126: 616.78003 | Z126: 361.80879 | AA126: 580.72088 | AB126: 2158.1212 | AC126: 885.92627 | AD126: 9137.482 | AE126: 182340.67 | AF126: 7128.7599 | AG126: 20362.916 | AH126: 0 | AI126: 2083.4272 | AJ126: 152765.57
B127: 5601 | C127: Utilidad en venta de bienes | D127: 96.16441 | E127: 110.09264 | F127: 1816.5781 | G127: 25.29703 | H127: 2048.1322 | I127: 56.03448 | J127: 6.699 | K127: 0 | L127: 0.62878 | M127: 13.13801 | N127: 129.15776 | O127: 0.3012 | P127: 171.08659 | Q127: 32.10616 | R127: 409.15198 | S127: 3.91983 | T127: 0 | U127: 0 | V127: 0 | W127: 0 | X127: 8.34185 | Y127: 0 | Z127: 0 | AA127: 0.60643 | AB127: 0 | AC127: 0.29911 | AD127: 13.16722 | AE127: 2470.4514 | AF127: 129.15776 | AG127: 13.76679 | AH127: 0 | AI127: 0.90554 | AJ127: 2326.6213
B128: 5602 | C128: Utilidad en venta de acciones y participaciones | D128: 0 | E128: 0 | F128: 0 | G128: 71.58033 | H128: 71.58033 | I128: 0 | J128: 0 | K128: 0 | L128: 0 | M128: 0 | N128: 0 | O128: 0 | P128: 0 | Q128: 0 | R128: 0 | S128: 0 | T128: 0 | U128: 0 | V128: 0 | W128: 0 | X128: 0 | Y128: 0 | Z128: 0 | AA128: 0 | AB128: 0 | AC128: 0 | AD128: 0 | AE128: 71.58033 | AF128: 0 | AG128: 0 | AH128: 0 | AI128: 0 | AJ128: 71.58033
B129: 5603 | C129: Arrendamientos | D129: 1.81043 | E129: 47.91313 | F129: 846.44244 | G129: 647.11721 | H129: 1543.2832 | I129: 30.3487 | J129: 0 | K129: 0 | L129: 6.9822 | M129: 0 | N129: 94.7994 | O129: 2.23215 | P129: 0 | Q129: 0 | R129: 134.36245 | S129: 0 | T129: 67.48586 | U129: 0 | V129: 0 | W129: 2.13725 | X129: 15.3 | Y129: 0 | Z129: 0 | AA129: 0 | AB129: 0 | AC129: 0 | AD129: 84.92311 | AE129: 1762.5688 | AF129: 94.7994 | AG129: 6.9822 | AH129: 0 | AI129: 0 | AJ129: 1660.7872
B130: 5604 | C130: Recuperaciones de activos financieros | D130: 8348.4867 | E130: 43511.763 | F130: 45260.387 | G130: 15093.481 | H130: 112214.12 | I130: 11472.351 | J130: 1492.1948 | K130: 1497.408 | L130: 14814.578 | M130: 1351.3886 | N130: 2620.9756 | O130: 1173.7898 | P130: 1628.2389 | Q130: 1598.0128 | R130: 37648.937 | S130: 2763.4545 | T130: 217.22312 | U130: 37.69226 | V130: 24.19585 | W130: 549.50396 | X130: 315.62565 | Y130: 616.78003 | Z130: 361.80879 | AA130: 275.93774 | AB130: 1898.559 | AC130: 352.12604 | AD130: 7412.907 | AE130: 157275.96 | AF130: 4118.3836 | AG130: 16190.162 | AH130: 0 | AI130: 1244.8438 | AJ130: 135722.57
B131: 5690 | C131: Otros | D131: 2142.7859 | E131: 3719.5338 | F131: 2131.9917 | G131: 2771.9524 | H131: 10766.264 | I131: 262.69695 | J131: 357.49665 | K131: 1847.713 | L131: 2194.1205 | M131: 1957.5829 | N131: 938.70615 | O131: 237.26711 | P131: 247.24377 | Q131: 324.53574 | R131: 8367.3628 | S131: 21.36074 | T131: 472.79353 | U131: 0 | V131: 0.30166 | W131: 15.78099 | X131: 19.00775 | Y131: 0 | Z131: 0 | AA131: 304.17671 | AB131: 259.56222 | AC131: 533.50112 | AD131: 1626.4847 | AE131: 20760.111 | AF131: 2786.4192 | AG131: 4152.0051 | AH131: 0 | AI131: 837.67783 | AJ131: 12984.009
B132: 47 | C132: OTROS GASTOS Y PÉRDIDAS | D132: 4055.1673 | E132: 10765.588 | F132: 8500.2949 | G132: 414.61408 | H132: 23735.664 | I132: 3759.8905 | J132: 233.88818 | K132: 48.915 | L132: 1364.1657 | M132: 275.19859 | N132: 6646.2791 | O132: 288.69361 | P132: 577.07914 | Q132: 504.70338 | R132: 13698.813 | S132: 132.609 | T132: 232.44716 | U132: 128.8307 | V132: 11.98213 | W132: 6.2188 | X132: 0 | Y132: 1127.4961 | Z132: 0.9 | AA132: 34.19208 | AB132: 450.15172 | AC132: 37.39286 | AD132: 2162.2206 | AE132: 39596.698 | AF132: 6695.1941 | AG132: 1651.3465 | AH132: 0 | AI132: 1199.0811 | AJ132: 30051.076
B133: 4701 | C133: Pérdida en venta de bienes | D133: 0.80977 | E133: 0 | F133: 13.08147 | G133: 88.56491 | H133: 102.45615 | I133: 121.34114 | J133: 0 | K133: 2.921 | L133: 1.92505 | M133: 0 | N133: 37.24001 | O133: 0 | P133: 479.9518 | Q133: 0.10398 | R133: 643.48298 | S133: 16.53564 | T133: 40.96357 | U133: 0 | V133: 0 | W133: 0 | X133: 0 | Y133: 0.82232 | Z133: 0 | AA133: 0 | AB133: 0 | AC133: 0 | AD133: 58.32153 | AE133: 804.26066 | AF133: 40.16101 | AG133: 1.92505 | AH133: 0 | AI133: 0.82232 | AJ133: 761.35228
B134: 4702 | C134: Pérdida en venta de acciones y participaciones | D134: 0 | E134: 0 | F134: 0 | G134: 0 | H134: 0 | I134: 0 | J134: 0 | K134: 0 | L134: 0 | M134: 0 | N134: 0 | O134: 0 | P134: 0 | Q134: 0 | R134: 0 | S134: 0 | T134: 0 | U134: 0 | V134: 0 | W134: 0 | X134: 0 | Y134: 0 | Z134: 0 | AA134: 0 | AB134: 0 | AC134: 0 | AD134: 0 | AE134: 0 | AF134: 0 | AG134: 0 | AH134: 0 | AI134: 0 | AJ134: 0
B135: 4703 | C135: INTERESES y comisiones devengados en ejercicios anteriores | D135: 1607.7215 | E135: 3472.1215 | F135: 8487.2124 | G135: 326.04917 | H135: 13893.105 | I135: 1813.2595 | J135: 203.46164 | K135: 9.852 | L135: 1206.0361 | M135: 173.09108 | N135: 161.52262 | O135: 285.72176 | P135: 42.6557 | Q135: 504.5994 | R135: 4400.1998 | S135: 111.5863 | T135: 191.48359 | U135: 128.8307 | V135: 2.66814 | W135: 5.75942 | X135: 0 | Y135: 34.49543 | Z135: 0 | AA135: 33.27598 | AB135: 384.48207 | AC135: 31.25 | AD135: 923.83163 | AE135: 19217.136 | AF135: 171.37462 | AG135: 1381.7953 | AH135: 0 | AI135: 99.02141 | AJ135: 17564.945
B136: 4790 | C136: Otros | D136: 2446.636 | E136: 7293.4661 | F136: 0.001 | G136: 0 | H136: 9740.1031 | I136: 1825.2899 | J136: 30.42654 | K136: 36.142 | L136: 156.20463 | M136: 102.10751 | N136: 6447.5165 | O136: 2.97185 | P136: 54.47164 | Q136: 0 | R136: 8655.1305 | S136: 4.48706 | T136: 0 | U136: 0 | V136: 9.31399 | W136: 0.45938 | X136: 0 | Y136: 1092.1784 | Z136: 0.9 | AA136: 0.9161 | AB136: 65.66965 | AC136: 6.14286 | AD136: 1180.0674 | AE136: 19575.301 | AF136: 6483.6584 | AG136: 267.62613 | AH136: 0 | AI136: 1099.2373 | AJ136: 11724.779
C137: GANANCIA O (PÉRDIDA) ANTES DE IMPUESTOS | D137: 55022.331 | E137: 51061.15 | F137: 82834.689 | G137: 54908.073 | H137: 243826.24 | I137: 8371.3493 | J137: 32280.723 | K137: 2272.785 | L137: 34631.282 | M137: 8625.5294 | N137: 27799.184 | O137: 4084.1402 | P137: 4104.1096 | Q137: 6425.2195 | R137: 128594.32 | S137: 438.9848 | T137: 64.23734 | U137: 106.25217 | V137: 151.30415 | W137: 688.46898 | X137: -633.56799 | Y137: -341.73251 | Z137: -117.81559 | AA137: -1037.3646 | AB137: 1123.6441 | AC137: 2251.6771 | AD137: 2694.0879 | AE137: 375114.65 | AF137: 30071.969 | AG137: 43408.116 | AH137: 0 | AI137: 872.57992 | AJ137: 300761.99
B139: 48 | C139: IMPUESTOS Y PARTICIPACIÓN A EMPLEADOS | D139: 17735.165 | E139: 8000 | F139: 26385.238 | G139: 23872 | H139: 75992.403 | I139: 3676.4841 | J139: 12719.9 | K139: 740.27 | L139: 12159.501 | M139: 3075.1462 | N139: 10598 | O139: 1650.7617 | P139: 1811.3344 | Q139: 2250 | R139: 48681.397 | S139: 381.78895 | T139: 24.92409 | U139: 33.7334 | V139: 13.7567 | W139: 249.56999 | X139: 0 | Y139: 0 | Z139: 0 | AA139: 0 | AB139: 407.32099 | AC139: 869.18288 | AD139: 1980.277 | AE139: 126654.08 | AF139: 11338.27 | AG139: 15248.404 | AH139: 0 | AI139: 869.18288 | AJ139: 99198.221
B140: 4810 | C140: Participación a empleados | D140: 8253.3497 | E140: 0 | F140: 10955.18 | G140: 9724 | H140: 28932.53 | I140: 1255.7024 | J140: 4841.8 | K140: 340.918 | L140: 4662.0044 | M140: 1270 | N140: 4170 | O140: 612.62103 | P140: 615.61644 | Q140: 950 | R140: 18718.662 | S140: 72.73225 | T140: 9.6356 | U140: 13.03131 | V140: 5.57704 | W140: 103.27034 | X140: 0 | Y140: 0 | Z140: 0 | AA140: 0 | AB140: 168.54662 | AC140: 337.75156 | AD140: 710.54472 | AE140: 48361.737 | AF140: 4510.918 | AG140: 5937.5815 | AH140: 0 | AI140: 337.75156 | AJ140: 37575.486
B141: 4815 | C141: Impuesto a la renta | D141: 9481.8153 | E141: 8000 | F141: 15430.058 | G141: 14148 | H141: 47059.874 | I141: 2420.7818 | J141: 7878.1 | K141: 399.352 | L141: 7497.4964 | M141: 1805.1463 | N141: 6428 | O141: 1038.1407 | P141: 1195.718 | Q141: 1300 | R141: 29962.735 | S141: 309.0567 | T141: 15.28849 | U141: 20.70209 | V141: 8.17966 | W141: 146.29965 | X141: 0 | Y141: 0 | Z141: 0 | AA141: 0 | AB141: 238.77437 | AC141: 531.43132 | AD141: 1269.7323 | AE141: 78292.341 | AF141: 6827.352 | AG141: 9310.8223 | AH141: 0 | AI141: 531.43132 | AJ141: 61622.735
B142: 4890 | C142: Otros | D142: 0 | E142: 0 | F142: 0 | G142: 0 | H142: 0 | I142: 0 | J142: 0 | K142: 0 | L142: 0 | M142: 0 | N142: 0 | O142: 0 | P142: 0 | Q142: 0 | R142: 0 | S142: 0 | T142: 0 | U142: 0 | V142: 0 | W142: 0 | X142: 0 | Y142: 0 | Z142: 0 | AA142: 0 | AB142: 0 | AC142: 0 | AD142: 0 | AE142: 0 | AF142: 0 | AG142: 0 | AH142: 0 | AI142: 0 | AJ142: 0
C143: GANANCIA O (PÉRDIDA) DEL EJERCICIO | D143: 37287.166 | E143: 43061.15 | F143: 56449.451 | G143: 31036.073 | H143: 167833.84 | I143: 4694.8651 | J143: 19560.823 | K143: 1532.515 | L143: 22471.782 | M143: 5550.3832 | N143: 17201.184 | O143: 2433.3785 | P143: 2292.7751 | Q143: 4175.2195 | R143: 79912.925 | S143: 57.19585 | T143: 39.31325 | U143: 72.51877 | V143: 137.54745 | W143: 438.89899 | X143: -633.56799 | Y143: -341.73251 | Z143: -117.81559 | AA143: -1037.3646 | AB143: 716.32311 | AC143: 1382.4942 | AD143: 713.81088 | AE143: 248460.58 | AF143: 18733.699 | AG143: 28159.712 | AH143: 0 | AI143: 3.39704 | AJ143: 201563.77

Sheet BALANCE %
B3: ESTADO DE SITUACIÓN CONSOLIDADO
B4: SISTEMA DE BANCOS PRIVADOS
B5: 31/05/2022
B6: (en porcentajes)
B8: CÓDIGO | C8: CUENTA | D8: BP GUAYAQUIL | E8: BP PACIFICO | F8: BP PICHINCHA | G8: BP PRODUBANCO | H8: BANCOS PRIVADOS GRANDES | I8: BP AUSTRO | J8: BP BOLIVARIANO | K8: BP CITIBANK | L8: BP DINERS | M8: BP GENERAL RUMIÑAHUI | N8: BP INTERNACIONAL | O8: BP LOJA | P8: BP MACHALA | Q8: BP SOLIDARIO | R8: BANCOS PRIVADOS MEDIANOS | S8: BP PROCREDIT | T8: BP AMAZONAS | U8: BP COMERCIAL DE MANABI | V8: BP LITORAL | W8: BP COOPNACIONAL | X8: BP CAPITAL | Y8: BP FINCA S.A. | Z8: BP DELBANK | AA8: BP D-MIRO S.A. | AB8: BP BANCO DESARROLLO DE LOS PUEBLOS S.A., CODESARROLLO | AC8: BP VISIONFUND ECUADOR S.A. | AD8: BANCOS PRIVADOS PEQUEÑOS | AE8: TOTAL BANCOS PRIVADOS | AF8: BANCOS PRIVADOS COMERCIALES | AG8: BANCOS PRIVADOS CONSUMO | AH8: BANCOS PRIVADOS VIVIENDA | AI8: BANCOS PRIVADOS MICROCRÉDITO | AJ8: BANCA MÚLTIPLE
C9: ACTIVO
B10: 11 | C10: FONDOS DISPONIBLES | D10: 0.1223079 | E10: 0.1792381 | F10: 0.10765839 | G10: 0.15734738 | H10: 0.13455603 | I10: 0.15070159 | J10: 0.17509124 | K10: 0.3211318 | L10: 0.054087783 | M10: 0.16630376 | N10: 0.1277802 | O10: 0.20755983 | P10: 0.16815633 | Q10: 0.089290588 | R10: 0.14613953 | S10: 0.097962447 | T10: 0.10296113 | U10: 0.12017489 | V10: 0.058301551 | W10: 0.31646765 | X10: 0.060145047 | Y10: 0.13494502 | Z10: 0.22369657 | AA10: 0.0567199 | AB10: 0.098309962 | AC10: 0.039394228 | AD10: 0.12099656 | AE10: 0.13793452 | AF10: 0.15277579 | AG10: 0.088489843 | AH10: 0 | AI10: 0.073873501 | AJ10: 0.14039591
B11: 12 | C11: OPERACIONES INTERBANCARIAS | D11: 0 | E11: 0 | F11: 0 | G11: 0 | H11: 0 | I11: 0 | J11: 0 | K11: 0 | L11: 0 | M11: 0 | N11: 0 | O11: 0 | P11: 0 | Q11: 0 | R11: 0 | S11: 0 | T11: 0 | U11: 0 | V11: 0 | W11: 0 | X11: 0 | Y11: 0 | Z11: 0 | AA11: 0 | AB11: 0 | AC11: 0 | AD11: 0 | AE11: 0 | AF11: 0 | AG11: 0 | AH11: 0 | AI11: 0 | AJ11: 0
B12: 13 | C12: INVERSIONES | D12: 0.1605074 | E12: 0.14791673 | F12: 0.1781162 | G12: 0.10935397 | H12: 0.15559589 | I12: 0.18894837 | J12: 0.16372374 | K12: 0.19915556 | L12: 0.080377521 | M12: 0.1410227 | N12: 0.16528492 | O12: 0.12406263 | P12: 0.17917559 | Q12: 0.099664487 | R12: 0.15312355 | S12: 0.061352845 | T12: 0.24088279 | U12: 0.1398001 | V12: 0.14706059 | W12: 0.25432885 | X12: 0.10618313 | Y12: 0.11236891 | Z12: 0.15741382 | AA12: 0.14375069 | AB12: 0.12929572 | AC12: 0.019344686 | AD12: 0.13394364 | AE12: 0.15403903 | AF12: 0.16966356 | AG12: 0.099758731 | AH12: 0 | AI12: 0.092653436 | AJ12: 0.15675684
C13: INVERSIONES DEL SECTOR PRIVADO | D13: 0.028466303 | E13: 0.045576132 | F13: 0.040240692 | G13: 0.035274823 | H13: 0.03813051 | I13: 0.089069565 | J13: 0.057209092 | K13: 0.010587812 | L13: 0.0037953668 | M13: 0.046109415 | N13: 0.059358012 | O13: 0.056695106 | P13: 0.036796644 | Q13: 0.058748509 | R13: 0.051863966 | S13: 0.015697955 | T13: 0.09435568 | U13: 0.074286801 | V13: 0.061070641 | W13: 0.191337 | X13: 0.016065473 | Y13: 0.056526826 | Z13: 0.10569533 | AA13: 0.10935843 | AB13: 0.075170185 | AC13: 0.0036702701 | AD13: 0.067906333 | AE13: 0.043697266 | AF13: 0.05305323 | AG13: 0.017449956 | AH13: 0 | AI13: 0.058258969 | AJ13: 0.044520367
C14: INVERSIONES DEL SECTOR PUBLICO | D14: 0.13251792 | E14: 0.08635945 | F14: 0.13427745 | G14: 0.071665659 | H14: 0.11232663 | I14: 0.075795448 | J14: 0.098161009 | K14: 0.18856775 | L14: 0.065477552 | M14: 0.099750831 | N14: 0.077292996 | O14: 0.067228498 | P14: 0.14108354 | Q14: 0.040915978 | R14: 0.08756853 | S14: 0.043284129 | T14: 0.14134786 | U14: 0.066182977 | V14: 0.085989952 | W14: 0.06338035 | X14: 0.080968787 | Y14: 0.05584208 | Z14: 0.050221343 | AA14: 0.03439226 | AB14: 0.05481868 | AC14: 0.0156391 | AD14: 0.064336377 | AE14: 0.1024848 | AF14: 0.091678072 | AG14: 0.076220298 | AH14: 0 | AI14: 0.03438258 | AJ14: 0.10609756
B15: 1307 | C15: De disponibilidad restringida | D15: 0 | E15: 0.016490136 | F15: 0.011827054 | G15: 0.0024177083 | H15: 0.0087351436 | I15: 0.024315809 | J15: 0.0086172149 | K15: 0 | L15: 0.011428783 | M15: 9.8802523e-05 | N15: 0.028676945 | O15: 0.00014633747 | P15: 0.0013893121 | Q15: 0 | R15: 0.014132737 | S15: 0.0023707614 | T15: 0.0051792492 | U15: 0.00081725271 | V15: 0 | W15: 0 | X15: 0.0091488711 | Y15: 0 | Z15: 0.0015759409 | AA15: 0 | AB15: 0 | AC15: 3.531551e-05 | AD15: 0.001889724 | AE15: 0.010291482 | AF15: 0.024969725 | AG15: 0.0078205174 | AH15: 0 | AI15: 1.1887488e-05 | AJ15: 0.008908853
B16: 1399 | C16: (Provisión para inversiones) | D16: -0.00047681492 | E16: -0.00050898539 | F16: -0.008228995 | G16: -4.215749e-06 | H16: -0.0035963937 | I16: -0.00023244846 | J16: -0.00026357765 | K16: 0 | L16: -0.00032418133 | M16: -0.0049363513 | N16: -4.3028099e-05 | O16: -7.316874e-06 | P16: -9.3908418e-05 | Q16: 0 | R16: -0.00044168316 | S16: 0 | T16: 0 | U16: -0.0014869356 | V16: 0 | W16: -0.00038850345 | X16: 0 | Y16: 0 | Z16: -7.8797044e-05 | AA16: 0 | AB16: -0.0006931438 | AC16: 0 | AD16: -0.00018879955 | AE16: -0.0024345168 | AF16: -3.7465629e-05 | AG16: -0.00173204 | AH16: 0 | AI16: 0 | AJ16: -0.0027699402
B17: 14 | C17: CARTERA DE CRÉDITOS | D17: 0.65434598 | E17: 0.5733756 | F17: 0.61189648 | G17: 0.67310584 | H17: 0.62364934 | I17: 0.56053398 | J17: 0.61628005 | K17: 0.45033101 | L17: 0.80027775 | M17: 0.65455406 | N17: 0.65805584 | O17: 0.61635111 | P17: 0.59320612 | Q17: 0.76027304 | R17: 0.64420153 | S17: 0.80163942 | T17: 0.53787655 | U17: 0.61963702 | V17: 0.71211684 | W17: 0.39462979 | X17: 0.53966589 | Y17: 0.67071447 | Z17: 0.46676788 | AA17: 0.71328527 | AB17: 0.71586893 | AC17: 0.91017958 | AD17: 0.67548151 | AE17: 0.63222764 | AF17: 0.63120215 | AG17: 0.75458998 | AH17: 0 | AI17: 0.76705255 | AJ17: 0.62231585
C18: CARTERA DE CRÉDITOS PRODUCTIVO | D18: 0.35005502 | E18: 0.21213691 | F18: 0.25789686 | G18: 0.43851518 | H18: 0.30016294 | I18: 0.31845217 | J18: 0.46751342 | K18: 0.47768885 | L18: 0.053484083 | M18: 0.071249421 | N18: 0.57330381 | O18: 0.20309367 | P18: 0.40346491 | Q18: 4.206197e-05 | R18: 0.3608248 | S18: 0.63511252 | T18: 0.26634282 | U18: 0.34605609 | V18: 0.21292292 | W18: 0.36490452 | X18: 0.046340553 | Y18: 0 | Z18: 0.33213658 | AA18: 0 | AB18: 0.090938365 | AC18: 0 | AD18: 0.33122151 | AE18: 0.32133113 | AF18: 0.56094316 | AG18: 0.060875955 | AH18: 0 | AI18: 0 | AJ18: 0.31621195
C19: CARTERA DE CRÉDITOS CONSUMO | D19: 0.25614143 | E19: 0.29518867 | F19: 0.25123968 | G19: 0.21874049 | H19: 0.25515054 | I19: 0.23824433 | J19: 0.15127197 | K19: 0 | L19: 0.85191733 | M19: 0.54100883 | N19: 0.083928812 | O19: 0.29988666 | P19: 0.17771778 | Q19: 0.37648461 | R19: 0.27205784 | S19: 0.0071157035 | T19: 0.281924 | U19: 0.17592976 | V19: 0.50424762 | W19: 0.004157191 | X19: 0.47212795 | Y19: 0.062708384 | Z19: 0.1070248 | AA19: 0 | AB19: 0.28893569 | AC19: 0.00041644412 | AD19: 0.12003181 | AE19: 0.25615506 | AF19: 0.07307889 | AG19: 0.75248488 | AH19: 0 | AI19: 0.018566324 | AJ19: 0.24102815
C20: CARTERA DE CRÉDITOS INMOBILIARIO | D20: 0.035438712 | E20: 0.059002268 | F20: 0.059814169 | G20: 0.041692546 | H20: 0.051532677 | I20: 0.026186803 | J20: 0.018619355 | K20: 0 | L20: 9.5475034e-05 | M20: 0.099638751 | N20: 0.027980413 | O20: 0.060653674 | P20: 0.021763349 | Q20: 3.1286611e-05 | R20: 0.024523638 | S20: 0.052525433 | T20: 0.0057192277 | U20: 0.00020686301 | V20: 0.0021392659 | W20: 0.00066837674 | X20: 2.5229e-08 | Y20: 0 | Z20: 0.050723786 | AA20: 0 | AB20: 0.052292564 | AC20: 0 | AD20: 0.026377962 | AE20: 0.041722128 | AF20: 0.024363237 | AG20: 0.030591707 | AH20: 0 | AI20: 0 | AJ20: 0.044760836
C21: CARTERA DE CRÉDITOS MICROCRÉDITO | D21: 0.041906965 | E21: 0.00092381842 | F21: 0.11813161 | G21: 0.0045431747 | H21: 0.057938406 | I21: 0.0032394687 | J21: 0 | K21: 0 | L21: 0 | M21: 1.5818e-08 | N21: 0.00048148179 | O21: 0.11363387 | P21: 0.005300895 | Q21: 0.46380284 | R21: 0.027303453 | S21: 0.12715489 | T21: 0.00071912933 | U21: 0.13649206 | V21: 0.038334003 | W21: 0.037079035 | X21: 0.059254521 | Y21: 0.64287553 | Z21: 0.0016899161 | AA21: 0.78013848 | AB21: 0.34330692 | AC21: 0.97829969 | AD21: 0.22968388 | AE21: 0.053629969 | AF21: 0.00041923809 | AG21: 0.0004697407 | AH21: 0 | AI21: 0.806508 | AJ21: 0.058583039
C22: CARTERA DE CRÉDITOS VIVIENDA DE INTERÉS SOCIAL Y PÚBLICO | D22: 0 | E22: 0.0029166991 | F22: 0.0003415332 | G22: 0 | H22: 0.00074197986 | I22: 0 | J22: 0 | K22: 0 | L22: 0 | M22: 0.0058546745 | N22: 9.2686992e-05 | O22: 0 | P22: 0 | Q22: 0 | R22: 0.0003613329 | S22: 0 | T22: 0 | U22: 0 | V22: 0 | W22: 0 | X22: 0 | Y22: 0 | Z22: 0 | AA22: 0 | AB22: 0 | AC22: 0 | AD22: 0 | AE22: 0.00059052397 | AF22: 8.0704854e-05 | AG22: 0.0017921741 | AH22: 0 | AI22: 0 | AJ22: 0.00056141602
C23: CARTERA DE CRÃ¿DITOS EDUCATIVO | D23: 0.00031895373 | E23: 0.043485168 | F23: 0.0015056475 | G23: 0.00022552375 | H23: 0.0096851163 | I23: 0 | J23: 0.0006301591 | K23: 0 | L23: 0 | M23: 0 | N23: 0 | O23: 0.00049605023 | P23: 0.0027936597 | Q23: 0 | R23: 0.00033244127 | S23: 0.00046289349 | T23: 0 | U23: 0 | V23: 0 | W23: 0 | X23: 0 | Y23: 0 | Z23: 0 | AA23: 0 | AB23: 0 | AC23: 0 | AD23: 0.00015361416 | AE23: 0.0062599728 | AF23: 0 | AG23: 0 | AH23: 0 | AI23: 0 | AJ23: 0.0074658837
C24: CARTERA DE CRÉDITO INVERSIÓN PÚBLICA | D24: 0 | E24: 0 | F24: 0 | G24: 0 | H24: 0 | I24: 0 | J24: 0 | K24: 0 | L24: 0 | M24: 0 | N24: 0 | O24: 0 | P24: 0 | Q24: 0 | R24: 0 | S24: 0 | T24: 0 | U24: 0 | V24: 0 | W24: 0 | X24: 0 | Y24: 0 | Z24: 0 | AA24: 0 | AB24: 0 | AC24: 0 | AD24: 0 | AE24: 0 | AF24: 0 | AG24: 0 | AH24: 0 | AI24: 0 | AJ24: 0
B25: 1499 | C25: (PROVISIONES PARA CRÉDITOS INCOBRABLES) | D25: -0.0295151 | E25: -0.040277929 | F25: -0.077033016 | G25: -0.030611085 | H25: -0.051562313 | I25: -0.025588793 | J25: -0.021754856 | K25: -0.027357839 | L25: -0.10521913 | M25: -0.063197632 | N25: -0.027731371 | O25: -0.061412813 | P25: -0.017834468 | Q25: -0.080087757 | R25: -0.041201969 | S25: -0.02073202 | T25: -0.016828626 | U25: -0.039047754 | V25: -0.045526971 | W25: -0.01217934 | X25: -0.038057159 | Y25: -0.034869444 | Z25: -0.024807197 | AA25: -0.066853208 | AB25: -0.059604613 | AC25: -0.068536551 | AD25: -0.031987267 | AE25: -0.047461137 | AF25: -0.027683083 | AG25: -0.091624479 | AH25: 0 | AI25: -0.058021769 | AJ25: -0.046295422
B26: 149905 | C26: (CARTERA DE CRÉDITOS PRODUCTIVO) | D26: -0.006611408 | E26: -0.0035214961 | F26: -0.018173328 | G26: -0.0071096433 | H26: -0.010843113 | I26: -0.0040419934 | J26: -0.0060766664 | K26: -0.013245232 | L26: -0.0013031147 | M26: -0.0034755127 | N26: -0.014493461 | O26: -0.0095907231 | P26: -0.0043085782 | Q26: -7.63891e-07 | R26: -0.0071051382 | S26: -0.0098190886 | T26: -0.004067978 | U26: -0.0054548563 | V26: -0.0020455547 | W26: -0.0036211616 | X26: -0.0014769158 | Y26: 0 | Z26: -0.0059575019 | AA26: 0 | AB26: -0.0014669754 | AC26: 0 | AD26: -0.0048981408 | AE26: -0.0094014775 | AF26: -0.014332096 | AG26: -0.001977205 | AH26: 0 | AI26: 0 | AJ26: -0.0094686943
B27: 149910 | C27: (CARTERA DE CRÉDITOS DE CONSUMO) | D27: -0.004886227 | E27: -0.0075313813 | F27: -0.0049783022 | G27: -0.003705466 | H27: -0.0052478822 | I27: -0.010428609 | J27: -0.0029204287 | K27: 0 | L27: -0.0221082 | M27: -0.013899097 | N27: -0.003016296 | O27: -0.0061029106 | P27: -0.0045501003 | Q27: -0.019378876 | R27: -0.0079821373 | S27: -0.00017719325 | T27: -0.006936158 | U27: -0.01016766 | V27: -0.019677447 | W27: -2.4711935e-05 | X27: -0.01285711 | Y27: -0.0029010583 | Z27: -0.0038020113 | AA27: 0 | AB27: -0.0052316671 | AC27: -4.421789e-06 | AD27: -0.0031692351 | AE27: -0.0060835704 | AF27: -0.0026263635 | AG27: -0.019565526 | AH27: 0 | AI27: -0.0008539314 | AJ27: -0.0054958263
B28: 149915 | C28: (CARTERA DE CRÉDITOS INMOBILIARIO) | D28: -0.00075725606 | E28: -0.0014353543 | F28: -0.0013858865 | G28: -0.00090976346 | H28: -0.0011851718 | I28: -0.00041509146 | J28: -0.00050542338 | K28: 0 | L28: 0 | M28: -0.0015263051 | N28: -0.00061042085 | O28: -0.00091289155 | P28: -0.00050366064 | Q28: -1.6364144e-05 | R28: -0.00048679657 | S28: -0.00066375789 | T28: -8.9355554e-05 | U28: -2.06863e-06 | V28: -2.4696e-08 | W28: -4.469252e-06 | X28: -2.5229e-08 | Y28: 0 | Z28: -0.001025512 | AA28: 0 | AB28: -0.0011683603 | AC28: 0 | AD28: -0.00040966005 | AE28: -0.00092724061 | AF28: -0.00053150851 | AG28: -0.00046721748 | AH28: 0 | AI28: 0 | AJ28: -0.0010117668
B29: 149920 | C29: (CARTERA DE CRÉDITOS PARA MICROCRÉDITO) | D29: -0.0010940151 | E29: -8.2857012e-05 | F29: -0.002264724 | G29: -9.5297902e-05 | H29: -0.0011819446 | I29: -0.0002774784 | J29: 0 | K29: 0 | L29: 0 | M29: -1.384e-08 | N29: -2.1590314e-05 | O29: -0.002551937 | P29: -0.00028683392 | Q29: -0.02964895 | R29: -0.0015659251 | S29: -0.003044766 | T29: -9.672434e-05 | U29: -0.012482829 | V29: -0.0013610909 | W29: -0.00033245804 | X29: -0.0024981316 | Y29: -0.010132082 | Z29: -6.5814758e-05 | AA29: -0.045709938 | AB29: -0.012688553 | AC29: -0.045074638 | AD29: -0.0089387124 | AE29: -0.0015733494 | AF29: -1.879922e-05 | AG29: -1.6682724e-05 | AH29: 0 | AI29: -0.035041942 | AJ29: -0.0016429765
B30: 149940 | C30: (CARTERA DE CRÉDITOS DE VIVIENDA DE INTERÉS SOCIAL Y PÚBLICO) | D30: 0 | E30: -0.00054939122 | F30: -5.050289e-06 | G30: 0 | H30: -0.00011527746 | I30: 0 | J30: 0 | K30: 0 | L30: 0 | M30: -8.669674e-05 | N30: -1.056505e-06 | O30: 0 | P30: 0 | Q30: 0 | R30: -5.273155e-06 | S30: 0 | T30: 0 | U30: 0 | V30: 0 | W30: 0 | X30: 0 | Y30: 0 | Z30: 0 | AA30: 0 | AB30: 0 | AC30: 0 | AD30: 0 | AE30: -7.4883675e-05 | AF30: -9.19925e-07 | AG30: -2.6538735e-05 | AH30: 0 | AI30: 0 | AJ30: -8.7224218e-05
B31: 149945 | C31: (CARTERA DE CRÉDITO REFINANCIADA) | D31: -0.00076187939 | E31: -0.002808541 | F31: -0.00093722098 | G31: -0.00063715819 | H31: -0.0012325881 | I31: -0.0021507433 | J31: -1.8136554e-05 | K31: 0 | L31: -0.0020662871 | M31: -0.00060443965 | N31: -0.00091836433 | O31: -0.0046161195 | P31: -0.00035362552 | Q31: -0.00047116933 | R31: -0.0010519526 | S31: -0.0049141897 | T31: -0.0013813139 | U31: -0.00186261 | V31: -0.010568414 | W31: -0.0005977507 | X31: -0.0001986338 | Y31: -0.0067064235 | Z31: -0.0034314367 | AA31: -0.0052713371 | AB31: -0.020504115 | AC31: -0.0047837168 | AD31: -0.0059246776 | AE31: -0.0013324628 | AF31: -0.00079964252 | AG31: -0.0017229841 | AH31: 0 | AI31: -0.0055288839 | AJ31: -0.0013350729
B32: 149950 | C32: (CARTERA DE CRÉDITO REESTRUCTURADA) | D32: -0.002790832 | E32: -0.0090265551 | F32: -0.0085820764 | G32: -0.0076752219 | H32: -0.0073829608 | I32: -0.0060959594 | J32: -0.0013013967 | K32: -0.0017995904 | L32: -0.022090344 | M32: -0.021080192 | N32: -0.0027480505 | O32: -0.015193525 | P32: -0.0033672769 | Q32: -0.0012960529 | R32: -0.0068187124 | S32: -0.0015680669 | T32: -0.0040588298 | U32: -7.4623999e-05 | V32: -0.010341173 | W32: 0 | X32: -0.0030969522 | Y32: -0.014961781 | Z32: -0.0079483089 | AA32: -0.0035521906 | AB32: -0.003324229 | AC32: -0.00063853671 | AD32: -0.0030280538 | AE32: -0.007047622 | AF32: -0.0026254381 | AG32: -0.021637155 | AH32: 0 | AI32: -0.0059240094 | AJ32: -0.0064576461
B33: 149955 | C33: (CARTERA DE CRÉDITO EDUCATIVO) | D33: -1.3722543e-05 | E33: -0.0012604986 | F33: -1.7898643e-05 | G33: -3.701315e-06 | H33: -0.00027044339 | I33: 0 | J33: -2.0812295e-05 | K33: 0 | L33: 0 | M33: 0 | N33: 0 | O33: -4.849053e-06 | P33: -3.9469422e-05 | Q33: 0 | R33: -7.599178e-06 | S33: -4.994222e-06 | T33: 0 | U33: 0 | V33: 0 | W33: 0 | X33: 0 | Y33: 0 | Z33: 0 | AA33: 0 | AB33: 0 | AC33: 0 | AD33: -1.657364e-06 | AE33: -0.0001741532 | AF33: 0 | AG33: 0 | AH33: 0 | AI33: 0 | AJ33: -0.00020770178
B34: 149960 | C34: (CARTERA DE CRÉDITO DE INVERSIÓN PÚBLICA) | D34: 0 | E34: 0 | F34: 0 | G34: 0 | H34: 0 | I34: 0 | J34: 0 | K34: 0 | L34: 0 | M34: 0 | N34: 0 | O34: 0 | P34: 0 | Q34: 0 | R34: 0 | S34: 0 | T34: 0 | U34: 0 | V34: 0 | W34: 0 | X34: 0 | Y34: 0 | Z34: 0 | AA34: 0 | AB34: 0 | AC34: 0 | AD34: 0 | AE34: 0 | AF34: 0 | AG34: 0 | AH34: 0 | AI34: 0 | AJ34: 0
B35: 149980 | C35: PROVISIÓN GÉNERICA POR TECNOLOGÍA CREDITICIA | D35: 0 | E35: 0 | F35: 0 | G35: 0 | H35: 0 | I35: 0 | J35: 0 | K35: 0 | L35: 0 | M35: 0 | N35: 0 | O35: 0 | P35: 0 | Q35: 0 | R35: 0 | S35: 0 | T35: 0 | U35: -0.0026785404 | V35: -0.0006693343 | W35: 0 | X35: -0.0073609812 | Y35: 0 | Z35: 0 | AA35: 0 | AB35: 0 | AC35: 0 | AD35: -0.00026874092 | AE35: -9.150257e-06 | AF35: 0 | AG35: -8.201865e-06 | AH35: 0 | AI35: 0 | AJ35: -1.0300259e-05
B36: 149985 | C36: PROVISIÓN ANTICÍCLICA | D36: -0.00019068459 | E36: -0.0012387494 | F36: -0.012414878 | G36: -0.00064306937 | H36: -0.0055398568 | I36: 0 | J36: -0.00053354442 | K36: 0 | L36: 0 | M36: -0.00099638467 | N36: 0 | O36: 0 | P36: -0.00093247458 | Q36: 0 | R36: -0.00024317693 | S36: 0 | T36: -0.00012919938 | U36: 0 | V36: -0.00064457404 | W36: 0 | X36: -0.00074126134 | Y36: 0 | Z36: -0.0018026356 | AA36: 0 | AB36: 0 | AC36: 0 | AD36: -8.3766572e-05 | AE36: -0.0035981234 | AF36: 0 | AG36: -0.00031290173 | AH36: 0 | AI36: 0 | AJ36: -0.0042678858
... B44: 1 | C44: TOTAL ACTIVO | D44: 1 | E44: 1 | F44: 1 | G44: 1 | H44: 1 | I44: 1 | J44: 1 | K44: 1 | L44: 1 | M44: 1 | N44: 1 | O44: 1 | P44: 1 | Q44: 1 | R44: 1 | S44: 1 | T44: 1 | U44: 1 | V44: 1 | W44: 1 | X44: 1 | Y44: 1 | Z44: 1 | AA44: 1 | AB44: 1 | AC44: 1 | AD44: 1 | AE44: 1 | AF44: 1 | AG44: 1 | AH44: 0 | AI44: 1 | AJ44: 1
C47: PASIVOS
B48: 21 | C48: OBLIGACIONES CON EL PÚBLICO | D48: 0.86848658 | E48: 0.87349035 | F48: 0.90361787 | G48: 0.84214244 | H48: 0.87897975 | I48: 0.92849319 | J48: 0.88090067 | K48: 0.91704589 | L48: 0.61865049 | M48: 0.92774138 | N48: 0.92656051 | O48: 0.92333518 | P48: 0.92680055 | Q48: 0.59944311 | R48: 0.86543756 | S48: 0.64153196 | T48: 0.91641313 | U48: 0.9745992 | V48: 0.9507785 | W48: 0.97839733 | X48: 0.91880302 | Y48: 0.8494628 | Z48: 0.8857499 | AA48: 0.5124507 | AB48: 0.8398632 | AC48: 0.25027102 | AD48: 0.76043753 | AE48: 0.8706161 | AF48: 0.92536889 | AG48: 0.72673035 | AH48: 0 | AI48: 0.53310782 | AJ48: 0.87640829
B49: 2101 | C49: Depósitos a la vista | D49: 0.52661618 | E49: 0.44499769 | F49: 0.61418847 | G49: 0.51918817 | H49: 0.54502709 | I49: 0.47324169 | J49: 0.56689705 | K49: 0.9159501 | L49: 0.0090326927 | M49: 0.41812565 | N49: 0.55155314 | O49: 0.50936271 | P49: 0.48924272 | Q49: 0.12229509 | R49: 0.46369026 | S49: 0.38089195 | T49: 0.33271883 | U49: 0.72548597 | V49: 0.34382059 | W49: 0.68722085 | X49: 0.1015907 | Y49: 0.080017588 | Z49: 0.47036763 | AA49: 0.069567154 | AB49: 0.31262659 | AC49: 0.077185409 | AD49: 0.35444241 | AE49: 0.51206634 | AF49: 0.59719054 | AG49: 0.15095894 | AH49: 0 | AI49: 0.075302493 | AJ49: 0.52989536
B50: 2102 | C50: Operaciones de reporto | D50: 0 | E50: 0 | F50: 0 | G50: 0 | H50: 0 | I50: 0 | J50: 0 | K50: 0 | L50: 0 | M50: 0 | N50: 0 | O50: 0 | P50: 0 | Q50: 0 | R50: 0 | S50: 0 | T50: 0 | U50: 0 | V50: 0 | W50: 0 | X50: 0 | Y50: 0 | Z50: 0 | AA50: 0 | AB50: 0 | AC50: 0 | AD50: 0 | AE50: 0 | AF50: 0 | AG50: 0 | AH50: 0 | AI50: 0 | AJ50: 0
B51: 2103 | C51: Depósitos a plazo | D51: 0.31467151 | E51: 0.37384489 | F51: 0.2541022 | G51: 0.30209125 | H51: 0.299097 | I51: 0.43560204 | J51: 0.27505757 | K51: 0 | L51: 0.60358618 | M51: 0.50960117 | N51: 0.35205195 | O51: 0.41394769 | P51: 0.39947307 | Q51: 0.47225819 | R51: 0.38004376 | S51: 0.23092976 | T51: 0.54307855 | U51: 0.20632396 | V51: 0.59355049 | W51: 0.25755795 | X51: 0.81480534 | Y51: 0.76944521 | Z51: 0.37377445 | AA51: 0.44288354 | AB51: 0.51587956 | AC51: 0.17292157 | AD51: 0.38145002 | AE51: 0.32834451 | AF51: 0.30796064 | AG51: 0.57169567 | AH51: 0 | AI51: 0.45775226 | AJ51: 0.31323467
B52: 2104 | C52: Depósitos de garantía | D52: 0 | E52: 0 | F52: 3.0284868e-05 | G52: 0 | H52: 1.2521155e-05 | I52: 0.00011225764 | J52: 0.00011464789 | K52: 0 | L52: 0 | M52: 0 | N52: 2.1465063e-05 | O52: 0 | P52: 0 | Q52: 0 | R52: 5.083773e-05 | S52: 0 | T52: 9.780751e-05 | U52: 6.337503e-06 | V52: 3.4480771e-05 | W52: 0 | X52: 0 | Y52: 0 | Z52: 0 | AA52: 0 | AB52: 0 | AC52: 0 | AD52: 1.748837e-05 | AE52: 2.5238778e-05 | AF52: 1.8776759e-05 | AG52: 3.68957e-07 | AH52: 0 | AI52: 0 | AJ52: 2.7804671e-05
B53: 2105 | C53: Depósitos restringidos | D53: 0.027198891 | E53: 0.054647767 | F53: 0.035296912 | G53: 0.020863021 | H53: 0.03484313 | I53: 0.019537207 | J53: 0.038831407 | K53: 0.0010957857 | L53: 0.0060316191 | M53: 1.4564197e-05 | N53: 0.022933957 | O53: 2.4781878e-05 | P53: 0.038084755 | Q53: 0.004889835 | R53: 0.021652704 | S53: 0.029710247 | T53: 0.040517943 | U53: 0.042782931 | V53: 0.013372943 | W53: 0.033618529 | X53: 0.002406987 | Y53: 0 | Z53: 0.04160782 | AA53: 0 | AB53: 0.011357053 | AC53: 0.00016404309 | AD53: 0.024527614 | AE53: 0.030180025 | AF53: 0.020198925 | AG53: 0.0040753728 | AH53: 0 | AI53: 5.3070403e-05 | AJ53: 0.033250449
B54: 22 | C54: OPERACIONES INTERBANCARIAS | D54: 0 | E54: 0 | F54: 0 | G54: 0 | H54: 0 | I54: 0 | J54: 0 | K54: 0 | L54: 0 | M54: 0 | N54: 0 | O54: 0 | P54: 0 | Q54: 0 | R54: 0 | S54: 0 | T54: 0 | U54: 0 | V54: 0 | W54: 0 | X54: 0 | Y54: 0 | Z54: 0 | AA54: 0 | AB54: 0 | AC54: 0 | AD54: 0 | AE54: 0 | AF54: 0 | AG54: 0 | AH54: 0 | AI54: 0 | AJ54: 0
B55: 23 | C55: OBLIGACIONES INMEDIATAS | D55: 0.0083685239 | E55: 0.0071555989 | F55: 0.0065777782 | G55: 0.0061808749 | H55: 0.0069666236 | I55: 0.0019649863 | J55: 0.010825872 | K55: 0.035471224 | L55: 0 | M55: 0.0030903561 | N55: 0.0026867704 | O55: 0.0036211775 | P55: 0.0029113546 | Q55: 0.00028847248 | R55: 0.0055142241 | S55: 1.8955409e-05 | T55: 0.0023497676 | U55: 0.00053494823 | V55: 0.0013561029 | W55: 0.0029460964 | X55: 0.0010192473 | Y55: 0 | Z55: 0.05552687 | AA55: 0.00029275655 | AB55: 0.0033243515 | AC55: 0 | AD55: 0.0019866192 | AE55: 0.0063258205 | AF55: 0.0067927252 | AG55: 0.0010595836 | AH55: 0 | AI55: 0.00010642009 | AJ55: 0.0066708568
B56: 24 | C56: ACEPTACIONES EN CIRCULACIÓN | D56: 0 | E56: 0.0013884392 | F56: 6.316106e-06 | G56: 0 | H56: 0.00028118267 | I56: 2.9156915e-05 | J56: 0.00037619045 | K56: 0.00038679897 | L56: 0 | M56: 0 | N56: 0 | O56: 0 | P56: 0.0010236464 | Q56: 0 | R56: 0.00017414427 | S56: 0 | T56: 0 | U56: 0 | V56: 0 | W56: 0 | X56: 0 | Y56: 0 | Z56: 0 | AA56: 0 | AB56: 0 | AC56: 0 | AD56: 0 | AE56: 0.00023680041 | AF56: 4.8443056e-05 | AG56: 0 | AH56: 0 | AI56: 0 | AJ56: 0.00027528393
B57: 25 | C57: CUENTAS POR PAGAR | D57: 0.031671308 | E57: 0.032153098 | F57: 0.027243429 | G57: 0.030026372 | H57: 0.029622856 | I57: 0.019566253 | J57: 0.029080199 | K57: 0.044014444 | L57: 0.29953249 | M57: 0.027662393 | N57: 0.032566794 | O57: 0.020175972 | P57: 0.019291153 | Q57: 0.054699903 | R57: 0.060126525 | S57: 0.019168437 | T57: 0.028019526 | U57: 0.018253791 | V57: 0.041166109 | W57: 0.018460809 | X57: 0.058099049 | Y57: 0.031540852 | Z57: 0.053256169 | AA57: 0.027447795 | AB57: 0.036652477 | AC57: 0.057149291 | AD57: 0.027620177 | AE57: 0.039549961 | AF57: 0.034000508 | AG57: 0.20482894 | AH57: 0 | AI57: 0.038337697 | AJ57: 0.028912285
B58: 26 | C58: OBLIGACIONES FINANCIERAS | D58: 0.07938253 | E58: 0.07899171 | F58: 0.021632757 | G58: 0.084380186 | H58: 0.056383007 | I58: 0.04788083 | J58: 0.062294233 | K58: 0.00036277959 | L58: 0.028912982 | M58: 0.024301961 | N58: 0.038008174 | O58: 0.040862547 | P58: 0.030116235 | Q58: 0.3426772 | R58: 0.055241351 | S58: 0.32034154 | T58: 0.049368398 | U58: 0 | V58: 0 | W58: 0 | X58: 0 | Y58: 0.09723303 | Z58: 0 | AA58: 0.4563723 | AB58: 0.11809881 | AC58: 0.69016348 | AD58: 0.20022699 | AE58: 0.060774195 | AF58: 0.03329343 | AG58: 0.027044283 | AH58: 0 | AI58: 0.41960584 | AJ58: 0.063926741
B59: 2601 | C59: Sobregiros | D59: 0 | E59: 0 | F59: 0.00090848413 | G59: 2.9374227e-05 | H59: 0.00038122391 | I59: 0 | J59: 0 | K59: 0.00036277959 | L59: 0 | M59: 0 | N59: 0 | O59: 0 | P59: 0 | Q59: 0 | R59: 1.2984249e-05 | S59: 0 | T59: 0 | U59: 0 | V59: 0 | W59: 0 | X59: 0 | Y59: 0 | Z59: 0 | AA59: 0 | AB59: 0 | AC59: 0 | AD59: 0 | AE59: 0.00024795416 | AF59: 4.5434847e-05 | AG59: 0 | AH59: 0 | AI59: 0 | AJ59: 0.00028883734
... B73: 2 | C73: TOTAL PASIVOS | D73: 1 | E73: 1 | F73: 1 | G73: 1 | H73: 1 | I73: 1 | J73: 1 | K73: 1 | L73: 1 | M73: 1 | N73: 1 | O73: 1 | P73: 1 | Q73: 1 | R73: 1 | S73: 1 | T73: 1 | U73: 1 | V73: 1 | W73: 1 | X73: 1 | Y73: 1 | Z73: 1 | AA73: 1 | AB73: 1 | AC73: 1 | AD73: 1 | AE73: 1 | AF73: 1 | AG73: 1 | AH73: 0 | AI73: 1 | AJ73: 1
C75: PATRIMONIO
B76: 31 | C76: CAPITAL SOCIAL | D76: 0.84876934 | E76: 0.7228193 | F76: 0.70418644 | G76: 0.81817501 | H76: 0.75235017 | I76: 0.68063744 | J76: 0.82293896 | K76: 0.83095278 | L76: 0.64488011 | M76: 0.78655991 | N76: 0.81178146 | O76: 0.72629846 | P76: 0.78493059 | Q76: 0.58435409 | R76: 0.73683095 | S76: 0.89721629 | T76: 0.79475491 | U76: 0.79956057 | V76: 0.97689591 | W76: 0.68383133 | X76: 1.5954953 | Y76: 1.9557363 | Z76: 0.98879129 | AA76: 1.0517938 | AB76: 0.77680069 | AC76: 0.94473308 | AD76: 0.92595354 | AE76: 0.75423291 | AF76: 0.81498609 | AG76: 0.67392463 | AH76: 0 | AI76: 1.1945831 | AJ76: 0.75298706
B77: 32 | C77: PRIMA O DESCUENTO EN COLOCACIÓN DE ACCIONES Y CERTIFICADOS | D77: 0 | E77: 0 | F77: 0 | G77: 0.0022897422 | H77: 0.00034925587 | I77: 0 | J77: 0 | K77: 0 | L77: 0 | M77: 0 | N77: 0 | O77: 0 | P77: 0 | Q77: 0.0075277705 | R77: 0.00061347477 | S77: 0 | T77: 0 | U77: 0 | V77: 0 | W77: 0 | X77: 0 | Y77: 0 | Z77: 0 | AA77: 0 | AB77: 0 | AC77: 0 | AD77: 0 | AE77: 0.00043082368 | AF77: 0 | AG77: 0 | AH77: 0 | AI77: 0 | AJ77: 0.00054290549
B78: 33 | C78: RESERVAS | D78: 0.1408703 | E78: 0.18532549 | F78: 0.2176942 | G78: 0.18970216 | H78: 0.1913474 | I78: 0.17602347 | J78: 0.13357561 | K78: 0.14359503 | L78: 0.30968862 | M78: 0.19512986 | N78: 0.13398907 | O78: 0.15482282 | P78: 0.10185551 | Q78: 0.24557003 | R78: 0.19212383 | S78: 0.10136574 | T78: 0.072561414 | U78: 0.10771513 | V78: 0.040477699 | W78: 0.25949233 | X78: 0 | Y78: 2.785346e-06 | Z78: 0.0097641065 | AA78: 0.05460409 | AB78: 0.11917774 | AC78: 0.054231106 | AD78: 0.099880685 | AE78: 0.18764447 | AF78: 0.13559478 | AG78: 0.28618887 | AH78: 0 | AI78: 0.043415009 | AJ78: 0.1821717
B79: 34 | C79: OTROS APORTES PATRIMONIALES | D79: 0 | E79: 0 | F79: 0 | G79: 0 | H79: 0 | I79: 0 | J79: 0 | K79: 0 | L79: 0 | M79: 0 | N79: 0 | O79: 0 | P79: 0 | Q79: 9.7401829e-05 | R79: 7.937751e-06 | S79: 0.00090179628 | T79: 0 | U79: 0 | V79: 0 | W79: 9.9711793e-05 | X79: 0 | Y79: 0 | Z79: 0 | AA79: 0 | AB79: 0.057199976 | AC79: 0.0010358107 | AD79: 0.0068839142 | AE79: 0.00030300279 | AF79: 0 | AG79: 0 | AH79: 0 | AI79: 0.00038830287 | AJ79: 0.00037752668
B80: 35 | C80: SUPERÁVIT POR VALUACIONES | D80: 0.010360357 | E80: 0.083236371 | F80: 0.061643054 | G80: -0.010894793 | H80: 0.046847046 | I80: 0.14327789 | J80: 0.042471331 | K80: 0.0061161694 | L80: 0.045431276 | M80: 0.014804335 | N80: 0.054229462 | O80: 0.062155779 | P80: 0.10458767 | Q80: 0.0041832879 | R80: 0.054170658 | S80: 0.017146335 | T80: 0.13268368 | U80: 0.084452162 | V80: 0.0076566527 | W80: 0.056576629 | X80: 0.0014378357 | Y80: 0.0011394759 | Z80: 0.0014446034 | AA80: 0.026442367 | AB80: 0.046821597 | AC80: 0 | AD80: 0.040145661 | AE80: 0.049237818 | AF80: 0.04618697 | AG80: 0.039834678 | AH80: 0 | AI80: 0.011409342 | AJ80: 0.051262171
B81: 36 | C81: RESULTADOS | D81: 1.76e-10 | E81: 0.0086188419 | F81: 0.016476299 | G81: 0.00072788366 | H81: 0.0091061305 | I81: 6.1193446e-05 | J81: 0.0010141027 | K81: 0.019336018 | L81: 0 | M81: 0.0035058888 | N81: 0 | O81: 0.056722944 | P81: 0.0086262342 | Q81: 0.15826742 | R81: 0.016253148 | S81: -0.016630169 | T81: 0 | U81: 0.0082721319 | V81: -0.02503026 | W81: 0 | X81: -0.5969331 | Y81: -0.9568786 | Z81: 0 | AA81: -0.13284022 | AB81: 0 | AC81: 0 | AD81: -0.072863801 | AE81: 0.008150979 | AF81: 0.0032321581 | AG81: 5.1819437e-05 | AH81: 0 | AI81: -0.24979579 | AJ81: 0.012658637
B82: 3601 | C82: Utilidades o excedentes acumulados | D82: 1.76e-10 | E82: 0.0086188419 | F82: 0.016476299 | G82: 0.00072788366 | H82: 0.0091061305 | I82: 6.1193446e-05 | J82: 0.0010141027 | K82: 0.019336018 | L82: 0 | M82: 0.0035058888 | N82: 0 | O82: 0.056722944 | P82: 0.0086262342 | Q82: 0.15826742 | R82: 0.016253148 | S82: 0.010077658 | T82: 0 | U82: 0.0082721319 | V82: 0.0081514978 | W82: 0 | X82: 0 | Y82: 2.5073355e-05 | Z82: 0 | AA82: 0 | AB82: 0 | AC82: 0 | AD82: 0.0033804459 | AE82: 0.011474743 | AF82: 0.0032321581 | AG82: 0.00071742185 | AH82: 0 | AI82: 5.073907e-06 | AJ82: 0.013989454
B83: 3602 | C83: (Pérdidas acumuladas) | D83: 0 | E83: 0 | F83: 0 | G83: 0 | H83: 0 | I83: 0 | J83: 0 | K83: 0 | L83: 0 | M83: 0 | N83: 0 | O83: 0 | P83: 0 | Q83: 0 | R83: 0 | S83: -0.026707827 | T83: 0 | U83: 0 | V83: -0.033181758 | W83: 0 | X83: -0.5969331 | Y83: -0.95690367 | Z83: 0 | AA83: -0.13284022 | AB83: 0 | AC83: 0 | AD83: -0.076244246 | AE83: -0.0033237645 | AF83: 0 | AG83: -0.00066560242 | AH83: 0 | AI83: -0.24980087 | AJ83: -0.0013308169
B84: 3603 | C84: Utilidad o excedente del ejercicio | D84: 0 | E84: 0 | F84: 0 | G84: 0 | H84: 0 | I84: 0 | J84: 0 | K84: 0 | L84: 0 | M84: 0 | N84: 0 | O84: 0 | P84: 0 | Q84: 0 | R84: 0 | S84: 0 | T84: 0 | U84: 0 | V84: 0 | W84: 0 | X84: 0 | Y84: 0 | Z84: 0 | AA84: 0 | AB84: 0 | AC84: 0 | AD84: 0 | AE84: 0 | AF84: 0 | AG84: 0 | AH84: 0 | AI84: 0 | AJ84: 0
B85: 3604 | C85: (Pérdida del ejercicio) | D85: 0 | E85: 0 | F85: 0 | G85: 0 | H85: 0 | I85: 0 | J85: 0 | K85: 0 | L85: 0 | M85: 0 | N85: 0 | O85: 0 | P85: 0 | Q85: 0 | R85: 0 | S85: 0 | T85: 0 | U85: 0 | V85: 0 | W85: 0 | X85: 0 | Y85: 0 | Z85: 0 | AA85: 0 | AB85: 0 | AC85: 0 | AD85: 0 | AE85: 0 | AF85: 0 | AG85: 0 | AH85: 0 | AI85: 0 | AJ85: 0
B86: 37 | C86: (DESVALORIZACIÓN DEL PATRIMONIO) | D86: 0 | E86: 0 | F86: 0 | G86: 0 | H86: 0 | I86: 0 | J86: 0 | K86: 0 | L86: 0 | M86: 0 | N86: 0 | O86: 0 | P86: 0 | Q86: 0 | R86: 0 | S86: 0 | T86: 0 | U86: 0 | V86: 0 | W86: 0 | X86: 0 | Y86: 0 | Z86: 0 | AA86: 0 | AB86: 0 | AC86: 0 | AD86: 0 | AE86: 0 | AF86: 0 | AG86: 0 | AH86: 0 | AI86: 0 | AJ86: 0
B87: 3 | C87: TOTAL PATRIMONIO | D87: 1 | E87: 1 | F87: 1 | G87: 1 | H87: 1 | I87: 1 | J87: 1 | K87: 1 | L87: 1 | M87: 1 | N87: 1 | O87: 1 | P87: 1 | Q87: 1 | R87: 1 | S87: 1 | T87: 1 | U87: 1 | V87: 1 | W87: 1 | X87: 1 | Y87: 1 | Z87: 1 | AA87: 1 | AB87: 1 | AC87: 1 | AD87: 1 | AE87: 1 | AF87: 1 | AG87: 1 | AH87: 0 | AI87: 1 | AJ87: 1

Sheet EPyG %
B3: ESTADO DE PÉRDIDAS Y GANANCIAS
B4: SISTEMA DE BANCOS PRIVADOS
B5: 31/05/2022
B6: (en porcentajes)
B8: CÓDIGO | C8: CUENTA | D8: BP GUAYAQUIL | E8: BP PACIFICO | F8: BP PICHINCHA | G8: BP PRODUBANCO | H8: BANCOS PRIVADOS GRANDES | I8: BP AUSTRO | J8: BP BOLIVARIANO | K8: BP CITIBANK | L8: BP DINERS | M8: BP GENERAL RUMIÑAHUI | N8: BP INTERNACIONAL | O8: BP LOJA | P8: BP MACHALA | Q8: BP SOLIDARIO | R8: BANCOS PRIVADOS MEDIANOS | S8: BP PROCREDIT | T8: BP AMAZONAS | U8: BP COMERCIAL DE MANABI | V8: BP LITORAL | W8: BP COOPNACIONAL | X8: BP CAPITAL | Y8: BP FINCA S.A. | Z8: BP DELBANK | AA8: BP D-MIRO S.A. | AB8: BP BANCO DESARROLLO DE LOS PUEBLOS S.A., CODESARROLLO | AC8: BP VISIONFUND ECUADOR S.A. | AD8: BANCOS PRIVADOS PEQUEÑOS | AE8: TOTAL BANCOS PRIVADOS | AF8: BANCOS PRIVADOS COMERCIALES | AG8: BANCOS PRIVADOS CONSUMO | AH8: BANCOS PRIVADOS VIVIENDA | AI8: BANCOS PRIVADOS MICROCRÉDITO | AJ8: BANCA MÚLTIPLE
C9: TOTAL INGRESOS | D9: 1 | E9: 1 | F9: 1 | G9: 1 | H9: 1 | I9: 1 | J9: 1 | K9: 1 | L9: 1 | M9: 1 | N9: 1 | O9: 1 | P9: 1 | Q9: 1 | R9: 1 | S9: 1 | T9: 1 | U9: 1 | V9: 1 | W9: 1 | X9: 1 | Y9: 1 | Z9: 1 | AA9: 1 | AB9: 1 | AC9: 1 | AD9: 1 | AE9: 1 | AF9: 1 | AG9: 1 | AH9: 0 | AI9: 1 | AJ9: 1
B11: 51 | C11: INTERESES Y DESCUENTOS GANADOS | D11: 0.67508833 | E11: 0.60002421 | F11: 0.7143389 | G11: 0.69385369 | H11: 0.68051713 | I11: 0.7113919 | J11: 0.75112215 | K11: 0.55707948 | L11: 0.4664324 | M11: 0.81654124 | N11: 0.77141365 | O11: 0.86604976 | P11: 0.84270462 | Q11: 0.7692829 | R11: 0.68558301 | S11: 0.84068448 | T11: 0.80475518 | U11: 0.86013517 | V11: 0.90032165 | W11: 0.8352522 | X11: 0.75193128 | Y11: 0.78538396 | Z11: 0.31278219 | AA11: 0.77872122 | AB11: 0.79006077 | AC11: 0.86146654 | AD11: 0.80458305 | AE11: 0.68661936 | AF11: 0.75076633 | AG11: 0.5384683 | AH11: 0 | AI11: 0.8119614 | AJ11: 0.69946912
B12: 5101 | C12: Depósitos | D12: 0.0005625104 | E12: 5.73287e-05 | F12: 0.000222181 | G12: 0.0030807328 | H12: 0.0007171893 | I12: 0.01393141 | J12: 0.0072689096 | K12: 0.008475121 | L12: 8.93554e-05 | M12: 0.0073423531 | N12: 0.0059315694 | O12: 0.0022947014 | P12: 0.0075620705 | Q12: 0.0005093244 | R12: 0.0053279401 | S12: 0.0040374516 | T12: 0.0083106545 | U12: 3.37541e-05 | V12: 3.29955e-05 | W12: 0.14271329 | X12: 0.000534588 | Y12: 6.60047e-05 | Z12: 0.012140827 | AA12: 0.0005231631 | AB12: 0.002773611 | AC12: 0.0020988349 | AD12: 0.011946769 | AE12: 0.002620058 | AF12: 0.0061765957 | AG12: 0.0015135883 | AH12: 0 | AI12: 0.001008046 | AJ12: 0.0025101032
B13: 5102 | C13: Operaciones interbancarias | D13: 0 | E13: 0 | F13: 5.6671e-06 | G13: 0.0001617516 | H13: 2.89541e-05 | I13: 0 | J13: 8.80297e-05 | K13: 0.0004382977 | L13: 8.135e-07 | M13: 0 | N13: 0 | O13: 0 | P13: 0 | Q13: 0 | R13: 2.43593e-05 | S13: 0 | T13: 0 | U13: 0 | V13: 0 | W13: 0 | X13: 0 | Y13: 0 | Z13: 0 | AA13: 0 | AB13: 0 | AC13: 0 | AD13: 0 | AE13: 2.642e-05 | AF13: 4.22222e-05 | AG13: 6.476e-07 | AH13: 0 | AI13: 0 | AJ13: 2.8882e-05
B14: 5103 | C14: INTERESES y descuentos de inversiones en títulos valores | D14: 0.024826112 | E14: 0.028754401 | F14: 0.042959677 | G14: 0.017583553 | H14: 0.032613111 | I14: 0.075190597 | J14: 0.027269853 | K14: 0.15403366 | L14: 0.004574636 | M14: 0.020564651 | N14: 0.059727533 | O14: 0.028170976 | P14: 0.068877378 | Q14: 0.0097735475 | R14: 0.035754152 | S14: 0.0079805881 | T14: 0.10567193 | U14: 0.048648192 | V14: 0.02864036 | W14: 0.19048425 | X14: 0.021250514 | Y14: 0.0053356671 | Z14: 0.033920426 | AA14: 0.037357427 | AB14: 0.023325557 | AC14: 0.0021556225 | AD14: 0.038218125 | AE14: 0.033836 | AF14: 0.068812264 | AG14: 0.0078966175 | AH14: 0 | AI14: 0.01581538 | AJ14: 0.034742806
B15: 5104 | C15: INTERESES Y DESCUENTOS DE CARTERA DE CRÉDITOS | D15: 0.6496997 | E15: 0.57117255 | F15: 0.66955378 | G15: 0.67302765 | H15: 0.64643014 | I15: 0.62224934 | J15: 0.7152182 | K15: 0.39280753 | L15: 0.46173239 | M15: 0.78863424 | N15: 0.70575455 | O15: 0.83558409 | P15: 0.76626517 | Q15: 0.75900003 | R15: 0.64420838 | S15: 0.82866644 | T15: 0.69010489 | U15: 0.81011103 | V15: 0.8716483 | W15: 0.50205465 | X15: 0.73014618 | Y15: 0.77998229 | Z15: 0.26672094 | AA15: 0.74084063 | AB15: 0.7639616 | AC15: 0.85721208 | AD15: 0.75430023 | AE15: 0.64958052 | AF15: 0.67560762 | AG15: 0.52902943 | AH15: 0 | AI15: 0.79513797 | AJ15: 0.6615224
B16: 5190 | C16: Otros INTERESES y descuentos | D16: 0 | E16: 3.99334e-05 | F16: 0.0015975903 | G16: 0 | H16: 0.0007277364 | I16: 2.05522e-05 | J16: 0.0012771571 | K16: 0.0013248652 | L16: 3.52021e-05 | M16: 0 | N16: 0 | O16: 0 | P16: 0 | Q16: 3e-10 | R16: 0.000268177 | S16: 0 | T16: 0.0006677008 | U16: 0.0013421983 | V16: 0 | W16: 0 | X16: 0 | Y16: 0 | Z16: 0 | AA16: 0 | AB16: 0 | AC16: 0 | AD16: 0.0001179288 | AE16: 0.000556367 | AF16: 0.0001276274 | AG16: 2.80226e-05 | AH16: 0 | AI16: 0 | AJ16: 0.000664927
B17: 41 | C17: INTERESES CAUSADOS | D17: 0.21269795 | E17: 0.23501569 | F17: 0.14039396 | G17: 0.1959966 | H17: 0.18195754 | I17: 0.30606201 | J17: 0.2480842 | K17: 0.0017218398 | L17: 0.12561094 | M17: 0.23185353 | N17: 0.2868856 | O17: 0.27491468 | P17: 0.30106771 | Q17: 0.20493903 | R17: 0.22471285 | S17: 0.3362896 | T17: 0.42183009 | U17: 0.13488068 | V17: 0.15332587 | W17: 0.20974184 | X17: 0.48793194 | Y17: 0.40323062 | Z17: 0.089308967 | AA17: 0.32607006 | AB17: 0.29311282 | AC17: 0.19487338 | AD17: 0.30584161 | AE17: 0.20031197 | AF17: 0.2594151 | AG17: 0.1466881 | AH17: 0 | AI17: 0.29561013 | AJ17: 0.20159759
B18: 4101 | C18: Obligaciones con el público | D18: 0.16960284 | E18: 0.1947675 | F18: 0.1187853 | G18: 0.14189834 | H18: 0.14732522 | I18: 0.2742222 | J18: 0.20223379 | K18: 0.0014535472 | L18: 0.12075406 | M18: 0.21267942 | N18: 0.2706417 | O18: 0.25883359 | P18: 0.27041327 | Q18: 0.11399385 | R18: 0.19728992 | S18: 0.17427588 | T18: 0.38821774 | U18: 0.13486713 | V18: 0.15332587 | W18: 0.20974184 | X18: 0.48793194 | Y18: 0.36681016 | Z18: 0.089308967 | AA18: 0.14549544 | AB18: 0.26146791 | AC18: 0.045028846 | AD18: 0.21653686 | AE18: 0.16606157 | AF18: 0.24471017 | AG18: 0.13905554 | AH18: 0 | AI18: 0.16330544 | AJ18: 0.16356249
B19: 4102 | C19: Operaciones interbancarias | D19: 0 | E19: 0 | F19: 8.59086e-05 | G19: 0 | H19: 3.86951e-05 | I19: 0 | J19: 0 | K19: 0.0002682925 | L19: 0 | M19: 0 | N19: 0 | O19: 0 | P19: 0 | Q19: 2.565e-06 | R19: 5.2266e-06 | S19: 0 | T19: 0 | U19: 0 | V19: 0 | W19: 0 | X19: 0 | Y19: 0 | Z19: 0 | AA19: 0 | AB19: 0 | AC19: 0 | AD19: 0 | AE19: 2.64199e-05 | AF19: 2.58453e-05 | AG19: 0 | AH19: 0 | AI19: 0 | AJ19: 3.02263e-05
B20: 4103 | C20: Obligaciones financieras | D20: 0.036547956 | E20: 0.040248188 | F20: 0.017183198 | G20: 0.051758997 | H20: 0.031063291 | I20: 0.03183981 | J20: 0.041751679 | K20: 0 | L20: 0.0048568846 | M20: 0.012164173 | N20: 0.0162439 | O20: 0.016081092 | P20: 0.016265795 | Q20: 0.090942619 | R20: 0.025580229 | S20: 0.16201373 | T20: 0.033553888 | U20: 0 | V20: 0 | W20: 0 | X20: 0 | Y20: 0.036420457 | Z20: 0 | AA20: 0.18057462 | AB20: 0.031644917 | AC20: 0.14984453 | AD20: 0.089297487 | AE20: 0.031370758 | AF20: 0.014679087 | AG20: 0.0062556421 | AH20: 0 | AI20: 0.13230469 | AJ20: 0.034705246
B21: 4104 | C21: Valores en circulación y obligaciones convertibles en acciones | D21: 0.0065471591 | E21: 0 | F21: 0.0043328038 | G21: 0.0023392673 | H21: 0.0035272899 | I21: 0 | J21: 0.0040987299 | K21: 0 | L21: 0 | M21: 0.007009943 | N21: 0 | O21: 0 | P21: 0.014388643 | Q21: 0 | R21: 0.0018374705 | S21: 0 | T21: 0 | U21: 0 | V21: 0 | W21: 0 | X21: 0 | Y21: 0 | Z21: 0 | AA21: 0 | AB21: 0 | AC21: 0 | AD21: 0 | AE21: 0.0028510197 | AF21: 0 | AG21: 0.0013769156 | AH21: 0 | AI21: 0 | AJ21: 0.0032969485
B22: 4105 | C22: Otros INTERESES | D22: 0 | E22: 0 | F22: 6.7469e-06 | G22: 0 | H22: 3.039e-06 | I22: 0 | J22: 0 | K22: 0 | L22: 0 | M22: 0 | N22: 0 | O22: 0 | P22: 0 | Q22: 0 | R22: 0 | S22: 0 | T22: 5.8463e-05 | U22: 1.35549e-05 | V22: 0 | W22: 0 | X22: 0 | Y22: 0 | Z22: 0 | AA22: 0 | AB22: 0 | AC22: 0 | AD22: 7.2588e-06 | AE22: 2.202e-06 | AF22: 0 | AG22: 0 | AH22: 0 | AI22: 0 | AJ22: 2.685e-06
C23: MARGEN NETO INTERESES | D23: 0.46239037 | E23: 0.36500852 | F23: 0.57394494 | G23: 0.49785709 | H23: 0.49855959 | I23: 0.40532989 | J23: 0.50303795 | K23: 0.55535764 | L23: 0.34082146 | M23: 0.58468771 | N23: 0.48452805 | O23: 0.59113509 | P23: 0.54163691 | Q23: 0.56434387 | R23: 0.46087016 | S23: 0.50439487 | T23: 0.38292509 | U23: 0.72525449 | V23: 0.74699578 | W23: 0.62551036 | X23: 0.26399934 | Y23: 0.38215334 | Z23: 0.22347322 | AA23: 0.45265116 | AB23: 0.49694795 | AC23: 0.66659316 | AD23: 0.49874144 | AE23: 0.48630739 | AF23: 0.49135123 | AG23: 0.39178021 | AH23: 0 | AI23: 0.51635126 | AJ23: 0.49787153
B25: 52 | C25: COMISIONES GANADAS | D25: 0.076239232 | E25: 0.062204672 | F25: 0.016069571 | G25: 0.045503807 | H25: 0.041257662 | I25: 0.045450506 | J25: 0.089759212 | K25: 0.067087206 | L25: 0.120075 | M25: 0.038873424 | N25: 0.071207395 | O25: 0.019089092 | P25: 0.020116459 | Q25: 0.024006279 | R25: 0.073566399 | S25: 0.0015125001 | T25: 0.010953067 | U25: 0.0027995783 | V25: 0 | W25: 0 | X25: 0 | Y25: 0 | Z25: 0.0097295016 | AA25: 0 | AB25: 0.0021804396 | AC25: 0 | AD25: 0.002428899 | AE25: 0.05037216 | AF25: 0.070810487 | AG25: 0.10322118 | AH25: 0 | AI25: 0 | AJ25: 0.04252383
B26: 5201 | C26: Cartera de créditos | D26: 8.38118e-05 | E26: 0 | F26: 0 | G26: 0 | H26: 1.52831e-05 | I26: 0 | J26: 0 | K26: 0 | L26: 0 | M26: 2.48731e-05 | N26: 0 | O26: 0 | P26: 0 | Q26: 0 | R26: 1.605e-06 | S26: 0 | T26: 0 | U26: 0 | V26: 0 | W26: 0 | X26: 0 | Y26: 0 | Z26: 0 | AA26: 0 | AB26: 0 | AC26: 0 | AD26: 0 | AE26: 1.02855e-05 | AF26: 0 | AG26: 4.8857e-06 | AH26: 0 | AI26: 0 | AJ26: 1.19049e-05
B27: 5202 | C27: Deudores por aceptación | D27: 0 | E27: 0 | F27: 0 | G27: 0 | H27: 0 | I27: 0 | J27: 9.65504e-05 | K27: 8.66077e-05 | L27: 0 | M27: 0 | N27: 0 | O27: 0 | P27: 0.0011692217 | Q27: 0 | R27: 7.13055e-05 | S27: 0 | T27: 0 | U27: 0 | V27: 0 | W27: 0 | X27: 0 | Y27: 0 | Z27: 0 | AA27: 0 | AB27: 0 | AC27: 0 | AD27: 0 | AE27: 2.31926e-05 | AF27: 8.3431e-06 | AG27: 0 | AH27: 0 | AI27: 0 | AJ27: 2.76376e-05
B28: 5203 | C28: Avales | D28: 0 | E28: 2.09909e-05 | F28: 0.0015087557 | G28: 0.000719717 | H28: 0.000801333 | I28: 0.0005282667 | J28: 0.0043800471 | K28: 0 | L28: 0 | M28: 0.0003933752 | N28: 0.0018040447 | O28: 0.0011650867 | P28: 0.0010776824 | Q28: 0 | R28: 0.0012986047 | S28: 0 | T28: 0.001365694 | U28: 0 | V28: 0 | W28: 0 | X28: 0 | Y28: 0 | Z28: 0 | AA28: 0 | AB28: 0 | AC28: 0 | AD28: 0.0001602248 | AE28: 0.0009400552 | AF28: 0.0016302568 | AG28: 7.7268e-05 | AH28: 0 | AI28: 0 | AJ28: 0.0010107458
B29: 5204 | C29: Fianzas | D29: 0.0068515576 | E29: 0.0043867362 | F29: 0.0050998929 | G29: 0.0072651568 | H29: 0.0056272423 | I29: 0.0018760716 | J29: 0.009794242 | K29: 0.062577528 | L29: 0 | M29: 0.0016501835 | N29: 0.0076611168 | O29: 0 | P29: 0.0045813798 | Q29: 4.11505e-05 | R29: 0.0048508085 | S29: 0.0006850766 | T29: 0.0013852366 | U29: 0.0027995783 | V29: 0 | W29: 0 | X29: 0 | Y29: 0 | Z29: 0 | AA29: 0 | AB29: 0.0010010275 | AC29: 0 | AD29: 0.0006057096 | AE29: 0.0051944066 | AF29: 0.012951344 | AG29: 0.0003241344 | AH29: 0 | AI29: 0 | AJ29: 0.0052950378
B30: 5205 | C30: Cartas de Crédito | D30: 0.0046536798 | E30: 0.0010646191 | F30: 0.0008004833 | G30: 0.0045922792 | H30: 0.0021759073 | I30: 0.0007121877 | J30: 0.0074910108 | K30: 0.0002896029 | L30: 0 | M30: 0.0001813717 | N30: 0.012525418 | O30: 0 | P30: 0.0014669752 | Q30: 0 | R30: 0.0037305633 | S30: 0.000771301 | T30: 0 | U30: 0 | V30: 0 | W30: 0 | X30: 0 | Y30: 0 | Z30: 0 | AA30: 0 | AB30: 0 | AC30: 0 | AD30: 0.0002053805 | AE30: 0.0026108185 | AF30: 0.011346713 | AG30: 3.56256e-05 | AH30: 0 | AI30: 0 | AJ30: 0.0023058264
B31: 5290 | C31: Otras | D31: 0.064650183 | E31: 0.056732325 | F31: 0.0086604388 | G31: 0.032926654 | H31: 0.032637896 | I31: 0.04233398 | J31: 0.067997362 | K31: 0.0041334673 | L31: 0.120075 | M31: 0.036623621 | N31: 0.049216815 | O31: 0.017924005 | P31: 0.0118212 | Q31: 0.023965128 | R31: 0.063613511 | S31: 5.61225e-05 | T31: 0.0082021367 | U31: 0 | V31: 0 | W31: 0 | X31: 0 | Y31: 0 | Z31: 0.0097295016 | AA31: 0 | AB31: 0.0011794121 | AC31: 0 | AD31: 0.001457584 | AE31: 0.041593402 | AF31: 0.044873829 | AG31: 0.10277927 | AH31: 0 | AI31: 0 | AJ31: 0.033872677
B32: 54 | C32: INGRESOS POR SERVICIOS | D32: 0.19426455 | E32: 0.15150445 | F32: 0.11703739 | G32: 0.1386824 | H32: 0.14168421 | I32: 0.094585336 | J32: 0.11465235 | K32: 0.050675188 | L32: 0.21954286 | M32: 0.071432341 | N32: 0.095099288 | O32: 0.059761357 | P32: 0.075149191 | Q32: 0.12517088 | R32: 0.12900278 | S32: 0.018729898 | T32: 0.069336043 | U32: 0.12116459 | V32: 0.046105913 | W32: 0.056126629 | X32: 0.011189895 | Y32: 0.0004277411 | Z32: 0.4886949 | AA32: 0.0061850625 | AB32: 0.030074049 | AC32: 0.02512189 | AD32: 0.043650459 | AE32: 0.13403964 | AF32: 0.09081981 | AG32: 0.18914485 | AH32: 0 | AI32: 0.011945802 | AJ32: 0.1316634
B33: 5401 | C33: Servicios fiduciarios | D33: 0 | E33: 0 | F33: 0 | G33: 0 | H33: 0 | I33: 0 | J33: 0 | K33: 0 | L33: 0 | M33: 0 | N33: 0 | O33: 0 | P33: 0 | Q33: 0 | R33: 0 | S33: 0 | T33: 0 | U33: 0 | V33: 0 | W33: 0 | X33: 0 | Y33: 0 | Z33: 0 | AA33: 0 | AB33: 0 | AC33: 0 | AD33: 0 | AE33: 0 | AF33: 0 | AG33: 0 | AH33: 0 | AI33: 0 | AJ33: 0
B34: 5402 | C34: Servicios especiales | D34: 0 | E34: 0 | F34: 0 | G34: 0 | H34: 0 | I34: 0 | J34: 0 | K34: 0 | L34: 0 | M34: 0 | N34: 0 | O34: 0 | P34: 0 | Q34: 0 | R34: 0 | S34: 0 | T34: 0 | U34: 0 | V34: 0 | W34: 0 | X34: 0 | Y34: 0 | Z34: 0 | AA34: 0 | AB34: 0 | AC34: 0 | AD34: 0 | AE34: 0 | AF34: 0 | AG34: 0 | AH34: 0 | AI34: 0 | AJ34: 0
B35: 5404 | C35: Manejo y cobranzas | D35: 0.0037885273 | E35: 0 | F35: 0 | G35: 0.0002494934 | H35: 0.0007315633 | I35: 0 | J35: 0.0002938083 | K35: 0 | L35: 0 | M35: 0 | N35: 0 | O35: 0 | P35: 0 | Q35: 0 | R35: 5.32534e-05 | S35: 0 | T35: 0 | U35: 0.023882284 | V35: 0 | W35: 0 | X35: 0 | Y35: 0 | Z35: 0 | AA35: 0.0026170903 | AB35: 0 | AC35: 0 | AD35: 0.0009687582 | AE35: 0.000519455 | AF35: 0 | AG35: 0 | AH35: 0 | AI35: 0.0009555909 | AJ35: 0.0006218203
B36: 5405 | C36: Garantías crediticias | D36: 0 | E36: 0 | F36: 0 | G36: 0 | H36: 0 | I36: 0 | J36: 0 | K36: 0 | L36: 0 | M36: 0 | N36: 0 | O36: 0 | P36: 0 | Q36: 0 | R36: 0 | S36: 0 | T36: 0 | U36: 0 | V36: 0 | W36: 0 | X36: 0 | Y36: 0 | Z36: 0 | AA36: 0 | AB36: 0 | AC36: 0 | AD36: 0 | AE36: 0 | AF36: 0 | AG36: 0 | AH36: 0 | AI36: 0 | AJ36: 0
... B59: 4390 | C59: Otras | D59: 0 | E59: 0 | F59: 0 | G59: 0 | H59: 0 | I59: 0 | J59: 0 | K59: 0 | L59: 0 | M59: 0 | N59: 0 | O59: 0 | P59: 0 | Q59: 0 | R59: 0 | S59: 0 | T59: 0 | U59: 0 | V59: 0 | W59: 0 | X59: 0 | Y59: 0 | Z59: 0 | AA59: 0 | AB59: 0 | AC59: 0 | AD59: 0 | AE59: 0 | AF59: 0 | AG59: 0 | AH59: 0 | AI59: 0 | AJ59: 0
C60: MARGEN BRUTO FINANCIERO | D60: 0.69828892 | E60: 0.53110546 | F60: 0.70764563 | G60: 0.69370674 | H60: 0.66764923 | I60: 0.50063896 | J60: 0.70928753 | K60: 0.66724963 | L60: 0.72352707 | M60: 0.69319042 | N60: 0.65824989 | O60: 0.65694543 | P60: 0.62611093 | Q60: 0.69074449 | R60: 0.6673118 | S60: 0.50231091 | T60: 0.44946752 | U60: 0.79751004 | V60: 0.788399 | W60: 0.68080279 | X60: 0.26530394 | Y60: 0.38964684 | Z60: 0.69588637 | AA60: 0.45818869 | AB60: 0.55276683 | AC60: 0.69810475 | AD60: 0.53995199 | AE60: 0.66295458 | AF60: 0.65911685 | AG60: 0.71805662 | AH60: 0 | AI60: 0.53228865 | AJ60: 0.65765254
B62: 44 | C62: PROVISIONES | D62: 0.14253932 | E62: 0.20147855 | F62: 0.27748929 | G62: 0.14748111 | H62: 0.21615426 | I62: 0.1508143 | J62: 0.091549648 | K62: 0.031587827 | L62: 0.26012907 | M62: 0.17639245 | N62: 0.069530586 | O62: 0.16959261 | P62: 0.1017697 | Q62: 0.11213972 | R62: 0.14916047 | S62: 0.18588365 | T62: 0.12441495 | U62: 0.058375594 | V62: 0.0055799253 | W62: 0.029314714 | X62: 0.11756549 | Y62: 0.01695095 | Z62: 0.070907785 | AA62: 0.2633847 | AB62: 0.25705207 | AC62: 0.1050704 | AD62: 0.1567637 | AE62: 0.19223171 | AF62: 0.06587547 | AG62: 0.24176496 | AH62: 0 | AI62: 0.1405324 | AJ62: 0.19612553
B63: 4401 | C63: Inversiones | D63: 0 | E63: 1.11e-08 | F63: 0.0023019491 | G63: 0 | H63: 0.0010368508 | I63: 0.0051175827 | J63: 0 | K63: 0 | L63: 0.0035640483 | M63: 0 | N63: 0.0013272161 | O63: 0 | P63: 0.0026064873 | Q63: 0 | R63: 0.0019594648 | S63: 0 | T63: 0 | U63: 0 | V63: 0 | W63: 0 | X63: 0 | Y63: 0 | Z63: 0 | AA63: 0 | AB63: 0.010809418 | AC63: 0 | AD63: 0.0019241182 | AE63: 0.0013687938 | AF63: 0.0011993622 | AG63: 0.0028371556 | AH63: 0 | AI63: 0 | AJ63: 0.0012070886
B64: 4402 | C64: CARTERA DE CRÉDITOS | D64: 0.13454712 | E64: 0.18148141 | F64: 0.2350994 | G64: 0.12517715 | H64: 0.18788352 | I64: 0.11730465 | J64: 0.08309769 | K64: 0 | L64: 0.25332538 | M64: 0.16929634 | N64: 0.054847898 | O64: 0.16898424 | P64: 0.096229585 | Q64: 0.10796252 | R64: 0.13716775 | S64: 0.18203534 | T64: 0.081611827 | U64: 0.029709343 | V64: 0 | W64: 0.028306362 | X64: 0.10444138 | Y64: 0.0098143182 | Z64: 0.070907785 | AA64: 0.21962861 | AB64: 0.22533175 | AC64: 0.099119047 | AD64: 0.13822068 | AE64: 0.16960477 | AF64: 0.049564271 | AG64: 0.23491304 | AH64: 0 | AI64: 0.12047667 | AJ64: 0.17092622
B65: 440210 | C65: CRÉDITO PRODUCTIVO | D65: 0.0082769393 | E65: 0.077231562 | F65: 0.079999148 | G65: 0.038782434 | H65: 0.059628463 | I65: 0 | J65: 0.018499525 | K65: 0 | L65: 0.0026839427 | M65: 0 | N65: 0.019752753 | O65: 0.047874062 | P65: 0.021515649 | Q65: 6.2291e-06 | R65: 0.010325077 | S65: 0.14173235 | T65: 0.023750998 | U65: 0.011181348 | V65: 0 | W65: 0.0059322397 | X65: 0.028905224 | Y65: 0 | Z65: 0.036194919 | AA65: 0 | AB65: 0.0047186638 | AC65: 0 | AD65: 0.043665018 | AE65: 0.043019059 | AF65: 0.017849923 | AG65: 0.0021365488 | AH65: 0 | AI65: 0 | AJ65: 0.050802915
B66: 440220 | C66: CRÉDITO DE CONSUMO | D66: 0.096192239 | E66: 0.088119379 | F66: 0.061895287 | G66: 0.082786185 | H66: 0.076909065 | I66: 0.11414485 | J66: 0.062764709 | K66: 0 | L66: 0.25064143 | M66: 0.16929634 | N66: 0.033567246 | O66: 0.105266 | P66: 0.06498177 | Q66: 0.042441596 | R66: 0.11934428 | S66: 0.0005272811 | T66: 0.056195311 | U66: 0.0089319131 | V66: 0 | W66: 0.0041620319 | X66: 0.075520137 | Y66: 0 | Z66: 0.028981274 | AA66: 0 | AB66: 0.059407359 | AC66: 3.6232e-06 | AD66: 0.020195237 | AE66: 0.088675113 | AF66: 0.030333634 | AG66: 0.23277649 | AH66: 0 | AI66: 1.3815e-06 | AJ66: 0.075462392
B67: 440230 | C67: CRÉDITO INMOBILIARIO | D67: 0.0038386903 | E67: 0.0057026917 | F67: 0.021124433 | G67: 0.0021519764 | H67: 0.011729525 | I67: 0.0021544119 | J67: 0.0018137449 | K67: 0 | L67: 0 | M67: 0 | N67: 0.0013906894 | O67: 0.004266605 | P67: 0.0017913838 | Q67: 3.07549e-05 | R67: 0.0011052007 | S67: 0.0027610328 | T67: 0.0011354157 | U67: 1.2348e-06 | V67: 0 | W67: 1.07e-05 | X67: 0 | Y67: 0 | Z67: 0.0045904126 | AA67: 0 | AB67: 0.0068829348 | AC67: 0 | AD67: 0.002221877 | AE67: 0.007932528 | AF67: 0.001256721 | AG67: 0 | AH67: 0 | AI67: 0 | AJ67: 0.0095757154
B68: 440235 | C68: CRÉDITO DE VIVIENDA DE INTERÉS SOCIAL Y PÚBLICO | D68: 0 | E68: 0.0062372703 | F68: 0 | G68: 0 | H68: 0.0012724337 | I68: 0 | J68: 0 | K68: 0 | L68: 0 | M68: 0 | N68: 1.9925e-06 | O68: 0 | P68: 0 | Q68: 0 | R68: 3.493e-07 | S68: 0 | T68: 0 | U68: 0 | V68: 0 | W68: 0 | X68: 0 | Y68: 0 | Z68: 0 | AA68: 0 | AB68: 0 | AC68: 0 | AD68: 0 | AE68: 0.000812994 | AF68: 1.8005e-06 | AG68: 0 | AH68: 0 | AI68: 0 | AJ68: 0.000991173
B69: 440240 | C69: MICROCRÉDITO | D69: 0.026195709 | E69: 0.0013148187 | F69: 0.071766719 | G69: 0.0014437708 | H69: 0.037606001 | I69: 0.0010053863 | J69: 0 | K69: 0 | L69: 0 | M69: 0 | N69: 0.0001352175 | O69: 0.011565329 | P69: 0.0077355865 | Q69: 0.065483944 | R69: 0.0063796373 | S69: 0.036974871 | T69: 0.0005301017 | U69: 0.0095948471 | V69: 0 | W69: 0.018201391 | X69: 1.60231e-05 | Y69: 0.0098143182 | Z69: 0.0011411784 | AA69: 0.21962861 | AB69: 0.15432279 | AC69: 0.099115423 | AD69: 0.072127949 | AE69: 0.028688917 | AF69: 0.0001221917 | AG69: 0 | AH69: 0 | AI69: 0.12047529 | AJ69: 0.033513424
B70: 440245 | C70: CRÉDITO EDUCATIVO | D70: 4.35463e-05 | E70: 0.0028756901 | F70: 0.0003138099 | G70: 1.27866e-05 | H70: 0.0007380295 | I70: 0 | J70: 1.97116e-05 | K70: 0 | L70: 0 | M70: 0 | N70: 0 | O70: 1.22522e-05 | P70: 0.0002051962 | Q70: 0 | R70: 1.3204e-05 | S70: 3.98045e-05 | T70: 0 | U70: 0 | V70: 0 | W70: 0 | X70: 0 | Y70: 0 | Z70: 0 | AA70: 0 | AB70: 0 | AC70: 0 | AD70: 1.05991e-05 | AE70: 0.0004761573 | AF70: 0 | AG70: 0 | AH70: 0 | AI70: 0 | AJ70: 0.0005805951
B71: 440250 | C71: CRÉDITO DE INVERSIÓN PÚBLICA | D71: 0 | E71: 0 | F71: 0 | G71: 0 | H71: 0 | I71: 0 | J71: 0 | K71: 0 | L71: 0 | M71: 0 | N71: 0 | O71: 0 | P71: 0 | Q71: 0 | R71: 0 | S71: 0 | T71: 0 | U71: 0 | V71: 0 | W71: 0 | X71: 0 | Y71: 0 | Z71: 0 | AA71: 0 | AB71: 0 | AC71: 0 | AD71: 0 | AE71: 0 | AF71: 0 | AG71: 0 | AH71: 0 | AI71: 0 | AJ71: 0
B72: 4403 | C72: Cuentas por cobrar | D72: 0.0064602605 | E72: 0.014882119 | F72: 0.019209896 | G72: 0.020215133 | H72: 0.016166181 | I72: 0.026508109 | J72: 0.0003978932 | K72: 0.012483526 | L72: 0.0024158768 | M72: 0.0068411709 | N72: 0.0071213286 | O72: 0 | P72: 0.0023529425 | Q72: 0.0040155834 | R72: 0.0065791127 | S72: 0.0025753032 | T72: 0.038857149 | U72: 0.001117107 | V72: 0.0024500726 | W72: 0.0009493395 | X72: 0.012766673 | Y72: 0.0071327069 | Z72: 0 | AA72: 0.043756086 | AB72: 0.020772175 | AC72: 0.0040301497 | AD72: 0.014695618 | AE72: 0.012995125 | AF72: 0.0076378818 | AG72: 0.0032853648 | AH72: 0 | AI72: 0.019322177 | AJ72: 0.014595784
B73: 4404 | C73: Bienes realizables, adjudicados por pago y de arrendamiento mercantil | D73: 0 | E73: 1.27556e-05 | F73: 0 | G73: 0.0001799359 | H73: 3.19718e-05 | I73: 0 | J73: 0 | K73: 0 | L73: 0 | M73: 0.0002534095 | N73: 0 | O73: 0.000608367 | P73: 0 | Q73: 0 | R73: 3.98163e-05 | S73: 0 | T73: 0 | U73: 0.027184952 | V73: 0 | W73: 0 | X73: 0.0003574337 | Y73: 0 | Z73: 0 | AA73: 0 | AB73: 0 | AC73: 0 | AD73: 0.0008093186 | AE73: 6.24335e-05 | AF73: 0 | AG73: 4.97755e-05 | AH73: 0 | AI73: 0 | AJ73: 6.96421e-05
... B76: 4407 | C76: Operaciones interbancarias y de reporto | D76: 0 | E76: 0 | F76: 0 | G76: 0 | H76: 0 | I76: 0 | J76: 0 | K76: 0 | L76: 0 | M76: 0 | N76: 0 | O76: 0 | P76: 0 | Q76: 0 | R76: 0 | S76: 0 | T76: 0 | U76: 0 | V76: 0 | W76: 0 | X76: 0 | Y76: 0 | Z76: 0 | AA76: 0 | AB76: 0 | AC76: 0 | AD76: 0 | AE76: 0 | AF76: 0 | AG76: 0 | AH76: 0 | AI76: 0 | AJ76: 0
C77: MARGEN NETO FINANCIERO | D77: 0.55574961 | E77: 0.3296269 | F77: 0.43015634 | G77: 0.54622563 | H77: 0.45149497 | I77: 0.34982466 | J77: 0.61773788 | K77: 0.6356618 | L77: 0.463398 | M77: 0.51679798 | N77: 0.5887193 | O77: 0.48735282 | P77: 0.52434123 | Q77: 0.57860477 | R77: 0.51815134 | S77: 0.31642726 | T77: 0.32505257 | U77: 0.73913444 | V77: 0.78281907 | W77: 0.65148807 | X77: 0.14773845 | Y77: 0.37269589 | Z77: 0.62497859 | AA77: 0.194804 | AB77: 0.29571476 | AC77: 0.59303435 | AD77: 0.3831883 | AE77: 0.47072287 | AF77: 0.59324138 | AG77: 0.47629166 | AH77: 0 | AI77: 0.39175626 | AJ77: 0.46152701
B79: 45 | C79: GASTOS DE OPERACIÓN | D79: 0.38290784 | E79: 0.30244854 | F79: 0.39888757 | G79: 0.42554779 | H79: 0.38065117 | I79: 0.36153247 | J79: 0.41739938 | K79: 0.71681053 | L79: 0.40070119 | M79: 0.40305414 | N79: 0.36593792 | O79: 0.39311314 | P79: 0.44941087 | Q79: 0.47027307 | R79: 0.40615238 | S79: 0.42423227 | T79: 0.36667575 | U79: 0.66175969 | V79: 0.75030725 | W79: 0.62755172 | X79: 0.7278046 | Y79: 0.44836965 | Z79: 0.82309735 | AA79: 0.49863664 | AB79: 0.33793858 | AC79: 0.43916235 | AD79: 0.45707551 | AE79: 0.39168958 | AF79: 0.39973831 | AG79: 0.40379526 | AH79: 0 | AI79: 0.46321315 | AJ79: 0.38862716
B80: 4501 | C80: Gastos de personal | D80: 0.14175232 | E80: 0.082531599 | F80: 0.089838627 | G80: 0.11278918 | H80: 0.1015605 | I80: 0.11017178 | J80: 0.12855413 | K80: 0.24683296 | L80: 0.072168971 | M80: 0.13581714 | N80: 0.12103759 | O80: 0.15548756 | P80: 0.19011879 | Q80: 0.26299462 | R80: 0.12767033 | S80: 0.13499742 | T80: 0.128353 | U80: 0.213505 | V80: 0.36577195 | W80: 0.21216032 | X80: 0.34826651 | Y80: 0.23992641 | Z80: 0.3224624 | AA80: 0.24014233 | AB80: 0.17614607 | AC80: 0.2564192 | AD80: 0.19417165 | AE80: 0.11337804 | AF80: 0.13315575 | AG80: 0.086881245 | AH80: 0 | AI80: 0.24629394 | AJ80: 0.11369947
B81: 4502 | C81: Honorarios | D81: 0.0048039078 | E81: 0.0072653779 | F81: 0.054838334 | G81: 0.010303473 | H81: 0.028740319 | I81: 0.032712899 | J81: 0.0045092797 | K81: 0.007114875 | L81: 0.0030845662 | M81: 0.014314853 | N81: 0.0011293471 | O81: 0.0054446227 | P81: 0.0060904149 | Q81: 0.011676187 | R81: 0.0086653914 | S81: 0.010663071 | T81: 0.023547417 | U81: 0.062855813 | V81: 0.056208474 | W81: 0.037531855 | X81: 0.047084877 | Y81: 0.010873248 | Z81: 0.034154786 | AA81: 0.029239332 | AB81: 0.008740252 | AC81: 0.025732423 | AD81: 0.020929964 | AE81: 0.021930393 | AF81: 0.0017059471 | AG81: 0.0056903816 | AH81: 0 | AI81: 0.023245139 | AJ81: 0.025586411
B82: 4503 | C82: Servicios varios | D82: 0.10954471 | E82: 0.057169435 | F82: 0.10888702 | G82: 0.16005612 | H82: 0.10680825 | I82: 0.096057184 | J82: 0.090018677 | K82: 0.22630906 | L82: 0.22455571 | M82: 0.094764231 | N82: 0.053180696 | O82: 0.080488318 | P82: 0.10879836 | Q82: 0.10245765 | R82: 0.12390057 | S82: 0.11916613 | T82: 0.075287569 | U82: 0.10151191 | V82: 0.12506099 | W82: 0.068531242 | X82: 0.10183314 | Y82: 0.087545208 | Z82: 0.34163226 | AA82: 0.077362828 | AB82: 0.072382725 | AC82: 0.082166348 | AD82: 0.097673774 | AE82: 0.11203967 | AF82: 0.06985856 | AG82: 0.19831263 | AH82: 0 | AI82: 0.08177631 | AJ82: 0.1044109
B83: 4504 | C83: Impuestos, contribuciones y multas | D83: 0.065397279 | E83: 0.080136358 | F83: 0.064861382 | G83: 0.080292855 | H83: 0.070594036 | I83: 0.07855022 | J83: 0.11302496 | K83: 0.21354413 | L83: 0.067854323 | M83: 0.075830379 | N83: 0.093883786 | O83: 0.10325312 | P83: 0.092939174 | Q83: 0.05200235 | R83: 0.08643011 | S83: 0.084834846 | T83: 0.073198725 | U83: 0.13261973 | V83: 0.081436995 | W83: 0.15066467 | X83: 0.075640562 | Y83: 0.049375377 | Z83: 0.092802443 | AA83: 0.038253954 | AB83: 0.046877307 | AC83: 0.039150635 | AD83: 0.070118048 | AE83: 0.075727731 | AF83: 0.10541095 | AG83: 0.069523259 | AH83: 0 | AI83: 0.04141587 | AJ83: 0.074667749
B84: 4505 | C84: Depreciaciones | D84: 0.015849336 | E84: 0.018235528 | F84: 0.017732266 | G84: 0.012093053 | H84: 0.016571135 | I84: 0.015490274 | J84: 0.013900891 | K84: 0.0055980113 | L84: 0.0045650937 | M84: 0.010291481 | N84: 0.014749771 | O84: 0.014552285 | P84: 0.014123144 | Q84: 0.009796113 | R84: 0.011125431 | S84: 0.012271155 | T84: 0.017291026 | U84: 0.050793602 | V84: 0.017774161 | W84: 0.028408212 | X84: 0.047508896 | Y84: 0.018146805 | Z84: 0.0059799349 | AA84: 0.0086542952 | AB84: 0.013412873 | AC84: 0.0090525022 | AD84: 0.015576451 | AE84: 0.014764171 | AF84: 0.01386816 | AG84: 0.0057893293 | AH84: 0 | AI84: 0.011213107 | AJ84: 0.01604543
B85: 4506 | C85: Amortizaciones | D85: 0.024223491 | E85: 0.032471152 | F85: 0.0095994152 | G85: 0.01872977 | H85: 0.01842235 | I85: 0.011134657 | J85: 0.010450482 | K85: 0.0020651969 | L85: 0.0008762341 | M85: 0.0252001 | N85: 0.010210075 | O85: 0.0042514607 | P85: 0.0149414 | Q85: 0.0062652043 | R85: 0.0084044943 | S85: 0.0045130974 | T85: 0.015407952 | U85: 0.027423202 | V85: 0.050031848 | W85: 0.036252669 | X85: 0.034564768 | Y85: 0.0039749648 | Z85: 0.011329903 | AA85: 0.035938656 | AB85: 0.0060191804 | AC85: 0.0074029889 | AD85: 0.013957508 | AE85: 0.01500367 | AF85: 0.0094254595 | AG85: 0.0060240585 | AH85: 0 | AI85: 0.016953127 | AJ85: 0.016579196
B86: 4507 | C86: Otros gastos | D86: 0.021336804 | E86: 0.024639084 | F86: 0.053130527 | G86: 0.031283344 | H86: 0.037954576 | I86: 0.017415464 | J86: 0.056940966 | K86: 0.015346292 | L86: 0.027596298 | M86: 0.04683595 | N86: 0.071746655 | O86: 0.02963577 | P86: 0.02239959 | Q86: 0.025080949 | R86: 0.039956056 | S86: 0.057786546 | T86: 0.033590059 | U86: 0.073050425 | V86: 0.054022834 | W86: 0.094002751 | X86: 0.07290585 | Y86: 0.038527638 | Z86: 0.014735623 | AA86: 0.069045252 | AB86: 0.014360175 | AC86: 0.019238252 | AD86: 0.044648116 | AE86: 0.038845899 | AF86: 0.066313475 | AG86: 0.031574356 | AH86: 0 | AI86: 0.042315653 | AJ86: 0.037638
C87: MARGEN DE INTERMEDIACIÓN | D87: 0.17284176 | E87: 0.027178368 | F87: 0.031268775 | G87: 0.12067785 | H87: 0.070843804 | I87: -0.011707815 | J87: 0.2003385 | K87: -0.081148727 | L87: 0.062696812 | M87: 0.11374384 | N87: 0.22278138 | O87: 0.094239685 | P87: 0.074930357 | Q87: 0.1083317 | R87: 0.11199895 | S87: -0.107805 | T87: -0.041623178 | U87: 0.077374751 | V87: 0.032511819 | W87: 0.023936349 | X87: -0.58006615 | Y87: -0.075673764 | Z87: -0.19811876 | AA87: -0.30383265 | AB87: -0.042223822 | AC87: 0.153872 | AD87: -0.073887217 | AE87: 0.07903329 | AF87: 0.19350308 | AG87: 0.072496396 | AH87: 0 | AI87: -0.071456888 | AJ87: 0.072899852
B89: 55 | C89: OTROS INGRESOS OPERACIONALES | D89: 0.0004387586 | E89: 0.021480406 | F89: 0.067829757 | G89: 0.030050959 | H89: 0.039919123 | I89: 0.014691457 | J89: 0.016051491 | K89: 0.016825112 | L89: 0.066019999 | M89: 0.0009915633 | N89: 0.0018286442 | O89: 0.005857521 | P89: 0.0004144281 | Q89: 0.038282821 | R89: 0.026240924 | S89: 0.011524928 | T89: 0.0013651726 | U89: 0 | V89: 0.039903068 | W89: 0 | X89: 0.030446992 | Y89: 0.10353994 | Z89: 0 | AA89: 0.14436482 | AB89: 0.0045768857 | AC89: 0 | AD89: 0.027404757 | AE89: 0.035020878 | AF89: 0.0032732893 | AG89: 0.053050291 | AH89: 0 | AI89: 0.078966818 | AJ89: 0.034582383
B90: 5501 | C90: Utilidades en acciones y participaciones | D90: 0.0004387586 | E90: 0.0010820002 | F90: 0.04393631 | G90: 0.0082765958 | H90: 0.021441549 | I90: 0.0028268244 | J90: 0.0012781097 | K90: 0.0076415562 | L90: 0.055506378 | M90: 0 | N90: 0.0017443431 | O90: 0.0027254857 | P90: 0 | Q90: 0 | R90: 0.015676015 | S90: 0 | T90: 0.0013651726 | U90: 0 | V90: 0 | W90: 0 | X90: 0 | Y90: 0 | Z90: 0 | AA90: 0 | AB90: 0 | AC90: 0 | AD90: 0.0001601636 | AE90: 0.018802175 | AF90: 0.0023124356 | AG90: 0.044185774 | AH90: 0 | AI90: 0 | AJ90: 0.01699127
B91: 5502 | C91: Utilidad en venta de bienes realizables y recuperados | D91: 0 | E91: 0 | F91: 0 | G91: 0 | H91: 0 | I91: 0 | J91: 0 | K91: 0 | L91: 0 | M91: 0 | N91: 0 | O91: 0 | P91: 0 | Q91: 0 | R91: 0 | S91: 0 | T91: 0 | U91: 0 | V91: 0 | W91: 0 | X91: 0 | Y91: 0 | Z91: 0 | AA91: 0 | AB91: 1.81967e-05 | AC91: 0 | AD91: 3.2391e-06 | AE91: 1.163e-07 | AF91: 0 | AG91: 0 | AH91: 0 | AI91: 0 | AJ91: 1.418e-07
B92: 5505 | C92: Ingresos por subsidios realizados | D92: 0 | E92: 0 | F92: 0 | G92: 0 | H92: 0 | I92: 0 | J92: 0 | K92: 0 | L92: 0 | M92: 0 | N92: 0 | O92: 0 | P92: 0 | Q92: 0 | R92: 0 | S92: 0 | T92: 0 | U92: 0 | V92: 0 | W92: 0 | X92: 0 | Y92: 0 | Z92: 0 | AA92: 0 | AB92: 0 | AC92: 0 | AD92: 0 | AE92: 0 | AF92: 0 | AG92: 0 | AH92: 0 | AI92: 0 | AJ92: 0
B93: 5506 | C93: Ingresos por subsidios recuperados | D93: 0 | E93: 0 | F93: 0 | G93: 0 | H93: 0 | I93: 0 | J93: 0 | K93: 0 | L93: 0 | M93: 0 | N93: 0 | O93: 0 | P93: 0 | Q93: 0 | R93: 0 | S93: 0 | T93: 0 | U93: 0 | V93: 0 | W93: 0 | X93: 0 | Y93: 0 | Z93: 0 | AA93: 0 | AB93: 0 | AC93: 0 | AD93: 0 | AE93: 0 | AF93: 0 | AG93: 0 | AH93: 0 | AI93: 0 | AJ93: 0
B94: 5507 | C94: Ingresos por demora en transferencias | D94: 0 | E94: 0 | F94: 0 | G94: 0 | H94: 0 | I94: 0 | J94: 0 | K94: 0 | L94: 0 | M94: 0 | N94: 0 | O94: 0 | P94: 0 | Q94: 0 | R94: 0 | S94: 0 | T94: 0 | U94: 0 | V94: 0 | W94: 0 | X94: 0 | Y94: 0 | Z94: 0 | AA94: 0 | AB94: 0 | AC94: 0 | AD94: 0 | AE94: 0 | AF94: 0 | AG94: 0 | AH94: 0 | AI94: 0 | AJ94: 0
B95: 5590 | C95: Otros | D95: 0 | E95: 0.020398405 | F95: 0.023893447 | G95: 0.021774363 | H95: 0.018477574 | I95: 0.011864633 | J95: 0.014773382 | K95: 0.0091835553 | L95: 0.010513621 | M95: 0.0009915633 | N95: 8.43011e-05 | O95: 0.0031320353 | P95: 0.0004144281 | Q95: 0.038282821 | R95: 0.010564909 | S95: 0.011524928 | T95: 0 | U95: 0 | V95: 0.039903068 | W95: 0 | X95: 0.030446992 | Y95: 0.10353994 | Z95: 0 | AA95: 0.14436482 | AB95: 0.004558689 | AC95: 0 | AD95: 0.027241354 | AE95: 0.016218587 | AF95: 0.0009608537 | AG95: 0.0088645165 | AH95: 0 | AI95: 0.078966818 | AJ95: 0.017590972
B96: 46 | C96: OTRAS PÉRDIDAS OPERACIONALES | D96: 0.0004721388 | E96: 0.0026664819 | F96: 0.039538994 | G96: 0.0045519147 | H96: 0.019182278 | I96: 4.738e-07 | J96: 0.0004838578 | K96: 0.0055786817 | L96: 0.036081533 | M96: 0.0043851568 | N96: 0.0013563717 | O96: 0.0021605339 | P96: 0 | Q96: 0.070046642 | R96: 0.016041824 | S96: 0 | T96: 0.0051603595 | U96: 0 | V96: 0.0007833961 | W96: 0 | X96: 0.0048960586 | Y96: 0 | Z96: 0.0010507184 | AA96: 0.021914978 | AB96: 0.000311104 | AC96: 0 | AD96: 0.0030216518 | AE96: 0.017580586 | AF96: 0.0017631168 | AG96: 0.029589898 | AH96: 0 | AI96: 0.0080019231 | AJ96: 0.017348825
B97: 4601 | C97: Pérdida en acciones y participaciones | D97: 9.61938e-05 | E97: 7.74237e-05 | F97: 0.031677771 | G97: 0.0045290603 | H97: 0.015040945 | I97: 0 | J97: 0.0003958809 | K97: 0.0053572447 | L97: 0.036081533 | M97: 0 | N97: 0.0013563717 | O97: 0.0019208292 | P97: 0 | Q97: 0 | R97: 0.0099197002 | S97: 0 | T97: 0.000989714 | U97: 0 | V97: 0 | W97: 0 | X97: 0 | Y97: 0 | Z97: 0 | AA97: 0 | AB97: 0 | AC97: 0 | AD97: 0.0001161144 | AE97: 0.012839359 | AF97: 0.0017417852 | AG97: 0.028722653 | AH97: 0 | AI97: 0 | AJ97: 0.011779195
B98: 4602 | C98: Pérdida en venta de bienes realizables y recuperados | D98: 0.0003521908 | E98: 0.0014423196 | F98: 2.96677e-05 | G98: 2.28544e-05 | H98: 0.0003755558 | I98: 0 | J98: 0 | K98: 0 | L98: 0 | M98: 0.0032219494 | N98: 0 | O98: 0 | P98: 0 | Q98: 1.1362e-06 | R98: 0.0002080032 | S98: 0 | T98: 0 | U98: 0 | V98: 0.0007833961 | W98: 0 | X98: 0.0048960586 | Y98: 0 | Z98: 0.0010507184 | AA98: 0 | AB98: 0 | AC98: 0 | AD98: 0.0001480182 | AE98: 0.0003128886 | AF98: 0 | AG98: 0.0006387632 | AH98: 0 | AI98: 0 | AJ98: 0.0002982915
B99: 4690 | C99: Otras | D99: 2.37543e-05 | E99: 0.0011467386 | F99: 0.0078315559 | G99: 0 | H99: 0.0037657771 | I99: 4.738e-07 | J99: 8.79769e-05 | K99: 0.000221437 | L99: 0 | M99: 0.0011632073 | N99: 0 | O99: 0.0002397047 | P99: 0 | Q99: 0.070045505 | R99: 0.0059141205 | S99: 0 | T99: 0.0041706455 | U99: 0 | V99: 0 | W99: 0 | X99: 0 | Y99: 0 | Z99: 0 | AA99: 0.021914978 | AB99: 0.000311104 | AC99: 0 | AD99: 0.0027575192 | AE99: 0.0044283387 | AF99: 2.13315e-05 | AG99: 0.0002284809 | AH99: 0 | AI99: 0.0080019231 | AJ99: 0.0052713391
C100: MARGEN OPERACIONAL | D100: 0.17280838 | E100: 0.045992292 | F100: 0.059559538 | G100: 0.14617689 | H100: 0.091580649 | I100: 0.0029831686 | J100: 0.21590613 | K100: -0.069902297 | L100: 0.092635278 | M100: 0.11035024 | N100: 0.22325366 | O100: 0.097936672 | P100: 0.075344785 | Q100: 0.076567882 | R100: 0.12219805 | S100: -0.096280076 | T100: -0.045418365 | U100: 0.077374751 | V100: 0.071631491 | W100: 0.023936349 | X100: -0.55451522 | Y100: 0.027866173 | Z100: -0.19916948 | AA100: -0.18138281 | AB100: -0.03795804 | AC100: 0.153872 | AD100: -0.049504112 | AE100: 0.096473582 | AF100: 0.19501325 | AG100: 0.095956789 | AH100: 0 | AI100: -0.0004919939 | AJ100: 0.09013341
B102: 56 | C102: OTROS INGRESOS | D102: 0.03773926 | E102: 0.15096467 | F102: 0.07222157 | G102: 0.074094984 | H102: 0.082303461 | I102: 0.11382935 | J102: 0.013073364 | K102: 0.2284804 | L102: 0.083054902 | M102: 0.065714406 | N102: 0.027549282 | O102: 0.046783012 | P102: 0.058527739 | Q102: 0.030081548 | R102: 0.059430913 | S102: 0.12110172 | T102: 0.074659681 | U102: 0.014774914 | V102: 0.012643625 | W102: 0.10672183 | X102: 0.2003029 | Y102: 0.10170988 | Z102: 0.15052768 | AA102: 0.066502443 | AB102: 0.14019252 | AC102: 0.097152735 | AD102: 0.10565863 | AE102: 0.075702572 | AF102: 0.046905451 | AG102: 0.079118757 | AH102: 0 | AI102: 0.08711678 | AJ102: 0.077334881
B103: 5601 | C103: Utilidad en venta de bienes | D103: 0.0003427225 | E103: 0.0003507142 | F103: 0.0026210184 | G103: 0.0001007222 | H103: 0.0013310476 | I103: 0.0005395598 | J103: 4.71767e-05 | K103: 0 | L103: 3.069e-06 | M103: 0.000259882 | N103: 0.0009404184 | O103: 9.9683e-06 | P103: 0.0048927303 | Q103: 0.0004941041 | R103: 0.0005222589 | S103: 0.0001702199 | T103: 0 | U103: 0 | V103: 0 | W103: 0 | X103: 0.0046637236 | Y103: 0 | Z103: 0 | AA103: 6.94466e-05 | AB103: 0 | AC103: 3.28011e-05 | AD103: 0.0001522553 | AE103: 0.0010256599 | AF103: 0.0008498256 | AG103: 5.34899e-05 | AH103: 0 | AI103: 3.78644e-05 | AJ103: 0.0011778111
B104: 5602 | C104: Utilidad en venta de acciones y participaciones | D104: 0 | E104: 0 | F104: 0 | G104: 0.000285003 | H104: 4.65189e-05 | I104: 0 | J104: 0 | K104: 0 | L104: 0 | M104: 0 | N104: 0 | O104: 0 | P104: 0 | Q104: 0 | R104: 0 | S104: 0 | T104: 0 | U104: 0 | V104: 0 | W104: 0 | X104: 0 | Y104: 0 | Z104: 0 | AA104: 0 | AB104: 0 | AC104: 0 | AD104: 0 | AE104: 2.97181e-05 | AF104: 0 | AG104: 0 | AH104: 0 | AI104: 0 | AJ104: 3.62363e-05
B105: 5603 | C105: Arrendamientos | D105: 6.4522e-06 | E105: 0.0001526334 | F105: 0.0012212749 | G105: 0.0025765509 | H105: 0.0010029545 | I105: 0.0002922297 | J105: 0 | K105: 0 | L105: 3.40794e-05 | M105: 0 | N105: 0.0006902496 | O105: 7.38734e-05 | P105: 0 | Q105: 0 | R105: 0.0001715059 | S105: 0 | T105: 0.0066514272 | U105: 0 | V105: 0 | W105: 0.000401978 | X105: 0.0085538545 | Y105: 0 | Z105: 0 | AA105: 0 | AB105: 0 | AC105: 0 | AD105: 0.0009819838 | AE105: 0.0007317676 | AF105: 0.0006237562 | AG105: 2.71289e-05 | AH105: 0 | AI105: 0 | AJ105: 0.0008407443
B106: 5604 | C106: Recuperaciones de activos financieros | D106: 0.029753362 | E106: 0.13861228 | F106: 0.065303169 | G106: 0.060095949 | H106: 0.072926121 | I106: 0.11046804 | J106: 0.010508568 | K106: 0.10227683 | L106: 0.072308471 | M106: 0.026731719 | N106: 0.019083744 | O106: 0.038846774 | P106: 0.046564337 | Q106: 0.024592936 | R106: 0.048056693 | S106: 0.1200039 | T106: 0.021409578 | U106: 0.014774914 | V106: 0.012487933 | W106: 0.10335174 | X106: 0.17645856 | Y106: 0.10170988 | Z106: 0.15052768 | AA106: 0.031599576 | AB106: 0.12333124 | AC106: 0.038614961 | AD106: 0.085717005 | AE106: 0.065296429 | AF106: 0.02709793 | AG106: 0.062905799 | AH106: 0 | AI106: 0.052052111 | AJ106: 0.068707163
B107: 5690 | C107: Otros | D107: 0.0076367236 | E107: 0.01184905 | F107: 0.0030761075 | G107: 0.011036759 | H107: 0.0069968189 | I107: 0.0025295265 | J107: 0.002517619 | K107: 0.12620357 | L107: 0.010709282 | M107: 0.038722805 | N107: 0.0068348699 | O107: 0.0078523957 | P107: 0.0070706715 | Q107: 0.0049945074 | R107: 0.010680455 | S107: 0.000927597 | T107: 0.046598676 | U107: 0 | V107: 0.0001556924 | W107: 0.0029681182 | X107: 0.010626767 | Y107: 0 | Z107: 0 | AA107: 0.03483342 | AB107: 0.016861278 | AC107: 0.058504974 | AD107: 0.018807385 | AE107: 0.0086189976 | AF107: 0.018333938 | AG107: 0.01613234 | AH107: 0 | AI107: 0.035026804 | AJ107: 0.0065729261
B108: 47 | C108: OTROS GASTOS Y PÉRDIDAS | D108: 0.014452303 | E108: 0.034295154 | F108: 0.012264504 | G108: 0.0016508204 | H108: 0.01542542 | I108: 0.036204237 | J108: 0.001647124 | K108: 0.0033410208 | L108: 0.0066583564 | M108: 0.0054436832 | N108: 0.048392623 | O108: 0.0095543645 | P108: 0.016503296 | Q108: 0.0077672332 | R108: 0.017485744 | S108: 0.0057585886 | T108: 0.022910064 | U108: 0.050500089 | V108: 0.0061842024 | W108: 0.0011696436 | X108: 0 | Y108: 0.18592932 | Z108: 0.0003744379 | AA108: 0.0039155762 | AB108: 0.029242057 | AC108: 0.004100588 | AD108: 0.025002212 | AE108: 0.016439403 | AF108: 0.044052696 | AG108: 0.0064161969 | AH108: 0 | AI108: 0.05013858 | AJ108: 0.015212828
B109: 4701 | C109: Pérdida en venta de bienes | D109: 2.886e-06 | E109: 0 | F109: 1.88744e-05 | G109: 0.0003526285 | H109: 6.65846e-05 | I109: 0.001168402 | J109: 0 | K109: 0.0001995118 | L109: 9.396e-06 | M109: 0 | N109: 0.0002711505 | O109: 0 | P109: 0.01372565 | Q109: 1.6002e-06 | R109: 0.0008213688 | S109: 0.0007180655 | T109: 0.0040373821 | U109: 0 | V109: 0 | W109: 0 | X109: 0 | Y109: 0.0001356044 | Z109: 0 | AA109: 0 | AB109: 0 | AC109: 0 | AD109: 0.0006743841 | AE109: 0.0003339058 | AF109: 0.0002642494 | AG109: 7.4797e-06 | AH109: 0 | AI109: 3.43846e-05 | AJ109: 0.0003854212
B110: 4702 | C110: Pérdida en venta de acciones y participaciones | D110: 0 | E110: 0 | F110: 0 | G110: 0 | H110: 0 | I110: 0 | J110: 0 | K110: 0 | L110: 0 | M110: 0 | N110: 0 | O110: 0 | P110: 0 | Q110: 0 | R110: 0 | S110: 0 | T110: 0 | U110: 0 | V110: 0 | W110: 0 | X110: 0 | Y110: 0 | Z110: 0 | AA110: 0 | AB110: 0 | AC110: 0 | AD110: 0 | AE110: 0 | AF110: 0 | AG110: 0 | AH110: 0 | AI110: 0 | AJ110: 0
B111: 4703 | C111: INTERESES y comisiones devengados en ejercicios anteriores | D111: 0.0057297954 | E111: 0.011060886 | F111: 0.012245628 | G111: 0.0012981919 | H111: 0.0090289016 | I111: 0.017459997 | J111: 0.0014328495 | K111: 0.000672917 | L111: 0.0058865413 | M111: 0.003423902 | N111: 0.0011760721 | O111: 0.0094560106 | P111: 0.0012198667 | Q111: 0.007765633 | R111: 0.0056166008 | S111: 0.0048456711 | T111: 0.018872682 | U111: 0.050500089 | V111: 0.0013770772 | W111: 0.0010832425 | X111: 0 | Y111: 0.0056884558 | Z111: 0 | AA111: 0.0038106671 | AB111: 0.024976127 | AC111: 0.0034269477 | AD111: 0.01068246 | AE111: 0.0079783989 | AF111: 0.001127602 | AG111: 0.0053688737 | AH111: 0 | AI111: 0.0041404981 | AJ111: 0.0088919441
B112: 4790 | C112: Otros | D112: 0.0087196217 | E112: 0.023234267 | F112: 1.4e-09 | G112: 0 | H112: 0.0063299338 | I112: 0.017575838 | J112: 0.0002142746 | K112: 0.0024685919 | L112: 0.0007624192 | M112: 0.0020197812 | N112: 0.046945401 | O112: 9.83539e-05 | P112: 0.0015577787 | Q112: 0 | R112: 0.011047774 | S112: 0.000194852 | T112: 0 | U112: 0 | V112: 0.0048071252 | W112: 8.64011e-05 | X112: 0 | Y112: 0.18010526 | Z112: 0.0003744379 | AA112: 0.0001049091 | AB112: 0.0042659298 | AC112: 0.0006736403 | AD112: 0.013645368 | AE112: 0.0081270986 | AF112: 0.042660845 | AG112: 0.0010398435 | AH112: 0 | AI112: 0.045963697 | AJ112: 0.005935463
C113: GANANCIA O PERDIDA ANTES DE IMPUESTOS (MARGEN BENFICIO NETO) | D113: 0.19609534 | E113: 0.16266181 | F113: 0.1195166 | G113: 0.21862106 | H113: 0.15845869 | I113: 0.080608282 | J113: 0.22733237 | K113: 0.15523708 | L113: 0.16903182 | M113: 0.17062097 | N113: 0.20241031 | O113: 0.13516532 | P113: 0.11736923 | Q113: 0.098882196 | R113: 0.16414322 | S113: 0.019063057 | T113: 0.0063312521 | U113: 0.041649576 | V113: 0.078090914 | W113: 0.12948854 | X113: -0.35421232 | Y113: -0.05635327 | Z113: -0.049016242 | AA113: -0.11879594 | AB113: 0.072992423 | AC113: 0.24692414 | AD113: 0.031152306 | AE113: 0.15573675 | AF113: 0.19786601 | AG113: 0.16865935 | AH113: 0 | AI113: 0.036486206 | AJ113: 0.15225546
C115: IMPUESTOS Y PARTICIPACIÓN A EMPLEADOS | D115: 0.063206758 | E115: 0.025485021 | F115: 0.038069487 | G115: 0.095048352 | H115: 0.049386221 | I115: 0.035401112 | J115: 0.089578074 | K115: 0.050562352 | L115: 0.059349306 | M115: 0.060829243 | N115: 0.077165737 | O115: 0.054632241 | P115: 0.051800499 | Q115: 0.034626823 | R115: 0.062138991 | S115: 0.016579308 | T115: 0.002456526 | U115: 0.013223088 | V115: 0.0071000913 | W115: 0.046939592 | X115: 0 | Y115: 0 | Z115: 0 | AA115: 0 | AB115: 0.026459753 | AC115: 0.095316616 | AD115: 0.02289836 | AE115: 0.052583109 | AF115: 0.07460297 | AG115: 0.059246659 | AH115: 0 | AI115: 0.036344161 | AJ115: 0.050217353
C117: GANANCIA O (PÉRDIDA) DEL EJERCICIO | D117: 0.13288858 | E117: 0.13717679 | F117: 0.081447117 | G117: 0.1235727 | H117: 0.10907247 | I117: 0.04520717 | J117: 0.1377543 | K117: 0.10467473 | L117: 0.10968252 | M117: 0.10979172 | N117: 0.12524458 | O117: 0.080533079 | P117: 0.065568729 | Q117: 0.064255373 | R117: 0.10200423 | S117: 0.0024837482 | T117: 0.0038747261 | U117: 0.028426488 | V117: 0.070990823 | W117: 0.082548946 | X117: -0.35421232 | Y117: -0.05635327 | Z117: -0.049016242 | AA117: -0.11879594 | AB117: 0.046532669 | AC117: 0.15160753 | AD117: 0.0082539455 | AE117: 0.10315364 | AF117: 0.12326304 | AG117: 0.10941269 | AH117: 0 | AI117: 0.0001420444 | AJ117: 0.10203811

Sheet CONSCOND
B3: ESTADO DE SITUACIÓN
B4: SISTEMA DE BANCOS PRIVADOS
B5: CONSCOND
B6: 31/05/2022
B7: (en miles de dólares)
B9: CÓDIGO | C9: CUENTA | D9: BP GUAYAQUIL | E9: BP PACIFICO | F9: BP PICHINCHA | G9: BP PRODUBANCO | H9: BANCOS GRANDES | I9: BP AUSTRO | J9: BP BOLIVARIANO | K9: BP CITIBANK | L9: BP DINERS | M9: BP GENERAL RUMIÑAHUI | N9: BP INTERNACIONAL | O9: BP LOJA | P9: BP MACHALA | Q9: BP SOLIDARIO | R9: BANCOS MEDIANOS | S9: BP PROCREDIT | T9: BP AMAZONAS | U9: BP COMERCIAL DE MANABI | V9: BP LITORAL | W9: BP COOPNACIONAL | X9: BP CAPITAL | Y9: BP FINCA S.A. | Z9: BP DELBANK | AA9: BP D-MIRO S.A. | AB9: BP BANCO DESARROLLO DE LOS PUEBLOS S.A., CODESARROLLO | AC9: BP VISIONFUND ECUADOR S.A. | AD9: BANCOS PEQUEÑOS | AE9: BANCOS PRIVADOS | AF9: BANCOS PRIVADOS COMERCIALES | AG9: BANCOS PRIVADOS CONSUMO | AH9: BANCOS PRIVADOS VIVIENDA | AI9: BANCOS PRIVADOS MICROCRÉDITO | AJ9: BANCA MÚLTIPLE
C10: ACTIVO
B11: 11 | C11: FONDOS DISPONIBLES | D11: 792200.41 | E11: 1236038.6 | F11: 1488170.3 | G11: 987314.77 | H11: 4503724 | I11: 366159.71 | J11: 768019.82 | K11: 204523.83 | L11: 121830.17 | M11: 168221.88 | N11: 548137.48 | O11: 141836.42 | P11: 163203.33 | Q11: 74083.198 | R11: 2556015.8 | S11: 58397.463 | T11: 30121.58 | U11: 7352.3701 | V11: 2360.7643 | W11: 64574.45 | X11: 2383.9728 | Y11: 11518.839 | Z11: 7097.2385 | AA11: 6089.1321 | AB11: 23600.842 | AC11: 3852.1231 | AD11: 217348.78 | AE11: 7277088.6 | AF11: 752661.31 | AG11: 292412.82 | AH11: 0 | AI11: 21460.095 | AJ11: 6210554.4
B12: 12 | C12: OPERACIONES INTERBANCARIAS | D12: 0 | E12: 0 | F12: 0 | G12: 0 | H12: 0 | I12: 0 | J12: 0 | K12: 0 | L12: 0 | M12: 0 | N12: 0 | O12: 0 | P12: 0 | Q12: 0 | R12: 0 | S12: 0 | T12: 0 | U12: 0 | V12: 0 | W12: 0 | X12: 0 | Y12: 0 | Z12: 0 | AA12: 0 | AB12: 0 | AC12: 0 | AD12: 0 | AE12: 0 | AF12: 0 | AG12: 0 | AH12: 0 | AI12: 0 | AJ12: 0
B13: 13 | C13: INVERSIONES | D13: 1039622.4 | E13: 1020044.2 | F13: 2462114.2 | G13: 686168.36 | H13: 5207949.2 | I13: 459087.92 | J13: 718157.42 | K13: 126839.06 | L13: 181046.56 | M13: 142649.24 | N13: 709021.14 | O13: 84778.438 | P13: 173898.02 | Q13: 82690.283 | R13: 2678168.1 | S13: 36573.714 | T13: 70470.969 | U13: 8553.0518 | V13: 5954.8227 | W13: 51895.18 | X13: 4208.7871 | Y13: 9591.7532 | Z13: 4994.2805 | AA13: 15432.272 | AB13: 31039.458 | AC13: 1891.5997 | AD13: 240605.89 | AE13: 8126723.1 | AF13: 835860.2 | AG13: 329650.62 | AH13: 0 | AI13: 26915.625 | AJ13: 6934296.7
C14: INVERSIONES DEL SECTOR PRIVADO | D14: 184379.07 | E14: 314296.22 | F14: 556250.24 | G14: 221340.54 | H14: 1276266.1 | I14: 216412.35 | J14: 250941.83 | K14: 6743.212 | L14: 8548.8843 | M14: 46641.235 | N14: 254627.49 | O14: 38742.712 | P14: 35712.809 | Q14: 48742.847 | R14: 907113.36 | S14: 9357.8793 | T14: 27604.032 | U14: 4544.9101 | V14: 2472.8911 | W14: 39041.848 | X14: 636.78811 | Y14: 4825.1014 | Z14: 3353.404 | AA14: 11740.111 | AB14: 18045.777 | AC14: 358.8935 | AD14: 121981.64 | AE14: 2305361.1 | AF14: 261370.7 | AG14: 57663.011 | AH14: 0 | AI14: 16924.106 | AJ14: 1969403.2
C15: INVERSIONES DEL SECTOR PUBLICO | D15: 858331.69 | E15: 595540.85 | F15: 1856127.7 | G15: 449683.77 | H15: 3759684 | I15: 184160.22 | J15: 430573.22 | K15: 120095.85 | L15: 147485.09 | M15: 100901.35 | N15: 331563.01 | O15: 45940.726 | P15: 136927.96 | Q15: 33947.436 | R15: 1531594.9 | S15: 25802.575 | T15: 41351.733 | U15: 4049.1133 | V15: 3481.9315 | W15: 12932.605 | X15: 3209.3647 | Y15: 4766.6518 | Z15: 1593.3765 | AA15: 3692.1613 | AB15: 13160.081 | AC15: 1529.2529 | AD15: 115568.85 | AE15: 5406847.8 | AF15: 451658.87 | AG15: 251868.37 | AH15: 0 | AI15: 9988.066 | AJ15: 4693332.5
B16: 1307 | C16: De disponibilidad restringida | D16: 0 | E16: 113717.14 | F16: 163486.29 | G16: 15170.504 | H16: 292373.93 | I16: 59080.129 | J16: 37798.531 | K16: 0 | L16: 25742.793 | M16: 99.9421 | N16: 123015.21 | O16: 100 | P16: 1348.3903 | Q16: 0 | R16: 247185 | S16: 1413.2604 | T16: 1515.2046 | U16: 50 | V16: 0 | W16: 0 | X16: 362.63435 | Y16: 0 | Z16: 50 | AA16: 0 | AB16: 0 | AC16: 3.45329 | AD16: 3394.5527 | AE16: 542953.48 | AF16: 123015.21 | AG16: 25842.735 | AH16: 0 | AI16: 3.45329 | AJ16: 394092.08
B17: 1399 | C17: (Provisión para inversiones) | D17: -3088.3775 | E17: -3509.9991 | F17: -113750.04 | G17: -26.45275 | H17: -120374.87 | I17: -564.7801 | J17: -1156.1564 | K17: 0 | L17: -730.20311 | M17: -4993.2867 | N17: -184.57722 | O17: -5 | P17: -91.14237 | Q17: 0 | R17: -7725.1458 | S17: 0 | T17: 0 | U17: -90.97159 | V17: 0 | W17: -79.27318 | X17: 0 | Y17: 0 | Z17: -2.5 | AA17: 0 | AB17: -166.4 | AC17: 0 | AD17: -339.14477 | AE17: -128439.16 | AF17: -184.57722 | AG17: -5723.4898 | AH17: 0 | AI17: 0 | AJ17: -122531.09
B18: 14 | C18: CARTERA DE CRÉDITOS | D18: 4238263.8 | E18: 3954038.5 | F18: 8458292.9 | G18: 4223567.8 | H18: 20874163 | I18: 1361929.6 | J18: 2703249.4 | K18: 286808.78 | L18: 1802587.8 | M18: 662103.62 | N18: 2822855.7 | O18: 421184.74 | P18: 575733.39 | Q18: 630788.3 | R18: 11267241 | S18: 477874.02 | T18: 157357.37 | U18: 37909.756 | V18: 28835.254 | W18: 80523.243 | X18: 21390.769 | Y18: 57251.849 | Z18: 14809.181 | AA18: 76574.329 | AB18: 171855.52 | AC18: 89000.953 | AD18: 1213382.2 | AE18: 33354787 | AF18: 3109664.5 | AG18: 2493526.7 | AH18: 0 | AI18: 222827.13 | AJ18: 27528768
C19: CARTERA DE CRÉDITOS PRODUCTIVO | D19: 2267341.1 | E19: 1462911.1 | F19: 3564928.5 | G19: 2751571.2 | H19: 10046752 | I19: 773743.35 | J19: 2050699.8 | K19: 304232.57 | L19: 120470.37 | M19: 72071.203 | N19: 2459295.8 | O19: 138784.46 | P19: 391580.95 | Q19: 34.89825 | R19: 6310913.4 | S19: 378603.86 | T19: 77919.375 | U19: 21171.914 | V19: 8621.7402 | W19: 74457.876 | X19: 1836.8033 | Y19: 0 | Z19: 10537.723 | AA19: 0 | AB19: 21831.175 | AC19: 0 | AD19: 594980.46 | AE19: 16952646 | AF19: 2763528.4 | AG19: 201163.31 | AH19: 0 | AI19: 0 | AJ19: 13987954
C20: CARTERA DE CREDITOS CONSUMO | D20: 1659053.5 | E20: 2035641.9 | F20: 3472905.7 | G20: 1372540.9 | H20: 8540142 | I20: 578862.32 | J20: 663539.02 | K20: 0 | L20: 1918903.5 | M20: 547248.77 | N20: 360028.61 | O20: 204928.13 | P20: 172483.15 | Q20: 312364.21 | R20: 4758357.7 | S20: 4241.8196 | T20: 82477.694 | U20: 10763.486 | V20: 20418.149 | W20: 848.26467 | X20: 18713.764 | Y20: 5352.756 | Z20: 3395.5844 | AA20: 0 | AB20: 69363.528 | AC20: 40.72155 | AD20: 215615.77 | AE20: 13514115 | AF20: 360028.61 | AG20: 2486570.4 | AH20: 0 | AI20: 5393.4776 | AJ20: 10662123
C21: CARTERA DE CRÉDITOS INMOBILIARIO | D21: 229540.05 | E21: 406883.8 | F21: 826815.94 | G21: 261610.11 | H21: 1724849.9 | I21: 63626.083 | J21: 81671.895 | K21: 0 | L21: 215.053 | M21: 100787.97 | N21: 120027.31 | O21: 41447.807 | P21: 21122.315 | Q21: 25.95808 | R21: 428924.39 | S21: 31311.509 | T21: 1673.1769 | U21: 12.656 | V21: 86.62381 | W21: 136.38064 | X21: 0.001 | Y21: 0 | Z21: 1609.3175 | AA21: 0 | AB21: 12553.647 | AC21: 0 | AD21: 47383.312 | AE21: 2201157.6 | AF21: 120027.31 | AG21: 101089.65 | AH21: 0 | AI21: 0 | AJ21: 1980040.6
C22: CARTERA DE CRÉDITOS MICROCRÉDITO | D22: 271435.57 | E22: 6370.7169 | F22: 1632942.5 | G22: 28507.265 | H22: 1939256 | I22: 7870.9383 | J22: 0 | K22: 0 | L22: 0 | M22: 0.016 | N22: 2065.4077 | O22: 77651.927 | P22: 5144.7585 | Q22: 384810.97 | R22: 477544.02 | S22: 75799.689 | T22: 210.3834 | U22: 8350.6643 | V22: 1552.2322 | W22: 7565.8865 | X22: 2348.675 | Y22: 54875.531 | Z22: 53.6161 | AA22: 83751.316 | AB22: 82416.189 | AC22: 95662.006 | AD22: 412586.19 | AE22: 2829386.2 | AF22: 2065.4077 | AG22: 1552.2482 | AH22: 0 | AI22: 234288.85 | AJ22: 2591479.7
C23: CARTERA DE CRÉDITOS VIVIENDA DE INTERÉS SOCIAL Y PÚBLICO | D23: 0 | E23: 20113.763 | F23: 4721.0402 | G23: 0 | H23: 24834.803 | I23: 0 | J23: 0 | K23: 0 | L23: 0 | M23: 5922.2016 | N23: 397.59849 | O23: 0 | P23: 0 | Q23: 0 | R23: 6319.8001 | S23: 0 | T23: 0 | U23: 0 | V23: 0 | W23: 0 | X23: 0 | Y23: 0 | Z23: 0 | AA23: 0 | AB23: 0 | AC23: 0 | AD23: 0 | AE23: 31154.603 | AF23: 397.59849 | AG23: 5922.2016 | AH23: 0 | AI23: 0 | AJ23: 24834.803
C24: CARTERA DE CRÉDITOS EDUCATIVO | D24: 2065.895 | E24: 299876.78 | F24: 20812.683 | G24: 1415.1041 | H24: 324170.46 | I24: 0 | J24: 2764.1284 | K24: 0 | L24: 0 | M24: 0 | N24: 0 | O24: 338.9769 | P24: 2711.3732 | Q24: 0 | R24: 5814.4785 | S24: 275.94049 | T24: 0 | U24: 0 | V24: 0 | W24: 0 | X24: 0 | Y24: 0 | Z24: 0 | AA24: 0 | AB24: 0 | AC24: 0 | AD24: 275.94049 | AE24: 330260.88 | AF24: 0 | AG24: 0 | AH24: 0 | AI24: 0 | AJ24: 330260.88
C25: CARTERA DE CRÉDITO INVERSIÓN PÚBLICA | D25: 0 | E25: 0 | F25: 0 | G25: 0 | H25: 0 | I25: 0 | J25: 0 | K25: 0 | L25: 0 | M25: 0 | N25: 0 | O25: 0 | P25: 0 | Q25: 0 | R25: 0 | S25: 0 | T25: 0 | U25: 0 | V25: 0 | W25: 0 | X25: 0 | Y25: 0 | Z25: 0 | AA25: 0 | AB25: 0 | AC25: 0 | AD25: 0 | AE25: 0 | AF25: 0 | AG25: 0 | AH25: 0 | AI25: 0 | AJ25: 0
B26: 1499 | C26: (PROVISIONES PARA CRÉDITOS INCOBRABLES) | D26: -191172.23 | E26: -277759.44 | F26: -1064833.4 | G26: -192076.77 | H26: -1725841.8 | I26: -62173.1 | J26: -95425.451 | K26: -17423.78 | L26: -237001.12 | M26: -63926.546 | N26: -118958.99 | O26: -41966.566 | P26: -17309.159 | Q26: -66447.733 | R26: -720632.45 | S26: -12358.791 | T26: -4923.2641 | U26: -2388.9645 | V26: -1843.4921 | W26: -2485.1646 | X26: -1508.4739 | Y26: -2976.4381 | Z26: -787.05989 | AA26: -7176.9876 | AB26: -14309.019 | AC26: -6701.7745 | AD26: -57459.428 | AE26: -2503933.7 | AF26: -136382.77 | AG26: -302771.16 | AH26: 0 | AI26: -16855.2 | AJ26: -2047924.6
B27: 149905 | C27: (CARTERA DE CRÉDITOS PRODUCTIVO) | D27: -42822.745 | E27: -24284.485 | F27: -251211.33 | G27: -44611.202 | H27: -362929.77 | I27: -9820.8327 | J27: -26654.675 | K27: -8435.681 | L27: -2935.2042 | M27: -3515.5988 | N27: -62172.458 | O27: -6553.8394 | P27: -4181.6702 | Q27: -0.63379 | R27: -124270.59 | S27: -5853.3641 | T27: -1190.0989 | U27: -333.73131 | V27: -82.82923 | W27: -738.88917 | X27: -58.5406 | Y27: 0 | Z27: -189.01413 | AA27: 0 | AB27: -352.17037 | AC27: 0 | AD27: -8798.6378 | AE27: -495999 | AF27: -70608.139 | AG27: -6533.6322 | AH27: 0 | AI27: 0 | AJ27: -418857.23
B28: 149910 | C28: (CARTERA DE CRÉDITOS DE CONSUMO) | D28: -31648.577 | E28: -51936.936 | F28: -68815.461 | G28: -23250.856 | H28: -175651.83 | I28: -25338.395 | J28: -12810.162 | K28: 0 | L28: -49797.674 | M28: -14059.408 | N28: -12938.976 | O28: -4170.4359 | P28: -4416.0782 | Q28: -16078.393 | R28: -139609.52 | S28: -105.6286 | T28: -2029.1934 | U28: -622.0634 | V28: -796.78521 | W28: -5.04241 | X28: -509.61802 | Y28: -247.63287 | Z28: -120.62671 | AA28: 0 | AB28: -1255.9434 | AC28: -0.43238 | AD28: -5692.9664 | AE28: -320954.32 | AF28: -12938.976 | AG28: -64653.867 | AH28: 0 | AI28: -248.06525 | AJ28: -243113.41
B29: 149915 | C29: (CARTERA DE CRÉDITOS INMOBILIARIO) | D29: -4904.8226 | E29: -9898.3042 | F29: -19157.218 | G29: -5708.5342 | H29: -39668.879 | I29: -1008.5479 | J29: -2216.9879 | K29: 0 | L29: 0 | M29: -1543.9093 | N29: -2618.5164 | O29: -623.82623 | P29: -488.82545 | Q29: -13.57711 | R29: -8514.1903 | S29: -395.67996 | T29: -26.14123 | U29: -0.12656 | V29: -0.001 | W29: -0.91194 | X29: -0.001 | Y29: 0 | Z29: -32.5365 | AA29: 0 | AB29: -280.48314 | AC29: 0 | AD29: -735.88133 | AE29: -48918.951 | AF29: -2618.5164 | AG29: -1543.9103 | AH29: 0 | AI29: 0 | AJ29: -44756.524
B30: 149920 | C30: (CARTERA DE CRÉDITOS PARA MICROCRÉDITO) | D30: -7086.0445 | E30: -571.38779 | F30: -31305.457 | G30: -597.97008 | H30: -39560.859 | I30: -674.18936 | J30: 0 | K30: 0 | L30: 0 | M30: -0.014 | N30: -92.61576 | O30: -1743.8711 | P30: -278.3853 | Q30: -24599.335 | R30: -27388.41 | S30: -1815.0487 | T30: -28.29699 | U30: -763.7068 | V30: -55.11371 | W30: -67.83725 | X30: -99.01859 | Y30: -864.8694 | Z30: -2.08811 | AA30: -4907.164 | AB30: -3046.0855 | AC30: -4407.5761 | AD30: -16056.805 | AE30: -83006.074 | AF30: -92.61576 | AG30: -55.12771 | AH30: 0 | AI30: -10179.61 | AJ30: -72678.721
B31: 149940 | C31: (CARTERA DE CRÉDITOS DE VIVIENDA DE INTERÉS SOCIAL Y PÚBLICO) | D31: 0 | E31: -3788.6406 | F31: -69.81054 | G31: 0 | H31: -3858.4511 | I31: 0 | J31: 0 | K31: 0 | L31: 0 | M31: -87.69669 | N31: -4.53208 | O31: 0 | P31: 0 | Q31: 0 | R31: -92.22877 | S31: 0 | T31: 0 | U31: 0 | V31: 0 | W31: 0 | X31: 0 | Y31: 0 | Z31: 0 | AA31: 0 | AB31: 0 | AC31: 0 | AD31: 0 | AE31: -3950.6799 | AF31: -4.53208 | AG31: -87.69669 | AH31: 0 | AI31: 0 | AJ31: -3858.4511
B32: 149945 | C32: (CARTERA DE CRÉDITO REFINANCIADA) | D32: -4934.7684 | E32: -19367.897 | F32: -12955.279 | G32: -3998.0055 | H32: -41255.95 | I32: -5225.6617 | J32: -79.55414 | K32: 0 | L32: -4654.2139 | M32: -611.41119 | N32: -3939.4985 | O32: -3154.4343 | P32: -343.20957 | Q32: -390.92285 | R32: -18398.906 | S32: -2929.4513 | T32: -404.10743 | U32: -113.95557 | V32: -427.93947 | W32: -121.96957 | X32: -7.87326 | Y32: -572.45693 | Z32: -108.86946 | AA32: -565.90135 | AB32: -4922.3332 | AC32: -467.77071 | AD32: -10642.628 | AE32: -70297.484 | AF32: -3939.4985 | AG32: -5693.5645 | AH32: 0 | AI32: -1606.129 | AJ32: -59058.292
B33: 149950 | C33: (CARTERA DE CRÉDITO REESTRUCTURADA) | D33: -18076.496 | E33: -62247.76 | F33: -118630.71 | G33: -48160.064 | H33: -247115.03 | I33: -14811.355 | J33: -5708.4436 | K33: -1146.131 | L33: -49757.456 | M33: -21323.329 | N33: -11788.286 | O33: -10382.525 | P33: -3268.0947 | Q33: -1075.3176 | R33: -119260.94 | S33: -934.75745 | T33: -1187.4226 | U33: -4.56554 | V33: -418.73794 | W33: 0 | X33: -122.75408 | Y33: -1277.1301 | Z33: -252.17662 | AA33: -381.34337 | AB33: -798.0331 | AC33: -62.43864 | AD33: -5439.3594 | AE33: -371815.33 | AF33: -12934.417 | AG33: -71499.523 | AH33: 0 | AI33: -1720.9121 | AJ33: -285660.48
B34: 149955 | C34: (CARTERA DE CRÉDITO EDUCATIVO) | D34: -88.88227 | E34: -8692.4875 | F34: -247.41434 | G34: -23.22481 | H34: -9052.0089 | I34: 0 | J34: -91.291 | K34: 0 | L34: 0 | M34: 0 | N34: 0 | O34: -3.31361 | P34: -38.30686 | Q34: 0 | R34: -132.91147 | S34: -2.97716 | T34: 0 | U34: 0 | V34: 0 | W34: 0 | X34: 0 | Y34: 0 | Z34: 0 | AA34: 0 | AB34: 0 | AC34: 0 | AD34: -2.97716 | AE34: -9187.8975 | AF34: 0 | AG34: 0 | AH34: 0 | AI34: 0 | AJ34: -9187.8975
B35: 149960 | C35: (CARTERA DE CRÉDITO DE INVERSIÓN PÚBLICA) | D35: 0 | E35: 0 | F35: 0 | G35: 0 | H35: 0 | I35: 0 | J35: 0 | K35: 0 | L35: 0 | M35: 0 | N35: 0 | O35: 0 | P35: 0 | Q35: 0 | R35: 0 | S35: 0 | T35: 0 | U35: 0 | V35: 0 | W35: 0 | X35: 0 | Y35: 0 | Z35: 0 | AA35: 0 | AB35: 0 | AC35: 0 | AD35: 0 | AE35: 0 | AF35: 0 | AG35: 0 | AH35: 0 | AI35: 0 | AJ35: 0
B36: 149980 | C36: PROVISIÓN GÉNERICA POR TECNOLOGÍA CREDITICIA | D36: 0 | E36: 0 | F36: 0 | G36: 0 | H36: 0 | I36: 0 | J36: 0 | K36: 0 | L36: 0 | M36: 0 | N36: 0 | O36: 0 | P36: 0 | Q36: 0 | R36: 0 | S36: 0 | T36: 0 | U36: -163.87467 | V36: -27.10289 | W36: 0 | X36: -291.76765 | Y36: 0 | Z36: 0 | AA36: 0 | AB36: 0 | AC36: 0 | AD36: -482.74521 | AE36: -482.74521 | AF36: 0 | AG36: -27.10289 | AH36: 0 | AI36: 0 | AJ36: -455.64232
B37: 149985 | C37: PROVISIÓN ANTICÍCLICA | D37: -1235.083 | E37: -8542.5028 | F37: -171611.83 | G37: -4035.0966 | H37: -185424.51 | I37: 0 | J37: -2340.338 | K37: 0 | L37: 0 | M37: -1007.8769 | N37: 0 | O37: 0 | P37: -905.00878 | Q37: 0 | R37: -4253.2236 | S37: 0 | T37: -37.79766 | U37: 0 | V37: -26.10029 | W37: 0 | X37: -29.38142 | Y37: 0 | Z37: -57.19236 | AA37: 0 | AB37: 0 | AC37: 0 | AD37: -150.47173 | AE37: -189828.2 | AF37: 0 | AG37: -1033.9771 | AH37: 0 | AI37: 0 | AJ37: -188794.23
... B49: +1+4 | C49: TOTAL ACTIVO Y GASTOS | D49: 6720401.7 | E49: 7166919.2 | F49: 14459710 | G49: 6494865.8 | H49: 34841897 | I49: 2528857.7 | J49: 4508834.7 | K49: 649992.59 | L49: 2434861.2 | M49: 1056537.3 | N49: 4409829.8 | O49: 711134.47 | P49: 1003220 | Q49: 890489.84 | R49: 18193758 | S49: 619091.76 | T49: 302659.7 | U49: 63659.166 | V49: 42292.298 | W49: 208925.49 | X49: 42059.295 | Y49: 91765.34 | Z49: 34248.497 | AA49: 117124.11 | AB49: 254743.28 | AC49: 105520.36 | AD49: 1882089.3 | AE49: 54917743 | AF49: 5059822.4 | AG49: 3533690.7 | AH49: 0 | AI49: 314409.81 | AJ49: 46009820
C51: PASIVOS
B52: 21 | C52: OBLIGACIONES CON EL PÚBLICO | D52: 5098291.4 | E52: 5282140.4 | F52: 11260193 | G52: 4851768.7 | H52: 26492394 | I52: 2043022.2 | J52: 3498858.9 | K52: 506984.53 | L52: 1091780.9 | M52: 850333.16 | N52: 3577829.7 | O52: 569346.89 | P52: 830901.15 | Q52: 398910.15 | R52: 13367967 | S52: 345261.97 | T52: 243751.96 | U52: 46134.849 | V52: 27574.166 | W52: 168108.17 | X52: 30666.169 | Y52: 64693.752 | Z52: 18033.29 | AA52: 45329.211 | AB52: 178481.48 | AC52: 19702.17 | AD52: 1187737.2 | AE52: 41048098 | AF52: 4084814.2 | AG52: 1969688.2 | AH52: 0 | AI52: 129725.13 | AJ52: 34863871
B53: 2101 | C53: Depósitos a la vista | D53: 3091403.9 | E53: 2690974.5 | F53: 7653545.9 | G53: 2991157.7 | H53: 16427082 | I53: 1041303.6 | J53: 2251664.5 | K53: 506378.72 | L53: 15940.699 | M53: 383238.38 | N53: 2129772.6 | O53: 314083.2 | P53: 438619.01 | Q53: 81383.456 | R53: 7162384.1 | S53: 204989.79 | T53: 88498.148 | U53: 34342.513 | V53: 9971.3719 | W53: 118078.25 | X53: 3390.7132 | Y53: 6094.0138 | Z53: 9576.378 | AA53: 6153.6148 | AB53: 66437.076 | AC53: 6076.2931 | AD53: 553608.16 | AE53: 24143074 | AF53: 2636151.3 | AG53: 409150.45 | AH53: 0 | AI53: 18323.922 | AJ53: 21079449
B54: 2102 | C54: Operaciones de reporto | D54: 0 | E54: 0 | F54: 0 | G54: 0 | H54: 0 | I54: 0 | J54: 0 | K54: 0 | L54: 0 | M54: 0 | N54: 0 | O54: 0 | P54: 0 | Q54: 0 | R54: 0 | S54: 0 | T54: 0 | U54: 0 | V54: 0 | W54: 0 | X54: 0 | Y54: 0 | Z54: 0 | AA54: 0 | AB54: 0 | AC54: 0 | AD54: 0 | AE54: 0 | AF54: 0 | AG54: 0 | AH54: 0 | AI54: 0 | AJ54: 0
B55: 2103 | C55: Depósitos a plazo | D55: 1847221.5 | E55: 2260701.8 | F55: 3166426.9 | G55: 1740414.4 | H55: 9014764.6 | I55: 958482.65 | J55: 1092504.1 | K55: 0 | L55: 1065195.7 | M55: 467081.43 | N55: 1359416.8 | O55: 255248.4 | P55: 358138.15 | Q55: 314272.67 | R55: 5870339.9 | S55: 124282.61 | T55: 144450.63 | U55: 9766.8096 | V55: 17213.956 | W55: 44253.591 | X55: 27195.119 | Y55: 58599.738 | Z55: 7609.8038 | AA55: 39175.596 | AB55: 109630.88 | AC55: 13612.963 | AD55: 595791.7 | AE55: 15480896 | AF55: 1359416.8 | AG55: 1549491.1 | AH55: 0 | AI55: 111388.3 | AJ55: 12460600
B56: 2104 | C56: Depósitos de garantía | D56: 0 | E56: 0 | F56: 377.38681 | G56: 0 | H56: 377.38681 | I56: 247.00758 | J56: 455.37121 | K56: 0 | L56: 0 | M56: 0 | N56: 82.8854 | O56: 0 | P56: 0 | Q56: 0 | R56: 785.26419 | S56: 0 | T56: 26.01531 | U56: 0.3 | V56: 1 | W56: 0 | X56: 0 | Y56: 0 | Z56: 0 | AA56: 0 | AB56: 0 | AC56: 0 | AD56: 27.31531 | AE56: 1189.9663 | AF56: 82.8854 | AG56: 1 | AH56: 0 | AI56: 0 | AJ56: 1106.0809
B57: 2105 | C57: Depósitos restringidos | D57: 159666.11 | E57: 330464.07 | F57: 439843.07 | G57: 120196.47 | H57: 1050169.7 | I57: 42988.95 | J57: 154234.88 | K57: 605.8 | L57: 10644.47 | M57: 13.349 | N57: 88557.403 | O57: 15.281 | P57: 34143.988 | Q57: 3254.0283 | R57: 334458.15 | S57: 15989.567 | T57: 10777.157 | U57: 2025.2265 | V57: 387.83769 | W57: 5776.3337 | X57: 80.33612 | Y57: 0 | Z57: 847.10806 | AA57: 0 | AB57: 2413.5163 | AC57: 12.91402 | AD57: 38309.996 | AE57: 1422937.9 | AF57: 89163.203 | AG57: 11045.656 | AH57: 0 | AI57: 12.91402 | AJ57: 1322716.1
B58: 22 | C58: OPERACIONES INTERBANCARIAS | D58: 0 | E58: 0 | F58: 0 | G58: 0 | H58: 0 | I58: 0 | J58: 0 | K58: 0 | L58: 0 | M58: 0 | N58: 0 | O58: 0 | P58: 0 | Q58: 0 | R58: 0 | S58: 0 | T58: 0 | U58: 0 | V58: 0 | W58: 0 | X58: 0 | Y58: 0 | Z58: 0 | AA58: 0 | AB58: 0 | AC58: 0 | AD58: 0 | AE58: 0 | AF58: 0 | AG58: 0 | AH58: 0 | AI58: 0 | AJ58: 0
B59: 23 | C59: OBLIGACIONES INMEDIATAS | D59: 49125.887 | E59: 43271.088 | F59: 81967.231 | G59: 35609.386 | H59: 209973.59 | I59: 4323.6834 | J59: 42999.4 | K59: 19610.1 | L59: 0 | M59: 2832.5052 | N59: 10374.721 | O59: 2232.8903 | P59: 2610.1063 | Q59: 191.96918 | R59: 85175.375 | S59: 10.20149 | T59: 625.00243 | U59: 25.32298 | V59: 39.32925 | W59: 506.19811 | X59: 34.01862 | Y59: 0 | Z59: 1130.4908 | AA59: 25.896 | AB59: 706.46645 | AC59: 0 | AD59: 3102.9262 | AE59: 298251.89 | AF59: 29984.821 | AG59: 2871.8344 | AH59: 0 | AI59: 25.896 | AJ59: 265369.34
B60: 24 | C60: ACEPTACIONES EN CIRCULACIÓN | D60: 0 | E60: 8396.1213 | F60: 78.70647 | G60: 0 | H60: 8474.8278 | I60: 64.1558 | J60: 1494.1949 | K60: 213.84 | L60: 0 | M60: 0 | N60: 0 | O60: 0 | P60: 917.726 | Q60: 0 | R60: 2689.9167 | S60: 0 | T60: 0 | U60: 0 | V60: 0 | W60: 0 | X60: 0 | Y60: 0 | Z60: 0 | AA60: 0 | AB60: 0 | AC60: 0 | AD60: 0 | AE60: 11164.745 | AF60: 213.84 | AG60: 0 | AH60: 0 | AI60: 0 | AJ60: 10950.905
B61: 25 | C61: CUENTAS POR PAGAR | D61: 185920.61 | E61: 194435.09 | F61: 339486.74 | G61: 172988.56 | H61: 892831.01 | I61: 43052.861 | J61: 115503.96 | K61: 24333.179 | L61: 528608.4 | M61: 25354.318 | N61: 125753.73 | O61: 12440.907 | P61: 17295.028 | Q61: 36401.03 | R61: 928743.41 | S61: 10316.138 | T61: 7452.7678 | U61: 864.08433 | V61: 1193.886 | W61: 3171.9352 | X61: 1939.1264 | Y61: 2402.1017 | Z61: 1084.2608 | AA61: 2427.9153 | AB61: 7789.1117 | AC61: 4498.983 | AD61: 43140.31 | AE61: 1864714.7 | AF61: 150086.91 | AG61: 555156.6 | AH61: 0 | AI61: 9329 | AJ61: 1150142.2
B62: 26 | C62: OBLIGACIONES FINANCIERAS | D62: 466000.61 | E62: 477675.91 | F62: 269570.83 | G62: 486132.9 | H62: 1699380.3 | I62: 105355.21 | J62: 247427.14 | K62: 200.561 | L62: 51025 | M62: 22274.271 | N62: 146765.13 | O62: 25196.662 | P62: 27000 | Q62: 228040.68 | R62: 853284.65 | S62: 172402.56 | T62: 13131.243 | U62: 0 | V62: 0 | W62: 0 | X62: 0 | Y62: 7405.1148 | Z62: 0 | AA62: 40368.755 | AB62: 25097.48 | AC62: 54331.973 | AD62: 312737.12 | AE62: 2865402 | AF62: 146965.69 | AG62: 73299.271 | AH62: 0 | AI62: 102105.84 | AJ62: 2543031.2
B63: 2601 | C63: Sobregiros | D63: 0 | E63: 0 | F63: 11320.833 | G63: 169.23141 | H63: 11490.064 | I63: 0 | J63: 0 | K63: 200.561 | L63: 0 | M63: 0 | N63: 0 | O63: 0 | P63: 0 | Q63: 0 | R63: 200.561 | S63: 0 | T63: 0 | U63: 0 | V63: 0 | W63: 0 | X63: 0 | Y63: 0 | Z63: 0 | AA63: 0 | AB63: 0 | AC63: 0 | AD63: 0 | AE63: 11690.625 | AF63: 200.561 | AG63: 0 | AH63: 0 | AI63: 0 | AJ63: 11490.064
... B77: 2 | C77: TOTAL PASIVOS | D77: 5870316.9 | E77: 6047165.1 | F77: 12461234 | G77: 5761221 | H77: 30139937 | I77: 2200363.1 | J77: 3971910.8 | K77: 552845.32 | L77: 1764778.2 | M77: 916562.72 | N77: 3861409.6 | O77: 616619.95 | P77: 896526.4 | Q77: 665467.91 | R77: 15446484 | S77: 538183.58 | T77: 265984.79 | U77: 47337.254 | V77: 29001.672 | W77: 171819.94 | X77: 33376.217 | Y77: 76158.429 | Z77: 20359.347 | AA77: 88455.75 | AB77: 212512.56 | AC77: 78723.338 | AD77: 1561912.9 | AE77: 47148334 | AF77: 4414255 | AG77: 2710342.6 | AH77: 0 | AI77: 243337.52 | AJ77: 39780398
C79: PATRIMONIO
B80: 31 | C80: CAPITAL SOCIAL | D80: 483370 | E80: 582479.74 | F80: 919241.6 | G80: 394760 | H80: 2379851.3 | I80: 152900 | J80: 325000 | K80: 68559.042 | L80: 300000 | M80: 70334.805 | N80: 333706.68 | O80: 46700 | P80: 56300 | Q80: 93522.016 | R80: 1447022.5 | S80: 51931 | T80: 21083.923 | U80: 11010.6 | V80: 11090.785 | W80: 21738.121 | X80: 11000 | Y80: 18663.2 | Z80: 11356.808 | AA80: 20968.6 | AB80: 20846.8 | AC80: 16701.1 | AD80: 216390.94 | AE80: 4043264.8 | AF80: 402265.72 | AG80: 381425.59 | AH80: 0 | AI80: 56332.9 | AJ80: 3203240.6
B81: 32 | C81: PRIMA O DESCUENTO EN COLOCACIÓN DE ACCIONES Y CERTIFICADOS | D81: 0 | E81: 0 | F81: 0 | G81: 1104.7742 | H81: 1104.7742 | I81: 0 | J81: 0 | K81: 0 | L81: 0 | M81: 0 | N81: 0 | O81: 0 | P81: 0 | Q81: 1204.77 | R81: 1204.77 | S81: 0 | T81: 0 | U81: 0 | V81: 0 | W81: 0 | X81: 0 | Y81: 0 | Z81: 0 | AA81: 0 | AB81: 0 | AC81: 0 | AD81: 0 | AE81: 2309.5442 | AF81: 0 | AG81: 0 | AH81: 0 | AI81: 0 | AJ81: 2309.5442
B82: 33 | C82: RESERVAS | D82: 80224.95 | E82: 149343.47 | F82: 284176.97 | G82: 91529.105 | H82: 605274.49 | I82: 39542.328 | J82: 52752.481 | K82: 11847.53 | L82: 144068 | M82: 17448.666 | N82: 55080.156 | O82: 9954.8961 | P82: 7305.697 | Q82: 39301.863 | R82: 377301.62 | S82: 5867.0629 | T82: 1924.9699 | U82: 1483.3251 | V82: 459.54687 | W82: 8248.9282 | X82: 0 | Y82: 0.02658 | Z82: 112.1461 | AA82: 1088.5892 | AB82: 3198.3423 | AC82: 958.70372 | AD82: 23341.641 | AE82: 1005917.7 | AF82: 66927.686 | AG82: 161976.21 | AH82: 0 | AI82: 2047.3195 | AJ82: 774966.53
B83: 34 | C83: OTROS APORTES PATRIMONIALES | D83: 0 | E83: 0 | F83: 0 | G83: 0 | H83: 0 | I83: 0 | J83: 0 | K83: 0 | L83: 0 | M83: 0 | N83: 0 | O83: 0 | P83: 0 | Q83: 15.58852 | R83: 15.58852 | S83: 52.19609 | T83: 0 | U83: 0 | V83: 0 | W83: 3.16971 | X83: 0 | Y83: 0 | Z83: 0 | AA83: 0 | AB83: 1535.061 | AC83: 18.31118 | AD83: 1608.738 | AE83: 1624.3265 | AF83: 0 | AG83: 0 | AH83: 0 | AI83: 18.31118 | AJ83: 1606.0153
B84: 35 | C84: SUPERÁVIT POR VALUACIONES | D84: 5900.1727 | E84: 67075.546 | F84: 80468.547 | G84: -5256.6122 | H84: 148187.65 | I84: 32186.283 | J84: 16773.033 | K84: 504.624 | L84: 21134.755 | M84: 1323.8153 | N84: 22292.618 | O84: 3996.5318 | P84: 7501.6642 | Q84: 669.50763 | R84: 106382.83 | S84: 992.43219 | T84: 3519.9436 | U84: 1162.975 | V84: 86.92665 | W84: 1798.4985 | X84: 9.91303 | Y84: 10.87379 | Z84: 16.59206 | AA84: 527.15602 | AB84: 1256.5391 | AC84: 0 | AD84: 9381.85 | AE84: 263952.34 | AF84: 22797.242 | AG84: 22545.497 | AH84: 0 | AI84: 538.02981 | AJ84: 218071.57
B85: 36 | C85: RESULTADOS | D85: 0.0001 | E85: 6945.4437 | F85: 21508.082 | G85: 351.19547 | H85: 28804.721 | I85: 13.74664 | J85: 400.49553 | K85: 1595.348 | L85: 0 | M85: 313.49933 | N85: 0 | O85: 3647.2079 | P85: 618.72603 | Q85: 25329.656 | R85: 31918.679 | S85: -962.55642 | T85: 0 | U85: 113.91399 | V85: -284.17074 | W85: 0 | X85: -4115.5021 | Y85: -9131.3007 | Z85: 0 | AA85: -2648.3075 | AB85: 0 | AC85: 0 | AD85: -17027.924 | AE85: 43695.477 | AF85: 1595.348 | AG85: 29.32859 | AH85: 0 | AI85: -11779.608 | AJ85: 53850.409
B86: 3601 | C86: Utilidades o excedentes acumulados | D86: 0.0001 | E86: 6945.4437 | F86: 21508.082 | G86: 351.19547 | H86: 28804.721 | I86: 13.74664 | J86: 400.49553 | K86: 1595.348 | L86: 0 | M86: 313.49933 | N86: 0 | O86: 3647.2079 | P86: 618.72603 | Q86: 25329.656 | R86: 31918.679 | S86: 583.2962 | T86: 0 | U86: 113.91399 | V86: 92.54467 | W86: 0 | X86: 0 | Y86: 0.23927 | Z86: 0 | AA86: 0 | AB86: 0 | AC86: 0 | AD86: 789.99413 | AE86: 61513.395 | AF86: 1595.348 | AG86: 406.044 | AH86: 0 | AI86: 0.23927 | AJ86: 59511.763
B87: 3602 | C87: (Pérdidas acumuladas) | D87: 0 | E87: 0 | F87: 0 | G87: 0 | H87: 0 | I87: 0 | J87: 0 | K87: 0 | L87: 0 | M87: 0 | N87: 0 | O87: 0 | P87: 0 | Q87: 0 | R87: 0 | S87: -1545.8526 | T87: 0 | U87: 0 | V87: -376.71541 | W87: 0 | X87: -4115.5021 | Y87: -9131.54 | Z87: 0 | AA87: -2648.3075 | AB87: 0 | AC87: 0 | AD87: -17817.918 | AE87: -17817.918 | AF87: 0 | AG87: -376.71541 | AH87: 0 | AI87: -11779.848 | AJ87: -5661.3547
B88: 3603 | C88: Utilidad o excedente del ejercicio | D88: 0 | E88: 0 | F88: 0 | G88: 0 | H88: 0 | I88: 0 | J88: 0 | K88: 0 | L88: 0 | M88: 0 | N88: 0 | O88: 0 | P88: 0 | Q88: 0 | R88: 0 | S88: 0 | T88: 0 | U88: 0 | V88: 0 | W88: 0 | X88: 0 | Y88: 0 | Z88: 0 | AA88: 0 | AB88: 0 | AC88: 0 | AD88: 0 | AE88: 0 | AF88: 0 | AG88: 0 | AH88: 0 | AI88: 0 | AJ88: 0
B89: 3604 | C89: (Pérdida del ejercicio) | D89: 0 | E89: 0 | F89: 0 | G89: 0 | H89: 0 | I89: 0 | J89: 0 | K89: 0 | L89: 0 | M89: 0 | N89: 0 | O89: 0 | P89: 0 | Q89: 0 | R89: 0 | S89: 0 | T89: 0 | U89: 0 | V89: 0 | W89: 0 | X89: 0 | Y89: 0 | Z89: 0 | AA89: 0 | AB89: 0 | AC89: 0 | AD89: 0 | AE89: 0 | AF89: 0 | AG89: 0 | AH89: 0 | AI89: 0 | AJ89: 0
B90: 37 | C90: (DESVALORIZACIÓN DEL PATRIMONIO) | D90: 0 | E90: 0 | F90: 0 | G90: 0 | H90: 0 | I90: 0 | J90: 0 | K90: 0 | L90: 0 | M90: 0 | N90: 0 | O90: 0 | P90: 0 | Q90: 0 | R90: 0 | S90: 0 | T90: 0 | U90: 0 | V90: 0 | W90: 0 | X90: 0 | Y90: 0 | Z90: 0 | AA90: 0 | AB90: 0 | AC90: 0 | AD90: 0 | AE90: 0 | AF90: 0 | AG90: 0 | AH90: 0 | AI90: 0 | AJ90: 0
B91: 3 | C91: TOTAL PATRIMONIO | D91: 569495.12 | E91: 805844.19 | F91: 1305395.2 | G91: 482488.46 | H91: 3163223 | I91: 224642.36 | J91: 394926.01 | K91: 82506.544 | L91: 465202.75 | M91: 89420.785 | N91: 411079.46 | O91: 64298.636 | P91: 71726.087 | Q91: 160043.4 | R91: 1963846 | S91: 57880.135 | T91: 26528.836 | U91: 13770.814 | V91: 11353.088 | W91: 31788.717 | X91: 6894.4109 | Y91: 9542.7996 | Z91: 11485.547 | AA91: 19936.038 | AB91: 26836.742 | AC91: 17678.115 | AD91: 233695.24 | AE91: 5360764.2 | AF91: 493586 | AG91: 565976.63 | AH91: 0 | AI91: 47156.952 | AJ91: 4254044.7
... B100: 7 | C100: CUENTAS DE ORDEN | D100: 16966978 | E100: 14668514 | F100: 36336016 | G100: 10478419 | H100: 78449927 | I100: 8441376.7 | J100: 5751575.9 | K100: 2238058 | L100: 6631451.5 | M100: 4377091.2 | N100: 16026307 | O100: 1559975.7 | P100: 1839466.2 | Q100: 1729958.5 | R100: 48595261 | S100: 2080821.3 | T100: 856318.15 | U100: 180543.16 | V100: 118247.81 | W100: 198272.49 | X100: 106794.73 | Y100: 110741.39 | Z100: 117814.27 | AA100: 237769.09 | AB100: 861540.83 | AC100: 275504.66 | AD100: 5144367.9 | AE100: 1.3218956e+08 | AF100: 18264365 | AG100: 11126791 | AH100: 0 | AI100: 624015.14 | AJ100: 1.0217439e+08

Sheet RK
B3: RANKING EN BASE A LA PARTICIPACIÓN DE LAS PRINCIPALES CUENTAS DEL BALANCE
B4: SISTEMA DE BANCOS PRIVADOS
B5: 31/05/2022
B6: (en miles de dólares y porcentajes)
C8: ACTIVOS | J8: PASIVOS
B9: ENTIDADES | C9: abril de 2022 (USD) | D9: abril de 2022 (%) | E9: mayo de 2022 (USD) | F9: mayo de 2022 (%) | I9: ENTIDADES | J9: abril de 2022 (USD) | K9: abril de 2022 (%) | L9: mayo de 2022 (USD) | M9: mayo de 2022 (%)
B10: BP PICHINCHA | C10: 13761232 | D10: 0.26096898 | E10: 13823078 | F10: 0.26201133 | I10: BP PICHINCHA | J10: 12412956 | K10: 0.2631101 | L10: 12461234 | M10: 0.2642985
B11: BP PACIFICO | C11: 7038713 | D11: 0.13348266 | E11: 6896070.5 | F11: 0.13071246 | I11: BP PACIFICO | J11: 6198251.1 | K11: 0.13138067 | L11: 6047165.1 | M11: 0.1282583
B12: BP GUAYAQUIL | C12: 6403420.8 | D12: 0.12143493 | E12: 6477099.2 | F12: 0.12277102 | I12: BP GUAYAQUIL | J12: 5804416.9 | K12: 0.1230328 | L12: 5870316.9 | M12: 0.12450741
B13: BP PRODUBANCO | C13: 6269594.5 | D13: 0.11889704 | E13: 6274745.5 | F13: 0.11893548 | I13: BP PRODUBANCO | J13: 5764171.6 | K13: 0.12217975 | L13: 5761221 | M13: 0.12219352
B14: BP BOLIVARIANO | C14: 4400898.3 | D14: 0.083458951 | E14: 4386397.7 | F14: 0.083142545 | I14: BP BOLIVARIANO | J14: 3990764.6 | K14: 0.084589883 | L14: 3971910.8 | M14: 0.084242868
B15: BP INTERNACIONAL | C15: 4241956.7 | D15: 0.080444771 | E15: 4289690.3 | F15: 0.081309492 | I15: BP INTERNACIONAL | J15: 3818070.2 | K15: 0.080929382 | L15: 3861409.6 | M15: 0.081899176
B16: BP AUSTRO | C16: 2435213.2 | D16: 0.046181557 | E16: 2429700.3 | F16: 0.046054071 | I16: BP AUSTRO | J16: 2207416.7 | K16: 0.04678931 | L16: 2200363.1 | M16: 0.046668948
B17: BP DINERS | C17: 2253528 | D17: 0.042736066 | E17: 2252452.7 | F17: 0.042694408 | I17: BP DINERS | J17: 1770013.2 | K17: 0.037517926 | L17: 1764778.2 | M17: 0.03743034
B18: BP GENERAL RUMIÑAHUI | C18: 1033406.1 | D18: 0.019597587 | E18: 1011533.9 | F18: 0.019173251 | I18: BP GENERAL RUMIÑAHUI | J18: 939517.36 | K18: 0.019914395 | L18: 916562.72 | M18: 0.019439981
B19: BP MACHALA | C19: 985575.65 | D19: 0.018690527 | E19: 970545.26 | F19: 0.018396326 | I19: BP MACHALA | J19: 912091.32 | K19: 0.019333062 | L19: 896526.4 | M19: 0.019015018
B20: BP SOLIDARIO | C20: 821177.99 | D20: 0.015572878 | E20: 829686.53 | F20: 0.015726401 | I20: BP SOLIDARIO | J20: 658077.79 | K20: 0.013948887 | L20: 665467.91 | M20: 0.014114346
B21: BP LOJA | C21: 691588.83 | D21: 0.01311534 | E21: 683351.96 | F21: 0.012952684 | I21: BP LOJA | J21: 625450.4 | K21: 0.013257303 | L21: 616619.95 | M21: 0.013078298
... B38: BANCOS PRIVADOS PEQUEÑOS | C38: 1791818.2 | D38: 0.033980168 | E38: 1796321.9 | F38: 0.034048618 | I38: BANCOS PRIVADOS PEQUEÑOS | J38: 1557021.8 | K38: 0.033003273 | L38: 1561912.9 | M38: 0.033127637
C40: PATRIMONIO | J40: INVERSIONES
B41: ENTIDADES | C41: abril de 2022 (USD) | D41: abril de 2022 (%) | E41: mayo de 2022 (USD) | F41: mayo de 2022 (%) | I41: ENTIDADES | J41: abril de 2022 (USD) | K41: abril de 2022 (%) | L41: mayo de 2022 (USD) | M41: mayo de 2022 (%)
B42: BP PICHINCHA | C42: 1306838.5 | D42: 0.2437057 | E42: 1305395.2 | F42: 0.24350916 | I42: BP PICHINCHA | J42: 2385117.4 | K42: 0.29165407 | L42: 2462114.2 | M42: 0.30296519
B43: BP PACIFICO | C43: 806354.57 | D43: 0.15037298 | E43: 805844.19 | F43: 0.15032263 | I43: BP GUAYAQUIL | J43: 1035210.3 | K43: 0.12658634 | L43: 1039622.4 | M43: 0.12792639
B44: BP GUAYAQUIL | C44: 569499.67 | D44: 0.10620311 | E44: 569495.12 | F44: 0.10623394 | I44: BP PACIFICO | J44: 1022136.5 | K44: 0.12498767 | L44: 1020044.2 | M44: 0.12551728
B45: BP PRODUBANCO | C45: 481740.71 | D45: 0.089837387 | E45: 482488.46 | F45: 0.090003671 | I45: BP BOLIVARIANO | J45: 715313.91 | K45: 0.087469158 | L45: 718157.42 | M45: 0.088369864
B46: BP DINERS | C46: 465504.24 | D46: 0.08680953 | E46: 465202.75 | F46: 0.086779185 | I46: BP INTERNACIONAL | J46: 748590.42 | K46: 0.091538237 | L46: 709021.14 | M46: 0.087245637
B47: BP INTERNACIONAL | C47: 411119.19 | D47: 0.076667537 | E47: 411079.46 | F47: 0.076682995 | I47: BP PRODUBANCO | J47: 709819.6 | K47: 0.086797311 | L47: 686168.36 | M47: 0.084433583
B48: BP BOLIVARIANO | C48: 395077.04 | D48: 0.073675919 | E48: 394926.01 | F48: 0.073669722 | I48: BP AUSTRO | J48: 470611.31 | K48: 0.057546729 | L48: 459087.92 | M48: 0.056491149
B49: BP AUSTRO | C49: 224457.5 | D49: 0.041857943 | E49: 224642.36 | F49: 0.041904913 | I49: BP DINERS | J49: 189830.8 | K49: 0.023212662 | L49: 181046.56 | M49: 0.022277929
B50: BP SOLIDARIO | C50: 159991.4 | D50: 0.029835987 | E50: 160043.4 | F50: 0.029854587 | I50: BP MACHALA | J50: 208827.58 | K50: 0.025535604 | L50: 173898.02 | M50: 0.021398295
B51: BP GENERAL RUMIÑAHUI | C51: 89414.813 | D51: 0.016674516 | E51: 89420.785 | F51: 0.016680604 | I51: BP GENERAL RUMIÑAHUI | J51: 146436.12 | K51: 0.017906326 | L51: 142649.24 | M51: 0.017553106
B52: BP CITIBANK | C52: 82511.578 | D52: 0.015387167 | E52: 82506.544 | F52: 0.015390817 | I52: BP CITIBANK | J52: 119856.98 | K52: 0.014656207 | L52: 126839.06 | M52: 0.015607652
B53: BP MACHALA | C53: 71742.705 | D53: 0.013378934 | E53: 71726.087 | F53: 0.013379825 | I53: BP LOJA | J53: 99577.819 | K53: 0.012176456 | L53: 84778.438 | M53: 0.010432057
... B70: BANCOS PRIVADOS PEQUEÑOS | C70: 233811.36 | D70: 0.043602297 | E70: 233695.24 | F70: 0.043593643 | I70: BANCOS PRIVADOS PEQUEÑOS | J70: 237374.59 | K70: 0.02903 | L70: 240605.89 | M70: 0.002961
C72: CARTERA | J72: DEPOSITOS A LA VISTA
B73: ENTIDADES | C73: abril de 2022 (USD) | D73: abril de 2022 (%) | E73: mayo de 2022 (USD) | F73: mayo de 2022 (%) | I73: ENTIDADES | J73: abril de 2022 (USD) | K73: abril de 2022 (%) | L73: mayo de 2022 (USD) | M73: mayo de 2022 (%)
B74: BP PICHINCHA | C74: 8359219.7 | D74: 0.2534167 | E74: 8458292.9 | F74: 0.25358558 | I74: BP PICHINCHA | J74: 7633475.1 | K74: 0.31349857 | L74: 7653545.9 | M74: 0.31700793
B75: BP GUAYAQUIL | C75: 4232383.4 | D75: 0.12830822 | E75: 4238263.8 | F75: 0.12706613 | I75: BP GUAYAQUIL | J75: 3119246.6 | K75: 0.12810408 | L75: 3091403.9 | M75: 0.12804516
B76: BP PRODUBANCO | C76: 4115352 | D76: 0.12476032 | E76: 4223567.8 | F76: 0.12662554 | I76: BP PRODUBANCO | J76: 2985527.1 | K76: 0.12261237 | L76: 2991157.7 | M76: 0.12389299
B77: BP PACIFICO | C77: 3922917.1 | D77: 0.1189265 | E77: 3954038.5 | F77: 0.11854486 | I77: BP PACIFICO | J77: 2755627.6 | K77: 0.11317065 | L77: 2690974.5 | M77: 0.11145948
B78: BP INTERNACIONAL | C78: 2778782.4 | D78: 0.0842411 | E78: 2822855.7 | F78: 0.084631203 | I78: BP BOLIVARIANO | J78: 2340110.5 | K78: 0.096105806 | L78: 2251664.5 | M78: 0.093263371
B79: BP BOLIVARIANO | C79: 2671248.2 | D79: 0.080981112 | E79: 2703249.4 | F79: 0.081045321 | I79: BP INTERNACIONAL | J79: 2146469.2 | K79: 0.088153168 | L79: 2129772.6 | M79: 0.088214639
B80: BP DINERS | C80: 1825155.5 | D80: 0.055331109 | E80: 1802587.8 | F80: 0.054042852 | I80: BP AUSTRO | J80: 1052137 | K80: 0.043210127 | L80: 1041303.6 | M80: 0.043130529
B81: BP AUSTRO | C81: 1334996.5 | D81: 0.040471531 | E81: 1361929.6 | F81: 0.040831609 | I81: BP CITIBANK | J81: 485193.03 | K81: 0.019926353 | L81: 506378.72 | M81: 0.020974078
B82: BP GENERAL RUMIÑAHUI | C82: 656853.76 | D82: 0.019913068 | E82: 662103.62 | F82: 0.019850333 | I82: BP MACHALA | J82: 460593.13 | K82: 0.018916061 | L82: 438619.01 | M82: 0.018167488
B83: BP SOLIDARIO | C83: 615977.02 | D83: 0.018673856 | E83: 630788.3 | F83: 0.018911478 | I83: BP GENERAL RUMIÑAHUI | J83: 409841.45 | K83: 0.016831745 | L83: 383238.38 | M83: 0.015873636
B84: BP MACHALA | C84: 570428.3 | D84: 0.017293008 | E84: 575733.39 | F84: 0.017260893 | I84: BP LOJA | J84: 317372.59 | K84: 0.013034149 | L84: 314083.2 | M84: 0.013009246
B85: BP PROCREDIT | C85: 477577.68 | D85: 0.014478165 | E85: 477874.02 | F85: 0.014327 | I85: BP PROCREDIT | J85: 198639.42 | K85: 0.0081579062 | L85: 204989.79 | M85: 0.0084906251
... B102: BANCOS PRIVADOS PEQUEÑOS | C102: 1204277.9 | D102: 0.036508687 | E102: 1213382.2 | F102: 0.036378054 | I102: BANCOS PRIVADOS PEQUEÑOS | J102: 548456.24 | K102: 0.022524505 | L102: 553608.16 | M102: 0.022930309
C104: DEPOSITOS A PLAZO | J104: CAPITAL Y RESERVAS
B105: ENTIDADES | C105: abril de 2022 (USD) | D105: abril de 2022 (%) | E105: mayo de 2022 (USD) | F105: mayo de 2022 (%) | I105: ENTIDADES | J105: abril de 2022 (USD) | K105: abril de 2022 (%) | L105: mayo de 2022 (USD) | M105: mayo de 2022 (%)
B106: BP PICHINCHA | C106: 3163554.8 | D106: 0.20674855 | E106: 3166426.9 | F106: 0.2045377 | I106: BP PICHINCHA | J106: 1203418.6 | K106: 0.23836847 | L106: 1203418.6 | M106: 0.23833929
B107: BP PACIFICO | C107: 2315337.7 | D107: 0.15131482 | E107: 2260701.8 | F107: 0.14603171 | I107: BP PACIFICO | J107: 731823.2 | K107: 0.1449567 | L107: 731823.2 | M107: 0.14493895
B108: BP GUAYAQUIL | C108: 1754303.9 | D108: 0.11464944 | E108: 1847221.5 | F108: 0.11932264 | I108: BP GUAYAQUIL | J108: 563594.95 | K108: 0.1116347 | L108: 563594.95 | M108: 0.11162103
B109: BP PRODUBANCO | C109: 1735435.5 | D109: 0.11341633 | E109: 1740414.4 | F109: 0.11242336 | I109: BP PRODUBANCO | J109: 486289.1 | K109: 0.096322256 | L109: 486289.1 | M109: 0.096310462
B110: BP INTERNACIONAL | C110: 1296559.8 | D110: 0.084734386 | E110: 1359416.8 | F110: 0.087812538 | I110: BP DINERS | J110: 444068 | K110: 0.087959263 | L110: 444068 | M110: 0.087948493
B111: BP BOLIVARIANO | C111: 1025207.4 | D111: 0.067000625 | E111: 1092504.1 | F111: 0.070571116 | I111: BP INTERNACIONAL | J111: 388786.84 | K111: 0.077009386 | L111: 388786.84 | M111: 0.076999957
B112: BP DINERS | C112: 1074961 | D112: 0.070252183 | E112: 1065195.7 | F112: 0.068807109 | I112: BP BOLIVARIANO | J112: 377752.48 | K112: 0.074823743 | L112: 377752.48 | M112: 0.074814582
B113: BP AUSTRO | C113: 959187.21 | D113: 0.062685992 | E113: 958482.65 | F113: 0.061913899 | I113: BP AUSTRO | J113: 192442.33 | K113: 0.038118228 | L113: 192442.33 | M113: 0.038113561
B114: BP GENERAL RUMIÑAHUI | C114: 465089.37 | D114: 0.030395098 | E114: 467081.43 | F114: 0.030171472 | I114: BP SOLIDARIO | J114: 132823.88 | K114: 0.026309238 | L114: 132823.88 | M114: 0.026306016
B115: BP MACHALA | C115: 351659.58 | D115: 0.022982093 | E115: 358138.15 | F115: 0.0231342 | I115: BP GENERAL RUMIÑAHUI | J115: 87783.471 | K115: 0.017387809 | L115: 87783.471 | M115: 0.01738568
B116: BP SOLIDARIO | C116: 311232.01 | D116: 0.02034002 | E116: 314272.67 | F116: 0.020300677 | I116: BP CITIBANK | J116: 80406.572 | K116: 0.015926621 | L116: 80406.572 | M116: 0.015924671
B117: BP LOJA | C117: 256754.49 | D117: 0.016779738 | E117: 255248.4 | F117: 0.01648796 | I117: BP MACHALA | J117: 63605.697 | K117: 0.012598769 | L117: 63605.697 | M117: 0.012597227
... B134: BANCOS PRIVADOS PEQUEÑOS | C134: 592177.5 | D134: 0.038700718 | E134: 595791.7 | F134: 0.038485608 | I134: BANCOS PRIVADOS PEQUEÑOS | J134: 239114.34 | K134: 0.04736284 | L134: 239732.58 | M134: 0.047479483
C136: RESULTADOS
B137: ENTIDADES | C137: abril de 2022 (USD) | D137: abril de 2022 (%) | E137: mayo de 2022 (USD) | F137: mayo de 2022 (%)
B138: BP PICHINCHA | C138: 41437.368 | D138: 0.21680271 | E138: 56449.451 | F138: 0.22719681
B139: BP PACIFICO | C139: 34107.322 | D139: 0.17845149 | E139: 43061.15 | F139: 0.1733118
B140: BP GUAYAQUIL | C140: 29504.182 | D140: 0.15436759 | E140: 37287.166 | F140: 0.15007277
B141: BP PRODUBANCO | C141: 23682.131 | D141: 0.12390629 | E141: 31036.073 | F141: 0.12491347
B142: BP DINERS | C142: 18010.584 | D142: 0.094232419 | E142: 22471.782 | F142: 0.090444054
B143: BP BOLIVARIANO | C143: 15056.73 | D143: 0.078777687 | E143: 19560.823 | F143: 0.078728076
B144: BP INTERNACIONAL | C144: 12767.387 | D144: 0.066799709 | E144: 17201.184 | F144: 0.06923104
B145: BP GENERAL RUMIÑAHUI | C145: 4473.9079 | D145: 0.023407746 | E145: 5550.3832 | F145: 0.02233909
B146: BP AUSTRO | C146: 3338.9784 | D146: 0.017469729 | E146: 4694.8651 | F146: 0.018895815
B147: BP SOLIDARIO | C147: 3108.7948 | D147: 0.016265395 | E147: 4175.2195 | F147: 0.016804354
B148: BP LOJA | C148: 1838.4178 | D148: 0.0096187085 | E148: 2433.3785 | F148: 0.0097938214
B149: BP MACHALA | C149: 1741.6282 | D149: 0.0091123001 | E149: 2292.7751 | F149: 0.0092279233
... B166: BANCOS PRIVADOS PEQUEÑOS | C166: 985.03585 | D166: 0.0051537647 | E166: 713.81088 | F166: 0.0028729342
B168: Fuente: Estados de situación remitidos por las entidades / Sistema de Administración de Balances (S.A.B.)
B169: Elaboración: Dirección de Estudios y Gestión de la Información / Subdirección de Estadísticas y Estudios/OM
B170: Nota: Agrupación de entidades en base a su participación en el Activo Total.
B171: Grandes (Mayor al 10%)
B172: Medianas (Entre el 1%% y 10%)
B173: Pequeñas (Menor al 1%)
B174: Fecha de consolidación: 06-08-2020
B175: Código Orgánico Monetario y Financiero Art 162 : Composición del sector financiero privado, Bancos Múltiple y Especializada

Sheet Gráficos RK

Sheet COMPOS CART
B3: COMPOSICIÓN DE LA CARTERA DE CRÉDITOS POR VENCIMIENTOS Y LÍNEAS DE NEGOCIO
B4: SISTEMA DE BANCOS PRIVADOS
B5: 31/05/2022
B6: En miles de dólares
B8: CÓDIGO | C8: CUENTA | D8: BP GUAYAQUIL | E8: BP PACIFICO | F8: BP PICHINCHA | G8: BP PRODUBANCO | H8: BANCOS PRIVADOS GRANDES | I8: BP AUSTRO | J8: BP BOLIVARIANO | K8: BP CITIBANK | L8: BP DINERS | M8: BP GENERAL RUMIÑAHUI | N8: BP INTERNACIONAL | O8: BP LOJA | P8: BP MACHALA | Q8: BP SOLIDARIO | R8: BANCOS PRIVADOS MEDIANOS | S8: BP PROCREDIT | T8: BP AMAZONAS | U8: BP COMERCIAL DE MANABI | V8: BP LITORAL | W8: BP COOPNACIONAL | X8: BP CAPITAL | Y8: BP FINCA S.A. | Z8: BP DELBANK | AA8: BP D-MIRO S.A. | AB8: BP BANCO DESARROLLO DE LOS PUEBLOS S.A., CODESARROLLO | AC8: BP VISIONFUND ECUADOR S.A. | AD8: BANCOS PRIVADOS PEQUEÑOS | AE8: TOTAL BANCOS PRIVADOS | AF8: BANCOS PRIVADOS COMERCIALES | AG8: BANCOS PRIVADOS CONSUMO | AH8: BANCOS PRIVADOS VIVIENDA | AI8: BANCOS PRIVADOS MICROCRÉDITO | AJ8: BANCA MÚLTIPLE
C9: CARTERA BRUTA | D9: 4429436 | E9: 4231798 | F9: 9523126.3 | G9: 4415644.6 | H9: 22600005 | I9: 1424102.7 | J9: 2798674.8 | K9: 304232.57 | L9: 2039588.9 | M9: 726030.16 | N9: 2941814.7 | O9: 463151.31 | P9: 593042.55 | Q9: 697236.04 | R9: 11987874 | S9: 490232.81 | T9: 162280.63 | U9: 40298.721 | V9: 30678.746 | W9: 83008.408 | X9: 22899.243 | Y9: 60228.287 | Z9: 15596.241 | AA9: 83751.316 | AB9: 186164.54 | AC9: 95702.727 | AD9: 1270841.7 | AE9: 35858720 | AF9: 3246047.3 | AG9: 2796297.8 | AH9: 0 | AI9: 239682.33 | AJ9: 29576693
B11: 1401 | C11: CARTERA DE CRÉDITOS PRODUCTIVO POR VENCER | D11: 2241191.5 | E11: 968887.2 | F11: 3350688.8 | G11: 2716610 | H11: 9277377.5 | I11: 674450.52 | J11: 2045113.2 | K11: 301367.23 | L11: 94609.611 | M11: 55854.923 | N11: 2390100.7 | O11: 110196.74 | P11: 381300.22 | Q11: 34.87525 | R11: 6053028 | S11: 353252.23 | T11: 75761.48 | U11: 18059.056 | V11: 7732.5619 | W11: 74273.378 | X11: 1836.7133 | Y11: 0 | Z11: 7607.1979 | AA11: 0 | AB11: 18571.81 | AC11: 0 | AD11: 557094.42 | AE11: 15887500 | AF11: 2691467.9 | AG11: 158197.1 | AH11: 0 | AI11: 0 | AJ11: 13037835
B12: 1402 | C12: CARTERA DE CRÉDITOS DE CONSUMO POR VENCER | D12: 1565730.5 | E12: 1935012.4 | F12: 3223463.8 | G12: 1258533.7 | H12: 7982740.5 | I12: 507566.76 | J12: 638872.37 | K12: 0 | L12: 1723200.1 | M12: 510292.92 | N12: 339282.11 | O12: 187055.84 | P12: 167099.85 | Q12: 299074.35 | R12: 4372444.3 | S12: 3970.2334 | T12: 72968.954 | U12: 9743.7942 | V12: 16683.215 | W12: 803.41368 | X12: 17680.915 | Y12: 4267.3952 | Z12: 3019.148 | AA12: 0 | AB12: 58461.453 | AC12: 40.6166 | AD12: 187639.14 | AE12: 12542824 | AF12: 339282.11 | AG12: 2250176.2 | AH12: 0 | AI12: 4308.0118 | AJ12: 9949057.6
B13: 1403 | C13: CARTERA DE CRÉDITOS INMOBILIARIO POR VENCER | D13: 212831.88 | E13: 355382.59 | F13: 705415.85 | G13: 240660.34 | H13: 1514290.7 | I13: 60550.919 | J13: 76975.033 | K13: 0 | L13: 215.053 | M13: 92129.3 | N13: 114908.48 | O13: 38295.062 | P13: 20716.027 | Q13: 12.61 | R13: 403802.48 | S13: 30674.21 | T13: 1276.1935 | U13: 12.656 | V13: 0 | W13: 136.37664 | X13: 0 | Y13: 0 | Z13: 1359.5851 | AA13: 0 | AB13: 7349.6903 | AC13: 0 | AD13: 40808.712 | AE13: 1958901.8 | AF13: 114908.48 | AG13: 92344.353 | AH13: 0 | AI13: 0 | AJ13: 1751649
B14: 1404 | C14: CARTERA DE CRÉDITOS PARA MICROCRÉDITO POR VENCER | D14: 260845.81 | E14: 3879.4754 | F14: 1429350.8 | G14: 27002.692 | H14: 1721078.8 | I14: 6079.7437 | J14: 0 | K14: 0 | L14: 0 | M14: 0 | N14: 1911.2094 | O14: 70218.364 | P14: 4790.5778 | Q14: 370671.69 | R14: 453671.58 | S14: 66392.963 | T14: 181.42291 | U14: 7178.4894 | V14: 1264.9323 | W14: 7396.6778 | X14: 2242.9133 | Y14: 40099.088 | Z14: 35.79815 | AA14: 74011.123 | AB14: 60922.866 | AC14: 90068.075 | AD14: 349794.35 | AE14: 2524544.7 | AF14: 1911.2094 | AG14: 1264.9323 | AH14: 0 | AI14: 204178.29 | AJ14: 2317190.3
B15: 1408 | C15: CARTERA DE CRÉDITO DE VIVIENDA DE INTERÉS SOCIAL Y PÚBLICO POR VENCER | D15: 0 | E15: 11662.604 | F15: 4721.0332 | G15: 0 | H15: 16383.638 | I15: 0 | J15: 0 | K15: 0 | L15: 0 | M15: 5905.3987 | N15: 397.59849 | O15: 0 | P15: 0 | Q15: 0 | R15: 6302.9972 | S15: 0 | T15: 0 | U15: 0 | V15: 0 | W15: 0 | X15: 0 | Y15: 0 | Z15: 0 | AA15: 0 | AB15: 0 | AC15: 0 | AD15: 0 | AE15: 22686.635 | AF15: 397.59849 | AG15: 5905.3987 | AH15: 0 | AI15: 0 | AJ15: 16383.638
B16: 1409 | C16: CARTERA DE CRÉDITOS PRODUCTIVO REFINANCIADA POR VENCER | D16: 4228.0126 | E16: 92875.931 | F16: 53603.662 | G16: 7061.9487 | H16: 157769.55 | I16: 71868.202 | J16: 0 | K16: 0 | L16: 18626.702 | M16: 2933.0028 | N16: 30536.399 | O16: 12925.361 | P16: 1985.4405 | Q16: 0 | R16: 138875.11 | S16: 6118.5197 | T16: 1373.1145 | U16: 2213.4633 | V16: 209.52351 | W16: 0 | X16: 0 | Y16: 0 | Z16: 284.04967 | AA16: 0 | AB16: 356.45616 | AC16: 0 | AD16: 10555.127 | AE16: 307199.79 | AF16: 30536.399 | AG16: 21769.228 | AH16: 0 | AI16: 0 | AJ16: 254894.16
B17: 1410 | C17: CARTERA DE CRÉDITOS CONSUMO REFINANCIADA POR VENCER | D17: 45524.52 | E17: 262.42475 | F17: 22617.257 | G17: 6059.7397 | H17: 74463.942 | I17: 17457.754 | J17: 276.94723 | K17: 0 | L17: 37844.659 | M17: 1213.9487 | N17: 940.88278 | O17: 5407.3483 | P17: 414.04623 | Q17: 2056.6 | R17: 65612.186 | S17: 73.29368 | T17: 3300.635 | U17: 19.02531 | V17: 624.30923 | W17: 0 | X17: 0 | Y17: 237.38674 | Z17: 101.78699 | AA17: 0 | AB17: 2503.3569 | AC17: 0 | AD17: 6859.7939 | AE17: 146935.92 | AF17: 940.88278 | AG17: 39682.916 | AH17: 0 | AI17: 237.38674 | AJ17: 106074.74
B18: 1411 | C18: CARTERA DE CRÉDITOS INMOBILIARIO REFINANCIADA POR VENCER | D18: 8847.6259 | E18: 7467.1131 | F18: 7345.6541 | G18: 2403.9652 | H18: 26064.358 | I18: 1532.0261 | J18: 466.97375 | K18: 0 | L18: 0 | M18: 295.35744 | N18: 650.72871 | O18: 1038.2966 | P18: 47.50937 | Q18: 0 | R18: 4030.892 | S18: 419.37811 | T18: 258.84795 | U18: 0 | V18: 30.64385 | W18: 0 | X18: 0 | Y18: 0 | Z18: 154.05133 | AA18: 0 | AB18: 789.7706 | AC18: 0 | AD18: 1652.6918 | AE18: 31747.942 | AF18: 650.72871 | AG18: 326.00129 | AH18: 0 | AI18: 0 | AJ18: 30771.212
B19: 1412 | C19: CARTERA DE CRÉDITOS PARA MICROCRÉDITO REFINANCIADA POR VENCER | D19: 1374.2047 | E19: 163.50504 | F19: 12672.946 | G19: 29.69277 | H19: 14240.349 | I19: 301.33376 | J19: 0 | K19: 0 | L19: 0 | M19: 0 | N19: 8 | O19: 1889.3783 | P19: 0 | Q19: 242.87927 | R19: 2441.5913 | S19: 3641.3096 | T19: 0 | U19: 127.03802 | V19: 15.28671 | W19: 0 | X19: 0 | Y19: 5065.8481 | Z19: 11.94732 | AA19: 1563.6542 | AB19: 5673.4742 | AC19: 1004.5094 | AD19: 17103.068 | AE19: 33785.008 | AF19: 8 | AG19: 15.28671 | AH19: 0 | AI19: 7634.0117 | AJ19: 26127.709
B20: 1416 | C20: CARTERA DE CRÉDITOS DE VIVIENDA DE INTERÉS SOCIAL Y PÚBLICO REFINANCIADA POR VENCER | D20: 0 | E20: 210.10229 | F20: 0 | G20: 0 | H20: 210.10229 | I20: 0 | J20: 0 | K20: 0 | L20: 0 | M20: 0 | N20: 0 | O20: 0 | P20: 0 | Q20: 0 | R20: 0 | S20: 0 | T20: 0 | U20: 0 | V20: 0 | W20: 0 | X20: 0 | Y20: 0 | Z20: 0 | AA20: 0 | AB20: 0 | AC20: 0 | AD20: 0 | AE20: 210.10229 | AF20: 0 | AG20: 0 | AH20: 0 | AI20: 0 | AJ20: 210.10229
B21: 1417 | C21: CARTERA DE CRÉDITOS PRODUCTIVO REESTRUCTURADA POR VENCER | D21: 1732.3468 | E21: 95843.896 | F21: 71618.459 | G21: 8057.109 | H21: 177251.81 | I21: 12367.883 | J21: 39.7883 | K21: 0 | L21: 1971.5398 | M21: 10849.055 | N21: 18824.432 | O21: 6153.744 | P21: 1605.5128 | Q21: 0 | R21: 51811.955 | S21: 7889.0784 | T21: 55.62399 | U21: 0 | V21: 82.03229 | W21: 0 | X21: 0 | Y21: 0 | Z21: 877.90849 | AA21: 0 | AB21: 0 | AC21: 0 | AD21: 8904.6431 | AE21: 237968.41 | AF21: 18824.432 | AG21: 12902.627 | AH21: 0 | AI21: 0 | AJ21: 206241.35
B22: 1418 | C22: CARTERA DE CRÉDITOS DE CONSUMO REESTRUCTURADA POR VENCER | D22: 12608.917 | E22: 32174.033 | F22: 74923.744 | G22: 55586.859 | H22: 175293.55 | I22: 8945.5203 | J22: 8644.1052 | K22: 0 | L22: 70974.277 | M22: 11565.532 | N22: 3644.555 | O22: 2169.8432 | P22: 587.65909 | Q22: 329.57275 | R22: 106861.06 | S22: 0 | T22: 1193.1653 | U22: 25.39691 | V22: 276.20814 | W22: 0 | X22: 21.55693 | Y22: 74.20948 | Z22: 50.92754 | AA22: 0 | AB22: 150.96299 | AC22: 0 | AD22: 1792.4273 | AE22: 283947.04 | AF22: 3644.555 | AG22: 82816.017 | AH22: 0 | AI22: 74.20948 | AJ22: 197412.26
... B45: 149450 | C45: EDUCATIVO POR VENCER | D45: 0 | E45: 0 | F45: 104.40924 | G45: 0 | H45: 104.40924 | I45: 0 | J45: 0 | K45: 0 | L45: 0 | M45: 0 | N45: 0 | O45: 0 | P45: 0 | Q45: 0 | R45: 0 | S45: 0 | T45: 0 | U45: 0 | V45: 0 | W45: 0 | X45: 0 | Y45: 0 | Z45: 0 | AA45: 0 | AB45: 0 | AC45: 0 | AD45: 0 | AE45: 104.40924 | AF45: 0 | AG45: 0 | AH45: 0 | AI45: 0 | AJ45: 104.40924
C46: TOTAL CARTERA POR VENCER | D46: 4370785.7 | E46: 4101386.6 | F46: 9293754.5 | G46: 4351961.7 | H46: 22117888 | I46: 1368589 | J46: 2774810 | K46: 304232.56 | L46: 1961314.1 | M46: 709143.02 | N46: 2919843.9 | O46: 451819.58 | P46: 585944.42 | Q46: 674691.77 | R46: 11750388 | S46: 477596.55 | T46: 157298.41 | U46: 37921.972 | V46: 28779.051 | W46: 82841.555 | X46: 22155.023 | Y46: 52522.76 | Z46: 15139.539 | AA46: 76249.909 | AB46: 175402.34 | AC46: 91183.043 | AD46: 1217090.1 | AE46: 35085367 | AF46: 3224076.5 | AG46: 2699236.2 | AH46: 0 | AI46: 219955.71 | AJ46: 28942099
B48: 1425 | C48: CARTERA DE CRÉDITOS PRODUCTIVO QUE NO DEVENGA INTERESES | D48: 6359.0262 | E48: 2491.8903 | F48: 30004.705 | G48: 2042.1047 | H48: 40897.726 | I48: 2570.6285 | J48: 520.85442 | K48: 0 | L48: 313.58563 | M48: 336.99607 | N48: 571.10048 | O48: 244.1611 | P48: 1015.3247 | Q48: 0 | R48: 5572.6508 | S48: 3586.0563 | T48: 85.00754 | U48: 59.86855 | V48: 24.84664 | W48: 0 | X48: 0 | Y48: 0 | Z48: 136.05224 | AA48: 0 | AB48: 52.27315 | AC48: 0 | AD48: 3944.1044 | AE48: 50414.482 | AF48: 571.10048 | AG48: 675.42834 | AH48: 0 | AI48: 0 | AJ48: 49167.953
B49: 1426 | C49: CARTERA DE CRÉDITOS DE CONSUMO QUE NO DEVENGA INTERESES | D49: 8673.3301 | E49: 30901.856 | F49: 29970.017 | G49: 18299.093 | H49: 87844.296 | I49: 20501.213 | J49: 6892.879 | K49: 0 | L49: 29571.198 | M49: 7914.8022 | N49: 8833.1729 | O49: 1833.5488 | P49: 3373.2256 | Q49: 8648.8944 | R49: 87568.933 | S49: 12.67372 | T49: 1396.5962 | U49: 354.42203 | V49: 464.80472 | W49: 0 | X49: 345.08615 | Y49: 120.22339 | Z49: 74.3486 | AA49: 0 | AB49: 600.65307 | AC49: 0 | AD49: 3368.8078 | AE49: 178782.04 | AF49: 8833.1729 | AG49: 37950.804 | AH49: 0 | AI49: 120.22339 | AJ49: 131877.84
B50: 1427 | C50: CARTERA DE CRÉDITOS INMOBILIARIO QUE NO DEVENGA INTERESES | D50: 2053.6218 | E50: 6404.4341 | F50: 14551.549 | G50: 2936.2238 | H50: 25945.828 | I50: 987.68621 | J50: 1430.5176 | K50: 0 | L50: 0 | M50: 1778.6076 | N50: 1562.9118 | O50: 331.56772 | P50: 318.94869 | Q50: 0.98261 | R50: 6411.2222 | S50: 155.43577 | T50: 135.97653 | U50: 0 | V50: 0 | W50: 0 | X50: 0 | Y50: 0 | Z50: 29.29576 | AA50: 0 | AB50: 104.79328 | AC50: 0 | AD50: 425.50134 | AE50: 32782.552 | AF50: 1562.9118 | AG50: 1778.6076 | AH50: 0 | AI50: 0 | AJ50: 29441.033
B51: 1428 | C51: CARTERA DE CRÉDITOS PARA MICROCRÉDITO QUE NO DEVENGA INTERESES | D51: 5034.8517 | E51: 373.77334 | F51: 18652.947 | G51: 493.97169 | H51: 24555.544 | I51: 751.3426 | J51: 0 | K51: 0 | L51: 0 | M51: 0 | N51: 60.1301 | O51: 805.7275 | P51: 307.7324 | Q51: 9472.3511 | R51: 11397.284 | S51: 1534.8892 | T51: 20.45659 | U51: 477.04123 | V51: 68.07543 | W51: 22.55576 | X51: 15.85347 | Y51: 2197.5267 | Z51: 2.29471 | AA51: 3814.1593 | AB51: 1874.8755 | AC51: 1504.646 | AD51: 11532.374 | AE51: 47485.201 | AF51: 60.1301 | AG51: 68.07543 | AH51: 0 | AI51: 7516.332 | AJ51: 39840.664
B52: 1432 | C52: CARTERA DE CRÉDITO DE VIVIENDA DE INTERÉS SOCIAL Y PÚBLICO QUE NO DEVENGA INTERESES | D52: 0 | E52: 2636.4019 | F52: 0 | G52: 0 | H52: 2636.4019 | I52: 0 | J52: 0 | K52: 0 | L52: 0 | M52: 16.11073 | N52: 0 | O52: 0 | P52: 0 | Q52: 0 | R52: 16.11073 | S52: 0 | T52: 0 | U52: 0 | V52: 0 | W52: 0 | X52: 0 | Y52: 0 | Z52: 0 | AA52: 0 | AB52: 0 | AC52: 0 | AD52: 0 | AE52: 2652.5126 | AF52: 0 | AG52: 16.11073 | AH52: 0 | AI52: 0 | AJ52: 2636.4019
B53: 1433 | C53: CARTERA DE CRÉDITOS PRODUCTIVO REFINANCIADA QUE NO DEVENGA INTERESES | D53: 749.07936 | E53: 396.42148 | F53: 2130.3771 | G53: 687.66496 | H53: 3963.5429 | I53: 762.02756 | J53: 0 | K53: 0 | L53: 321.28057 | M53: 107.20419 | N53: 48.46012 | O53: 199.15419 | P53: 10.56662 | Q53: 0 | R53: 1448.6933 | S53: 2419.2265 | T53: 6.85098 | U53: 199.07449 | V53: 4.50988 | W53: 0 | X53: 0 | Y53: 0 | Z53: 0 | AA53: 0 | AB53: 0 | AC53: 0 | AD53: 2629.6619 | AE53: 8041.8981 | AF53: 48.46012 | AG53: 432.99464 | AH53: 0 | AI53: 0 | AJ53: 7560.4433
B54: 1434 | C54: CARTERA DE CRÉDITOS DE CONSUMO REFINANCIADA QUE NO DEVENGA INTERESES | D54: 2682.2449 | E54: 25.21478 | F54: 1157.9653 | G54: 334.65822 | H54: 4200.0833 | I54: 4435.9963 | J54: 23.35858 | K54: 0 | L54: 5034.9145 | M54: 72.13712 | N54: 173.2163 | O54: 321.64003 | P54: 86.27115 | Q54: 209.956 | R54: 10357.49 | S54: 0 | T54: 743.63024 | U54: 0.53738 | V54: 107.0138 | W54: 0 | X54: 0 | Y54: 133.76345 | Z54: 9.31695 | AA54: 0 | AB54: 399.74509 | AC54: 0 | AD54: 1394.0069 | AE54: 15951.58 | AF54: 173.2163 | AG54: 5214.0654 | AH54: 0 | AI54: 133.76345 | AJ54: 10430.535
B55: 1435 | C55: CARTERA DE CRÉDITOS INMOBILIARIO REFINANCIADA QUE NO DEVENGA INTERESES | D55: 542.45638 | E55: 971.44941 | F55: 152.03307 | G55: 70.99182 | H55: 1736.9307 | I55: 0 | J55: 0 | K55: 0 | L55: 0 | M55: 0 | N55: 79.71842 | O55: 60.05914 | P55: 0 | Q55: 0 | R55: 139.77756 | S55: 9.63218 | T55: 0 | U55: 0 | V55: 0 | W55: 0 | X55: 0 | Y55: 0 | Z55: 0 | AA55: 0 | AB55: 18.35007 | AC55: 0 | AD55: 27.98225 | AE55: 1904.6905 | AF55: 79.71842 | AG55: 0 | AH55: 0 | AI55: 0 | AJ55: 1824.9721
B56: 1436 | C56: CARTERA DE CRÉDITOS PARA MICROCRÉDITO REFINANCIADA QUE NO DEVENGA INTERESES | D56: 624.16488 | E56: 0 | F56: 1312.83 | G56: 5.70663 | H56: 1942.7015 | I56: 25.50104 | J56: 0 | K56: 0 | L56: 0 | M56: 0 | N56: 8.86457 | O56: 352.91936 | P56: 0 | Q56: 29.74219 | R56: 417.02716 | S56: 317.6796 | T56: 0 | U56: 1.49101 | V56: 0 | W56: 0 | X56: 0 | Y56: 1532.4027 | Z56: 0 | AA56: 447.45487 | AB56: 1716.8393 | AC56: 339.17052 | AD56: 4355.0381 | AE56: 6714.7667 | AF56: 8.86457 | AG56: 0 | AH56: 0 | AI56: 2319.0281 | AJ56: 4386.874
B57: 1440 | C57: CARTERA DE CRÉDITOS DE VIVIENDA DE INTERÉS SOCIAL Y PÚBLICO REFINANCIADA QUE NO DEVENGA INTERESES | D57: 0 | E57: 0 | F57: 0 | G57: 0 | H57: 0 | I57: 0 | J57: 0 | K57: 0 | L57: 0 | M57: 0 | N57: 0 | O57: 0 | P57: 0 | Q57: 0 | R57: 0 | S57: 0 | T57: 0 | U57: 0 | V57: 0 | W57: 0 | X57: 0 | Y57: 0 | Z57: 0 | AA57: 0 | AB57: 0 | AC57: 0 | AD57: 0 | AE57: 0 | AF57: 0 | AG57: 0 | AH57: 0 | AI57: 0 | AJ57: 0
B58: 1441 | C58: CARTERA DE CRÉDITOS PRODUCTIVO REESTRUCTURADA QUE NO DEVENGA INTERESES | D58: 1243.3005 | E58: 3611.3613 | F58: 10577.596 | G58: 1370.2251 | H58: 16802.483 | I58: 465.36252 | J58: 0 | K58: 0 | L58: 581.14977 | M58: 383.09443 | N58: 669.53784 | O58: 988.20496 | P58: 137.15562 | Q58: 0 | R58: 3224.5051 | S58: 292.25322 | T58: 35.89805 | U58: 0 | V58: 0 | W58: 0 | X58: 0 | Y58: 0 | Z58: 20.53457 | AA58: 0 | AB58: 20.53104 | AC58: 0 | AD58: 369.21688 | AE58: 20396.205 | AF58: 669.53784 | AG58: 964.2442 | AH58: 0 | AI58: 0 | AJ58: 18762.423
B59: 1442 | C59: CARTERA DE CRÉDITOS DE CONSUMO REESTRUCTURADA QUE NO DEVENGA INTERESES | D59: 1891.2806 | E59: 13624.587 | F59: 17745.067 | G59: 15484.969 | H59: 48745.904 | I59: 5259.5253 | J59: 2522.9944 | K59: 0 | L59: 21741.64 | M59: 2329.1567 | N59: 1793.6416 | O59: 275.39912 | P59: 82.0047 | Q59: 115.7088 | R59: 34120.07 | S59: 0 | T59: 747.09456 | U59: 2.41504 | V59: 43.43999 | W59: 0 | X59: 0 | Y59: 48.57484 | Z59: 40.02103 | AA59: 0 | AB59: 75.95563 | AC59: 0 | AD59: 957.50109 | AE59: 83823.475 | AF59: 1793.6416 | AG59: 24114.236 | AH59: 0 | AI59: 48.57484 | AJ59: 57867.022
... B82: 149550 | C82: EDUCATIVO QUE NO DEVENGA INTERESES | D82: 0 | E82: 0 | F82: 0 | G82: 0 | H82: 0 | I82: 0 | J82: 0 | K82: 0 | L82: 0 | M82: 0 | N82: 0 | O82: 0 | P82: 0 | Q82: 0 | R82: 0 | S82: 0 | T82: 0 | U82: 0 | V82: 0 | W82: 0 | X82: 0 | Y82: 0 | Z82: 0 | AA82: 0 | AB82: 0 | AC82: 0 | AD82: 0 | AE82: 0 | AF82: 0 | AG82: 0 | AH82: 0 | AI82: 0 | AJ82: 0
C83: TOTAL CARTERA QUE NO DEVENGA INTERES | D83: 31223.427 | E83: 76117.58 | F83: 166006.23 | G83: 46927.276 | H83: 320274.51 | I83: 35904.766 | J83: 11556.134 | K83: 0 | L83: 57919.115 | M83: 14380.448 | N83: 14607.444 | O83: 6801.0067 | P83: 5475.9638 | Q83: 19208.685 | R83: 165853.56 | S83: 9644.63 | T83: 3462.8944 | U83: 1096.8943 | V83: 1235.0244 | W83: 130.15061 | X83: 471.66136 | Y83: 6761.1302 | Z83: 326.0454 | AA83: 4672.0114 | AB83: 7140.4143 | AC83: 1858.4459 | AD83: 36799.302 | AE83: 522927.38 | AF83: 14607.444 | AG83: 73534.588 | AH83: 0 | AI83: 13291.587 | AJ83: 421493.76
B85: 1449 | C85: CARTERA DE CRÉDITOS PRODUCTIVO VENCIDA | D85: 10829.635 | E85: 7570.5539 | F85: 12153.024 | G85: 4826.6766 | H85: 35379.89 | I85: 2164.9361 | J85: 4972.1047 | K85: 0.002 | L85: 1167.4686 | M85: 296.95543 | N85: 1301.4018 | O85: 513.70187 | P85: 701.75029 | Q85: 0.02 | R85: 11118.341 | S85: 1742.6176 | T85: 554.39273 | U85: 119.7721 | V85: 7.52967 | W85: 0 | X85: 0.09 | Y85: 0 | Z85: 56.1638 | AA85: 0 | AB85: 116.01868 | AC85: 0 | AD85: 2596.5846 | AE85: 49094.815 | AF85: 1301.4038 | AG85: 1471.9536 | AH85: 0 | AI85: 0 | AJ85: 46321.458
B86: 1450 | C86: CARTERA DE CRÉDITOS DE CONSUMO VENCIDA | D86: 11724.331 | E86: 19751.2 | F86: 16780.524 | G86: 3573.1512 | H86: 51829.206 | I86: 8757.7242 | J86: 5425.1992 | K86: 0 | L86: 12447.091 | M86: 1916.5127 | N86: 4332.1302 | O86: 1119.5613 | P86: 639.06273 | Q86: 1367.2302 | R86: 36004.512 | S86: 68.56004 | T86: 742.6466 | U86: 612.47237 | V86: 400.53898 | W86: 1.329 | X86: 196.55789 | Y86: 175.74046 | Z86: 40.47831 | AA86: 0 | AB86: 369.28233 | AC86: 0.10495 | AD86: 2607.7109 | AE86: 90441.429 | AF86: 4332.1302 | AG86: 14764.143 | AH86: 0 | AI86: 175.84541 | AJ86: 71169.31
B87: 1451 | C87: CARTERA DE CRÉDITOS INMOBILIARIO VENCIDA | D87: 493.6952 | E87: 5909.996 | F87: 5213.4737 | G87: 2588.3109 | H87: 14205.476 | I87: 76.68802 | J87: 1211.8385 | K87: 0 | L87: 0 | M87: 63.36545 | N87: 263.03878 | O87: 116.74942 | P87: 39.82976 | Q87: 12.36547 | R87: 1783.8754 | S87: 30.56784 | T87: 2.15892 | U87: 0 | V87: 0.001 | W87: 0.004 | X87: 0.001 | Y87: 0 | Z87: 12.01811 | AA87: 0 | AB87: 97.71871 | AC87: 0 | AD87: 142.46958 | AE87: 16131.821 | AF87: 263.03878 | AG87: 63.36645 | AH87: 0 | AI87: 0 | AJ87: 15805.415
B88: 1452 | C88: CARTERA DE CRÉDITOS PARA MICROCRÉDITO VENCIDA | D88: 2499.4885 | E88: 816.04181 | F88: 5131.9922 | G88: 137.30173 | H88: 8584.8242 | I88: 190.89576 | J88: 0 | K88: 0 | L88: 0 | M88: 0.014 | N88: 48.13835 | O88: 543.25686 | P88: 35.62232 | Q88: 1790.8984 | R88: 2608.8257 | S88: 385.62835 | T88: 8.50295 | U88: 473.91079 | V88: 12.76653 | W88: 21.68162 | X88: 60.53263 | Y88: 317.70641 | Z88: 1.10352 | AA88: 2476.7985 | AB88: 1331.1481 | AC88: 2464.7239 | AD88: 7554.5033 | AE88: 18748.153 | AF88: 48.13835 | AG88: 12.78053 | AH88: 0 | AI88: 5259.2288 | AJ88: 13428.006
B89: 1456 | C89: CARTERA DE CRÉDITOS DE VIVIENDA DE INTERÉS SOCIAL Y PÚBLICO VENCIDA | D89: 0 | E89: 2554.0768 | F89: 0.007 | G89: 0 | H89: 2554.0838 | I89: 0 | J89: 0 | K89: 0 | L89: 0 | M89: 0.69221 | N89: 0 | O89: 0 | P89: 0 | Q89: 0 | R89: 0.69221 | S89: 0 | T89: 0 | U89: 0 | V89: 0 | W89: 0 | X89: 0 | Y89: 0 | Z89: 0 | AA89: 0 | AB89: 0 | AC89: 0 | AD89: 0 | AE89: 2554.776 | AF89: 0 | AG89: 0.69221 | AH89: 0 | AI89: 0 | AJ89: 2554.0838
B90: 1457 | C90: CARTERA DE CRÉDITOS PRODUCTIVO REFINANCIADA VENCIDA | D90: 604.11712 | E90: 788.90755 | F90: 711.09559 | G90: 1118.016 | H90: 3222.1363 | I90: 2222.2837 | J90: 0 | K90: 0 | L90: 60.02221 | M90: 50.81785 | N90: 172.97758 | O90: 85.18511 | P90: 2.11979 | Q90: 0 | R90: 2593.4063 | S90: 216.10408 | T90: 0.35668 | U90: 11.73329 | V90: 7.43909 | W90: 0 | X90: 0 | Y90: 0 | Z90: 3.16531 | AA90: 0 | AB90: 0 | AC90: 0 | AD90: 238.79845 | AE90: 6054.341 | AF90: 172.97758 | AG90: 118.27915 | AH90: 0 | AI90: 0 | AJ90: 5763.0843
